Workbook

Sheet Raw Snapshot
A1: subscription_id | B1: customer_id | C1: company_name | D1: account_owner | E1: region | F1: plan_name | G1: billing_cycle | H1: mrr
A2: SUB025 | B2: CUST025 | C2: Montreal Manufacturing Pro | D2: Sarah Chen | E2: Eastern Canada | F2: Analytics Enterprise | G2: Annual | H2: 6840
A3: SUB031 | B3: CUST031 | C3: Toronto Digital Media | D3: James Wilson | E3: Eastern Canada | F3: Platform Suite | G3: Annual | H3: 6750
A4: SUB018 | B4: CUST018 | C4: Vancouver FinTech Labs | D4: Michael Rodriguez | E4: Western Canada | F4: Analytics Enterprise | G4: Monthly | H4: 6300
A5: SUB016 | B5: CUST016 | C5: Quebec Manufacturing | D5: Sarah Chen | E5: Eastern Canada | F5: Platform Suite | G5: Annual | H5: 6300
A6: SUB053 | B6: CUST027 | C6: Pacific Finance Corp | D6: Michael Rodriguez | E6: Western Canada | F6: Analytics Enterprise | G6: Monthly | H6: 5580
A7: SUB006 | B7: CUST006 | C7: Northern Retail Solutions | D7: Michael Rodriguez | E7: Western Canada | F7: Analytics Enterprise | G7: Annual | H7: 5580
A8: SUB009 | B8: CUST009 | C8: West Coast Logistics | D8: Michael Rodriguez | E8: Western Canada | F8: Platform Suite | G8: Annual | H8: 5400
A9: SUB037 | B9: CUST037 | C9: Maritime SaaS Ventures | D9: Sarah Chen | E9: Eastern Canada | F9: Platform Suite | G9: Monthly | H9: 5250
A10: SUB022 | B10: CUST022 | C10: Toronto Tech Ventures | D10: James Wilson | E10: Eastern Canada | F10: Platform Suite | G10: Monthly | H10: 4950
A11: SUB032 | B11: CUST032 | C11: BC Manufacturing Systems | D11: Michael Rodriguez | E11: Western Canada | F11: Analytics Enterprise | G11: Monthly | H11: 4680
A12: SUB057 | B12: CUST021 | C12: Calgary Commerce Solutions | D12: Michael Rodriguez | E12: Western Canada | F12: Platform Suite | G12: Monthly | H12: 4200
A13: SUB048 | B13: CUST025 | C13: Montreal Manufacturing Pro | D13: Sarah Chen | E13: Eastern Canada | F13: Sales Hub | G13: Monthly | H13: 3960
... A52: SUB017 | B52: CUST017 | C52: Capital Education Tech | D52: James Wilson | E52: Eastern Canada | F52: Analytics Starter | G52: Monthly | H52: 540

Sheet Raw Events
A1: event_id | B1: subscription_id | C1: customer_id | D1: company_name | E1: region | F1: month | G1: event_date | H1: event_date | I1: event_type | J1: old_value | K1: new_value | L1: field_changed | M1: reason | N1: plan_name | O1: billing_cycle | P1: price_per_seat | Q1: discount_percent
A2: EVT001 | B2: SUB001 | C2: CUST001 | D2: TechVision Solutions | E2: Eastern Canada | F2: 45292 | G2: 45299 | H2: 45299 | I2: created | N2: Analytics Growth | O2: Monthly | P2: 95 | Q2: 0
A3: EVT002 | B3: SUB002 | C3: CUST002 | D3: Pacific Analytics Inc | E3: Western Canada | F3: 45292 | G3: 45313 | H3: 45313 | I3: created | N3: Platform Suite | O3: Annual | P3: 1800 | Q3: 0
A4: EVT003 | B4: SUB003 | C4: CUST003 | D4: Maple Healthcare Systems | E4: Eastern Canada | F4: 45323 | G4: 45327 | H4: 45327 | I4: created | N4: Marketing Pro | O4: Monthly | P4: 85 | Q4: 0
A5: EVT004 | B5: SUB004 | C5: CUST004 | D5: Prairie Commerce Group | E5: Western Canada | F5: 45323 | G5: 45341 | H5: 45341 | I5: created | N5: Sales Hub | O5: Monthly | P5: 110 | Q5: 0
A6: EVT005 | B6: SUB055 | C6: CUST004 | D6: Prairie Commerce Group | E6: Western Canada | F6: 45323 | G6: 45341 | H6: 45341 | I6: created | N6: Analytics Enterprise | O6: Monthly | P6: 180 | Q6: 0
A7: EVT006 | B7: SUB005 | C7: CUST005 | D7: Atlantic Media Corp | E7: Eastern Canada | F7: 45352 | G7: 45355 | H7: 45355 | I7: created | N7: Analytics Starter | O7: Monthly | P7: 45 | Q7: 0
A8: EVT007 | B8: SUB006 | C8: CUST006 | D8: Northern Retail Solutions | E8: Western Canada | F8: 45352 | G8: 45369 | H8: 45369 | I8: created | N8: Analytics Enterprise | O8: Annual | P8: 2160 | Q8: 0
A9: EVT008 | B9: SUB007 | C9: CUST007 | D9: Ontario Manufacturing Tech | E9: Eastern Canada | F9: 45383 | G9: 45383 | H9: 45383 | I9: created | N9: Marketing Pro | O9: Monthly | P9: 85 | Q9: 0
A10: EVT009 | B10: SUB050 | C10: CUST007 | D10: Ontario Manufacturing Tech | E10: Eastern Canada | F10: 45383 | G10: 45383 | H10: 45383 | I10: created | N10: Analytics Starter | O10: Monthly | P10: 45 | Q10: 12
A11: EVT010 | B11: SUB008 | C11: CUST008 | D11: Quantum Education Platform | E11: Eastern Canada | F11: 45383 | G11: 45397 | H11: 45397 | I11: created | N11: Analytics Growth | O11: Monthly | P11: 95 | Q11: 0
A12: EVT011 | B12: SUB009 | C12: CUST009 | D12: West Coast Logistics | E12: Western Canada | F12: 45383 | G12: 45411 | H12: 45411 | I12: created | N12: Platform Suite | O12: Annual | P12: 1800 | Q12: 0
A13: EVT012 | B13: SUB010 | C13: CUST010 | D13: Montreal Finance Hub | E13: Eastern Canada | F13: 45413 | G13: 45425 | H13: 45425 | I13: created | N13: Analytics Starter | O13: Monthly | P13: 45 | Q13: 0
... A23: EVT022 | B23: SUB017 | C23: CUST017 | D23: Capital Education Tech | E23: Eastern Canada | F23: 45505 | G23: 45523 | H23: 45523 | I23: created | N23: Analytics Starter | O23: Monthly | P23: 45 | Q23: 0
A24: EVT023 | B24: SUB001 | C24: CUST001 | D24: TechVision Solutions | E24: Eastern Canada | F24: 45505 | G24: 45531 | H24: 45531 | I24: cancelled | J24: active | K24: churned | L24: status | M24: Missing features | N24: Analytics Growth | O24: Monthly | P24: 95 | Q24: 0
A25: EVT024 | B25: SUB018 | C25: CUST018 | D25: Vancouver FinTech Labs | E25: Western Canada | F25: 45536 | G25: 45537 | H25: 45537 | I25: created | N25: Analytics Enterprise | O25: Monthly | P25: 180 | Q25: 0
A26: EVT025 | B26: SUB042 | C26: CUST003 | D26: Maple Healthcare Systems | E26: Eastern Canada | F26: 45536 | G26: 45545 | H26: 45545 | I26: created | N26: Sales Hub | O26: Monthly | P26: 110 | Q26: 0
A27: EVT026 | B27: SUB019 | C27: CUST019 | D27: Central Healthcare Partners | E27: Central Canada | F27: 45536 | G27: 45551 | H27: 45551 | I27: created | N27: Marketing Pro | O27: Monthly | P27: 85 | Q27: 0
A28: EVT027 | B28: SUB060 | C28: CUST019 | D28: Central Healthcare Partners | E28: Central Canada | F28: 45536 | G28: 45551 | H28: 45551 | I28: created | N28: Sales Hub | O28: Monthly | P28: 110 | Q28: 0
A29: EVT028 | B29: SUB020 | C29: CUST020 | D29: Atlantic SaaS Systems | E29: Eastern Canada | F29: 45536 | G29: 45565 | H29: 45565 | I29: created | N29: Sales Hub | O29: Monthly | P29: 110 | Q29: 0
A30: EVT029 | B30: SUB043 | C30: CUST006 | D30: Northern Retail Solutions | E30: Western Canada | F30: 45566 | G30: 45570 | H30: 45570 | I30: created | N30: Marketing Pro | O30: Monthly | P30: 85 | Q30: 0
A31: EVT030 | B31: SUB021 | C31: CUST021 | D31: Calgary Commerce Solutions | E31: Western Canada | F31: 45566 | G31: 45579 | H31: 45579 | I31: created | N31: Analytics Growth | O31: Monthly | P31: 95 | Q31: 0
A32: EVT031 | B32: SUB022 | C32: CUST022 | D32: Toronto Tech Ventures | E32: Eastern Canada | F32: 45566 | G32: 45593 | H32: 45593 | I32: created | N32: Platform Suite | O32: Monthly | P32: 150 | Q32: 0
A33: EVT032 | B33: SUB059 | C33: CUST008 | D33: Quantum Education Platform | E33: Eastern Canada | F33: 45597 | G33: 45601 | H33: 45601 | I33: created | N33: Marketing Pro | O33: Monthly | P33: 85 | Q33: 0
A34: EVT033 | B34: SUB023 | C34: CUST023 | D34: Island Media Productions | E34: Eastern Canada | F34: 45597 | G34: 45607 | H34: 45607 | I34: created | N34: Analytics Starter | O34: Monthly | P34: 45 | Q34: 0
A35: EVT034 | B35: SUB005 | C35: CUST005 | D35: Atlantic Media Corp | E35: Eastern Canada | F35: 45597 | G35: 45616 | H35: 45616 | I35: cancelled | J35: active | K35: churned | L35: status | M35: Price too high | N35: Analytics Starter | O35: Monthly | P35: 45 | Q35: 0
A36: EVT035 | B36: SUB024 | C36: CUST024 | D36: Western Retail Group | E36: Western Canada | F36: 45597 | G36: 45621 | H36: 45621 | I36: created | N36: Marketing Pro | O36: Monthly | P36: 85 | Q36: 0
A37: EVT036 | B37: SUB025 | C37: CUST025 | D37: Montreal Manufacturing Pro | E37: Eastern Canada | F37: 45627 | G37: 45635 | H37: 45635 | I37: created | N37: Analytics Enterprise | O37: Annual | P37: 2160 | Q37: 0
A38: EVT037 | B38: SUB056 | C38: CUST016 | D38: Quebec Manufacturing | E38: Eastern Canada | F38: 45627 | G38: 45638 | H38: 45638 | I38: created | N38: Marketing Pro | O38: Monthly | P38: 85 | Q38: 0
A39: EVT038 | B39: SUB044 | C39: CUST009 | D39: West Coast Logistics | E39: Western Canada | F39: 45627 | G39: 45646 | H39: 45646 | I39: created | N39: Analytics Growth | O39: Monthly | P39: 95 | Q39: 0
A40: EVT039 | B40: SUB008 | C40: CUST008 | D40: Quantum Education Platform | E40: Eastern Canada | F40: 45627 | G40: 45648 | H40: 45648 | I40: cancelled | J40: active | K40: churned | L40: status | M40: Price too high | N40: Analytics Growth | O40: Monthly | P40: 95 | Q40: 0
A41: EVT040 | B41: SUB026 | C41: CUST026 | D41: Ontario Education Connect | E41: Eastern Canada | F41: 45627 | G41: 45649 | H41: 45649 | I41: created | N41: Analytics Growth | O41: Monthly | P41: 95 | Q41: 0
A42: EVT041 | B42: SUB027 | C42: CUST027 | D42: Pacific Finance Corp | E42: Western Canada | F42: 45658 | G42: 45663 | H42: 45663 | I42: created | N42: Sales Hub | O42: Monthly | P42: 110 | Q42: 0
A43: EVT042 | B43: SUB014 | C43: CUST014 | D43: Toronto Media Group | E43: Eastern Canada | F43: 45658 | G43: 45665 | H43: 45665 | I43: price_change | J43: 80 | K43: 85 | L43: price_per_seat | M43: Annual price increase applied at renewal | N43: Marketing Pro | O43: Monthly | P43: 85 | Q43: 0
A44: EVT043 | B44: SUB013 | C44: CUST013 | D44: Alberta Tech Innovators | E44: Western Canada | F44: 45658 | G44: 45672 | H44: 45672 | I44: cancelled | J44: active | K44: churned | L44: status | M44: Switched to competitor | N44: Analytics Starter | O44: Monthly | P44: 45 | Q44: 0
A45: EVT044 | B45: SUB028 | C45: CUST028 | D45: Prairie SaaS Innovations | E45: Central Canada | F45: 45658 | G45: 45677 | H45: 45677 | I45: created | N45: Analytics Starter | O45: Monthly | P45: 45 | Q45: 0
A46: EVT045 | B46: SUB054 | C46: CUST002 | D46: Pacific Analytics Inc | E46: Western Canada | F46: 45658 | G46: 45679 | H46: 45679 | I46: created | N46: Analytics Growth | O46: Annual | P46: 1140 | Q46: 5
A47: EVT046 | B47: SUB057 | C47: CUST021 | D47: Calgary Commerce Solutions | E47: Western Canada | F47: 45658 | G47: 45685 | H47: 45685 | I47: created | N47: Platform Suite | O47: Monthly | P47: 150 | Q47: 0
A48: EVT047 | B48: SUB029 | C48: CUST029 | D48: Halifax Healthcare Tech | E48: Eastern Canada | F48: 45689 | G48: 45691 | H48: 45691 | I48: created | N48: Marketing Pro | O48: Monthly | P48: 85 | Q48: 0
A49: EVT048 | B49: SUB045 | C49: CUST010 | D49: Montreal Finance Hub | E49: Eastern Canada | F49: 45689 | G49: 45696 | H49: 45696 | I49: created | N49: Marketing Pro | O49: Monthly | P49: 85 | Q49: 0
A50: EVT049 | B50: SUB051 | C50: CUST014 | D50: Toronto Media Group | E50: Eastern Canada | F50: 45689 | G50: 45698 | H50: 45698 | I50: created | N50: Sales Hub | O50: Monthly | P50: 110 | Q50: 0
A51: EVT050 | B51: SUB030 | C51: CUST030 | D51: Alberta E-commerce Hub | E51: Western Canada | F51: 45689 | G51: 45705 | H51: 45705 | I51: created | N51: Analytics Growth | O51: Monthly | P51: 95 | Q51: 0
A52: EVT051 | B52: SUB031 | C52: CUST031 | D52: Toronto Digital Media | E52: Eastern Canada | F52: 45717 | G52: 45719 | H52: 45719 | I52: created | N52: Platform Suite | O52: Annual | P52: 1800 | Q52: 0
A53: EVT052 | B53: SUB058 | C53: CUST024 | D53: Western Retail Group | E53: Western Canada | F53: 45717 | G53: 45724 | H53: 45724 | I53: created | N53: Sales Hub | O53: Monthly | P53: 110 | Q53: 0
A54: EVT053 | B54: SUB010 | C54: CUST010 | D54: Montreal Finance Hub | E54: Eastern Canada | F54: 45717 | G54: 45729 | H54: 45729 | I54: plan_downgrade | J54: Analytics Growth | K54: Analytics Starter | L54: plan_name | M54: Cost reduction initiative - downgraded to starter tier | N54: Analytics Starter | O54: Monthly | P54: 45 | Q54: 0
A55: EVT054 | B55: SUB052 | C55: CUST018 | D55: Vancouver FinTech Labs | E55: Western Canada | F55: 45717 | G55: 45731 | H55: 45731 | I55: created | N55: Marketing Pro | O55: Monthly | P55: 85 | Q55: 0
A56: EVT055 | B56: SUB054 | C56: CUST002 | D56: Pacific Analytics Inc | E56: Western Canada | F56: 45717 | G56: 45731 | H56: 45731 | I56: discount_added | J56: 0 | K56: 5 | L56: discount_percent | M56: Annual contract loyalty discount applied | N56: Analytics Growth | O56: Annual | P56: 1140 | Q56: 5
A57: EVT056 | B57: SUB032 | C57: CUST032 | D57: BC Manufacturing Systems | E57: Western Canada | F57: 45717 | G57: 45733 | H57: 45733 | I57: created | N57: Analytics Enterprise | O57: Monthly | P57: 180 | Q57: 0
A58: EVT057 | B58: SUB019 | C58: CUST019 | D58: Central Healthcare Partners | E58: Central Canada | F58: 45717 | G58: 45736 | H58: 45736 | I58: seats_change | J58: 22 | K58: 19 | L58: seats | M58: Headcount reduction - Q1 restructuring | N58: Marketing Pro | O58: Monthly | P58: 85 | Q58: 0
A59: EVT058 | B59: SUB033 | C59: CUST033 | D59: Ottawa Retail Solutions | E59: Eastern Canada | F59: 45717 | G59: 45747 | H59: 45747 | I59: created | N59: Marketing Pro | O59: Monthly | P59: 85 | Q59: 0
A60: EVT059 | B60: SUB027 | C60: CUST027 | D60: Pacific Finance Corp | E60: Western Canada | F60: 45748 | G60: 45753 | H60: 45753 | I60: price_change | J60: 100 | K60: 110 | L60: price_per_seat | M60: Annual price increase applied at renewal | N60: Sales Hub | O60: Monthly | P60: 110 | Q60: 0
A61: EVT060 | B61: SUB034 | C61: CUST034 | D61: Quebec Education Platform | E61: Eastern Canada | F61: 45748 | G61: 45761 | H61: 45761 | I61: created | N61: Analytics Starter | O61: Monthly | P61: 45 | Q61: 0
A62: EVT061 | B62: SUB012 | C62: CUST012 | D62: Maritime E-commerce | E62: Eastern Canada | F62: 45748 | G62: 45762 | H62: 45762 | I62: seats_change | J62: 18 | K62: 23 | L62: seats | M62: New hires onboarded - sales team expansion | N62: Analytics Growth | O62: Monthly | P62: 95 | Q62: 0
A63: EVT062 | B63: SUB047 | C63: CUST022 | D63: Toronto Tech Ventures | E63: Eastern Canada | F63: 45748 | G63: 45765 | H63: 45765 | I63: created | N63: Sales Hub | O63: Monthly | P63: 110 | Q63: 0
A64: EVT063 | B64: SUB035 | C64: CUST035 | D64: Vancouver Health Systems | E64: Western Canada | F64: 45748 | G64: 45775 | H64: 45775 | I64: created | N64: Sales Hub | O64: Monthly | P64: 110 | Q64: 0
A65: EVT064 | B65: SUB004 | C65: CUST004 | D65: Prairie Commerce Group | E65: Western Canada | F65: 45778 | G65: 45787 | H65: 45787 | I65: seats_change | J65: 15 | K65: 18 | L65: seats | M65: Team expansion - 3 new account managers onboarded | N65: Sales Hub | O65: Monthly | P65: 110 | Q65: 0
A66: EVT065 | B66: SUB036 | C66: CUST036 | D66: Manitoba Finance Group | E66: Central Canada | F66: 45778 | G66: 45789 | H66: 45789 | I66: created | N66: Analytics Growth | O66: Monthly | P66: 95 | Q66: 0
A67: EVT066 | B67: SUB061 | C67: CUST013 | D67: Alberta Tech Innovators | E67: Western Canada | F67: 45778 | G67: 45797 | H67: 45797 | I67: created | M67: Returning customer â€” reactivation | N67: Analytics Growth | O67: Monthly | P67: 95 | Q67: 0
A68: EVT067 | B68: SUB048 | C68: CUST025 | D68: Montreal Manufacturing Pro | E68: Eastern Canada | F68: 45778 | G68: 45799 | H68: 45799 | I68: created | N68: Sales Hub | O68: Monthly | P68: 110 | Q68: 0
A69: EVT068 | B69: SUB021 | C69: CUST021 | D69: Calgary Commerce Solutions | E69: Western Canada | F69: 45778 | G69: 45803 | H69: 45803 | I69: cancelled | J69: active | K69: churned | L69: status | M69: Company downsizing | N69: Analytics Growth | O69: Monthly | P69: 95 | Q69: 0
A70: EVT069 | B70: SUB037 | C70: CUST037 | D70: Maritime SaaS Ventures | E70: Eastern Canada | F70: 45778 | G70: 45803 | H70: 45803 | I70: created | N70: Platform Suite | O70: Monthly | P70: 150 | Q70: 0
A71: EVT070 | B71: SUB018 | C71: CUST018 | D71: Vancouver FinTech Labs | E71: Western Canada | F71: 45809 | G71: 45809 | H71: 45809 | I71: seats_change | J71: 30 | K71: 35 | L71: seats | M71: Department growth - added analytics sub-team | N71: Analytics Enterprise | O71: Monthly | P71: 180 | Q71: 0
A72: EVT071 | B72: SUB053 | C72: CUST027 | D72: Pacific Finance Corp | E72: Western Canada | F72: 45809 | G72: 45813 | H72: 45813 | I72: created | N72: Analytics Enterprise | O72: Monthly | P72: 180 | Q72: 0
A73: EVT072 | B73: SUB038 | C73: CUST038 | D73: Calgary Tech Partners | E73: Western Canada | F73: 45809 | G73: 45817 | H73: 45817 | I73: created | N73: Analytics Starter | O73: Monthly | P73: 45 | Q73: 0
A74: EVT073 | B74: SUB049 | C74: CUST012 | D74: Maritime E-commerce | E74: Eastern Canada | F74: 45809 | G74: 45818 | H74: 45818 | I74: cancelled | J74: active | K74: cancelled | L74: status | M74: No longer needed | N74: Analytics Starter | O74: Monthly | P74: 45 | Q74: 0
A75: EVT074 | B75: SUB026 | C75: CUST026 | D75: Ontario Education Connect | E75: Eastern Canada | F75: 45809 | G75: 45823 | H75: 45823 | I75: plan_upgrade | J75: Analytics Starter | K75: Analytics Growth | L75: plan_name | M75: Growing usage - upgraded for advanced features and higher limits | N75: Analytics Growth | O75: Monthly | P75: 95 | Q75: 0
A76: EVT075 | B76: SUB039 | C76: CUST039 | D76: Toronto Commerce Cloud | E76: Eastern Canada | F76: 45809 | G76: 45831 | H76: 45831 | I76: created | N76: Marketing Pro | O76: Monthly | P76: 85 | Q76: 0
A77: EVT076 | B77: SUB023 | C77: CUST023 | D77: Island Media Productions | E77: Eastern Canada | F77: 45809 | G77: 45833 | H77: 45833 | I77: cancelled | J77: active | K77: churned | L77: status | M77: Missing features | N77: Analytics Starter | O77: Monthly | P77: 45 | Q77: 0
A78: EVT077 | B78: SUB059 | C78: CUST008 | D78: Quantum Education Platform | E78: Eastern Canada | F78: 45839 | G78: 45843 | H78: 45843 | I78: price_change | J78: 75 | K78: 85 | L78: price_per_seat | M78: Annual price increase applied at renewal | N78: Marketing Pro | O78: Monthly | P78: 85 | Q78: 0
A79: EVT078 | B79: SUB060 | C79: CUST019 | D79: Central Healthcare Partners | E79: Central Canada | F79: 45839 | G79: 45858 | H79: 45858 | I79: cancelled | J79: active | K79: cancelled | L79: status | M79: Budget cuts | N79: Sales Hub | O79: Monthly | P79: 110 | Q79: 0
A80: EVT079 | B80: SUB011 | C80: CUST011 | D80: Prairie Health Connect | E80: Central Canada | F80: 45839 | G80: 45860 | H80: 45860 | I80: seats_change | J80: 14 | K80: 18 | L80: seats | M80: Team expansion - mid-year headcount increase | N80: Sales Hub | O80: Monthly | P80: 110 | Q80: 0
A81: EVT080 | B81: SUB029 | C81: CUST029 | D81: Halifax Healthcare Tech | E81: Eastern Canada | F81: 45870 | G81: 45872 | H81: 45872 | I81: price_change | J81: 90 | K81: 85 | L81: price_per_seat | M81: Renewal negotiation - competitive pricing match | N81: Marketing Pro | O81: Monthly | P81: 85 | Q81: 0
A82: EVT081 | B82: SUB032 | C82: CUST032 | D82: BC Manufacturing Systems | E82: Western Canada | F82: 45870 | G82: 45881 | H82: 45881 | I82: plan_upgrade | J82: Analytics Growth | K82: Analytics Enterprise | L82: plan_name | M82: Enterprise SSO and audit logs required | N82: Analytics Enterprise | O82: Monthly | P82: 180 | Q82: 0
A83: EVT082 | B83: SUB017 | C83: CUST017 | D83: Capital Education Tech | E83: Eastern Canada | F83: 45870 | G83: 45888 | H83: 45888 | I83: plan_downgrade | J83: Analytics Growth | K83: Analytics Starter | L83: plan_name | M83: Reduced usage - advanced features no longer needed | N83: Analytics Starter | O83: Monthly | P83: 45 | Q83: 0
A84: EVT083 | B84: SUB022 | C84: CUST022 | D84: Toronto Tech Ventures | E84: Eastern Canada | F84: 45870 | G84: 45889 | H84: 45889 | I84: seats_change | J84: 28 | K84: 33 | L84: seats | M84: Team expansion - ops team grew | N84: Platform Suite | O84: Monthly | P84: 150 | Q84: 0
A85: EVT084 | B85: SUB055 | C85: CUST004 | D85: Prairie Commerce Group | E85: Western Canada | F85: 45870 | G85: 45899 | H85: 45899 | I85: cancelled | J85: active | K85: churned | L85: status | M85: Switched to competitor | N85: Analytics Enterprise | O85: Monthly | P85: 180 | Q85: 0
A86: EVT085 | B86: SUB030 | C86: CUST030 | D86: Alberta E-commerce Hub | E86: Western Canada | F86: 45901 | G86: 45905 | H86: 45905 | I86: plan_upgrade | J86: Analytics Starter | K86: Analytics Growth | L86: plan_name | M86: Upgraded for advanced analytics and API access | N86: Analytics Growth | O86: Monthly | P86: 95 | Q86: 0
A87: EVT086 | B87: SUB053 | C87: CUST027 | D87: Pacific Finance Corp | E87: Western Canada | F87: 45901 | G87: 45910 | H87: 45910 | I87: seats_change | J87: 26 | K87: 31 | L87: seats | M87: Department expansion - data team scaling | N87: Analytics Enterprise | O87: Monthly | P87: 180 | Q87: 0
A88: EVT087 | B88: SUB033 | C88: CUST033 | D88: Ottawa Retail Solutions | E88: Eastern Canada | F88: 45901 | G88: 45930 | H88: 45930 | I88: price_change | J88: 90 | K88: 85 | L88: price_per_seat | M88: Renewal negotiation - loyalty discount applied | N88: Marketing Pro | O88: Monthly | P88: 85 | Q88: 0
A89: EVT088 | B89: SUB024 | C89: CUST024 | D89: Western Retail Group | E89: Western Canada | F89: 45931 | G89: 45935 | H89: 45935 | I89: seats_change | J89: 26 | K89: 31 | L89: seats | M89: New department added - customer success team | N89: Marketing Pro | O89: Monthly | P89: 85 | Q89: 0
A90: EVT089 | B90: SUB062 | C90: CUST023 | D90: Island Media Productions | E90: Eastern Canada | F90: 45931 | G90: 45945 | H90: 45945 | I90: created | M90: Returning customer â€” reactivation | N90: Marketing Pro | O90: Monthly | P90: 85 | Q90: 0
A91: EVT090 | B91: SUB036 | C91: CUST036 | D91: Manitoba Finance Group | E91: Central Canada | F91: 45931 | G91: 45950 | H91: 45950 | I91: plan_upgrade | J91: Analytics Starter | K91: Analytics Growth | L91: plan_name | M91: Reached Starter usage limits - upgraded | N91: Analytics Growth | O91: Monthly | P91: 95 | Q91: 0
A92: EVT091 | B92: SUB015 | C92: CUST015 | D92: BC Retail Networks | E92: Western Canada | F92: 45962 | G92: 45962 | H92: 45962 | I92: discount_added | J92: 0 | K92: 10 | L92: discount_percent | M92: Retention discount - customer at-risk of churning | N92: Analytics Growth | O92: Monthly | P92: 95 | Q92: 10
A93: EVT092 | B93: SUB039 | C93: CUST039 | D93: Toronto Commerce Cloud | E93: Eastern Canada | F93: 45962 | G93: 45976 | H93: 45976 | I93: seats_change | J93: 32 | K93: 29 | L93: seats | M93: Restructuring - reduced team size | N93: Marketing Pro | O93: Monthly | P93: 85 | Q93: 0
A94: EVT093 | B94: SUB047 | C94: CUST022 | D94: Toronto Tech Ventures | E94: Eastern Canada | F94: 45992 | G94: 45999 | H94: 45999 | I94: seats_change | J94: 22 | K94: 26 | L94: seats | M94: Year-end headcount increase | N94: Sales Hub | O94: Monthly | P94: 110 | Q94: 0
A95: EVT094 | B95: SUB050 | C95: CUST007 | D95: Ontario Manufacturing Tech | E95: Eastern Canada | F95: 45992 | G95: 46006 | H95: 46006 | I95: discount_added | J95: 0 | K95: 12 | L95: discount_percent | M95: Retention discount - at-risk account escalated | N95: Analytics Starter | O95: Monthly | P95: 45 | Q95: 12
A96: EVT095 | B96: SUB015 | C96: CUST015 | D96: BC Retail Networks | E96: Western Canada | F96: 45992 | G96: 46021 | H96: 46021 | I96: cancelled | J96: active | K96: churned | L96: status | M96: Switched to competitor | N96: Analytics Growth | O96: Monthly | P96: 95 | Q96: 10
A97: EVT096 | B97: SUB040 | C97: CUST040 | D97: BC Education Innovations | E97: Western Canada | F97: 46023 | G97: 46048 | H97: 46048 | I97: created | N97: Analytics Growth | O97: Monthly | P97: 95 | Q97: 0
A98: EVT097 | B98: SUB050 | C98: CUST007 | D98: Ontario Manufacturing Tech | E98: Eastern Canada | F98: 46054 | G98: 46073 | H98: 46073 | I98: cancelled | J98: active | K98: churned | L98: status | M98: Poor support | N98: Analytics Starter | O98: Monthly | P98: 45 | Q98: 12

Sheet Raw Cash
A1: month | B1: invoice_count | C1: revenue | D1: running_total | E1: prior_month_revenue | F1: pct_change
A2: 45292 | B2: 2 | C2: 48700 | D2: 48700
A3: 45323 | B3: 4 | C3: 10185 | D3: 58885 | E3: 48700 | F3: -79.1
A4: 45352 | B4: 6 | C4: 77640 | D4: 136525 | E4: 10185 | F4: 662.3
A5: 45383 | B5: 8 | C5: 78930 | D5: 215455 | E5: 77640 | F5: 1.7
A6: 45413 | B6: 10 | C6: 17580 | D6: 233035 | E6: 78930 | F6: -77.7
A7: 45444 | B7: 13 | C7: 20595 | D7: 253630 | E7: 17580 | F7: 17.2
A8: 45474 | B8: 16 | C8: 26400 | D8: 280030 | E8: 20595 | F8: 28.2
A9: 45505 | B9: 19 | C9: 106740 | D9: 386770 | E9: 26400 | F9: 304.3
A10: 45536 | B10: 22 | C10: 42010 | D10: 428780 | E10: 106740 | F10: -60.6
A11: 45566 | B11: 25 | C11: 51390 | D11: 480170 | E11: 42010 | F11: 22.3
A12: 45597 | B12: 28 | C12: 55700 | D12: 535870 | E12: 51390 | F12: 8.4
A13: 45627 | B13: 31 | C13: 144560 | D13: 680430 | E13: 55700 | F13: 159.5
A14: 45658 | B14: 33 | C14: 139635 | D14: 820065 | E14: 144560 | F14: -3.4
... A27: 46054 | B27: 2 | C27: 2075 | D27: 2475630 | E27: 179985 | F27: -98.8

Sheet Ref
A1: plan_name | B1: monthly_price
A2: Analytics Starter | B2: 45
A3: Analytics Growth | B3: 95
A4: Analytics Enterprise | B4: 180
A5: Marketing Pro | B5: 85
A6: Sales Hub | B6: 110
A7: Platform Suite | B7: 150

Sheet Engine
A1: event_id | B1: subscription_id | C1: customer_id | D1: company_name | E1: region | F1: month | G1: event_date | H1: event_type | I1: old_value | J1: new_value | K1: field_changed | L1: reason | M1: plan_name | N1: billing_cycle | O1: seats | P1: price_per_seat | Q1: discount_percent | R1: movement | S1: mrr_delta | T1: is_new_logo | U1: is_logo_churn | V1: is_logo_reactivation
A2: EVT001 | B2: SUB001 | C2: CUST001 | D2: TechVision Solutions | E2: Eastern Canada | F2: 45292 | G2: 45299 | H2: created | M2: Analytics Growth | N2: Monthly | O2: 20 | P2: 95 | Q2: 0 | R2: {=_xlfn.IFS(H2="created", "New", H2="cancelled", "Churned", AND(H2="seats_change", J2 > I2), "Expansion", AND(H2="seats_change", J2 < I2), "Contraction", AND(H2="price_change", J2 > I2), "Expansion", AND(H2="price_change", J2 < I2), "Contraction", H2="plan_upgrade", "Expansion", H2="plan_downgrade", "Contraction", H2="discount_added", "Contraction")} -> New | S2: {=IF(N2="Monthly",_xlfn.IFS(H2="created",O2*P2*(1-Q2/100),H2="cancelled",-(O2*P2*(1-Q2/100)),H2="seats_change",(J2-I2)*P2*(1-Q2/100),H2="price_change",(J2-I2)*O2*(1-Q2/100),H2="discount_added",-(O2*P2*(J2-I2)/100),H2="plan_upgrade",O2*(_xlfn.XLOOKUP(J2,$M:$M,$P:$P)-_xlfn.XLOOKUP(I2,$M:$M,$P:$P))*(1-Q2/100),H2="plan_downgrade",O2*(_xlfn.XLOOKUP(J2,$M:$M,$P:$P)-_xlfn.XLOOKUP(I2,$M:$M,$P:$P))*(1-Q2/100)),_xlfn.IFS(H2="created",O2*P2*(1-Q2/100)/12,H2="cancelled",-(O2*P2*(1-Q2/100))/12,H2="seats_change",(J2-I2)*P2*(1-Q2/100)/12,H2="price_change",(J2-I2)*O2*(1-Q2/100)/12,H2="plan_upgrade",(O2*(_xlfn.XLOOKUP(J2,$M:$M,$P:$P)-_xlfn.XLOOKUP(I2,$M:$M,$P:$P))*(1-Q2/100))/12,H2="plan_downgrade",(O2*(_xlfn.XLOOKUP(J2,$M:$M,$P:$P)-_xlfn.XLOOKUP(I2,$M:$M,$P:$P))*(1-Q2/100))/12,H2="discount_added",-(O2*P2*(J2-I2)/100)/12))} -> 1900 | T2: =IF(H2<>"created",0,IF(COUNTIFS($C$1:C1,$C2,$H$1:H1,"created")=0,1,0)) -> 1 | U2: =IF(H2<>"cancelled",0,IF(COUNTIFS($C$2:$C$98,$C2,$H$2:$H$98,"created",$F$2:$F$98,"<="&F2)-COUNTIFS($C$2:$C$98,$C2,$H$2:$H$98,"cancelled",$F$2:$F$98,"<="&F2)=0,1,0)) -> 0 | V2: =IF(AND(H2="created",T2=0,COUNTIFS($C$2:$C$98,$C2,$H$2:$H$98,"cancelled",$F$2:$F$98,"<"&F2)>0,COUNTIFS($C$2:$C$98,$C2,$H$2:$H$98,"created",$F$2:$F$98,"<"&F2)-COUNTIFS($C$2:$C$98,$C2,$H$2:$H$98,"cancelled",$F$2:$F$98,"<"&F2)=0),1,0) -> 0
A3: EVT002 | B3: SUB002 | C3: CUST002 | D3: Pacific Analytics Inc | E3: Western Canada | F3: 45292 | G3: 45313 | H3: created | M3: Platform Suite | N3: Annual | O3: 26 | P3: 1800 | Q3: 0 | R3: {=_xlfn.IFS(H3="created", "New", H3="cancelled", "Churned", AND(H3="seats_change", J3 > I3), "Expansion", AND(H3="seats_change", J3 < I3), "Contraction", AND(H3="price_change", J3 > I3), "Expansion", AND(H3="price_change", J3 < I3), "Contraction", H3="plan_upgrade", "Expansion", H3="plan_downgrade", "Contraction", H3="discount_added", "Contraction")} -> New | S3: {=IF(N3="Monthly",_xlfn.IFS(H3="created",O3*P3*(1-Q3/100),H3="cancelled",-(O3*P3*(1-Q3/100)),H3="seats_change",(J3-I3)*P3*(1-Q3/100),H3="price_change",(J3-I3)*O3*(1-Q3/100),H3="discount_added",-(O3*P3*(J3-I3)/100),H3="plan_upgrade",O3*(_xlfn.XLOOKUP(J3,$M:$M,$P:$P)-_xlfn.XLOOKUP(I3,$M:$M,$P:$P))*(1-Q3/100),H3="plan_downgrade",O3*(_xlfn.XLOOKUP(J3,$M:$M,$P:$P)-_xlfn.XLOOKUP(I3,$M:$M,$P:$P))*(1-Q3/100)),_xlfn.IFS(H3="created",O3*P3*(1-Q3/100)/12,H3="cancelled",-(O3*P3*(1-Q3/100))/12,H3="seats_change",(J3-I3)*P3*(1-Q3/100)/12,H3="price_change",(J3-I3)*O3*(1-Q3/100)/12,H3="plan_upgrade",(O3*(_xlfn.XLOOKUP(J3,$M:$M,$P:$P)-_xlfn.XLOOKUP(I3,$M:$M,$P:$P))*(1-Q3/100))/12,H3="plan_downgrade",(O3*(_xlfn.XLOOKUP(J3,$M:$M,$P:$P)-_xlfn.XLOOKUP(I3,$M:$M,$P:$P))*(1-Q3/100))/12,H3="discount_added",-(O3*P3*(J3-I3)/100)/12))} -> 3900 | T3: =IF(H3<>"created",0,IF(COUNTIFS($C$1:C2,$C3,$H$1:H2,"created")=0,1,0)) -> 1 | U3: =IF(H3<>"cancelled",0,IF(COUNTIFS($C$2:$C$98,$C3,$H$2:$H$98,"created",$F$2:$F$98,"<="&F3)-COUNTIFS($C$2:$C$98,$C3,$H$2:$H$98,"cancelled",$F$2:$F$98,"<="&F3)=0,1,0)) -> 0 | V3: =IF(AND(H3="created",T3=0,COUNTIFS($C$2:$C$98,$C3,$H$2:$H$98,"cancelled",$F$2:$F$98,"<"&F3)>0,COUNTIFS($C$2:$C$98,$C3,$H$2:$H$98,"created",$F$2:$F$98,"<"&F3)-COUNTIFS($C$2:$C$98,$C3,$H$2:$H$98,"cancelled",$F$2:$F$98,"<"&F3)=0),1,0) -> 0
A4: EVT003 | B4: SUB003 | C4: CUST003 | D4: Maple Healthcare Systems | E4: Eastern Canada | F4: 45323 | G4: 45327 | H4: created | M4: Marketing Pro | N4: Monthly | O4: 23 | P4: 85 | Q4: 0 | R4: {=_xlfn.IFS(H4="created", "New", H4="cancelled", "Churned", AND(H4="seats_change", J4 > I4), "Expansion", AND(H4="seats_change", J4 < I4), "Contraction", AND(H4="price_change", J4 > I4), "Expansion", AND(H4="price_change", J4 < I4), "Contraction", H4="plan_upgrade", "Expansion", H4="plan_downgrade", "Contraction", H4="discount_added", "Contraction")} -> New | S4: {=IF(N4="Monthly",_xlfn.IFS(H4="created",O4*P4*(1-Q4/100),H4="cancelled",-(O4*P4*(1-Q4/100)),H4="seats_change",(J4-I4)*P4*(1-Q4/100),H4="price_change",(J4-I4)*O4*(1-Q4/100),H4="discount_added",-(O4*P4*(J4-I4)/100),H4="plan_upgrade",O4*(_xlfn.XLOOKUP(J4,$M:$M,$P:$P)-_xlfn.XLOOKUP(I4,$M:$M,$P:$P))*(1-Q4/100),H4="plan_downgrade",O4*(_xlfn.XLOOKUP(J4,$M:$M,$P:$P)-_xlfn.XLOOKUP(I4,$M:$M,$P:$P))*(1-Q4/100)),_xlfn.IFS(H4="created",O4*P4*(1-Q4/100)/12,H4="cancelled",-(O4*P4*(1-Q4/100))/12,H4="seats_change",(J4-I4)*P4*(1-Q4/100)/12,H4="price_change",(J4-I4)*O4*(1-Q4/100)/12,H4="plan_upgrade",(O4*(_xlfn.XLOOKUP(J4,$M:$M,$P:$P)-_xlfn.XLOOKUP(I4,$M:$M,$P:$P))*(1-Q4/100))/12,H4="plan_downgrade",(O4*(_xlfn.XLOOKUP(J4,$M:$M,$P:$P)-_xlfn.XLOOKUP(I4,$M:$M,$P:$P))*(1-Q4/100))/12,H4="discount_added",-(O4*P4*(J4-I4)/100)/12))} -> 1955 | T4: =IF(H4<>"created",0,IF(COUNTIFS($C$1:C3,$C4,$H$1:H3,"created")=0,1,0)) -> 1 | U4: =IF(H4<>"cancelled",0,IF(COUNTIFS($C$2:$C$98,$C4,$H$2:$H$98,"created",$F$2:$F$98,"<="&F4)-COUNTIFS($C$2:$C$98,$C4,$H$2:$H$98,"cancelled",$F$2:$F$98,"<="&F4)=0,1,0)) -> 0 | V4: =IF(AND(H4="created",T4=0,COUNTIFS($C$2:$C$98,$C4,$H$2:$H$98,"cancelled",$F$2:$F$98,"<"&F4)>0,COUNTIFS($C$2:$C$98,$C4,$H$2:$H$98,"created",$F$2:$F$98,"<"&F4)-COUNTIFS($C$2:$C$98,$C4,$H$2:$H$98,"cancelled",$F$2:$F$98,"<"&F4)=0),1,0) -> 0
A5: EVT004 | B5: SUB004 | C5: CUST004 | D5: Prairie Commerce Group | E5: Western Canada | F5: 45323 | G5: 45341 | H5: created | M5: Sales Hub | N5: Monthly | O5: 18 | P5: 110 | Q5: 0 | R5: {=_xlfn.IFS(H5="created", "New", H5="cancelled", "Churned", AND(H5="seats_change", J5 > I5), "Expansion", AND(H5="seats_change", J5 < I5), "Contraction", AND(H5="price_change", J5 > I5), "Expansion", AND(H5="price_change", J5 < I5), "Contraction", H5="plan_upgrade", "Expansion", H5="plan_downgrade", "Contraction", H5="discount_added", "Contraction")} -> New | S5: {=IF(N5="Monthly",_xlfn.IFS(H5="created",O5*P5*(1-Q5/100),H5="cancelled",-(O5*P5*(1-Q5/100)),H5="seats_change",(J5-I5)*P5*(1-Q5/100),H5="price_change",(J5-I5)*O5*(1-Q5/100),H5="discount_added",-(O5*P5*(J5-I5)/100),H5="plan_upgrade",O5*(_xlfn.XLOOKUP(J5,$M:$M,$P:$P)-_xlfn.XLOOKUP(I5,$M:$M,$P:$P))*(1-Q5/100),H5="plan_downgrade",O5*(_xlfn.XLOOKUP(J5,$M:$M,$P:$P)-_xlfn.XLOOKUP(I5,$M:$M,$P:$P))*(1-Q5/100)),_xlfn.IFS(H5="created",O5*P5*(1-Q5/100)/12,H5="cancelled",-(O5*P5*(1-Q5/100))/12,H5="seats_change",(J5-I5)*P5*(1-Q5/100)/12,H5="price_change",(J5-I5)*O5*(1-Q5/100)/12,H5="plan_upgrade",(O5*(_xlfn.XLOOKUP(J5,$M:$M,$P:$P)-_xlfn.XLOOKUP(I5,$M:$M,$P:$P))*(1-Q5/100))/12,H5="plan_downgrade",(O5*(_xlfn.XLOOKUP(J5,$M:$M,$P:$P)-_xlfn.XLOOKUP(I5,$M:$M,$P:$P))*(1-Q5/100))/12,H5="discount_added",-(O5*P5*(J5-I5)/100)/12))} -> 1980 | T5: =IF(H5<>"created",0,IF(COUNTIFS($C$1:C4,$C5,$H$1:H4,"created")=0,1,0)) -> 1 | U5: =IF(H5<>"cancelled",0,IF(COUNTIFS($C$2:$C$98,$C5,$H$2:$H$98,"created",$F$2:$F$98,"<="&F5)-COUNTIFS($C$2:$C$98,$C5,$H$2:$H$98,"cancelled",$F$2:$F$98,"<="&F5)=0,1,0)) -> 0 | V5: =IF(AND(H5="created",T5=0,COUNTIFS($C$2:$C$98,$C5,$H$2:$H$98,"cancelled",$F$2:$F$98,"<"&F5)>0,COUNTIFS($C$2:$C$98,$C5,$H$2:$H$98,"created",$F$2:$F$98,"<"&F5)-COUNTIFS($C$2:$C$98,$C5,$H$2:$H$98,"cancelled",$F$2:$F$98,"<"&F5)=0),1,0) -> 0
A6: EVT005 | B6: SUB055 | C6: CUST004 | D6: Prairie Commerce Group | E6: Western Canada | F6: 45323 | G6: 45341 | H6: created | M6: Analytics Enterprise | N6: Monthly | O6: 26 | P6: 180 | Q6: 0 | R6: {=_xlfn.IFS(H6="created", "New", H6="cancelled", "Churned", AND(H6="seats_change", J6 > I6), "Expansion", AND(H6="seats_change", J6 < I6), "Contraction", AND(H6="price_change", J6 > I6), "Expansion", AND(H6="price_change", J6 < I6), "Contraction", H6="plan_upgrade", "Expansion", H6="plan_downgrade", "Contraction", H6="discount_added", "Contraction")} -> New | S6: {=IF(N6="Monthly",_xlfn.IFS(H6="created",O6*P6*(1-Q6/100),H6="cancelled",-(O6*P6*(1-Q6/100)),H6="seats_change",(J6-I6)*P6*(1-Q6/100),H6="price_change",(J6-I6)*O6*(1-Q6/100),H6="discount_added",-(O6*P6*(J6-I6)/100),H6="plan_upgrade",O6*(_xlfn.XLOOKUP(J6,$M:$M,$P:$P)-_xlfn.XLOOKUP(I6,$M:$M,$P:$P))*(1-Q6/100),H6="plan_downgrade",O6*(_xlfn.XLOOKUP(J6,$M:$M,$P:$P)-_xlfn.XLOOKUP(I6,$M:$M,$P:$P))*(1-Q6/100)),_xlfn.IFS(H6="created",O6*P6*(1-Q6/100)/12,H6="cancelled",-(O6*P6*(1-Q6/100))/12,H6="seats_change",(J6-I6)*P6*(1-Q6/100)/12,H6="price_change",(J6-I6)*O6*(1-Q6/100)/12,H6="plan_upgrade",(O6*(_xlfn.XLOOKUP(J6,$M:$M,$P:$P)-_xlfn.XLOOKUP(I6,$M:$M,$P:$P))*(1-Q6/100))/12,H6="plan_downgrade",(O6*(_xlfn.XLOOKUP(J6,$M:$M,$P:$P)-_xlfn.XLOOKUP(I6,$M:$M,$P:$P))*(1-Q6/100))/12,H6="discount_added",-(O6*P6*(J6-I6)/100)/12))} -> 4680 | T6: =IF(H6<>"created",0,IF(COUNTIFS($C$1:C5,$C6,$H$1:H5,"created")=0,1,0)) -> 0 | U6: =IF(H6<>"cancelled",0,IF(COUNTIFS($C$2:$C$98,$C6,$H$2:$H$98,"created",$F$2:$F$98,"<="&F6)-COUNTIFS($C$2:$C$98,$C6,$H$2:$H$98,"cancelled",$F$2:$F$98,"<="&F6)=0,1,0)) -> 0 | V6: =IF(AND(H6="created",T6=0,COUNTIFS($C$2:$C$98,$C6,$H$2:$H$98,"cancelled",$F$2:$F$98,"<"&F6)>0,COUNTIFS($C$2:$C$98,$C6,$H$2:$H$98,"created",$F$2:$F$98,"<"&F6)-COUNTIFS($C$2:$C$98,$C6,$H$2:$H$98,"cancelled",$F$2:$F$98,"<"&F6)=0),1,0) -> 0
A7: EVT006 | B7: SUB005 | C7: CUST005 | D7: Atlantic Media Corp | E7: Eastern Canada | F7: 45352 | G7: 45355 | H7: created | M7: Analytics Starter | N7: Monthly | O7: 11 | P7: 45 | Q7: 0 | R7: {=_xlfn.IFS(H7="created", "New", H7="cancelled", "Churned", AND(H7="seats_change", J7 > I7), "Expansion", AND(H7="seats_change", J7 < I7), "Contraction", AND(H7="price_change", J7 > I7), "Expansion", AND(H7="price_change", J7 < I7), "Contraction", H7="plan_upgrade", "Expansion", H7="plan_downgrade", "Contraction", H7="discount_added", "Contraction")} -> New | S7: {=IF(N7="Monthly",_xlfn.IFS(H7="created",O7*P7*(1-Q7/100),H7="cancelled",-(O7*P7*(1-Q7/100)),H7="seats_change",(J7-I7)*P7*(1-Q7/100),H7="price_change",(J7-I7)*O7*(1-Q7/100),H7="discount_added",-(O7*P7*(J7-I7)/100),H7="plan_upgrade",O7*(_xlfn.XLOOKUP(J7,$M:$M,$P:$P)-_xlfn.XLOOKUP(I7,$M:$M,$P:$P))*(1-Q7/100),H7="plan_downgrade",O7*(_xlfn.XLOOKUP(J7,$M:$M,$P:$P)-_xlfn.XLOOKUP(I7,$M:$M,$P:$P))*(1-Q7/100)),_xlfn.IFS(H7="created",O7*P7*(1-Q7/100)/12,H7="cancelled",-(O7*P7*(1-Q7/100))/12,H7="seats_change",(J7-I7)*P7*(1-Q7/100)/12,H7="price_change",(J7-I7)*O7*(1-Q7/100)/12,H7="plan_upgrade",(O7*(_xlfn.XLOOKUP(J7,$M:$M,$P:$P)-_xlfn.XLOOKUP(I7,$M:$M,$P:$P))*(1-Q7/100))/12,H7="plan_downgrade",(O7*(_xlfn.XLOOKUP(J7,$M:$M,$P:$P)-_xlfn.XLOOKUP(I7,$M:$M,$P:$P))*(1-Q7/100))/12,H7="discount_added",-(O7*P7*(J7-I7)/100)/12))} -> 495 | T7: =IF(H7<>"created",0,IF(COUNTIFS($C$1:C6,$C7,$H$1:H6,"created")=0,1,0)) -> 1 | U7: =IF(H7<>"cancelled",0,IF(COUNTIFS($C$2:$C$98,$C7,$H$2:$H$98,"created",$F$2:$F$98,"<="&F7)-COUNTIFS($C$2:$C$98,$C7,$H$2:$H$98,"cancelled",$F$2:$F$98,"<="&F7)=0,1,0)) -> 0 | V7: =IF(AND(H7="created",T7=0,COUNTIFS($C$2:$C$98,$C7,$H$2:$H$98,"cancelled",$F$2:$F$98,"<"&F7)>0,COUNTIFS($C$2:$C$98,$C7,$H$2:$H$98,"created",$F$2:$F$98,"<"&F7)-COUNTIFS($C$2:$C$98,$C7,$H$2:$H$98,"cancelled",$F$2:$F$98,"<"&F7)=0),1,0) -> 0
A8: EVT007 | B8: SUB006 | C8: CUST006 | D8: Northern Retail Solutions | E8: Western Canada | F8: 45352 | G8: 45369 | H8: created | M8: Analytics Enterprise | N8: Annual | O8: 31 | P8: 2160 | Q8: 0 | R8: {=_xlfn.IFS(H8="created", "New", H8="cancelled", "Churned", AND(H8="seats_change", J8 > I8), "Expansion", AND(H8="seats_change", J8 < I8), "Contraction", AND(H8="price_change", J8 > I8), "Expansion", AND(H8="price_change", J8 < I8), "Contraction", H8="plan_upgrade", "Expansion", H8="plan_downgrade", "Contraction", H8="discount_added", "Contraction")} -> New | S8: {=IF(N8="Monthly",_xlfn.IFS(H8="created",O8*P8*(1-Q8/100),H8="cancelled",-(O8*P8*(1-Q8/100)),H8="seats_change",(J8-I8)*P8*(1-Q8/100),H8="price_change",(J8-I8)*O8*(1-Q8/100),H8="discount_added",-(O8*P8*(J8-I8)/100),H8="plan_upgrade",O8*(_xlfn.XLOOKUP(J8,$M:$M,$P:$P)-_xlfn.XLOOKUP(I8,$M:$M,$P:$P))*(1-Q8/100),H8="plan_downgrade",O8*(_xlfn.XLOOKUP(J8,$M:$M,$P:$P)-_xlfn.XLOOKUP(I8,$M:$M,$P:$P))*(1-Q8/100)),_xlfn.IFS(H8="created",O8*P8*(1-Q8/100)/12,H8="cancelled",-(O8*P8*(1-Q8/100))/12,H8="seats_change",(J8-I8)*P8*(1-Q8/100)/12,H8="price_change",(J8-I8)*O8*(1-Q8/100)/12,H8="plan_upgrade",(O8*(_xlfn.XLOOKUP(J8,$M:$M,$P:$P)-_xlfn.XLOOKUP(I8,$M:$M,$P:$P))*(1-Q8/100))/12,H8="plan_downgrade",(O8*(_xlfn.XLOOKUP(J8,$M:$M,$P:$P)-_xlfn.XLOOKUP(I8,$M:$M,$P:$P))*(1-Q8/100))/12,H8="discount_added",-(O8*P8*(J8-I8)/100)/12))} -> 5580 | T8: =IF(H8<>"created",0,IF(COUNTIFS($C$1:C7,$C8,$H$1:H7,"created")=0,1,0)) -> 1 | U8: =IF(H8<>"cancelled",0,IF(COUNTIFS($C$2:$C$98,$C8,$H$2:$H$98,"created",$F$2:$F$98,"<="&F8)-COUNTIFS($C$2:$C$98,$C8,$H$2:$H$98,"cancelled",$F$2:$F$98,"<="&F8)=0,1,0)) -> 0 | V8: =IF(AND(H8="created",T8=0,COUNTIFS($C$2:$C$98,$C8,$H$2:$H$98,"cancelled",$F$2:$F$98,"<"&F8)>0,COUNTIFS($C$2:$C$98,$C8,$H$2:$H$98,"created",$F$2:$F$98,"<"&F8)-COUNTIFS($C$2:$C$98,$C8,$H$2:$H$98,"cancelled",$F$2:$F$98,"<"&F8)=0),1,0) -> 0
A9: EVT008 | B9: SUB007 | C9: CUST007 | D9: Ontario Manufacturing Tech | E9: Eastern Canada | F9: 45383 | G9: 45383 | H9: created | M9: Marketing Pro | N9: Monthly | O9: 16 | P9: 85 | Q9: 0 | R9: {=_xlfn.IFS(H9="created", "New", H9="cancelled", "Churned", AND(H9="seats_change", J9 > I9), "Expansion", AND(H9="seats_change", J9 < I9), "Contraction", AND(H9="price_change", J9 > I9), "Expansion", AND(H9="price_change", J9 < I9), "Contraction", H9="plan_upgrade", "Expansion", H9="plan_downgrade", "Contraction", H9="discount_added", "Contraction")} -> New | S9: {=IF(N9="Monthly",_xlfn.IFS(H9="created",O9*P9*(1-Q9/100),H9="cancelled",-(O9*P9*(1-Q9/100)),H9="seats_change",(J9-I9)*P9*(1-Q9/100),H9="price_change",(J9-I9)*O9*(1-Q9/100),H9="discount_added",-(O9*P9*(J9-I9)/100),H9="plan_upgrade",O9*(_xlfn.XLOOKUP(J9,$M:$M,$P:$P)-_xlfn.XLOOKUP(I9,$M:$M,$P:$P))*(1-Q9/100),H9="plan_downgrade",O9*(_xlfn.XLOOKUP(J9,$M:$M,$P:$P)-_xlfn.XLOOKUP(I9,$M:$M,$P:$P))*(1-Q9/100)),_xlfn.IFS(H9="created",O9*P9*(1-Q9/100)/12,H9="cancelled",-(O9*P9*(1-Q9/100))/12,H9="seats_change",(J9-I9)*P9*(1-Q9/100)/12,H9="price_change",(J9-I9)*O9*(1-Q9/100)/12,H9="plan_upgrade",(O9*(_xlfn.XLOOKUP(J9,$M:$M,$P:$P)-_xlfn.XLOOKUP(I9,$M:$M,$P:$P))*(1-Q9/100))/12,H9="plan_downgrade",(O9*(_xlfn.XLOOKUP(J9,$M:$M,$P:$P)-_xlfn.XLOOKUP(I9,$M:$M,$P:$P))*(1-Q9/100))/12,H9="discount_added",-(O9*P9*(J9-I9)/100)/12))} -> 1360 | T9: =IF(H9<>"created",0,IF(COUNTIFS($C$1:C8,$C9,$H$1:H8,"created")=0,1,0)) -> 1 | U9: =IF(H9<>"cancelled",0,IF(COUNTIFS($C$2:$C$98,$C9,$H$2:$H$98,"created",$F$2:$F$98,"<="&F9)-COUNTIFS($C$2:$C$98,$C9,$H$2:$H$98,"cancelled",$F$2:$F$98,"<="&F9)=0,1,0)) -> 0 | V9: =IF(AND(H9="created",T9=0,COUNTIFS($C$2:$C$98,$C9,$H$2:$H$98,"cancelled",$F$2:$F$98,"<"&F9)>0,COUNTIFS($C$2:$C$98,$C9,$H$2:$H$98,"created",$F$2:$F$98,"<"&F9)-COUNTIFS($C$2:$C$98,$C9,$H$2:$H$98,"cancelled",$F$2:$F$98,"<"&F9)=0),1,0) -> 0
A10: EVT009 | B10: SUB050 | C10: CUST007 | D10: Ontario Manufacturing Tech | E10: Eastern Canada | F10: 45383 | G10: 45383 | H10: created | M10: Analytics Starter | N10: Monthly | O10: 15 | P10: 45 | Q10: 12 | R10: {=_xlfn.IFS(H10="created", "New", H10="cancelled", "Churned", AND(H10="seats_change", J10 > I10), "Expansion", AND(H10="seats_change", J10 < I10), "Contraction", AND(H10="price_change", J10 > I10), "Expansion", AND(H10="price_change", J10 < I10), "Contraction", H10="plan_upgrade", "Expansion", H10="plan_downgrade", "Contraction", H10="discount_added", "Contraction")} -> New | S10: {=IF(N10="Monthly",_xlfn.IFS(H10="created",O10*P10*(1-Q10/100),H10="cancelled",-(O10*P10*(1-Q10/100)),H10="seats_change",(J10-I10)*P10*(1-Q10/100),H10="price_change",(J10-I10)*O10*(1-Q10/100),H10="discount_added",-(O10*P10*(J10-I10)/100),H10="plan_upgrade",O10*(_xlfn.XLOOKUP(J10,$M:$M,$P:$P)-_xlfn.XLOOKUP(I10,$M:$M,$P:$P))*(1-Q10/100),H10="plan_downgrade",O10*(_xlfn.XLOOKUP(J10,$M:$M,$P:$P)-_xlfn.XLOOKUP(I10,$M:$M,$P:$P))*(1-Q10/100)),_xlfn.IFS(H10="created",O10*P10*(1-Q10/100)/12,H10="cancelled",-(O10*P10*(1-Q10/100))/12,H10="seats_change",(J10-I10)*P10*(1-Q10/100)/12,H10="price_change",(J10-I10)*O10*(1-Q10/100)/12,H10="plan_upgrade",(O10*(_xlfn.XLOOKUP(J10,$M:$M,$P:$P)-_xlfn.XLOOKUP(I10,$M:$M,$P:$P))*(1-Q10/100))/12,H10="plan_downgrade",(O10*(_xlfn.XLOOKUP(J10,$M:$M,$P:$P)-_xlfn.XLOOKUP(I10,$M:$M,$P:$P))*(1-Q10/100))/12,H10="discount_added",-(O10*P10*(J10-I10)/100)/12))} -> 594 | T10: =IF(H10<>"created",0,IF(COUNTIFS($C$1:C9,$C10,$H$1:H9,"created")=0,1,0)) -> 0 | U10: =IF(H10<>"cancelled",0,IF(COUNTIFS($C$2:$C$98,$C10,$H$2:$H$98,"created",$F$2:$F$98,"<="&F10)-COUNTIFS($C$2:$C$98,$C10,$H$2:$H$98,"cancelled",$F$2:$F$98,"<="&F10)=0,1,0)) -> 0 | V10: =IF(AND(H10="created",T10=0,COUNTIFS($C$2:$C$98,$C10,$H$2:$H$98,"cancelled",$F$2:$F$98,"<"&F10)>0,COUNTIFS($C$2:$C$98,$C10,$H$2:$H$98,"created",$F$2:$F$98,"<"&F10)-COUNTIFS($C$2:$C$98,$C10,$H$2:$H$98,"cancelled",$F$2:$F$98,"<"&F10)=0),1,0) -> 0
A11: EVT010 | B11: SUB008 | C11: CUST008 | D11: Quantum Education Platform | E11: Eastern Canada | F11: 45383 | G11: 45397 | H11: created | M11: Analytics Growth | N11: Monthly | O11: 22 | P11: 95 | Q11: 0 | R11: {=_xlfn.IFS(H11="created", "New", H11="cancelled", "Churned", AND(H11="seats_change", J11 > I11), "Expansion", AND(H11="seats_change", J11 < I11), "Contraction", AND(H11="price_change", J11 > I11), "Expansion", AND(H11="price_change", J11 < I11), "Contraction", H11="plan_upgrade", "Expansion", H11="plan_downgrade", "Contraction", H11="discount_added", "Contraction")} -> New | S11: {=IF(N11="Monthly",_xlfn.IFS(H11="created",O11*P11*(1-Q11/100),H11="cancelled",-(O11*P11*(1-Q11/100)),H11="seats_change",(J11-I11)*P11*(1-Q11/100),H11="price_change",(J11-I11)*O11*(1-Q11/100),H11="discount_added",-(O11*P11*(J11-I11)/100),H11="plan_upgrade",O11*(_xlfn.XLOOKUP(J11,$M:$M,$P:$P)-_xlfn.XLOOKUP(I11,$M:$M,$P:$P))*(1-Q11/100),H11="plan_downgrade",O11*(_xlfn.XLOOKUP(J11,$M:$M,$P:$P)-_xlfn.XLOOKUP(I11,$M:$M,$P:$P))*(1-Q11/100)),_xlfn.IFS(H11="created",O11*P11*(1-Q11/100)/12,H11="cancelled",-(O11*P11*(1-Q11/100))/12,H11="seats_change",(J11-I11)*P11*(1-Q11/100)/12,H11="price_change",(J11-I11)*O11*(1-Q11/100)/12,H11="plan_upgrade",(O11*(_xlfn.XLOOKUP(J11,$M:$M,$P:$P)-_xlfn.XLOOKUP(I11,$M:$M,$P:$P))*(1-Q11/100))/12,H11="plan_downgrade",(O11*(_xlfn.XLOOKUP(J11,$M:$M,$P:$P)-_xlfn.XLOOKUP(I11,$M:$M,$P:$P))*(1-Q11/100))/12,H11="discount_added",-(O11*P11*(J11-I11)/100)/12))} -> 2090 | T11: =IF(H11<>"created",0,IF(COUNTIFS($C$1:C10,$C11,$H$1:H10,"created")=0,1,0)) -> 1 | U11: =IF(H11<>"cancelled",0,IF(COUNTIFS($C$2:$C$98,$C11,$H$2:$H$98,"created",$F$2:$F$98,"<="&F11)-COUNTIFS($C$2:$C$98,$C11,$H$2:$H$98,"cancelled",$F$2:$F$98,"<="&F11)=0,1,0)) -> 0 | V11: =IF(AND(H11="created",T11=0,COUNTIFS($C$2:$C$98,$C11,$H$2:$H$98,"cancelled",$F$2:$F$98,"<"&F11)>0,COUNTIFS($C$2:$C$98,$C11,$H$2:$H$98,"created",$F$2:$F$98,"<"&F11)-COUNTIFS($C$2:$C$98,$C11,$H$2:$H$98,"cancelled",$F$2:$F$98,"<"&F11)=0),1,0) -> 0
A12: EVT011 | B12: SUB009 | C12: CUST009 | D12: West Coast Logistics | E12: Western Canada | F12: 45383 | G12: 45411 | H12: created | M12: Platform Suite | N12: Annual | O12: 36 | P12: 1800 | Q12: 0 | R12: {=_xlfn.IFS(H12="created", "New", H12="cancelled", "Churned", AND(H12="seats_change", J12 > I12), "Expansion", AND(H12="seats_change", J12 < I12), "Contraction", AND(H12="price_change", J12 > I12), "Expansion", AND(H12="price_change", J12 < I12), "Contraction", H12="plan_upgrade", "Expansion", H12="plan_downgrade", "Contraction", H12="discount_added", "Contraction")} -> New | S12: {=IF(N12="Monthly",_xlfn.IFS(H12="created",O12*P12*(1-Q12/100),H12="cancelled",-(O12*P12*(1-Q12/100)),H12="seats_change",(J12-I12)*P12*(1-Q12/100),H12="price_change",(J12-I12)*O12*(1-Q12/100),H12="discount_added",-(O12*P12*(J12-I12)/100),H12="plan_upgrade",O12*(_xlfn.XLOOKUP(J12,$M:$M,$P:$P)-_xlfn.XLOOKUP(I12,$M:$M,$P:$P))*(1-Q12/100),H12="plan_downgrade",O12*(_xlfn.XLOOKUP(J12,$M:$M,$P:$P)-_xlfn.XLOOKUP(I12,$M:$M,$P:$P))*(1-Q12/100)),_xlfn.IFS(H12="created",O12*P12*(1-Q12/100)/12,H12="cancelled",-(O12*P12*(1-Q12/100))/12,H12="seats_change",(J12-I12)*P12*(1-Q12/100)/12,H12="price_change",(J12-I12)*O12*(1-Q12/100)/12,H12="plan_upgrade",(O12*(_xlfn.XLOOKUP(J12,$M:$M,$P:$P)-_xlfn.XLOOKUP(I12,$M:$M,$P:$P))*(1-Q12/100))/12,H12="plan_downgrade",(O12*(_xlfn.XLOOKUP(J12,$M:$M,$P:$P)-_xlfn.XLOOKUP(I12,$M:$M,$P:$P))*(1-Q12/100))/12,H12="discount_added",-(O12*P12*(J12-I12)/100)/12))} -> 5400 | T12: =IF(H12<>"created",0,IF(COUNTIFS($C$1:C11,$C12,$H$1:H11,"created")=0,1,0)) -> 1 | U12: =IF(H12<>"cancelled",0,IF(COUNTIFS($C$2:$C$98,$C12,$H$2:$H$98,"created",$F$2:$F$98,"<="&F12)-COUNTIFS($C$2:$C$98,$C12,$H$2:$H$98,"cancelled",$F$2:$F$98,"<="&F12)=0,1,0)) -> 0 | V12: =IF(AND(H12="created",T12=0,COUNTIFS($C$2:$C$98,$C12,$H$2:$H$98,"cancelled",$F$2:$F$98,"<"&F12)>0,COUNTIFS($C$2:$C$98,$C12,$H$2:$H$98,"created",$F$2:$F$98,"<"&F12)-COUNTIFS($C$2:$C$98,$C12,$H$2:$H$98,"cancelled",$F$2:$F$98,"<"&F12)=0),1,0) -> 0
A13: EVT012 | B13: SUB010 | C13: CUST010 | D13: Montreal Finance Hub | E13: Eastern Canada | F13: 45413 | G13: 45425 | H13: created | M13: Analytics Starter | N13: Monthly | O13: 13 | P13: 45 | Q13: 0 | R13: {=_xlfn.IFS(H13="created", "New", H13="cancelled", "Churned", AND(H13="seats_change", J13 > I13), "Expansion", AND(H13="seats_change", J13 < I13), "Contraction", AND(H13="price_change", J13 > I13), "Expansion", AND(H13="price_change", J13 < I13), "Contraction", H13="plan_upgrade", "Expansion", H13="plan_downgrade", "Contraction", H13="discount_added", "Contraction")} -> New | S13: {=IF(N13="Monthly",_xlfn.IFS(H13="created",O13*P13*(1-Q13/100),H13="cancelled",-(O13*P13*(1-Q13/100)),H13="seats_change",(J13-I13)*P13*(1-Q13/100),H13="price_change",(J13-I13)*O13*(1-Q13/100),H13="discount_added",-(O13*P13*(J13-I13)/100),H13="plan_upgrade",O13*(_xlfn.XLOOKUP(J13,$M:$M,$P:$P)-_xlfn.XLOOKUP(I13,$M:$M,$P:$P))*(1-Q13/100),H13="plan_downgrade",O13*(_xlfn.XLOOKUP(J13,$M:$M,$P:$P)-_xlfn.XLOOKUP(I13,$M:$M,$P:$P))*(1-Q13/100)),_xlfn.IFS(H13="created",O13*P13*(1-Q13/100)/12,H13="cancelled",-(O13*P13*(1-Q13/100))/12,H13="seats_change",(J13-I13)*P13*(1-Q13/100)/12,H13="price_change",(J13-I13)*O13*(1-Q13/100)/12,H13="plan_upgrade",(O13*(_xlfn.XLOOKUP(J13,$M:$M,$P:$P)-_xlfn.XLOOKUP(I13,$M:$M,$P:$P))*(1-Q13/100))/12,H13="plan_downgrade",(O13*(_xlfn.XLOOKUP(J13,$M:$M,$P:$P)-_xlfn.XLOOKUP(I13,$M:$M,$P:$P))*(1-Q13/100))/12,H13="discount_added",-(O13*P13*(J13-I13)/100)/12))} -> 585 | T13: =IF(H13<>"created",0,IF(COUNTIFS($C$1:C12,$C13,$H$1:H12,"created")=0,1,0)) -> 1 | U13: =IF(H13<>"cancelled",0,IF(COUNTIFS($C$2:$C$98,$C13,$H$2:$H$98,"created",$F$2:$F$98,"<="&F13)-COUNTIFS($C$2:$C$98,$C13,$H$2:$H$98,"cancelled",$F$2:$F$98,"<="&F13)=0,1,0)) -> 0 | V13: =IF(AND(H13="created",T13=0,COUNTIFS($C$2:$C$98,$C13,$H$2:$H$98,"cancelled",$F$2:$F$98,"<"&F13)>0,COUNTIFS($C$2:$C$98,$C13,$H$2:$H$98,"created",$F$2:$F$98,"<"&F13)-COUNTIFS($C$2:$C$98,$C13,$H$2:$H$98,"cancelled",$F$2:$F$98,"<"&F13)=0),1,0) -> 0
... A23: EVT022 | B23: SUB017 | C23: CUST017 | D23: Capital Education Tech | E23: Eastern Canada | F23: 45505 | G23: 45523 | H23: created | M23: Analytics Starter | N23: Monthly | O23: 12 | P23: 45 | Q23: 0 | R23: {=_xlfn.IFS(H23="created", "New", H23="cancelled", "Churned", AND(H23="seats_change", J23 > I23), "Expansion", AND(H23="seats_change", J23 < I23), "Contraction", AND(H23="price_change", J23 > I23), "Expansion", AND(H23="price_change", J23 < I23), "Contraction", H23="plan_upgrade", "Expansion", H23="plan_downgrade", "Contraction", H23="discount_added", "Contraction")} -> New | S23: {=IF(N23="Monthly",_xlfn.IFS(H23="created",O23*P23*(1-Q23/100),H23="cancelled",-(O23*P23*(1-Q23/100)),H23="seats_change",(J23-I23)*P23*(1-Q23/100),H23="price_change",(J23-I23)*O23*(1-Q23/100),H23="discount_added",-(O23*P23*(J23-I23)/100),H23="plan_upgrade",O23*(_xlfn.XLOOKUP(J23,$M:$M,$P:$P)-_xlfn.XLOOKUP(I23,$M:$M,$P:$P))*(1-Q23/100),H23="plan_downgrade",O23*(_xlfn.XLOOKUP(J23,$M:$M,$P:$P)-_xlfn.XLOOKUP(I23,$M:$M,$P:$P))*(1-Q23/100)),_xlfn.IFS(H23="created",O23*P23*(1-Q23/100)/12,H23="cancelled",-(O23*P23*(1-Q23/100))/12,H23="seats_change",(J23-I23)*P23*(1-Q23/100)/12,H23="price_change",(J23-I23)*O23*(1-Q23/100)/12,H23="plan_upgrade",(O23*(_xlfn.XLOOKUP(J23,$M:$M,$P:$P)-_xlfn.XLOOKUP(I23,$M:$M,$P:$P))*(1-Q23/100))/12,H23="plan_downgrade",(O23*(_xlfn.XLOOKUP(J23,$M:$M,$P:$P)-_xlfn.XLOOKUP(I23,$M:$M,$P:$P))*(1-Q23/100))/12,H23="discount_added",-(O23*P23*(J23-I23)/100)/12))} -> 540 | T23: =IF(H23<>"created",0,IF(COUNTIFS($C$1:C22,$C23,$H$1:H22,"created")=0,1,0)) -> 1 | U23: =IF(H23<>"cancelled",0,IF(COUNTIFS($C$2:$C$98,$C23,$H$2:$H$98,"created",$F$2:$F$98,"<="&F23)-COUNTIFS($C$2:$C$98,$C23,$H$2:$H$98,"cancelled",$F$2:$F$98,"<="&F23)=0,1,0)) -> 0 | V23: =IF(AND(H23="created",T23=0,COUNTIFS($C$2:$C$98,$C23,$H$2:$H$98,"cancelled",$F$2:$F$98,"<"&F23)>0,COUNTIFS($C$2:$C$98,$C23,$H$2:$H$98,"created",$F$2:$F$98,"<"&F23)-COUNTIFS($C$2:$C$98,$C23,$H$2:$H$98,"cancelled",$F$2:$F$98,"<"&F23)=0),1,0) -> 0
A24: EVT023 | B24: SUB001 | C24: CUST001 | D24: TechVision Solutions | E24: Eastern Canada | F24: 45505 | G24: 45531 | H24: cancelled | I24: active | J24: churned | K24: status | L24: Missing features | M24: Analytics Growth | N24: Monthly | O24: 20 | P24: 95 | Q24: 0 | R24: {=_xlfn.IFS(H24="created", "New", H24="cancelled", "Churned", AND(H24="seats_change", J24 > I24), "Expansion", AND(H24="seats_change", J24 < I24), "Contraction", AND(H24="price_change", J24 > I24), "Expansion", AND(H24="price_change", J24 < I24), "Contraction", H24="plan_upgrade", "Expansion", H24="plan_downgrade", "Contraction", H24="discount_added", "Contraction")} -> Churned | S24: {=IF(N24="Monthly",_xlfn.IFS(H24="created",O24*P24*(1-Q24/100),H24="cancelled",-(O24*P24*(1-Q24/100)),H24="seats_change",(J24-I24)*P24*(1-Q24/100),H24="price_change",(J24-I24)*O24*(1-Q24/100),H24="discount_added",-(O24*P24*(J24-I24)/100),H24="plan_upgrade",O24*(_xlfn.XLOOKUP(J24,$M:$M,$P:$P)-_xlfn.XLOOKUP(I24,$M:$M,$P:$P))*(1-Q24/100),H24="plan_downgrade",O24*(_xlfn.XLOOKUP(J24,$M:$M,$P:$P)-_xlfn.XLOOKUP(I24,$M:$M,$P:$P))*(1-Q24/100)),_xlfn.IFS(H24="created",O24*P24*(1-Q24/100)/12,H24="cancelled",-(O24*P24*(1-Q24/100))/12,H24="seats_change",(J24-I24)*P24*(1-Q24/100)/12,H24="price_change",(J24-I24)*O24*(1-Q24/100)/12,H24="plan_upgrade",(O24*(_xlfn.XLOOKUP(J24,$M:$M,$P:$P)-_xlfn.XLOOKUP(I24,$M:$M,$P:$P))*(1-Q24/100))/12,H24="plan_downgrade",(O24*(_xlfn.XLOOKUP(J24,$M:$M,$P:$P)-_xlfn.XLOOKUP(I24,$M:$M,$P:$P))*(1-Q24/100))/12,H24="discount_added",-(O24*P24*(J24-I24)/100)/12))} -> -1900 | T24: =IF(H24<>"created",0,IF(COUNTIFS($C$1:C23,$C24,$H$1:H23,"created")=0,1,0)) -> 0 | U24: =IF(H24<>"cancelled",0,IF(COUNTIFS($C$2:$C$98,$C24,$H$2:$H$98,"created",$F$2:$F$98,"<="&F24)-COUNTIFS($C$2:$C$98,$C24,$H$2:$H$98,"cancelled",$F$2:$F$98,"<="&F24)=0,1,0)) -> 0 | V24: =IF(AND(H24="created",T24=0,COUNTIFS($C$2:$C$98,$C24,$H$2:$H$98,"cancelled",$F$2:$F$98,"<"&F24)>0,COUNTIFS($C$2:$C$98,$C24,$H$2:$H$98,"created",$F$2:$F$98,"<"&F24)-COUNTIFS($C$2:$C$98,$C24,$H$2:$H$98,"cancelled",$F$2:$F$98,"<"&F24)=0),1,0) -> 0
A25: EVT024 | B25: SUB018 | C25: CUST018 | D25: Vancouver FinTech Labs | E25: Western Canada | F25: 45536 | G25: 45537 | H25: created | M25: Analytics Enterprise | N25: Monthly | O25: 35 | P25: 180 | Q25: 0 | R25: {=_xlfn.IFS(H25="created", "New", H25="cancelled", "Churned", AND(H25="seats_change", J25 > I25), "Expansion", AND(H25="seats_change", J25 < I25), "Contraction", AND(H25="price_change", J25 > I25), "Expansion", AND(H25="price_change", J25 < I25), "Contraction", H25="plan_upgrade", "Expansion", H25="plan_downgrade", "Contraction", H25="discount_added", "Contraction")} -> New | S25: {=IF(N25="Monthly",_xlfn.IFS(H25="created",O25*P25*(1-Q25/100),H25="cancelled",-(O25*P25*(1-Q25/100)),H25="seats_change",(J25-I25)*P25*(1-Q25/100),H25="price_change",(J25-I25)*O25*(1-Q25/100),H25="discount_added",-(O25*P25*(J25-I25)/100),H25="plan_upgrade",O25*(_xlfn.XLOOKUP(J25,$M:$M,$P:$P)-_xlfn.XLOOKUP(I25,$M:$M,$P:$P))*(1-Q25/100),H25="plan_downgrade",O25*(_xlfn.XLOOKUP(J25,$M:$M,$P:$P)-_xlfn.XLOOKUP(I25,$M:$M,$P:$P))*(1-Q25/100)),_xlfn.IFS(H25="created",O25*P25*(1-Q25/100)/12,H25="cancelled",-(O25*P25*(1-Q25/100))/12,H25="seats_change",(J25-I25)*P25*(1-Q25/100)/12,H25="price_change",(J25-I25)*O25*(1-Q25/100)/12,H25="plan_upgrade",(O25*(_xlfn.XLOOKUP(J25,$M:$M,$P:$P)-_xlfn.XLOOKUP(I25,$M:$M,$P:$P))*(1-Q25/100))/12,H25="plan_downgrade",(O25*(_xlfn.XLOOKUP(J25,$M:$M,$P:$P)-_xlfn.XLOOKUP(I25,$M:$M,$P:$P))*(1-Q25/100))/12,H25="discount_added",-(O25*P25*(J25-I25)/100)/12))} -> 6300 | T25: =IF(H25<>"created",0,IF(COUNTIFS($C$1:C24,$C25,$H$1:H24,"created")=0,1,0)) -> 1 | U25: =IF(H25<>"cancelled",0,IF(COUNTIFS($C$2:$C$98,$C25,$H$2:$H$98,"created",$F$2:$F$98,"<="&F25)-COUNTIFS($C$2:$C$98,$C25,$H$2:$H$98,"cancelled",$F$2:$F$98,"<="&F25)=0,1,0)) -> 0 | V25: =IF(AND(H25="created",T25=0,COUNTIFS($C$2:$C$98,$C25,$H$2:$H$98,"cancelled",$F$2:$F$98,"<"&F25)>0,COUNTIFS($C$2:$C$98,$C25,$H$2:$H$98,"created",$F$2:$F$98,"<"&F25)-COUNTIFS($C$2:$C$98,$C25,$H$2:$H$98,"cancelled",$F$2:$F$98,"<"&F25)=0),1,0) -> 0
A26: EVT025 | B26: SUB042 | C26: CUST003 | D26: Maple Healthcare Systems | E26: Eastern Canada | F26: 45536 | G26: 45545 | H26: created | M26: Sales Hub | N26: Monthly | O26: 19 | P26: 110 | Q26: 0 | R26: {=_xlfn.IFS(H26="created", "New", H26="cancelled", "Churned", AND(H26="seats_change", J26 > I26), "Expansion", AND(H26="seats_change", J26 < I26), "Contraction", AND(H26="price_change", J26 > I26), "Expansion", AND(H26="price_change", J26 < I26), "Contraction", H26="plan_upgrade", "Expansion", H26="plan_downgrade", "Contraction", H26="discount_added", "Contraction")} -> New | S26: {=IF(N26="Monthly",_xlfn.IFS(H26="created",O26*P26*(1-Q26/100),H26="cancelled",-(O26*P26*(1-Q26/100)),H26="seats_change",(J26-I26)*P26*(1-Q26/100),H26="price_change",(J26-I26)*O26*(1-Q26/100),H26="discount_added",-(O26*P26*(J26-I26)/100),H26="plan_upgrade",O26*(_xlfn.XLOOKUP(J26,$M:$M,$P:$P)-_xlfn.XLOOKUP(I26,$M:$M,$P:$P))*(1-Q26/100),H26="plan_downgrade",O26*(_xlfn.XLOOKUP(J26,$M:$M,$P:$P)-_xlfn.XLOOKUP(I26,$M:$M,$P:$P))*(1-Q26/100)),_xlfn.IFS(H26="created",O26*P26*(1-Q26/100)/12,H26="cancelled",-(O26*P26*(1-Q26/100))/12,H26="seats_change",(J26-I26)*P26*(1-Q26/100)/12,H26="price_change",(J26-I26)*O26*(1-Q26/100)/12,H26="plan_upgrade",(O26*(_xlfn.XLOOKUP(J26,$M:$M,$P:$P)-_xlfn.XLOOKUP(I26,$M:$M,$P:$P))*(1-Q26/100))/12,H26="plan_downgrade",(O26*(_xlfn.XLOOKUP(J26,$M:$M,$P:$P)-_xlfn.XLOOKUP(I26,$M:$M,$P:$P))*(1-Q26/100))/12,H26="discount_added",-(O26*P26*(J26-I26)/100)/12))} -> 2090 | T26: =IF(H26<>"created",0,IF(COUNTIFS($C$1:C25,$C26,$H$1:H25,"created")=0,1,0)) -> 0 | U26: =IF(H26<>"cancelled",0,IF(COUNTIFS($C$2:$C$98,$C26,$H$2:$H$98,"created",$F$2:$F$98,"<="&F26)-COUNTIFS($C$2:$C$98,$C26,$H$2:$H$98,"cancelled",$F$2:$F$98,"<="&F26)=0,1,0)) -> 0 | V26: =IF(AND(H26="created",T26=0,COUNTIFS($C$2:$C$98,$C26,$H$2:$H$98,"cancelled",$F$2:$F$98,"<"&F26)>0,COUNTIFS($C$2:$C$98,$C26,$H$2:$H$98,"created",$F$2:$F$98,"<"&F26)-COUNTIFS($C$2:$C$98,$C26,$H$2:$H$98,"cancelled",$F$2:$F$98,"<"&F26)=0),1,0) -> 0
A27: EVT026 | B27: SUB019 | C27: CUST019 | D27: Central Healthcare Partners | E27: Central Canada | F27: 45536 | G27: 45551 | H27: created | M27: Marketing Pro | N27: Monthly | O27: 19 | P27: 85 | Q27: 0 | R27: {=_xlfn.IFS(H27="created", "New", H27="cancelled", "Churned", AND(H27="seats_change", J27 > I27), "Expansion", AND(H27="seats_change", J27 < I27), "Contraction", AND(H27="price_change", J27 > I27), "Expansion", AND(H27="price_change", J27 < I27), "Contraction", H27="plan_upgrade", "Expansion", H27="plan_downgrade", "Contraction", H27="discount_added", "Contraction")} -> New | S27: {=IF(N27="Monthly",_xlfn.IFS(H27="created",O27*P27*(1-Q27/100),H27="cancelled",-(O27*P27*(1-Q27/100)),H27="seats_change",(J27-I27)*P27*(1-Q27/100),H27="price_change",(J27-I27)*O27*(1-Q27/100),H27="discount_added",-(O27*P27*(J27-I27)/100),H27="plan_upgrade",O27*(_xlfn.XLOOKUP(J27,$M:$M,$P:$P)-_xlfn.XLOOKUP(I27,$M:$M,$P:$P))*(1-Q27/100),H27="plan_downgrade",O27*(_xlfn.XLOOKUP(J27,$M:$M,$P:$P)-_xlfn.XLOOKUP(I27,$M:$M,$P:$P))*(1-Q27/100)),_xlfn.IFS(H27="created",O27*P27*(1-Q27/100)/12,H27="cancelled",-(O27*P27*(1-Q27/100))/12,H27="seats_change",(J27-I27)*P27*(1-Q27/100)/12,H27="price_change",(J27-I27)*O27*(1-Q27/100)/12,H27="plan_upgrade",(O27*(_xlfn.XLOOKUP(J27,$M:$M,$P:$P)-_xlfn.XLOOKUP(I27,$M:$M,$P:$P))*(1-Q27/100))/12,H27="plan_downgrade",(O27*(_xlfn.XLOOKUP(J27,$M:$M,$P:$P)-_xlfn.XLOOKUP(I27,$M:$M,$P:$P))*(1-Q27/100))/12,H27="discount_added",-(O27*P27*(J27-I27)/100)/12))} -> 1615 | T27: =IF(H27<>"created",0,IF(COUNTIFS($C$1:C26,$C27,$H$1:H26,"created")=0,1,0)) -> 1 | U27: =IF(H27<>"cancelled",0,IF(COUNTIFS($C$2:$C$98,$C27,$H$2:$H$98,"created",$F$2:$F$98,"<="&F27)-COUNTIFS($C$2:$C$98,$C27,$H$2:$H$98,"cancelled",$F$2:$F$98,"<="&F27)=0,1,0)) -> 0 | V27: =IF(AND(H27="created",T27=0,COUNTIFS($C$2:$C$98,$C27,$H$2:$H$98,"cancelled",$F$2:$F$98,"<"&F27)>0,COUNTIFS($C$2:$C$98,$C27,$H$2:$H$98,"created",$F$2:$F$98,"<"&F27)-COUNTIFS($C$2:$C$98,$C27,$H$2:$H$98,"cancelled",$F$2:$F$98,"<"&F27)=0),1,0) -> 0
A28: EVT027 | B28: SUB060 | C28: CUST019 | D28: Central Healthcare Partners | E28: Central Canada | F28: 45536 | G28: 45551 | H28: created | M28: Sales Hub | N28: Monthly | O28: 16 | P28: 110 | Q28: 0 | R28: {=_xlfn.IFS(H28="created", "New", H28="cancelled", "Churned", AND(H28="seats_change", J28 > I28), "Expansion", AND(H28="seats_change", J28 < I28), "Contraction", AND(H28="price_change", J28 > I28), "Expansion", AND(H28="price_change", J28 < I28), "Contraction", H28="plan_upgrade", "Expansion", H28="plan_downgrade", "Contraction", H28="discount_added", "Contraction")} -> New | S28: {=IF(N28="Monthly",_xlfn.IFS(H28="created",O28*P28*(1-Q28/100),H28="cancelled",-(O28*P28*(1-Q28/100)),H28="seats_change",(J28-I28)*P28*(1-Q28/100),H28="price_change",(J28-I28)*O28*(1-Q28/100),H28="discount_added",-(O28*P28*(J28-I28)/100),H28="plan_upgrade",O28*(_xlfn.XLOOKUP(J28,$M:$M,$P:$P)-_xlfn.XLOOKUP(I28,$M:$M,$P:$P))*(1-Q28/100),H28="plan_downgrade",O28*(_xlfn.XLOOKUP(J28,$M:$M,$P:$P)-_xlfn.XLOOKUP(I28,$M:$M,$P:$P))*(1-Q28/100)),_xlfn.IFS(H28="created",O28*P28*(1-Q28/100)/12,H28="cancelled",-(O28*P28*(1-Q28/100))/12,H28="seats_change",(J28-I28)*P28*(1-Q28/100)/12,H28="price_change",(J28-I28)*O28*(1-Q28/100)/12,H28="plan_upgrade",(O28*(_xlfn.XLOOKUP(J28,$M:$M,$P:$P)-_xlfn.XLOOKUP(I28,$M:$M,$P:$P))*(1-Q28/100))/12,H28="plan_downgrade",(O28*(_xlfn.XLOOKUP(J28,$M:$M,$P:$P)-_xlfn.XLOOKUP(I28,$M:$M,$P:$P))*(1-Q28/100))/12,H28="discount_added",-(O28*P28*(J28-I28)/100)/12))} -> 1760 | T28: =IF(H28<>"created",0,IF(COUNTIFS($C$1:C27,$C28,$H$1:H27,"created")=0,1,0)) -> 0 | U28: =IF(H28<>"cancelled",0,IF(COUNTIFS($C$2:$C$98,$C28,$H$2:$H$98,"created",$F$2:$F$98,"<="&F28)-COUNTIFS($C$2:$C$98,$C28,$H$2:$H$98,"cancelled",$F$2:$F$98,"<="&F28)=0,1,0)) -> 0 | V28: =IF(AND(H28="created",T28=0,COUNTIFS($C$2:$C$98,$C28,$H$2:$H$98,"cancelled",$F$2:$F$98,"<"&F28)>0,COUNTIFS($C$2:$C$98,$C28,$H$2:$H$98,"created",$F$2:$F$98,"<"&F28)-COUNTIFS($C$2:$C$98,$C28,$H$2:$H$98,"cancelled",$F$2:$F$98,"<"&F28)=0),1,0) -> 0
A29: EVT028 | B29: SUB020 | C29: CUST020 | D29: Atlantic SaaS Systems | E29: Eastern Canada | F29: 45536 | G29: 45565 | H29: created | M29: Sales Hub | N29: Monthly | O29: 15 | P29: 110 | Q29: 0 | R29: {=_xlfn.IFS(H29="created", "New", H29="cancelled", "Churned", AND(H29="seats_change", J29 > I29), "Expansion", AND(H29="seats_change", J29 < I29), "Contraction", AND(H29="price_change", J29 > I29), "Expansion", AND(H29="price_change", J29 < I29), "Contraction", H29="plan_upgrade", "Expansion", H29="plan_downgrade", "Contraction", H29="discount_added", "Contraction")} -> New | S29: {=IF(N29="Monthly",_xlfn.IFS(H29="created",O29*P29*(1-Q29/100),H29="cancelled",-(O29*P29*(1-Q29/100)),H29="seats_change",(J29-I29)*P29*(1-Q29/100),H29="price_change",(J29-I29)*O29*(1-Q29/100),H29="discount_added",-(O29*P29*(J29-I29)/100),H29="plan_upgrade",O29*(_xlfn.XLOOKUP(J29,$M:$M,$P:$P)-_xlfn.XLOOKUP(I29,$M:$M,$P:$P))*(1-Q29/100),H29="plan_downgrade",O29*(_xlfn.XLOOKUP(J29,$M:$M,$P:$P)-_xlfn.XLOOKUP(I29,$M:$M,$P:$P))*(1-Q29/100)),_xlfn.IFS(H29="created",O29*P29*(1-Q29/100)/12,H29="cancelled",-(O29*P29*(1-Q29/100))/12,H29="seats_change",(J29-I29)*P29*(1-Q29/100)/12,H29="price_change",(J29-I29)*O29*(1-Q29/100)/12,H29="plan_upgrade",(O29*(_xlfn.XLOOKUP(J29,$M:$M,$P:$P)-_xlfn.XLOOKUP(I29,$M:$M,$P:$P))*(1-Q29/100))/12,H29="plan_downgrade",(O29*(_xlfn.XLOOKUP(J29,$M:$M,$P:$P)-_xlfn.XLOOKUP(I29,$M:$M,$P:$P))*(1-Q29/100))/12,H29="discount_added",-(O29*P29*(J29-I29)/100)/12))} -> 1650 | T29: =IF(H29<>"created",0,IF(COUNTIFS($C$1:C28,$C29,$H$1:H28,"created")=0,1,0)) -> 1 | U29: =IF(H29<>"cancelled",0,IF(COUNTIFS($C$2:$C$98,$C29,$H$2:$H$98,"created",$F$2:$F$98,"<="&F29)-COUNTIFS($C$2:$C$98,$C29,$H$2:$H$98,"cancelled",$F$2:$F$98,"<="&F29)=0,1,0)) -> 0 | V29: =IF(AND(H29="created",T29=0,COUNTIFS($C$2:$C$98,$C29,$H$2:$H$98,"cancelled",$F$2:$F$98,"<"&F29)>0,COUNTIFS($C$2:$C$98,$C29,$H$2:$H$98,"created",$F$2:$F$98,"<"&F29)-COUNTIFS($C$2:$C$98,$C29,$H$2:$H$98,"cancelled",$F$2:$F$98,"<"&F29)=0),1,0) -> 0
A30: EVT029 | B30: SUB043 | C30: CUST006 | D30: Northern Retail Solutions | E30: Western Canada | F30: 45566 | G30: 45570 | H30: created | M30: Marketing Pro | N30: Monthly | O30: 33 | P30: 85 | Q30: 0 | R30: {=_xlfn.IFS(H30="created", "New", H30="cancelled", "Churned", AND(H30="seats_change", J30 > I30), "Expansion", AND(H30="seats_change", J30 < I30), "Contraction", AND(H30="price_change", J30 > I30), "Expansion", AND(H30="price_change", J30 < I30), "Contraction", H30="plan_upgrade", "Expansion", H30="plan_downgrade", "Contraction", H30="discount_added", "Contraction")} -> New | S30: {=IF(N30="Monthly",_xlfn.IFS(H30="created",O30*P30*(1-Q30/100),H30="cancelled",-(O30*P30*(1-Q30/100)),H30="seats_change",(J30-I30)*P30*(1-Q30/100),H30="price_change",(J30-I30)*O30*(1-Q30/100),H30="discount_added",-(O30*P30*(J30-I30)/100),H30="plan_upgrade",O30*(_xlfn.XLOOKUP(J30,$M:$M,$P:$P)-_xlfn.XLOOKUP(I30,$M:$M,$P:$P))*(1-Q30/100),H30="plan_downgrade",O30*(_xlfn.XLOOKUP(J30,$M:$M,$P:$P)-_xlfn.XLOOKUP(I30,$M:$M,$P:$P))*(1-Q30/100)),_xlfn.IFS(H30="created",O30*P30*(1-Q30/100)/12,H30="cancelled",-(O30*P30*(1-Q30/100))/12,H30="seats_change",(J30-I30)*P30*(1-Q30/100)/12,H30="price_change",(J30-I30)*O30*(1-Q30/100)/12,H30="plan_upgrade",(O30*(_xlfn.XLOOKUP(J30,$M:$M,$P:$P)-_xlfn.XLOOKUP(I30,$M:$M,$P:$P))*(1-Q30/100))/12,H30="plan_downgrade",(O30*(_xlfn.XLOOKUP(J30,$M:$M,$P:$P)-_xlfn.XLOOKUP(I30,$M:$M,$P:$P))*(1-Q30/100))/12,H30="discount_added",-(O30*P30*(J30-I30)/100)/12))} -> 2805 | T30: =IF(H30<>"created",0,IF(COUNTIFS($C$1:C29,$C30,$H$1:H29,"created")=0,1,0)) -> 0 | U30: =IF(H30<>"cancelled",0,IF(COUNTIFS($C$2:$C$98,$C30,$H$2:$H$98,"created",$F$2:$F$98,"<="&F30)-COUNTIFS($C$2:$C$98,$C30,$H$2:$H$98,"cancelled",$F$2:$F$98,"<="&F30)=0,1,0)) -> 0 | V30: =IF(AND(H30="created",T30=0,COUNTIFS($C$2:$C$98,$C30,$H$2:$H$98,"cancelled",$F$2:$F$98,"<"&F30)>0,COUNTIFS($C$2:$C$98,$C30,$H$2:$H$98,"created",$F$2:$F$98,"<"&F30)-COUNTIFS($C$2:$C$98,$C30,$H$2:$H$98,"cancelled",$F$2:$F$98,"<"&F30)=0),1,0) -> 0
A31: EVT030 | B31: SUB021 | C31: CUST021 | D31: Calgary Commerce Solutions | E31: Western Canada | F31: 45566 | G31: 45579 | H31: created | M31: Analytics Growth | N31: Monthly | O31: 25 | P31: 95 | Q31: 0 | R31: {=_xlfn.IFS(H31="created", "New", H31="cancelled", "Churned", AND(H31="seats_change", J31 > I31), "Expansion", AND(H31="seats_change", J31 < I31), "Contraction", AND(H31="price_change", J31 > I31), "Expansion", AND(H31="price_change", J31 < I31), "Contraction", H31="plan_upgrade", "Expansion", H31="plan_downgrade", "Contraction", H31="discount_added", "Contraction")} -> New | S31: {=IF(N31="Monthly",_xlfn.IFS(H31="created",O31*P31*(1-Q31/100),H31="cancelled",-(O31*P31*(1-Q31/100)),H31="seats_change",(J31-I31)*P31*(1-Q31/100),H31="price_change",(J31-I31)*O31*(1-Q31/100),H31="discount_added",-(O31*P31*(J31-I31)/100),H31="plan_upgrade",O31*(_xlfn.XLOOKUP(J31,$M:$M,$P:$P)-_xlfn.XLOOKUP(I31,$M:$M,$P:$P))*(1-Q31/100),H31="plan_downgrade",O31*(_xlfn.XLOOKUP(J31,$M:$M,$P:$P)-_xlfn.XLOOKUP(I31,$M:$M,$P:$P))*(1-Q31/100)),_xlfn.IFS(H31="created",O31*P31*(1-Q31/100)/12,H31="cancelled",-(O31*P31*(1-Q31/100))/12,H31="seats_change",(J31-I31)*P31*(1-Q31/100)/12,H31="price_change",(J31-I31)*O31*(1-Q31/100)/12,H31="plan_upgrade",(O31*(_xlfn.XLOOKUP(J31,$M:$M,$P:$P)-_xlfn.XLOOKUP(I31,$M:$M,$P:$P))*(1-Q31/100))/12,H31="plan_downgrade",(O31*(_xlfn.XLOOKUP(J31,$M:$M,$P:$P)-_xlfn.XLOOKUP(I31,$M:$M,$P:$P))*(1-Q31/100))/12,H31="discount_added",-(O31*P31*(J31-I31)/100)/12))} -> 2375 | T31: =IF(H31<>"created",0,IF(COUNTIFS($C$1:C30,$C31,$H$1:H30,"created")=0,1,0)) -> 1 | U31: =IF(H31<>"cancelled",0,IF(COUNTIFS($C$2:$C$98,$C31,$H$2:$H$98,"created",$F$2:$F$98,"<="&F31)-COUNTIFS($C$2:$C$98,$C31,$H$2:$H$98,"cancelled",$F$2:$F$98,"<="&F31)=0,1,0)) -> 0 | V31: =IF(AND(H31="created",T31=0,COUNTIFS($C$2:$C$98,$C31,$H$2:$H$98,"cancelled",$F$2:$F$98,"<"&F31)>0,COUNTIFS($C$2:$C$98,$C31,$H$2:$H$98,"created",$F$2:$F$98,"<"&F31)-COUNTIFS($C$2:$C$98,$C31,$H$2:$H$98,"cancelled",$F$2:$F$98,"<"&F31)=0),1,0) -> 0
A32: EVT031 | B32: SUB022 | C32: CUST022 | D32: Toronto Tech Ventures | E32: Eastern Canada | F32: 45566 | G32: 45593 | H32: created | M32: Platform Suite | N32: Monthly | O32: 33 | P32: 150 | Q32: 0 | R32: {=_xlfn.IFS(H32="created", "New", H32="cancelled", "Churned", AND(H32="seats_change", J32 > I32), "Expansion", AND(H32="seats_change", J32 < I32), "Contraction", AND(H32="price_change", J32 > I32), "Expansion", AND(H32="price_change", J32 < I32), "Contraction", H32="plan_upgrade", "Expansion", H32="plan_downgrade", "Contraction", H32="discount_added", "Contraction")} -> New | S32: {=IF(N32="Monthly",_xlfn.IFS(H32="created",O32*P32*(1-Q32/100),H32="cancelled",-(O32*P32*(1-Q32/100)),H32="seats_change",(J32-I32)*P32*(1-Q32/100),H32="price_change",(J32-I32)*O32*(1-Q32/100),H32="discount_added",-(O32*P32*(J32-I32)/100),H32="plan_upgrade",O32*(_xlfn.XLOOKUP(J32,$M:$M,$P:$P)-_xlfn.XLOOKUP(I32,$M:$M,$P:$P))*(1-Q32/100),H32="plan_downgrade",O32*(_xlfn.XLOOKUP(J32,$M:$M,$P:$P)-_xlfn.XLOOKUP(I32,$M:$M,$P:$P))*(1-Q32/100)),_xlfn.IFS(H32="created",O32*P32*(1-Q32/100)/12,H32="cancelled",-(O32*P32*(1-Q32/100))/12,H32="seats_change",(J32-I32)*P32*(1-Q32/100)/12,H32="price_change",(J32-I32)*O32*(1-Q32/100)/12,H32="plan_upgrade",(O32*(_xlfn.XLOOKUP(J32,$M:$M,$P:$P)-_xlfn.XLOOKUP(I32,$M:$M,$P:$P))*(1-Q32/100))/12,H32="plan_downgrade",(O32*(_xlfn.XLOOKUP(J32,$M:$M,$P:$P)-_xlfn.XLOOKUP(I32,$M:$M,$P:$P))*(1-Q32/100))/12,H32="discount_added",-(O32*P32*(J32-I32)/100)/12))} -> 4950 | T32: =IF(H32<>"created",0,IF(COUNTIFS($C$1:C31,$C32,$H$1:H31,"created")=0,1,0)) -> 1 | U32: =IF(H32<>"cancelled",0,IF(COUNTIFS($C$2:$C$98,$C32,$H$2:$H$98,"created",$F$2:$F$98,"<="&F32)-COUNTIFS($C$2:$C$98,$C32,$H$2:$H$98,"cancelled",$F$2:$F$98,"<="&F32)=0,1,0)) -> 0 | V32: =IF(AND(H32="created",T32=0,COUNTIFS($C$2:$C$98,$C32,$H$2:$H$98,"cancelled",$F$2:$F$98,"<"&F32)>0,COUNTIFS($C$2:$C$98,$C32,$H$2:$H$98,"created",$F$2:$F$98,"<"&F32)-COUNTIFS($C$2:$C$98,$C32,$H$2:$H$98,"cancelled",$F$2:$F$98,"<"&F32)=0),1,0) -> 0
A33: EVT032 | B33: SUB059 | C33: CUST008 | D33: Quantum Education Platform | E33: Eastern Canada | F33: 45597 | G33: 45601 | H33: created | M33: Marketing Pro | N33: Monthly | O33: 22 | P33: 85 | Q33: 0 | R33: {=_xlfn.IFS(H33="created", "New", H33="cancelled", "Churned", AND(H33="seats_change", J33 > I33), "Expansion", AND(H33="seats_change", J33 < I33), "Contraction", AND(H33="price_change", J33 > I33), "Expansion", AND(H33="price_change", J33 < I33), "Contraction", H33="plan_upgrade", "Expansion", H33="plan_downgrade", "Contraction", H33="discount_added", "Contraction")} -> New | S33: {=IF(N33="Monthly",_xlfn.IFS(H33="created",O33*P33*(1-Q33/100),H33="cancelled",-(O33*P33*(1-Q33/100)),H33="seats_change",(J33-I33)*P33*(1-Q33/100),H33="price_change",(J33-I33)*O33*(1-Q33/100),H33="discount_added",-(O33*P33*(J33-I33)/100),H33="plan_upgrade",O33*(_xlfn.XLOOKUP(J33,$M:$M,$P:$P)-_xlfn.XLOOKUP(I33,$M:$M,$P:$P))*(1-Q33/100),H33="plan_downgrade",O33*(_xlfn.XLOOKUP(J33,$M:$M,$P:$P)-_xlfn.XLOOKUP(I33,$M:$M,$P:$P))*(1-Q33/100)),_xlfn.IFS(H33="created",O33*P33*(1-Q33/100)/12,H33="cancelled",-(O33*P33*(1-Q33/100))/12,H33="seats_change",(J33-I33)*P33*(1-Q33/100)/12,H33="price_change",(J33-I33)*O33*(1-Q33/100)/12,H33="plan_upgrade",(O33*(_xlfn.XLOOKUP(J33,$M:$M,$P:$P)-_xlfn.XLOOKUP(I33,$M:$M,$P:$P))*(1-Q33/100))/12,H33="plan_downgrade",(O33*(_xlfn.XLOOKUP(J33,$M:$M,$P:$P)-_xlfn.XLOOKUP(I33,$M:$M,$P:$P))*(1-Q33/100))/12,H33="discount_added",-(O33*P33*(J33-I33)/100)/12))} -> 1870 | T33: =IF(H33<>"created",0,IF(COUNTIFS($C$1:C32,$C33,$H$1:H32,"created")=0,1,0)) -> 0 | U33: =IF(H33<>"cancelled",0,IF(COUNTIFS($C$2:$C$98,$C33,$H$2:$H$98,"created",$F$2:$F$98,"<="&F33)-COUNTIFS($C$2:$C$98,$C33,$H$2:$H$98,"cancelled",$F$2:$F$98,"<="&F33)=0,1,0)) -> 0 | V33: =IF(AND(H33="created",T33=0,COUNTIFS($C$2:$C$98,$C33,$H$2:$H$98,"cancelled",$F$2:$F$98,"<"&F33)>0,COUNTIFS($C$2:$C$98,$C33,$H$2:$H$98,"created",$F$2:$F$98,"<"&F33)-COUNTIFS($C$2:$C$98,$C33,$H$2:$H$98,"cancelled",$F$2:$F$98,"<"&F33)=0),1,0) -> 0
A34: EVT033 | B34: SUB023 | C34: CUST023 | D34: Island Media Productions | E34: Eastern Canada | F34: 45597 | G34: 45607 | H34: created | M34: Analytics Starter | N34: Monthly | O34: 10 | P34: 45 | Q34: 0 | R34: {=_xlfn.IFS(H34="created", "New", H34="cancelled", "Churned", AND(H34="seats_change", J34 > I34), "Expansion", AND(H34="seats_change", J34 < I34), "Contraction", AND(H34="price_change", J34 > I34), "Expansion", AND(H34="price_change", J34 < I34), "Contraction", H34="plan_upgrade", "Expansion", H34="plan_downgrade", "Contraction", H34="discount_added", "Contraction")} -> New | S34: {=IF(N34="Monthly",_xlfn.IFS(H34="created",O34*P34*(1-Q34/100),H34="cancelled",-(O34*P34*(1-Q34/100)),H34="seats_change",(J34-I34)*P34*(1-Q34/100),H34="price_change",(J34-I34)*O34*(1-Q34/100),H34="discount_added",-(O34*P34*(J34-I34)/100),H34="plan_upgrade",O34*(_xlfn.XLOOKUP(J34,$M:$M,$P:$P)-_xlfn.XLOOKUP(I34,$M:$M,$P:$P))*(1-Q34/100),H34="plan_downgrade",O34*(_xlfn.XLOOKUP(J34,$M:$M,$P:$P)-_xlfn.XLOOKUP(I34,$M:$M,$P:$P))*(1-Q34/100)),_xlfn.IFS(H34="created",O34*P34*(1-Q34/100)/12,H34="cancelled",-(O34*P34*(1-Q34/100))/12,H34="seats_change",(J34-I34)*P34*(1-Q34/100)/12,H34="price_change",(J34-I34)*O34*(1-Q34/100)/12,H34="plan_upgrade",(O34*(_xlfn.XLOOKUP(J34,$M:$M,$P:$P)-_xlfn.XLOOKUP(I34,$M:$M,$P:$P))*(1-Q34/100))/12,H34="plan_downgrade",(O34*(_xlfn.XLOOKUP(J34,$M:$M,$P:$P)-_xlfn.XLOOKUP(I34,$M:$M,$P:$P))*(1-Q34/100))/12,H34="discount_added",-(O34*P34*(J34-I34)/100)/12))} -> 450 | T34: =IF(H34<>"created",0,IF(COUNTIFS($C$1:C33,$C34,$H$1:H33,"created")=0,1,0)) -> 1 | U34: =IF(H34<>"cancelled",0,IF(COUNTIFS($C$2:$C$98,$C34,$H$2:$H$98,"created",$F$2:$F$98,"<="&F34)-COUNTIFS($C$2:$C$98,$C34,$H$2:$H$98,"cancelled",$F$2:$F$98,"<="&F34)=0,1,0)) -> 0 | V34: =IF(AND(H34="created",T34=0,COUNTIFS($C$2:$C$98,$C34,$H$2:$H$98,"cancelled",$F$2:$F$98,"<"&F34)>0,COUNTIFS($C$2:$C$98,$C34,$H$2:$H$98,"created",$F$2:$F$98,"<"&F34)-COUNTIFS($C$2:$C$98,$C34,$H$2:$H$98,"cancelled",$F$2:$F$98,"<"&F34)=0),1,0) -> 0
A35: EVT034 | B35: SUB005 | C35: CUST005 | D35: Atlantic Media Corp | E35: Eastern Canada | F35: 45597 | G35: 45616 | H35: cancelled | I35: active | J35: churned | K35: status | L35: Price too high | M35: Analytics Starter | N35: Monthly | O35: 11 | P35: 45 | Q35: 0 | R35: {=_xlfn.IFS(H35="created", "New", H35="cancelled", "Churned", AND(H35="seats_change", J35 > I35), "Expansion", AND(H35="seats_change", J35 < I35), "Contraction", AND(H35="price_change", J35 > I35), "Expansion", AND(H35="price_change", J35 < I35), "Contraction", H35="plan_upgrade", "Expansion", H35="plan_downgrade", "Contraction", H35="discount_added", "Contraction")} -> Churned | S35: {=IF(N35="Monthly",_xlfn.IFS(H35="created",O35*P35*(1-Q35/100),H35="cancelled",-(O35*P35*(1-Q35/100)),H35="seats_change",(J35-I35)*P35*(1-Q35/100),H35="price_change",(J35-I35)*O35*(1-Q35/100),H35="discount_added",-(O35*P35*(J35-I35)/100),H35="plan_upgrade",O35*(_xlfn.XLOOKUP(J35,$M:$M,$P:$P)-_xlfn.XLOOKUP(I35,$M:$M,$P:$P))*(1-Q35/100),H35="plan_downgrade",O35*(_xlfn.XLOOKUP(J35,$M:$M,$P:$P)-_xlfn.XLOOKUP(I35,$M:$M,$P:$P))*(1-Q35/100)),_xlfn.IFS(H35="created",O35*P35*(1-Q35/100)/12,H35="cancelled",-(O35*P35*(1-Q35/100))/12,H35="seats_change",(J35-I35)*P35*(1-Q35/100)/12,H35="price_change",(J35-I35)*O35*(1-Q35/100)/12,H35="plan_upgrade",(O35*(_xlfn.XLOOKUP(J35,$M:$M,$P:$P)-_xlfn.XLOOKUP(I35,$M:$M,$P:$P))*(1-Q35/100))/12,H35="plan_downgrade",(O35*(_xlfn.XLOOKUP(J35,$M:$M,$P:$P)-_xlfn.XLOOKUP(I35,$M:$M,$P:$P))*(1-Q35/100))/12,H35="discount_added",-(O35*P35*(J35-I35)/100)/12))} -> -495 | T35: =IF(H35<>"created",0,IF(COUNTIFS($C$1:C34,$C35,$H$1:H34,"created")=0,1,0)) -> 0 | U35: =IF(H35<>"cancelled",0,IF(COUNTIFS($C$2:$C$98,$C35,$H$2:$H$98,"created",$F$2:$F$98,"<="&F35)-COUNTIFS($C$2:$C$98,$C35,$H$2:$H$98,"cancelled",$F$2:$F$98,"<="&F35)=0,1,0)) -> 1 | V35: =IF(AND(H35="created",T35=0,COUNTIFS($C$2:$C$98,$C35,$H$2:$H$98,"cancelled",$F$2:$F$98,"<"&F35)>0,COUNTIFS($C$2:$C$98,$C35,$H$2:$H$98,"created",$F$2:$F$98,"<"&F35)-COUNTIFS($C$2:$C$98,$C35,$H$2:$H$98,"cancelled",$F$2:$F$98,"<"&F35)=0),1,0) -> 0
A36: EVT035 | B36: SUB024 | C36: CUST024 | D36: Western Retail Group | E36: Western Canada | F36: 45597 | G36: 45621 | H36: created | M36: Marketing Pro | N36: Monthly | O36: 31 | P36: 85 | Q36: 0 | R36: {=_xlfn.IFS(H36="created", "New", H36="cancelled", "Churned", AND(H36="seats_change", J36 > I36), "Expansion", AND(H36="seats_change", J36 < I36), "Contraction", AND(H36="price_change", J36 > I36), "Expansion", AND(H36="price_change", J36 < I36), "Contraction", H36="plan_upgrade", "Expansion", H36="plan_downgrade", "Contraction", H36="discount_added", "Contraction")} -> New | S36: {=IF(N36="Monthly",_xlfn.IFS(H36="created",O36*P36*(1-Q36/100),H36="cancelled",-(O36*P36*(1-Q36/100)),H36="seats_change",(J36-I36)*P36*(1-Q36/100),H36="price_change",(J36-I36)*O36*(1-Q36/100),H36="discount_added",-(O36*P36*(J36-I36)/100),H36="plan_upgrade",O36*(_xlfn.XLOOKUP(J36,$M:$M,$P:$P)-_xlfn.XLOOKUP(I36,$M:$M,$P:$P))*(1-Q36/100),H36="plan_downgrade",O36*(_xlfn.XLOOKUP(J36,$M:$M,$P:$P)-_xlfn.XLOOKUP(I36,$M:$M,$P:$P))*(1-Q36/100)),_xlfn.IFS(H36="created",O36*P36*(1-Q36/100)/12,H36="cancelled",-(O36*P36*(1-Q36/100))/12,H36="seats_change",(J36-I36)*P36*(1-Q36/100)/12,H36="price_change",(J36-I36)*O36*(1-Q36/100)/12,H36="plan_upgrade",(O36*(_xlfn.XLOOKUP(J36,$M:$M,$P:$P)-_xlfn.XLOOKUP(I36,$M:$M,$P:$P))*(1-Q36/100))/12,H36="plan_downgrade",(O36*(_xlfn.XLOOKUP(J36,$M:$M,$P:$P)-_xlfn.XLOOKUP(I36,$M:$M,$P:$P))*(1-Q36/100))/12,H36="discount_added",-(O36*P36*(J36-I36)/100)/12))} -> 2635 | T36: =IF(H36<>"created",0,IF(COUNTIFS($C$1:C35,$C36,$H$1:H35,"created")=0,1,0)) -> 1 | U36: =IF(H36<>"cancelled",0,IF(COUNTIFS($C$2:$C$98,$C36,$H$2:$H$98,"created",$F$2:$F$98,"<="&F36)-COUNTIFS($C$2:$C$98,$C36,$H$2:$H$98,"cancelled",$F$2:$F$98,"<="&F36)=0,1,0)) -> 0 | V36: =IF(AND(H36="created",T36=0,COUNTIFS($C$2:$C$98,$C36,$H$2:$H$98,"cancelled",$F$2:$F$98,"<"&F36)>0,COUNTIFS($C$2:$C$98,$C36,$H$2:$H$98,"created",$F$2:$F$98,"<"&F36)-COUNTIFS($C$2:$C$98,$C36,$H$2:$H$98,"cancelled",$F$2:$F$98,"<"&F36)=0),1,0) -> 0
A37: EVT036 | B37: SUB025 | C37: CUST025 | D37: Montreal Manufacturing Pro | E37: Eastern Canada | F37: 45627 | G37: 45635 | H37: created | M37: Analytics Enterprise | N37: Annual | O37: 38 | P37: 2160 | Q37: 0 | R37: {=_xlfn.IFS(H37="created", "New", H37="cancelled", "Churned", AND(H37="seats_change", J37 > I37), "Expansion", AND(H37="seats_change", J37 < I37), "Contraction", AND(H37="price_change", J37 > I37), "Expansion", AND(H37="price_change", J37 < I37), "Contraction", H37="plan_upgrade", "Expansion", H37="plan_downgrade", "Contraction", H37="discount_added", "Contraction")} -> New | S37: {=IF(N37="Monthly",_xlfn.IFS(H37="created",O37*P37*(1-Q37/100),H37="cancelled",-(O37*P37*(1-Q37/100)),H37="seats_change",(J37-I37)*P37*(1-Q37/100),H37="price_change",(J37-I37)*O37*(1-Q37/100),H37="discount_added",-(O37*P37*(J37-I37)/100),H37="plan_upgrade",O37*(_xlfn.XLOOKUP(J37,$M:$M,$P:$P)-_xlfn.XLOOKUP(I37,$M:$M,$P:$P))*(1-Q37/100),H37="plan_downgrade",O37*(_xlfn.XLOOKUP(J37,$M:$M,$P:$P)-_xlfn.XLOOKUP(I37,$M:$M,$P:$P))*(1-Q37/100)),_xlfn.IFS(H37="created",O37*P37*(1-Q37/100)/12,H37="cancelled",-(O37*P37*(1-Q37/100))/12,H37="seats_change",(J37-I37)*P37*(1-Q37/100)/12,H37="price_change",(J37-I37)*O37*(1-Q37/100)/12,H37="plan_upgrade",(O37*(_xlfn.XLOOKUP(J37,$M:$M,$P:$P)-_xlfn.XLOOKUP(I37,$M:$M,$P:$P))*(1-Q37/100))/12,H37="plan_downgrade",(O37*(_xlfn.XLOOKUP(J37,$M:$M,$P:$P)-_xlfn.XLOOKUP(I37,$M:$M,$P:$P))*(1-Q37/100))/12,H37="discount_added",-(O37*P37*(J37-I37)/100)/12))} -> 6840 | T37: =IF(H37<>"created",0,IF(COUNTIFS($C$1:C36,$C37,$H$1:H36,"created")=0,1,0)) -> 1 | U37: =IF(H37<>"cancelled",0,IF(COUNTIFS($C$2:$C$98,$C37,$H$2:$H$98,"created",$F$2:$F$98,"<="&F37)-COUNTIFS($C$2:$C$98,$C37,$H$2:$H$98,"cancelled",$F$2:$F$98,"<="&F37)=0,1,0)) -> 0 | V37: =IF(AND(H37="created",T37=0,COUNTIFS($C$2:$C$98,$C37,$H$2:$H$98,"cancelled",$F$2:$F$98,"<"&F37)>0,COUNTIFS($C$2:$C$98,$C37,$H$2:$H$98,"created",$F$2:$F$98,"<"&F37)-COUNTIFS($C$2:$C$98,$C37,$H$2:$H$98,"cancelled",$F$2:$F$98,"<"&F37)=0),1,0) -> 0
A38: EVT037 | B38: SUB056 | C38: CUST016 | D38: Quebec Manufacturing | E38: Eastern Canada | F38: 45627 | G38: 45638 | H38: created | M38: Marketing Pro | N38: Monthly | O38: 38 | P38: 85 | Q38: 0 | R38: {=_xlfn.IFS(H38="created", "New", H38="cancelled", "Churned", AND(H38="seats_change", J38 > I38), "Expansion", AND(H38="seats_change", J38 < I38), "Contraction", AND(H38="price_change", J38 > I38), "Expansion", AND(H38="price_change", J38 < I38), "Contraction", H38="plan_upgrade", "Expansion", H38="plan_downgrade", "Contraction", H38="discount_added", "Contraction")} -> New | S38: {=IF(N38="Monthly",_xlfn.IFS(H38="created",O38*P38*(1-Q38/100),H38="cancelled",-(O38*P38*(1-Q38/100)),H38="seats_change",(J38-I38)*P38*(1-Q38/100),H38="price_change",(J38-I38)*O38*(1-Q38/100),H38="discount_added",-(O38*P38*(J38-I38)/100),H38="plan_upgrade",O38*(_xlfn.XLOOKUP(J38,$M:$M,$P:$P)-_xlfn.XLOOKUP(I38,$M:$M,$P:$P))*(1-Q38/100),H38="plan_downgrade",O38*(_xlfn.XLOOKUP(J38,$M:$M,$P:$P)-_xlfn.XLOOKUP(I38,$M:$M,$P:$P))*(1-Q38/100)),_xlfn.IFS(H38="created",O38*P38*(1-Q38/100)/12,H38="cancelled",-(O38*P38*(1-Q38/100))/12,H38="seats_change",(J38-I38)*P38*(1-Q38/100)/12,H38="price_change",(J38-I38)*O38*(1-Q38/100)/12,H38="plan_upgrade",(O38*(_xlfn.XLOOKUP(J38,$M:$M,$P:$P)-_xlfn.XLOOKUP(I38,$M:$M,$P:$P))*(1-Q38/100))/12,H38="plan_downgrade",(O38*(_xlfn.XLOOKUP(J38,$M:$M,$P:$P)-_xlfn.XLOOKUP(I38,$M:$M,$P:$P))*(1-Q38/100))/12,H38="discount_added",-(O38*P38*(J38-I38)/100)/12))} -> 3230 | T38: =IF(H38<>"created",0,IF(COUNTIFS($C$1:C37,$C38,$H$1:H37,"created")=0,1,0)) -> 0 | U38: =IF(H38<>"cancelled",0,IF(COUNTIFS($C$2:$C$98,$C38,$H$2:$H$98,"created",$F$2:$F$98,"<="&F38)-COUNTIFS($C$2:$C$98,$C38,$H$2:$H$98,"cancelled",$F$2:$F$98,"<="&F38)=0,1,0)) -> 0 | V38: =IF(AND(H38="created",T38=0,COUNTIFS($C$2:$C$98,$C38,$H$2:$H$98,"cancelled",$F$2:$F$98,"<"&F38)>0,COUNTIFS($C$2:$C$98,$C38,$H$2:$H$98,"created",$F$2:$F$98,"<"&F38)-COUNTIFS($C$2:$C$98,$C38,$H$2:$H$98,"cancelled",$F$2:$F$98,"<"&F38)=0),1,0) -> 0
A39: EVT038 | B39: SUB044 | C39: CUST009 | D39: West Coast Logistics | E39: Western Canada | F39: 45627 | G39: 45646 | H39: created | M39: Analytics Growth | N39: Monthly | O39: 35 | P39: 95 | Q39: 0 | R39: {=_xlfn.IFS(H39="created", "New", H39="cancelled", "Churned", AND(H39="seats_change", J39 > I39), "Expansion", AND(H39="seats_change", J39 < I39), "Contraction", AND(H39="price_change", J39 > I39), "Expansion", AND(H39="price_change", J39 < I39), "Contraction", H39="plan_upgrade", "Expansion", H39="plan_downgrade", "Contraction", H39="discount_added", "Contraction")} -> New | S39: {=IF(N39="Monthly",_xlfn.IFS(H39="created",O39*P39*(1-Q39/100),H39="cancelled",-(O39*P39*(1-Q39/100)),H39="seats_change",(J39-I39)*P39*(1-Q39/100),H39="price_change",(J39-I39)*O39*(1-Q39/100),H39="discount_added",-(O39*P39*(J39-I39)/100),H39="plan_upgrade",O39*(_xlfn.XLOOKUP(J39,$M:$M,$P:$P)-_xlfn.XLOOKUP(I39,$M:$M,$P:$P))*(1-Q39/100),H39="plan_downgrade",O39*(_xlfn.XLOOKUP(J39,$M:$M,$P:$P)-_xlfn.XLOOKUP(I39,$M:$M,$P:$P))*(1-Q39/100)),_xlfn.IFS(H39="created",O39*P39*(1-Q39/100)/12,H39="cancelled",-(O39*P39*(1-Q39/100))/12,H39="seats_change",(J39-I39)*P39*(1-Q39/100)/12,H39="price_change",(J39-I39)*O39*(1-Q39/100)/12,H39="plan_upgrade",(O39*(_xlfn.XLOOKUP(J39,$M:$M,$P:$P)-_xlfn.XLOOKUP(I39,$M:$M,$P:$P))*(1-Q39/100))/12,H39="plan_downgrade",(O39*(_xlfn.XLOOKUP(J39,$M:$M,$P:$P)-_xlfn.XLOOKUP(I39,$M:$M,$P:$P))*(1-Q39/100))/12,H39="discount_added",-(O39*P39*(J39-I39)/100)/12))} -> 3325 | T39: =IF(H39<>"created",0,IF(COUNTIFS($C$1:C38,$C39,$H$1:H38,"created")=0,1,0)) -> 0 | U39: =IF(H39<>"cancelled",0,IF(COUNTIFS($C$2:$C$98,$C39,$H$2:$H$98,"created",$F$2:$F$98,"<="&F39)-COUNTIFS($C$2:$C$98,$C39,$H$2:$H$98,"cancelled",$F$2:$F$98,"<="&F39)=0,1,0)) -> 0 | V39: =IF(AND(H39="created",T39=0,COUNTIFS($C$2:$C$98,$C39,$H$2:$H$98,"cancelled",$F$2:$F$98,"<"&F39)>0,COUNTIFS($C$2:$C$98,$C39,$H$2:$H$98,"created",$F$2:$F$98,"<"&F39)-COUNTIFS($C$2:$C$98,$C39,$H$2:$H$98,"cancelled",$F$2:$F$98,"<"&F39)=0),1,0) -> 0
A40: EVT039 | B40: SUB008 | C40: CUST008 | D40: Quantum Education Platform | E40: Eastern Canada | F40: 45627 | G40: 45648 | H40: cancelled | I40: active | J40: churned | K40: status | L40: Price too high | M40: Analytics Growth | N40: Monthly | O40: 22 | P40: 95 | Q40: 0 | R40: {=_xlfn.IFS(H40="created", "New", H40="cancelled", "Churned", AND(H40="seats_change", J40 > I40), "Expansion", AND(H40="seats_change", J40 < I40), "Contraction", AND(H40="price_change", J40 > I40), "Expansion", AND(H40="price_change", J40 < I40), "Contraction", H40="plan_upgrade", "Expansion", H40="plan_downgrade", "Contraction", H40="discount_added", "Contraction")} -> Churned | S40: {=IF(N40="Monthly",_xlfn.IFS(H40="created",O40*P40*(1-Q40/100),H40="cancelled",-(O40*P40*(1-Q40/100)),H40="seats_change",(J40-I40)*P40*(1-Q40/100),H40="price_change",(J40-I40)*O40*(1-Q40/100),H40="discount_added",-(O40*P40*(J40-I40)/100),H40="plan_upgrade",O40*(_xlfn.XLOOKUP(J40,$M:$M,$P:$P)-_xlfn.XLOOKUP(I40,$M:$M,$P:$P))*(1-Q40/100),H40="plan_downgrade",O40*(_xlfn.XLOOKUP(J40,$M:$M,$P:$P)-_xlfn.XLOOKUP(I40,$M:$M,$P:$P))*(1-Q40/100)),_xlfn.IFS(H40="created",O40*P40*(1-Q40/100)/12,H40="cancelled",-(O40*P40*(1-Q40/100))/12,H40="seats_change",(J40-I40)*P40*(1-Q40/100)/12,H40="price_change",(J40-I40)*O40*(1-Q40/100)/12,H40="plan_upgrade",(O40*(_xlfn.XLOOKUP(J40,$M:$M,$P:$P)-_xlfn.XLOOKUP(I40,$M:$M,$P:$P))*(1-Q40/100))/12,H40="plan_downgrade",(O40*(_xlfn.XLOOKUP(J40,$M:$M,$P:$P)-_xlfn.XLOOKUP(I40,$M:$M,$P:$P))*(1-Q40/100))/12,H40="discount_added",-(O40*P40*(J40-I40)/100)/12))} -> -2090 | T40: =IF(H40<>"created",0,IF(COUNTIFS($C$1:C39,$C40,$H$1:H39,"created")=0,1,0)) -> 0 | U40: =IF(H40<>"cancelled",0,IF(COUNTIFS($C$2:$C$98,$C40,$H$2:$H$98,"created",$F$2:$F$98,"<="&F40)-COUNTIFS($C$2:$C$98,$C40,$H$2:$H$98,"cancelled",$F$2:$F$98,"<="&F40)=0,1,0)) -> 0 | V40: =IF(AND(H40="created",T40=0,COUNTIFS($C$2:$C$98,$C40,$H$2:$H$98,"cancelled",$F$2:$F$98,"<"&F40)>0,COUNTIFS($C$2:$C$98,$C40,$H$2:$H$98,"created",$F$2:$F$98,"<"&F40)-COUNTIFS($C$2:$C$98,$C40,$H$2:$H$98,"cancelled",$F$2:$F$98,"<"&F40)=0),1,0) -> 0
A41: EVT040 | B41: SUB026 | C41: CUST026 | D41: Ontario Education Connect | E41: Eastern Canada | F41: 45627 | G41: 45649 | H41: created | M41: Analytics Growth | N41: Monthly | O41: 16 | P41: 95 | Q41: 0 | R41: {=_xlfn.IFS(H41="created", "New", H41="cancelled", "Churned", AND(H41="seats_change", J41 > I41), "Expansion", AND(H41="seats_change", J41 < I41), "Contraction", AND(H41="price_change", J41 > I41), "Expansion", AND(H41="price_change", J41 < I41), "Contraction", H41="plan_upgrade", "Expansion", H41="plan_downgrade", "Contraction", H41="discount_added", "Contraction")} -> New | S41: {=IF(N41="Monthly",_xlfn.IFS(H41="created",O41*P41*(1-Q41/100),H41="cancelled",-(O41*P41*(1-Q41/100)),H41="seats_change",(J41-I41)*P41*(1-Q41/100),H41="price_change",(J41-I41)*O41*(1-Q41/100),H41="discount_added",-(O41*P41*(J41-I41)/100),H41="plan_upgrade",O41*(_xlfn.XLOOKUP(J41,$M:$M,$P:$P)-_xlfn.XLOOKUP(I41,$M:$M,$P:$P))*(1-Q41/100),H41="plan_downgrade",O41*(_xlfn.XLOOKUP(J41,$M:$M,$P:$P)-_xlfn.XLOOKUP(I41,$M:$M,$P:$P))*(1-Q41/100)),_xlfn.IFS(H41="created",O41*P41*(1-Q41/100)/12,H41="cancelled",-(O41*P41*(1-Q41/100))/12,H41="seats_change",(J41-I41)*P41*(1-Q41/100)/12,H41="price_change",(J41-I41)*O41*(1-Q41/100)/12,H41="plan_upgrade",(O41*(_xlfn.XLOOKUP(J41,$M:$M,$P:$P)-_xlfn.XLOOKUP(I41,$M:$M,$P:$P))*(1-Q41/100))/12,H41="plan_downgrade",(O41*(_xlfn.XLOOKUP(J41,$M:$M,$P:$P)-_xlfn.XLOOKUP(I41,$M:$M,$P:$P))*(1-Q41/100))/12,H41="discount_added",-(O41*P41*(J41-I41)/100)/12))} -> 1520 | T41: =IF(H41<>"created",0,IF(COUNTIFS($C$1:C40,$C41,$H$1:H40,"created")=0,1,0)) -> 1 | U41: =IF(H41<>"cancelled",0,IF(COUNTIFS($C$2:$C$98,$C41,$H$2:$H$98,"created",$F$2:$F$98,"<="&F41)-COUNTIFS($C$2:$C$98,$C41,$H$2:$H$98,"cancelled",$F$2:$F$98,"<="&F41)=0,1,0)) -> 0 | V41: =IF(AND(H41="created",T41=0,COUNTIFS($C$2:$C$98,$C41,$H$2:$H$98,"cancelled",$F$2:$F$98,"<"&F41)>0,COUNTIFS($C$2:$C$98,$C41,$H$2:$H$98,"created",$F$2:$F$98,"<"&F41)-COUNTIFS($C$2:$C$98,$C41,$H$2:$H$98,"cancelled",$F$2:$F$98,"<"&F41)=0),1,0) -> 0
A42: EVT041 | B42: SUB027 | C42: CUST027 | D42: Pacific Finance Corp | E42: Western Canada | F42: 45658 | G42: 45663 | H42: created | M42: Sales Hub | N42: Monthly | O42: 28 | P42: 110 | Q42: 0 | R42: {=_xlfn.IFS(H42="created", "New", H42="cancelled", "Churned", AND(H42="seats_change", J42 > I42), "Expansion", AND(H42="seats_change", J42 < I42), "Contraction", AND(H42="price_change", J42 > I42), "Expansion", AND(H42="price_change", J42 < I42), "Contraction", H42="plan_upgrade", "Expansion", H42="plan_downgrade", "Contraction", H42="discount_added", "Contraction")} -> New | S42: {=IF(N42="Monthly",_xlfn.IFS(H42="created",O42*P42*(1-Q42/100),H42="cancelled",-(O42*P42*(1-Q42/100)),H42="seats_change",(J42-I42)*P42*(1-Q42/100),H42="price_change",(J42-I42)*O42*(1-Q42/100),H42="discount_added",-(O42*P42*(J42-I42)/100),H42="plan_upgrade",O42*(_xlfn.XLOOKUP(J42,$M:$M,$P:$P)-_xlfn.XLOOKUP(I42,$M:$M,$P:$P))*(1-Q42/100),H42="plan_downgrade",O42*(_xlfn.XLOOKUP(J42,$M:$M,$P:$P)-_xlfn.XLOOKUP(I42,$M:$M,$P:$P))*(1-Q42/100)),_xlfn.IFS(H42="created",O42*P42*(1-Q42/100)/12,H42="cancelled",-(O42*P42*(1-Q42/100))/12,H42="seats_change",(J42-I42)*P42*(1-Q42/100)/12,H42="price_change",(J42-I42)*O42*(1-Q42/100)/12,H42="plan_upgrade",(O42*(_xlfn.XLOOKUP(J42,$M:$M,$P:$P)-_xlfn.XLOOKUP(I42,$M:$M,$P:$P))*(1-Q42/100))/12,H42="plan_downgrade",(O42*(_xlfn.XLOOKUP(J42,$M:$M,$P:$P)-_xlfn.XLOOKUP(I42,$M:$M,$P:$P))*(1-Q42/100))/12,H42="discount_added",-(O42*P42*(J42-I42)/100)/12))} -> 3080 | T42: =IF(H42<>"created",0,IF(COUNTIFS($C$1:C41,$C42,$H$1:H41,"created")=0,1,0)) -> 1 | U42: =IF(H42<>"cancelled",0,IF(COUNTIFS($C$2:$C$98,$C42,$H$2:$H$98,"created",$F$2:$F$98,"<="&F42)-COUNTIFS($C$2:$C$98,$C42,$H$2:$H$98,"cancelled",$F$2:$F$98,"<="&F42)=0,1,0)) -> 0 | V42: =IF(AND(H42="created",T42=0,COUNTIFS($C$2:$C$98,$C42,$H$2:$H$98,"cancelled",$F$2:$F$98,"<"&F42)>0,COUNTIFS($C$2:$C$98,$C42,$H$2:$H$98,"created",$F$2:$F$98,"<"&F42)-COUNTIFS($C$2:$C$98,$C42,$H$2:$H$98,"cancelled",$F$2:$F$98,"<"&F42)=0),1,0) -> 0
A43: EVT042 | B43: SUB014 | C43: CUST014 | D43: Toronto Media Group | E43: Eastern Canada | F43: 45658 | G43: 45665 | H43: price_change | I43: 80 | J43: 85 | K43: price_per_seat | L43: Annual price increase applied at renewal | M43: Marketing Pro | N43: Monthly | O43: 28 | P43: 85 | Q43: 0 | R43: {=_xlfn.IFS(H43="created", "New", H43="cancelled", "Churned", AND(H43="seats_change", J43 > I43), "Expansion", AND(H43="seats_change", J43 < I43), "Contraction", AND(H43="price_change", J43 > I43), "Expansion", AND(H43="price_change", J43 < I43), "Contraction", H43="plan_upgrade", "Expansion", H43="plan_downgrade", "Contraction", H43="discount_added", "Contraction")} -> Expansion | S43: {=IF(N43="Monthly",_xlfn.IFS(H43="created",O43*P43*(1-Q43/100),H43="cancelled",-(O43*P43*(1-Q43/100)),H43="seats_change",(J43-I43)*P43*(1-Q43/100),H43="price_change",(J43-I43)*O43*(1-Q43/100),H43="discount_added",-(O43*P43*(J43-I43)/100),H43="plan_upgrade",O43*(_xlfn.XLOOKUP(J43,$M:$M,$P:$P)-_xlfn.XLOOKUP(I43,$M:$M,$P:$P))*(1-Q43/100),H43="plan_downgrade",O43*(_xlfn.XLOOKUP(J43,$M:$M,$P:$P)-_xlfn.XLOOKUP(I43,$M:$M,$P:$P))*(1-Q43/100)),_xlfn.IFS(H43="created",O43*P43*(1-Q43/100)/12,H43="cancelled",-(O43*P43*(1-Q43/100))/12,H43="seats_change",(J43-I43)*P43*(1-Q43/100)/12,H43="price_change",(J43-I43)*O43*(1-Q43/100)/12,H43="plan_upgrade",(O43*(_xlfn.XLOOKUP(J43,$M:$M,$P:$P)-_xlfn.XLOOKUP(I43,$M:$M,$P:$P))*(1-Q43/100))/12,H43="plan_downgrade",(O43*(_xlfn.XLOOKUP(J43,$M:$M,$P:$P)-_xlfn.XLOOKUP(I43,$M:$M,$P:$P))*(1-Q43/100))/12,H43="discount_added",-(O43*P43*(J43-I43)/100)/12))} -> 140 | T43: =IF(H43<>"created",0,IF(COUNTIFS($C$1:C42,$C43,$H$1:H42,"created")=0,1,0)) -> 0 | U43: =IF(H43<>"cancelled",0,IF(COUNTIFS($C$2:$C$98,$C43,$H$2:$H$98,"created",$F$2:$F$98,"<="&F43)-COUNTIFS($C$2:$C$98,$C43,$H$2:$H$98,"cancelled",$F$2:$F$98,"<="&F43)=0,1,0)) -> 0 | V43: =IF(AND(H43="created",T43=0,COUNTIFS($C$2:$C$98,$C43,$H$2:$H$98,"cancelled",$F$2:$F$98,"<"&F43)>0,COUNTIFS($C$2:$C$98,$C43,$H$2:$H$98,"created",$F$2:$F$98,"<"&F43)-COUNTIFS($C$2:$C$98,$C43,$H$2:$H$98,"cancelled",$F$2:$F$98,"<"&F43)=0),1,0) -> 0
A44: EVT043 | B44: SUB013 | C44: CUST013 | D44: Alberta Tech Innovators | E44: Western Canada | F44: 45658 | G44: 45672 | H44: cancelled | I44: active | J44: churned | K44: status | L44: Switched to competitor | M44: Analytics Starter | N44: Monthly | O44: 10 | P44: 45 | Q44: 0 | R44: {=_xlfn.IFS(H44="created", "New", H44="cancelled", "Churned", AND(H44="seats_change", J44 > I44), "Expansion", AND(H44="seats_change", J44 < I44), "Contraction", AND(H44="price_change", J44 > I44), "Expansion", AND(H44="price_change", J44 < I44), "Contraction", H44="plan_upgrade", "Expansion", H44="plan_downgrade", "Contraction", H44="discount_added", "Contraction")} -> Churned | S44: {=IF(N44="Monthly",_xlfn.IFS(H44="created",O44*P44*(1-Q44/100),H44="cancelled",-(O44*P44*(1-Q44/100)),H44="seats_change",(J44-I44)*P44*(1-Q44/100),H44="price_change",(J44-I44)*O44*(1-Q44/100),H44="discount_added",-(O44*P44*(J44-I44)/100),H44="plan_upgrade",O44*(_xlfn.XLOOKUP(J44,$M:$M,$P:$P)-_xlfn.XLOOKUP(I44,$M:$M,$P:$P))*(1-Q44/100),H44="plan_downgrade",O44*(_xlfn.XLOOKUP(J44,$M:$M,$P:$P)-_xlfn.XLOOKUP(I44,$M:$M,$P:$P))*(1-Q44/100)),_xlfn.IFS(H44="created",O44*P44*(1-Q44/100)/12,H44="cancelled",-(O44*P44*(1-Q44/100))/12,H44="seats_change",(J44-I44)*P44*(1-Q44/100)/12,H44="price_change",(J44-I44)*O44*(1-Q44/100)/12,H44="plan_upgrade",(O44*(_xlfn.XLOOKUP(J44,$M:$M,$P:$P)-_xlfn.XLOOKUP(I44,$M:$M,$P:$P))*(1-Q44/100))/12,H44="plan_downgrade",(O44*(_xlfn.XLOOKUP(J44,$M:$M,$P:$P)-_xlfn.XLOOKUP(I44,$M:$M,$P:$P))*(1-Q44/100))/12,H44="discount_added",-(O44*P44*(J44-I44)/100)/12))} -> -450 | T44: =IF(H44<>"created",0,IF(COUNTIFS($C$1:C43,$C44,$H$1:H43,"created")=0,1,0)) -> 0 | U44: =IF(H44<>"cancelled",0,IF(COUNTIFS($C$2:$C$98,$C44,$H$2:$H$98,"created",$F$2:$F$98,"<="&F44)-COUNTIFS($C$2:$C$98,$C44,$H$2:$H$98,"cancelled",$F$2:$F$98,"<="&F44)=0,1,0)) -> 1 | V44: =IF(AND(H44="created",T44=0,COUNTIFS($C$2:$C$98,$C44,$H$2:$H$98,"cancelled",$F$2:$F$98,"<"&F44)>0,COUNTIFS($C$2:$C$98,$C44,$H$2:$H$98,"created",$F$2:$F$98,"<"&F44)-COUNTIFS($C$2:$C$98,$C44,$H$2:$H$98,"cancelled",$F$2:$F$98,"<"&F44)=0),1,0) -> 0
A45: EVT044 | B45: SUB028 | C45: CUST028 | D45: Prairie SaaS Innovations | E45: Central Canada | F45: 45658 | G45: 45677 | H45: created | M45: Analytics Starter | N45: Monthly | O45: 15 | P45: 45 | Q45: 0 | R45: {=_xlfn.IFS(H45="created", "New", H45="cancelled", "Churned", AND(H45="seats_change", J45 > I45), "Expansion", AND(H45="seats_change", J45 < I45), "Contraction", AND(H45="price_change", J45 > I45), "Expansion", AND(H45="price_change", J45 < I45), "Contraction", H45="plan_upgrade", "Expansion", H45="plan_downgrade", "Contraction", H45="discount_added", "Contraction")} -> New | S45: {=IF(N45="Monthly",_xlfn.IFS(H45="created",O45*P45*(1-Q45/100),H45="cancelled",-(O45*P45*(1-Q45/100)),H45="seats_change",(J45-I45)*P45*(1-Q45/100),H45="price_change",(J45-I45)*O45*(1-Q45/100),H45="discount_added",-(O45*P45*(J45-I45)/100),H45="plan_upgrade",O45*(_xlfn.XLOOKUP(J45,$M:$M,$P:$P)-_xlfn.XLOOKUP(I45,$M:$M,$P:$P))*(1-Q45/100),H45="plan_downgrade",O45*(_xlfn.XLOOKUP(J45,$M:$M,$P:$P)-_xlfn.XLOOKUP(I45,$M:$M,$P:$P))*(1-Q45/100)),_xlfn.IFS(H45="created",O45*P45*(1-Q45/100)/12,H45="cancelled",-(O45*P45*(1-Q45/100))/12,H45="seats_change",(J45-I45)*P45*(1-Q45/100)/12,H45="price_change",(J45-I45)*O45*(1-Q45/100)/12,H45="plan_upgrade",(O45*(_xlfn.XLOOKUP(J45,$M:$M,$P:$P)-_xlfn.XLOOKUP(I45,$M:$M,$P:$P))*(1-Q45/100))/12,H45="plan_downgrade",(O45*(_xlfn.XLOOKUP(J45,$M:$M,$P:$P)-_xlfn.XLOOKUP(I45,$M:$M,$P:$P))*(1-Q45/100))/12,H45="discount_added",-(O45*P45*(J45-I45)/100)/12))} -> 675 | T45: =IF(H45<>"created",0,IF(COUNTIFS($C$1:C44,$C45,$H$1:H44,"created")=0,1,0)) -> 1 | U45: =IF(H45<>"cancelled",0,IF(COUNTIFS($C$2:$C$98,$C45,$H$2:$H$98,"created",$F$2:$F$98,"<="&F45)-COUNTIFS($C$2:$C$98,$C45,$H$2:$H$98,"cancelled",$F$2:$F$98,"<="&F45)=0,1,0)) -> 0 | V45: =IF(AND(H45="created",T45=0,COUNTIFS($C$2:$C$98,$C45,$H$2:$H$98,"cancelled",$F$2:$F$98,"<"&F45)>0,COUNTIFS($C$2:$C$98,$C45,$H$2:$H$98,"created",$F$2:$F$98,"<"&F45)-COUNTIFS($C$2:$C$98,$C45,$H$2:$H$98,"cancelled",$F$2:$F$98,"<"&F45)=0),1,0) -> 0
A46: EVT045 | B46: SUB054 | C46: CUST002 | D46: Pacific Analytics Inc | E46: Western Canada | F46: 45658 | G46: 45679 | H46: created | M46: Analytics Growth | N46: Annual | O46: 22 | P46: 1140 | Q46: 5 | R46: {=_xlfn.IFS(H46="created", "New", H46="cancelled", "Churned", AND(H46="seats_change", J46 > I46), "Expansion", AND(H46="seats_change", J46 < I46), "Contraction", AND(H46="price_change", J46 > I46), "Expansion", AND(H46="price_change", J46 < I46), "Contraction", H46="plan_upgrade", "Expansion", H46="plan_downgrade", "Contraction", H46="discount_added", "Contraction")} -> New | S46: {=IF(N46="Monthly",_xlfn.IFS(H46="created",O46*P46*(1-Q46/100),H46="cancelled",-(O46*P46*(1-Q46/100)),H46="seats_change",(J46-I46)*P46*(1-Q46/100),H46="price_change",(J46-I46)*O46*(1-Q46/100),H46="discount_added",-(O46*P46*(J46-I46)/100),H46="plan_upgrade",O46*(_xlfn.XLOOKUP(J46,$M:$M,$P:$P)-_xlfn.XLOOKUP(I46,$M:$M,$P:$P))*(1-Q46/100),H46="plan_downgrade",O46*(_xlfn.XLOOKUP(J46,$M:$M,$P:$P)-_xlfn.XLOOKUP(I46,$M:$M,$P:$P))*(1-Q46/100)),_xlfn.IFS(H46="created",O46*P46*(1-Q46/100)/12,H46="cancelled",-(O46*P46*(1-Q46/100))/12,H46="seats_change",(J46-I46)*P46*(1-Q46/100)/12,H46="price_change",(J46-I46)*O46*(1-Q46/100)/12,H46="plan_upgrade",(O46*(_xlfn.XLOOKUP(J46,$M:$M,$P:$P)-_xlfn.XLOOKUP(I46,$M:$M,$P:$P))*(1-Q46/100))/12,H46="plan_downgrade",(O46*(_xlfn.XLOOKUP(J46,$M:$M,$P:$P)-_xlfn.XLOOKUP(I46,$M:$M,$P:$P))*(1-Q46/100))/12,H46="discount_added",-(O46*P46*(J46-I46)/100)/12))} -> 1985.5 | T46: =IF(H46<>"created",0,IF(COUNTIFS($C$1:C45,$C46,$H$1:H45,"created")=0,1,0)) -> 0 | U46: =IF(H46<>"cancelled",0,IF(COUNTIFS($C$2:$C$98,$C46,$H$2:$H$98,"created",$F$2:$F$98,"<="&F46)-COUNTIFS($C$2:$C$98,$C46,$H$2:$H$98,"cancelled",$F$2:$F$98,"<="&F46)=0,1,0)) -> 0 | V46: =IF(AND(H46="created",T46=0,COUNTIFS($C$2:$C$98,$C46,$H$2:$H$98,"cancelled",$F$2:$F$98,"<"&F46)>0,COUNTIFS($C$2:$C$98,$C46,$H$2:$H$98,"created",$F$2:$F$98,"<"&F46)-COUNTIFS($C$2:$C$98,$C46,$H$2:$H$98,"cancelled",$F$2:$F$98,"<"&F46)=0),1,0) -> 0
A47: EVT046 | B47: SUB057 | C47: CUST021 | D47: Calgary Commerce Solutions | E47: Western Canada | F47: 45658 | G47: 45685 | H47: created | M47: Platform Suite | N47: Monthly | O47: 28 | P47: 150 | Q47: 0 | R47: {=_xlfn.IFS(H47="created", "New", H47="cancelled", "Churned", AND(H47="seats_change", J47 > I47), "Expansion", AND(H47="seats_change", J47 < I47), "Contraction", AND(H47="price_change", J47 > I47), "Expansion", AND(H47="price_change", J47 < I47), "Contraction", H47="plan_upgrade", "Expansion", H47="plan_downgrade", "Contraction", H47="discount_added", "Contraction")} -> New | S47: {=IF(N47="Monthly",_xlfn.IFS(H47="created",O47*P47*(1-Q47/100),H47="cancelled",-(O47*P47*(1-Q47/100)),H47="seats_change",(J47-I47)*P47*(1-Q47/100),H47="price_change",(J47-I47)*O47*(1-Q47/100),H47="discount_added",-(O47*P47*(J47-I47)/100),H47="plan_upgrade",O47*(_xlfn.XLOOKUP(J47,$M:$M,$P:$P)-_xlfn.XLOOKUP(I47,$M:$M,$P:$P))*(1-Q47/100),H47="plan_downgrade",O47*(_xlfn.XLOOKUP(J47,$M:$M,$P:$P)-_xlfn.XLOOKUP(I47,$M:$M,$P:$P))*(1-Q47/100)),_xlfn.IFS(H47="created",O47*P47*(1-Q47/100)/12,H47="cancelled",-(O47*P47*(1-Q47/100))/12,H47="seats_change",(J47-I47)*P47*(1-Q47/100)/12,H47="price_change",(J47-I47)*O47*(1-Q47/100)/12,H47="plan_upgrade",(O47*(_xlfn.XLOOKUP(J47,$M:$M,$P:$P)-_xlfn.XLOOKUP(I47,$M:$M,$P:$P))*(1-Q47/100))/12,H47="plan_downgrade",(O47*(_xlfn.XLOOKUP(J47,$M:$M,$P:$P)-_xlfn.XLOOKUP(I47,$M:$M,$P:$P))*(1-Q47/100))/12,H47="discount_added",-(O47*P47*(J47-I47)/100)/12))} -> 4200 | T47: =IF(H47<>"created",0,IF(COUNTIFS($C$1:C46,$C47,$H$1:H46,"created")=0,1,0)) -> 0 | U47: =IF(H47<>"cancelled",0,IF(COUNTIFS($C$2:$C$98,$C47,$H$2:$H$98,"created",$F$2:$F$98,"<="&F47)-COUNTIFS($C$2:$C$98,$C47,$H$2:$H$98,"cancelled",$F$2:$F$98,"<="&F47)=0,1,0)) -> 0 | V47: =IF(AND(H47="created",T47=0,COUNTIFS($C$2:$C$98,$C47,$H$2:$H$98,"cancelled",$F$2:$F$98,"<"&F47)>0,COUNTIFS($C$2:$C$98,$C47,$H$2:$H$98,"created",$F$2:$F$98,"<"&F47)-COUNTIFS($C$2:$C$98,$C47,$H$2:$H$98,"cancelled",$F$2:$F$98,"<"&F47)=0),1,0) -> 0
A48: EVT047 | B48: SUB029 | C48: CUST029 | D48: Halifax Healthcare Tech | E48: Eastern Canada | F48: 45689 | G48: 45691 | H48: created | M48: Marketing Pro | N48: Monthly | O48: 22 | P48: 85 | Q48: 0 | R48: {=_xlfn.IFS(H48="created", "New", H48="cancelled", "Churned", AND(H48="seats_change", J48 > I48), "Expansion", AND(H48="seats_change", J48 < I48), "Contraction", AND(H48="price_change", J48 > I48), "Expansion", AND(H48="price_change", J48 < I48), "Contraction", H48="plan_upgrade", "Expansion", H48="plan_downgrade", "Contraction", H48="discount_added", "Contraction")} -> New | S48: {=IF(N48="Monthly",_xlfn.IFS(H48="created",O48*P48*(1-Q48/100),H48="cancelled",-(O48*P48*(1-Q48/100)),H48="seats_change",(J48-I48)*P48*(1-Q48/100),H48="price_change",(J48-I48)*O48*(1-Q48/100),H48="discount_added",-(O48*P48*(J48-I48)/100),H48="plan_upgrade",O48*(_xlfn.XLOOKUP(J48,$M:$M,$P:$P)-_xlfn.XLOOKUP(I48,$M:$M,$P:$P))*(1-Q48/100),H48="plan_downgrade",O48*(_xlfn.XLOOKUP(J48,$M:$M,$P:$P)-_xlfn.XLOOKUP(I48,$M:$M,$P:$P))*(1-Q48/100)),_xlfn.IFS(H48="created",O48*P48*(1-Q48/100)/12,H48="cancelled",-(O48*P48*(1-Q48/100))/12,H48="seats_change",(J48-I48)*P48*(1-Q48/100)/12,H48="price_change",(J48-I48)*O48*(1-Q48/100)/12,H48="plan_upgrade",(O48*(_xlfn.XLOOKUP(J48,$M:$M,$P:$P)-_xlfn.XLOOKUP(I48,$M:$M,$P:$P))*(1-Q48/100))/12,H48="plan_downgrade",(O48*(_xlfn.XLOOKUP(J48,$M:$M,$P:$P)-_xlfn.XLOOKUP(I48,$M:$M,$P:$P))*(1-Q48/100))/12,H48="discount_added",-(O48*P48*(J48-I48)/100)/12))} -> 1870 | T48: =IF(H48<>"created",0,IF(COUNTIFS($C$1:C47,$C48,$H$1:H47,"created")=0,1,0)) -> 1 | U48: =IF(H48<>"cancelled",0,IF(COUNTIFS($C$2:$C$98,$C48,$H$2:$H$98,"created",$F$2:$F$98,"<="&F48)-COUNTIFS($C$2:$C$98,$C48,$H$2:$H$98,"cancelled",$F$2:$F$98,"<="&F48)=0,1,0)) -> 0 | V48: =IF(AND(H48="created",T48=0,COUNTIFS($C$2:$C$98,$C48,$H$2:$H$98,"cancelled",$F$2:$F$98,"<"&F48)>0,COUNTIFS($C$2:$C$98,$C48,$H$2:$H$98,"created",$F$2:$F$98,"<"&F48)-COUNTIFS($C$2:$C$98,$C48,$H$2:$H$98,"cancelled",$F$2:$F$98,"<"&F48)=0),1,0) -> 0
A49: EVT048 | B49: SUB045 | C49: CUST010 | D49: Montreal Finance Hub | E49: Eastern Canada | F49: 45689 | G49: 45696 | H49: created | M49: Marketing Pro | N49: Monthly | O49: 13 | P49: 85 | Q49: 0 | R49: {=_xlfn.IFS(H49="created", "New", H49="cancelled", "Churned", AND(H49="seats_change", J49 > I49), "Expansion", AND(H49="seats_change", J49 < I49), "Contraction", AND(H49="price_change", J49 > I49), "Expansion", AND(H49="price_change", J49 < I49), "Contraction", H49="plan_upgrade", "Expansion", H49="plan_downgrade", "Contraction", H49="discount_added", "Contraction")} -> New | S49: {=IF(N49="Monthly",_xlfn.IFS(H49="created",O49*P49*(1-Q49/100),H49="cancelled",-(O49*P49*(1-Q49/100)),H49="seats_change",(J49-I49)*P49*(1-Q49/100),H49="price_change",(J49-I49)*O49*(1-Q49/100),H49="discount_added",-(O49*P49*(J49-I49)/100),H49="plan_upgrade",O49*(_xlfn.XLOOKUP(J49,$M:$M,$P:$P)-_xlfn.XLOOKUP(I49,$M:$M,$P:$P))*(1-Q49/100),H49="plan_downgrade",O49*(_xlfn.XLOOKUP(J49,$M:$M,$P:$P)-_xlfn.XLOOKUP(I49,$M:$M,$P:$P))*(1-Q49/100)),_xlfn.IFS(H49="created",O49*P49*(1-Q49/100)/12,H49="cancelled",-(O49*P49*(1-Q49/100))/12,H49="seats_change",(J49-I49)*P49*(1-Q49/100)/12,H49="price_change",(J49-I49)*O49*(1-Q49/100)/12,H49="plan_upgrade",(O49*(_xlfn.XLOOKUP(J49,$M:$M,$P:$P)-_xlfn.XLOOKUP(I49,$M:$M,$P:$P))*(1-Q49/100))/12,H49="plan_downgrade",(O49*(_xlfn.XLOOKUP(J49,$M:$M,$P:$P)-_xlfn.XLOOKUP(I49,$M:$M,$P:$P))*(1-Q49/100))/12,H49="discount_added",-(O49*P49*(J49-I49)/100)/12))} -> 1105 | T49: =IF(H49<>"created",0,IF(COUNTIFS($C$1:C48,$C49,$H$1:H48,"created")=0,1,0)) -> 0 | U49: =IF(H49<>"cancelled",0,IF(COUNTIFS($C$2:$C$98,$C49,$H$2:$H$98,"created",$F$2:$F$98,"<="&F49)-COUNTIFS($C$2:$C$98,$C49,$H$2:$H$98,"cancelled",$F$2:$F$98,"<="&F49)=0,1,0)) -> 0 | V49: =IF(AND(H49="created",T49=0,COUNTIFS($C$2:$C$98,$C49,$H$2:$H$98,"cancelled",$F$2:$F$98,"<"&F49)>0,COUNTIFS($C$2:$C$98,$C49,$H$2:$H$98,"created",$F$2:$F$98,"<"&F49)-COUNTIFS($C$2:$C$98,$C49,$H$2:$H$98,"cancelled",$F$2:$F$98,"<"&F49)=0),1,0) -> 0
A50: EVT049 | B50: SUB051 | C50: CUST014 | D50: Toronto Media Group | E50: Eastern Canada | F50: 45689 | G50: 45698 | H50: created | M50: Sales Hub | N50: Monthly | O50: 23 | P50: 110 | Q50: 0 | R50: {=_xlfn.IFS(H50="created", "New", H50="cancelled", "Churned", AND(H50="seats_change", J50 > I50), "Expansion", AND(H50="seats_change", J50 < I50), "Contraction", AND(H50="price_change", J50 > I50), "Expansion", AND(H50="price_change", J50 < I50), "Contraction", H50="plan_upgrade", "Expansion", H50="plan_downgrade", "Contraction", H50="discount_added", "Contraction")} -> New | S50: {=IF(N50="Monthly",_xlfn.IFS(H50="created",O50*P50*(1-Q50/100),H50="cancelled",-(O50*P50*(1-Q50/100)),H50="seats_change",(J50-I50)*P50*(1-Q50/100),H50="price_change",(J50-I50)*O50*(1-Q50/100),H50="discount_added",-(O50*P50*(J50-I50)/100),H50="plan_upgrade",O50*(_xlfn.XLOOKUP(J50,$M:$M,$P:$P)-_xlfn.XLOOKUP(I50,$M:$M,$P:$P))*(1-Q50/100),H50="plan_downgrade",O50*(_xlfn.XLOOKUP(J50,$M:$M,$P:$P)-_xlfn.XLOOKUP(I50,$M:$M,$P:$P))*(1-Q50/100)),_xlfn.IFS(H50="created",O50*P50*(1-Q50/100)/12,H50="cancelled",-(O50*P50*(1-Q50/100))/12,H50="seats_change",(J50-I50)*P50*(1-Q50/100)/12,H50="price_change",(J50-I50)*O50*(1-Q50/100)/12,H50="plan_upgrade",(O50*(_xlfn.XLOOKUP(J50,$M:$M,$P:$P)-_xlfn.XLOOKUP(I50,$M:$M,$P:$P))*(1-Q50/100))/12,H50="plan_downgrade",(O50*(_xlfn.XLOOKUP(J50,$M:$M,$P:$P)-_xlfn.XLOOKUP(I50,$M:$M,$P:$P))*(1-Q50/100))/12,H50="discount_added",-(O50*P50*(J50-I50)/100)/12))} -> 2530 | T50: =IF(H50<>"created",0,IF(COUNTIFS($C$1:C49,$C50,$H$1:H49,"created")=0,1,0)) -> 0 | U50: =IF(H50<>"cancelled",0,IF(COUNTIFS($C$2:$C$98,$C50,$H$2:$H$98,"created",$F$2:$F$98,"<="&F50)-COUNTIFS($C$2:$C$98,$C50,$H$2:$H$98,"cancelled",$F$2:$F$98,"<="&F50)=0,1,0)) -> 0 | V50: =IF(AND(H50="created",T50=0,COUNTIFS($C$2:$C$98,$C50,$H$2:$H$98,"cancelled",$F$2:$F$98,"<"&F50)>0,COUNTIFS($C$2:$C$98,$C50,$H$2:$H$98,"created",$F$2:$F$98,"<"&F50)-COUNTIFS($C$2:$C$98,$C50,$H$2:$H$98,"cancelled",$F$2:$F$98,"<"&F50)=0),1,0) -> 0
A51: EVT050 | B51: SUB030 | C51: CUST030 | D51: Alberta E-commerce Hub | E51: Western Canada | F51: 45689 | G51: 45705 | H51: created | M51: Analytics Growth | N51: Monthly | O51: 20 | P51: 95 | Q51: 0 | R51: {=_xlfn.IFS(H51="created", "New", H51="cancelled", "Churned", AND(H51="seats_change", J51 > I51), "Expansion", AND(H51="seats_change", J51 < I51), "Contraction", AND(H51="price_change", J51 > I51), "Expansion", AND(H51="price_change", J51 < I51), "Contraction", H51="plan_upgrade", "Expansion", H51="plan_downgrade", "Contraction", H51="discount_added", "Contraction")} -> New | S51: {=IF(N51="Monthly",_xlfn.IFS(H51="created",O51*P51*(1-Q51/100),H51="cancelled",-(O51*P51*(1-Q51/100)),H51="seats_change",(J51-I51)*P51*(1-Q51/100),H51="price_change",(J51-I51)*O51*(1-Q51/100),H51="discount_added",-(O51*P51*(J51-I51)/100),H51="plan_upgrade",O51*(_xlfn.XLOOKUP(J51,$M:$M,$P:$P)-_xlfn.XLOOKUP(I51,$M:$M,$P:$P))*(1-Q51/100),H51="plan_downgrade",O51*(_xlfn.XLOOKUP(J51,$M:$M,$P:$P)-_xlfn.XLOOKUP(I51,$M:$M,$P:$P))*(1-Q51/100)),_xlfn.IFS(H51="created",O51*P51*(1-Q51/100)/12,H51="cancelled",-(O51*P51*(1-Q51/100))/12,H51="seats_change",(J51-I51)*P51*(1-Q51/100)/12,H51="price_change",(J51-I51)*O51*(1-Q51/100)/12,H51="plan_upgrade",(O51*(_xlfn.XLOOKUP(J51,$M:$M,$P:$P)-_xlfn.XLOOKUP(I51,$M:$M,$P:$P))*(1-Q51/100))/12,H51="plan_downgrade",(O51*(_xlfn.XLOOKUP(J51,$M:$M,$P:$P)-_xlfn.XLOOKUP(I51,$M:$M,$P:$P))*(1-Q51/100))/12,H51="discount_added",-(O51*P51*(J51-I51)/100)/12))} -> 1900 | T51: =IF(H51<>"created",0,IF(COUNTIFS($C$1:C50,$C51,$H$1:H50,"created")=0,1,0)) -> 1 | U51: =IF(H51<>"cancelled",0,IF(COUNTIFS($C$2:$C$98,$C51,$H$2:$H$98,"created",$F$2:$F$98,"<="&F51)-COUNTIFS($C$2:$C$98,$C51,$H$2:$H$98,"cancelled",$F$2:$F$98,"<="&F51)=0,1,0)) -> 0 | V51: =IF(AND(H51="created",T51=0,COUNTIFS($C$2:$C$98,$C51,$H$2:$H$98,"cancelled",$F$2:$F$98,"<"&F51)>0,COUNTIFS($C$2:$C$98,$C51,$H$2:$H$98,"created",$F$2:$F$98,"<"&F51)-COUNTIFS($C$2:$C$98,$C51,$H$2:$H$98,"cancelled",$F$2:$F$98,"<"&F51)=0),1,0) -> 0
A52: EVT051 | B52: SUB031 | C52: CUST031 | D52: Toronto Digital Media | E52: Eastern Canada | F52: 45717 | G52: 45719 | H52: created | M52: Platform Suite | N52: Annual | O52: 45 | P52: 1800 | Q52: 0 | R52: {=_xlfn.IFS(H52="created", "New", H52="cancelled", "Churned", AND(H52="seats_change", J52 > I52), "Expansion", AND(H52="seats_change", J52 < I52), "Contraction", AND(H52="price_change", J52 > I52), "Expansion", AND(H52="price_change", J52 < I52), "Contraction", H52="plan_upgrade", "Expansion", H52="plan_downgrade", "Contraction", H52="discount_added", "Contraction")} -> New | S52: {=IF(N52="Monthly",_xlfn.IFS(H52="created",O52*P52*(1-Q52/100),H52="cancelled",-(O52*P52*(1-Q52/100)),H52="seats_change",(J52-I52)*P52*(1-Q52/100),H52="price_change",(J52-I52)*O52*(1-Q52/100),H52="discount_added",-(O52*P52*(J52-I52)/100),H52="plan_upgrade",O52*(_xlfn.XLOOKUP(J52,$M:$M,$P:$P)-_xlfn.XLOOKUP(I52,$M:$M,$P:$P))*(1-Q52/100),H52="plan_downgrade",O52*(_xlfn.XLOOKUP(J52,$M:$M,$P:$P)-_xlfn.XLOOKUP(I52,$M:$M,$P:$P))*(1-Q52/100)),_xlfn.IFS(H52="created",O52*P52*(1-Q52/100)/12,H52="cancelled",-(O52*P52*(1-Q52/100))/12,H52="seats_change",(J52-I52)*P52*(1-Q52/100)/12,H52="price_change",(J52-I52)*O52*(1-Q52/100)/12,H52="plan_upgrade",(O52*(_xlfn.XLOOKUP(J52,$M:$M,$P:$P)-_xlfn.XLOOKUP(I52,$M:$M,$P:$P))*(1-Q52/100))/12,H52="plan_downgrade",(O52*(_xlfn.XLOOKUP(J52,$M:$M,$P:$P)-_xlfn.XLOOKUP(I52,$M:$M,$P:$P))*(1-Q52/100))/12,H52="discount_added",-(O52*P52*(J52-I52)/100)/12))} -> 6750 | T52: =IF(H52<>"created",0,IF(COUNTIFS($C$1:C51,$C52,$H$1:H51,"created")=0,1,0)) -> 1 | U52: =IF(H52<>"cancelled",0,IF(COUNTIFS($C$2:$C$98,$C52,$H$2:$H$98,"created",$F$2:$F$98,"<="&F52)-COUNTIFS($C$2:$C$98,$C52,$H$2:$H$98,"cancelled",$F$2:$F$98,"<="&F52)=0,1,0)) -> 0 | V52: =IF(AND(H52="created",T52=0,COUNTIFS($C$2:$C$98,$C52,$H$2:$H$98,"cancelled",$F$2:$F$98,"<"&F52)>0,COUNTIFS($C$2:$C$98,$C52,$H$2:$H$98,"created",$F$2:$F$98,"<"&F52)-COUNTIFS($C$2:$C$98,$C52,$H$2:$H$98,"cancelled",$F$2:$F$98,"<"&F52)=0),1,0) -> 0
A53: EVT052 | B53: SUB058 | C53: CUST024 | D53: Western Retail Group | E53: Western Canada | F53: 45717 | G53: 45724 | H53: created | M53: Sales Hub | N53: Monthly | O53: 26 | P53: 110 | Q53: 0 | R53: {=_xlfn.IFS(H53="created", "New", H53="cancelled", "Churned", AND(H53="seats_change", J53 > I53), "Expansion", AND(H53="seats_change", J53 < I53), "Contraction", AND(H53="price_change", J53 > I53), "Expansion", AND(H53="price_change", J53 < I53), "Contraction", H53="plan_upgrade", "Expansion", H53="plan_downgrade", "Contraction", H53="discount_added", "Contraction")} -> New | S53: {=IF(N53="Monthly",_xlfn.IFS(H53="created",O53*P53*(1-Q53/100),H53="cancelled",-(O53*P53*(1-Q53/100)),H53="seats_change",(J53-I53)*P53*(1-Q53/100),H53="price_change",(J53-I53)*O53*(1-Q53/100),H53="discount_added",-(O53*P53*(J53-I53)/100),H53="plan_upgrade",O53*(_xlfn.XLOOKUP(J53,$M:$M,$P:$P)-_xlfn.XLOOKUP(I53,$M:$M,$P:$P))*(1-Q53/100),H53="plan_downgrade",O53*(_xlfn.XLOOKUP(J53,$M:$M,$P:$P)-_xlfn.XLOOKUP(I53,$M:$M,$P:$P))*(1-Q53/100)),_xlfn.IFS(H53="created",O53*P53*(1-Q53/100)/12,H53="cancelled",-(O53*P53*(1-Q53/100))/12,H53="seats_change",(J53-I53)*P53*(1-Q53/100)/12,H53="price_change",(J53-I53)*O53*(1-Q53/100)/12,H53="plan_upgrade",(O53*(_xlfn.XLOOKUP(J53,$M:$M,$P:$P)-_xlfn.XLOOKUP(I53,$M:$M,$P:$P))*(1-Q53/100))/12,H53="plan_downgrade",(O53*(_xlfn.XLOOKUP(J53,$M:$M,$P:$P)-_xlfn.XLOOKUP(I53,$M:$M,$P:$P))*(1-Q53/100))/12,H53="discount_added",-(O53*P53*(J53-I53)/100)/12))} -> 2860 | T53: =IF(H53<>"created",0,IF(COUNTIFS($C$1:C52,$C53,$H$1:H52,"created")=0,1,0)) -> 0 | U53: =IF(H53<>"cancelled",0,IF(COUNTIFS($C$2:$C$98,$C53,$H$2:$H$98,"created",$F$2:$F$98,"<="&F53)-COUNTIFS($C$2:$C$98,$C53,$H$2:$H$98,"cancelled",$F$2:$F$98,"<="&F53)=0,1,0)) -> 0 | V53: =IF(AND(H53="created",T53=0,COUNTIFS($C$2:$C$98,$C53,$H$2:$H$98,"cancelled",$F$2:$F$98,"<"&F53)>0,COUNTIFS($C$2:$C$98,$C53,$H$2:$H$98,"created",$F$2:$F$98,"<"&F53)-COUNTIFS($C$2:$C$98,$C53,$H$2:$H$98,"cancelled",$F$2:$F$98,"<"&F53)=0),1,0) -> 0
A54: EVT053 | B54: SUB010 | C54: CUST010 | D54: Montreal Finance Hub | E54: Eastern Canada | F54: 45717 | G54: 45729 | H54: plan_downgrade | I54: Analytics Growth | J54: Analytics Starter | K54: plan_name | L54: Cost reduction initiative - downgraded to starter tier | M54: Analytics Starter | N54: Monthly | O54: 13 | P54: 45 | Q54: 0 | R54: {=_xlfn.IFS(H54="created", "New", H54="cancelled", "Churned", AND(H54="seats_change", J54 > I54), "Expansion", AND(H54="seats_change", J54 < I54), "Contraction", AND(H54="price_change", J54 > I54), "Expansion", AND(H54="price_change", J54 < I54), "Contraction", H54="plan_upgrade", "Expansion", H54="plan_downgrade", "Contraction", H54="discount_added", "Contraction")} -> Contraction | S54: {=IF(N54="Monthly",_xlfn.IFS(H54="created",O54*P54*(1-Q54/100),H54="cancelled",-(O54*P54*(1-Q54/100)),H54="seats_change",(J54-I54)*P54*(1-Q54/100),H54="price_change",(J54-I54)*O54*(1-Q54/100),H54="discount_added",-(O54*P54*(J54-I54)/100),H54="plan_upgrade",O54*(_xlfn.XLOOKUP(J54,$M:$M,$P:$P)-_xlfn.XLOOKUP(I54,$M:$M,$P:$P))*(1-Q54/100),H54="plan_downgrade",O54*(_xlfn.XLOOKUP(J54,$M:$M,$P:$P)-_xlfn.XLOOKUP(I54,$M:$M,$P:$P))*(1-Q54/100)),_xlfn.IFS(H54="created",O54*P54*(1-Q54/100)/12,H54="cancelled",-(O54*P54*(1-Q54/100))/12,H54="seats_change",(J54-I54)*P54*(1-Q54/100)/12,H54="price_change",(J54-I54)*O54*(1-Q54/100)/12,H54="plan_upgrade",(O54*(_xlfn.XLOOKUP(J54,$M:$M,$P:$P)-_xlfn.XLOOKUP(I54,$M:$M,$P:$P))*(1-Q54/100))/12,H54="plan_downgrade",(O54*(_xlfn.XLOOKUP(J54,$M:$M,$P:$P)-_xlfn.XLOOKUP(I54,$M:$M,$P:$P))*(1-Q54/100))/12,H54="discount_added",-(O54*P54*(J54-I54)/100)/12))} -> -650 | T54: =IF(H54<>"created",0,IF(COUNTIFS($C$1:C53,$C54,$H$1:H53,"created")=0,1,0)) -> 0 | U54: =IF(H54<>"cancelled",0,IF(COUNTIFS($C$2:$C$98,$C54,$H$2:$H$98,"created",$F$2:$F$98,"<="&F54)-COUNTIFS($C$2:$C$98,$C54,$H$2:$H$98,"cancelled",$F$2:$F$98,"<="&F54)=0,1,0)) -> 0 | V54: =IF(AND(H54="created",T54=0,COUNTIFS($C$2:$C$98,$C54,$H$2:$H$98,"cancelled",$F$2:$F$98,"<"&F54)>0,COUNTIFS($C$2:$C$98,$C54,$H$2:$H$98,"created",$F$2:$F$98,"<"&F54)-COUNTIFS($C$2:$C$98,$C54,$H$2:$H$98,"cancelled",$F$2:$F$98,"<"&F54)=0),1,0) -> 0
A55: EVT054 | B55: SUB052 | C55: CUST018 | D55: Vancouver FinTech Labs | E55: Western Canada | F55: 45717 | G55: 45731 | H55: created | M55: Marketing Pro | N55: Monthly | O55: 35 | P55: 85 | Q55: 0 | R55: {=_xlfn.IFS(H55="created", "New", H55="cancelled", "Churned", AND(H55="seats_change", J55 > I55), "Expansion", AND(H55="seats_change", J55 < I55), "Contraction", AND(H55="price_change", J55 > I55), "Expansion", AND(H55="price_change", J55 < I55), "Contraction", H55="plan_upgrade", "Expansion", H55="plan_downgrade", "Contraction", H55="discount_added", "Contraction")} -> New | S55: {=IF(N55="Monthly",_xlfn.IFS(H55="created",O55*P55*(1-Q55/100),H55="cancelled",-(O55*P55*(1-Q55/100)),H55="seats_change",(J55-I55)*P55*(1-Q55/100),H55="price_change",(J55-I55)*O55*(1-Q55/100),H55="discount_added",-(O55*P55*(J55-I55)/100),H55="plan_upgrade",O55*(_xlfn.XLOOKUP(J55,$M:$M,$P:$P)-_xlfn.XLOOKUP(I55,$M:$M,$P:$P))*(1-Q55/100),H55="plan_downgrade",O55*(_xlfn.XLOOKUP(J55,$M:$M,$P:$P)-_xlfn.XLOOKUP(I55,$M:$M,$P:$P))*(1-Q55/100)),_xlfn.IFS(H55="created",O55*P55*(1-Q55/100)/12,H55="cancelled",-(O55*P55*(1-Q55/100))/12,H55="seats_change",(J55-I55)*P55*(1-Q55/100)/12,H55="price_change",(J55-I55)*O55*(1-Q55/100)/12,H55="plan_upgrade",(O55*(_xlfn.XLOOKUP(J55,$M:$M,$P:$P)-_xlfn.XLOOKUP(I55,$M:$M,$P:$P))*(1-Q55/100))/12,H55="plan_downgrade",(O55*(_xlfn.XLOOKUP(J55,$M:$M,$P:$P)-_xlfn.XLOOKUP(I55,$M:$M,$P:$P))*(1-Q55/100))/12,H55="discount_added",-(O55*P55*(J55-I55)/100)/12))} -> 2975 | T55: =IF(H55<>"created",0,IF(COUNTIFS($C$1:C54,$C55,$H$1:H54,"created")=0,1,0)) -> 0 | U55: =IF(H55<>"cancelled",0,IF(COUNTIFS($C$2:$C$98,$C55,$H$2:$H$98,"created",$F$2:$F$98,"<="&F55)-COUNTIFS($C$2:$C$98,$C55,$H$2:$H$98,"cancelled",$F$2:$F$98,"<="&F55)=0,1,0)) -> 0 | V55: =IF(AND(H55="created",T55=0,COUNTIFS($C$2:$C$98,$C55,$H$2:$H$98,"cancelled",$F$2:$F$98,"<"&F55)>0,COUNTIFS($C$2:$C$98,$C55,$H$2:$H$98,"created",$F$2:$F$98,"<"&F55)-COUNTIFS($C$2:$C$98,$C55,$H$2:$H$98,"cancelled",$F$2:$F$98,"<"&F55)=0),1,0) -> 0
A56: EVT055 | B56: SUB054 | C56: CUST002 | D56: Pacific Analytics Inc | E56: Western Canada | F56: 45717 | G56: 45731 | H56: discount_added | I56: 0 | J56: 5 | K56: discount_percent | L56: Annual contract loyalty discount applied | M56: Analytics Growth | N56: Annual | O56: 22 | P56: 1140 | Q56: 5 | R56: {=_xlfn.IFS(H56="created", "New", H56="cancelled", "Churned", AND(H56="seats_change", J56 > I56), "Expansion", AND(H56="seats_change", J56 < I56), "Contraction", AND(H56="price_change", J56 > I56), "Expansion", AND(H56="price_change", J56 < I56), "Contraction", H56="plan_upgrade", "Expansion", H56="plan_downgrade", "Contraction", H56="discount_added", "Contraction")} -> Contraction | S56: {=IF(N56="Monthly",_xlfn.IFS(H56="created",O56*P56*(1-Q56/100),H56="cancelled",-(O56*P56*(1-Q56/100)),H56="seats_change",(J56-I56)*P56*(1-Q56/100),H56="price_change",(J56-I56)*O56*(1-Q56/100),H56="discount_added",-(O56*P56*(J56-I56)/100),H56="plan_upgrade",O56*(_xlfn.XLOOKUP(J56,$M:$M,$P:$P)-_xlfn.XLOOKUP(I56,$M:$M,$P:$P))*(1-Q56/100),H56="plan_downgrade",O56*(_xlfn.XLOOKUP(J56,$M:$M,$P:$P)-_xlfn.XLOOKUP(I56,$M:$M,$P:$P))*(1-Q56/100)),_xlfn.IFS(H56="created",O56*P56*(1-Q56/100)/12,H56="cancelled",-(O56*P56*(1-Q56/100))/12,H56="seats_change",(J56-I56)*P56*(1-Q56/100)/12,H56="price_change",(J56-I56)*O56*(1-Q56/100)/12,H56="plan_upgrade",(O56*(_xlfn.XLOOKUP(J56,$M:$M,$P:$P)-_xlfn.XLOOKUP(I56,$M:$M,$P:$P))*(1-Q56/100))/12,H56="plan_downgrade",(O56*(_xlfn.XLOOKUP(J56,$M:$M,$P:$P)-_xlfn.XLOOKUP(I56,$M:$M,$P:$P))*(1-Q56/100))/12,H56="discount_added",-(O56*P56*(J56-I56)/100)/12))} -> -104.5 | T56: =IF(H56<>"created",0,IF(COUNTIFS($C$1:C55,$C56,$H$1:H55,"created")=0,1,0)) -> 0 | U56: =IF(H56<>"cancelled",0,IF(COUNTIFS($C$2:$C$98,$C56,$H$2:$H$98,"created",$F$2:$F$98,"<="&F56)-COUNTIFS($C$2:$C$98,$C56,$H$2:$H$98,"cancelled",$F$2:$F$98,"<="&F56)=0,1,0)) -> 0 | V56: =IF(AND(H56="created",T56=0,COUNTIFS($C$2:$C$98,$C56,$H$2:$H$98,"cancelled",$F$2:$F$98,"<"&F56)>0,COUNTIFS($C$2:$C$98,$C56,$H$2:$H$98,"created",$F$2:$F$98,"<"&F56)-COUNTIFS($C$2:$C$98,$C56,$H$2:$H$98,"cancelled",$F$2:$F$98,"<"&F56)=0),1,0) -> 0
A57: EVT056 | B57: SUB032 | C57: CUST032 | D57: BC Manufacturing Systems | E57: Western Canada | F57: 45717 | G57: 45733 | H57: created | M57: Analytics Enterprise | N57: Monthly | O57: 26 | P57: 180 | Q57: 0 | R57: {=_xlfn.IFS(H57="created", "New", H57="cancelled", "Churned", AND(H57="seats_change", J57 > I57), "Expansion", AND(H57="seats_change", J57 < I57), "Contraction", AND(H57="price_change", J57 > I57), "Expansion", AND(H57="price_change", J57 < I57), "Contraction", H57="plan_upgrade", "Expansion", H57="plan_downgrade", "Contraction", H57="discount_added", "Contraction")} -> New | S57: {=IF(N57="Monthly",_xlfn.IFS(H57="created",O57*P57*(1-Q57/100),H57="cancelled",-(O57*P57*(1-Q57/100)),H57="seats_change",(J57-I57)*P57*(1-Q57/100),H57="price_change",(J57-I57)*O57*(1-Q57/100),H57="discount_added",-(O57*P57*(J57-I57)/100),H57="plan_upgrade",O57*(_xlfn.XLOOKUP(J57,$M:$M,$P:$P)-_xlfn.XLOOKUP(I57,$M:$M,$P:$P))*(1-Q57/100),H57="plan_downgrade",O57*(_xlfn.XLOOKUP(J57,$M:$M,$P:$P)-_xlfn.XLOOKUP(I57,$M:$M,$P:$P))*(1-Q57/100)),_xlfn.IFS(H57="created",O57*P57*(1-Q57/100)/12,H57="cancelled",-(O57*P57*(1-Q57/100))/12,H57="seats_change",(J57-I57)*P57*(1-Q57/100)/12,H57="price_change",(J57-I57)*O57*(1-Q57/100)/12,H57="plan_upgrade",(O57*(_xlfn.XLOOKUP(J57,$M:$M,$P:$P)-_xlfn.XLOOKUP(I57,$M:$M,$P:$P))*(1-Q57/100))/12,H57="plan_downgrade",(O57*(_xlfn.XLOOKUP(J57,$M:$M,$P:$P)-_xlfn.XLOOKUP(I57,$M:$M,$P:$P))*(1-Q57/100))/12,H57="discount_added",-(O57*P57*(J57-I57)/100)/12))} -> 4680 | T57: =IF(H57<>"created",0,IF(COUNTIFS($C$1:C56,$C57,$H$1:H56,"created")=0,1,0)) -> 1 | U57: =IF(H57<>"cancelled",0,IF(COUNTIFS($C$2:$C$98,$C57,$H$2:$H$98,"created",$F$2:$F$98,"<="&F57)-COUNTIFS($C$2:$C$98,$C57,$H$2:$H$98,"cancelled",$F$2:$F$98,"<="&F57)=0,1,0)) -> 0 | V57: =IF(AND(H57="created",T57=0,COUNTIFS($C$2:$C$98,$C57,$H$2:$H$98,"cancelled",$F$2:$F$98,"<"&F57)>0,COUNTIFS($C$2:$C$98,$C57,$H$2:$H$98,"created",$F$2:$F$98,"<"&F57)-COUNTIFS($C$2:$C$98,$C57,$H$2:$H$98,"cancelled",$F$2:$F$98,"<"&F57)=0),1,0) -> 0
A58: EVT057 | B58: SUB019 | C58: CUST019 | D58: Central Healthcare Partners | E58: Central Canada | F58: 45717 | G58: 45736 | H58: seats_change | I58: 22 | J58: 19 | K58: seats | L58: Headcount reduction - Q1 restructuring | M58: Marketing Pro | N58: Monthly | O58: 19 | P58: 85 | Q58: 0 | R58: {=_xlfn.IFS(H58="created", "New", H58="cancelled", "Churned", AND(H58="seats_change", J58 > I58), "Expansion", AND(H58="seats_change", J58 < I58), "Contraction", AND(H58="price_change", J58 > I58), "Expansion", AND(H58="price_change", J58 < I58), "Contraction", H58="plan_upgrade", "Expansion", H58="plan_downgrade", "Contraction", H58="discount_added", "Contraction")} -> Contraction | S58: {=IF(N58="Monthly",_xlfn.IFS(H58="created",O58*P58*(1-Q58/100),H58="cancelled",-(O58*P58*(1-Q58/100)),H58="seats_change",(J58-I58)*P58*(1-Q58/100),H58="price_change",(J58-I58)*O58*(1-Q58/100),H58="discount_added",-(O58*P58*(J58-I58)/100),H58="plan_upgrade",O58*(_xlfn.XLOOKUP(J58,$M:$M,$P:$P)-_xlfn.XLOOKUP(I58,$M:$M,$P:$P))*(1-Q58/100),H58="plan_downgrade",O58*(_xlfn.XLOOKUP(J58,$M:$M,$P:$P)-_xlfn.XLOOKUP(I58,$M:$M,$P:$P))*(1-Q58/100)),_xlfn.IFS(H58="created",O58*P58*(1-Q58/100)/12,H58="cancelled",-(O58*P58*(1-Q58/100))/12,H58="seats_change",(J58-I58)*P58*(1-Q58/100)/12,H58="price_change",(J58-I58)*O58*(1-Q58/100)/12,H58="plan_upgrade",(O58*(_xlfn.XLOOKUP(J58,$M:$M,$P:$P)-_xlfn.XLOOKUP(I58,$M:$M,$P:$P))*(1-Q58/100))/12,H58="plan_downgrade",(O58*(_xlfn.XLOOKUP(J58,$M:$M,$P:$P)-_xlfn.XLOOKUP(I58,$M:$M,$P:$P))*(1-Q58/100))/12,H58="discount_added",-(O58*P58*(J58-I58)/100)/12))} -> -255 | T58: =IF(H58<>"created",0,IF(COUNTIFS($C$1:C57,$C58,$H$1:H57,"created")=0,1,0)) -> 0 | U58: =IF(H58<>"cancelled",0,IF(COUNTIFS($C$2:$C$98,$C58,$H$2:$H$98,"created",$F$2:$F$98,"<="&F58)-COUNTIFS($C$2:$C$98,$C58,$H$2:$H$98,"cancelled",$F$2:$F$98,"<="&F58)=0,1,0)) -> 0 | V58: =IF(AND(H58="created",T58=0,COUNTIFS($C$2:$C$98,$C58,$H$2:$H$98,"cancelled",$F$2:$F$98,"<"&F58)>0,COUNTIFS($C$2:$C$98,$C58,$H$2:$H$98,"created",$F$2:$F$98,"<"&F58)-COUNTIFS($C$2:$C$98,$C58,$H$2:$H$98,"cancelled",$F$2:$F$98,"<"&F58)=0),1,0) -> 0
A59: EVT058 | B59: SUB033 | C59: CUST033 | D59: Ottawa Retail Solutions | E59: Eastern Canada | F59: 45717 | G59: 45747 | H59: created | M59: Marketing Pro | N59: Monthly | O59: 25 | P59: 85 | Q59: 0 | R59: {=_xlfn.IFS(H59="created", "New", H59="cancelled", "Churned", AND(H59="seats_change", J59 > I59), "Expansion", AND(H59="seats_change", J59 < I59), "Contraction", AND(H59="price_change", J59 > I59), "Expansion", AND(H59="price_change", J59 < I59), "Contraction", H59="plan_upgrade", "Expansion", H59="plan_downgrade", "Contraction", H59="discount_added", "Contraction")} -> New | S59: {=IF(N59="Monthly",_xlfn.IFS(H59="created",O59*P59*(1-Q59/100),H59="cancelled",-(O59*P59*(1-Q59/100)),H59="seats_change",(J59-I59)*P59*(1-Q59/100),H59="price_change",(J59-I59)*O59*(1-Q59/100),H59="discount_added",-(O59*P59*(J59-I59)/100),H59="plan_upgrade",O59*(_xlfn.XLOOKUP(J59,$M:$M,$P:$P)-_xlfn.XLOOKUP(I59,$M:$M,$P:$P))*(1-Q59/100),H59="plan_downgrade",O59*(_xlfn.XLOOKUP(J59,$M:$M,$P:$P)-_xlfn.XLOOKUP(I59,$M:$M,$P:$P))*(1-Q59/100)),_xlfn.IFS(H59="created",O59*P59*(1-Q59/100)/12,H59="cancelled",-(O59*P59*(1-Q59/100))/12,H59="seats_change",(J59-I59)*P59*(1-Q59/100)/12,H59="price_change",(J59-I59)*O59*(1-Q59/100)/12,H59="plan_upgrade",(O59*(_xlfn.XLOOKUP(J59,$M:$M,$P:$P)-_xlfn.XLOOKUP(I59,$M:$M,$P:$P))*(1-Q59/100))/12,H59="plan_downgrade",(O59*(_xlfn.XLOOKUP(J59,$M:$M,$P:$P)-_xlfn.XLOOKUP(I59,$M:$M,$P:$P))*(1-Q59/100))/12,H59="discount_added",-(O59*P59*(J59-I59)/100)/12))} -> 2125 | T59: =IF(H59<>"created",0,IF(COUNTIFS($C$1:C58,$C59,$H$1:H58,"created")=0,1,0)) -> 1 | U59: =IF(H59<>"cancelled",0,IF(COUNTIFS($C$2:$C$98,$C59,$H$2:$H$98,"created",$F$2:$F$98,"<="&F59)-COUNTIFS($C$2:$C$98,$C59,$H$2:$H$98,"cancelled",$F$2:$F$98,"<="&F59)=0,1,0)) -> 0 | V59: =IF(AND(H59="created",T59=0,COUNTIFS($C$2:$C$98,$C59,$H$2:$H$98,"cancelled",$F$2:$F$98,"<"&F59)>0,COUNTIFS($C$2:$C$98,$C59,$H$2:$H$98,"created",$F$2:$F$98,"<"&F59)-COUNTIFS($C$2:$C$98,$C59,$H$2:$H$98,"cancelled",$F$2:$F$98,"<"&F59)=0),1,0) -> 0
A60: EVT059 | B60: SUB027 | C60: CUST027 | D60: Pacific Finance Corp | E60: Western Canada | F60: 45748 | G60: 45753 | H60: price_change | I60: 100 | J60: 110 | K60: price_per_seat | L60: Annual price increase applied at renewal | M60: Sales Hub | N60: Monthly | O60: 28 | P60: 110 | Q60: 0 | R60: {=_xlfn.IFS(H60="created", "New", H60="cancelled", "Churned", AND(H60="seats_change", J60 > I60), "Expansion", AND(H60="seats_change", J60 < I60), "Contraction", AND(H60="price_change", J60 > I60), "Expansion", AND(H60="price_change", J60 < I60), "Contraction", H60="plan_upgrade", "Expansion", H60="plan_downgrade", "Contraction", H60="discount_added", "Contraction")} -> Expansion | S60: {=IF(N60="Monthly",_xlfn.IFS(H60="created",O60*P60*(1-Q60/100),H60="cancelled",-(O60*P60*(1-Q60/100)),H60="seats_change",(J60-I60)*P60*(1-Q60/100),H60="price_change",(J60-I60)*O60*(1-Q60/100),H60="discount_added",-(O60*P60*(J60-I60)/100),H60="plan_upgrade",O60*(_xlfn.XLOOKUP(J60,$M:$M,$P:$P)-_xlfn.XLOOKUP(I60,$M:$M,$P:$P))*(1-Q60/100),H60="plan_downgrade",O60*(_xlfn.XLOOKUP(J60,$M:$M,$P:$P)-_xlfn.XLOOKUP(I60,$M:$M,$P:$P))*(1-Q60/100)),_xlfn.IFS(H60="created",O60*P60*(1-Q60/100)/12,H60="cancelled",-(O60*P60*(1-Q60/100))/12,H60="seats_change",(J60-I60)*P60*(1-Q60/100)/12,H60="price_change",(J60-I60)*O60*(1-Q60/100)/12,H60="plan_upgrade",(O60*(_xlfn.XLOOKUP(J60,$M:$M,$P:$P)-_xlfn.XLOOKUP(I60,$M:$M,$P:$P))*(1-Q60/100))/12,H60="plan_downgrade",(O60*(_xlfn.XLOOKUP(J60,$M:$M,$P:$P)-_xlfn.XLOOKUP(I60,$M:$M,$P:$P))*(1-Q60/100))/12,H60="discount_added",-(O60*P60*(J60-I60)/100)/12))} -> 280 | T60: =IF(H60<>"created",0,IF(COUNTIFS($C$1:C59,$C60,$H$1:H59,"created")=0,1,0)) -> 0 | U60: =IF(H60<>"cancelled",0,IF(COUNTIFS($C$2:$C$98,$C60,$H$2:$H$98,"created",$F$2:$F$98,"<="&F60)-COUNTIFS($C$2:$C$98,$C60,$H$2:$H$98,"cancelled",$F$2:$F$98,"<="&F60)=0,1,0)) -> 0 | V60: =IF(AND(H60="created",T60=0,COUNTIFS($C$2:$C$98,$C60,$H$2:$H$98,"cancelled",$F$2:$F$98,"<"&F60)>0,COUNTIFS($C$2:$C$98,$C60,$H$2:$H$98,"created",$F$2:$F$98,"<"&F60)-COUNTIFS($C$2:$C$98,$C60,$H$2:$H$98,"cancelled",$F$2:$F$98,"<"&F60)=0),1,0) -> 0
A61: EVT060 | B61: SUB034 | C61: CUST034 | D61: Quebec Education Platform | E61: Eastern Canada | F61: 45748 | G61: 45761 | H61: created | M61: Analytics Starter | N61: Monthly | O61: 16 | P61: 45 | Q61: 0 | R61: {=_xlfn.IFS(H61="created", "New", H61="cancelled", "Churned", AND(H61="seats_change", J61 > I61), "Expansion", AND(H61="seats_change", J61 < I61), "Contraction", AND(H61="price_change", J61 > I61), "Expansion", AND(H61="price_change", J61 < I61), "Contraction", H61="plan_upgrade", "Expansion", H61="plan_downgrade", "Contraction", H61="discount_added", "Contraction")} -> New | S61: {=IF(N61="Monthly",_xlfn.IFS(H61="created",O61*P61*(1-Q61/100),H61="cancelled",-(O61*P61*(1-Q61/100)),H61="seats_change",(J61-I61)*P61*(1-Q61/100),H61="price_change",(J61-I61)*O61*(1-Q61/100),H61="discount_added",-(O61*P61*(J61-I61)/100),H61="plan_upgrade",O61*(_xlfn.XLOOKUP(J61,$M:$M,$P:$P)-_xlfn.XLOOKUP(I61,$M:$M,$P:$P))*(1-Q61/100),H61="plan_downgrade",O61*(_xlfn.XLOOKUP(J61,$M:$M,$P:$P)-_xlfn.XLOOKUP(I61,$M:$M,$P:$P))*(1-Q61/100)),_xlfn.IFS(H61="created",O61*P61*(1-Q61/100)/12,H61="cancelled",-(O61*P61*(1-Q61/100))/12,H61="seats_change",(J61-I61)*P61*(1-Q61/100)/12,H61="price_change",(J61-I61)*O61*(1-Q61/100)/12,H61="plan_upgrade",(O61*(_xlfn.XLOOKUP(J61,$M:$M,$P:$P)-_xlfn.XLOOKUP(I61,$M:$M,$P:$P))*(1-Q61/100))/12,H61="plan_downgrade",(O61*(_xlfn.XLOOKUP(J61,$M:$M,$P:$P)-_xlfn.XLOOKUP(I61,$M:$M,$P:$P))*(1-Q61/100))/12,H61="discount_added",-(O61*P61*(J61-I61)/100)/12))} -> 720 | T61: =IF(H61<>"created",0,IF(COUNTIFS($C$1:C60,$C61,$H$1:H60,"created")=0,1,0)) -> 1 | U61: =IF(H61<>"cancelled",0,IF(COUNTIFS($C$2:$C$98,$C61,$H$2:$H$98,"created",$F$2:$F$98,"<="&F61)-COUNTIFS($C$2:$C$98,$C61,$H$2:$H$98,"cancelled",$F$2:$F$98,"<="&F61)=0,1,0)) -> 0 | V61: =IF(AND(H61="created",T61=0,COUNTIFS($C$2:$C$98,$C61,$H$2:$H$98,"cancelled",$F$2:$F$98,"<"&F61)>0,COUNTIFS($C$2:$C$98,$C61,$H$2:$H$98,"created",$F$2:$F$98,"<"&F61)-COUNTIFS($C$2:$C$98,$C61,$H$2:$H$98,"cancelled",$F$2:$F$98,"<"&F61)=0),1,0) -> 0
A62: EVT061 | B62: SUB012 | C62: CUST012 | D62: Maritime E-commerce | E62: Eastern Canada | F62: 45748 | G62: 45762 | H62: seats_change | I62: 18 | J62: 23 | K62: seats | L62: New hires onboarded - sales team expansion | M62: Analytics Growth | N62: Monthly | O62: 23 | P62: 95 | Q62: 0 | R62: {=_xlfn.IFS(H62="created", "New", H62="cancelled", "Churned", AND(H62="seats_change", J62 > I62), "Expansion", AND(H62="seats_change", J62 < I62), "Contraction", AND(H62="price_change", J62 > I62), "Expansion", AND(H62="price_change", J62 < I62), "Contraction", H62="plan_upgrade", "Expansion", H62="plan_downgrade", "Contraction", H62="discount_added", "Contraction")} -> Expansion | S62: {=IF(N62="Monthly",_xlfn.IFS(H62="created",O62*P62*(1-Q62/100),H62="cancelled",-(O62*P62*(1-Q62/100)),H62="seats_change",(J62-I62)*P62*(1-Q62/100),H62="price_change",(J62-I62)*O62*(1-Q62/100),H62="discount_added",-(O62*P62*(J62-I62)/100),H62="plan_upgrade",O62*(_xlfn.XLOOKUP(J62,$M:$M,$P:$P)-_xlfn.XLOOKUP(I62,$M:$M,$P:$P))*(1-Q62/100),H62="plan_downgrade",O62*(_xlfn.XLOOKUP(J62,$M:$M,$P:$P)-_xlfn.XLOOKUP(I62,$M:$M,$P:$P))*(1-Q62/100)),_xlfn.IFS(H62="created",O62*P62*(1-Q62/100)/12,H62="cancelled",-(O62*P62*(1-Q62/100))/12,H62="seats_change",(J62-I62)*P62*(1-Q62/100)/12,H62="price_change",(J62-I62)*O62*(1-Q62/100)/12,H62="plan_upgrade",(O62*(_xlfn.XLOOKUP(J62,$M:$M,$P:$P)-_xlfn.XLOOKUP(I62,$M:$M,$P:$P))*(1-Q62/100))/12,H62="plan_downgrade",(O62*(_xlfn.XLOOKUP(J62,$M:$M,$P:$P)-_xlfn.XLOOKUP(I62,$M:$M,$P:$P))*(1-Q62/100))/12,H62="discount_added",-(O62*P62*(J62-I62)/100)/12))} -> 475 | T62: =IF(H62<>"created",0,IF(COUNTIFS($C$1:C61,$C62,$H$1:H61,"created")=0,1,0)) -> 0 | U62: =IF(H62<>"cancelled",0,IF(COUNTIFS($C$2:$C$98,$C62,$H$2:$H$98,"created",$F$2:$F$98,"<="&F62)-COUNTIFS($C$2:$C$98,$C62,$H$2:$H$98,"cancelled",$F$2:$F$98,"<="&F62)=0,1,0)) -> 0 | V62: =IF(AND(H62="created",T62=0,COUNTIFS($C$2:$C$98,$C62,$H$2:$H$98,"cancelled",$F$2:$F$98,"<"&F62)>0,COUNTIFS($C$2:$C$98,$C62,$H$2:$H$98,"created",$F$2:$F$98,"<"&F62)-COUNTIFS($C$2:$C$98,$C62,$H$2:$H$98,"cancelled",$F$2:$F$98,"<"&F62)=0),1,0) -> 0
A63: EVT062 | B63: SUB047 | C63: CUST022 | D63: Toronto Tech Ventures | E63: Eastern Canada | F63: 45748 | G63: 45765 | H63: created | M63: Sales Hub | N63: Monthly | O63: 26 | P63: 110 | Q63: 0 | R63: {=_xlfn.IFS(H63="created", "New", H63="cancelled", "Churned", AND(H63="seats_change", J63 > I63), "Expansion", AND(H63="seats_change", J63 < I63), "Contraction", AND(H63="price_change", J63 > I63), "Expansion", AND(H63="price_change", J63 < I63), "Contraction", H63="plan_upgrade", "Expansion", H63="plan_downgrade", "Contraction", H63="discount_added", "Contraction")} -> New | S63: {=IF(N63="Monthly",_xlfn.IFS(H63="created",O63*P63*(1-Q63/100),H63="cancelled",-(O63*P63*(1-Q63/100)),H63="seats_change",(J63-I63)*P63*(1-Q63/100),H63="price_change",(J63-I63)*O63*(1-Q63/100),H63="discount_added",-(O63*P63*(J63-I63)/100),H63="plan_upgrade",O63*(_xlfn.XLOOKUP(J63,$M:$M,$P:$P)-_xlfn.XLOOKUP(I63,$M:$M,$P:$P))*(1-Q63/100),H63="plan_downgrade",O63*(_xlfn.XLOOKUP(J63,$M:$M,$P:$P)-_xlfn.XLOOKUP(I63,$M:$M,$P:$P))*(1-Q63/100)),_xlfn.IFS(H63="created",O63*P63*(1-Q63/100)/12,H63="cancelled",-(O63*P63*(1-Q63/100))/12,H63="seats_change",(J63-I63)*P63*(1-Q63/100)/12,H63="price_change",(J63-I63)*O63*(1-Q63/100)/12,H63="plan_upgrade",(O63*(_xlfn.XLOOKUP(J63,$M:$M,$P:$P)-_xlfn.XLOOKUP(I63,$M:$M,$P:$P))*(1-Q63/100))/12,H63="plan_downgrade",(O63*(_xlfn.XLOOKUP(J63,$M:$M,$P:$P)-_xlfn.XLOOKUP(I63,$M:$M,$P:$P))*(1-Q63/100))/12,H63="discount_added",-(O63*P63*(J63-I63)/100)/12))} -> 2860 | T63: =IF(H63<>"created",0,IF(COUNTIFS($C$1:C62,$C63,$H$1:H62,"created")=0,1,0)) -> 0 | U63: =IF(H63<>"cancelled",0,IF(COUNTIFS($C$2:$C$98,$C63,$H$2:$H$98,"created",$F$2:$F$98,"<="&F63)-COUNTIFS($C$2:$C$98,$C63,$H$2:$H$98,"cancelled",$F$2:$F$98,"<="&F63)=0,1,0)) -> 0 | V63: =IF(AND(H63="created",T63=0,COUNTIFS($C$2:$C$98,$C63,$H$2:$H$98,"cancelled",$F$2:$F$98,"<"&F63)>0,COUNTIFS($C$2:$C$98,$C63,$H$2:$H$98,"created",$F$2:$F$98,"<"&F63)-COUNTIFS($C$2:$C$98,$C63,$H$2:$H$98,"cancelled",$F$2:$F$98,"<"&F63)=0),1,0) -> 0
A64: EVT063 | B64: SUB035 | C64: CUST035 | D64: Vancouver Health Systems | E64: Western Canada | F64: 45748 | G64: 45775 | H64: created | M64: Sales Hub | N64: Monthly | O64: 20 | P64: 110 | Q64: 0 | R64: {=_xlfn.IFS(H64="created", "New", H64="cancelled", "Churned", AND(H64="seats_change", J64 > I64), "Expansion", AND(H64="seats_change", J64 < I64), "Contraction", AND(H64="price_change", J64 > I64), "Expansion", AND(H64="price_change", J64 < I64), "Contraction", H64="plan_upgrade", "Expansion", H64="plan_downgrade", "Contraction", H64="discount_added", "Contraction")} -> New | S64: {=IF(N64="Monthly",_xlfn.IFS(H64="created",O64*P64*(1-Q64/100),H64="cancelled",-(O64*P64*(1-Q64/100)),H64="seats_change",(J64-I64)*P64*(1-Q64/100),H64="price_change",(J64-I64)*O64*(1-Q64/100),H64="discount_added",-(O64*P64*(J64-I64)/100),H64="plan_upgrade",O64*(_xlfn.XLOOKUP(J64,$M:$M,$P:$P)-_xlfn.XLOOKUP(I64,$M:$M,$P:$P))*(1-Q64/100),H64="plan_downgrade",O64*(_xlfn.XLOOKUP(J64,$M:$M,$P:$P)-_xlfn.XLOOKUP(I64,$M:$M,$P:$P))*(1-Q64/100)),_xlfn.IFS(H64="created",O64*P64*(1-Q64/100)/12,H64="cancelled",-(O64*P64*(1-Q64/100))/12,H64="seats_change",(J64-I64)*P64*(1-Q64/100)/12,H64="price_change",(J64-I64)*O64*(1-Q64/100)/12,H64="plan_upgrade",(O64*(_xlfn.XLOOKUP(J64,$M:$M,$P:$P)-_xlfn.XLOOKUP(I64,$M:$M,$P:$P))*(1-Q64/100))/12,H64="plan_downgrade",(O64*(_xlfn.XLOOKUP(J64,$M:$M,$P:$P)-_xlfn.XLOOKUP(I64,$M:$M,$P:$P))*(1-Q64/100))/12,H64="discount_added",-(O64*P64*(J64-I64)/100)/12))} -> 2200 | T64: =IF(H64<>"created",0,IF(COUNTIFS($C$1:C63,$C64,$H$1:H63,"created")=0,1,0)) -> 1 | U64: =IF(H64<>"cancelled",0,IF(COUNTIFS($C$2:$C$98,$C64,$H$2:$H$98,"created",$F$2:$F$98,"<="&F64)-COUNTIFS($C$2:$C$98,$C64,$H$2:$H$98,"cancelled",$F$2:$F$98,"<="&F64)=0,1,0)) -> 0 | V64: =IF(AND(H64="created",T64=0,COUNTIFS($C$2:$C$98,$C64,$H$2:$H$98,"cancelled",$F$2:$F$98,"<"&F64)>0,COUNTIFS($C$2:$C$98,$C64,$H$2:$H$98,"created",$F$2:$F$98,"<"&F64)-COUNTIFS($C$2:$C$98,$C64,$H$2:$H$98,"cancelled",$F$2:$F$98,"<"&F64)=0),1,0) -> 0
A65: EVT064 | B65: SUB004 | C65: CUST004 | D65: Prairie Commerce Group | E65: Western Canada | F65: 45778 | G65: 45787 | H65: seats_change | I65: 15 | J65: 18 | K65: seats | L65: Team expansion - 3 new account managers onboarded | M65: Sales Hub | N65: Monthly | O65: 18 | P65: 110 | Q65: 0 | R65: {=_xlfn.IFS(H65="created", "New", H65="cancelled", "Churned", AND(H65="seats_change", J65 > I65), "Expansion", AND(H65="seats_change", J65 < I65), "Contraction", AND(H65="price_change", J65 > I65), "Expansion", AND(H65="price_change", J65 < I65), "Contraction", H65="plan_upgrade", "Expansion", H65="plan_downgrade", "Contraction", H65="discount_added", "Contraction")} -> Expansion | S65: {=IF(N65="Monthly",_xlfn.IFS(H65="created",O65*P65*(1-Q65/100),H65="cancelled",-(O65*P65*(1-Q65/100)),H65="seats_change",(J65-I65)*P65*(1-Q65/100),H65="price_change",(J65-I65)*O65*(1-Q65/100),H65="discount_added",-(O65*P65*(J65-I65)/100),H65="plan_upgrade",O65*(_xlfn.XLOOKUP(J65,$M:$M,$P:$P)-_xlfn.XLOOKUP(I65,$M:$M,$P:$P))*(1-Q65/100),H65="plan_downgrade",O65*(_xlfn.XLOOKUP(J65,$M:$M,$P:$P)-_xlfn.XLOOKUP(I65,$M:$M,$P:$P))*(1-Q65/100)),_xlfn.IFS(H65="created",O65*P65*(1-Q65/100)/12,H65="cancelled",-(O65*P65*(1-Q65/100))/12,H65="seats_change",(J65-I65)*P65*(1-Q65/100)/12,H65="price_change",(J65-I65)*O65*(1-Q65/100)/12,H65="plan_upgrade",(O65*(_xlfn.XLOOKUP(J65,$M:$M,$P:$P)-_xlfn.XLOOKUP(I65,$M:$M,$P:$P))*(1-Q65/100))/12,H65="plan_downgrade",(O65*(_xlfn.XLOOKUP(J65,$M:$M,$P:$P)-_xlfn.XLOOKUP(I65,$M:$M,$P:$P))*(1-Q65/100))/12,H65="discount_added",-(O65*P65*(J65-I65)/100)/12))} -> 330 | T65: =IF(H65<>"created",0,IF(COUNTIFS($C$1:C64,$C65,$H$1:H64,"created")=0,1,0)) -> 0 | U65: =IF(H65<>"cancelled",0,IF(COUNTIFS($C$2:$C$98,$C65,$H$2:$H$98,"created",$F$2:$F$98,"<="&F65)-COUNTIFS($C$2:$C$98,$C65,$H$2:$H$98,"cancelled",$F$2:$F$98,"<="&F65)=0,1,0)) -> 0 | V65: =IF(AND(H65="created",T65=0,COUNTIFS($C$2:$C$98,$C65,$H$2:$H$98,"cancelled",$F$2:$F$98,"<"&F65)>0,COUNTIFS($C$2:$C$98,$C65,$H$2:$H$98,"created",$F$2:$F$98,"<"&F65)-COUNTIFS($C$2:$C$98,$C65,$H$2:$H$98,"cancelled",$F$2:$F$98,"<"&F65)=0),1,0) -> 0
A66: EVT065 | B66: SUB036 | C66: CUST036 | D66: Manitoba Finance Group | E66: Central Canada | F66: 45778 | G66: 45789 | H66: created | M66: Analytics Growth | N66: Monthly | O66: 18 | P66: 95 | Q66: 0 | R66: {=_xlfn.IFS(H66="created", "New", H66="cancelled", "Churned", AND(H66="seats_change", J66 > I66), "Expansion", AND(H66="seats_change", J66 < I66), "Contraction", AND(H66="price_change", J66 > I66), "Expansion", AND(H66="price_change", J66 < I66), "Contraction", H66="plan_upgrade", "Expansion", H66="plan_downgrade", "Contraction", H66="discount_added", "Contraction")} -> New | S66: {=IF(N66="Monthly",_xlfn.IFS(H66="created",O66*P66*(1-Q66/100),H66="cancelled",-(O66*P66*(1-Q66/100)),H66="seats_change",(J66-I66)*P66*(1-Q66/100),H66="price_change",(J66-I66)*O66*(1-Q66/100),H66="discount_added",-(O66*P66*(J66-I66)/100),H66="plan_upgrade",O66*(_xlfn.XLOOKUP(J66,$M:$M,$P:$P)-_xlfn.XLOOKUP(I66,$M:$M,$P:$P))*(1-Q66/100),H66="plan_downgrade",O66*(_xlfn.XLOOKUP(J66,$M:$M,$P:$P)-_xlfn.XLOOKUP(I66,$M:$M,$P:$P))*(1-Q66/100)),_xlfn.IFS(H66="created",O66*P66*(1-Q66/100)/12,H66="cancelled",-(O66*P66*(1-Q66/100))/12,H66="seats_change",(J66-I66)*P66*(1-Q66/100)/12,H66="price_change",(J66-I66)*O66*(1-Q66/100)/12,H66="plan_upgrade",(O66*(_xlfn.XLOOKUP(J66,$M:$M,$P:$P)-_xlfn.XLOOKUP(I66,$M:$M,$P:$P))*(1-Q66/100))/12,H66="plan_downgrade",(O66*(_xlfn.XLOOKUP(J66,$M:$M,$P:$P)-_xlfn.XLOOKUP(I66,$M:$M,$P:$P))*(1-Q66/100))/12,H66="discount_added",-(O66*P66*(J66-I66)/100)/12))} -> 1710 | T66: =IF(H66<>"created",0,IF(COUNTIFS($C$1:C65,$C66,$H$1:H65,"created")=0,1,0)) -> 1 | U66: =IF(H66<>"cancelled",0,IF(COUNTIFS($C$2:$C$98,$C66,$H$2:$H$98,"created",$F$2:$F$98,"<="&F66)-COUNTIFS($C$2:$C$98,$C66,$H$2:$H$98,"cancelled",$F$2:$F$98,"<="&F66)=0,1,0)) -> 0 | V66: =IF(AND(H66="created",T66=0,COUNTIFS($C$2:$C$98,$C66,$H$2:$H$98,"cancelled",$F$2:$F$98,"<"&F66)>0,COUNTIFS($C$2:$C$98,$C66,$H$2:$H$98,"created",$F$2:$F$98,"<"&F66)-COUNTIFS($C$2:$C$98,$C66,$H$2:$H$98,"cancelled",$F$2:$F$98,"<"&F66)=0),1,0) -> 0
A67: EVT066 | B67: SUB061 | C67: CUST013 | D67: Alberta Tech Innovators | E67: Western Canada | F67: 45778 | G67: 45797 | H67: created | L67: Returning customer â€” reactivation | M67: Analytics Growth | N67: Monthly | O67: 12 | P67: 95 | Q67: 0 | R67: {=_xlfn.IFS(H67="created", "New", H67="cancelled", "Churned", AND(H67="seats_change", J67 > I67), "Expansion", AND(H67="seats_change", J67 < I67), "Contraction", AND(H67="price_change", J67 > I67), "Expansion", AND(H67="price_change", J67 < I67), "Contraction", H67="plan_upgrade", "Expansion", H67="plan_downgrade", "Contraction", H67="discount_added", "Contraction")} -> New | S67: {=IF(N67="Monthly",_xlfn.IFS(H67="created",O67*P67*(1-Q67/100),H67="cancelled",-(O67*P67*(1-Q67/100)),H67="seats_change",(J67-I67)*P67*(1-Q67/100),H67="price_change",(J67-I67)*O67*(1-Q67/100),H67="discount_added",-(O67*P67*(J67-I67)/100),H67="plan_upgrade",O67*(_xlfn.XLOOKUP(J67,$M:$M,$P:$P)-_xlfn.XLOOKUP(I67,$M:$M,$P:$P))*(1-Q67/100),H67="plan_downgrade",O67*(_xlfn.XLOOKUP(J67,$M:$M,$P:$P)-_xlfn.XLOOKUP(I67,$M:$M,$P:$P))*(1-Q67/100)),_xlfn.IFS(H67="created",O67*P67*(1-Q67/100)/12,H67="cancelled",-(O67*P67*(1-Q67/100))/12,H67="seats_change",(J67-I67)*P67*(1-Q67/100)/12,H67="price_change",(J67-I67)*O67*(1-Q67/100)/12,H67="plan_upgrade",(O67*(_xlfn.XLOOKUP(J67,$M:$M,$P:$P)-_xlfn.XLOOKUP(I67,$M:$M,$P:$P))*(1-Q67/100))/12,H67="plan_downgrade",(O67*(_xlfn.XLOOKUP(J67,$M:$M,$P:$P)-_xlfn.XLOOKUP(I67,$M:$M,$P:$P))*(1-Q67/100))/12,H67="discount_added",-(O67*P67*(J67-I67)/100)/12))} -> 1140 | T67: =IF(H67<>"created",0,IF(COUNTIFS($C$1:C66,$C67,$H$1:H66,"created")=0,1,0)) -> 0 | U67: =IF(H67<>"cancelled",0,IF(COUNTIFS($C$2:$C$98,$C67,$H$2:$H$98,"created",$F$2:$F$98,"<="&F67)-COUNTIFS($C$2:$C$98,$C67,$H$2:$H$98,"cancelled",$F$2:$F$98,"<="&F67)=0,1,0)) -> 0 | V67: =IF(AND(H67="created",T67=0,COUNTIFS($C$2:$C$98,$C67,$H$2:$H$98,"cancelled",$F$2:$F$98,"<"&F67)>0,COUNTIFS($C$2:$C$98,$C67,$H$2:$H$98,"created",$F$2:$F$98,"<"&F67)-COUNTIFS($C$2:$C$98,$C67,$H$2:$H$98,"cancelled",$F$2:$F$98,"<"&F67)=0),1,0) -> 1
A68: EVT067 | B68: SUB048 | C68: CUST025 | D68: Montreal Manufacturing Pro | E68: Eastern Canada | F68: 45778 | G68: 45799 | H68: created | M68: Sales Hub | N68: Monthly | O68: 36 | P68: 110 | Q68: 0 | R68: {=_xlfn.IFS(H68="created", "New", H68="cancelled", "Churned", AND(H68="seats_change", J68 > I68), "Expansion", AND(H68="seats_change", J68 < I68), "Contraction", AND(H68="price_change", J68 > I68), "Expansion", AND(H68="price_change", J68 < I68), "Contraction", H68="plan_upgrade", "Expansion", H68="plan_downgrade", "Contraction", H68="discount_added", "Contraction")} -> New | S68: {=IF(N68="Monthly",_xlfn.IFS(H68="created",O68*P68*(1-Q68/100),H68="cancelled",-(O68*P68*(1-Q68/100)),H68="seats_change",(J68-I68)*P68*(1-Q68/100),H68="price_change",(J68-I68)*O68*(1-Q68/100),H68="discount_added",-(O68*P68*(J68-I68)/100),H68="plan_upgrade",O68*(_xlfn.XLOOKUP(J68,$M:$M,$P:$P)-_xlfn.XLOOKUP(I68,$M:$M,$P:$P))*(1-Q68/100),H68="plan_downgrade",O68*(_xlfn.XLOOKUP(J68,$M:$M,$P:$P)-_xlfn.XLOOKUP(I68,$M:$M,$P:$P))*(1-Q68/100)),_xlfn.IFS(H68="created",O68*P68*(1-Q68/100)/12,H68="cancelled",-(O68*P68*(1-Q68/100))/12,H68="seats_change",(J68-I68)*P68*(1-Q68/100)/12,H68="price_change",(J68-I68)*O68*(1-Q68/100)/12,H68="plan_upgrade",(O68*(_xlfn.XLOOKUP(J68,$M:$M,$P:$P)-_xlfn.XLOOKUP(I68,$M:$M,$P:$P))*(1-Q68/100))/12,H68="plan_downgrade",(O68*(_xlfn.XLOOKUP(J68,$M:$M,$P:$P)-_xlfn.XLOOKUP(I68,$M:$M,$P:$P))*(1-Q68/100))/12,H68="discount_added",-(O68*P68*(J68-I68)/100)/12))} -> 3960 | T68: =IF(H68<>"created",0,IF(COUNTIFS($C$1:C67,$C68,$H$1:H67,"created")=0,1,0)) -> 0 | U68: =IF(H68<>"cancelled",0,IF(COUNTIFS($C$2:$C$98,$C68,$H$2:$H$98,"created",$F$2:$F$98,"<="&F68)-COUNTIFS($C$2:$C$98,$C68,$H$2:$H$98,"cancelled",$F$2:$F$98,"<="&F68)=0,1,0)) -> 0 | V68: =IF(AND(H68="created",T68=0,COUNTIFS($C$2:$C$98,$C68,$H$2:$H$98,"cancelled",$F$2:$F$98,"<"&F68)>0,COUNTIFS($C$2:$C$98,$C68,$H$2:$H$98,"created",$F$2:$F$98,"<"&F68)-COUNTIFS($C$2:$C$98,$C68,$H$2:$H$98,"cancelled",$F$2:$F$98,"<"&F68)=0),1,0) -> 0
A69: EVT068 | B69: SUB021 | C69: CUST021 | D69: Calgary Commerce Solutions | E69: Western Canada | F69: 45778 | G69: 45803 | H69: cancelled | I69: active | J69: churned | K69: status | L69: Company downsizing | M69: Analytics Growth | N69: Monthly | O69: 25 | P69: 95 | Q69: 0 | R69: {=_xlfn.IFS(H69="created", "New", H69="cancelled", "Churned", AND(H69="seats_change", J69 > I69), "Expansion", AND(H69="seats_change", J69 < I69), "Contraction", AND(H69="price_change", J69 > I69), "Expansion", AND(H69="price_change", J69 < I69), "Contraction", H69="plan_upgrade", "Expansion", H69="plan_downgrade", "Contraction", H69="discount_added", "Contraction")} -> Churned | S69: {=IF(N69="Monthly",_xlfn.IFS(H69="created",O69*P69*(1-Q69/100),H69="cancelled",-(O69*P69*(1-Q69/100)),H69="seats_change",(J69-I69)*P69*(1-Q69/100),H69="price_change",(J69-I69)*O69*(1-Q69/100),H69="discount_added",-(O69*P69*(J69-I69)/100),H69="plan_upgrade",O69*(_xlfn.XLOOKUP(J69,$M:$M,$P:$P)-_xlfn.XLOOKUP(I69,$M:$M,$P:$P))*(1-Q69/100),H69="plan_downgrade",O69*(_xlfn.XLOOKUP(J69,$M:$M,$P:$P)-_xlfn.XLOOKUP(I69,$M:$M,$P:$P))*(1-Q69/100)),_xlfn.IFS(H69="created",O69*P69*(1-Q69/100)/12,H69="cancelled",-(O69*P69*(1-Q69/100))/12,H69="seats_change",(J69-I69)*P69*(1-Q69/100)/12,H69="price_change",(J69-I69)*O69*(1-Q69/100)/12,H69="plan_upgrade",(O69*(_xlfn.XLOOKUP(J69,$M:$M,$P:$P)-_xlfn.XLOOKUP(I69,$M:$M,$P:$P))*(1-Q69/100))/12,H69="plan_downgrade",(O69*(_xlfn.XLOOKUP(J69,$M:$M,$P:$P)-_xlfn.XLOOKUP(I69,$M:$M,$P:$P))*(1-Q69/100))/12,H69="discount_added",-(O69*P69*(J69-I69)/100)/12))} -> -2375 | T69: =IF(H69<>"created",0,IF(COUNTIFS($C$1:C68,$C69,$H$1:H68,"created")=0,1,0)) -> 0 | U69: =IF(H69<>"cancelled",0,IF(COUNTIFS($C$2:$C$98,$C69,$H$2:$H$98,"created",$F$2:$F$98,"<="&F69)-COUNTIFS($C$2:$C$98,$C69,$H$2:$H$98,"cancelled",$F$2:$F$98,"<="&F69)=0,1,0)) -> 0 | V69: =IF(AND(H69="created",T69=0,COUNTIFS($C$2:$C$98,$C69,$H$2:$H$98,"cancelled",$F$2:$F$98,"<"&F69)>0,COUNTIFS($C$2:$C$98,$C69,$H$2:$H$98,"created",$F$2:$F$98,"<"&F69)-COUNTIFS($C$2:$C$98,$C69,$H$2:$H$98,"cancelled",$F$2:$F$98,"<"&F69)=0),1,0) -> 0
A70: EVT069 | B70: SUB037 | C70: CUST037 | D70: Maritime SaaS Ventures | E70: Eastern Canada | F70: 45778 | G70: 45803 | H70: created | M70: Platform Suite | N70: Monthly | O70: 35 | P70: 150 | Q70: 0 | R70: {=_xlfn.IFS(H70="created", "New", H70="cancelled", "Churned", AND(H70="seats_change", J70 > I70), "Expansion", AND(H70="seats_change", J70 < I70), "Contraction", AND(H70="price_change", J70 > I70), "Expansion", AND(H70="price_change", J70 < I70), "Contraction", H70="plan_upgrade", "Expansion", H70="plan_downgrade", "Contraction", H70="discount_added", "Contraction")} -> New | S70: {=IF(N70="Monthly",_xlfn.IFS(H70="created",O70*P70*(1-Q70/100),H70="cancelled",-(O70*P70*(1-Q70/100)),H70="seats_change",(J70-I70)*P70*(1-Q70/100),H70="price_change",(J70-I70)*O70*(1-Q70/100),H70="discount_added",-(O70*P70*(J70-I70)/100),H70="plan_upgrade",O70*(_xlfn.XLOOKUP(J70,$M:$M,$P:$P)-_xlfn.XLOOKUP(I70,$M:$M,$P:$P))*(1-Q70/100),H70="plan_downgrade",O70*(_xlfn.XLOOKUP(J70,$M:$M,$P:$P)-_xlfn.XLOOKUP(I70,$M:$M,$P:$P))*(1-Q70/100)),_xlfn.IFS(H70="created",O70*P70*(1-Q70/100)/12,H70="cancelled",-(O70*P70*(1-Q70/100))/12,H70="seats_change",(J70-I70)*P70*(1-Q70/100)/12,H70="price_change",(J70-I70)*O70*(1-Q70/100)/12,H70="plan_upgrade",(O70*(_xlfn.XLOOKUP(J70,$M:$M,$P:$P)-_xlfn.XLOOKUP(I70,$M:$M,$P:$P))*(1-Q70/100))/12,H70="plan_downgrade",(O70*(_xlfn.XLOOKUP(J70,$M:$M,$P:$P)-_xlfn.XLOOKUP(I70,$M:$M,$P:$P))*(1-Q70/100))/12,H70="discount_added",-(O70*P70*(J70-I70)/100)/12))} -> 5250 | T70: =IF(H70<>"created",0,IF(COUNTIFS($C$1:C69,$C70,$H$1:H69,"created")=0,1,0)) -> 1 | U70: =IF(H70<>"cancelled",0,IF(COUNTIFS($C$2:$C$98,$C70,$H$2:$H$98,"created",$F$2:$F$98,"<="&F70)-COUNTIFS($C$2:$C$98,$C70,$H$2:$H$98,"cancelled",$F$2:$F$98,"<="&F70)=0,1,0)) -> 0 | V70: =IF(AND(H70="created",T70=0,COUNTIFS($C$2:$C$98,$C70,$H$2:$H$98,"cancelled",$F$2:$F$98,"<"&F70)>0,COUNTIFS($C$2:$C$98,$C70,$H$2:$H$98,"created",$F$2:$F$98,"<"&F70)-COUNTIFS($C$2:$C$98,$C70,$H$2:$H$98,"cancelled",$F$2:$F$98,"<"&F70)=0),1,0) -> 0
A71: EVT070 | B71: SUB018 | C71: CUST018 | D71: Vancouver FinTech Labs | E71: Western Canada | F71: 45809 | G71: 45809 | H71: seats_change | I71: 30 | J71: 35 | K71: seats | L71: Department growth - added analytics sub-team | M71: Analytics Enterprise | N71: Monthly | O71: 35 | P71: 180 | Q71: 0 | R71: {=_xlfn.IFS(H71="created", "New", H71="cancelled", "Churned", AND(H71="seats_change", J71 > I71), "Expansion", AND(H71="seats_change", J71 < I71), "Contraction", AND(H71="price_change", J71 > I71), "Expansion", AND(H71="price_change", J71 < I71), "Contraction", H71="plan_upgrade", "Expansion", H71="plan_downgrade", "Contraction", H71="discount_added", "Contraction")} -> Expansion | S71: {=IF(N71="Monthly",_xlfn.IFS(H71="created",O71*P71*(1-Q71/100),H71="cancelled",-(O71*P71*(1-Q71/100)),H71="seats_change",(J71-I71)*P71*(1-Q71/100),H71="price_change",(J71-I71)*O71*(1-Q71/100),H71="discount_added",-(O71*P71*(J71-I71)/100),H71="plan_upgrade",O71*(_xlfn.XLOOKUP(J71,$M:$M,$P:$P)-_xlfn.XLOOKUP(I71,$M:$M,$P:$P))*(1-Q71/100),H71="plan_downgrade",O71*(_xlfn.XLOOKUP(J71,$M:$M,$P:$P)-_xlfn.XLOOKUP(I71,$M:$M,$P:$P))*(1-Q71/100)),_xlfn.IFS(H71="created",O71*P71*(1-Q71/100)/12,H71="cancelled",-(O71*P71*(1-Q71/100))/12,H71="seats_change",(J71-I71)*P71*(1-Q71/100)/12,H71="price_change",(J71-I71)*O71*(1-Q71/100)/12,H71="plan_upgrade",(O71*(_xlfn.XLOOKUP(J71,$M:$M,$P:$P)-_xlfn.XLOOKUP(I71,$M:$M,$P:$P))*(1-Q71/100))/12,H71="plan_downgrade",(O71*(_xlfn.XLOOKUP(J71,$M:$M,$P:$P)-_xlfn.XLOOKUP(I71,$M:$M,$P:$P))*(1-Q71/100))/12,H71="discount_added",-(O71*P71*(J71-I71)/100)/12))} -> 900 | T71: =IF(H71<>"created",0,IF(COUNTIFS($C$1:C70,$C71,$H$1:H70,"created")=0,1,0)) -> 0 | U71: =IF(H71<>"cancelled",0,IF(COUNTIFS($C$2:$C$98,$C71,$H$2:$H$98,"created",$F$2:$F$98,"<="&F71)-COUNTIFS($C$2:$C$98,$C71,$H$2:$H$98,"cancelled",$F$2:$F$98,"<="&F71)=0,1,0)) -> 0 | V71: =IF(AND(H71="created",T71=0,COUNTIFS($C$2:$C$98,$C71,$H$2:$H$98,"cancelled",$F$2:$F$98,"<"&F71)>0,COUNTIFS($C$2:$C$98,$C71,$H$2:$H$98,"created",$F$2:$F$98,"<"&F71)-COUNTIFS($C$2:$C$98,$C71,$H$2:$H$98,"cancelled",$F$2:$F$98,"<"&F71)=0),1,0) -> 0
A72: EVT071 | B72: SUB053 | C72: CUST027 | D72: Pacific Finance Corp | E72: Western Canada | F72: 45809 | G72: 45813 | H72: created | M72: Analytics Enterprise | N72: Monthly | O72: 31 | P72: 180 | Q72: 0 | R72: {=_xlfn.IFS(H72="created", "New", H72="cancelled", "Churned", AND(H72="seats_change", J72 > I72), "Expansion", AND(H72="seats_change", J72 < I72), "Contraction", AND(H72="price_change", J72 > I72), "Expansion", AND(H72="price_change", J72 < I72), "Contraction", H72="plan_upgrade", "Expansion", H72="plan_downgrade", "Contraction", H72="discount_added", "Contraction")} -> New | S72: {=IF(N72="Monthly",_xlfn.IFS(H72="created",O72*P72*(1-Q72/100),H72="cancelled",-(O72*P72*(1-Q72/100)),H72="seats_change",(J72-I72)*P72*(1-Q72/100),H72="price_change",(J72-I72)*O72*(1-Q72/100),H72="discount_added",-(O72*P72*(J72-I72)/100),H72="plan_upgrade",O72*(_xlfn.XLOOKUP(J72,$M:$M,$P:$P)-_xlfn.XLOOKUP(I72,$M:$M,$P:$P))*(1-Q72/100),H72="plan_downgrade",O72*(_xlfn.XLOOKUP(J72,$M:$M,$P:$P)-_xlfn.XLOOKUP(I72,$M:$M,$P:$P))*(1-Q72/100)),_xlfn.IFS(H72="created",O72*P72*(1-Q72/100)/12,H72="cancelled",-(O72*P72*(1-Q72/100))/12,H72="seats_change",(J72-I72)*P72*(1-Q72/100)/12,H72="price_change",(J72-I72)*O72*(1-Q72/100)/12,H72="plan_upgrade",(O72*(_xlfn.XLOOKUP(J72,$M:$M,$P:$P)-_xlfn.XLOOKUP(I72,$M:$M,$P:$P))*(1-Q72/100))/12,H72="plan_downgrade",(O72*(_xlfn.XLOOKUP(J72,$M:$M,$P:$P)-_xlfn.XLOOKUP(I72,$M:$M,$P:$P))*(1-Q72/100))/12,H72="discount_added",-(O72*P72*(J72-I72)/100)/12))} -> 5580 | T72: =IF(H72<>"created",0,IF(COUNTIFS($C$1:C71,$C72,$H$1:H71,"created")=0,1,0)) -> 0 | U72: =IF(H72<>"cancelled",0,IF(COUNTIFS($C$2:$C$98,$C72,$H$2:$H$98,"created",$F$2:$F$98,"<="&F72)-COUNTIFS($C$2:$C$98,$C72,$H$2:$H$98,"cancelled",$F$2:$F$98,"<="&F72)=0,1,0)) -> 0 | V72: =IF(AND(H72="created",T72=0,COUNTIFS($C$2:$C$98,$C72,$H$2:$H$98,"cancelled",$F$2:$F$98,"<"&F72)>0,COUNTIFS($C$2:$C$98,$C72,$H$2:$H$98,"created",$F$2:$F$98,"<"&F72)-COUNTIFS($C$2:$C$98,$C72,$H$2:$H$98,"cancelled",$F$2:$F$98,"<"&F72)=0),1,0) -> 0
A73: EVT072 | B73: SUB038 | C73: CUST038 | D73: Calgary Tech Partners | E73: Western Canada | F73: 45809 | G73: 45817 | H73: created | M73: Analytics Starter | N73: Monthly | O73: 13 | P73: 45 | Q73: 0 | R73: {=_xlfn.IFS(H73="created", "New", H73="cancelled", "Churned", AND(H73="seats_change", J73 > I73), "Expansion", AND(H73="seats_change", J73 < I73), "Contraction", AND(H73="price_change", J73 > I73), "Expansion", AND(H73="price_change", J73 < I73), "Contraction", H73="plan_upgrade", "Expansion", H73="plan_downgrade", "Contraction", H73="discount_added", "Contraction")} -> New | S73: {=IF(N73="Monthly",_xlfn.IFS(H73="created",O73*P73*(1-Q73/100),H73="cancelled",-(O73*P73*(1-Q73/100)),H73="seats_change",(J73-I73)*P73*(1-Q73/100),H73="price_change",(J73-I73)*O73*(1-Q73/100),H73="discount_added",-(O73*P73*(J73-I73)/100),H73="plan_upgrade",O73*(_xlfn.XLOOKUP(J73,$M:$M,$P:$P)-_xlfn.XLOOKUP(I73,$M:$M,$P:$P))*(1-Q73/100),H73="plan_downgrade",O73*(_xlfn.XLOOKUP(J73,$M:$M,$P:$P)-_xlfn.XLOOKUP(I73,$M:$M,$P:$P))*(1-Q73/100)),_xlfn.IFS(H73="created",O73*P73*(1-Q73/100)/12,H73="cancelled",-(O73*P73*(1-Q73/100))/12,H73="seats_change",(J73-I73)*P73*(1-Q73/100)/12,H73="price_change",(J73-I73)*O73*(1-Q73/100)/12,H73="plan_upgrade",(O73*(_xlfn.XLOOKUP(J73,$M:$M,$P:$P)-_xlfn.XLOOKUP(I73,$M:$M,$P:$P))*(1-Q73/100))/12,H73="plan_downgrade",(O73*(_xlfn.XLOOKUP(J73,$M:$M,$P:$P)-_xlfn.XLOOKUP(I73,$M:$M,$P:$P))*(1-Q73/100))/12,H73="discount_added",-(O73*P73*(J73-I73)/100)/12))} -> 585 | T73: =IF(H73<>"created",0,IF(COUNTIFS($C$1:C72,$C73,$H$1:H72,"created")=0,1,0)) -> 1 | U73: =IF(H73<>"cancelled",0,IF(COUNTIFS($C$2:$C$98,$C73,$H$2:$H$98,"created",$F$2:$F$98,"<="&F73)-COUNTIFS($C$2:$C$98,$C73,$H$2:$H$98,"cancelled",$F$2:$F$98,"<="&F73)=0,1,0)) -> 0 | V73: =IF(AND(H73="created",T73=0,COUNTIFS($C$2:$C$98,$C73,$H$2:$H$98,"cancelled",$F$2:$F$98,"<"&F73)>0,COUNTIFS($C$2:$C$98,$C73,$H$2:$H$98,"created",$F$2:$F$98,"<"&F73)-COUNTIFS($C$2:$C$98,$C73,$H$2:$H$98,"cancelled",$F$2:$F$98,"<"&F73)=0),1,0) -> 0
A74: EVT073 | B74: SUB049 | C74: CUST012 | D74: Maritime E-commerce | E74: Eastern Canada | F74: 45809 | G74: 45818 | H74: cancelled | I74: active | J74: cancelled | K74: status | L74: No longer needed | M74: Analytics Starter | N74: Monthly | O74: 19 | P74: 45 | Q74: 0 | R74: {=_xlfn.IFS(H74="created", "New", H74="cancelled", "Churned", AND(H74="seats_change", J74 > I74), "Expansion", AND(H74="seats_change", J74 < I74), "Contraction", AND(H74="price_change", J74 > I74), "Expansion", AND(H74="price_change", J74 < I74), "Contraction", H74="plan_upgrade", "Expansion", H74="plan_downgrade", "Contraction", H74="discount_added", "Contraction")} -> Churned | S74: {=IF(N74="Monthly",_xlfn.IFS(H74="created",O74*P74*(1-Q74/100),H74="cancelled",-(O74*P74*(1-Q74/100)),H74="seats_change",(J74-I74)*P74*(1-Q74/100),H74="price_change",(J74-I74)*O74*(1-Q74/100),H74="discount_added",-(O74*P74*(J74-I74)/100),H74="plan_upgrade",O74*(_xlfn.XLOOKUP(J74,$M:$M,$P:$P)-_xlfn.XLOOKUP(I74,$M:$M,$P:$P))*(1-Q74/100),H74="plan_downgrade",O74*(_xlfn.XLOOKUP(J74,$M:$M,$P:$P)-_xlfn.XLOOKUP(I74,$M:$M,$P:$P))*(1-Q74/100)),_xlfn.IFS(H74="created",O74*P74*(1-Q74/100)/12,H74="cancelled",-(O74*P74*(1-Q74/100))/12,H74="seats_change",(J74-I74)*P74*(1-Q74/100)/12,H74="price_change",(J74-I74)*O74*(1-Q74/100)/12,H74="plan_upgrade",(O74*(_xlfn.XLOOKUP(J74,$M:$M,$P:$P)-_xlfn.XLOOKUP(I74,$M:$M,$P:$P))*(1-Q74/100))/12,H74="plan_downgrade",(O74*(_xlfn.XLOOKUP(J74,$M:$M,$P:$P)-_xlfn.XLOOKUP(I74,$M:$M,$P:$P))*(1-Q74/100))/12,H74="discount_added",-(O74*P74*(J74-I74)/100)/12))} -> -855 | T74: =IF(H74<>"created",0,IF(COUNTIFS($C$1:C73,$C74,$H$1:H73,"created")=0,1,0)) -> 0 | U74: =IF(H74<>"cancelled",0,IF(COUNTIFS($C$2:$C$98,$C74,$H$2:$H$98,"created",$F$2:$F$98,"<="&F74)-COUNTIFS($C$2:$C$98,$C74,$H$2:$H$98,"cancelled",$F$2:$F$98,"<="&F74)=0,1,0)) -> 0 | V74: =IF(AND(H74="created",T74=0,COUNTIFS($C$2:$C$98,$C74,$H$2:$H$98,"cancelled",$F$2:$F$98,"<"&F74)>0,COUNTIFS($C$2:$C$98,$C74,$H$2:$H$98,"created",$F$2:$F$98,"<"&F74)-COUNTIFS($C$2:$C$98,$C74,$H$2:$H$98,"cancelled",$F$2:$F$98,"<"&F74)=0),1,0) -> 0
A75: EVT074 | B75: SUB026 | C75: CUST026 | D75: Ontario Education Connect | E75: Eastern Canada | F75: 45809 | G75: 45823 | H75: plan_upgrade | I75: Analytics Starter | J75: Analytics Growth | K75: plan_name | L75: Growing usage - upgraded for advanced features and higher limits | M75: Analytics Growth | N75: Monthly | O75: 16 | P75: 95 | Q75: 0 | R75: {=_xlfn.IFS(H75="created", "New", H75="cancelled", "Churned", AND(H75="seats_change", J75 > I75), "Expansion", AND(H75="seats_change", J75 < I75), "Contraction", AND(H75="price_change", J75 > I75), "Expansion", AND(H75="price_change", J75 < I75), "Contraction", H75="plan_upgrade", "Expansion", H75="plan_downgrade", "Contraction", H75="discount_added", "Contraction")} -> Expansion | S75: {=IF(N75="Monthly",_xlfn.IFS(H75="created",O75*P75*(1-Q75/100),H75="cancelled",-(O75*P75*(1-Q75/100)),H75="seats_change",(J75-I75)*P75*(1-Q75/100),H75="price_change",(J75-I75)*O75*(1-Q75/100),H75="discount_added",-(O75*P75*(J75-I75)/100),H75="plan_upgrade",O75*(_xlfn.XLOOKUP(J75,$M:$M,$P:$P)-_xlfn.XLOOKUP(I75,$M:$M,$P:$P))*(1-Q75/100),H75="plan_downgrade",O75*(_xlfn.XLOOKUP(J75,$M:$M,$P:$P)-_xlfn.XLOOKUP(I75,$M:$M,$P:$P))*(1-Q75/100)),_xlfn.IFS(H75="created",O75*P75*(1-Q75/100)/12,H75="cancelled",-(O75*P75*(1-Q75/100))/12,H75="seats_change",(J75-I75)*P75*(1-Q75/100)/12,H75="price_change",(J75-I75)*O75*(1-Q75/100)/12,H75="plan_upgrade",(O75*(_xlfn.XLOOKUP(J75,$M:$M,$P:$P)-_xlfn.XLOOKUP(I75,$M:$M,$P:$P))*(1-Q75/100))/12,H75="plan_downgrade",(O75*(_xlfn.XLOOKUP(J75,$M:$M,$P:$P)-_xlfn.XLOOKUP(I75,$M:$M,$P:$P))*(1-Q75/100))/12,H75="discount_added",-(O75*P75*(J75-I75)/100)/12))} -> 800 | T75: =IF(H75<>"created",0,IF(COUNTIFS($C$1:C74,$C75,$H$1:H74,"created")=0,1,0)) -> 0 | U75: =IF(H75<>"cancelled",0,IF(COUNTIFS($C$2:$C$98,$C75,$H$2:$H$98,"created",$F$2:$F$98,"<="&F75)-COUNTIFS($C$2:$C$98,$C75,$H$2:$H$98,"cancelled",$F$2:$F$98,"<="&F75)=0,1,0)) -> 0 | V75: =IF(AND(H75="created",T75=0,COUNTIFS($C$2:$C$98,$C75,$H$2:$H$98,"cancelled",$F$2:$F$98,"<"&F75)>0,COUNTIFS($C$2:$C$98,$C75,$H$2:$H$98,"created",$F$2:$F$98,"<"&F75)-COUNTIFS($C$2:$C$98,$C75,$H$2:$H$98,"cancelled",$F$2:$F$98,"<"&F75)=0),1,0) -> 0
A76: EVT075 | B76: SUB039 | C76: CUST039 | D76: Toronto Commerce Cloud | E76: Eastern Canada | F76: 45809 | G76: 45831 | H76: created | M76: Marketing Pro | N76: Monthly | O76: 29 | P76: 85 | Q76: 0 | R76: {=_xlfn.IFS(H76="created", "New", H76="cancelled", "Churned", AND(H76="seats_change", J76 > I76), "Expansion", AND(H76="seats_change", J76 < I76), "Contraction", AND(H76="price_change", J76 > I76), "Expansion", AND(H76="price_change", J76 < I76), "Contraction", H76="plan_upgrade", "Expansion", H76="plan_downgrade", "Contraction", H76="discount_added", "Contraction")} -> New | S76: {=IF(N76="Monthly",_xlfn.IFS(H76="created",O76*P76*(1-Q76/100),H76="cancelled",-(O76*P76*(1-Q76/100)),H76="seats_change",(J76-I76)*P76*(1-Q76/100),H76="price_change",(J76-I76)*O76*(1-Q76/100),H76="discount_added",-(O76*P76*(J76-I76)/100),H76="plan_upgrade",O76*(_xlfn.XLOOKUP(J76,$M:$M,$P:$P)-_xlfn.XLOOKUP(I76,$M:$M,$P:$P))*(1-Q76/100),H76="plan_downgrade",O76*(_xlfn.XLOOKUP(J76,$M:$M,$P:$P)-_xlfn.XLOOKUP(I76,$M:$M,$P:$P))*(1-Q76/100)),_xlfn.IFS(H76="created",O76*P76*(1-Q76/100)/12,H76="cancelled",-(O76*P76*(1-Q76/100))/12,H76="seats_change",(J76-I76)*P76*(1-Q76/100)/12,H76="price_change",(J76-I76)*O76*(1-Q76/100)/12,H76="plan_upgrade",(O76*(_xlfn.XLOOKUP(J76,$M:$M,$P:$P)-_xlfn.XLOOKUP(I76,$M:$M,$P:$P))*(1-Q76/100))/12,H76="plan_downgrade",(O76*(_xlfn.XLOOKUP(J76,$M:$M,$P:$P)-_xlfn.XLOOKUP(I76,$M:$M,$P:$P))*(1-Q76/100))/12,H76="discount_added",-(O76*P76*(J76-I76)/100)/12))} -> 2465 | T76: =IF(H76<>"created",0,IF(COUNTIFS($C$1:C75,$C76,$H$1:H75,"created")=0,1,0)) -> 1 | U76: =IF(H76<>"cancelled",0,IF(COUNTIFS($C$2:$C$98,$C76,$H$2:$H$98,"created",$F$2:$F$98,"<="&F76)-COUNTIFS($C$2:$C$98,$C76,$H$2:$H$98,"cancelled",$F$2:$F$98,"<="&F76)=0,1,0)) -> 0 | V76: =IF(AND(H76="created",T76=0,COUNTIFS($C$2:$C$98,$C76,$H$2:$H$98,"cancelled",$F$2:$F$98,"<"&F76)>0,COUNTIFS($C$2:$C$98,$C76,$H$2:$H$98,"created",$F$2:$F$98,"<"&F76)-COUNTIFS($C$2:$C$98,$C76,$H$2:$H$98,"cancelled",$F$2:$F$98,"<"&F76)=0),1,0) -> 0
A77: EVT076 | B77: SUB023 | C77: CUST023 | D77: Island Media Productions | E77: Eastern Canada | F77: 45809 | G77: 45833 | H77: cancelled | I77: active | J77: churned | K77: status | L77: Missing features | M77: Analytics Starter | N77: Monthly | O77: 10 | P77: 45 | Q77: 0 | R77: {=_xlfn.IFS(H77="created", "New", H77="cancelled", "Churned", AND(H77="seats_change", J77 > I77), "Expansion", AND(H77="seats_change", J77 < I77), "Contraction", AND(H77="price_change", J77 > I77), "Expansion", AND(H77="price_change", J77 < I77), "Contraction", H77="plan_upgrade", "Expansion", H77="plan_downgrade", "Contraction", H77="discount_added", "Contraction")} -> Churned | S77: {=IF(N77="Monthly",_xlfn.IFS(H77="created",O77*P77*(1-Q77/100),H77="cancelled",-(O77*P77*(1-Q77/100)),H77="seats_change",(J77-I77)*P77*(1-Q77/100),H77="price_change",(J77-I77)*O77*(1-Q77/100),H77="discount_added",-(O77*P77*(J77-I77)/100),H77="plan_upgrade",O77*(_xlfn.XLOOKUP(J77,$M:$M,$P:$P)-_xlfn.XLOOKUP(I77,$M:$M,$P:$P))*(1-Q77/100),H77="plan_downgrade",O77*(_xlfn.XLOOKUP(J77,$M:$M,$P:$P)-_xlfn.XLOOKUP(I77,$M:$M,$P:$P))*(1-Q77/100)),_xlfn.IFS(H77="created",O77*P77*(1-Q77/100)/12,H77="cancelled",-(O77*P77*(1-Q77/100))/12,H77="seats_change",(J77-I77)*P77*(1-Q77/100)/12,H77="price_change",(J77-I77)*O77*(1-Q77/100)/12,H77="plan_upgrade",(O77*(_xlfn.XLOOKUP(J77,$M:$M,$P:$P)-_xlfn.XLOOKUP(I77,$M:$M,$P:$P))*(1-Q77/100))/12,H77="plan_downgrade",(O77*(_xlfn.XLOOKUP(J77,$M:$M,$P:$P)-_xlfn.XLOOKUP(I77,$M:$M,$P:$P))*(1-Q77/100))/12,H77="discount_added",-(O77*P77*(J77-I77)/100)/12))} -> -450 | T77: =IF(H77<>"created",0,IF(COUNTIFS($C$1:C76,$C77,$H$1:H76,"created")=0,1,0)) -> 0 | U77: =IF(H77<>"cancelled",0,IF(COUNTIFS($C$2:$C$98,$C77,$H$2:$H$98,"created",$F$2:$F$98,"<="&F77)-COUNTIFS($C$2:$C$98,$C77,$H$2:$H$98,"cancelled",$F$2:$F$98,"<="&F77)=0,1,0)) -> 1 | V77: =IF(AND(H77="created",T77=0,COUNTIFS($C$2:$C$98,$C77,$H$2:$H$98,"cancelled",$F$2:$F$98,"<"&F77)>0,COUNTIFS($C$2:$C$98,$C77,$H$2:$H$98,"created",$F$2:$F$98,"<"&F77)-COUNTIFS($C$2:$C$98,$C77,$H$2:$H$98,"cancelled",$F$2:$F$98,"<"&F77)=0),1,0) -> 0
A78: EVT077 | B78: SUB059 | C78: CUST008 | D78: Quantum Education Platform | E78: Eastern Canada | F78: 45839 | G78: 45843 | H78: price_change | I78: 75 | J78: 85 | K78: price_per_seat | L78: Annual price increase applied at renewal | M78: Marketing Pro | N78: Monthly | O78: 22 | P78: 85 | Q78: 0 | R78: {=_xlfn.IFS(H78="created", "New", H78="cancelled", "Churned", AND(H78="seats_change", J78 > I78), "Expansion", AND(H78="seats_change", J78 < I78), "Contraction", AND(H78="price_change", J78 > I78), "Expansion", AND(H78="price_change", J78 < I78), "Contraction", H78="plan_upgrade", "Expansion", H78="plan_downgrade", "Contraction", H78="discount_added", "Contraction")} -> Expansion | S78: {=IF(N78="Monthly",_xlfn.IFS(H78="created",O78*P78*(1-Q78/100),H78="cancelled",-(O78*P78*(1-Q78/100)),H78="seats_change",(J78-I78)*P78*(1-Q78/100),H78="price_change",(J78-I78)*O78*(1-Q78/100),H78="discount_added",-(O78*P78*(J78-I78)/100),H78="plan_upgrade",O78*(_xlfn.XLOOKUP(J78,$M:$M,$P:$P)-_xlfn.XLOOKUP(I78,$M:$M,$P:$P))*(1-Q78/100),H78="plan_downgrade",O78*(_xlfn.XLOOKUP(J78,$M:$M,$P:$P)-_xlfn.XLOOKUP(I78,$M:$M,$P:$P))*(1-Q78/100)),_xlfn.IFS(H78="created",O78*P78*(1-Q78/100)/12,H78="cancelled",-(O78*P78*(1-Q78/100))/12,H78="seats_change",(J78-I78)*P78*(1-Q78/100)/12,H78="price_change",(J78-I78)*O78*(1-Q78/100)/12,H78="plan_upgrade",(O78*(_xlfn.XLOOKUP(J78,$M:$M,$P:$P)-_xlfn.XLOOKUP(I78,$M:$M,$P:$P))*(1-Q78/100))/12,H78="plan_downgrade",(O78*(_xlfn.XLOOKUP(J78,$M:$M,$P:$P)-_xlfn.XLOOKUP(I78,$M:$M,$P:$P))*(1-Q78/100))/12,H78="discount_added",-(O78*P78*(J78-I78)/100)/12))} -> 220 | T78: =IF(H78<>"created",0,IF(COUNTIFS($C$1:C77,$C78,$H$1:H77,"created")=0,1,0)) -> 0 | U78: =IF(H78<>"cancelled",0,IF(COUNTIFS($C$2:$C$98,$C78,$H$2:$H$98,"created",$F$2:$F$98,"<="&F78)-COUNTIFS($C$2:$C$98,$C78,$H$2:$H$98,"cancelled",$F$2:$F$98,"<="&F78)=0,1,0)) -> 0 | V78: =IF(AND(H78="created",T78=0,COUNTIFS($C$2:$C$98,$C78,$H$2:$H$98,"cancelled",$F$2:$F$98,"<"&F78)>0,COUNTIFS($C$2:$C$98,$C78,$H$2:$H$98,"created",$F$2:$F$98,"<"&F78)-COUNTIFS($C$2:$C$98,$C78,$H$2:$H$98,"cancelled",$F$2:$F$98,"<"&F78)=0),1,0) -> 0
A79: EVT078 | B79: SUB060 | C79: CUST019 | D79: Central Healthcare Partners | E79: Central Canada | F79: 45839 | G79: 45858 | H79: cancelled | I79: active | J79: cancelled | K79: status | L79: Budget cuts | M79: Sales Hub | N79: Monthly | O79: 16 | P79: 110 | Q79: 0 | R79: {=_xlfn.IFS(H79="created", "New", H79="cancelled", "Churned", AND(H79="seats_change", J79 > I79), "Expansion", AND(H79="seats_change", J79 < I79), "Contraction", AND(H79="price_change", J79 > I79), "Expansion", AND(H79="price_change", J79 < I79), "Contraction", H79="plan_upgrade", "Expansion", H79="plan_downgrade", "Contraction", H79="discount_added", "Contraction")} -> Churned | S79: {=IF(N79="Monthly",_xlfn.IFS(H79="created",O79*P79*(1-Q79/100),H79="cancelled",-(O79*P79*(1-Q79/100)),H79="seats_change",(J79-I79)*P79*(1-Q79/100),H79="price_change",(J79-I79)*O79*(1-Q79/100),H79="discount_added",-(O79*P79*(J79-I79)/100),H79="plan_upgrade",O79*(_xlfn.XLOOKUP(J79,$M:$M,$P:$P)-_xlfn.XLOOKUP(I79,$M:$M,$P:$P))*(1-Q79/100),H79="plan_downgrade",O79*(_xlfn.XLOOKUP(J79,$M:$M,$P:$P)-_xlfn.XLOOKUP(I79,$M:$M,$P:$P))*(1-Q79/100)),_xlfn.IFS(H79="created",O79*P79*(1-Q79/100)/12,H79="cancelled",-(O79*P79*(1-Q79/100))/12,H79="seats_change",(J79-I79)*P79*(1-Q79/100)/12,H79="price_change",(J79-I79)*O79*(1-Q79/100)/12,H79="plan_upgrade",(O79*(_xlfn.XLOOKUP(J79,$M:$M,$P:$P)-_xlfn.XLOOKUP(I79,$M:$M,$P:$P))*(1-Q79/100))/12,H79="plan_downgrade",(O79*(_xlfn.XLOOKUP(J79,$M:$M,$P:$P)-_xlfn.XLOOKUP(I79,$M:$M,$P:$P))*(1-Q79/100))/12,H79="discount_added",-(O79*P79*(J79-I79)/100)/12))} -> -1760 | T79: =IF(H79<>"created",0,IF(COUNTIFS($C$1:C78,$C79,$H$1:H78,"created")=0,1,0)) -> 0 | U79: =IF(H79<>"cancelled",0,IF(COUNTIFS($C$2:$C$98,$C79,$H$2:$H$98,"created",$F$2:$F$98,"<="&F79)-COUNTIFS($C$2:$C$98,$C79,$H$2:$H$98,"cancelled",$F$2:$F$98,"<="&F79)=0,1,0)) -> 0 | V79: =IF(AND(H79="created",T79=0,COUNTIFS($C$2:$C$98,$C79,$H$2:$H$98,"cancelled",$F$2:$F$98,"<"&F79)>0,COUNTIFS($C$2:$C$98,$C79,$H$2:$H$98,"created",$F$2:$F$98,"<"&F79)-COUNTIFS($C$2:$C$98,$C79,$H$2:$H$98,"cancelled",$F$2:$F$98,"<"&F79)=0),1,0) -> 0
A80: EVT079 | B80: SUB011 | C80: CUST011 | D80: Prairie Health Connect | E80: Central Canada | F80: 45839 | G80: 45860 | H80: seats_change | I80: 14 | J80: 18 | K80: seats | L80: Team expansion - mid-year headcount increase | M80: Sales Hub | N80: Monthly | O80: 18 | P80: 110 | Q80: 0 | R80: {=_xlfn.IFS(H80="created", "New", H80="cancelled", "Churned", AND(H80="seats_change", J80 > I80), "Expansion", AND(H80="seats_change", J80 < I80), "Contraction", AND(H80="price_change", J80 > I80), "Expansion", AND(H80="price_change", J80 < I80), "Contraction", H80="plan_upgrade", "Expansion", H80="plan_downgrade", "Contraction", H80="discount_added", "Contraction")} -> Expansion | S80: {=IF(N80="Monthly",_xlfn.IFS(H80="created",O80*P80*(1-Q80/100),H80="cancelled",-(O80*P80*(1-Q80/100)),H80="seats_change",(J80-I80)*P80*(1-Q80/100),H80="price_change",(J80-I80)*O80*(1-Q80/100),H80="discount_added",-(O80*P80*(J80-I80)/100),H80="plan_upgrade",O80*(_xlfn.XLOOKUP(J80,$M:$M,$P:$P)-_xlfn.XLOOKUP(I80,$M:$M,$P:$P))*(1-Q80/100),H80="plan_downgrade",O80*(_xlfn.XLOOKUP(J80,$M:$M,$P:$P)-_xlfn.XLOOKUP(I80,$M:$M,$P:$P))*(1-Q80/100)),_xlfn.IFS(H80="created",O80*P80*(1-Q80/100)/12,H80="cancelled",-(O80*P80*(1-Q80/100))/12,H80="seats_change",(J80-I80)*P80*(1-Q80/100)/12,H80="price_change",(J80-I80)*O80*(1-Q80/100)/12,H80="plan_upgrade",(O80*(_xlfn.XLOOKUP(J80,$M:$M,$P:$P)-_xlfn.XLOOKUP(I80,$M:$M,$P:$P))*(1-Q80/100))/12,H80="plan_downgrade",(O80*(_xlfn.XLOOKUP(J80,$M:$M,$P:$P)-_xlfn.XLOOKUP(I80,$M:$M,$P:$P))*(1-Q80/100))/12,H80="discount_added",-(O80*P80*(J80-I80)/100)/12))} -> 440 | T80: =IF(H80<>"created",0,IF(COUNTIFS($C$1:C79,$C80,$H$1:H79,"created")=0,1,0)) -> 0 | U80: =IF(H80<>"cancelled",0,IF(COUNTIFS($C$2:$C$98,$C80,$H$2:$H$98,"created",$F$2:$F$98,"<="&F80)-COUNTIFS($C$2:$C$98,$C80,$H$2:$H$98,"cancelled",$F$2:$F$98,"<="&F80)=0,1,0)) -> 0 | V80: =IF(AND(H80="created",T80=0,COUNTIFS($C$2:$C$98,$C80,$H$2:$H$98,"cancelled",$F$2:$F$98,"<"&F80)>0,COUNTIFS($C$2:$C$98,$C80,$H$2:$H$98,"created",$F$2:$F$98,"<"&F80)-COUNTIFS($C$2:$C$98,$C80,$H$2:$H$98,"cancelled",$F$2:$F$98,"<"&F80)=0),1,0) -> 0
A81: EVT080 | B81: SUB029 | C81: CUST029 | D81: Halifax Healthcare Tech | E81: Eastern Canada | F81: 45870 | G81: 45872 | H81: price_change | I81: 90 | J81: 85 | K81: price_per_seat | L81: Renewal negotiation - competitive pricing match | M81: Marketing Pro | N81: Monthly | O81: 22 | P81: 85 | Q81: 0 | R81: {=_xlfn.IFS(H81="created", "New", H81="cancelled", "Churned", AND(H81="seats_change", J81 > I81), "Expansion", AND(H81="seats_change", J81 < I81), "Contraction", AND(H81="price_change", J81 > I81), "Expansion", AND(H81="price_change", J81 < I81), "Contraction", H81="plan_upgrade", "Expansion", H81="plan_downgrade", "Contraction", H81="discount_added", "Contraction")} -> Contraction | S81: {=IF(N81="Monthly",_xlfn.IFS(H81="created",O81*P81*(1-Q81/100),H81="cancelled",-(O81*P81*(1-Q81/100)),H81="seats_change",(J81-I81)*P81*(1-Q81/100),H81="price_change",(J81-I81)*O81*(1-Q81/100),H81="discount_added",-(O81*P81*(J81-I81)/100),H81="plan_upgrade",O81*(_xlfn.XLOOKUP(J81,$M:$M,$P:$P)-_xlfn.XLOOKUP(I81,$M:$M,$P:$P))*(1-Q81/100),H81="plan_downgrade",O81*(_xlfn.XLOOKUP(J81,$M:$M,$P:$P)-_xlfn.XLOOKUP(I81,$M:$M,$P:$P))*(1-Q81/100)),_xlfn.IFS(H81="created",O81*P81*(1-Q81/100)/12,H81="cancelled",-(O81*P81*(1-Q81/100))/12,H81="seats_change",(J81-I81)*P81*(1-Q81/100)/12,H81="price_change",(J81-I81)*O81*(1-Q81/100)/12,H81="plan_upgrade",(O81*(_xlfn.XLOOKUP(J81,$M:$M,$P:$P)-_xlfn.XLOOKUP(I81,$M:$M,$P:$P))*(1-Q81/100))/12,H81="plan_downgrade",(O81*(_xlfn.XLOOKUP(J81,$M:$M,$P:$P)-_xlfn.XLOOKUP(I81,$M:$M,$P:$P))*(1-Q81/100))/12,H81="discount_added",-(O81*P81*(J81-I81)/100)/12))} -> -110 | T81: =IF(H81<>"created",0,IF(COUNTIFS($C$1:C80,$C81,$H$1:H80,"created")=0,1,0)) -> 0 | U81: =IF(H81<>"cancelled",0,IF(COUNTIFS($C$2:$C$98,$C81,$H$2:$H$98,"created",$F$2:$F$98,"<="&F81)-COUNTIFS($C$2:$C$98,$C81,$H$2:$H$98,"cancelled",$F$2:$F$98,"<="&F81)=0,1,0)) -> 0 | V81: =IF(AND(H81="created",T81=0,COUNTIFS($C$2:$C$98,$C81,$H$2:$H$98,"cancelled",$F$2:$F$98,"<"&F81)>0,COUNTIFS($C$2:$C$98,$C81,$H$2:$H$98,"created",$F$2:$F$98,"<"&F81)-COUNTIFS($C$2:$C$98,$C81,$H$2:$H$98,"cancelled",$F$2:$F$98,"<"&F81)=0),1,0) -> 0
A82: EVT081 | B82: SUB032 | C82: CUST032 | D82: BC Manufacturing Systems | E82: Western Canada | F82: 45870 | G82: 45881 | H82: plan_upgrade | I82: Analytics Growth | J82: Analytics Enterprise | K82: plan_name | L82: Enterprise SSO and audit logs required | M82: Analytics Enterprise | N82: Monthly | O82: 26 | P82: 180 | Q82: 0 | R82: {=_xlfn.IFS(H82="created", "New", H82="cancelled", "Churned", AND(H82="seats_change", J82 > I82), "Expansion", AND(H82="seats_change", J82 < I82), "Contraction", AND(H82="price_change", J82 > I82), "Expansion", AND(H82="price_change", J82 < I82), "Contraction", H82="plan_upgrade", "Expansion", H82="plan_downgrade", "Contraction", H82="discount_added", "Contraction")} -> Expansion | S82: {=IF(N82="Monthly",_xlfn.IFS(H82="created",O82*P82*(1-Q82/100),H82="cancelled",-(O82*P82*(1-Q82/100)),H82="seats_change",(J82-I82)*P82*(1-Q82/100),H82="price_change",(J82-I82)*O82*(1-Q82/100),H82="discount_added",-(O82*P82*(J82-I82)/100),H82="plan_upgrade",O82*(_xlfn.XLOOKUP(J82,$M:$M,$P:$P)-_xlfn.XLOOKUP(I82,$M:$M,$P:$P))*(1-Q82/100),H82="plan_downgrade",O82*(_xlfn.XLOOKUP(J82,$M:$M,$P:$P)-_xlfn.XLOOKUP(I82,$M:$M,$P:$P))*(1-Q82/100)),_xlfn.IFS(H82="created",O82*P82*(1-Q82/100)/12,H82="cancelled",-(O82*P82*(1-Q82/100))/12,H82="seats_change",(J82-I82)*P82*(1-Q82/100)/12,H82="price_change",(J82-I82)*O82*(1-Q82/100)/12,H82="plan_upgrade",(O82*(_xlfn.XLOOKUP(J82,$M:$M,$P:$P)-_xlfn.XLOOKUP(I82,$M:$M,$P:$P))*(1-Q82/100))/12,H82="plan_downgrade",(O82*(_xlfn.XLOOKUP(J82,$M:$M,$P:$P)-_xlfn.XLOOKUP(I82,$M:$M,$P:$P))*(1-Q82/100))/12,H82="discount_added",-(O82*P82*(J82-I82)/100)/12))} -> 2210 | T82: =IF(H82<>"created",0,IF(COUNTIFS($C$1:C81,$C82,$H$1:H81,"created")=0,1,0)) -> 0 | U82: =IF(H82<>"cancelled",0,IF(COUNTIFS($C$2:$C$98,$C82,$H$2:$H$98,"created",$F$2:$F$98,"<="&F82)-COUNTIFS($C$2:$C$98,$C82,$H$2:$H$98,"cancelled",$F$2:$F$98,"<="&F82)=0,1,0)) -> 0 | V82: =IF(AND(H82="created",T82=0,COUNTIFS($C$2:$C$98,$C82,$H$2:$H$98,"cancelled",$F$2:$F$98,"<"&F82)>0,COUNTIFS($C$2:$C$98,$C82,$H$2:$H$98,"created",$F$2:$F$98,"<"&F82)-COUNTIFS($C$2:$C$98,$C82,$H$2:$H$98,"cancelled",$F$2:$F$98,"<"&F82)=0),1,0) -> 0
A83: EVT082 | B83: SUB017 | C83: CUST017 | D83: Capital Education Tech | E83: Eastern Canada | F83: 45870 | G83: 45888 | H83: plan_downgrade | I83: Analytics Growth | J83: Analytics Starter | K83: plan_name | L83: Reduced usage - advanced features no longer needed | M83: Analytics Starter | N83: Monthly | O83: 12 | P83: 45 | Q83: 0 | R83: {=_xlfn.IFS(H83="created", "New", H83="cancelled", "Churned", AND(H83="seats_change", J83 > I83), "Expansion", AND(H83="seats_change", J83 < I83), "Contraction", AND(H83="price_change", J83 > I83), "Expansion", AND(H83="price_change", J83 < I83), "Contraction", H83="plan_upgrade", "Expansion", H83="plan_downgrade", "Contraction", H83="discount_added", "Contraction")} -> Contraction | S83: {=IF(N83="Monthly",_xlfn.IFS(H83="created",O83*P83*(1-Q83/100),H83="cancelled",-(O83*P83*(1-Q83/100)),H83="seats_change",(J83-I83)*P83*(1-Q83/100),H83="price_change",(J83-I83)*O83*(1-Q83/100),H83="discount_added",-(O83*P83*(J83-I83)/100),H83="plan_upgrade",O83*(_xlfn.XLOOKUP(J83,$M:$M,$P:$P)-_xlfn.XLOOKUP(I83,$M:$M,$P:$P))*(1-Q83/100),H83="plan_downgrade",O83*(_xlfn.XLOOKUP(J83,$M:$M,$P:$P)-_xlfn.XLOOKUP(I83,$M:$M,$P:$P))*(1-Q83/100)),_xlfn.IFS(H83="created",O83*P83*(1-Q83/100)/12,H83="cancelled",-(O83*P83*(1-Q83/100))/12,H83="seats_change",(J83-I83)*P83*(1-Q83/100)/12,H83="price_change",(J83-I83)*O83*(1-Q83/100)/12,H83="plan_upgrade",(O83*(_xlfn.XLOOKUP(J83,$M:$M,$P:$P)-_xlfn.XLOOKUP(I83,$M:$M,$P:$P))*(1-Q83/100))/12,H83="plan_downgrade",(O83*(_xlfn.XLOOKUP(J83,$M:$M,$P:$P)-_xlfn.XLOOKUP(I83,$M:$M,$P:$P))*(1-Q83/100))/12,H83="discount_added",-(O83*P83*(J83-I83)/100)/12))} -> -600 | T83: =IF(H83<>"created",0,IF(COUNTIFS($C$1:C82,$C83,$H$1:H82,"created")=0,1,0)) -> 0 | U83: =IF(H83<>"cancelled",0,IF(COUNTIFS($C$2:$C$98,$C83,$H$2:$H$98,"created",$F$2:$F$98,"<="&F83)-COUNTIFS($C$2:$C$98,$C83,$H$2:$H$98,"cancelled",$F$2:$F$98,"<="&F83)=0,1,0)) -> 0 | V83: =IF(AND(H83="created",T83=0,COUNTIFS($C$2:$C$98,$C83,$H$2:$H$98,"cancelled",$F$2:$F$98,"<"&F83)>0,COUNTIFS($C$2:$C$98,$C83,$H$2:$H$98,"created",$F$2:$F$98,"<"&F83)-COUNTIFS($C$2:$C$98,$C83,$H$2:$H$98,"cancelled",$F$2:$F$98,"<"&F83)=0),1,0) -> 0
A84: EVT083 | B84: SUB022 | C84: CUST022 | D84: Toronto Tech Ventures | E84: Eastern Canada | F84: 45870 | G84: 45889 | H84: seats_change | I84: 28 | J84: 33 | K84: seats | L84: Team expansion - ops team grew | M84: Platform Suite | N84: Monthly | O84: 33 | P84: 150 | Q84: 0 | R84: {=_xlfn.IFS(H84="created", "New", H84="cancelled", "Churned", AND(H84="seats_change", J84 > I84), "Expansion", AND(H84="seats_change", J84 < I84), "Contraction", AND(H84="price_change", J84 > I84), "Expansion", AND(H84="price_change", J84 < I84), "Contraction", H84="plan_upgrade", "Expansion", H84="plan_downgrade", "Contraction", H84="discount_added", "Contraction")} -> Expansion | S84: {=IF(N84="Monthly",_xlfn.IFS(H84="created",O84*P84*(1-Q84/100),H84="cancelled",-(O84*P84*(1-Q84/100)),H84="seats_change",(J84-I84)*P84*(1-Q84/100),H84="price_change",(J84-I84)*O84*(1-Q84/100),H84="discount_added",-(O84*P84*(J84-I84)/100),H84="plan_upgrade",O84*(_xlfn.XLOOKUP(J84,$M:$M,$P:$P)-_xlfn.XLOOKUP(I84,$M:$M,$P:$P))*(1-Q84/100),H84="plan_downgrade",O84*(_xlfn.XLOOKUP(J84,$M:$M,$P:$P)-_xlfn.XLOOKUP(I84,$M:$M,$P:$P))*(1-Q84/100)),_xlfn.IFS(H84="created",O84*P84*(1-Q84/100)/12,H84="cancelled",-(O84*P84*(1-Q84/100))/12,H84="seats_change",(J84-I84)*P84*(1-Q84/100)/12,H84="price_change",(J84-I84)*O84*(1-Q84/100)/12,H84="plan_upgrade",(O84*(_xlfn.XLOOKUP(J84,$M:$M,$P:$P)-_xlfn.XLOOKUP(I84,$M:$M,$P:$P))*(1-Q84/100))/12,H84="plan_downgrade",(O84*(_xlfn.XLOOKUP(J84,$M:$M,$P:$P)-_xlfn.XLOOKUP(I84,$M:$M,$P:$P))*(1-Q84/100))/12,H84="discount_added",-(O84*P84*(J84-I84)/100)/12))} -> 750 | T84: =IF(H84<>"created",0,IF(COUNTIFS($C$1:C83,$C84,$H$1:H83,"created")=0,1,0)) -> 0 | U84: =IF(H84<>"cancelled",0,IF(COUNTIFS($C$2:$C$98,$C84,$H$2:$H$98,"created",$F$2:$F$98,"<="&F84)-COUNTIFS($C$2:$C$98,$C84,$H$2:$H$98,"cancelled",$F$2:$F$98,"<="&F84)=0,1,0)) -> 0 | V84: =IF(AND(H84="created",T84=0,COUNTIFS($C$2:$C$98,$C84,$H$2:$H$98,"cancelled",$F$2:$F$98,"<"&F84)>0,COUNTIFS($C$2:$C$98,$C84,$H$2:$H$98,"created",$F$2:$F$98,"<"&F84)-COUNTIFS($C$2:$C$98,$C84,$H$2:$H$98,"cancelled",$F$2:$F$98,"<"&F84)=0),1,0) -> 0
A85: EVT084 | B85: SUB055 | C85: CUST004 | D85: Prairie Commerce Group | E85: Western Canada | F85: 45870 | G85: 45899 | H85: cancelled | I85: active | J85: churned | K85: status | L85: Switched to competitor | M85: Analytics Enterprise | N85: Monthly | O85: 26 | P85: 180 | Q85: 0 | R85: {=_xlfn.IFS(H85="created", "New", H85="cancelled", "Churned", AND(H85="seats_change", J85 > I85), "Expansion", AND(H85="seats_change", J85 < I85), "Contraction", AND(H85="price_change", J85 > I85), "Expansion", AND(H85="price_change", J85 < I85), "Contraction", H85="plan_upgrade", "Expansion", H85="plan_downgrade", "Contraction", H85="discount_added", "Contraction")} -> Churned | S85: {=IF(N85="Monthly",_xlfn.IFS(H85="created",O85*P85*(1-Q85/100),H85="cancelled",-(O85*P85*(1-Q85/100)),H85="seats_change",(J85-I85)*P85*(1-Q85/100),H85="price_change",(J85-I85)*O85*(1-Q85/100),H85="discount_added",-(O85*P85*(J85-I85)/100),H85="plan_upgrade",O85*(_xlfn.XLOOKUP(J85,$M:$M,$P:$P)-_xlfn.XLOOKUP(I85,$M:$M,$P:$P))*(1-Q85/100),H85="plan_downgrade",O85*(_xlfn.XLOOKUP(J85,$M:$M,$P:$P)-_xlfn.XLOOKUP(I85,$M:$M,$P:$P))*(1-Q85/100)),_xlfn.IFS(H85="created",O85*P85*(1-Q85/100)/12,H85="cancelled",-(O85*P85*(1-Q85/100))/12,H85="seats_change",(J85-I85)*P85*(1-Q85/100)/12,H85="price_change",(J85-I85)*O85*(1-Q85/100)/12,H85="plan_upgrade",(O85*(_xlfn.XLOOKUP(J85,$M:$M,$P:$P)-_xlfn.XLOOKUP(I85,$M:$M,$P:$P))*(1-Q85/100))/12,H85="plan_downgrade",(O85*(_xlfn.XLOOKUP(J85,$M:$M,$P:$P)-_xlfn.XLOOKUP(I85,$M:$M,$P:$P))*(1-Q85/100))/12,H85="discount_added",-(O85*P85*(J85-I85)/100)/12))} -> -4680 | T85: =IF(H85<>"created",0,IF(COUNTIFS($C$1:C84,$C85,$H$1:H84,"created")=0,1,0)) -> 0 | U85: =IF(H85<>"cancelled",0,IF(COUNTIFS($C$2:$C$98,$C85,$H$2:$H$98,"created",$F$2:$F$98,"<="&F85)-COUNTIFS($C$2:$C$98,$C85,$H$2:$H$98,"cancelled",$F$2:$F$98,"<="&F85)=0,1,0)) -> 0 | V85: =IF(AND(H85="created",T85=0,COUNTIFS($C$2:$C$98,$C85,$H$2:$H$98,"cancelled",$F$2:$F$98,"<"&F85)>0,COUNTIFS($C$2:$C$98,$C85,$H$2:$H$98,"created",$F$2:$F$98,"<"&F85)-COUNTIFS($C$2:$C$98,$C85,$H$2:$H$98,"cancelled",$F$2:$F$98,"<"&F85)=0),1,0) -> 0
A86: EVT085 | B86: SUB030 | C86: CUST030 | D86: Alberta E-commerce Hub | E86: Western Canada | F86: 45901 | G86: 45905 | H86: plan_upgrade | I86: Analytics Starter | J86: Analytics Growth | K86: plan_name | L86: Upgraded for advanced analytics and API access | M86: Analytics Growth | N86: Monthly | O86: 20 | P86: 95 | Q86: 0 | R86: {=_xlfn.IFS(H86="created", "New", H86="cancelled", "Churned", AND(H86="seats_change", J86 > I86), "Expansion", AND(H86="seats_change", J86 < I86), "Contraction", AND(H86="price_change", J86 > I86), "Expansion", AND(H86="price_change", J86 < I86), "Contraction", H86="plan_upgrade", "Expansion", H86="plan_downgrade", "Contraction", H86="discount_added", "Contraction")} -> Expansion | S86: {=IF(N86="Monthly",_xlfn.IFS(H86="created",O86*P86*(1-Q86/100),H86="cancelled",-(O86*P86*(1-Q86/100)),H86="seats_change",(J86-I86)*P86*(1-Q86/100),H86="price_change",(J86-I86)*O86*(1-Q86/100),H86="discount_added",-(O86*P86*(J86-I86)/100),H86="plan_upgrade",O86*(_xlfn.XLOOKUP(J86,$M:$M,$P:$P)-_xlfn.XLOOKUP(I86,$M:$M,$P:$P))*(1-Q86/100),H86="plan_downgrade",O86*(_xlfn.XLOOKUP(J86,$M:$M,$P:$P)-_xlfn.XLOOKUP(I86,$M:$M,$P:$P))*(1-Q86/100)),_xlfn.IFS(H86="created",O86*P86*(1-Q86/100)/12,H86="cancelled",-(O86*P86*(1-Q86/100))/12,H86="seats_change",(J86-I86)*P86*(1-Q86/100)/12,H86="price_change",(J86-I86)*O86*(1-Q86/100)/12,H86="plan_upgrade",(O86*(_xlfn.XLOOKUP(J86,$M:$M,$P:$P)-_xlfn.XLOOKUP(I86,$M:$M,$P:$P))*(1-Q86/100))/12,H86="plan_downgrade",(O86*(_xlfn.XLOOKUP(J86,$M:$M,$P:$P)-_xlfn.XLOOKUP(I86,$M:$M,$P:$P))*(1-Q86/100))/12,H86="discount_added",-(O86*P86*(J86-I86)/100)/12))} -> 1000 | T86: =IF(H86<>"created",0,IF(COUNTIFS($C$1:C85,$C86,$H$1:H85,"created")=0,1,0)) -> 0 | U86: =IF(H86<>"cancelled",0,IF(COUNTIFS($C$2:$C$98,$C86,$H$2:$H$98,"created",$F$2:$F$98,"<="&F86)-COUNTIFS($C$2:$C$98,$C86,$H$2:$H$98,"cancelled",$F$2:$F$98,"<="&F86)=0,1,0)) -> 0 | V86: =IF(AND(H86="created",T86=0,COUNTIFS($C$2:$C$98,$C86,$H$2:$H$98,"cancelled",$F$2:$F$98,"<"&F86)>0,COUNTIFS($C$2:$C$98,$C86,$H$2:$H$98,"created",$F$2:$F$98,"<"&F86)-COUNTIFS($C$2:$C$98,$C86,$H$2:$H$98,"cancelled",$F$2:$F$98,"<"&F86)=0),1,0) -> 0
A87: EVT086 | B87: SUB053 | C87: CUST027 | D87: Pacific Finance Corp | E87: Western Canada | F87: 45901 | G87: 45910 | H87: seats_change | I87: 26 | J87: 31 | K87: seats | L87: Department expansion - data team scaling | M87: Analytics Enterprise | N87: Monthly | O87: 31 | P87: 180 | Q87: 0 | R87: {=_xlfn.IFS(H87="created", "New", H87="cancelled", "Churned", AND(H87="seats_change", J87 > I87), "Expansion", AND(H87="seats_change", J87 < I87), "Contraction", AND(H87="price_change", J87 > I87), "Expansion", AND(H87="price_change", J87 < I87), "Contraction", H87="plan_upgrade", "Expansion", H87="plan_downgrade", "Contraction", H87="discount_added", "Contraction")} -> Expansion | S87: {=IF(N87="Monthly",_xlfn.IFS(H87="created",O87*P87*(1-Q87/100),H87="cancelled",-(O87*P87*(1-Q87/100)),H87="seats_change",(J87-I87)*P87*(1-Q87/100),H87="price_change",(J87-I87)*O87*(1-Q87/100),H87="discount_added",-(O87*P87*(J87-I87)/100),H87="plan_upgrade",O87*(_xlfn.XLOOKUP(J87,$M:$M,$P:$P)-_xlfn.XLOOKUP(I87,$M:$M,$P:$P))*(1-Q87/100),H87="plan_downgrade",O87*(_xlfn.XLOOKUP(J87,$M:$M,$P:$P)-_xlfn.XLOOKUP(I87,$M:$M,$P:$P))*(1-Q87/100)),_xlfn.IFS(H87="created",O87*P87*(1-Q87/100)/12,H87="cancelled",-(O87*P87*(1-Q87/100))/12,H87="seats_change",(J87-I87)*P87*(1-Q87/100)/12,H87="price_change",(J87-I87)*O87*(1-Q87/100)/12,H87="plan_upgrade",(O87*(_xlfn.XLOOKUP(J87,$M:$M,$P:$P)-_xlfn.XLOOKUP(I87,$M:$M,$P:$P))*(1-Q87/100))/12,H87="plan_downgrade",(O87*(_xlfn.XLOOKUP(J87,$M:$M,$P:$P)-_xlfn.XLOOKUP(I87,$M:$M,$P:$P))*(1-Q87/100))/12,H87="discount_added",-(O87*P87*(J87-I87)/100)/12))} -> 900 | T87: =IF(H87<>"created",0,IF(COUNTIFS($C$1:C86,$C87,$H$1:H86,"created")=0,1,0)) -> 0 | U87: =IF(H87<>"cancelled",0,IF(COUNTIFS($C$2:$C$98,$C87,$H$2:$H$98,"created",$F$2:$F$98,"<="&F87)-COUNTIFS($C$2:$C$98,$C87,$H$2:$H$98,"cancelled",$F$2:$F$98,"<="&F87)=0,1,0)) -> 0 | V87: =IF(AND(H87="created",T87=0,COUNTIFS($C$2:$C$98,$C87,$H$2:$H$98,"cancelled",$F$2:$F$98,"<"&F87)>0,COUNTIFS($C$2:$C$98,$C87,$H$2:$H$98,"created",$F$2:$F$98,"<"&F87)-COUNTIFS($C$2:$C$98,$C87,$H$2:$H$98,"cancelled",$F$2:$F$98,"<"&F87)=0),1,0) -> 0
A88: EVT087 | B88: SUB033 | C88: CUST033 | D88: Ottawa Retail Solutions | E88: Eastern Canada | F88: 45901 | G88: 45930 | H88: price_change | I88: 90 | J88: 85 | K88: price_per_seat | L88: Renewal negotiation - loyalty discount applied | M88: Marketing Pro | N88: Monthly | O88: 25 | P88: 85 | Q88: 0 | R88: {=_xlfn.IFS(H88="created", "New", H88="cancelled", "Churned", AND(H88="seats_change", J88 > I88), "Expansion", AND(H88="seats_change", J88 < I88), "Contraction", AND(H88="price_change", J88 > I88), "Expansion", AND(H88="price_change", J88 < I88), "Contraction", H88="plan_upgrade", "Expansion", H88="plan_downgrade", "Contraction", H88="discount_added", "Contraction")} -> Contraction | S88: {=IF(N88="Monthly",_xlfn.IFS(H88="created",O88*P88*(1-Q88/100),H88="cancelled",-(O88*P88*(1-Q88/100)),H88="seats_change",(J88-I88)*P88*(1-Q88/100),H88="price_change",(J88-I88)*O88*(1-Q88/100),H88="discount_added",-(O88*P88*(J88-I88)/100),H88="plan_upgrade",O88*(_xlfn.XLOOKUP(J88,$M:$M,$P:$P)-_xlfn.XLOOKUP(I88,$M:$M,$P:$P))*(1-Q88/100),H88="plan_downgrade",O88*(_xlfn.XLOOKUP(J88,$M:$M,$P:$P)-_xlfn.XLOOKUP(I88,$M:$M,$P:$P))*(1-Q88/100)),_xlfn.IFS(H88="created",O88*P88*(1-Q88/100)/12,H88="cancelled",-(O88*P88*(1-Q88/100))/12,H88="seats_change",(J88-I88)*P88*(1-Q88/100)/12,H88="price_change",(J88-I88)*O88*(1-Q88/100)/12,H88="plan_upgrade",(O88*(_xlfn.XLOOKUP(J88,$M:$M,$P:$P)-_xlfn.XLOOKUP(I88,$M:$M,$P:$P))*(1-Q88/100))/12,H88="plan_downgrade",(O88*(_xlfn.XLOOKUP(J88,$M:$M,$P:$P)-_xlfn.XLOOKUP(I88,$M:$M,$P:$P))*(1-Q88/100))/12,H88="discount_added",-(O88*P88*(J88-I88)/100)/12))} -> -125 | T88: =IF(H88<>"created",0,IF(COUNTIFS($C$1:C87,$C88,$H$1:H87,"created")=0,1,0)) -> 0 | U88: =IF(H88<>"cancelled",0,IF(COUNTIFS($C$2:$C$98,$C88,$H$2:$H$98,"created",$F$2:$F$98,"<="&F88)-COUNTIFS($C$2:$C$98,$C88,$H$2:$H$98,"cancelled",$F$2:$F$98,"<="&F88)=0,1,0)) -> 0 | V88: =IF(AND(H88="created",T88=0,COUNTIFS($C$2:$C$98,$C88,$H$2:$H$98,"cancelled",$F$2:$F$98,"<"&F88)>0,COUNTIFS($C$2:$C$98,$C88,$H$2:$H$98,"created",$F$2:$F$98,"<"&F88)-COUNTIFS($C$2:$C$98,$C88,$H$2:$H$98,"cancelled",$F$2:$F$98,"<"&F88)=0),1,0) -> 0
A89: EVT088 | B89: SUB024 | C89: CUST024 | D89: Western Retail Group | E89: Western Canada | F89: 45931 | G89: 45935 | H89: seats_change | I89: 26 | J89: 31 | K89: seats | L89: New department added - customer success team | M89: Marketing Pro | N89: Monthly | O89: 31 | P89: 85 | Q89: 0 | R89: {=_xlfn.IFS(H89="created", "New", H89="cancelled", "Churned", AND(H89="seats_change", J89 > I89), "Expansion", AND(H89="seats_change", J89 < I89), "Contraction", AND(H89="price_change", J89 > I89), "Expansion", AND(H89="price_change", J89 < I89), "Contraction", H89="plan_upgrade", "Expansion", H89="plan_downgrade", "Contraction", H89="discount_added", "Contraction")} -> Expansion | S89: {=IF(N89="Monthly",_xlfn.IFS(H89="created",O89*P89*(1-Q89/100),H89="cancelled",-(O89*P89*(1-Q89/100)),H89="seats_change",(J89-I89)*P89*(1-Q89/100),H89="price_change",(J89-I89)*O89*(1-Q89/100),H89="discount_added",-(O89*P89*(J89-I89)/100),H89="plan_upgrade",O89*(_xlfn.XLOOKUP(J89,$M:$M,$P:$P)-_xlfn.XLOOKUP(I89,$M:$M,$P:$P))*(1-Q89/100),H89="plan_downgrade",O89*(_xlfn.XLOOKUP(J89,$M:$M,$P:$P)-_xlfn.XLOOKUP(I89,$M:$M,$P:$P))*(1-Q89/100)),_xlfn.IFS(H89="created",O89*P89*(1-Q89/100)/12,H89="cancelled",-(O89*P89*(1-Q89/100))/12,H89="seats_change",(J89-I89)*P89*(1-Q89/100)/12,H89="price_change",(J89-I89)*O89*(1-Q89/100)/12,H89="plan_upgrade",(O89*(_xlfn.XLOOKUP(J89,$M:$M,$P:$P)-_xlfn.XLOOKUP(I89,$M:$M,$P:$P))*(1-Q89/100))/12,H89="plan_downgrade",(O89*(_xlfn.XLOOKUP(J89,$M:$M,$P:$P)-_xlfn.XLOOKUP(I89,$M:$M,$P:$P))*(1-Q89/100))/12,H89="discount_added",-(O89*P89*(J89-I89)/100)/12))} -> 425 | T89: =IF(H89<>"created",0,IF(COUNTIFS($C$1:C88,$C89,$H$1:H88,"created")=0,1,0)) -> 0 | U89: =IF(H89<>"cancelled",0,IF(COUNTIFS($C$2:$C$98,$C89,$H$2:$H$98,"created",$F$2:$F$98,"<="&F89)-COUNTIFS($C$2:$C$98,$C89,$H$2:$H$98,"cancelled",$F$2:$F$98,"<="&F89)=0,1,0)) -> 0 | V89: =IF(AND(H89="created",T89=0,COUNTIFS($C$2:$C$98,$C89,$H$2:$H$98,"cancelled",$F$2:$F$98,"<"&F89)>0,COUNTIFS($C$2:$C$98,$C89,$H$2:$H$98,"created",$F$2:$F$98,"<"&F89)-COUNTIFS($C$2:$C$98,$C89,$H$2:$H$98,"cancelled",$F$2:$F$98,"<"&F89)=0),1,0) -> 0
A90: EVT089 | B90: SUB062 | C90: CUST023 | D90: Island Media Productions | E90: Eastern Canada | F90: 45931 | G90: 45945 | H90: created | L90: Returning customer â€” reactivation | M90: Marketing Pro | N90: Monthly | O90: 11 | P90: 85 | Q90: 0 | R90: {=_xlfn.IFS(H90="created", "New", H90="cancelled", "Churned", AND(H90="seats_change", J90 > I90), "Expansion", AND(H90="seats_change", J90 < I90), "Contraction", AND(H90="price_change", J90 > I90), "Expansion", AND(H90="price_change", J90 < I90), "Contraction", H90="plan_upgrade", "Expansion", H90="plan_downgrade", "Contraction", H90="discount_added", "Contraction")} -> New | S90: {=IF(N90="Monthly",_xlfn.IFS(H90="created",O90*P90*(1-Q90/100),H90="cancelled",-(O90*P90*(1-Q90/100)),H90="seats_change",(J90-I90)*P90*(1-Q90/100),H90="price_change",(J90-I90)*O90*(1-Q90/100),H90="discount_added",-(O90*P90*(J90-I90)/100),H90="plan_upgrade",O90*(_xlfn.XLOOKUP(J90,$M:$M,$P:$P)-_xlfn.XLOOKUP(I90,$M:$M,$P:$P))*(1-Q90/100),H90="plan_downgrade",O90*(_xlfn.XLOOKUP(J90,$M:$M,$P:$P)-_xlfn.XLOOKUP(I90,$M:$M,$P:$P))*(1-Q90/100)),_xlfn.IFS(H90="created",O90*P90*(1-Q90/100)/12,H90="cancelled",-(O90*P90*(1-Q90/100))/12,H90="seats_change",(J90-I90)*P90*(1-Q90/100)/12,H90="price_change",(J90-I90)*O90*(1-Q90/100)/12,H90="plan_upgrade",(O90*(_xlfn.XLOOKUP(J90,$M:$M,$P:$P)-_xlfn.XLOOKUP(I90,$M:$M,$P:$P))*(1-Q90/100))/12,H90="plan_downgrade",(O90*(_xlfn.XLOOKUP(J90,$M:$M,$P:$P)-_xlfn.XLOOKUP(I90,$M:$M,$P:$P))*(1-Q90/100))/12,H90="discount_added",-(O90*P90*(J90-I90)/100)/12))} -> 935 | T90: =IF(H90<>"created",0,IF(COUNTIFS($C$1:C89,$C90,$H$1:H89,"created")=0,1,0)) -> 0 | U90: =IF(H90<>"cancelled",0,IF(COUNTIFS($C$2:$C$98,$C90,$H$2:$H$98,"created",$F$2:$F$98,"<="&F90)-COUNTIFS($C$2:$C$98,$C90,$H$2:$H$98,"cancelled",$F$2:$F$98,"<="&F90)=0,1,0)) -> 0 | V90: =IF(AND(H90="created",T90=0,COUNTIFS($C$2:$C$98,$C90,$H$2:$H$98,"cancelled",$F$2:$F$98,"<"&F90)>0,COUNTIFS($C$2:$C$98,$C90,$H$2:$H$98,"created",$F$2:$F$98,"<"&F90)-COUNTIFS($C$2:$C$98,$C90,$H$2:$H$98,"cancelled",$F$2:$F$98,"<"&F90)=0),1,0) -> 1
A91: EVT090 | B91: SUB036 | C91: CUST036 | D91: Manitoba Finance Group | E91: Central Canada | F91: 45931 | G91: 45950 | H91: plan_upgrade | I91: Analytics Starter | J91: Analytics Growth | K91: plan_name | L91: Reached Starter usage limits - upgraded | M91: Analytics Growth | N91: Monthly | O91: 18 | P91: 95 | Q91: 0 | R91: {=_xlfn.IFS(H91="created", "New", H91="cancelled", "Churned", AND(H91="seats_change", J91 > I91), "Expansion", AND(H91="seats_change", J91 < I91), "Contraction", AND(H91="price_change", J91 > I91), "Expansion", AND(H91="price_change", J91 < I91), "Contraction", H91="plan_upgrade", "Expansion", H91="plan_downgrade", "Contraction", H91="discount_added", "Contraction")} -> Expansion | S91: {=IF(N91="Monthly",_xlfn.IFS(H91="created",O91*P91*(1-Q91/100),H91="cancelled",-(O91*P91*(1-Q91/100)),H91="seats_change",(J91-I91)*P91*(1-Q91/100),H91="price_change",(J91-I91)*O91*(1-Q91/100),H91="discount_added",-(O91*P91*(J91-I91)/100),H91="plan_upgrade",O91*(_xlfn.XLOOKUP(J91,$M:$M,$P:$P)-_xlfn.XLOOKUP(I91,$M:$M,$P:$P))*(1-Q91/100),H91="plan_downgrade",O91*(_xlfn.XLOOKUP(J91,$M:$M,$P:$P)-_xlfn.XLOOKUP(I91,$M:$M,$P:$P))*(1-Q91/100)),_xlfn.IFS(H91="created",O91*P91*(1-Q91/100)/12,H91="cancelled",-(O91*P91*(1-Q91/100))/12,H91="seats_change",(J91-I91)*P91*(1-Q91/100)/12,H91="price_change",(J91-I91)*O91*(1-Q91/100)/12,H91="plan_upgrade",(O91*(_xlfn.XLOOKUP(J91,$M:$M,$P:$P)-_xlfn.XLOOKUP(I91,$M:$M,$P:$P))*(1-Q91/100))/12,H91="plan_downgrade",(O91*(_xlfn.XLOOKUP(J91,$M:$M,$P:$P)-_xlfn.XLOOKUP(I91,$M:$M,$P:$P))*(1-Q91/100))/12,H91="discount_added",-(O91*P91*(J91-I91)/100)/12))} -> 900 | T91: =IF(H91<>"created",0,IF(COUNTIFS($C$1:C90,$C91,$H$1:H90,"created")=0,1,0)) -> 0 | U91: =IF(H91<>"cancelled",0,IF(COUNTIFS($C$2:$C$98,$C91,$H$2:$H$98,"created",$F$2:$F$98,"<="&F91)-COUNTIFS($C$2:$C$98,$C91,$H$2:$H$98,"cancelled",$F$2:$F$98,"<="&F91)=0,1,0)) -> 0 | V91: =IF(AND(H91="created",T91=0,COUNTIFS($C$2:$C$98,$C91,$H$2:$H$98,"cancelled",$F$2:$F$98,"<"&F91)>0,COUNTIFS($C$2:$C$98,$C91,$H$2:$H$98,"created",$F$2:$F$98,"<"&F91)-COUNTIFS($C$2:$C$98,$C91,$H$2:$H$98,"cancelled",$F$2:$F$98,"<"&F91)=0),1,0) -> 0
A92: EVT091 | B92: SUB015 | C92: CUST015 | D92: BC Retail Networks | E92: Western Canada | F92: 45962 | G92: 45962 | H92: discount_added | I92: 0 | J92: 10 | K92: discount_percent | L92: Retention discount - customer at-risk of churning | M92: Analytics Growth | N92: Monthly | O92: 19 | P92: 95 | Q92: 10 | R92: {=_xlfn.IFS(H92="created", "New", H92="cancelled", "Churned", AND(H92="seats_change", J92 > I92), "Expansion", AND(H92="seats_change", J92 < I92), "Contraction", AND(H92="price_change", J92 > I92), "Expansion", AND(H92="price_change", J92 < I92), "Contraction", H92="plan_upgrade", "Expansion", H92="plan_downgrade", "Contraction", H92="discount_added", "Contraction")} -> Contraction | S92: {=IF(N92="Monthly",_xlfn.IFS(H92="created",O92*P92*(1-Q92/100),H92="cancelled",-(O92*P92*(1-Q92/100)),H92="seats_change",(J92-I92)*P92*(1-Q92/100),H92="price_change",(J92-I92)*O92*(1-Q92/100),H92="discount_added",-(O92*P92*(J92-I92)/100),H92="plan_upgrade",O92*(_xlfn.XLOOKUP(J92,$M:$M,$P:$P)-_xlfn.XLOOKUP(I92,$M:$M,$P:$P))*(1-Q92/100),H92="plan_downgrade",O92*(_xlfn.XLOOKUP(J92,$M:$M,$P:$P)-_xlfn.XLOOKUP(I92,$M:$M,$P:$P))*(1-Q92/100)),_xlfn.IFS(H92="created",O92*P92*(1-Q92/100)/12,H92="cancelled",-(O92*P92*(1-Q92/100))/12,H92="seats_change",(J92-I92)*P92*(1-Q92/100)/12,H92="price_change",(J92-I92)*O92*(1-Q92/100)/12,H92="plan_upgrade",(O92*(_xlfn.XLOOKUP(J92,$M:$M,$P:$P)-_xlfn.XLOOKUP(I92,$M:$M,$P:$P))*(1-Q92/100))/12,H92="plan_downgrade",(O92*(_xlfn.XLOOKUP(J92,$M:$M,$P:$P)-_xlfn.XLOOKUP(I92,$M:$M,$P:$P))*(1-Q92/100))/12,H92="discount_added",-(O92*P92*(J92-I92)/100)/12))} -> -180.5 | T92: =IF(H92<>"created",0,IF(COUNTIFS($C$1:C91,$C92,$H$1:H91,"created")=0,1,0)) -> 0 | U92: =IF(H92<>"cancelled",0,IF(COUNTIFS($C$2:$C$98,$C92,$H$2:$H$98,"created",$F$2:$F$98,"<="&F92)-COUNTIFS($C$2:$C$98,$C92,$H$2:$H$98,"cancelled",$F$2:$F$98,"<="&F92)=0,1,0)) -> 0 | V92: =IF(AND(H92="created",T92=0,COUNTIFS($C$2:$C$98,$C92,$H$2:$H$98,"cancelled",$F$2:$F$98,"<"&F92)>0,COUNTIFS($C$2:$C$98,$C92,$H$2:$H$98,"created",$F$2:$F$98,"<"&F92)-COUNTIFS($C$2:$C$98,$C92,$H$2:$H$98,"cancelled",$F$2:$F$98,"<"&F92)=0),1,0) -> 0
A93: EVT092 | B93: SUB039 | C93: CUST039 | D93: Toronto Commerce Cloud | E93: Eastern Canada | F93: 45962 | G93: 45976 | H93: seats_change | I93: 32 | J93: 29 | K93: seats | L93: Restructuring - reduced team size | M93: Marketing Pro | N93: Monthly | O93: 29 | P93: 85 | Q93: 0 | R93: {=_xlfn.IFS(H93="created", "New", H93="cancelled", "Churned", AND(H93="seats_change", J93 > I93), "Expansion", AND(H93="seats_change", J93 < I93), "Contraction", AND(H93="price_change", J93 > I93), "Expansion", AND(H93="price_change", J93 < I93), "Contraction", H93="plan_upgrade", "Expansion", H93="plan_downgrade", "Contraction", H93="discount_added", "Contraction")} -> Contraction | S93: {=IF(N93="Monthly",_xlfn.IFS(H93="created",O93*P93*(1-Q93/100),H93="cancelled",-(O93*P93*(1-Q93/100)),H93="seats_change",(J93-I93)*P93*(1-Q93/100),H93="price_change",(J93-I93)*O93*(1-Q93/100),H93="discount_added",-(O93*P93*(J93-I93)/100),H93="plan_upgrade",O93*(_xlfn.XLOOKUP(J93,$M:$M,$P:$P)-_xlfn.XLOOKUP(I93,$M:$M,$P:$P))*(1-Q93/100),H93="plan_downgrade",O93*(_xlfn.XLOOKUP(J93,$M:$M,$P:$P)-_xlfn.XLOOKUP(I93,$M:$M,$P:$P))*(1-Q93/100)),_xlfn.IFS(H93="created",O93*P93*(1-Q93/100)/12,H93="cancelled",-(O93*P93*(1-Q93/100))/12,H93="seats_change",(J93-I93)*P93*(1-Q93/100)/12,H93="price_change",(J93-I93)*O93*(1-Q93/100)/12,H93="plan_upgrade",(O93*(_xlfn.XLOOKUP(J93,$M:$M,$P:$P)-_xlfn.XLOOKUP(I93,$M:$M,$P:$P))*(1-Q93/100))/12,H93="plan_downgrade",(O93*(_xlfn.XLOOKUP(J93,$M:$M,$P:$P)-_xlfn.XLOOKUP(I93,$M:$M,$P:$P))*(1-Q93/100))/12,H93="discount_added",-(O93*P93*(J93-I93)/100)/12))} -> -255 | T93: =IF(H93<>"created",0,IF(COUNTIFS($C$1:C92,$C93,$H$1:H92,"created")=0,1,0)) -> 0 | U93: =IF(H93<>"cancelled",0,IF(COUNTIFS($C$2:$C$98,$C93,$H$2:$H$98,"created",$F$2:$F$98,"<="&F93)-COUNTIFS($C$2:$C$98,$C93,$H$2:$H$98,"cancelled",$F$2:$F$98,"<="&F93)=0,1,0)) -> 0 | V93: =IF(AND(H93="created",T93=0,COUNTIFS($C$2:$C$98,$C93,$H$2:$H$98,"cancelled",$F$2:$F$98,"<"&F93)>0,COUNTIFS($C$2:$C$98,$C93,$H$2:$H$98,"created",$F$2:$F$98,"<"&F93)-COUNTIFS($C$2:$C$98,$C93,$H$2:$H$98,"cancelled",$F$2:$F$98,"<"&F93)=0),1,0) -> 0
A94: EVT093 | B94: SUB047 | C94: CUST022 | D94: Toronto Tech Ventures | E94: Eastern Canada | F94: 45992 | G94: 45999 | H94: seats_change | I94: 22 | J94: 26 | K94: seats | L94: Year-end headcount increase | M94: Sales Hub | N94: Monthly | O94: 26 | P94: 110 | Q94: 0 | R94: {=_xlfn.IFS(H94="created", "New", H94="cancelled", "Churned", AND(H94="seats_change", J94 > I94), "Expansion", AND(H94="seats_change", J94 < I94), "Contraction", AND(H94="price_change", J94 > I94), "Expansion", AND(H94="price_change", J94 < I94), "Contraction", H94="plan_upgrade", "Expansion", H94="plan_downgrade", "Contraction", H94="discount_added", "Contraction")} -> Expansion | S94: {=IF(N94="Monthly",_xlfn.IFS(H94="created",O94*P94*(1-Q94/100),H94="cancelled",-(O94*P94*(1-Q94/100)),H94="seats_change",(J94-I94)*P94*(1-Q94/100),H94="price_change",(J94-I94)*O94*(1-Q94/100),H94="discount_added",-(O94*P94*(J94-I94)/100),H94="plan_upgrade",O94*(_xlfn.XLOOKUP(J94,$M:$M,$P:$P)-_xlfn.XLOOKUP(I94,$M:$M,$P:$P))*(1-Q94/100),H94="plan_downgrade",O94*(_xlfn.XLOOKUP(J94,$M:$M,$P:$P)-_xlfn.XLOOKUP(I94,$M:$M,$P:$P))*(1-Q94/100)),_xlfn.IFS(H94="created",O94*P94*(1-Q94/100)/12,H94="cancelled",-(O94*P94*(1-Q94/100))/12,H94="seats_change",(J94-I94)*P94*(1-Q94/100)/12,H94="price_change",(J94-I94)*O94*(1-Q94/100)/12,H94="plan_upgrade",(O94*(_xlfn.XLOOKUP(J94,$M:$M,$P:$P)-_xlfn.XLOOKUP(I94,$M:$M,$P:$P))*(1-Q94/100))/12,H94="plan_downgrade",(O94*(_xlfn.XLOOKUP(J94,$M:$M,$P:$P)-_xlfn.XLOOKUP(I94,$M:$M,$P:$P))*(1-Q94/100))/12,H94="discount_added",-(O94*P94*(J94-I94)/100)/12))} -> 440 | T94: =IF(H94<>"created",0,IF(COUNTIFS($C$1:C93,$C94,$H$1:H93,"created")=0,1,0)) -> 0 | U94: =IF(H94<>"cancelled",0,IF(COUNTIFS($C$2:$C$98,$C94,$H$2:$H$98,"created",$F$2:$F$98,"<="&F94)-COUNTIFS($C$2:$C$98,$C94,$H$2:$H$98,"cancelled",$F$2:$F$98,"<="&F94)=0,1,0)) -> 0 | V94: =IF(AND(H94="created",T94=0,COUNTIFS($C$2:$C$98,$C94,$H$2:$H$98,"cancelled",$F$2:$F$98,"<"&F94)>0,COUNTIFS($C$2:$C$98,$C94,$H$2:$H$98,"created",$F$2:$F$98,"<"&F94)-COUNTIFS($C$2:$C$98,$C94,$H$2:$H$98,"cancelled",$F$2:$F$98,"<"&F94)=0),1,0) -> 0
A95: EVT094 | B95: SUB050 | C95: CUST007 | D95: Ontario Manufacturing Tech | E95: Eastern Canada | F95: 45992 | G95: 46006 | H95: discount_added | I95: 0 | J95: 12 | K95: discount_percent | L95: Retention discount - at-risk account escalated | M95: Analytics Starter | N95: Monthly | O95: 15 | P95: 45 | Q95: 12 | R95: {=_xlfn.IFS(H95="created", "New", H95="cancelled", "Churned", AND(H95="seats_change", J95 > I95), "Expansion", AND(H95="seats_change", J95 < I95), "Contraction", AND(H95="price_change", J95 > I95), "Expansion", AND(H95="price_change", J95 < I95), "Contraction", H95="plan_upgrade", "Expansion", H95="plan_downgrade", "Contraction", H95="discount_added", "Contraction")} -> Contraction | S95: {=IF(N95="Monthly",_xlfn.IFS(H95="created",O95*P95*(1-Q95/100),H95="cancelled",-(O95*P95*(1-Q95/100)),H95="seats_change",(J95-I95)*P95*(1-Q95/100),H95="price_change",(J95-I95)*O95*(1-Q95/100),H95="discount_added",-(O95*P95*(J95-I95)/100),H95="plan_upgrade",O95*(_xlfn.XLOOKUP(J95,$M:$M,$P:$P)-_xlfn.XLOOKUP(I95,$M:$M,$P:$P))*(1-Q95/100),H95="plan_downgrade",O95*(_xlfn.XLOOKUP(J95,$M:$M,$P:$P)-_xlfn.XLOOKUP(I95,$M:$M,$P:$P))*(1-Q95/100)),_xlfn.IFS(H95="created",O95*P95*(1-Q95/100)/12,H95="cancelled",-(O95*P95*(1-Q95/100))/12,H95="seats_change",(J95-I95)*P95*(1-Q95/100)/12,H95="price_change",(J95-I95)*O95*(1-Q95/100)/12,H95="plan_upgrade",(O95*(_xlfn.XLOOKUP(J95,$M:$M,$P:$P)-_xlfn.XLOOKUP(I95,$M:$M,$P:$P))*(1-Q95/100))/12,H95="plan_downgrade",(O95*(_xlfn.XLOOKUP(J95,$M:$M,$P:$P)-_xlfn.XLOOKUP(I95,$M:$M,$P:$P))*(1-Q95/100))/12,H95="discount_added",-(O95*P95*(J95-I95)/100)/12))} -> -81 | T95: =IF(H95<>"created",0,IF(COUNTIFS($C$1:C94,$C95,$H$1:H94,"created")=0,1,0)) -> 0 | U95: =IF(H95<>"cancelled",0,IF(COUNTIFS($C$2:$C$98,$C95,$H$2:$H$98,"created",$F$2:$F$98,"<="&F95)-COUNTIFS($C$2:$C$98,$C95,$H$2:$H$98,"cancelled",$F$2:$F$98,"<="&F95)=0,1,0)) -> 0 | V95: =IF(AND(H95="created",T95=0,COUNTIFS($C$2:$C$98,$C95,$H$2:$H$98,"cancelled",$F$2:$F$98,"<"&F95)>0,COUNTIFS($C$2:$C$98,$C95,$H$2:$H$98,"created",$F$2:$F$98,"<"&F95)-COUNTIFS($C$2:$C$98,$C95,$H$2:$H$98,"cancelled",$F$2:$F$98,"<"&F95)=0),1,0) -> 0
