Workbook

Sheet Assumptions
A1: 2026 FORECAST — ASSUMPTIONS (monthly base)
A2: The 2026 Plan of Record (monthly). Driver-based from the Dec-2025 leadership assumptions. All values are hardcoded inputs; every formula on 'Monthly Forecast' references this tab. Actuals are compared against this plan month by month, starting January.
A4: STARTING POSITION
A5: Opening MRR (Jan 2026) | B5: 143069.5 | C5: Dec 2025 closing MRR (Historical Baseline)
A7: MONTHLY RATES (scalar)
A8: Expansion rate / month | B8: 0.005 | C8: Plan: 0.50%/mo (compounds to ~1.5%/qtr). Applies to beginning-of-month MRR.
A9: Churn rate / month | B9: 0.0067 | C9: Plan: 0.67%/mo (compounds to ~2%/qtr). Beginning-of-month MRR.
A10: Gross margin | B10: 0.7 | C10: Plan — no cost-structure change (COGS = 1 − GM)
A12: MONTHLY DRIVERS
A13: Month | B13: Jan-26 | C13: Feb-26 | D13: Mar-26 | E13: Apr-26 | F13: May-26 | G13: Jun-26 | H13: Jul-26 | I13: Aug-26 | J13: Sep-26 | K13: Oct-26 | L13: Nov-26 | M13: Dec-26
A14: New customers | B14: 1 | C14: 1 | D14: 2 | E14: 2 | F14: 2 | G14: 2 | H14: 3 | I14: 3 | J14: 3 | K14: 3 | L14: 3 | M14: 3 | O14: Monthly phasing = analyst judgment; sums to Dec plan quarterly totals (4/6/9/9).
A15: Avg MRR / new customer | B15: 3000 | C15: 3000 | D15: 3000 | E15: 3200 | F15: 3200 | G15: 3200 | H15: 3200 | I15: 3200 | J15: 3200 | K15: 3400 | L15: 3400 | M15: 3400 | O15: Plan: Q1 $3,000 · Q2–Q3 $3,200 · Q4 $3,400 per new customer.
A16: Sales & Marketing | B16: 30000 | C16: 30000 | D16: 30000 | E16: 30000 | F16: 30000 | G16: 30000 | H16: 36000 | I16: 36000 | J16: 36000 | K16: 36000 | L16: 36000 | M16: 36000 | O16: Plan: $30k/mo H1, $36k/mo H2 (S&M acquisition push).
A17: Research & Development | B17: 25000 | C17: 25000 | D17: 25000 | E17: 25000 | F17: 25000 | G17: 25000 | H17: 25000 | I17: 25000 | J17: 25000 | K17: 25000 | L17: 25000 | M17: 25000 | O17: Plan: $75k/qtr ÷ 3.
A18: General & Administrative | B18: 19000 | C18: 19000 | D18: 19000 | E18: 19000 | F18: 19000 | G18: 19000 | H18: 19000 | I18: 19000 | J18: 19000 | K18: 19000 | L18: 19000 | M18: 19000 | O18: Plan: $57k/qtr ÷ 3.

Sheet Monthly Forecast
A1: 2026 PLAN OF RECORD — Monthly (driver-based). Every cell references Assumptions. Blue = subtotals.
A3: MRR WATERFALL
A4: Metric | B4: Jan-26 | C4: Feb-26 | D4: Mar-26 | E4: Apr-26 | F4: May-26 | G4: Jun-26 | H4: Jul-26 | I4: Aug-26 | J4: Sep-26 | K4: Oct-26 | L4: Nov-26 | M4: Dec-26 | N4: Q1 2026 | O4: Q2 2026 | P4: Q3 2026 | Q4: Q4 2026 | R4: FY 2026
A5: Opening MRR | B5: =Assumptions!$B$5 | C5: =B11 | D5: =C11 | E5: =D11 | F5: =E11 | G5: =F11 | H5: =G11 | I5: =H11 | J5: =I11 | ... M5: =L11 | N5: =B5 | O5: =E5 | P5: =H5 | Q5: =K5 | R5: =B5
A6: + New MRR | B6: =Assumptions!B14*Assumptions!B15 | C6: =Assumptions!C14*Assumptions!C15 | D6: =Assumptions!D14*Assumptions!D15 | E6: =Assumptions!E14*Assumptions!E15 | F6: =Assumptions!F14*Assumptions!F15 | G6: =Assumptions!G14*Assumptions!G15 | H6: =Assumptions!H14*Assumptions!H15 | I6: =Assumptions!I14*Assumptions!I15 | ... M6: =Assumptions!M14*Assumptions!M15 | N6: =SUM(B6:D6) | O6: =SUM(E6:G6) | P6: =SUM(H6:J6) | Q6: =SUM(K6:M6) | R6: =SUM(B6:M6)
A7: + Expansion MRR | B7: =B5*Assumptions!$B$8 | C7: =C5*Assumptions!$B$8 | D7: =D5*Assumptions!$B$8 | E7: =E5*Assumptions!$B$8 | F7: =F5*Assumptions!$B$8 | G7: =G5*Assumptions!$B$8 | H7: =H5*Assumptions!$B$8 | I7: =I5*Assumptions!$B$8 | ... M7: =M5*Assumptions!$B$8 | N7: =SUM(B7:D7) | O7: =SUM(E7:G7) | P7: =SUM(H7:J7) | Q7: =SUM(K7:M7) | R7: =SUM(B7:M7)
A8: − Contraction MRR | B8: 0 | C8: 0 | D8: 0 | E8: 0 | F8: 0 | G8: 0 | H8: 0 | I8: 0 | J8: 0 | K8: 0 | L8: 0 | M8: 0 | N8: =SUM(B8:D8) | O8: =SUM(E8:G8) | P8: =SUM(H8:J8) | Q8: =SUM(K8:M8) | R8: =SUM(B8:M8)
A9: − Churned MRR | B9: =B5*Assumptions!$B$9 | C9: =C5*Assumptions!$B$9 | D9: =D5*Assumptions!$B$9 | E9: =E5*Assumptions!$B$9 | F9: =F5*Assumptions!$B$9 | G9: =G5*Assumptions!$B$9 | H9: =H5*Assumptions!$B$9 | I9: =I5*Assumptions!$B$9 | ... M9: =M5*Assumptions!$B$9 | N9: =SUM(B9:D9) | O9: =SUM(E9:G9) | P9: =SUM(H9:J9) | Q9: =SUM(K9:M9) | R9: =SUM(B9:M9)
A10: Net New MRR | B10: =B6+B7-B8-B9 | C10: =C6+C7-C8-C9 | D10: =D6+D7-D8-D9 | E10: =E6+E7-E8-E9 | F10: =F6+F7-F8-F9 | G10: =G6+G7-G8-G9 | H10: =H6+H7-H8-H9 | I10: =I6+I7-I8-I9 | ... M10: =M6+M7-M8-M9 | N10: =SUM(B10:D10) | O10: =SUM(E10:G10) | P10: =SUM(H10:J10) | Q10: =SUM(K10:M10) | R10: =SUM(B10:M10)
A11: Closing MRR | B11: =B5+B10 | C11: =C5+C10 | D11: =D5+D10 | E11: =E5+E10 | F11: =F5+F10 | G11: =G5+G10 | H11: =H5+H10 | I11: =I5+I10 | ... M11: =M5+M10 | N11: =D11 | O11: =G11 | P11: =J11 | Q11: =M11 | R11: =M11
A12: Closing ARR | B12: =B11*12 | C12: =C11*12 | D12: =D11*12 | E12: =E11*12 | F12: =F11*12 | G12: =G11*12 | H12: =H11*12 | I12: =I11*12 | ... R12: =R11*12
A14: PROFIT & LOSS
A15: Metric | B15: Jan-26 | C15: Feb-26 | D15: Mar-26 | E15: Apr-26 | F15: May-26 | G15: Jun-26 | H15: Jul-26 | I15: Aug-26 | J15: Sep-26 | K15: Oct-26 | L15: Nov-26 | M15: Dec-26 | N15: Q1 2026 | O15: Q2 2026 | P15: Q3 2026 | Q15: Q4 2026 | R15: FY 2026
A16: Revenue | B16: =B11 | C16: =C11 | D16: =D11 | E16: =E11 | F16: =F11 | G16: =G11 | H16: =H11 | I16: =I11 | ... M16: =M11 | N16: =SUM(B16:D16) | O16: =SUM(E16:G16) | P16: =SUM(H16:J16) | Q16: =SUM(K16:M16) | R16: =SUM(B16:M16)
A17: COGS | B17: =B16*(1-Assumptions!$B$10) | C17: =C16*(1-Assumptions!$B$10) | D17: =D16*(1-Assumptions!$B$10) | E17: =E16*(1-Assumptions!$B$10) | F17: =F16*(1-Assumptions!$B$10) | G17: =G16*(1-Assumptions!$B$10) | H17: =H16*(1-Assumptions!$B$10) | I17: =I16*(1-Assumptions!$B$10) | ... M17: =M16*(1-Assumptions!$B$10) | N17: =SUM(B17:D17) | O17: =SUM(E17:G17) | P17: =SUM(H17:J17) | Q17: =SUM(K17:M17) | R17: =SUM(B17:M17)
A18: Gross Profit | B18: =B16-B17 | C18: =C16-C17 | D18: =D16-D17 | E18: =E16-E17 | F18: =F16-F17 | G18: =G16-G17 | H18: =H16-H17 | I18: =I16-I17 | ... M18: =M16-M17 | N18: =SUM(B18:D18) | O18: =SUM(E18:G18) | P18: =SUM(H18:J18) | Q18: =SUM(K18:M18) | R18: =SUM(B18:M18)
A19: Gross Margin % | B19: =B18/B16 | C19: =C18/C16 | D19: =D18/D16 | E19: =E18/E16 | F19: =F18/F16 | G19: =G18/G16 | H19: =H18/H16 | I19: =I18/I16 | ... R19: =R18/R16
A20: Sales & Marketing | B20: =Assumptions!B16 | C20: =Assumptions!C16 | D20: =Assumptions!D16 | E20: =Assumptions!E16 | F20: =Assumptions!F16 | G20: =Assumptions!G16 | H20: =Assumptions!H16 | I20: =Assumptions!I16 | ... M20: =Assumptions!M16 | N20: =SUM(B20:D20) | O20: =SUM(E20:G20) | P20: =SUM(H20:J20) | Q20: =SUM(K20:M20) | R20: =SUM(B20:M20)
A21: Research & Development | B21: =Assumptions!B17 | C21: =Assumptions!C17 | D21: =Assumptions!D17 | E21: =Assumptions!E17 | F21: =Assumptions!F17 | G21: =Assumptions!G17 | H21: =Assumptions!H17 | I21: =Assumptions!I17 | ... M21: =Assumptions!M17 | N21: =SUM(B21:D21) | O21: =SUM(E21:G21) | P21: =SUM(H21:J21) | Q21: =SUM(K21:M21) | R21: =SUM(B21:M21)
A22: General & Administrative | B22: =Assumptions!B18 | C22: =Assumptions!C18 | D22: =Assumptions!D18 | E22: =Assumptions!E18 | F22: =Assumptions!F18 | G22: =Assumptions!G18 | H22: =Assumptions!H18 | I22: =Assumptions!I18 | ... M22: =Assumptions!M18 | N22: =SUM(B22:D22) | O22: =SUM(E22:G22) | P22: =SUM(H22:J22) | Q22: =SUM(K22:M22) | R22: =SUM(B22:M22)
A23: Total OpEx | B23: =SUM(B20:B22) | C23: =SUM(C20:C22) | D23: =SUM(D20:D22) | E23: =SUM(E20:E22) | F23: =SUM(F20:F22) | G23: =SUM(G20:G22) | H23: =SUM(H20:H22) | I23: =SUM(I20:I22) | ... M23: =SUM(M20:M22) | N23: =SUM(B23:D23) | O23: =SUM(E23:G23) | P23: =SUM(H23:J23) | Q23: =SUM(K23:M23) | R23: =SUM(B23:M23)
A24: EBITDA | B24: =B18-B23 | C24: =C18-C23 | D24: =D18-D23 | E24: =E18-E23 | F24: =F18-F23 | G24: =G18-G23 | H24: =H18-H23 | I24: =I18-I23 | ... M24: =M18-M23 | N24: =SUM(B24:D24) | O24: =SUM(E24:G24) | P24: =SUM(H24:J24) | Q24: =SUM(K24:M24) | R24: =SUM(B24:M24)
A25: EBITDA Margin % | B25: =B24/B16 | C25: =C24/C16 | D25: =D24/D16 | E25: =E24/E16 | F25: =F24/F16 | G25: =G24/G16 | H25: =H24/H16 | I25: =I24/I16 | ... R25: =R24/R16
