Workbook

Sheet Price-Volume Bridge
A2: Scenario | B2: Quantity | C2: Price | D2: Δ Revenue | E2: Volume effect | F2: Price effect | G2: Dominant driver
A3: Northwind Retail:
A4: Prior | B4: 500 | C4: 20 | D4: =E4+F4 -> 1340 | E4: =(B5-B4)*C4 -> 800 | F4: =(C5-C4)*B5 -> 540 | G4: =IF(E4>F4, "Volume", "Price") -> Volume
A5: Current | B5: 540 | C5: 21
A6: Cascade Tools:
A7: Prior | B7: 1000 | C7: 50 | D7: =E7+F7 -> 2250 | E7: =(B8-B7)*C7 -> -2500 | F7: =(C8-C7)*B8 -> 4750 | G7: =IF(E7>F7, "Volume", "Price") -> Price
A8: Current | B8: 950 | C8: 55
A9: Riverstone Supply:
A10: Prior | B10: 2000 | C10: 8 | D10: =E10+F10 -> 2000 | E10: =(B11-B10)*C10 -> 3200 | F10: =(C11-C10)*B11 -> -1200 | G10: =IF(E10>F10, "Volume", "Price") -> Volume
A11: Current | B11: 2400 | C11: 7.5
A12: iDynamics:
A13: Prior (Q1 2025) | B13: 50 | C13: 3000 | D13: =E13+F13 -> 29200 | E13: =(B14-B13)*C13 -> 18000 | F13: =(C14-C13)*B14 -> 11200 | G13: =IF(E13>F13, "Volume", "Price") -> Volume
A14: Current (Q1 2026) | B14: 56 | C14: 3200
A16: Paragraph 1:
A17: Our total increase in revenue during this period was $29,200.
A18: This growth stemmed from an increase in volume of $18,000 from adding customers and a $11,200 increase in price.
A19: This indicates that our growth primarily comes from additional customers which is a healthy sign.
A20: This mix indicates that both the volume and price effect are positive and our growth was sustained from each side.
A21: The increase in volume means that we continue to grow our market share. The increase in price having a positive effect on revenue indicates that we have pricing power.
A23: Paragraph 2:
A24: Cascade saw an increase in revenue of $2,250 with the only gain coming from the price effect.
A25: This means that they have pricing power but the revenue increase comes at the cost of 50 customers.
A26: A price increase of 10% has come at the cost of a 5% decrease in customer base.
A27: I would look at the demand in future periods to see the effects of this price increase.
A28: Their strategy is to increase the price and lower the cost per unit.
A29: Based on the revenue delta, we can infer that a 1% price increase will create roughly a 2% decrease in customer base which is healthy.

Sheet billing_jan_2026
A1: invoice_id | B1: invoice_number | C1: invoice_date | D1: customer_id | E1: customer_name | F1: subscription_id | G1: plan_name | H1: billing_cycle | I1: period_start | J1: period_end | K1: seats | L1: unit_price_usd | M1: subtotal | N1: discount_pct | O1: discount_amount | P1: amount_due_usd | Q1: status | R1: payment_date | S1: failure_reason
A2: in_20260100001 | B2: INV-2026-01-0001 | C2: 46023 | D2: CUST007 | E2: Ontario Manufacturing Tech | F2: SUB007 | G2: Marketing Pro | H2: Monthly | I2: 46023 | J2: 46053 | K2: 16 | L2: 85 | M2: 1360 | N2: 0 | O2: 0 | P2: 1360 | Q2: paid | R2: 46023
A3: in_20260100002 | B3: INV-2026-01-0002 | C3: 46023 | D3: CUST007 | E3: Ontario Manufacturing Tech | F3: SUB050 | G3: Analytics Starter | H3: Monthly | I3: 46023 | J3: 46053 | K3: 15 | L3: 45 | M3: 675 | N3: 12 | O3: 81 | P3: 594 | Q3: paid | R3: 46023
A4: in_20260100003 | B4: INV-2026-01-0003 | C4: 46024 | D4: CUST018 | E4: Vancouver FinTech Labs | F4: SUB018 | G4: Analytics Enterprise | H4: Monthly | I4: 46024 | J4: 46053 | K4: 35 | L4: 180 | M4: 6300 | N4: 0 | O4: 0 | P4: 6300 | Q4: paid | R4: 46024
A5: in_20260100004 | B5: INV-2026-01-0004 | C5: 46025 | D5: CUST029 | E5: Halifax Healthcare Tech | F5: SUB029 | G5: Marketing Pro | H5: Monthly | I5: 46025 | J5: 46053 | K5: 22 | L5: 85 | M5: 1870 | N5: 0 | O5: 0 | P5: 1870 | Q5: paid | R5: 46025
A6: in_20260100005 | B6: INV-2026-01-0005 | C6: 46027 | D6: CUST003 | E6: Maple Healthcare Systems | F6: SUB003 | G6: Marketing Pro | H6: Monthly | I6: 46027 | J6: 46053 | K6: 23 | L6: 85 | M6: 1955 | N6: 0 | O6: 0 | P6: 1955 | Q6: paid | R6: 46027
A7: in_20260100006 | B7: INV-2026-01-0006 | C7: 46027 | D7: CUST006 | E7: Northern Retail Solutions | F7: SUB043 | G7: Marketing Pro | H7: Monthly | I7: 46027 | J7: 46053 | K7: 33 | L7: 85 | M7: 2805 | N7: 0 | O7: 0 | P7: 2805 | Q7: paid | R7: 46027
A8: in_20260100007 | B8: INV-2026-01-0007 | C8: 46027 | D8: CUST027 | E8: Pacific Finance Corp | F8: SUB053 | G8: Analytics Enterprise | H8: Monthly | I8: 46027 | J8: 46053 | K8: 31 | L8: 180 | M8: 5580 | N8: 0 | O8: 0 | P8: 5580 | Q8: paid | R8: 46027
A9: in_20260100008 | B9: INV-2026-01-0008 | C9: 46027 | D9: CUST008 | E9: Quantum Education Platform | F9: SUB059 | G9: Marketing Pro | H9: Monthly | I9: 46027 | J9: 46053 | K9: 22 | L9: 85 | M9: 1870 | N9: 0 | O9: 0 | P9: 1870 | Q9: paid | R9: 46027
A10: in_20260100009 | B10: INV-2026-01-0009 | C10: 46028 | D10: CUST027 | E10: Pacific Finance Corp | F10: SUB027 | G10: Sales Hub | H10: Monthly | I10: 46028 | J10: 46053 | K10: 28 | L10: 110 | M10: 3080 | N10: 0 | O10: 0 | P10: 3080 | Q10: paid | R10: 46028
A11: in_20260100010 | B11: INV-2026-01-0010 | C11: 46030 | D11: CUST014 | E11: Toronto Media Group | F11: SUB014 | G11: Marketing Pro | H11: Monthly | I11: 46030 | J11: 46053 | K11: 28 | L11: 85 | M11: 2380 | N11: 0 | O11: 0 | P11: 2380 | Q11: paid | R11: 46030
A12: in_20260100011 | B12: INV-2026-01-0011 | C12: 46030 | D12: CUST010 | E12: Montreal Finance Hub | F12: SUB045 | G12: Marketing Pro | H12: Monthly | I12: 46030 | J12: 46053 | K12: 13 | L12: 85 | M12: 1105 | N12: 0 | O12: 0 | P12: 1105 | Q12: paid | R12: 46030
A13: in_20260100012 | B13: INV-2026-01-0012 | C13: 46030 | D13: CUST024 | E13: Western Retail Group | F13: SUB058 | G13: Sales Hub | H13: Monthly | I13: 46030 | J13: 46053 | K13: 26 | L13: 110 | M13: 2860 | N13: 0 | O13: 0 | P13: 2860 | Q13: paid | R13: 46030
... A30: in_20260100029 | B30: INV-2026-01-0029 | C30: 46041 | D30: CUST017 | E30: Capital Education Tech | F30: SUB017 | G30: Analytics Starter | H30: Monthly | I30: 46041 | J30: 46053 | K30: 12 | L30: 45 | M30: 540 | N30: 0 | O30: 0 | P30: 540 | Q30: paid | R30: 46041
A31: in_20260100030 | B31: INV-2026-01-0030 | C31: 46042 | D31: CUST028 | E31: Prairie SaaS Innovations | F31: SUB028 | G31: Analytics Starter | H31: Monthly | I31: 46042 | J31: 46053 | K31: 15 | L31: 45 | M31: 675 | N31: 0 | O31: 0 | P31: 675 | Q31: failed | S31: Insufficient funds
A32: in_20260100031 | B32: INV-2026-01-0031 | C32: 46042 | D32: CUST009 | E32: West Coast Logistics | F32: SUB044 | G32: Analytics Growth | H32: Monthly | I32: 46042 | J32: 46053 | K32: 35 | L32: 95 | M32: 3325 | N32: 0 | O32: 0 | P32: 3325 | Q32: paid | R32: 46042
A33: in_20260100032 | B33: INV-2026-01-0032 | C33: 46042 | D33: CUST013 | E33: Alberta Tech Innovators | F33: SUB061 | G33: Analytics Growth | H33: Monthly | I33: 46042 | J33: 46053 | K33: 12 | L33: 95 | M33: 1140 | N33: 0 | O33: 0 | P33: 1140 | Q33: paid | R33: 46042
A34: in_20260100033 | B34: INV-2026-01-0033 | C34: 46044 | D34: CUST002 | E34: Pacific Analytics Inc | F34: SUB002 | G34: Platform Suite | H34: Annual | I34: 46044 | J34: 46408 | K34: 26 | L34: 1800 | M34: 46800 | N34: 0 | O34: 0 | P34: 46800 | Q34: paid | R34: 46044
A35: in_20260100034 | B35: INV-2026-01-0034 | C35: 46044 | D35: CUST015 | E35: BC Retail Networks | F35: SUB046 | G35: Analytics Enterprise | H35: Monthly | I35: 46044 | J35: 46053 | K35: 20 | L35: 180 | M35: 3600 | N35: 0 | O35: 0 | P35: 3600 | Q35: paid | R35: 46044
A36: in_20260100035 | B36: INV-2026-01-0035 | C36: 46044 | D36: CUST025 | E36: Montreal Manufacturing Pro | F36: SUB048 | G36: Sales Hub | H36: Monthly | I36: 46044 | J36: 46053 | K36: 36 | L36: 110 | M36: 3960 | N36: 0 | O36: 0 | P36: 3960 | Q36: paid | R36: 46044
A37: in_20260100036 | B37: INV-2026-01-0036 | C37: 46044 | D37: CUST002 | E37: Pacific Analytics Inc | F37: SUB054 | G37: Analytics Growth | H37: Annual | I37: 46044 | J37: 46408 | K37: 22 | L37: 1140 | M37: 25080 | N37: 5 | O37: 1254 | P37: 23826 | Q37: paid | R37: 46044
A38: in_20260100037 | B38: INV-2026-01-0037 | C38: 46045 | D38: CUST026 | E38: Ontario Education Connect | F38: SUB026 | G38: Analytics Growth | H38: Monthly | I38: 46045 | J38: 46053 | K38: 16 | L38: 95 | M38: 1520 | N38: 0 | O38: 0 | P38: 1520 | Q38: paid | R38: 46045
A39: in_20260100038 | B39: INV-2026-01-0038 | C39: 46045 | D39: CUST039 | E39: Toronto Commerce Cloud | F39: SUB039 | G39: Marketing Pro | H39: Monthly | I39: 46045 | J39: 46053 | K39: 29 | L39: 85 | M39: 2465 | N39: 0 | O39: 0 | P39: 2465 | Q39: paid | R39: 46045
A40: in_20260100039 | B40: INV-2026-01-0039 | C40: 46047 | D40: CUST024 | E40: Western Retail Group | F40: SUB024 | G40: Marketing Pro | H40: Monthly | I40: 46047 | J40: 46053 | K40: 31 | L40: 85 | M40: 2635 | N40: 0 | O40: 0 | P40: 2635 | Q40: paid | R40: 46047
A41: in_20260100040 | B41: INV-2026-01-0040 | C41: 46048 | D41: CUST037 | E41: Maritime SaaS Ventures | F41: SUB037 | G41: Platform Suite | H41: Monthly | I41: 46048 | J41: 46053 | K41: 35 | L41: 150 | M41: 5250 | N41: 0 | O41: 0 | P41: 5250 | Q41: paid | R41: 46048
A42: in_20260100041 | B42: INV-2026-01-0041 | C42: 46048 | D42: CUST040 | E42: BC Education Innovations | F42: SUB040 | G42: Analytics Growth | H42: Monthly | I42: 46048 | J42: 46053 | K42: 18 | L42: 95 | M42: 1710 | N42: 0 | O42: 0 | P42: 1710 | Q42: paid | R42: 46048
A43: in_20260100042 | B43: INV-2026-01-0042 | C43: 46049 | D43: CUST011 | E43: Prairie Health Connect | F43: SUB011 | G43: Sales Hub | H43: Monthly | I43: 46049 | J43: 46053 | K43: 18 | L43: 110 | M43: 1980 | N43: 0 | O43: 0 | P43: 1980 | Q43: paid | R43: 46049
... A48: in_20260100047 | B48: INV-2026-01-0047 | C48: 46053 | D48: CUST033 | E48: Ottawa Retail Solutions | F48: SUB033 | G48: Marketing Pro | H48: Monthly | I48: 46053 | J48: 46053 | K48: 25 | L48: 85 | M48: 2125 | N48: 0 | O48: 0 | P48: 2125 | Q48: paid | R48: 46053

Sheet billing_feb_2026
A1: invoice_id | B1: invoice_number | C1: invoice_date | D1: customer_id | E1: customer_name | F1: subscription_id | G1: plan_name | H1: billing_cycle | I1: period_start | J1: period_end | K1: seats | L1: unit_price_usd | M1: subtotal | N1: discount_pct | O1: discount_amount | P1: amount_due_usd | Q1: status | R1: payment_date | S1: failure_reason
A2: in_20260200001 | B2: INV-2026-02-0001 | C2: 46054 | D2: CUST007 | E2: Ontario Manufacturing Tech | F2: SUB007 | G2: Marketing Pro | H2: Monthly | I2: 46054 | J2: 46081 | K2: 16 | L2: 85 | M2: 1360 | N2: 0 | O2: 0 | P2: 1360 | Q2: paid | R2: 46054
A3: in_20260200002 | B3: INV-2026-02-0002 | C3: 46054 | D3: CUST007 | E3: Ontario Manufacturing Tech | F3: SUB050 | G3: Analytics Starter | H3: Monthly | I3: 46054 | J3: 46081 | K3: 15 | L3: 45 | M3: 675 | N3: 12 | O3: 81 | P3: 594 | Q3: paid | R3: 46054
A4: in_20260200003 | B4: INV-2026-02-0003 | C4: 46055 | D4: CUST018 | E4: Vancouver FinTech Labs | F4: SUB018 | G4: Analytics Enterprise | H4: Monthly | I4: 46055 | J4: 46081 | K4: 35 | L4: 180 | M4: 6300 | N4: 0 | O4: 0 | P4: 6300 | Q4: paid | R4: 46055
A5: in_20260200004 | B5: INV-2026-02-0004 | C5: 46056 | D5: CUST029 | E5: Halifax Healthcare Tech | F5: SUB029 | G5: Marketing Pro | H5: Monthly | I5: 46056 | J5: 46081 | K5: 22 | L5: 85 | M5: 1870 | N5: 0 | O5: 0 | P5: 1870 | Q5: paid | R5: 46056
A6: in_20260200005 | B6: INV-2026-02-0005 | C6: 46058 | D6: CUST003 | E6: Maple Healthcare Systems | F6: SUB003 | G6: Marketing Pro | H6: Monthly | I6: 46058 | J6: 46081 | K6: 23 | L6: 85 | M6: 1955 | N6: 0 | O6: 0 | P6: 1955 | Q6: paid | R6: 46058
A7: in_20260200006 | B7: INV-2026-02-0006 | C7: 46058 | D7: CUST006 | E7: Northern Retail Solutions | F7: SUB043 | G7: Marketing Pro | H7: Monthly | I7: 46058 | J7: 46081 | K7: 33 | L7: 85 | M7: 2805 | N7: 0 | O7: 0 | P7: 2805 | Q7: paid | R7: 46058
A8: in_20260200007 | B8: INV-2026-02-0007 | C8: 46058 | D8: CUST027 | E8: Pacific Finance Corp | F8: SUB053 | G8: Analytics Enterprise | H8: Monthly | I8: 46058 | J8: 46081 | K8: 31 | L8: 180 | M8: 5580 | N8: 0 | O8: 0 | P8: 5580 | Q8: paid | R8: 46058
A9: in_20260200008 | B9: INV-2026-02-0008 | C9: 46058 | D9: CUST008 | E9: Quantum Education Platform | F9: SUB059 | G9: Marketing Pro | H9: Monthly | I9: 46058 | J9: 46081 | K9: 22 | L9: 85 | M9: 1870 | N9: 0 | O9: 0 | P9: 1870 | Q9: paid | R9: 46058
A10: in_20260200009 | B10: INV-2026-02-0009 | C10: 46059 | D10: CUST027 | E10: Pacific Finance Corp | F10: SUB027 | G10: Sales Hub | H10: Monthly | I10: 46059 | J10: 46081 | K10: 28 | L10: 110 | M10: 3080 | N10: 0 | O10: 0 | P10: 3080 | Q10: paid | R10: 46059
A11: in_20260200010 | B11: INV-2026-02-0010 | C11: 46061 | D11: CUST014 | E11: Toronto Media Group | F11: SUB014 | G11: Marketing Pro | H11: Monthly | I11: 46061 | J11: 46081 | K11: 28 | L11: 85 | M11: 2380 | N11: 0 | O11: 0 | P11: 2380 | Q11: paid | R11: 46061
A12: in_20260200011 | B12: INV-2026-02-0011 | C12: 46061 | D12: CUST010 | E12: Montreal Finance Hub | F12: SUB045 | G12: Marketing Pro | H12: Monthly | I12: 46061 | J12: 46081 | K12: 13 | L12: 85 | M12: 1105 | N12: 0 | O12: 0 | P12: 1105 | Q12: paid | R12: 46061
A13: in_20260200012 | B13: INV-2026-02-0012 | C13: 46061 | D13: CUST024 | E13: Western Retail Group | F13: SUB058 | G13: Sales Hub | H13: Monthly | I13: 46061 | J13: 46081 | K13: 26 | L13: 110 | M13: 2860 | N13: 0 | O13: 0 | P13: 2860 | Q13: paid | R13: 46061
... A35: in_20260200034 | B35: INV-2026-02-0034 | C35: 46073 | D35: CUST042 | E35: Pacific Coast Analytics | F35: SUB064 | G35: Analytics Growth | H35: Monthly | I35: 46073 | J35: 46081 | K35: 32 | L35: 95 | M35: 3040 | N35: 0 | O35: 0 | P35: 3040 | Q35: paid | R35: 46073
A36: in_20260299001 | B36: CN-2026-02-0001 | C36: 46074 | D36: CUST007 | E36: Ontario Manufacturing Tech | F36: SUB050 | G36: Analytics Starter | H36: Monthly | I36: 46074 | J36: 46081 | K36: 15 | L36: 45 | M36: 675 | N36: 12 | O36: 81 | P36: -169.71 | Q36: refunded | R36: 46074 | S36: Prorated refund â€” subscription cancelled 2026-02-20
A37: in_20260200035 | B37: INV-2026-02-0035 | C37: 46075 | D37: CUST015 | E37: BC Retail Networks | F37: SUB046 | G37: Analytics Enterprise | H37: Monthly | I37: 46075 | J37: 46081 | K37: 20 | L37: 180 | M37: 3600 | N37: 0 | O37: 0 | P37: 3600 | Q37: paid | R37: 46075
A38: in_20260200036 | B38: INV-2026-02-0036 | C38: 46075 | D38: CUST025 | E38: Montreal Manufacturing Pro | F38: SUB048 | G38: Sales Hub | H38: Monthly | I38: 46075 | J38: 46081 | K38: 36 | L38: 110 | M38: 3960 | N38: 0 | O38: 0 | P38: 3960 | Q38: paid | R38: 46075
A39: in_20260200037 | B39: INV-2026-02-0037 | C39: 46076 | D39: CUST026 | E39: Ontario Education Connect | F39: SUB026 | G39: Analytics Growth | H39: Monthly | I39: 46076 | J39: 46081 | K39: 16 | L39: 95 | M39: 1520 | N39: 0 | O39: 0 | P39: 1520 | Q39: paid | R39: 46076
A40: in_20260200038 | B40: INV-2026-02-0038 | C40: 46076 | D40: CUST039 | E40: Toronto Commerce Cloud | F40: SUB039 | G40: Marketing Pro | H40: Monthly | I40: 46076 | J40: 46081 | K40: 29 | L40: 85 | M40: 2465 | N40: 0 | O40: 0 | P40: 2465 | Q40: paid | R40: 46076
A41: in_20260200039 | B41: INV-2026-02-0039 | C41: 46078 | D41: CUST024 | E41: Western Retail Group | F41: SUB024 | G41: Marketing Pro | H41: Monthly | I41: 46078 | J41: 46081 | K41: 31 | L41: 85 | M41: 2635 | N41: 0 | O41: 0 | P41: 2635 | Q41: paid | R41: 46078
A42: in_20260200040 | B42: INV-2026-02-0040 | C42: 46079 | D42: CUST037 | E42: Maritime SaaS Ventures | F42: SUB037 | G42: Platform Suite | H42: Monthly | I42: 46079 | J42: 46081 | K42: 35 | L42: 150 | M42: 5250 | N42: 0 | O42: 0 | P42: 5250 | Q42: paid | R42: 46079
A43: in_20260200041 | B43: INV-2026-02-0041 | C43: 46079 | D43: CUST040 | E43: BC Education Innovations | F43: SUB040 | G43: Analytics Growth | H43: Monthly | I43: 46079 | J43: 46081 | K43: 18 | L43: 95 | M43: 1710 | N43: 0 | O43: 0 | P43: 1710 | Q43: paid | R43: 46079
A44: in_20260200042 | B44: INV-2026-02-0042 | C44: 46080 | D44: CUST011 | E44: Prairie Health Connect | F44: SUB011 | G44: Sales Hub | H44: Monthly | I44: 46080 | J44: 46081 | K44: 18 | L44: 110 | M44: 1980 | N44: 0 | O44: 0 | P44: 1980 | Q44: paid | R44: 46080
A45: in_20260200043 | B45: INV-2026-02-0043 | C45: 46081 | D45: CUST020 | E45: Atlantic SaaS Systems | F45: SUB020 | G45: Sales Hub | H45: Monthly | I45: 46081 | J45: 46081 | K45: 15 | L45: 110 | M45: 1650 | N45: 0 | O45: 0 | P45: 1650 | Q45: paid | R45: 46081
A46: in_20260200044 | B46: INV-2026-02-0044 | C46: 46081 | D46: CUST022 | E46: Toronto Tech Ventures | F46: SUB022 | G46: Platform Suite | H46: Monthly | I46: 46081 | J46: 46081 | K46: 33 | L46: 150 | M46: 4950 | N46: 0 | O46: 0 | P46: 4950 | Q46: paid | R46: 46081
A47: in_20260200045 | B47: INV-2026-02-0045 | C47: 46081 | D47: CUST033 | E47: Ottawa Retail Solutions | F47: SUB033 | G47: Marketing Pro | H47: Monthly | I47: 46081 | J47: 46081 | K47: 25 | L47: 85 | M47: 2125 | N47: 0 | O47: 0 | P47: 2125 | Q47: paid | R47: 46081
A48: in_20260200046 | B48: INV-2026-02-0046 | C48: 46081 | D48: CUST035 | E48: Vancouver Health Systems | F48: SUB035 | G48: Sales Hub | H48: Monthly | I48: 46081 | J48: 46081 | K48: 20 | L48: 110 | M48: 2200 | N48: 0 | O48: 0 | P48: 2200 | Q48: paid | R48: 46081
A49: in_20260200047 | B49: INV-2026-02-0047 | C49: 46081 | D49: CUST021 | E49: Calgary Commerce Solutions | F49: SUB057 | G49: Platform Suite | H49: Monthly | I49: 46081 | J49: 46081 | K49: 28 | L49: 150 | M49: 4200 | N49: 0 | O49: 0 | P49: 4200 | Q49: paid | R49: 46081

Sheet bank_statement_jan_2026
A1: Account: iDynamics SaaS Inc - Operating
A2: Period: January 2026
A3: Opening Balance: | B3: 1250000
A5: transaction_date | B5: post_date | C5: description | D5: type | E5: amount | F5: reference_number | G5: running_balance
A6: 46023 | B6: 46023 | C6: ACH CREDIT â€” ONTARIO MANUFACTURING TECH â€” REF:SUB007 | D6: Credit | E6: 1360 | F6: TXN-2026-02-0001 | G6: 1251360
A7: 46023 | B7: 46023 | C7: ACH CREDIT â€” ONTARIO MANUFACTURING TECH â€” REF:SUB050 | D7: Credit | E7: 594 | F7: TXN-2026-02-0002 | G7: 1251954
A8: 46024 | B8: 46024 | C8: ACH CREDIT â€” VANCOUVER FINTECH LABS â€” REF:SUB018 | D8: Credit | E8: 6300 | F8: TXN-2026-02-0003 | G8: 1258254
A9: 46025 | B9: 46025 | C9: ACH CREDIT â€” HALIFAX HEALTHCARE TECH â€” REF:SUB029 | D9: Credit | E9: 1870 | F9: TXN-2026-02-0004 | G9: 1260124
A10: 46027 | B10: 46027 | C10: ACH CREDIT â€” MAPLE HEALTHCARE SYSTEMS â€” REF:SUB003 | D10: Credit | E10: 1955 | F10: TXN-2026-02-0005 | G10: 1262079
A11: 46027 | B11: 46027 | C11: ACH CREDIT â€” NORTHERN RETAIL SOLUTIONS â€” REF:SUB043 | D11: Credit | E11: 2805 | F11: TXN-2026-02-0006 | G11: 1264884
A12: 46027 | B12: 46027 | C12: ACH CREDIT â€” PACIFIC FINANCE CORP â€” REF:SUB053 | D12: Credit | E12: 5580 | F12: TXN-2026-02-0007 | G12: 1270464
A13: 46027 | B13: 46027 | C13: ACH CREDIT â€” QUANTUM EDUCATION PLATFORM â€” REF:SUB059 | D13: Credit | E13: 1870 | F13: TXN-2026-02-0008 | G13: 1272334
A14: 46028 | B14: 46028 | C14: ACH CREDIT â€” PACIFIC FINANCE CORP â€” REF:SUB027 | D14: Credit | E14: 3080 | F14: TXN-2026-02-0009 | G14: 1275414
A15: 46030 | B15: 46030 | C15: ACH CREDIT â€” TORONTO MEDIA GROUP â€” REF:SUB014 | D15: Credit | E15: 2380 | F15: TXN-2026-02-0010 | G15: 1277794
A16: 46030 | B16: 46030 | C16: ACH CREDIT â€” MONTREAL FINANCE HUB â€” REF:SUB045 | D16: Credit | E16: 1105 | F16: TXN-2026-02-0011 | G16: 1278899
A17: 46030 | B17: 46030 | C17: ACH CREDIT â€” WESTERN RETAIL GROUP â€” REF:SUB058 | D17: Credit | E17: 2860 | F17: TXN-2026-02-0012 | G17: 1281759
... A51: 46053 | B51: 46053 | C51: ACH CREDIT â€” OTTAWA RETAIL SOLUTIONS â€” REF:SUB033 | D51: Credit | E51: 2125 | F51: TXN-2026-02-0046 | G51: 1427975

Sheet bank_statement_feb_2026
A1: Account: iDynamics SaaS Inc - Operating
A2: Period: February 2026
A3: Opening Balance: | B3: 1427945
A5: transaction_date | B5: post_date | C5: description | D5: type | E5: amount | F5: reference_number | G5: running_balance
A6: 46058 | B6: 46058 | C6: ACH CREDIT â€” PRAIRIE SAAS INNOVATIONS â€” RETRY REF:SUB028 INV:INV-2026-01-0030 | D6: Credit | E6: 675 | F6: TXN-2026-02-0001 | G6: 1428650
A7: 46054 | B7: 46054 | C7: ACH CREDIT â€” ONTARIO MANUFACTURING TECH â€” REF:SUB007 | D7: Credit | E7: 1360 | F7: TXN-2026-02-0002 | G7: 1430010
A8: 46054 | B8: 46054 | C8: ACH CREDIT â€” ONTARIO MANUFACTURING TECH â€” REF:SUB050 | D8: Credit | E8: 594 | F8: TXN-2026-02-0003 | G8: 1430604
A9: 46055 | B9: 46055 | C9: ACH CREDIT â€” VANCOUVER FINTECH LABS â€” REF:SUB018 | D9: Credit | E9: 6300 | F9: TXN-2026-02-0004 | G9: 1436904
A10: 46056 | B10: 46056 | C10: ACH CREDIT â€” HALIFAX HEALTHCARE TECH â€” REF:SUB029 | D10: Credit | E10: 1870 | F10: TXN-2026-02-0005 | G10: 1438774
A11: 46058 | B11: 46058 | C11: ACH CREDIT â€” MAPLE HEALTHCARE SYSTEMS â€” REF:SUB003 | D11: Credit | E11: 1955 | F11: TXN-2026-02-0006 | G11: 1440729
A12: 46058 | B12: 46058 | C12: ACH CREDIT â€” NORTHERN RETAIL SOLUTIONS â€” REF:SUB043 | D12: Credit | E12: 2805 | F12: TXN-2026-02-0007 | G12: 1443534
A13: 46058 | B13: 46058 | C13: ACH CREDIT â€” PACIFIC FINANCE CORP â€” REF:SUB053 | D13: Credit | E13: 5580 | F13: TXN-2026-02-0008 | G13: 1449114
A14: 46058 | B14: 46058 | C14: ACH CREDIT â€” QUANTUM EDUCATION PLATFORM â€” REF:SUB059 | D14: Credit | E14: 1870 | F14: TXN-2026-02-0009 | G14: 1450984
A15: 46059 | B15: 46059 | C15: ACH CREDIT â€” PACIFIC FINANCE CORP â€” REF:SUB027 | D15: Credit | E15: 3080 | F15: TXN-2026-02-0010 | G15: 1454064
A16: 46061 | B16: 46061 | C16: ACH CREDIT â€” TORONTO MEDIA GROUP â€” REF:SUB014 | D16: Credit | E16: 2380 | F16: TXN-2026-02-0011 | G16: 1456444
A17: 46061 | B17: 46061 | C17: ACH CREDIT â€” MONTREAL FINANCE HUB â€” REF:SUB045 | D17: Credit | E17: 1105 | F17: TXN-2026-02-0012 | G17: 1457549
... A54: 46081 | B54: 46081 | C54: ACH CREDIT â€” CALGARY COMMERCE SOLUTIONS â€” REF:SUB057 | D54: Credit | E54: 4200 | F54: TXN-2026-02-0049 | G54: 1542624.3

Sheet Actuals
A1: Metric | B1: 46023 | C1: 46054 | D1: 46082 | E1: 46113 | F1: 46143
A2: Opening MRR | B2: 143069.5 | C2: =B7 -> 144779.5 | D2: =C7 -> 150305.5 | E2: =D7 -> 153685.5 | F2: =E7 -> 156830.5
A3: New MRR | B3: 1710 | C3: 6120 | D3: 3000 | E3: 3810 | F3: 4780
A4: Expansion MRR | B4: 0 | C4: 0 | D4: 380 | E4: 440 | F4: 425
A5: Contraction MRR | F5: 440
A6: Churned MRR | B6: 0 | C6: 594 | D6: 0 | E6: 1105 | F6: 1520
A7: Closing MRR | B7: =B2+B3+B4-B6 -> 144779.5 | C7: =C2+C3+C4-C6 -> 150305.5 | D7: =D2+D3+D4-D6 -> 153685.5 | E7: =E2+E3+E4-E6 -> 156830.5 | F7: =F2+F3+F4-F5-F6 -> 160075.5
A8: S&M | B8: 30000 | C8: 31000 | D8: 29000 | E8: 32000 | F8: 29000
A9: R&D | B9: 25000 | C9: 25000 | D9: 22000 | E9: 23000 | F9: 24000
A10: G&A | B10: 19000 | C10: 19000 | D10: 22000 | E10: 20000 | F10: 21000
A11: Total OpEx | B11: =B8+B9+B10 -> 74000 | C11: =C8+C9+C10 -> 75000 | D11: =D8+D9+D10 -> 73000 | E11: =E8+E9+E10 -> 75000 | F11: =F8+F9+F10 -> 74000
A12: COGS | B12: =B7*0.3 -> 43433.85 | C12: =C7*0.3 -> 45091.65 | D12: =D7*0.3 -> 46105.65 | E12: =E7*0.3 -> 47049.15 | F12: =F7*0.3 -> 48022.65
A13: Gross Profit | B13: =B7-B12 -> 101345.65 | C13: =C7-C12 -> 105213.85 | D13: =D7-D12 -> 107579.85 | E13: =E7-E12 -> 109781.35 | F13: =F7-F12 -> 112052.85
A14: EBITDA | B14: =B13-B11 -> 27345.65 | C14: =C13-C11 -> 30213.85 | D14: =D13-D11 -> 34579.85 | E14: =E13-E11 -> 34781.35 | F14: =F13-F11 -> 38052.85
A15: New Customers | B15: 1 | C15: 2 | D15: 2 | E15: 2 | F15: 1
A16: Active Customers | B16: 39 | C16: 41 | D16: 42 | E16: 44 | F16: 45
A17: Active Subscriptions | B17: 52 | C17: 53 | D17: 54 | E17: 55 | F17: 56
A19: Legend: | B19: INPUT = type here | C19: FORMULA = never type here | D19: ANCHOR = one-time historical

Sheet Billing Reconciliation
A1: Metric | B1: Jan-26 | C1: Feb-26
A2: MRR | B2: ='Jan 2026 A vs F '!B9 -> 144779.5 | C2: ='Feb 2026 A vs F'!B9 -> 150305.5
A3: Total Invoiced | B3: =SUM(billing_jan_2026!P2:P48) -> 178650 | C3: =SUM(billing_feb_2026!P2:P49) -> 113974.29
A4: Adjustment: SUB028 | C4: 675
A5: Total Collected | B5: =SUM(bank_statement_jan_2026!E6:E51) -> 177975 | C5: =SUM(bank_statement_feb_2026!E6:E54) -> 114649.29
A6: MRR vs Invoiced | B6: =B3-B2 -> 33870.5 | C6: =C3-C2+C4 -> -35656.21
A7: Invoiced vs Collected | B7: =B3-B5 -> 675 | C7: =C3+C4-C5 -> 0
A9: Bridge 1: MRR to Invoiced
A10: Item | B10: Jan-26 | C10: Feb-26 | H10: Annual MRR book (7 annual subs, monthly) | I10: 36755.5
A11: MRR | B11: =B2 -> 144779.5 | C11: =C2 -> 150305.5
A12: _+ Annual billing excess | B12: =SUMIF(billing_jan_2026!H:H, "Annual", billing_jan_2026!P:P) * (11/12) -> 64740.5 | C12: =SUMIF(billing_feb_2026!H:H, "Annual", billing_feb_2026!P:P) * (11/12) -> 0
A13: _- Annual MRR with no billing this month | B13: =-(I10-SUMIF(billing_jan_2026!H:H,"Annual",billing_jan_2026!P:P)/12) -> -30870 | C13: =-(I10-SUMIF(billing_feb_2026!H:H,"Annual",billing_feb_2026!P:P)/12) -> -36755.5
A14: Adjustment: SUB050 | C14: =SUMIF(billing_feb_2026!F:F,"SUB050",billing_feb_2026!P:P) -> 424.29
A15: _= Total Invoiced | B15: =B3 -> 178650 | C15: =C3 -> 113974.29
A16: Total | B16: =SUM(B11:B13) -> 178650 | C16: =SUM(C11:C14) -> 113974.29
A17: Difference | B17: =B16-B15 -> 0 | C17: =C16-C15 -> 0
A19: Bridge 2: Invoiced to Collected
A20: Item | B20: Jan-26 | C20: Feb-26
A21: Total Invoiced | B21: =B3 -> 178650 | C21: =C3 -> 113974.29 | D21: =D3 -> 0
A22: Adjustment: SUB028 | B22: =billing_jan_2026!P31 -> 675 | C22: 675
A23: Total Collected | B23: =B5 -> 177975 | C23: =C5 -> 114649.29
A24: Difference | B24: =B23+B22-B21 -> 0 | C24: =C23-SUM(C21:C22) -> 0
A26: Part 5:
A27: The database for January shows $2185 for SUB012.
A28: The billing file represents a point in time record while the database represents a historical period.
A29: They share the same number therefore $2185 is the correct number.
A31: Part 6:
A32: The negative row is row number 36.
A33: This row relates to Ontario Manufacturing Tech and their monthly Analytics Starter subscription.
A34: A refund was issued because OMT cancelled their subscription on 2026-02-20.
A35: Since a refund was issued, total collected will be lowered. They were billed at the beginning of the month and because of the cancellation occurring near the end, they received a prorated refund.
A36: Total billed will also be reduced since the billing system recorded that the invoice was partially reversed.
A38: Commentary:
A39: The difference between MRR and cash collected is driven by payment timing. Specifically, the prepayments from Pacific Analytics for SUB002 ($46,800) and SUB054 ($23,826) inflated the total invoiced amount above MRR.
... A43: Along with this, the negative entry from Ontario Manufacturing Tech (SUB050) comes from a prorated refund on February 20th following a cancellation in the middle of the month. This confirms that when the billing system properly records partial reversals, downstream reporting should be audited to make sure these changes are reflected.

Sheet Historical Baseline
A1: HISTORICAL BASELINE — 2024 & 2025 ACTUALS
A2: Fill this table from your MRR workbook and database. Show your source for every number.
A3: This is the foundation for the 2026 forecast. If these numbers are wrong, everything downstream is wrong.
A5: MRR WATERFALL (QUARTERLY)
A6: Metric | B6: Q1 2024 | C6: Q2 2024 | D6: Q3 2024 | E6: Q4 2024 | F6: Q1 2025 | G6: Q2 2025 | H6: Q3 2025 | I6: Q4 2025 | K6: Source
A7: Opening MRR | B7: =Waterfall!B4 -> 0 | C7: =B13 -> 20490 | D7: =C13 -> 35989 | E7: =D13 -> 63708.5 | F7: =E13 -> 91123.5 | G7: =F13 -> 126539.5 | H7: =G13 -> 152114.5 | I7: =H13 -> 150359.5 | K7: e.g. Waterfall tab, prior Q closing
A8: + New MRR | B8: =SUM(Waterfall!C4:C6) -> 20490 | C8: =SUM(Waterfall!C7:C9) -> 15499 | D8: =SUM(Waterfall!C10:C12) -> 29619.5 | E8: =SUM(Waterfall!C13:C15) -> 30000 | F8: =SUM(Waterfall!C16:C18) -> 36735.5 | G8: =SUM(Waterfall!C19:C21) -> 26470 | H8: =SUM(Waterfall!C22:C24) -> 0 | I8: =SUM(Waterfall!C25:C27) -> 935 | K8: Waterfall tab, sum of New column
A9: + Expansion MRR | B9: =SUM(Waterfall!D4:D6) -> 0 | C9: =SUM(Waterfall!D7:D9) -> 0 | D9: =SUM(Waterfall!D10:D12) -> 0 | E9: =SUM(Waterfall!D13:D15) -> 0 | F9: =SUM(Waterfall!D16:D18) -> 140 | G9: =SUM(Waterfall!D19:D21) -> 2785 | H9: =SUM(Waterfall!D22:D24) -> 5520 | I9: =SUM(Waterfall!D25:D27) -> 1765 | K9: Waterfall tab, sum of Expansion column
A10: − Contraction MRR | B10: =SUM(Waterfall!E4:E6) -> 0 | C10: =SUM(Waterfall!E7:E9) -> 0 | D10: =SUM(Waterfall!E10:E12) -> 0 | E10: =SUM(Waterfall!E13:E15) -> 0 | F10: =SUM(Waterfall!E16:E18) -> -1009.5 | G10: =SUM(Waterfall!E19:E21) -> 0 | H10: =SUM(Waterfall!E22:E24) -> -835 | I10: =SUM(Waterfall!E25:E27) -> -516.5 | K10: Waterfall tab, sum of Contraction column
A11: − Churned MRR | B11: =SUM(Waterfall!F4:F6) -> 0 | C11: =SUM(Waterfall!F7:F9) -> 0 | D11: =SUM(Waterfall!F10:F12) -> -1900 | E11: =SUM(Waterfall!F13:F15) -> -2585 | F11: =SUM(Waterfall!F16:F18) -> -450 | G11: =SUM(Waterfall!F19:F21) -> -3680 | H11: =SUM(Waterfall!F22:F24) -> -6440 | I11: =SUM(Waterfall!F25:F27) -> -1624.5 | K11: Waterfall tab, sum of Churned column
A12: Net New MRR | B12: =B13-B7 -> 20490 | C12: =C13-C7 -> 15499 | D12: =D13-D7 -> 27719.5 | E12: =E13-E7 -> 27415 | F12: =F13-F7 -> 35416 | G12: =G13-G7 -> 25575 | H12: =H13-H7 -> -1755 | I12: =I13-I7 -> -7290 | K12: Should equal Closing − Opening
A13: Closing MRR | B13: =Waterfall!H6 -> 20490 | C13: =Waterfall!H9 -> 35989 | D13: =Waterfall!H12 -> 63708.5 | E13: =Waterfall!H15 -> 91123.5 | F13: =Waterfall!H18 -> 126539.5 | G13: =Waterfall!H21 -> 152114.5 | H13: =Waterfall!H24 -> 150359.5 | I13: 143069.5 | K13: Waterfall tab, last month of quarter
A15: CUSTOMERS & SUBSCRIPTIONS
A16: Metric | B16: Q1 2024 | C16: Q2 2024 | D16: Q3 2024 | E16: Q4 2024 | F16: Q1 2025 | G16: Q2 2025 | H16: Q3 2025 | I16: Q4 2025 | K16: Source
A17: New customers | B17: =Retention!D19-0 -> 4 | C17: =Retention!G19-Retention!D19 -> 7 | D17: =Retention!J19-Retention!G19 -> 6 | E17: =Retention!M19-Retention!J19 -> 6 | F17: =Retention!Q19-Retention!N19 -> 6 | G17: =Retention!T19-Retention!Q19 -> 6 | H17: =Retention!V19-Retention!S19 -> 1 | I17: =SUM('Unit Economics'!J76:J78) -> 0 | K17: S&M data on Unit Economics tab
A18: Churned subscriptions | B18: =SUM(Retention!B17:D17) -> 0 | C18: =SUM(Retention!E17:G17) -> 0 | D18: =SUM(Retention!H17:J17) -> 1 | E18: =SUM(Retention!K17:M17) -> 2 | F18: =SUM(Retention!N17:P17) -> 1 | G18: =SUM(Retention!Q17:S17) -> 3 | H18: =SUM(Retention!T17:V17) -> 2 | I18: =SUM(Retention!W17:Y17) -> 1 | K18: Retention tab
A19: Active subscriptions (end of Q) | B19: =Retention!D16 -> 5 | C19: =Retention!G16 -> 13 | D19: =Retention!J16 -> 21 | E19: =Retention!M16 -> 31 | F19: =Retention!Q16 -> 46 | G19: =Retention!T16 -> 53 | H19: =Retention!W16 -> 51 | I19: =Retention!Z16 -> 51 | K19: Retention tab running count
A20: Active customers (end of Q) | B20: =Retention!D19 -> 4 | C20: =Retention!G19 -> 11 | D20: =Retention!J19 -> 17 | E20: =Retention!M19 -> 23 | F20: =Retention!Q19 -> 31 | G20: =Retention!T19 -> 37 | H20: =Retention!W19 -> 37 | I20: =Retention!Z19 -> 38 | K20: Unique cust IDs with ≥1 active sub
A22: P&L SUMMARY
A23: Metric | B23: Q1 2024 | C23: Q2 2024 | D23: Q3 2024 | E23: Q4 2024 | F23: Q1 2025 | G23: Q2 2025 | H23: Q3 2025 | I23: Q4 2025 | K23: Source
A24: Revenue | B24: =B13*3 -> 61470 | C24: =C13*3 -> 107967 | D24: =D13*3 -> 191125.5 | E24: =E13*3 -> 273370.5 | F24: =F13*3 -> 379618.5 | G24: =G13*3 -> 456343.5 | H24: =H13*3 -> 451078.5 | I24: =I13*3 -> 429208.5 | K24: Sum of monthly MRR from workbook
A25: COGS (30%) | B25: =B24*0.3 -> 18441 | C25: =C24*0.3 -> 32390.1 | D25: =D24*0.3 -> 57337.65 | E25: =E24*0.3 -> 82011.15 | F25: =F24*0.3 -> 113885.55 | G25: =G24*0.3 -> 136903.05 | H25: =H24*0.3 -> 135323.55 | I25: =I24*0.3 -> 128762.55 | K25: Revenue × 30%
A26: Gross Profit | B26: =B24-B25 -> 43029 | C26: =C24-C25 -> 75576.9 | D26: =D24-D25 -> 133787.85 | E26: =E24-E25 -> 191359.35 | F26: =F24-F25 -> 265732.95 | G26: =G24-G25 -> 319440.45 | H26: =H24-H25 -> 315754.95 | I26: =I24-I25 -> 300445.95 | K26: Revenue − COGS
A27: Gross Margin % | B27: =B26/B24 -> 0.7 | C27: =C26/C24 -> 0.7 | D27: =D26/D24 -> 0.7 | E27: =E26/E24 -> 0.7 | F27: =F26/F24 -> 0.7 | G27: =G26/G24 -> 0.7 | H27: =H26/H24 -> 0.7 | I27: =I26/I24 -> 0.7 | K27: GP / Revenue
A28: S&M | B28: 18500 | C28: 29000 | D28: 47000 | E28: 63000 | F28: ='Unit Economics'!I67+'Unit Economics'!I68+'Unit Economics'!I69 -> 88250 | G28: ='Unit Economics'!I70+'Unit Economics'!I71+'Unit Economics'!I72 -> 87550 | H28: ='Unit Economics'!I73+'Unit Economics'!I74+'Unit Economics'!I75 -> 91450 | I28: ='Unit Economics'!I76+'Unit Economics'!I77+'Unit Economics'!I78 -> 74150 | K28: Accounting data, Unit Economics tab
A29: R&D | B29: 15000 | C29: 25000 | D29: 42000 | E29: 57000 | F29: 62000 | G29: 68000 | H29: 72000 | I29: 65000 | K29: Company cost structure
A30: G&A | B30: 8000 | C30: 13000 | D30: 21000 | E30: 28000 | F30: 32000 | G30: 34000 | H30: 36000 | I30: 33000 | K30: Company cost structure
A31: Total OpEx | B31: =B28+B29+B30 -> 41500 | C31: =C28+C29+C30 -> 67000 | D31: =D28+D29+D30 -> 110000 | E31: =E28+E29+E30 -> 148000 | F31: =F28+F29+F30 -> 182250 | G31: =G28+G29+G30 -> 189550 | H31: =H28+H29+H30 -> 199450 | I31: =I28+I29+I30 -> 172150 | K31: S&M + R&D + G&A
A32: EBITDA | B32: =B26-B31 -> 1529 | C32: =C26-C31 -> 8576.9 | D32: =D26-D31 -> 23787.85 | E32: =E26-E31 -> 43359.35 | F32: =F26-F31 -> 83482.95 | G32: =G26-G31 -> 129890.45 | H32: =H26-H31 -> 116304.95 | I32: =I26-I31 -> 128295.95 | K32: Gross Profit − Total OpEx
A33: EBITDA Margin % | B33: =B32/B24 -> 0.024873922 | C33: =C32/C24 -> 0.079440014 | D33: =D32/D24 -> 0.12446194 | E33: =E32/E24 -> 0.1586102 | F33: =IF(F24=0,"",F32/F24) -> 0.21991275 | G33: =IF(G24=0,"",G32/G24) -> 0.28463307 | H33: =IF(H24=0,"",H32/H24) -> 0.25783749 | I33: =IF(I24=0,"",I32/I24) -> 0.29891288 | K33: EBITDA / Revenue
A35: KEY RATES (CALCULATED)
A36: Metric | B36: Q1 2024 | C36: Q2 2024 | D36: Q3 2024 | E36: Q4 2024 | F36: Q1 2025 | G36: Q2 2025 | H36: Q3 2025 | I36: Q4 2025 | K36: Source
A37: MRR churn rate (quarterly) | B37: =IF(B7=0,"",ABS(B11)/B7) | C37: =IF(C7=0,"",ABS(C11)/C7) -> 0 | D37: =IF(D7=0,"",ABS(D11)/D7) -> 0.052793909 | E37: =IF(E7=0,"",ABS(E11)/E7) -> 0.040575433 | F37: =IF(F7=0,"",ABS(F11)/F7) -> 0.0049383529 | G37: =IF(G7=0,"",ABS(G11)/G7) -> 0.029081828 | H37: =IF(H7=0,"",ABS(H11)/H7) -> 0.042336529 | I37: =IF(I7=0,"",ABS(I11)/I7) -> 0.010804106 | K37: Churned MRR / Opening MRR
A38: MRR expansion rate (quarterly) | B38: =IF(B7=0,"",B9/B7) | C38: =IF(C7=0,"",C9/C7) -> 0 | D38: =IF(D7=0,"",D9/D7) -> 0 | E38: =IF(E7=0,"",E9/E7) -> 0 | F38: =IF(F7=0,"",F9/F7) -> 0.0015363765 | G38: =IF(G7=0,"",G9/G7) -> 0.022008938 | H38: =IF(H7=0,"",H9/H7) -> 0.036288454 | I38: =IF(I7=0,"",I9/I7) -> 0.011738533 | K38: Expansion MRR / Opening MRR
A39: Avg MRR per new customer | B39: =IF(B17=0,"",B8/B17) -> 5122.5 | C39: =IF(C17=0,"",C8/C17) -> 2214.1429 | D39: =IF(D17=0,"",D8/D17) -> 4936.5833 | E39: =IF(E17=0,"",E8/E17) -> 5000 | F39: =IF(F17=0,"",F8/F17) -> 6122.5833 | G39: =IF(G17=0,"",G8/G17) -> 4411.6667 | H39: =IF(H17=0,"",H8/H17) -> 0 | I39: N/A | K39: New MRR / New customers
A40: CAC (quarterly S&M / new custs) | B40: =IF(B17=0,"N/A",B28/B17) -> 4625 | C40: =IF(C17=0,"N/A",C28/C17) -> 4142.8571 | D40: =IF(D17=0,"N/A",D28/D17) -> 7833.3333 | E40: =IF(E17=0,"N/A",E28/E17) -> 10500 | F40: =IF(F17=0,"N/A",F28/F17) -> 14708.333 | G40: =IF(G17=0,"N/A",G28/G17) -> 14591.667 | H40: =IF(H17=0,"N/A",H28/H17) -> 91450 | I40: =IF(I17=0,"N/A",I28/I17) -> N/A | K40: Only meaningful if new custs > 0
A43: RECONCILIATION NOTES
A44: Dec 2025 closing MRR (this table): | B44: =I13 -> 143069.5
A45: Feb 2026 snapshot MRR: | B45: ='Unit Economics'!B6 -> 144185.5
A46: Difference: | B46: =B44-B45 -> -1116
A47: Explanation: | B47: Waterfall closing ($150,918.50) exceeds Snapshot ($144,185.50) by $6,733. This gap exists because Snapshot only reflects currently active subscriptions while Waterfall has all movements including churned subs after Dec 2025.
A49: Which number are you using as the 2026 opening MRR, and why? | B49: Using $150,918.50 (Waterfall tab, Dec 2025 closing MRR, cell H26). This is the complete figure tied to month-by-month movement data.

Sheet Forecast Assumptions
A1: 2026 FORECAST ASSUMPTIONS
A2: From: David Chen, VP Finance — Leadership planning meeting, December 2025
A3: All values are hardcoded inputs. Every formula on the Forecast tab must reference these cells.
A5: STARTING POSITION
A6: Opening MRR (Jan 2026) | B6: ='Historical Baseline'!B44 -> 143069.5 | D6: ← Pull from your Historical Baseline tab
A7: Active subscriptions (Dec 2025) | B7: ='Historical Baseline'!I19 -> 51 | D7: ← Pull from your Historical Baseline tab
A8: Active customers (Dec 2025) | B8: ='Historical Baseline'!I20 -> 38 | D8: ← Pull from your Historical Baseline tab
A10: GROWTH ASSUMPTIONS
A11: Metric | B11: Q1 2026 | C11: Q2 2026 | D11: Q3 2026 | E11: Q4 2026
A12: New customers | B12: 4 | C12: 6 | D12: 9 | E12: 9
A13: Avg MRR per new customer | B13: 3000 | C13: 3200 | D13: 3200 | E13: 3400
A14: Quarterly expansion rate | B14: 0.015 | C14: 0.015 | D14: 0.015 | E14: 0.015
A15: Quarterly churn rate | B15: 0.02 | C15: 0.02 | D15: 0.02 | E15: 0.02
A17: Expansion rate: 0.50%/month compounded to quarterly. Seat adds + upsells from existing base.
A18: Churn rate: 0.67%/month compounded to quarterly. Target ~8% annual (down from 2025 actual).
A19: Both rates apply to BEGINNING-of-quarter MRR, not ending.
A21: MARGIN
A22: Gross margin | B22: 0.7 | C22: Same across all quarters — no cost structure changes planned.
A24: OPERATING EXPENSES
A25: Metric | B25: Q1 2026 | C25: Q2 2026 | D25: Q3 2026 | E25: Q4 2026
A26: Sales & Marketing | B26: 90000 | C26: 90000 | D26: 108000 | E26: 108000
A27: Research & Development | B27: 75000 | C27: 75000 | D27: 75000 | E27: 75000
A28: General & Administrative | B28: 57000 | C28: 57000 | D28: 57000 | E28: 57000
A29: Total OpEx | B29: 222000 | C29: 222000 | D29: 240000 | E29: 240000
A31: S&M increases H2 to fund acquisition push. Not repeating H2 2025 drought.
A33: REVENUE CONVENTION
A34: Quarterly Revenue = Closing MRR × 3
A35: This is the standard convention for forward-looking models: the ending run-rate × months in the period.

Sheet Jan 2026 A vs F 
A1: MRR Waterfall
A2: Metric | B2: Actual - Jan 26 | C2: Forecast - Jan 26 | D2: $ Variance | E2: % Variance | F2: F/U
A3: Opening MRR | B3: 143069.5 | C3: ='2026 Forecast'!B7 -> 143069.5 | D3: =B3-C3 -> 0 | E3: =IFERROR(B3/C3-1, 0) -> 0 | F3: {=_xlfn.IFS(D3<0, "U", D3>0, "F", D3=0, "-")} -> -
A4: + New MRR | B4: 1710 | C4: 4000 | D4: =B4-C4 -> -2290 | E4: =IFERROR(B4/C4-1, 0) -> -0.5725 | F4: {=_xlfn.IFS(D4<0, "U", D4>0, "F", D4=0, "-")} -> U
A5: + Expansion MRR | B5: 0 | C5: ='2026 Forecast'!B9/3 -> 715.3475 | D5: =B5-C5 -> -715.3475 | E5: =IFERROR(B5/C5-1, 0) -> -1 | F5: {=_xlfn.IFS(D5<0, "U", D5>0, "F", D5=0, "-")} -> U
A6: - Contraction MRR | B6: 0 | C6: 0 | D6: =B6-C6 -> 0 | E6: =IFERROR(B6/C6-1, 0) -> 0 | F6: {=_xlfn.IFS(D6<0, "U", D6>0, "F", D6=0, "-")} -> -
A7: − Churned MRR | B7: 0 | C7: ='2026 Forecast'!B10/3 -> 953.79667 | D7: =C7-B7 -> 953.79667 | E7: =IFERROR(B7/C7-1, 0) -> -1 | F7: {=_xlfn.IFS(D7>0, "U", D7<0, "F", D7=0, "-")} -> U
A8: Net New MRR | B8: =B4+B5-B7 -> 1710 | C8: =C4+C5-C7 -> 3761.5508 | D8: =B8-C8 -> -2051.5508 | E8: =B8/C8-1 -> -0.54540027 | F8: {=_xlfn.IFS(D8<0, "U", D8>0, "F", D8=0, "-")} -> U
A9: Closing MRR | B9: =B3+B4+B5-B7 -> 144779.5 | C9: =C3+C8 -> 146831.05 | D9: =B9-C9 -> -2051.5508 | E9: =B9/C9-1 -> -0.013972187 | F9: {=_xlfn.IFS(D9<0, "U", D9>0, "F", D9=0, "-")} -> U
A10: Closing ARR | B10: =B9*12 -> 1737354 | C10: =C9*12 -> 1761972.6 | D10: =B10-C10 -> -24618.61 | E10: =B10/C10-1 -> -0.013972187 | F10: {=_xlfn.IFS(D10<0, "U", D10>0, "F", D10=0, "-")} -> U
A12: P&L
A13: Metric | B13: Actual - Jan 26 | C13: Forecast - Jan 26 | D13: $ Variance | E13: % Variance | F13: F/U
A14: Revenue | B14: =B9 -> 144779.5 | C14: =C9 -> 146831.05 | D14: =B14-C14 -> -2051.5508 | E14: =B14/C14-1 -> -0.013972187 | F14: {=_xlfn.IFS(D14<0, "U", D14>0, "F", D14=0, "-")} -> U
A15: COGS | B15: =B14*(1-B17) -> 43433.85 | C15: =C14*0.3 -> 44049.315 | D15: =B15-C15 -> -615.46525 | E15: =B15/C15-1 -> -0.013972187 | F15: {=_xlfn.IFS(D15>0, "U", D15<0, "F", D15=0, "-")} -> F | H15: → Revenue × (1 − gross margin)
A16: Gross Profit | B16: =B14-B15 -> 101345.65 | C16: =C14-C15 -> 102781.74 | D16: =B16-C16 -> -1436.0856 | E16: =B16/C16-1 -> -0.013972187 | F16: {=_xlfn.IFS(D16<0, "U", D16>0, "F", D16=0, "-")} -> U | H16: → Revenue − COGS
A17: Gross Margin % | B17: 0.7 | C17: =C16/C14 -> 0.7 | E17: =B17/C17-1 -> 0 | F17: {=_xlfn.IFS(D17<0, "U", D17>0, "F", D17=0, "-")} -> - | H17: → GP / Revenue
A18: Sales & Marketing | B18: ='Forecast Assumptions'!B26/3 -> 30000 | C18: ='2026 Forecast'!B25/3 -> 30000 | D18: =B18-C18 -> 0 | E18: =B18/C18-1 -> 0 | F18: {=_xlfn.IFS(D18<0, "U", D18>0, "F", D18=0, "-")} -> - | H18: ← From Assumptions tab
A19: Research & Development | B19: ='Forecast Assumptions'!B27/3 -> 25000 | C19: ='2026 Forecast'!B26/3 -> 25000 | D19: =B19-C19 -> 0 | E19: =B19/C19-1 -> 0 | F19: {=_xlfn.IFS(D19<0, "U", D19>0, "F", D19=0, "-")} -> - | H19: ← From Assumptions tab
A20: General & Administrative | B20: ='Forecast Assumptions'!B28/3 -> 19000 | C20: ='2026 Forecast'!B27/3 -> 19000 | D20: =B20-C20 -> 0 | E20: =B20/C20-1 -> 0 | F20: {=_xlfn.IFS(D20<0, "U", D20>0, "F", D20=0, "-")} -> - | H20: ← From Assumptions tab
A21: Total OpEx | B21: =SUM(B18:B20) -> 74000 | C21: ='2026 Forecast'!B28/3 -> 74000 | D21: =B21-C21 -> 0 | E21: =B21/C21-1 -> 0 | F21: {=_xlfn.IFS(D21<0, "U", D21>0, "F", D21=0, "-")} -> - | H21: S&M + R&D + G&A
A22: EBITDA | B22: =B16-B21 -> 27345.65 | C22: =C16-C21 -> 28781.736 | D22: =B22-C22 -> -1436.0856 | E22: =B22/C22-1 -> -0.049895726 | F22: {=_xlfn.IFS(D22<0, "U", D22>0, "F", D22=0, "-")} -> U | H22: → Gross Profit − Total OpEx
A23: EBITDA Margin % | B23: =B22/B14 -> 0.18887791 | C23: =C22/C14 -> 0.19601941 | D23: =B23-C23 -> -0.0071414931 | E23: =B23/C23-1 -> -0.036432582 | F23: {=_xlfn.IFS(D23<0, "U", D23>0, "F", D23=0, "-")} -> U | H23: → EBITDA / Revenue
A25: Summary:
A26: January closed with an MRR of $144,780, -$2,051.55 (-1.4%) below expectation.
A27: This is due to the lack of new customers acquired this month.
A28: There was only 1 new customer signing this month which is less than the expected 1.3 new customers
A29: The customers revenue was $1,710 which is 43% less than the planned rate of $3000 per customer.
A30: There was no expansion recorded this month versus the expected $715.35.
A31: Offsetting this was the lack of churned MRR this month which resulted in a favorable variance of $954.
A32: EBITDA of $27,345.65 was 5% lower than the expected $28,781.74. This was driven by the shortfall in Gross Profit due to the Closing MRR being less than anticipated.
A33: Operating Expenses were in line with expectation.
A34: Currently, Q1 is approximately $6000 less than planned, which could be fixed with a strong performance in February.
A36: January 2026 — SaaS KPIs
A38: Metric | B38: Value | C38: Notes
A39: Active Customers | B39: 39 | C39: From your Jan 31 SQL snapshot
A40: Active Subscriptions | B40: 52 | C40: From your Jan 31 SQL snapshot
A41: ARPA | B41: ='Jan 2026 A vs F '!B9/'Jan 2026 A vs F '!B39 -> 3712.2949 | C41: Excel 04
A42: Gross Margin | B42: =B17 -> 0.7 | C42: Already in your P&L
A43: GRR | B43: =Retention!Z6 -> 1 | C43: Excel 03
A44: NRR | B44: =Retention!Z7 -> 1 | C44: Excel 03
A45: Quick Ratio | B45: N/A — no losses | C45: Excel 02
A46: S&M (actual) | B46: =B18 -> 30000 | C46: From Lisa's monthly close message
A47: CAC — this month | B47: =B46/1 -> 30000 | C47: Excel 04 — S&M ÷ new customers acquired this month (= 1 new logo Jan)
A48: LTV | B48: — | C48: Quarterly metric — calculated at Q1 close
A49: LTV:CAC | B49: — | C49: Quarterly metric — calculated at Q1 close
A50: CAC Payback | B50: — | C50: Quarterly metric — calculated at Q1 close
A52: * Monthly CAC note:
A53: Monthly CAC is noisy with one customer. Q1 CAC will be calculated after March closes using total Q1 S&M spend ÷ total new customers acquired.
A55: † Quarterly metrics note:
A56: LTV, LTV:CAC, and CAC Payback are calculated quarterly using the trailing 12-month gross churn rate. See Q1 Roll-Up (coming in 06d).
A59: Self-Check — KPIs
A61: Metric | B61: Your value
A62: ARPA | B62: =B41 -> 3712.2949
A63: GRR | B63: =B43 -> 1
A64: NRR | B64: =B44 -> 1
A65: Quick Ratio | B65: =B45 -> N/A — no losses
A66: CAC (monthly) | B66: =B47 -> 30000

Sheet Feb 2026 A vs F
A1: MRR Waterfall
A2: Metric | B2: Actual - Feb 26 | C2: Forecast - Feb 26 | D2: $ Variance | E2: % Variance | F2: F/U
A3: Opening MRR | B3: ='Jan 2026 A vs F '!B9 -> 144779.5 | C3: 146831.05 | D3: =B3-C3 -> -2051.55 | E3: =IFERROR(B3/C3-1, 0) -> -0.013972181 | F3: {=_xlfn.IFS(D3<0, "U", D3>0, "F", D3=0, "-")} -> U
A4: + New MRR | B4: 6120 | C4: 4000 | D4: =B4-C4 -> 2120 | E4: =IFERROR(B4/C4-1, 0) -> 0.53 | F4: {=_xlfn.IFS(D4<0, "U", D4>0, "F", D4=0, "-")} -> F
A5: + Expansion MRR | B5: 0 | C5: ='2026 Forecast'!B9/3 -> 715.3475 | D5: =B5-C5 -> -715.3475 | E5: =IFERROR(B5/C5-1, 0) -> -1 | F5: {=_xlfn.IFS(D5<0, "U", D5>0, "F", D5=0, "-")} -> U
A6: - Contraction MRR | B6: 0 | C6: 0 | D6: =B6-C6 -> 0 | E6: =IFERROR(B6/C6-1, 0) -> 0 | F6: {=_xlfn.IFS(D6<0, "U", D6>0, "F", D6=0, "-")} -> -
A7: − Churned MRR | B7: 594 | C7: ='2026 Forecast'!B10/3 -> 953.79667 | D7: =C7-B7 -> 359.79667 | E7: =IFERROR(B7/C7-1, 0) -> -0.37722575 | F7: {=_xlfn.IFS(D7>0, "F", D7<0, "U", D7=0, "-")} -> F
A8: Net New MRR | B8: =B4+B5-B7 -> 5526 | C8: =C4+C5-C7 -> 3761.5508 | D8: =B8-C8 -> 1764.4492 | E8: =B8/C8-1 -> 0.46907492 | F8: {=_xlfn.IFS(D8<0, "U", D8>0, "F", D8=0, "-")} -> F
A9: Closing MRR | B9: =B3+B4+B5-B7 -> 150305.5 | C9: =C3+C8 -> 150592.6 | D9: =B9-C9 -> -287.10083 | E9: =B9/C9-1 -> -0.0019064737 | F9: {=_xlfn.IFS(D9<0, "U", D9>0, "F", D9=0, "-")} -> U
A10: Closing ARR | B10: =B9*12 -> 1803666 | C10: =C9*12 -> 1807111.2 | D10: =B10-C10 -> -3445.21 | E10: =B10/C10-1 -> -0.0019064737 | F10: {=_xlfn.IFS(D10<0, "U", D10>0, "F", D10=0, "-")} -> U
A12: P&L
A13: Metric | B13: Actual - Feb 26 | C13: Forecast - Feb 26 | D13: $ Variance | E13: % Variance | F13: F/U
A14: Revenue | B14: =B9 -> 150305.5 | C14: =C9 -> 150592.6 | D14: =B14-C14 -> -287.10083 | E14: =B14/C14-1 -> -0.0019064737 | F14: {=_xlfn.IFS(D14<0, "U", D14>0, "F", D14=0, "-")} -> U | H14: → Revenue × (1 − gross margin)
A15: COGS | B15: =B14*(1-B17) -> 45091.65 | C15: =C14*0.3 -> 45177.78 | D15: =B15-C15 -> -86.13025 | E15: =B15/C15-1 -> -0.0019064737 | F15: {=_xlfn.IFS(D15>0, "U", D15<0, "F", D15=0, "-")} -> F | H15: → Revenue − COGS
A16: Gross Profit | B16: =B14-B15 -> 105213.85 | C16: =C14-C15 -> 105414.82 | D16: =B16-C16 -> -200.97058 | E16: =B16/C16-1 -> -0.0019064737 | F16: {=_xlfn.IFS(D16<0, "U", D16>0, "F", D16=0, "-")} -> U | H16: → GP / Revenue
A17: Gross Margin % | B17: 0.7 | C17: =C16/C14 -> 0.7 | D17: =B17-C17 -> 0 | E17: =B17/C17-1 -> 0 | F17: {=_xlfn.IFS(D17<0, "U", D17>0, "F", D17=0, "-")} -> - | H17: ← From Assumptions tab
A18: Sales & Marketing | B18: 31000 | C18: ='2026 Forecast'!B25/3 -> 30000 | D18: =B18-C18 -> 1000 | E18: =B18/C18-1 -> 0.033333333 | F18: {=_xlfn.IFS(D18<0, "U", D18>0, "F", D18=0, "-")} -> F | H18: ← From Assumptions tab
A19: Research & Development | B19: ='Forecast Assumptions'!B27/3 -> 25000 | C19: ='2026 Forecast'!B26/3 -> 25000 | D19: =B19-C19 -> 0 | E19: =B19/C19-1 -> 0 | F19: {=_xlfn.IFS(D19<0, "U", D19>0, "F", D19=0, "-")} -> - | H19: ← From Assumptions tab
A20: General & Administrative | B20: ='Forecast Assumptions'!B28/3 -> 19000 | C20: ='2026 Forecast'!B27/3 -> 19000 | D20: =B20-C20 -> 0 | E20: =B20/C20-1 -> 0 | F20: {=_xlfn.IFS(D20<0, "U", D20>0, "F", D20=0, "-")} -> - | H20: S&M + R&D + G&A
A21: Total OpEx | B21: =SUM(B18:B20) -> 75000 | C21: ='2026 Forecast'!B28/3 -> 74000 | D21: =B21-C21 -> 1000 | E21: =B21/C21-1 -> 0.013513514 | F21: {=_xlfn.IFS(D21<0, "U", D21>0, "F", D21=0, "-")} -> F | H21: → Gross Profit − Total OpEx
A22: EBITDA | B22: =B16-B21 -> 30213.85 | C22: =C16-C21 -> 31414.821 | D22: =B22-C22 -> -1200.9706 | E22: =B22/C22-1 -> -0.038229427 | F22: {=_xlfn.IFS(D22<0, "U", D22>0, "F", D22=0, "-")} -> U | H22: → EBITDA / Revenue
A23: EBITDA Margin % | B23: =B22/B14 -> 0.20101626 | C23: =C22/C14 -> 0.208608 | D23: =B23-C23 -> -0.0075917319 | E23: =B23/C23-1 -> -0.036392334 | F23: {=IFERROR(_xludf.IFS(D23<0, "U", D23>0, "F", D23=0, "-"), "-")} -> -
A27: February 2026 — SaaS KPIs
A29: Metric | B29: Value | C29: vs Jan 2026 | D29: Notes
A30: Active Customers | B30: 41 | C30: {=IFERROR(B30-_xludf.XLOOKUP("Active Customers",'KPI Tracker'!$A$4:$A$16,'KPI Tracker'!$B$4:$B$16),"—")} -> — | D30: From your Feb 28 SQL snapshot
A31: Active Subscriptions | B31: 53 | C31: {=IFERROR(B31-_xludf.XLOOKUP("Active Subscriptions",'KPI Tracker'!$A$4:$A$16,'KPI Tracker'!$B$4:$B$16),"—")} -> — | D31: From your Feb 28 SQL snapshot
A32: ARPA | B32: =B9/B30 -> 3665.9878 | C32: {=IFERROR(B32-_xludf.XLOOKUP("ARPA",'KPI Tracker'!$A$4:$A$16,'KPI Tracker'!$B$4:$B$16),"—")} -> — | D32: Excel 04
A33: Gross Margin | B33: =B17 -> 0.7 | C33: {=IFERROR(B33-_xludf.XLOOKUP("Gross Margin",'KPI Tracker'!$A$4:$A$16,'KPI Tracker'!$B$4:$B$16),"—")} -> — | D33: Already in your P&L
A34: GRR | B34: =Retention!AA6 -> 0.99589721 | C34: {=IFERROR(B34-_xludf.XLOOKUP("GRR",'KPI Tracker'!$A$4:$A$16,'KPI Tracker'!$B$4:$B$16),"—")} -> — | D34: Excel 03
A35: NRR | B35: =Retention!AA7 -> 0.98950128 | C35: {=IFERROR(B35-_xludf.XLOOKUP("NRR",'KPI Tracker'!$A$4:$A$16,'KPI Tracker'!$B$4:$B$16),"—")} -> — | D35: Excel 03
A36: Quick Ratio | B36: =IFERROR(IF((B6+B7)=0,"N/A — no losses",(B4+B5)/(B6+B7)),"N/A") -> 10.30303 | C36: {=IFERROR(IF(ISNUMBER(B36),B36-_xludf.XLOOKUP("Quick Ratio",'KPI Tracker'!$A$4:$A$16,'KPI Tracker'!$B$4:$B$16),"—"),"—")} -> — | D36: Excel 02
A37: S&M (actual) | B37: =B18 -> 31000 | C37: {=IFERROR(B37-_xludf.XLOOKUP("S&M (actual)",'KPI Tracker'!$A$4:$A$16,'KPI Tracker'!$B$4:$B$16),"—")} -> — | D37: From Lisa's monthly close message
A38: CAC — this month | B38: =IFERROR(IF(B39=0,"—",B37/B39),"—") -> 15500 | C38: {=IFERROR(IF(ISNUMBER(B38),B38-_xludf.XLOOKUP("CAC — monthly",'KPI Tracker'!$A$4:$A$16,'KPI Tracker'!$B$4:$B$16),"—"),"—")} -> — | D38: Excel 04 — S&M ÷ new customers acquired this month
A39: New customers acquired | B39: 2 | C39: — | D39: Enter count of new logos signed in Feb
A40: CAC — Q1 to date | B40: =IFERROR(IF(('Jan 2026 A vs F '!B46/'Jan 2026 A vs F '!B47+B39)=0,"—",('Jan 2026 A vs F '!B46+B37)/('Jan 2026 A vs F '!B46/'Jan 2026 A vs F '!B47+B39)),"—") -> 20333.333 | C40: — | D40: Cumulative S&M ÷ cumulative new customers in Q1 so far
A41: LTV | B41: — | C41: — | D41: Quarterly metric — calculated at Q1 close
A42: LTV:CAC | B42: — | C42: — | D42: Quarterly metric — calculated at Q1 close
A43: CAC Payback | B43: — | C43: — | D43: Quarterly metric — calculated at Q1 close
A44: * Monthly CAC note:
A45: Monthly CAC is noisy with small customer counts. Q1 CAC will be the definitive figure after March closes using total Q1 S&M ÷ total Q1 new customers.
A47: † Quarterly metrics note:
A48: LTV, LTV:CAC, and CAC Payback are calculated quarterly using the trailing 12-month gross churn rate. See Q1 Roll-Up (coming in 06d).
A51: Self-Check — KPIs
A53: Metric | B53: Your value | C53: Formula check
A54: ARPA | B54: =B32 -> 3665.9878 | C54: =B9/B30 -> 3665.9878
A55: GRR | B55: =B34 -> 0.99589721 | C55: =Retention!AA6 -> 0.99589721
A56: NRR | B56: =B35 -> 0.98950128 | C56: =Retention!AA7 -> 0.98950128
A57: Quick Ratio | B57: =B36 -> 10.30303 | C57: =IFERROR(IF((B6+B7)=0,"N/A — no losses",(B4+B5)/(B6+B7)),"N/A") -> 10.30303
A58: CAC (monthly) | B58: =B38 -> 15500 | C58: =IFERROR(IF(B39=0,"—",B37/B39),"—") -> 15500
A60: Summary:
A61: February finished with a Closing MRR of $150,306. This is $1,764 above what we expected to have currently and has driven EBITDA to $30,214 which is $235 more than our current forecast and provides a margin of 20.1% compared to the planned 20.2%.
A62: Our New MRR of $6,120 beat the plan by $2,120 (a 53% plus) based on the strength of our 2 new logos vs the expected 1.3 per month from Q1. There was no Expansion MRR in this month which is a miss compared to the expected $715 and offsets some of the gain of the New MRR.
A63: The churn of $594 was subscription based, not customer based. This means that the only reduction was in the tier of subscription or seats, no accounts were lost. This is significantly better as not only did we gain 2 new accounts, we can recover the subscription churn with a potential upsell in the future.
A64: OpEx ran $1000 more than anticipated. The revenue beat was partially offset by the overrun in costs and the variance in COGS is due to the increase in revenue meaning it is mechanical and expected. Overall, this leaves a EBITDA beat of $235

Sheet Mar 2026 A vs F
A1: MRR Waterfall | H1: MONTHLY CONFIG
A2: Metric | B2: ="Actual - "&TEXT($I$2,"mmm yy") -> Actual - Mar 26 | C2: Forecast - Mar 26 | D2: $ Variance | E2: % Variance | F2: F/U | H2: Current month: | I2: 46082 | J2: ← change this when creating a new month
A3: Opening MRR | B3: {=INDEX(Actuals!$B$2:$Y$2,MATCH($I$2,Actuals!$B$1:$Y$1,0))} -> 150305.5 | C3: 150592.6 | D3: =B3-C3 -> -287.1 | E3: =IFERROR(B3/C3-1, 0) -> -0.0019064682 | F3: {=_xlfn.IFS(D3<0, "U", D3>0, "F", D3=0, "-")} -> U | H3: Prior month tab: | I3: Feb 2026 A vs F | J3: ← change this when creating a new month
A4: + New MRR | B4: {=INDEX(Actuals!$B$3:$Y$3,MATCH($I$2,Actuals!$B$1:$Y$1,0))} -> 3000 | C4: 4000 | D4: =B4-C4 -> -1000 | E4: =IFERROR(B4/C4-1, 0) -> -0.25 | F4: {=_xlfn.IFS(D4<0, "U", D4>0, "F", D4=0, "-")} -> U | H4: Month-end date: | I4: =EOMONTH(I2,0) -> 46112 | J4: ← formula: last day of current month
A5: + Expansion MRR | B5: {=INDEX(Actuals!$B$4:$Y$4,MATCH($I$2,Actuals!$B$1:$Y$1,0))} -> 380 | C5: ='2026 Forecast'!B9/3 -> 715.3475 | D5: =B5-C5 -> -335.3475 | E5: =IFERROR(B5/C5-1, 0) -> -0.46878964 | F5: {=_xlfn.IFS(D5<0, "U", D5>0, "F", D5=0, "-")} -> U
A6: - Contraction MRR | B6: 0 | C6: 0 | D6: =B6-C6 -> 0 | E6: =IFERROR(B6/C6-1, 0) -> 0 | F6: {=_xlfn.IFS(D6<0, "U", D6>0, "F", D6=0, "-")} -> -
A7: − Churned MRR | B7: {=INDEX(Actuals!$B$6:$Y$6,MATCH($I$2,Actuals!$B$1:$Y$1,0))} -> 0 | C7: ='2026 Forecast'!B10/3 -> 953.79667 | D7: =C7-B7 -> 953.79667 | E7: =IFERROR(B7/C7-1, 0) -> -1 | F7: {=_xlfn.IFS(D7>0, "F", D7<0, "U", D7=0, "-")} -> F | J7: {=INDEX(Actuals!$B$8:$Y$8,MATCH($I$2,Actuals!$B$1:$Y$1,0))} -> 29000
A8: Net New MRR | B8: =B4+B5-B7 -> 3380 | C8: =C4+C5-C7 -> 3761.5508 | D8: =B8-C8 -> -381.55083 | E8: =B8/C8-1 -> -0.10143445 | F8: {=_xlfn.IFS(D8<0, "U", D8>0, "F", D8=0, "-")} -> U
A9: Closing MRR | B9: =B3+B4+B5-B7 -> 153685.5 | C9: =C3+C8 -> 154354.15 | D9: =B9-C9 -> -668.65083 | E9: =B9/C9-1 -> -0.0043319265 | F9: {=_xlfn.IFS(D9<0, "U", D9>0, "F", D9=0, "-")} -> U
A10: Closing ARR | B10: =B9*12 -> 1844226 | C10: =C9*12 -> 1852249.8 | D10: =B10-C10 -> -8023.81 | E10: =B10/C10-1 -> -0.0043319265 | F10: {=_xlfn.IFS(D10<0, "U", D10>0, "F", D10=0, "-")} -> U
A12: P&L
A13: Metric | B13: ="Actual - "&TEXT($I$2,"mmm yy") -> Actual - Mar 26 | C13: Forecast - Mar 26 | D13: $ Variance | E13: % Variance | F13: F/U
A14: Revenue | B14: =B9 -> 153685.5 | C14: =C9 -> 154354.15 | D14: =B14-C14 -> -668.65083 | E14: =B14/C14-1 -> -0.0043319265 | F14: {=_xlfn.IFS(D14<0, "U", D14>0, "F", D14=0, "-")} -> U | H14: → Revenue × (1 − gross margin)
A15: COGS | B15: =B14*(1-B17) -> 46105.65 | C15: =C14*0.3 -> 46306.245 | D15: =B15-C15 -> -200.59525 | E15: =B15/C15-1 -> -0.0043319265 | F15: {=_xlfn.IFS(D15>0, "U", D15<0, "F", D15=0, "-")} -> F | H15: → Revenue − COGS
A16: Gross Profit | B16: =B14-B15 -> 107579.85 | C16: =C14-C15 -> 108047.91 | D16: =B16-C16 -> -468.05558 | E16: =B16/C16-1 -> -0.0043319265 | F16: {=_xlfn.IFS(D16<0, "U", D16>0, "F", D16=0, "-")} -> U | H16: → GP / Revenue
A17: Gross Margin % | B17: 0.7 | C17: =C16/C14 -> 0.7 | D17: =B17-C17 -> 0 | E17: =B17/C17-1 -> 0 | F17: {=_xlfn.IFS(D17<0, "U", D17>0, "F", D17=0, "-")} -> - | H17: ← From Assumptions tab
A18: Sales & Marketing | B18: {=INDEX(Actuals!$B$8:$Y$8,MATCH($I$2,Actuals!$B$1:$Y$1,0))} -> 29000 | C18: ='2026 Forecast'!B25/3 -> 30000 | D18: =B18-C18 -> -1000 | E18: =B18/C18-1 -> -0.033333333 | F18: {=_xlfn.IFS(D18<0, "U", D18>0, "F", D18=0, "-")} -> U | H18: ← From Assumptions tab
A19: Research & Development | B19: {=INDEX(Actuals!$B$9:$Y$9,MATCH($I$2,Actuals!$B$1:$Y$1,0))} -> 22000 | C19: ='2026 Forecast'!B26/3 -> 25000 | D19: =B19-C19 -> -3000 | E19: =B19/C19-1 -> -0.12 | F19: {=_xlfn.IFS(D19<0, "U", D19>0, "F", D19=0, "-")} -> U | H19: ← From Assumptions tab
A20: General & Administrative | B20: {=INDEX(Actuals!$B$10:$Y$10,MATCH($I$2,Actuals!$B$1:$Y$1,0))} -> 22000 | C20: ='2026 Forecast'!B27/3 -> 19000 | D20: =B20-C20 -> 3000 | E20: =B20/C20-1 -> 0.15789474 | F20: {=_xlfn.IFS(D20<0, "U", D20>0, "F", D20=0, "-")} -> F | H20: S&M + R&D + G&A
A21: Total OpEx | B21: =SUM(B18:B20) -> 73000 | C21: ='2026 Forecast'!B28/3 -> 74000 | D21: =B21-C21 -> -1000 | E21: =B21/C21-1 -> -0.013513514 | F21: {=_xlfn.IFS(D21<0, "U", D21>0, "F", D21=0, "-")} -> U | H21: → Gross Profit − Total OpEx
A22: EBITDA | B22: =B16-B21 -> 34579.85 | C22: =C16-C21 -> 34047.906 | D22: =B22-C22 -> 531.94442 | E22: =B22/C22-1 -> 0.015623411 | F22: {=_xlfn.IFS(D22<0, "U", D22>0, "F", D22=0, "-")} -> F | H22: → EBITDA / Revenue
A23: EBITDA Margin % | B23: =B22/B14 -> 0.22500399 | C23: =C22/C14 -> 0.22058303 | D23: =B23-C23 -> 0.00442096 | E23: =B23/C23-1 -> 0.020042158 | F23: {=IFERROR(_xludf.IFS(D23<0, "U", D23>0, "F", D23=0, "-"), "-")} -> -
A27: March 2026 — SaaS KPIs
A29: Metric | B29: Value | C29: ="vs "&TEXT(EOMONTH($I$2,-1),"mmm yyyy") -> vs Feb 2026 | D29: Notes
A30: Active Customers | B30: {=INDEX(Actuals!$B$16:$Y$16,MATCH($I$2,Actuals!$B$1:$Y$1,0))} -> 42 | C30: {=IFERROR(B30-_xludf.XLOOKUP("Active Customers",'KPI Tracker'!$A$4:$A$16,'KPI Tracker'!$C$4:$C$16),"—")} -> — | D30: From your Mar 31SQL snapshot
A31: Active Subscriptions | B31: {=INDEX(Actuals!$B$17:$Y$17,MATCH($I$2,Actuals!$B$1:$Y$1,0))} -> 54 | C31: {=B31-INDEX(Actuals!$B$17:$Y$17,MATCH(DATE(YEAR($I$2),MONTH($I$2)-1,1),Actuals!$B$1:$Y$1,0))} -> 1 | D31: From your Mar 31 SQL snapshot
A32: ARPA | B32: =B9/B30 -> 3659.1786 | C32: {=IFERROR(B32-INDEX(Actuals!$B$7:$Y$7,MATCH(DATE(YEAR($I$2),MONTH($I$2)-1,1),Actuals!$B$1:$Y$1,0))/INDEX(Actuals!$B$16:$Y$16,MATCH(DATE(YEAR($I$2),MONTH($I$2)-1,1),Actuals!$B$1:$Y$1,0)),"—")} -> -6.8092334 | D32: Excel 04
A33: Gross Margin | B33: =B17 -> 0.7 | C33: =0 -> 0 | D33: Already in your P&L
A34: GRR | B34: {=INDEX(Retention!$B$6:$BJ$6,MATCH($I$2,Retention!$B$4:$BJ$4,0))} -> 1 | C34: {=B34-INDEX(Retention!$B$6:$BJ$6,MATCH(DATE(YEAR($I$2),MONTH($I$2)-1,1),Retention!$B$4:$BJ$4,0))} -> 0.0041027908 | D34: Excel 03
A35: NRR | B35: {=INDEX(Retention!$B$7:$BJ$7,MATCH($I$2,Retention!$B$4:$BJ$4,0))} -> 1.0025282 | C35: {=B35-INDEX(Retention!$B$7:$BJ$7,MATCH(DATE(YEAR($I$2),MONTH($I$2)-1,1),Retention!$B$4:$BJ$4,0))} -> 0.013026908 | D35: Excel 03
A36: Quick Ratio | B36: =IFERROR(IF((B6+B7)=0,"N/A — no losses",(B4+B5)/(B6+B7)),"N/A") -> N/A — no losses | C36: {=IFERROR(IF(ISNUMBER(B36),B36-_xludf.XLOOKUP("Quick Ratio",'KPI Tracker'!$A$4:$A$16,'KPI Tracker'!$B$4:$B$16),"—"),"—")} -> — | D36: Excel 02
A37: S&M (actual) | B37: =B18 -> 29000 | C37: {=B37-INDEX(Actuals!$B$8:$Y$8,MATCH(DATE(YEAR($I$2),MONTH($I$2)-1,1),Actuals!$B$1:$Y$1,0))} -> -2000 | D37: From Lisa's monthly close message
A38: CAC — this month | B38: =IFERROR(IF(B39=0,"—",B37/B39),"—") -> 14500 | C38: {=IFERROR(B38-INDEX(Actuals!$B$8:$Y$8,MATCH(DATE(YEAR($I$2),MONTH($I$2)-1,1),Actuals!$B$1:$Y$1,0))/INDEX(Actuals!$B$15:$Y$15,MATCH(DATE(YEAR($I$2),MONTH($I$2)-1,1),Actuals!$B$1:$Y$1,0)),"—")} -> -1000 | D38: Excel 04 — S&M ÷ new customers acquired this month
A39: New customers acquired | B39: {=INDEX(Actuals!$B$15:$Y$15,MATCH($I$2,Actuals!$B$1:$Y$1,0))} -> 2 | C39: — | D39: Enter count of new logos signed in Mar
A40: CAC — Q1 to date | B40: =IFERROR(IF(('Jan 2026 A vs F '!B46/'Jan 2026 A vs F '!B47+'Feb 2026 A vs F'!B39+B39)=0,"—",('Jan 2026 A vs F '!B46+'Feb 2026 A vs F'!B37+B37)/('Jan 2026 A vs F '!B46/'Jan 2026 A vs F '!B47+'Feb 2026 A vs F'!B39+B39)),"—") -> 18000 | C40: — | D40: Cumulative S&M ÷ cumulative new customers in Q1 so far
A41: LTV | B41: — | C41: — | D41: Quarterly metric — calculated at Q1 close
A42: LTV:CAC | B42: — | C42: — | D42: Quarterly metric — calculated at Q1 close
A43: CAC Payback | B43: — | C43: — | D43: Quarterly metric — calculated at Q1 close
A44: * Monthly CAC note:
A45: Monthly CAC is noisy with small customer counts. Q1 CAC will be the definitive figure after March closes using total Q1 S&M ÷ total Q1 new customers.
A47: † Quarterly metrics note:
A48: LTV, LTV:CAC, and CAC Payback are calculated quarterly using the trailing 12-month gross churn rate. See Q1 Roll-Up (coming in 06d).
A51: Self-Check — KPIs
A53: Metric | B53: Your value | C53: Formula check
A54: ARPA | B54: =B32 -> 3659.1786 | C54: =B9/B30 -> 3659.1786
A55: GRR | B55: =B34 -> 1 | C55: {=INDEX(Retention!$B$6:$BJ$6, MATCH($I$2, Retention!$B$4:$BJ$4,0))} -> 1 | E55: INDEX(Retention!$B$6:$AZ$6,MATCH($I$2,Retention!$B$4:$AZ$4,0))
A56: NRR | B56: =B35 -> 1.0025282 | C56: {=INDEX(Retention!$B$7:$BJ$7, MATCH($I$2, Retention!$B$4:$BJ$4,0))} -> 1.0025282
A57: Quick Ratio | B57: =B36 -> N/A — no losses | C57: =IFERROR(IF((B6+B7)=0,"N/A — no losses",(B4+B5)/(B6+B7)),"N/A") -> N/A — no losses
A58: CAC (monthly) | B58: =B38 -> 14500 | C58: =IFERROR(IF(B39=0,"—",B37/B39),"—") -> 14500
A60: Summary:
A61: =TEXT($I$2,"mmmm yyyy")&" — Closing MRR: "&TEXT(B9,"$#,##0")&" | NRR: "&TEXT(B35,"0.0%")&" | EBITDA margin: "&TEXT(B23,"0.0%") -> March 2026 — Closing MRR: $153,686 | NRR: 100.3% | EBITDA margin: 22.5%
A62: March closed at $153,686 MRR, bringing Q1 total net new MRR to $10,616, which is a 7.4% gain on the opening value of $143,070.
A63: Every month in Q1 had NRR reaching 100%. $380 of expansion MRR from an existing account, combined with zero churn for the second consecutive month, signals that the installed base is healthy and beginning to grow.
A64: EBITDA margin improved each month of Q1. 18.9% in January, 20.1% in February, 22.5% in March, each driven by OpEx tracking below forecast and revenue compounding based mostly on fixed cost. The direction is positive, though improvement has come from maintaining low costs rather than outperforming revenue.
A65: The key watch item for Q2 is new logo conversion. New MRR missed forecast in every month of Q1 ($10,830 actual vs. $12,000 planned) and the March expansion signal came from a single account. If this trend doesn't change, Q2 could face the same issue.
A67: Q1 2026 Roll-Up
A69: Q1 MRR Summary
A70: Movement | B70: Q1 Total
A71: Q1 Total New MRR | B71: ='Jan 2026 A vs F '!B4+'Feb 2026 A vs F'!B4+'Mar 2026 A vs F'!B4 -> 10830
A72: Q1 Total Expansion MRR | B72: ='Jan 2026 A vs F '!B5+'Feb 2026 A vs F'!B5+'Mar 2026 A vs F'!B5 -> 380
A73: Q1 Total Churned MRR | B73: ='Jan 2026 A vs F '!B7+'Feb 2026 A vs F'!B7+'Mar 2026 A vs F'!B7 -> 594
A74: Q1 Net New MRR | B74: ='Jan 2026 A vs F '!B8+'Feb 2026 A vs F'!B8+'Mar 2026 A vs F'!B8 -> 10616
A75: Q1 Closing MRR | B75: ='Mar 2026 A vs F'!B9 -> 153685.5
A77: Q1 P&L Summary
A78: Line | B78: Q1 Total
A79: Q1 Revenue | B79: ='Jan 2026 A vs F '!B14+'Feb 2026 A vs F'!B14+'Mar 2026 A vs F'!B14 -> 448770.5
A80: Q1 COGS | B80: ='Jan 2026 A vs F '!B15+'Feb 2026 A vs F'!B15+'Mar 2026 A vs F'!B15 -> 134631.15
A81: Q1 Gross Profit | B81: =B79-B80 -> 314139.35
A82: Q1 Gross Margin % | B82: =B81/B79 -> 0.7
A83: Q1 S&M | B83: ='Jan 2026 A vs F '!B18+'Feb 2026 A vs F'!B18+'Mar 2026 A vs F'!B18 -> 90000
A84: Q1 R&D + G&A | B84: ='Jan 2026 A vs F '!B19+'Jan 2026 A vs F '!B20+'Feb 2026 A vs F'!B19+'Feb 2026 A vs F'!B20+'Mar 2026 A vs F'!B19+'Mar 2026 A vs F'!B20 -> 132000
A85: Q1 Total OpEx | B85: ='Jan 2026 A vs F '!B21+'Feb 2026 A vs F'!B21+'Mar 2026 A vs F'!B21 -> 222000
A86: Q1 EBITDA | B86: =B81-B85 -> 92139.35
A87: Q1 EBITDA Margin % | B87: =B86/B79 -> 0.20531508
A89: Q1 Quarterly KPI's
A90: Metric | B90: Q1 Total
A91: Q1 New Customers | B91: =Actuals!B15+Actuals!C15+Actuals!D15 -> 5
A92: Quarterly CAC | B92: =B83/B91 -> 18000
A93: LTV | B93: =(B82/((B73/'Jan 2026 A vs F '!B3)*12)*'Mar 2026 A vs F'!B54) -> 51411.587
A94: LTV:CAC | B94: =B93/B92 -> 2.8561993
A95: CAC Payback (months) | B95: =B92/(B54*B82) -> 7.0273383
A97: Q1 Commentary:
A98: Q1 closed with $448,771 in revenue and $92,139.5 of EBITDA at a 20.5% margin. A solid first quarter, with margins expanding every month as the cost base remained largely fixed against compounding MRR.
A99: The unit economics require attention: LTV:CAC of 2.86x is below the 3x threshold that benchmarks a capital-efficient SaaS business, and CAC Payback of 7.03 months is significantly below the 12-month early-stage ceiling, leaves little margin for error. Both ratios reflect a business that is acquiring customers at a cost that outpaces the current lifetime value they generate.
A100: Across the quarter, MRR grew every month (+7.3% overall), EBITDA margin improved steadily, and March produced the first expansion MRR of Q1. The trend is directionally positive, though NRR spent two of three months exactly at 100% with no expansion.
A101: For Q2, the data points to one clear priority: expanding on our current logos. This would result in an improved LTV, push NRR above 100%, and reduce our dependancy on new logo volume since it has underperformed the entire quarter.

Sheet Apr 2026 A vs F 
A1: MRR Waterfall | H1: MONTHLY CONFIG
A2: Metric | B2: ="Actual - "&TEXT($I$2,"mmm yy") -> Actual - Apr 26 | C2: Forecast - Apr 26 | D2: $ Variance | E2: % Variance | F2: F/U | H2: Current month: | I2: 46113 | J2: ← change this when creating a new month
A3: Opening MRR | B3: {=INDEX(Actuals!$B$2:$Y$2,MATCH($I$2,Actuals!$B$1:$Y$1,0))} -> 153685.5 | C3: =INDEX('Monthly Forecast'!$B$5:$M$5,MATCH($I$2,'Monthly Forecast'!$B$4:$M$4,0)) -> 154325.79 | D3: =B3-C3 -> -640.29393 | E3: =IFERROR(B3/C3-1, 0) -> -0.0041489754 | F3: {=_xlfn.IFS(D3<0, "U", D3>0, "F", D3=0, "-")} -> U | H3: Prior month tab: | I3: Mar 2026 A vs F | J3: ← change this when creating a new month
A4: + New MRR | B4: {=INDEX(Actuals!$B$3:$Y$3,MATCH($I$2,Actuals!$B$1:$Y$1,0))} -> 3810 | C4: =INDEX('Monthly Forecast'!$B$6:$M$6,MATCH($I$2,'Monthly Forecast'!$B$4:$M$4,0)) -> 6400 | D4: =B4-C4 -> -2590 | E4: =IFERROR(B4/C4-1, 0) -> -0.4046875 | F4: {=_xlfn.IFS(D4<0, "U", D4>0, "F", D4=0, "-")} -> U | H4: Month-end date: | I4: =EOMONTH(I2,0) -> 46142 | J4: ← formula: last day of current month
A5: + Expansion MRR | B5: {=INDEX(Actuals!$B$4:$Y$4,MATCH($I$2,Actuals!$B$1:$Y$1,0))} -> 440 | C5: =INDEX('Monthly Forecast'!$B$7:$M$7,MATCH($I$2,'Monthly Forecast'!$B$4:$M$4,0)) -> 771.62897 | D5: =B5-C5 -> -331.62897 | E5: =IFERROR(B5/C5-1, 0) -> -0.42977776 | F5: {=_xlfn.IFS(D5<0, "U", D5>0, "F", D5=0, "-")} -> U
A6: - Contraction MRR | B6: 0 | C6: =INDEX('Monthly Forecast'!$B$8:$M$8,MATCH($I$2,'Monthly Forecast'!$B$4:$M$4,0)) -> 0 | D6: =B6-C6 -> 0 | E6: =IFERROR(B6/C6-1, 0) -> 0 | F6: {=_xlfn.IFS(D6<0, "U", D6>0, "F", D6=0, "-")} -> -
A7: − Churned MRR | B7: {=INDEX(Actuals!$B$6:$Y$6,MATCH($I$2,Actuals!$B$1:$Y$1,0))} -> 1105 | C7: =INDEX('Monthly Forecast'!$B$9:$M$9,MATCH($I$2,'Monthly Forecast'!$B$4:$M$4,0)) -> 1033.9828 | D7: =C7-B7 -> -71.017181 | E7: =IFERROR(B7/C7-1, 0) -> 0.068683134 | F7: {=_xlfn.IFS(D7>0, "F", D7<0, "U", D7=0, "-")} -> U
A8: Net New MRR | B8: =B4+B5-B7 -> 3145 | C8: =C4+C5-C6-C7 -> 6137.6462 | D8: =B8-C8 -> -2992.6462 | E8: =B8/C8-1 -> -0.48758858 | F8: {=_xlfn.IFS(D8<0, "U", D8>0, "F", D8=0, "-")} -> U
A9: Closing MRR | B9: =B3+B4+B5-B7 -> 156830.5 | C9: =C3+C8 -> 160463.44 | D9: =B9-C9 -> -3632.9401 | E9: =B9/C9-1 -> -0.022640298 | F9: {=_xlfn.IFS(D9<0, "U", D9>0, "F", D9=0, "-")} -> U
A10: Closing ARR | B10: =B9*12 -> 1881966 | C10: =C9*12 -> 1925561.3 | D10: =B10-C10 -> -43595.281 | E10: =B10/C10-1 -> -0.022640298 | F10: {=_xlfn.IFS(D10<0, "U", D10>0, "F", D10=0, "-")} -> U
A12: P&L
A13: Metric | B13: ="Actual - "&TEXT($I$2,"mmm yy") -> Actual - Apr 26 | C13: Forecast - Apr 26 | D13: $ Variance | E13: % Variance | F13: F/U
A14: Revenue | B14: =B9 -> 156830.5 | C14: =C9 -> 160463.44 | D14: =B14-C14 -> -3632.9401 | E14: =B14/C14-1 -> -0.022640298 | F14: {=_xlfn.IFS(D14<0, "U", D14>0, "F", D14=0, "-")} -> U | H14: → Revenue × (1 − gross margin)
A15: COGS | B15: =B14*(1-B17) -> 47049.15 | C15: =C14*0.3 -> 48139.032 | D15: =B15-C15 -> -1089.882 | E15: =B15/C15-1 -> -0.022640298 | F15: {=_xlfn.IFS(D15>0, "U", D15<0, "F", D15=0, "-")} -> F | H15: → Revenue − COGS
A16: Gross Profit | B16: =B14-B15 -> 109781.35 | C16: =C14-C15 -> 112324.41 | D16: =B16-C16 -> -2543.0581 | E16: =B16/C16-1 -> -0.022640298 | F16: {=_xlfn.IFS(D16<0, "U", D16>0, "F", D16=0, "-")} -> U | H16: → GP / Revenue
A17: Gross Margin % | B17: 0.7 | C17: =C16/C14 -> 0.7 | D17: =B17-C17 -> 0 | E17: =B17/C17-1 -> 0 | F17: {=_xlfn.IFS(D17<0, "U", D17>0, "F", D17=0, "-")} -> - | H17: ← From Assumptions tab
A18: Sales & Marketing | B18: =Actuals!E8 -> 32000 | C18: =INDEX('Monthly Forecast'!$B$20:$M$20,MATCH($I$2,'Monthly Forecast'!$B$4:$M$4,0)) -> 30000 | D18: =B18-C18 -> 2000 | E18: =B18/C18-1 -> 0.066666667 | F18: {=_xlfn.IFS(D18<0, "U", D18>0, "F", D18=0, "-")} -> F | H18: ← From Assumptions tab
A19: Research & Development | B19: =Actuals!E9 -> 23000 | C19: =INDEX('Monthly Forecast'!$B$21:$M$21,MATCH($I$2,'Monthly Forecast'!$B$4:$M$4,0)) -> 25000 | D19: =B19-C19 -> -2000 | E19: =B19/C19-1 -> -0.08 | F19: {=_xlfn.IFS(D19<0, "U", D19>0, "F", D19=0, "-")} -> U | H19: ← From Assumptions tab
A20: General & Administrative | B20: =Actuals!E10 -> 20000 | C20: =INDEX('Monthly Forecast'!$B$22:$M$22,MATCH($I$2,'Monthly Forecast'!$B$4:$M$4,0)) -> 19000 | D20: =B20-C20 -> 1000 | E20: =B20/C20-1 -> 0.052631579 | F20: {=_xlfn.IFS(D20<0, "U", D20>0, "F", D20=0, "-")} -> F | H20: S&M + R&D + G&A
A21: Total OpEx | B21: =SUM(B18:B20) -> 75000 | C21: =SUM(C18:C20) -> 74000 | D21: =B21-C21 -> 1000 | E21: =B21/C21-1 -> 0.013513514 | F21: {=_xlfn.IFS(D21<0, "U", D21>0, "F", D21=0, "-")} -> F | H21: → Gross Profit − Total OpEx
A22: EBITDA | B22: =B16-B21 -> 34781.35 | C22: =C16-C21 -> 38324.408 | D22: =B22-C22 -> -3543.0581 | E22: =B22/C22-1 -> -0.092449127 | F22: {=_xlfn.IFS(D22<0, "U", D22>0, "F", D22=0, "-")} -> U | H22: → EBITDA / Revenue
A23: EBITDA Margin % | B23: =B22/B14 -> 0.2217767 | C23: =C22/C14 -> 0.23883576 | D23: =B23-C23 -> -0.017059067 | E23: =B23/C23-1 -> -0.071425933 | F23: {=IFERROR(_xludf.IFS(D23<0, "U", D23>0, "F", D23=0, "-"), "-")} -> -
A27: April 2026 — SaaS KPIs
A29: Metric | B29: Value | C29: ="vs "&TEXT(EOMONTH($I$2,-1),"mmm yyyy") -> vs Mar 2026 | D29: Notes
A30: Active Customers | B30: {=INDEX(Actuals!$B$16:$Y$16,MATCH($I$2,Actuals!$B$1:$Y$1,0))} -> 44 | C30: {=B30-INDEX(Actuals!$B$16:$Y$16,MATCH(DATE(YEAR($I$2),MONTH($I$2)-1,1),Actuals!$B$1:$Y$1,0))} -> 2 | D30: From your Apr 30 SQL snapshot
A31: Active Subscriptions | B31: {=INDEX(Actuals!$B$17:$Y$17,MATCH($I$2,Actuals!$B$1:$Y$1,0))} -> 55 | C31: {=B31-INDEX(Actuals!$B$17:$Y$17,MATCH(DATE(YEAR($I$2),MONTH($I$2)-1,1),Actuals!$B$1:$Y$1,0))} -> 1 | D31: From your Apr 30 SQL snapshot
A32: ARPA | B32: =B9/B30 -> 3564.3295 | C32: {=IFERROR(B32-INDEX(Actuals!$B$7:$Y$7,MATCH(DATE(YEAR($I$2),MONTH($I$2)-1,1),Actuals!$B$1:$Y$1,0))/INDEX(Actuals!$B$16:$Y$16,MATCH(DATE(YEAR($I$2),MONTH($I$2)-1,1),Actuals!$B$1:$Y$1,0)),"—")} -> -94.849026 | D32: Excel 04
A33: Gross Margin | B33: =B17 -> 0.7 | C33: =0 -> 0 | D33: Already in your P&L
A34: GRR | B34: {=INDEX(Retention!$B$6:$BJ$6,MATCH($I$2,Retention!$B$4:$BJ$4,0))} -> 0.99280999 | C34: {=B34-INDEX(Retention!$B$6:$BJ$6,MATCH(DATE(YEAR($I$2),MONTH($I$2)-1,1),Retention!$B$4:$BJ$4,0))} -> -0.0071900082 | D34: Excel 03 | K34: =VLOOKUP('KPI Tracker'!A10,'KPI Tracker'!A4:F16,3) -> 10.30303
A35: NRR | B35: {=INDEX(Retention!$B$7:$BJ$7,MATCH($I$2,Retention!$B$4:$BJ$4,0))} -> 0.99567298 | C35: {=B35-INDEX(Retention!$B$7:$BJ$7,MATCH(DATE(YEAR($I$2),MONTH($I$2)-1,1),Retention!$B$4:$BJ$4,0))} -> -0.0068552028 | D35: Excel 03
A36: Quick Ratio | B36: =IFERROR(IF((B6+B7)=0,"N/A — no losses",(B4+B5)/(B6+B7)),"N/A") -> 3.8461538 | C36: =IFERROR(IF(ISNUMBER(B36),B36-INDEX('KPI Tracker'!$B$10:$F$10,MATCH(DATE(YEAR($I$2),MONTH($I$2)-1,1),'KPI Tracker'!$B$3:$F$3,0)),"—"),"—") -> — | D36: Excel 02
A37: S&M (actual) | B37: =B18 -> 32000 | C37: {=B37-INDEX(Actuals!$B$8:$Y$8,MATCH(DATE(YEAR($I$2),MONTH($I$2)-1,1),Actuals!$B$1:$Y$1,0))} -> 3000 | D37: From Lisa's monthly close message
A38: CAC — this month | B38: =IFERROR(IF(B39=0,"—",B37/B39),"—") -> 16000 | C38: {=IFERROR(B38-INDEX(Actuals!$B$8:$Y$8,MATCH(DATE(YEAR($I$2),MONTH($I$2)-1,1),Actuals!$B$1:$Y$1,0))/INDEX(Actuals!$B$15:$Y$15,MATCH(DATE(YEAR($I$2),MONTH($I$2)-1,1),Actuals!$B$1:$Y$1,0)),"—")} -> 1500 | D38: Excel 04 — S&M ÷ new customers acquired this month
A39: New customers acquired | B39: {=INDEX(Actuals!$B$15:$Y$15,MATCH($I$2,Actuals!$B$1:$Y$1,0))} -> 2 | C39: — | D39: Enter count of new logos signed in Apr
A40: CAC — Q1 to date | B40: =IFERROR(IF(('Jan 2026 A vs F '!B46/'Jan 2026 A vs F '!B47+'Feb 2026 A vs F'!B39+B39)=0,"—",('Jan 2026 A vs F '!B46+'Feb 2026 A vs F'!B37+B37)/('Jan 2026 A vs F '!B46/'Jan 2026 A vs F '!B47+'Feb 2026 A vs F'!B39+B39)),"—") -> 18600 | C40: — | D40: Cumulative S&M ÷ cumulative new customers in Q1 so far
A41: LTV | B41: — | C41: — | D41: Quarterly metric — calculated at Q1 close
A42: LTV:CAC | B42: — | C42: — | D42: Quarterly metric — calculated at Q1 close
A43: CAC Payback | B43: — | C43: — | D43: Quarterly metric — calculated at Q1 close
A44: * Monthly CAC note:
A45: Monthly CAC is noisy with small customer counts. Q1 CAC will be the definitive figure after March closes using total Q1 S&M ÷ total Q1 new customers.
A47: † Quarterly metrics note:
A48: LTV, LTV:CAC, and CAC Payback are calculated quarterly using the trailing 12-month gross churn rate. See Q1 Roll-Up (coming in 06d).
A51: Self-Check — KPIs
A53: Metric | B53: Your value | C53: Formula check
A54: ARPA | B54: =B32 -> 3564.3295 | C54: =B9/B30 -> 3564.3295
A55: GRR | B55: =B34 -> 0.99280999 | C55: {=INDEX(Retention!$B$6:$BJ$6, MATCH($I$2, Retention!$B$4:$BJ$4,0))} -> 0.99280999 | E55: INDEX(Retention!$B$6:$AZ$6,MATCH($I$2,Retention!$B$4:$AZ$4,0))
A56: NRR | B56: =B35 -> 0.99567298 | C56: {=INDEX(Retention!$B$7:$BJ$7, MATCH($I$2, Retention!$B$4:$BJ$4,0))} -> 0.99567298
A57: Quick Ratio | B57: =B36 -> 3.8461538 | C57: =IFERROR(IF((B6+B7)=0,"N/A — no losses",(B4+B5)/(B6+B7)),"N/A") -> 3.8461538
A58: CAC (monthly) | B58: =B38 -> 16000 | C58: =IFERROR(IF(B39=0,"—",B37/B39),"—") -> 16000
A60: Summary:
A61: =TEXT($I$2,"mmmm yyyy")&" — Closing MRR: "&TEXT(B9,"$#,##0")&" | NRR: "&TEXT(B35,"0.0%")&" | EBITDA margin: "&TEXT(B23,"0.0%") -> April 2026 — Closing MRR: $156,831 | NRR: 99.6% | EBITDA margin: 22.2%
A62: April closed at a Closing MRR of $156,830.50 — $3,633 (2.3%) below the April plan of $160,463. EBITDA of $34,781.35 landed $3,543 under plan, a 22.2% margin versus the 23.9% planned. The month missed plan on new-business quality and expansion; OpEx was essentially on target. Note the earlier read of a 'beat' compared April to the Q1/March-end target, not to April's own plan.
A63: New MRR of $3,810 was $2,590 short of the $6,400 plan. We signed 2 new logos — in line with the planned count — but at roughly $1,905 of MRR each versus the ~$3,200 assumed, so the shortfall is new-logo quality, not volume. Expansion MRR of $440 was $332 below the $772 plan, and churn ran slightly heavier than planned.
A64: The cancelled subscription this month was the Analytics Starter plan from Montreal Finance Hub. This is a revenue churn, not a logo churn: they still hold a Marketing Pro subscription, so we lost the revenue but kept the logo. That distinction matters because the active-customer count stays flat — Montreal Finance Hub remains a customer we can win back to multi-plan, unlike a full logo loss where the relationship ends entirely.
A65: OpEx ran $1,000 over plan ($75k vs $74k), from higher S&M and G&A. Combined with the revenue miss, that pulled EBITDA $3,543 below plan. The route back to plan is new-logo ARPA and expansion, not cost discipline — spend was close to target.

Sheet May 2026 A vs F 
A1: MRR Waterfall | H1: MONTHLY CONFIG
A2: Metric | B2: ="Actual - "&TEXT($I$2,"mmm yy") -> Actual - May 26 | C2: Forecast - May 26 | D2: $ Variance | E2: % Variance | F2: F/U | H2: Current month: | I2: 46143 | J2: ← change this when creating a new month
A3: Opening MRR | B3: =INDEX(Actuals!$B$2:$Y$2,MATCH($I$2,Actuals!$B$1:$Y$1,0)) -> 156830.5 | C3: =INDEX('Monthly Forecast'!$B$5:$M$5,MATCH($I$2,'Monthly Forecast'!$B$4:$M$4,0)) -> 160463.44 | D3: =B3-C3 -> -3632.9401 | E3: =IFERROR(B3/C3-1, 0) -> -0.022640298 | F3: {=_xlfn.IFS(D3<0, "U", D3>0, "F", D3=0, "-")} -> U | H3: Prior month tab: | I3: Apr 2026 A vs F | J3: ← change this when creating a new month
A4: + New MRR | B4: {=INDEX(Actuals!$B$3:$Y$3,MATCH($I$2,Actuals!$B$1:$Y$1,0))} -> 4780 | C4: =INDEX('Monthly Forecast'!$B$6:$M$6,MATCH($I$2,'Monthly Forecast'!$B$4:$M$4,0)) -> 6400 | D4: =B4-C4 -> -1620 | E4: =IFERROR(B4/C4-1, 0) -> -0.253125 | F4: {=_xlfn.IFS(D4<0, "U", D4>0, "F", D4=0, "-")} -> U | H4: Month-end date: | I4: =EOMONTH(I2,0) -> 46173 | J4: ← formula: last day of current month
A5: + Expansion MRR | B5: =INDEX(Actuals!$B$4:$Y$4,MATCH($I$2,Actuals!$B$1:$Y$1,0)) -> 425 | C5: =INDEX('Monthly Forecast'!$B$7:$M$7,MATCH($I$2,'Monthly Forecast'!$B$4:$M$4,0)) -> 802.3172 | D5: =B5-C5 -> -377.3172 | E5: =IFERROR(B5/C5-1, 0) -> -0.47028432 | F5: {=_xlfn.IFS(D5<0, "U", D5>0, "F", D5=0, "-")} -> U
A6: - Contraction MRR | B6: =INDEX(Actuals!$B$5:$Y$5,MATCH($I$2,Actuals!$B$1:$Y$1,0)) -> 440 | C6: =INDEX('Monthly Forecast'!$B$8:$M$8,MATCH($I$2,'Monthly Forecast'!$B$4:$M$4,0)) -> 0 | D6: =B6-C6 -> 440 | E6: =IFERROR(B6/C6-1, 0) -> 0 | F6: {=_xlfn.IFS(D6<0, "U", D6>0, "F", D6=0, "-")} -> F
A7: − Churned MRR | B7: {=INDEX(Actuals!$B$6:$Y$6,MATCH($I$2,Actuals!$B$1:$Y$1,0))} -> 1520 | C7: =INDEX('Monthly Forecast'!$B$9:$M$9,MATCH($I$2,'Monthly Forecast'!$B$4:$M$4,0)) -> 1075.105 | D7: =C7-B7 -> -444.89495 | E7: =IFERROR(B7/C7-1, 0) -> 0.41381533 | F7: {=_xlfn.IFS(D7>0, "F", D7<0, "U", D7=0, "-")} -> U
A8: Net New MRR | B8: =B4+B5-B6-B7 -> 3245 | C8: =C4+C5-C6-C7 -> 6127.2122 | D8: =B8-C8 -> -2882.2122 | E8: =B8/C8-1 -> -0.47039536 | F8: {=_xlfn.IFS(D8<0, "U", D8>0, "F", D8=0, "-")} -> U
A9: Closing MRR | B9: =B3+B4+B5-B6-B7 -> 160075.5 | C9: =C3+C8 -> 166590.65 | D9: =B9-C9 -> -6515.1522 | E9: =B9/C9-1 -> -0.03910875 | F9: {=_xlfn.IFS(D9<0, "U", D9>0, "F", D9=0, "-")} -> U
A10: Closing ARR | B10: =B9*12 -> 1920906 | C10: =C9*12 -> 1999087.8 | D10: =B10-C10 -> -78181.827 | E10: =B10/C10-1 -> -0.03910875 | F10: {=_xlfn.IFS(D10<0, "U", D10>0, "F", D10=0, "-")} -> U
A12: P&L
A13: Metric | B13: ="Actual - "&TEXT($I$2,"mmm yy") -> Actual - May 26 | C13: Forecast - May 26 | D13: $ Variance | E13: % Variance | F13: F/U
A14: Revenue | B14: =B9 -> 160075.5 | C14: =C9 -> 166590.65 | D14: =B14-C14 -> -6515.1522 | E14: =B14/C14-1 -> -0.03910875 | F14: {=_xlfn.IFS(D14<0, "U", D14>0, "F", D14=0, "-")} -> U | H14: → Revenue × (1 − gross margin)
A15: COGS | B15: =B14*(1-B17) -> 48022.65 | C15: =C14*0.3 -> 49977.196 | D15: =B15-C15 -> -1954.5457 | E15: =B15/C15-1 -> -0.03910875 | F15: {=_xlfn.IFS(D15>0, "U", D15<0, "F", D15=0, "-")} -> F | H15: → Revenue − COGS
A16: Gross Profit | B16: =B14-B15 -> 112052.85 | C16: =C14-C15 -> 116613.46 | D16: =B16-C16 -> -4560.6066 | E16: =B16/C16-1 -> -0.03910875 | F16: {=_xlfn.IFS(D16<0, "U", D16>0, "F", D16=0, "-")} -> U | H16: → GP / Revenue
A17: Gross Margin % | B17: 0.7 | C17: =C16/C14 -> 0.7 | D17: =B17-C17 -> 0 | E17: =B17/C17-1 -> 0 | F17: {=_xlfn.IFS(D17<0, "U", D17>0, "F", D17=0, "-")} -> - | H17: ← From Assumptions tab
A18: Sales & Marketing | B18: 29000 | C18: =INDEX('Monthly Forecast'!$B$20:$M$20,MATCH($I$2,'Monthly Forecast'!$B$4:$M$4,0)) -> 30000 | D18: =B18-C18 -> -1000 | E18: =B18/C18-1 -> -0.033333333 | F18: {=_xlfn.IFS(D18<0, "U", D18>0, "F", D18=0, "-")} -> U | H18: ← From Assumptions tab
A19: Research & Development | B19: 24000 | C19: =INDEX('Monthly Forecast'!$B$21:$M$21,MATCH($I$2,'Monthly Forecast'!$B$4:$M$4,0)) -> 25000 | D19: =B19-C19 -> -1000 | E19: =B19/C19-1 -> -0.04 | F19: {=_xlfn.IFS(D19<0, "U", D19>0, "F", D19=0, "-")} -> U | H19: ← From Assumptions tab
A20: General & Administrative | B20: 21000 | C20: =INDEX('Monthly Forecast'!$B$22:$M$22,MATCH($I$2,'Monthly Forecast'!$B$4:$M$4,0)) -> 19000 | D20: =B20-C20 -> 2000 | E20: =B20/C20-1 -> 0.10526316 | F20: {=_xlfn.IFS(D20<0, "U", D20>0, "F", D20=0, "-")} -> F | H20: S&M + R&D + G&A
A21: Total OpEx | B21: =SUM(B18:B20) -> 74000 | C21: =SUM(C18:C20) -> 74000 | D21: =B21-C21 -> 0 | E21: =B21/C21-1 -> 0 | F21: {=_xlfn.IFS(D21<0, "U", D21>0, "F", D21=0, "-")} -> - | H21: → Gross Profit − Total OpEx
A22: EBITDA | B22: =B16-B21 -> 38052.85 | C22: =C16-C21 -> 42613.457 | D22: =B22-C22 -> -4560.6066 | E22: =B22/C22-1 -> -0.10702269 | F22: {=_xlfn.IFS(D22<0, "U", D22>0, "F", D22=0, "-")} -> U | H22: → EBITDA / Revenue
A23: EBITDA Margin % | B23: =B22/B14 -> 0.23771814 | C23: =C22/C14 -> 0.25579741 | D23: =B23-C23 -> -0.018079266 | E23: =B23/C23-1 -> -0.070678066 | F23: {=IFERROR(_xludf.IFS(D23<0, "U", D23>0, "F", D23=0, "-"), "-")} -> -
A27: May 2026 — SaaS KPIs
A29: Metric | B29: Value | C29: ="vs "&TEXT(EOMONTH($I$2,-1),"mmm yyyy") -> vs Apr 2026 | D29: Notes
A30: Active Customers | B30: {=INDEX(Actuals!$B$16:$Y$16,MATCH($I$2,Actuals!$B$1:$Y$1,0))} -> 45 | C30: {=B30-INDEX(Actuals!$B$16:$Y$16,MATCH(DATE(YEAR($I$2),MONTH($I$2)-1,1),Actuals!$B$1:$Y$1,0))} -> 1 | D30: From your May 31 SQL snapshot
A31: Active Subscriptions | B31: {=INDEX(Actuals!$B$17:$Y$17,MATCH($I$2,Actuals!$B$1:$Y$1,0))} -> 56 | C31: {=B31-INDEX(Actuals!$B$17:$Y$17,MATCH(DATE(YEAR($I$2),MONTH($I$2)-1,1),Actuals!$B$1:$Y$1,0))} -> 1 | D31: From your May 31 SQL snapshot
A32: ARPA | B32: =B9/B30 -> 3557.2333 | C32: {=IFERROR(B32-INDEX(Actuals!$B$7:$Y$7,MATCH(DATE(YEAR($I$2),MONTH($I$2)-1,1),Actuals!$B$1:$Y$1,0))/INDEX(Actuals!$B$16:$Y$16,MATCH(DATE(YEAR($I$2),MONTH($I$2)-1,1),Actuals!$B$1:$Y$1,0)),"—")} -> -7.0962121 | D32: Excel 04
A33: Gross Margin | B33: =B17 -> 0.7 | C33: =0 -> 0 | D33: Already in your P&L
A34: GRR | B34: {=INDEX(Retention!$B$6:$BJ$6,MATCH($I$2,Retention!$B$4:$BJ$4,0))} -> 0.98750243 | C34: {=B34-INDEX(Retention!$B$6:$BJ$6,MATCH(DATE(YEAR($I$2),MONTH($I$2)-1,1),Retention!$B$4:$BJ$4,0))} -> -0.0053075609 | D34: Excel 03
A35: NRR | B35: {=INDEX(Retention!$B$7:$BJ$7,MATCH($I$2,Retention!$B$4:$BJ$4,0))} -> 0.99021236 | C35: {=B35-INDEX(Retention!$B$7:$BJ$7,MATCH(DATE(YEAR($I$2),MONTH($I$2)-1,1),Retention!$B$4:$BJ$4,0))} -> -0.0054606185 | D35: Excel 03
A36: Quick Ratio | B36: =IFERROR(IF((B6+B7)=0,"N/A — no losses",(B4+B5)/(B6+B7)),"N/A") -> 2.6556122 | C36: =IFERROR(IF(ISNUMBER(B36),B36-INDEX('KPI Tracker'!$B$10:$F$10,MATCH(DATE(YEAR($I$2),MONTH($I$2)-1,1),'KPI Tracker'!$B$3:$F$3,0)),"—"),"—") -> -1.1905416 | D36: Excel 02
A37: S&M (actual) | B37: =B18 -> 29000 | C37: {=B37-INDEX(Actuals!$B$8:$Y$8,MATCH(DATE(YEAR($I$2),MONTH($I$2)-1,1),Actuals!$B$1:$Y$1,0))} -> -3000 | D37: From Lisa's monthly close message
A38: CAC — this month | B38: =IFERROR(IF(B39=0,"—",B37/B39),"—") -> 29000 | C38: {=IFERROR(B38-INDEX(Actuals!$B$8:$Y$8,MATCH(DATE(YEAR($I$2),MONTH($I$2)-1,1),Actuals!$B$1:$Y$1,0))/INDEX(Actuals!$B$15:$Y$15,MATCH(DATE(YEAR($I$2),MONTH($I$2)-1,1),Actuals!$B$1:$Y$1,0)),"—")} -> 13000 | D38: Excel 04 — S&M ÷ new customers acquired this month
A39: New customers acquired | B39: {=INDEX(Actuals!$B$15:$Y$15,MATCH($I$2,Actuals!$B$1:$Y$1,0))} -> 1 | C39: — | D39: Enter count of new logos signed in May
A40: CAC — Q1 to date | B40: =IFERROR(IF(('Jan 2026 A vs F '!B46/'Jan 2026 A vs F '!B47+'Feb 2026 A vs F'!B39+B39)=0,"—",('Jan 2026 A vs F '!B46+'Feb 2026 A vs F'!B37+B37)/('Jan 2026 A vs F '!B46/'Jan 2026 A vs F '!B47+'Feb 2026 A vs F'!B39+B39)),"—") -> 22500 | C40: — | D40: Cumulative S&M ÷ cumulative new customers in Q1 so far
A41: LTV | B41: — | C41: — | D41: Quarterly metric — calculated at Q1 close
A42: LTV:CAC | B42: — | C42: — | D42: Quarterly metric — calculated at Q1 close
A43: CAC Payback | B43: — | C43: — | D43: Quarterly metric — calculated at Q1 close
A44: * Monthly CAC note:
A45: Monthly CAC is noisy with small customer counts. Q1 CAC will be the definitive figure after March closes using total Q1 S&M ÷ total Q1 new customers.
A47: † Quarterly metrics note:
A48: LTV, LTV:CAC, and CAC Payback are calculated quarterly using the trailing 12-month gross churn rate. See Q1 Roll-Up (coming in 06d).
A51: Self-Check — KPIs
A53: Metric | B53: Your value | C53: Formula check
A54: ARPA | B54: =B32 -> 3557.2333 | C54: =B9/B30 -> 3557.2333
A55: GRR | B55: =B34 -> 0.98750243 | C55: {=INDEX(Retention!$B$6:$BJ$6, MATCH($I$2, Retention!$B$4:$BJ$4,0))} -> 0.98750243
A56: NRR | B56: =B35 -> 0.99021236 | C56: {=INDEX(Retention!$B$7:$BJ$7, MATCH($I$2, Retention!$B$4:$BJ$4,0))} -> 0.99021236
A57: Quick Ratio | B57: =B36 -> 2.6556122 | C57: =IFERROR(IF((B6+B7)=0,"N/A — no losses",(B4+B5)/(B6+B7)),"N/A") -> 2.6556122
A58: CAC (monthly) | B58: =B38 -> 29000 | C58: =IFERROR(IF(B39=0,"—",B37/B39),"—") -> 29000
A60: Summary:
A61: =TEXT($I$2,"mmmm yyyy")&" — Closing MRR: "&TEXT(B9,"$#,##0")&" | NRR: "&TEXT(B35,"0.0%")&" | EBITDA margin: "&TEXT(B23,"0.0%") -> May 2026 — Closing MRR: $160,076 | NRR: 99.0% | EBITDA margin: 23.8%
A62: May closed at a Closing MRR of $160,076 — $6,515 (3.9%) below the plan of $166,591. EBITDA of $38,052.85 landed $4,561 under plan, a 23.8% margin versus the 25.6% planned. The month missed on expansion and new MRR and had more contraction and churned MRR than expected; OpEx was on target.
A63: New MRR of $4,780 was $1,620 short of the $6,400 plan. We signed 1 new logos — in line with the planned count — but at $4,780 of MRR versus the ~$6,400 assumed, so the shortfall is new-logo quality. Expansion MRR of $425 was $377 below the $802 plan, and churn ran heavier than planned.
A64: The cancelled subscription this month was the Analytics Growth plan from Ontario Education Connect. This is a logo churn meaning that we lost both the revenue and the logo.
A65: OpEx ran exactly on plan. Combined with the revenue miss, that pulled EBITDA $4,560.61 below plan. The route back to plan is new-logo ARPA and expansion, not cost discipline — spend was close to target.

Sheet 2026 Forecast
A2: Build formulas referencing the Assumptions tab. No hardcoded numbers.
A3: Black font = formulas. Green font = cross-tab references.
A5: MRR WATERFALL
A6: Metric | B6: Q1 2026 | C6: Q2 2026 | D6: Q3 2026 | E6: Q4 2026 | G6: FY 2026 | I6: Formula hints
A7: Opening MRR | B7: ='Forecast Assumptions'!B6 -> 143069.5 | C7: =B12 -> 154354.15 | D7: =C12 -> 172782.38 | E7: =D12 -> 200718.47 | G7: =B7 -> 143069.5 | I7: Q1 = Opening from Assumptions. Q2+ = prior Q closing.
A8: + New MRR | B8: ='Forecast Assumptions'!B12*'Forecast Assumptions'!B13 -> 12000 | C8: ='Forecast Assumptions'!C12*'Forecast Assumptions'!C13 -> 19200 | D8: ='Forecast Assumptions'!D12*'Forecast Assumptions'!D13 -> 28800 | E8: ='Forecast Assumptions'!E12*'Forecast Assumptions'!E13 -> 30600 | G8: =B8+C8+D8+E8 -> 90600 | I8: → New customers × Avg MRR per new customer
A9: + Expansion MRR | B9: =B7*'Forecast Assumptions'!B14 -> 2146.0425 | C9: =C7*'Forecast Assumptions'!C14 -> 2315.3123 | D9: =D7*'Forecast Assumptions'!D14 -> 2591.7357 | E9: =E7*'Forecast Assumptions'!E14 -> 3010.777 | G9: =B9+C9+D9+E9 -> 10063.868 | I9: → Opening MRR × quarterly expansion rate
A10: − Churned MRR | B10: =B7*'Forecast Assumptions'!B15 -> 2861.39 | C10: =C7*'Forecast Assumptions'!C15 -> 3087.0831 | D10: =D7*'Forecast Assumptions'!D15 -> 3455.6476 | E10: =E7*'Forecast Assumptions'!E15 -> 4014.3694 | G10: =B10+C10+D10+E10 -> 13418.49 | I10: → Opening MRR × quarterly churn rate
A11: Net New MRR | B11: =B8+B9-B10 -> 11284.653 | C11: =C8+C9-C10 -> 18428.229 | D11: =D8+D9-D10 -> 27936.088 | E11: =E8+E9-E10 -> 29596.408 | G11: =G8+G9-G10 -> 87245.377 | I11: → New + Expansion − Churned
A12: Closing MRR | B12: =B7+B11 -> 154354.15 | C12: =C7+C11 -> 172782.38 | D12: =D7+D11 -> 200718.47 | E12: =E7+E11 -> 230314.88 | G12: =E12 -> 230314.88 | I12: → Opening + Net New
A13: Closing ARR | B13: =B12*12 -> 1852249.8 | C13: =C12*12 -> 2073388.6 | D13: =D12*12 -> 2408621.6 | E13: =E12*12 -> 2763778.5 | G13: =G12*12 -> 2763778.5 | I13: → Closing MRR × 12
G14: ← Opening = Q1
G15: ← Sums for flows
G16: ← Q4 closing for balances
A18: PROFIT & LOSS
A19: Metric | B19: Q1 2026 | C19: Q2 2026 | D19: Q3 2026 | E19: Q4 2026 | G19: FY 2026
A20: Revenue | B20: =B12*3 -> 463062.46 | C20: =C12*3 -> 518347.15 | D20: =D12*3 -> 602155.41 | E20: =E12*3 -> 690944.63 | G20: =B20+C20+D20+E20 -> 2274509.6 | I20: → Closing MRR × 3
A21: COGS | B21: =B20*(1-'Forecast Assumptions'!B22) -> 138918.74 | C21: =C20*(1-'Forecast Assumptions'!B22) -> 155504.14 | D21: =D20*(1-'Forecast Assumptions'!B22) -> 180646.62 | E21: =E20*(1-'Forecast Assumptions'!B22) -> 207283.39 | G21: =B21+C21+D21+E21 -> 682352.89 | I21: → Revenue × (1 − gross margin)
A22: Gross Profit | B22: =B20-B21 -> 324143.72 | C22: =C20-C21 -> 362843 | D22: =D20-D21 -> 421508.79 | E22: =E20-E21 -> 483661.24 | G22: =B22+C22+D22+E22 -> 1592156.8 | I22: → Revenue − COGS
A23: Gross Margin % | B23: =B22/B20 -> 0.7 | C23: =C22/C20 -> 0.7 | D23: =D22/D20 -> 0.7 | E23: =E22/E20 -> 0.7 | G23: =G22/G20 -> 0.7 | I23: → GP / Revenue
A25: Sales & Marketing | B25: ='Forecast Assumptions'!B26 -> 90000 | C25: ='Forecast Assumptions'!C26 -> 90000 | D25: ='Forecast Assumptions'!D26 -> 108000 | E25: ='Forecast Assumptions'!E26 -> 108000 | G25: =B25+C25+D25+E25 -> 396000 | I25: ← From Assumptions tab
A26: Research & Development | B26: ='Forecast Assumptions'!B27 -> 75000 | C26: ='Forecast Assumptions'!C27 -> 75000 | D26: ='Forecast Assumptions'!D27 -> 75000 | E26: ='Forecast Assumptions'!E27 -> 75000 | G26: =B26+C26+D26+E26 -> 300000 | I26: ← From Assumptions tab
A27: General & Administrative | B27: ='Forecast Assumptions'!B28 -> 57000 | C27: ='Forecast Assumptions'!C28 -> 57000 | D27: ='Forecast Assumptions'!D28 -> 57000 | E27: ='Forecast Assumptions'!E28 -> 57000 | G27: =B27+C27+D27+E27 -> 228000 | I27: ← From Assumptions tab
A28: Total OpEx | B28: =B25+B26+B27 -> 222000 | C28: =C25+C26+C27 -> 222000 | D28: =D25+D26+D27 -> 240000 | E28: =E25+E26+E27 -> 240000 | G28: =G25+G26+G27 -> 924000 | I28: S&M + R&D + G&A
A30: EBITDA | B30: =B22-B28 -> 102143.72 | C30: =C22-C28 -> 140843 | D30: =D22-D28 -> 181508.79 | E30: =E22-E28 -> 243661.24 | G30: =B30+C30+D30+E30 -> 668156.75 | I30: → Gross Profit − Total OpEx
A31: EBITDA Margin % | B31: =B30/B20 -> 0.22058303 | C31: =C30/C20 -> 0.27171559 | D31: =D30/D20 -> 0.3014318 | E31: =E30/E20 -> 0.35264945 | G31: =G30/G20 -> 0.29375859 | I31: → EBITDA / Revenue
A33: KEY METRICS
A34: Dec 2026 MRR | B34: =E12 -> 230314.88 | I34: → Q4 Closing MRR
A35: Dec 2026 ARR | B35: =B34*12 -> 2763778.5 | I35: → Dec MRR × 12
A36: FY Revenue | B36: =G20 -> 2274509.6 | I36: → Sum of quarterly revenue
A37: MRR Growth % | B37: =(E12-B7)/B7 -> 0.60981116 | I37: → (Closing − Opening) / Opening
A38: New Customers (FY) | B38: ='Forecast Assumptions'!B12+'Forecast Assumptions'!C12+'Forecast Assumptions'!D12+'Forecast Assumptions'!E12 -> 28 | I38: → Sum from Assumptions
A39: Blended CAC | B39: =G25/B38 -> 14142.857 | I39: Total S&M / New customers
A40: CMGR | B40: =(E12/B7)^(1/12)-1 -> 0.040474029 | I40: → (Dec MRR / Jan Opening MRR)^(1/12) − 1 [monthly rate, standard]
A43: SELF-CHECK VALUES | E43: Assumes opening MRR = $143,069.50. Our opening is $150,918.50 (Waterfall tab, Dec 2025 closing). Same model logic, different starting MRR.
A44: Check | B44: Expected | C44: Your Value | D44: Match?
A45: Q1 Closing MRR | B45: 154354.15 | C45: =B12 -> 154354.15 | D45: =IF(ROUND(C45,2)=ROUND(B45,2),"✓","✗ diff: "&TEXT(C45-B45,"$#,##0.00")) -> ✓
A46: Q2 Closing MRR | B46: 172782.38 | C46: =C12 -> 172782.38 | D46: =IF(ROUND(C46,2)=ROUND(B46,2),"✓","✗ diff: "&TEXT(C46-B46,"$#,##0.00")) -> ✓
A47: Q3 Closing MRR | B47: 200718.47 | C47: =D12 -> 200718.47 | D47: =IF(ROUND(C47,2)=ROUND(B47,2),"✓","✗ diff: "&TEXT(C47-B47,"$#,##0.00")) -> ✓
A48: Q4 Closing MRR | B48: 230314.88 | C48: =E12 -> 230314.88 | D48: =IF(ROUND(C48,2)=ROUND(B48,2),"✓","✗ diff: "&TEXT(C48-B48,"$#,##0.00")) -> ✓
A49: FY Revenue | B49: 2274509.6 | C49: =G20 -> 2274509.6 | D49: =IF(ROUND(C49,2)=ROUND(B49,2),"✓","✗ diff: "&TEXT(C49-B49,"$#,##0.00")) -> ✓
A50: FY EBITDA | B50: 668156.75 | C50: =G30 -> 668156.75 | D50: =IF(ROUND(C50,2)=ROUND(B50,2),"✓","✗ diff: "&TEXT(C50-B50,"$#,##0.00")) -> ✓
A51: EBITDA Margin | B51: 0.294 | C51: =G31 -> 0.29375859 | D51: =IF(ROUND(C51,3)=ROUND(B51,3),"✓","✗ diff: "&TEXT(C51-B51,"0.0%")) -> ✓
A52: Total New Customers | B52: 28 | C52: =B38 -> 28 | D52: =IF(C52=B52,"✓","✗ diff: "&(C52-B52)) -> ✓
A53: Blended CAC | B53: 14142.86 | C53: =B39 -> 14142.857 | D53: =IF(ROUND(C53,2)=ROUND(B53,2),"✓","✗ diff: "&TEXT(C53-B53,"$#,##0.00")) -> ✓
A54: CMGR (monthly) | B54: 0.04 | C54: =B40 -> 0.040474029 | D54: =IF(ROUND(C54,2)=ROUND(B54,2),"✓","✗ diff: "&TEXT(C54-B54,"0.00%")) -> ✓

Sheet KPI Tracker
A1: KPI Tracker
A3: Metric | B3: 46023 | C3: 46054 | D3: 46082 | E3: Q1 2026 | F3: 46113 | J3: {=_xludf.XLOOKUP('Apr 2026 A vs F '!A36,$A$4:$A$16,_xludf.XLOOKUP('Apr 2026 A vs F '!I2,$B$3:$F$3,$B$4:$F$16))} -> #NAME?
A4: Closing MRR | B4: ='Jan 2026 A vs F '!B9 -> 144779.5 | C4: ='Feb 2026 A vs F'!B9 -> 150305.5 | D4: ='Mar 2026 A vs F'!B9 -> 153685.5 | E4: ='Mar 2026 A vs F'!B75 -> 153685.5 | F4: ='Apr 2026 A vs F '!B9 -> 156830.5
A5: Active Customers | B5: ='Jan 2026 A vs F '!B39 -> 39 | C5: ='Feb 2026 A vs F'!B30 -> 41 | D5: ='Mar 2026 A vs F'!B30 -> 42 | E5: ='Mar 2026 A vs F'!B30 -> 42 | F5: ='Apr 2026 A vs F '!B30 -> 44 | J5: {=INDEX(B4:F16, MATCH('Apr 2026 A vs F '!A36,A4:A16,0), MATCH('Apr 2026 A vs F '!I32,B3:F3,0))} -> #N/A | Q5: 46054 | R5: Q1 2026
A6: ARPA | B6: ='Jan 2026 A vs F '!B41 -> 3712.2949 | C6: ='Feb 2026 A vs F'!B32 -> 3665.9878 | D6: ='Mar 2026 A vs F'!B32 -> 3659.1786 | E6: ='Mar 2026 A vs F'!B75/'Mar 2026 A vs F'!B30 -> 3659.1786 | F6: ='Apr 2026 A vs F '!B32 -> 3564.3295
A7: Gross Margin | B7: ='Jan 2026 A vs F '!B42 -> 0.7 | C7: ='Feb 2026 A vs F'!B33 -> 0.7 | D7: ='Mar 2026 A vs F'!B33 -> 0.7 | E7: ='Mar 2026 A vs F'!B82 -> 0.7 | F7: ='Apr 2026 A vs F '!B33 -> 0.7 | J7: {=INDEX(B4:F16,MATCH(A8,A4:A16,0), MATCH('Apr 2026 A vs F '!I32,B3:F3,0))} -> #N/A
A8: GRR | B8: ='Jan 2026 A vs F '!B43 -> 1 | C8: ='Feb 2026 A vs F'!B34 -> 0.99589721 | D8: ='Mar 2026 A vs F'!B34 -> 1 | E8: ='Mar 2026 A vs F'!B34 -> 1 | F8: ='Apr 2026 A vs F '!B34 -> 0.99280999
A9: NRR | B9: ='Jan 2026 A vs F '!B44 -> 1 | C9: ='Feb 2026 A vs F'!B35 -> 0.98950128 | D9: ='Mar 2026 A vs F'!B35 -> 1.0025282 | E9: ='Mar 2026 A vs F'!B35 -> 1.0025282 | F9: ='Apr 2026 A vs F '!B35 -> 0.99567298 | J9: {=_xludf.XLOOKUP(A10,A4:A16,_xludf.XLOOKUP('Apr 2026 A vs F '!I32,B3:F3,B4:F16))} -> #NAME?
A10: Quick Ratio | C10: ='Feb 2026 A vs F'!B36 -> 10.30303 | D10: ='Mar 2026 A vs F'!B36 -> N/A — no losses | E10: — | F10: ='Apr 2026 A vs F '!B36 -> 3.8461538
A11: S&M (actual) | B11: ='Jan 2026 A vs F '!B46 -> 30000 | C11: ='Feb 2026 A vs F'!B37 -> 31000 | D11: ='Mar 2026 A vs F'!B37 -> 29000 | E11: ='Mar 2026 A vs F'!B83 -> 90000 | F11: ='Apr 2026 A vs F '!B37 -> 32000 | J11: {=INDEX(B4:F16,MATCH(A4,A4:A16,0), MATCH('Apr 2026 A vs F '!I32,B3:F3,0))} -> #N/A
A12: CAC — monthly | B12: ='Jan 2026 A vs F '!B47 -> 30000 | C12: ='Feb 2026 A vs F'!B38 -> 15500 | D12: ='Mar 2026 A vs F'!B38 -> 14500 | E12: ='Mar 2026 A vs F'!B92 -> 18000 | F12: ='Apr 2026 A vs F '!B38 -> 16000 | J12: {=INDEX(B4:F16,MATCH(A6,A4:A16,0), MATCH(R5,B3:F3,0))} -> 3659.1786
A13: CAC — trailing Q | B13: 0 | E13: ='Mar 2026 A vs F'!B92 -> 18000 | M13: {=INDEX(B4:F16,MATCH(A5,A3:A16,0), MATCH(Q5,B3:F3,0))} -> 3665.9878
A14: LTV | B14: 0 | E14: ='Mar 2026 A vs F'!B93 -> 51411.587 | J14: {=INDEX(B4:F16,MATCH(A16,A4:A16,0), MATCH(R5,B3:F3,0))} -> 7.0273383
A15: LTV:CAC | B15: 0 | E15: ='Mar 2026 A vs F'!B94 -> 2.8561993
A16: CAC Payback | B16: 0 | E16: ='Mar 2026 A vs F'!B95 -> 7.0273383
A18: LTV, LTV:CAC, and CAC Payback appear in the Q1 column only. Monthly figures are too sensitive to single-month churn swings to be meaningful.

Sheet Waterfall Data
A1: Month | B1: Movement | C1: Actual | D1: Forecast | E1: Variance
A2: 46023 | B2: Opening MRR | C2: ='Jan 2026 A vs F '!B3 -> 143069.5 | D2: ='Jan 2026 A vs F '!C3 -> 143069.5 | E2: ='Jan 2026 A vs F '!D3 -> 0
A3: 46023 | B3: New MRR | C3: ='Jan 2026 A vs F '!B4 -> 1710 | D3: ='Jan 2026 A vs F '!C4 -> 4000 | E3: ='Jan 2026 A vs F '!D4 -> -2290
A4: 46023 | B4: Expansion MRR | C4: ='Jan 2026 A vs F '!B5 -> 0 | D4: ='Jan 2026 A vs F '!C5 -> 715.3475 | E4: ='Jan 2026 A vs F '!D5 -> -715.3475
A5: 46023 | B5: Contraction MRR | C5: ='Jan 2026 A vs F '!B6 -> 0 | D5: ='Jan 2026 A vs F '!C6 -> 0 | E5: =C5-D5 -> 0
A6: 46023 | B6: Churned MRR | C6: ='Jan 2026 A vs F '!B7 -> 0 | D6: ='Jan 2026 A vs F '!C7 -> 953.79667 | E6: =D6-C6 -> 953.79667
A7: 46023 | B7: Net New MRR | C7: ='Jan 2026 A vs F '!B8 -> 1710 | D7: ='Jan 2026 A vs F '!C8 -> 3761.5508 | E7: ='Jan 2026 A vs F '!D8 -> -2051.5508
A8: 46023 | B8: Closing MRR | C8: ='Jan 2026 A vs F '!B9 -> 144779.5 | D8: ='Jan 2026 A vs F '!C9 -> 146831.05 | E8: ='Jan 2026 A vs F '!D9 -> -2051.5508
A9: =TEXT(DATE(2026,2,1),"mmm-yy") -> Feb-26 | B9: Opening MRR | C9: ='Feb 2026 A vs F'!B3 -> 144779.5 | D9: ='Feb 2026 A vs F'!C3 -> 146831.05 | E9: =C9-D9 -> -2051.55
A10: =TEXT(DATE(2026,2,1),"mmm-yy") -> Feb-26 | B10: New MRR | C10: ='Feb 2026 A vs F'!B4 -> 6120 | D10: ='Feb 2026 A vs F'!C4 -> 4000 | E10: =C10-D10 -> 2120
A11: =TEXT(DATE(2026,2,1),"mmm-yy") -> Feb-26 | B11: Expansion MRR | C11: ='Feb 2026 A vs F'!B5 -> 0 | D11: ='Feb 2026 A vs F'!C5 -> 715.3475 | E11: =C11-D11 -> -715.3475
A12: =TEXT(DATE(2026,2,1),"mmm-yy") -> Feb-26 | B12: Contraction MRR | C12: ='Feb 2026 A vs F'!B6 -> 0 | D12: ='Feb 2026 A vs F'!C6 -> 0 | E12: =D12-C12 -> 0
A13: =TEXT(DATE(2026,2,1),"mmm-yy") -> Feb-26 | B13: Churned MRR | C13: ='Feb 2026 A vs F'!B7 -> 594 | D13: ='Feb 2026 A vs F'!C7 -> 953.79667 | E13: =D13-C13 -> 359.79667
A14: =TEXT(DATE(2026,2,1),"mmm-yy") -> Feb-26 | B14: Net New MRR | C14: ='Feb 2026 A vs F'!B8 -> 5526 | D14: ='Feb 2026 A vs F'!C8 -> 3761.5508 | E14: =C14-D14 -> 1764.4492
A15: =TEXT(DATE(2026,2,1),"mmm-yy") -> Feb-26 | B15: Closing MRR | C15: ='Feb 2026 A vs F'!B9 -> 150305.5 | D15: ='Feb 2026 A vs F'!C9 -> 150592.6 | E15: =C15-D15 -> -287.10083
A16: =TEXT(DATE(2026,3,1),"mmm-yy") -> Mar-26 | B16: Opening MRR | C16: ='Mar 2026 A vs F'!B3 -> 150305.5 | D16: ='Mar 2026 A vs F'!C3 -> 150592.6 | E16: ='Mar 2026 A vs F'!D3 -> -287.1
A17: =TEXT(DATE(2026,3,1),"mmm-yy") -> Mar-26 | B17: New MRR | C17: ='Mar 2026 A vs F'!B4 -> 3000 | D17: ='Mar 2026 A vs F'!C4 -> 4000 | E17: ='Mar 2026 A vs F'!D4 -> -1000
A18: =TEXT(DATE(2026,3,1),"mmm-yy") -> Mar-26 | B18: Expansion MRR | C18: ='Mar 2026 A vs F'!B5 -> 380 | D18: ='Mar 2026 A vs F'!C5 -> 715.3475 | E18: ='Mar 2026 A vs F'!D5 -> -335.3475
A19: =TEXT(DATE(2026,3,1),"mmm-yy") -> Mar-26 | B19: Contraction MRR | C19: ='Mar 2026 A vs F'!B6 -> 0 | D19: ='Mar 2026 A vs F'!C6 -> 0 | E19: =D19-C19 -> 0
A20: =TEXT(DATE(2026,3,1),"mmm-yy") -> Mar-26 | B20: Churned MRR | C20: ='Mar 2026 A vs F'!B7 -> 0 | D20: ='Mar 2026 A vs F'!C7 -> 953.79667 | E20: ='Mar 2026 A vs F'!D7 -> 953.79667
A21: =TEXT(DATE(2026,3,1),"mmm-yy") -> Mar-26 | B21: Net New MRR | C21: ='Mar 2026 A vs F'!B8 -> 3380 | D21: ='Mar 2026 A vs F'!C8 -> 3761.5508 | E21: ='Mar 2026 A vs F'!D8 -> -381.55083
A22: =TEXT(DATE(2026,3,1),"mmm-yy") -> Mar-26 | B22: Closing MRR | C22: ='Mar 2026 A vs F'!B9 -> 153685.5 | D22: ='Mar 2026 A vs F'!C9 -> 154354.15 | E22: ='Mar 2026 A vs F'!D9 -> -668.65083
A23: =TEXT(DATE(2026,4,1),"mmm-yy") -> Apr-26 | B23: Opening MRR | C23: ='Apr 2026 A vs F '!B3 -> 153685.5 | D23: ='Apr 2026 A vs F '!C3 -> 154325.79 | E23: ='Apr 2026 A vs F '!D3 -> -640.29393
A24: =TEXT(DATE(2026,4,1),"mmm-yy") -> Apr-26 | B24: New MRR | C24: ='Apr 2026 A vs F '!B4 -> 3810 | D24: ='Apr 2026 A vs F '!C4 -> 6400 | E24: ='Apr 2026 A vs F '!D4 -> -2590
A25: =TEXT(DATE(2026,4,1),"mmm-yy") -> Apr-26 | B25: Expansion MRR | C25: ='Apr 2026 A vs F '!B5 -> 440 | D25: ='Apr 2026 A vs F '!C5 -> 771.62897 | E25: ='Apr 2026 A vs F '!D5 -> -331.62897
A26: =TEXT(DATE(2026,4,1),"mmm-yy") -> Apr-26 | B26: Contraction MRR | C26: ='Apr 2026 A vs F '!B6 -> 0 | D26: ='Apr 2026 A vs F '!C6 -> 0 | E26: ='Apr 2026 A vs F '!D6 -> 0
A27: =TEXT(DATE(2026,4,1),"mmm-yy") -> Apr-26 | B27: Churned MRR | C27: ='Apr 2026 A vs F '!B7 -> 1105 | D27: ='Apr 2026 A vs F '!C7 -> 1033.9828 | E27: ='Apr 2026 A vs F '!D7 -> -71.017181
A28: =TEXT(DATE(2026,4,1),"mmm-yy") -> Apr-26 | B28: Net New MRR | C28: ='Apr 2026 A vs F '!B8 -> 3145 | D28: ='Apr 2026 A vs F '!C8 -> 6137.6462 | E28: ='Apr 2026 A vs F '!D8 -> -2992.6462
A29: =TEXT(DATE(2026,4,1),"mmm-yy") -> Apr-26 | B29: Closing MRR | C29: ='Apr 2026 A vs F '!B9 -> 156830.5 | D29: ='Apr 2026 A vs F '!C9 -> 160463.44 | E29: ='Apr 2026 A vs F '!D9 -> -3632.9401

Sheet Engine
A1: event_id | B1: subscription_id | C1: customer_id | D1: company_name | E1: region | F1: month | G1: event_date | H1: event_type | I1: old_value | J1: new_value | K1: field_changed | L1: reason | M1: plan_name | N1: billing_cycle | O1: seats | P1: price_per_seat | Q1: discount_percent | R1: movement | S1: mrr_delta | T1: is_new_logo | U1: is_logo_churn | V1: is_logo_reactivation
A2: EVT001 | B2: SUB001 | C2: CUST001 | D2: TechVision Solutions | E2: Eastern Canada | F2: 45292 | G2: 45299 | H2: created | M2: Analytics Growth | N2: Monthly | O2: 20 | P2: 95 | Q2: 0 | R2: {=_xlfn.IFS(H2="created", "New", H2="cancelled", "Churned", AND(H2="seats_change", J2 > I2), "Expansion", AND(H2="seats_change", J2 < I2), "Contraction", AND(H2="price_change", J2 > I2), "Expansion", AND(H2="price_change", J2 < I2), "Contraction", H2="plan_upgrade", "Expansion", H2="plan_downgrade", "Contraction", H2="discount_added", "Contraction")} -> New | S2: {=IF(N2="Monthly",_xlfn.IFS(H2="created",O2*P2*(1-Q2/100),H2="cancelled",-(O2*P2*(1-Q2/100)),H2="seats_change",(J2-I2)*P2*(1-Q2/100),H2="price_change",(J2-I2)*O2*(1-Q2/100),H2="discount_added",-(O2*P2*(J2-I2)/100),H2="plan_upgrade",O2*(_xlfn.XLOOKUP(J2,$M:$M,$P:$P)-_xlfn.XLOOKUP(I2,$M:$M,$P:$P))*(1-Q2/100),H2="plan_downgrade",O2*(_xlfn.XLOOKUP(J2,$M:$M,$P:$P)-_xlfn.XLOOKUP(I2,$M:$M,$P:$P))*(1-Q2/100)),_xlfn.IFS(H2="created",O2*P2*(1-Q2/100)/12,H2="cancelled",-(O2*P2*(1-Q2/100))/12,H2="seats_change",(J2-I2)*P2*(1-Q2/100)/12,H2="price_change",(J2-I2)*O2*(1-Q2/100)/12,H2="plan_upgrade",(O2*(_xlfn.XLOOKUP(J2,$M:$M,$P:$P)-_xlfn.XLOOKUP(I2,$M:$M,$P:$P))*(1-Q2/100))/12,H2="plan_downgrade",(O2*(_xlfn.XLOOKUP(J2,$M:$M,$P:$P)-_xlfn.XLOOKUP(I2,$M:$M,$P:$P))*(1-Q2/100))/12,H2="discount_added",-(O2*P2*(J2-I2)/100)/12))} -> 1900 | T2: =IF(H2<>"created",0,IF(COUNTIFS($C$1:C1,$C2,$H$1:H1,"created")=0,1,0)) -> 1 | U2: =IF(H2<>"cancelled",0,IF(COUNTIFS($C$2:$C$1002,$C2,$H$2:$H$1002,"created",$F$2:$F$1002,"<="&F2)-COUNTIFS($C$2:$C$1002,$C2,$H$2:$H$1002,"cancelled",$F$2:$F$1002,"<="&F2)=0,1,0)) -> 0 | V2: =IF(AND(H2="created",T2=0,COUNTIFS($C$2:$C$1002,$C2,$H$2:$H$1002,"cancelled",$F$2:$F$1002,"<"&F2)>0,COUNTIFS($C$2:$C$1002,$C2,$H$2:$H$1002,"created",$F$2:$F$1002,"<"&F2)-COUNTIFS($C$2:$C$1002,$C2,$H$2:$H$1002,"cancelled",$F$2:$F$1002,"<"&F2)=0),1,0) -> 0
A3: EVT002 | B3: SUB002 | C3: CUST002 | D3: Pacific Analytics Inc | E3: Western Canada | F3: 45292 | G3: 45313 | H3: created | M3: Platform Suite | N3: Annual | O3: 26 | P3: 1800 | Q3: 0 | R3: {=_xlfn.IFS(H3="created", "New", H3="cancelled", "Churned", AND(H3="seats_change", J3 > I3), "Expansion", AND(H3="seats_change", J3 < I3), "Contraction", AND(H3="price_change", J3 > I3), "Expansion", AND(H3="price_change", J3 < I3), "Contraction", H3="plan_upgrade", "Expansion", H3="plan_downgrade", "Contraction", H3="discount_added", "Contraction")} -> New | S3: {=IF(N3="Monthly",_xlfn.IFS(H3="created",O3*P3*(1-Q3/100),H3="cancelled",-(O3*P3*(1-Q3/100)),H3="seats_change",(J3-I3)*P3*(1-Q3/100),H3="price_change",(J3-I3)*O3*(1-Q3/100),H3="discount_added",-(O3*P3*(J3-I3)/100),H3="plan_upgrade",O3*(_xlfn.XLOOKUP(J3,$M:$M,$P:$P)-_xlfn.XLOOKUP(I3,$M:$M,$P:$P))*(1-Q3/100),H3="plan_downgrade",O3*(_xlfn.XLOOKUP(J3,$M:$M,$P:$P)-_xlfn.XLOOKUP(I3,$M:$M,$P:$P))*(1-Q3/100)),_xlfn.IFS(H3="created",O3*P3*(1-Q3/100)/12,H3="cancelled",-(O3*P3*(1-Q3/100))/12,H3="seats_change",(J3-I3)*P3*(1-Q3/100)/12,H3="price_change",(J3-I3)*O3*(1-Q3/100)/12,H3="plan_upgrade",(O3*(_xlfn.XLOOKUP(J3,$M:$M,$P:$P)-_xlfn.XLOOKUP(I3,$M:$M,$P:$P))*(1-Q3/100))/12,H3="plan_downgrade",(O3*(_xlfn.XLOOKUP(J3,$M:$M,$P:$P)-_xlfn.XLOOKUP(I3,$M:$M,$P:$P))*(1-Q3/100))/12,H3="discount_added",-(O3*P3*(J3-I3)/100)/12))} -> 3900 | T3: =IF(H3<>"created",0,IF(COUNTIFS($C$1:C2,$C3,$H$1:H2,"created")=0,1,0)) -> 1 | U3: =IF(H3<>"cancelled",0,IF(COUNTIFS($C$2:$C$1002,$C3,$H$2:$H$1002,"created",$F$2:$F$1002,"<="&F3)-COUNTIFS($C$2:$C$1002,$C3,$H$2:$H$1002,"cancelled",$F$2:$F$1002,"<="&F3)=0,1,0)) -> 0 | V3: =IF(AND(H3="created",T3=0,COUNTIFS($C$2:$C$1002,$C3,$H$2:$H$1002,"cancelled",$F$2:$F$1002,"<"&F3)>0,COUNTIFS($C$2:$C$1002,$C3,$H$2:$H$1002,"created",$F$2:$F$1002,"<"&F3)-COUNTIFS($C$2:$C$1002,$C3,$H$2:$H$1002,"cancelled",$F$2:$F$1002,"<"&F3)=0),1,0) -> 0
A4: EVT003 | B4: SUB003 | C4: CUST003 | D4: Maple Healthcare Systems | E4: Eastern Canada | F4: 45323 | G4: 45327 | H4: created | M4: Marketing Pro | N4: Monthly | O4: 23 | P4: 85 | Q4: 0 | R4: {=_xlfn.IFS(H4="created", "New", H4="cancelled", "Churned", AND(H4="seats_change", J4 > I4), "Expansion", AND(H4="seats_change", J4 < I4), "Contraction", AND(H4="price_change", J4 > I4), "Expansion", AND(H4="price_change", J4 < I4), "Contraction", H4="plan_upgrade", "Expansion", H4="plan_downgrade", "Contraction", H4="discount_added", "Contraction")} -> New | S4: {=IF(N4="Monthly",_xlfn.IFS(H4="created",O4*P4*(1-Q4/100),H4="cancelled",-(O4*P4*(1-Q4/100)),H4="seats_change",(J4-I4)*P4*(1-Q4/100),H4="price_change",(J4-I4)*O4*(1-Q4/100),H4="discount_added",-(O4*P4*(J4-I4)/100),H4="plan_upgrade",O4*(_xlfn.XLOOKUP(J4,$M:$M,$P:$P)-_xlfn.XLOOKUP(I4,$M:$M,$P:$P))*(1-Q4/100),H4="plan_downgrade",O4*(_xlfn.XLOOKUP(J4,$M:$M,$P:$P)-_xlfn.XLOOKUP(I4,$M:$M,$P:$P))*(1-Q4/100)),_xlfn.IFS(H4="created",O4*P4*(1-Q4/100)/12,H4="cancelled",-(O4*P4*(1-Q4/100))/12,H4="seats_change",(J4-I4)*P4*(1-Q4/100)/12,H4="price_change",(J4-I4)*O4*(1-Q4/100)/12,H4="plan_upgrade",(O4*(_xlfn.XLOOKUP(J4,$M:$M,$P:$P)-_xlfn.XLOOKUP(I4,$M:$M,$P:$P))*(1-Q4/100))/12,H4="plan_downgrade",(O4*(_xlfn.XLOOKUP(J4,$M:$M,$P:$P)-_xlfn.XLOOKUP(I4,$M:$M,$P:$P))*(1-Q4/100))/12,H4="discount_added",-(O4*P4*(J4-I4)/100)/12))} -> 1955 | T4: =IF(H4<>"created",0,IF(COUNTIFS($C$1:C3,$C4,$H$1:H3,"created")=0,1,0)) -> 1 | U4: =IF(H4<>"cancelled",0,IF(COUNTIFS($C$2:$C$1002,$C4,$H$2:$H$1002,"created",$F$2:$F$1002,"<="&F4)-COUNTIFS($C$2:$C$1002,$C4,$H$2:$H$1002,"cancelled",$F$2:$F$1002,"<="&F4)=0,1,0)) -> 0 | V4: =IF(AND(H4="created",T4=0,COUNTIFS($C$2:$C$1002,$C4,$H$2:$H$1002,"cancelled",$F$2:$F$1002,"<"&F4)>0,COUNTIFS($C$2:$C$1002,$C4,$H$2:$H$1002,"created",$F$2:$F$1002,"<"&F4)-COUNTIFS($C$2:$C$1002,$C4,$H$2:$H$1002,"cancelled",$F$2:$F$1002,"<"&F4)=0),1,0) -> 0
A5: EVT004 | B5: SUB004 | C5: CUST004 | D5: Prairie Commerce Group | E5: Western Canada | F5: 45323 | G5: 45341 | H5: created | M5: Sales Hub | N5: Monthly | O5: 18 | P5: 110 | Q5: 0 | R5: {=_xlfn.IFS(H5="created", "New", H5="cancelled", "Churned", AND(H5="seats_change", J5 > I5), "Expansion", AND(H5="seats_change", J5 < I5), "Contraction", AND(H5="price_change", J5 > I5), "Expansion", AND(H5="price_change", J5 < I5), "Contraction", H5="plan_upgrade", "Expansion", H5="plan_downgrade", "Contraction", H5="discount_added", "Contraction")} -> New | S5: {=IF(N5="Monthly",_xlfn.IFS(H5="created",O5*P5*(1-Q5/100),H5="cancelled",-(O5*P5*(1-Q5/100)),H5="seats_change",(J5-I5)*P5*(1-Q5/100),H5="price_change",(J5-I5)*O5*(1-Q5/100),H5="discount_added",-(O5*P5*(J5-I5)/100),H5="plan_upgrade",O5*(_xlfn.XLOOKUP(J5,$M:$M,$P:$P)-_xlfn.XLOOKUP(I5,$M:$M,$P:$P))*(1-Q5/100),H5="plan_downgrade",O5*(_xlfn.XLOOKUP(J5,$M:$M,$P:$P)-_xlfn.XLOOKUP(I5,$M:$M,$P:$P))*(1-Q5/100)),_xlfn.IFS(H5="created",O5*P5*(1-Q5/100)/12,H5="cancelled",-(O5*P5*(1-Q5/100))/12,H5="seats_change",(J5-I5)*P5*(1-Q5/100)/12,H5="price_change",(J5-I5)*O5*(1-Q5/100)/12,H5="plan_upgrade",(O5*(_xlfn.XLOOKUP(J5,$M:$M,$P:$P)-_xlfn.XLOOKUP(I5,$M:$M,$P:$P))*(1-Q5/100))/12,H5="plan_downgrade",(O5*(_xlfn.XLOOKUP(J5,$M:$M,$P:$P)-_xlfn.XLOOKUP(I5,$M:$M,$P:$P))*(1-Q5/100))/12,H5="discount_added",-(O5*P5*(J5-I5)/100)/12))} -> 1980 | T5: =IF(H5<>"created",0,IF(COUNTIFS($C$1:C4,$C5,$H$1:H4,"created")=0,1,0)) -> 1 | U5: =IF(H5<>"cancelled",0,IF(COUNTIFS($C$2:$C$1002,$C5,$H$2:$H$1002,"created",$F$2:$F$1002,"<="&F5)-COUNTIFS($C$2:$C$1002,$C5,$H$2:$H$1002,"cancelled",$F$2:$F$1002,"<="&F5)=0,1,0)) -> 0 | V5: =IF(AND(H5="created",T5=0,COUNTIFS($C$2:$C$1002,$C5,$H$2:$H$1002,"cancelled",$F$2:$F$1002,"<"&F5)>0,COUNTIFS($C$2:$C$1002,$C5,$H$2:$H$1002,"created",$F$2:$F$1002,"<"&F5)-COUNTIFS($C$2:$C$1002,$C5,$H$2:$H$1002,"cancelled",$F$2:$F$1002,"<"&F5)=0),1,0) -> 0
A6: EVT005 | B6: SUB055 | C6: CUST004 | D6: Prairie Commerce Group | E6: Western Canada | F6: 45323 | G6: 45341 | H6: created | M6: Analytics Enterprise | N6: Monthly | O6: 26 | P6: 180 | Q6: 0 | R6: {=_xlfn.IFS(H6="created", "New", H6="cancelled", "Churned", AND(H6="seats_change", J6 > I6), "Expansion", AND(H6="seats_change", J6 < I6), "Contraction", AND(H6="price_change", J6 > I6), "Expansion", AND(H6="price_change", J6 < I6), "Contraction", H6="plan_upgrade", "Expansion", H6="plan_downgrade", "Contraction", H6="discount_added", "Contraction")} -> New | S6: {=IF(N6="Monthly",_xlfn.IFS(H6="created",O6*P6*(1-Q6/100),H6="cancelled",-(O6*P6*(1-Q6/100)),H6="seats_change",(J6-I6)*P6*(1-Q6/100),H6="price_change",(J6-I6)*O6*(1-Q6/100),H6="discount_added",-(O6*P6*(J6-I6)/100),H6="plan_upgrade",O6*(_xlfn.XLOOKUP(J6,$M:$M,$P:$P)-_xlfn.XLOOKUP(I6,$M:$M,$P:$P))*(1-Q6/100),H6="plan_downgrade",O6*(_xlfn.XLOOKUP(J6,$M:$M,$P:$P)-_xlfn.XLOOKUP(I6,$M:$M,$P:$P))*(1-Q6/100)),_xlfn.IFS(H6="created",O6*P6*(1-Q6/100)/12,H6="cancelled",-(O6*P6*(1-Q6/100))/12,H6="seats_change",(J6-I6)*P6*(1-Q6/100)/12,H6="price_change",(J6-I6)*O6*(1-Q6/100)/12,H6="plan_upgrade",(O6*(_xlfn.XLOOKUP(J6,$M:$M,$P:$P)-_xlfn.XLOOKUP(I6,$M:$M,$P:$P))*(1-Q6/100))/12,H6="plan_downgrade",(O6*(_xlfn.XLOOKUP(J6,$M:$M,$P:$P)-_xlfn.XLOOKUP(I6,$M:$M,$P:$P))*(1-Q6/100))/12,H6="discount_added",-(O6*P6*(J6-I6)/100)/12))} -> 4680 | T6: =IF(H6<>"created",0,IF(COUNTIFS($C$1:C5,$C6,$H$1:H5,"created")=0,1,0)) -> 0 | U6: =IF(H6<>"cancelled",0,IF(COUNTIFS($C$2:$C$1002,$C6,$H$2:$H$1002,"created",$F$2:$F$1002,"<="&F6)-COUNTIFS($C$2:$C$1002,$C6,$H$2:$H$1002,"cancelled",$F$2:$F$1002,"<="&F6)=0,1,0)) -> 0 | V6: =IF(AND(H6="created",T6=0,COUNTIFS($C$2:$C$1002,$C6,$H$2:$H$1002,"cancelled",$F$2:$F$1002,"<"&F6)>0,COUNTIFS($C$2:$C$1002,$C6,$H$2:$H$1002,"created",$F$2:$F$1002,"<"&F6)-COUNTIFS($C$2:$C$1002,$C6,$H$2:$H$1002,"cancelled",$F$2:$F$1002,"<"&F6)=0),1,0) -> 0
A7: EVT006 | B7: SUB005 | C7: CUST005 | D7: Atlantic Media Corp | E7: Eastern Canada | F7: 45352 | G7: 45355 | H7: created | M7: Analytics Starter | N7: Monthly | O7: 11 | P7: 45 | Q7: 0 | R7: {=_xlfn.IFS(H7="created", "New", H7="cancelled", "Churned", AND(H7="seats_change", J7 > I7), "Expansion", AND(H7="seats_change", J7 < I7), "Contraction", AND(H7="price_change", J7 > I7), "Expansion", AND(H7="price_change", J7 < I7), "Contraction", H7="plan_upgrade", "Expansion", H7="plan_downgrade", "Contraction", H7="discount_added", "Contraction")} -> New | S7: {=IF(N7="Monthly",_xlfn.IFS(H7="created",O7*P7*(1-Q7/100),H7="cancelled",-(O7*P7*(1-Q7/100)),H7="seats_change",(J7-I7)*P7*(1-Q7/100),H7="price_change",(J7-I7)*O7*(1-Q7/100),H7="discount_added",-(O7*P7*(J7-I7)/100),H7="plan_upgrade",O7*(_xlfn.XLOOKUP(J7,$M:$M,$P:$P)-_xlfn.XLOOKUP(I7,$M:$M,$P:$P))*(1-Q7/100),H7="plan_downgrade",O7*(_xlfn.XLOOKUP(J7,$M:$M,$P:$P)-_xlfn.XLOOKUP(I7,$M:$M,$P:$P))*(1-Q7/100)),_xlfn.IFS(H7="created",O7*P7*(1-Q7/100)/12,H7="cancelled",-(O7*P7*(1-Q7/100))/12,H7="seats_change",(J7-I7)*P7*(1-Q7/100)/12,H7="price_change",(J7-I7)*O7*(1-Q7/100)/12,H7="plan_upgrade",(O7*(_xlfn.XLOOKUP(J7,$M:$M,$P:$P)-_xlfn.XLOOKUP(I7,$M:$M,$P:$P))*(1-Q7/100))/12,H7="plan_downgrade",(O7*(_xlfn.XLOOKUP(J7,$M:$M,$P:$P)-_xlfn.XLOOKUP(I7,$M:$M,$P:$P))*(1-Q7/100))/12,H7="discount_added",-(O7*P7*(J7-I7)/100)/12))} -> 495 | T7: =IF(H7<>"created",0,IF(COUNTIFS($C$1:C6,$C7,$H$1:H6,"created")=0,1,0)) -> 1 | U7: =IF(H7<>"cancelled",0,IF(COUNTIFS($C$2:$C$1002,$C7,$H$2:$H$1002,"created",$F$2:$F$1002,"<="&F7)-COUNTIFS($C$2:$C$1002,$C7,$H$2:$H$1002,"cancelled",$F$2:$F$1002,"<="&F7)=0,1,0)) -> 0 | V7: =IF(AND(H7="created",T7=0,COUNTIFS($C$2:$C$1002,$C7,$H$2:$H$1002,"cancelled",$F$2:$F$1002,"<"&F7)>0,COUNTIFS($C$2:$C$1002,$C7,$H$2:$H$1002,"created",$F$2:$F$1002,"<"&F7)-COUNTIFS($C$2:$C$1002,$C7,$H$2:$H$1002,"cancelled",$F$2:$F$1002,"<"&F7)=0),1,0) -> 0
A8: EVT007 | B8: SUB006 | C8: CUST006 | D8: Northern Retail Solutions | E8: Western Canada | F8: 45352 | G8: 45369 | H8: created | M8: Analytics Enterprise | N8: Annual | O8: 31 | P8: 2160 | Q8: 0 | R8: {=_xlfn.IFS(H8="created", "New", H8="cancelled", "Churned", AND(H8="seats_change", J8 > I8), "Expansion", AND(H8="seats_change", J8 < I8), "Contraction", AND(H8="price_change", J8 > I8), "Expansion", AND(H8="price_change", J8 < I8), "Contraction", H8="plan_upgrade", "Expansion", H8="plan_downgrade", "Contraction", H8="discount_added", "Contraction")} -> New | S8: {=IF(N8="Monthly",_xlfn.IFS(H8="created",O8*P8*(1-Q8/100),H8="cancelled",-(O8*P8*(1-Q8/100)),H8="seats_change",(J8-I8)*P8*(1-Q8/100),H8="price_change",(J8-I8)*O8*(1-Q8/100),H8="discount_added",-(O8*P8*(J8-I8)/100),H8="plan_upgrade",O8*(_xlfn.XLOOKUP(J8,$M:$M,$P:$P)-_xlfn.XLOOKUP(I8,$M:$M,$P:$P))*(1-Q8/100),H8="plan_downgrade",O8*(_xlfn.XLOOKUP(J8,$M:$M,$P:$P)-_xlfn.XLOOKUP(I8,$M:$M,$P:$P))*(1-Q8/100)),_xlfn.IFS(H8="created",O8*P8*(1-Q8/100)/12,H8="cancelled",-(O8*P8*(1-Q8/100))/12,H8="seats_change",(J8-I8)*P8*(1-Q8/100)/12,H8="price_change",(J8-I8)*O8*(1-Q8/100)/12,H8="plan_upgrade",(O8*(_xlfn.XLOOKUP(J8,$M:$M,$P:$P)-_xlfn.XLOOKUP(I8,$M:$M,$P:$P))*(1-Q8/100))/12,H8="plan_downgrade",(O8*(_xlfn.XLOOKUP(J8,$M:$M,$P:$P)-_xlfn.XLOOKUP(I8,$M:$M,$P:$P))*(1-Q8/100))/12,H8="discount_added",-(O8*P8*(J8-I8)/100)/12))} -> 5580 | T8: =IF(H8<>"created",0,IF(COUNTIFS($C$1:C7,$C8,$H$1:H7,"created")=0,1,0)) -> 1 | U8: =IF(H8<>"cancelled",0,IF(COUNTIFS($C$2:$C$1002,$C8,$H$2:$H$1002,"created",$F$2:$F$1002,"<="&F8)-COUNTIFS($C$2:$C$1002,$C8,$H$2:$H$1002,"cancelled",$F$2:$F$1002,"<="&F8)=0,1,0)) -> 0 | V8: =IF(AND(H8="created",T8=0,COUNTIFS($C$2:$C$1002,$C8,$H$2:$H$1002,"cancelled",$F$2:$F$1002,"<"&F8)>0,COUNTIFS($C$2:$C$1002,$C8,$H$2:$H$1002,"created",$F$2:$F$1002,"<"&F8)-COUNTIFS($C$2:$C$1002,$C8,$H$2:$H$1002,"cancelled",$F$2:$F$1002,"<"&F8)=0),1,0) -> 0
A9: EVT008 | B9: SUB007 | C9: CUST007 | D9: Ontario Manufacturing Tech | E9: Eastern Canada | F9: 45383 | G9: 45383 | H9: created | M9: Marketing Pro | N9: Monthly | O9: 16 | P9: 85 | Q9: 0 | R9: {=_xlfn.IFS(H9="created", "New", H9="cancelled", "Churned", AND(H9="seats_change", J9 > I9), "Expansion", AND(H9="seats_change", J9 < I9), "Contraction", AND(H9="price_change", J9 > I9), "Expansion", AND(H9="price_change", J9 < I9), "Contraction", H9="plan_upgrade", "Expansion", H9="plan_downgrade", "Contraction", H9="discount_added", "Contraction")} -> New | S9: {=IF(N9="Monthly",_xlfn.IFS(H9="created",O9*P9*(1-Q9/100),H9="cancelled",-(O9*P9*(1-Q9/100)),H9="seats_change",(J9-I9)*P9*(1-Q9/100),H9="price_change",(J9-I9)*O9*(1-Q9/100),H9="discount_added",-(O9*P9*(J9-I9)/100),H9="plan_upgrade",O9*(_xlfn.XLOOKUP(J9,$M:$M,$P:$P)-_xlfn.XLOOKUP(I9,$M:$M,$P:$P))*(1-Q9/100),H9="plan_downgrade",O9*(_xlfn.XLOOKUP(J9,$M:$M,$P:$P)-_xlfn.XLOOKUP(I9,$M:$M,$P:$P))*(1-Q9/100)),_xlfn.IFS(H9="created",O9*P9*(1-Q9/100)/12,H9="cancelled",-(O9*P9*(1-Q9/100))/12,H9="seats_change",(J9-I9)*P9*(1-Q9/100)/12,H9="price_change",(J9-I9)*O9*(1-Q9/100)/12,H9="plan_upgrade",(O9*(_xlfn.XLOOKUP(J9,$M:$M,$P:$P)-_xlfn.XLOOKUP(I9,$M:$M,$P:$P))*(1-Q9/100))/12,H9="plan_downgrade",(O9*(_xlfn.XLOOKUP(J9,$M:$M,$P:$P)-_xlfn.XLOOKUP(I9,$M:$M,$P:$P))*(1-Q9/100))/12,H9="discount_added",-(O9*P9*(J9-I9)/100)/12))} -> 1360 | T9: =IF(H9<>"created",0,IF(COUNTIFS($C$1:C8,$C9,$H$1:H8,"created")=0,1,0)) -> 1 | U9: =IF(H9<>"cancelled",0,IF(COUNTIFS($C$2:$C$1002,$C9,$H$2:$H$1002,"created",$F$2:$F$1002,"<="&F9)-COUNTIFS($C$2:$C$1002,$C9,$H$2:$H$1002,"cancelled",$F$2:$F$1002,"<="&F9)=0,1,0)) -> 0 | V9: =IF(AND(H9="created",T9=0,COUNTIFS($C$2:$C$1002,$C9,$H$2:$H$1002,"cancelled",$F$2:$F$1002,"<"&F9)>0,COUNTIFS($C$2:$C$1002,$C9,$H$2:$H$1002,"created",$F$2:$F$1002,"<"&F9)-COUNTIFS($C$2:$C$1002,$C9,$H$2:$H$1002,"cancelled",$F$2:$F$1002,"<"&F9)=0),1,0) -> 0
A10: EVT009 | B10: SUB050 | C10: CUST007 | D10: Ontario Manufacturing Tech | E10: Eastern Canada | F10: 45383 | G10: 45383 | H10: created | M10: Analytics Starter | N10: Monthly | O10: 15 | P10: 45 | Q10: 12 | R10: {=_xlfn.IFS(H10="created", "New", H10="cancelled", "Churned", AND(H10="seats_change", J10 > I10), "Expansion", AND(H10="seats_change", J10 < I10), "Contraction", AND(H10="price_change", J10 > I10), "Expansion", AND(H10="price_change", J10 < I10), "Contraction", H10="plan_upgrade", "Expansion", H10="plan_downgrade", "Contraction", H10="discount_added", "Contraction")} -> New | S10: {=IF(N10="Monthly",_xlfn.IFS(H10="created",O10*P10*(1-Q10/100),H10="cancelled",-(O10*P10*(1-Q10/100)),H10="seats_change",(J10-I10)*P10*(1-Q10/100),H10="price_change",(J10-I10)*O10*(1-Q10/100),H10="discount_added",-(O10*P10*(J10-I10)/100),H10="plan_upgrade",O10*(_xlfn.XLOOKUP(J10,$M:$M,$P:$P)-_xlfn.XLOOKUP(I10,$M:$M,$P:$P))*(1-Q10/100),H10="plan_downgrade",O10*(_xlfn.XLOOKUP(J10,$M:$M,$P:$P)-_xlfn.XLOOKUP(I10,$M:$M,$P:$P))*(1-Q10/100)),_xlfn.IFS(H10="created",O10*P10*(1-Q10/100)/12,H10="cancelled",-(O10*P10*(1-Q10/100))/12,H10="seats_change",(J10-I10)*P10*(1-Q10/100)/12,H10="price_change",(J10-I10)*O10*(1-Q10/100)/12,H10="plan_upgrade",(O10*(_xlfn.XLOOKUP(J10,$M:$M,$P:$P)-_xlfn.XLOOKUP(I10,$M:$M,$P:$P))*(1-Q10/100))/12,H10="plan_downgrade",(O10*(_xlfn.XLOOKUP(J10,$M:$M,$P:$P)-_xlfn.XLOOKUP(I10,$M:$M,$P:$P))*(1-Q10/100))/12,H10="discount_added",-(O10*P10*(J10-I10)/100)/12))} -> 594 | T10: =IF(H10<>"created",0,IF(COUNTIFS($C$1:C9,$C10,$H$1:H9,"created")=0,1,0)) -> 0 | U10: =IF(H10<>"cancelled",0,IF(COUNTIFS($C$2:$C$1002,$C10,$H$2:$H$1002,"created",$F$2:$F$1002,"<="&F10)-COUNTIFS($C$2:$C$1002,$C10,$H$2:$H$1002,"cancelled",$F$2:$F$1002,"<="&F10)=0,1,0)) -> 0 | V10: =IF(AND(H10="created",T10=0,COUNTIFS($C$2:$C$1002,$C10,$H$2:$H$1002,"cancelled",$F$2:$F$1002,"<"&F10)>0,COUNTIFS($C$2:$C$1002,$C10,$H$2:$H$1002,"created",$F$2:$F$1002,"<"&F10)-COUNTIFS($C$2:$C$1002,$C10,$H$2:$H$1002,"cancelled",$F$2:$F$1002,"<"&F10)=0),1,0) -> 0
A11: EVT010 | B11: SUB008 | C11: CUST008 | D11: Quantum Education Platform | E11: Eastern Canada | F11: 45383 | G11: 45397 | H11: created | M11: Analytics Growth | N11: Monthly | O11: 22 | P11: 95 | Q11: 0 | R11: {=_xlfn.IFS(H11="created", "New", H11="cancelled", "Churned", AND(H11="seats_change", J11 > I11), "Expansion", AND(H11="seats_change", J11 < I11), "Contraction", AND(H11="price_change", J11 > I11), "Expansion", AND(H11="price_change", J11 < I11), "Contraction", H11="plan_upgrade", "Expansion", H11="plan_downgrade", "Contraction", H11="discount_added", "Contraction")} -> New | S11: {=IF(N11="Monthly",_xlfn.IFS(H11="created",O11*P11*(1-Q11/100),H11="cancelled",-(O11*P11*(1-Q11/100)),H11="seats_change",(J11-I11)*P11*(1-Q11/100),H11="price_change",(J11-I11)*O11*(1-Q11/100),H11="discount_added",-(O11*P11*(J11-I11)/100),H11="plan_upgrade",O11*(_xlfn.XLOOKUP(J11,$M:$M,$P:$P)-_xlfn.XLOOKUP(I11,$M:$M,$P:$P))*(1-Q11/100),H11="plan_downgrade",O11*(_xlfn.XLOOKUP(J11,$M:$M,$P:$P)-_xlfn.XLOOKUP(I11,$M:$M,$P:$P))*(1-Q11/100)),_xlfn.IFS(H11="created",O11*P11*(1-Q11/100)/12,H11="cancelled",-(O11*P11*(1-Q11/100))/12,H11="seats_change",(J11-I11)*P11*(1-Q11/100)/12,H11="price_change",(J11-I11)*O11*(1-Q11/100)/12,H11="plan_upgrade",(O11*(_xlfn.XLOOKUP(J11,$M:$M,$P:$P)-_xlfn.XLOOKUP(I11,$M:$M,$P:$P))*(1-Q11/100))/12,H11="plan_downgrade",(O11*(_xlfn.XLOOKUP(J11,$M:$M,$P:$P)-_xlfn.XLOOKUP(I11,$M:$M,$P:$P))*(1-Q11/100))/12,H11="discount_added",-(O11*P11*(J11-I11)/100)/12))} -> 2090 | T11: =IF(H11<>"created",0,IF(COUNTIFS($C$1:C10,$C11,$H$1:H10,"created")=0,1,0)) -> 1 | U11: =IF(H11<>"cancelled",0,IF(COUNTIFS($C$2:$C$1002,$C11,$H$2:$H$1002,"created",$F$2:$F$1002,"<="&F11)-COUNTIFS($C$2:$C$1002,$C11,$H$2:$H$1002,"cancelled",$F$2:$F$1002,"<="&F11)=0,1,0)) -> 0 | V11: =IF(AND(H11="created",T11=0,COUNTIFS($C$2:$C$1002,$C11,$H$2:$H$1002,"cancelled",$F$2:$F$1002,"<"&F11)>0,COUNTIFS($C$2:$C$1002,$C11,$H$2:$H$1002,"created",$F$2:$F$1002,"<"&F11)-COUNTIFS($C$2:$C$1002,$C11,$H$2:$H$1002,"cancelled",$F$2:$F$1002,"<"&F11)=0),1,0) -> 0
A12: EVT011 | B12: SUB009 | C12: CUST009 | D12: West Coast Logistics | E12: Western Canada | F12: 45383 | G12: 45411 | H12: created | M12: Platform Suite | N12: Annual | O12: 36 | P12: 1800 | Q12: 0 | R12: {=_xlfn.IFS(H12="created", "New", H12="cancelled", "Churned", AND(H12="seats_change", J12 > I12), "Expansion", AND(H12="seats_change", J12 < I12), "Contraction", AND(H12="price_change", J12 > I12), "Expansion", AND(H12="price_change", J12 < I12), "Contraction", H12="plan_upgrade", "Expansion", H12="plan_downgrade", "Contraction", H12="discount_added", "Contraction")} -> New | S12: {=IF(N12="Monthly",_xlfn.IFS(H12="created",O12*P12*(1-Q12/100),H12="cancelled",-(O12*P12*(1-Q12/100)),H12="seats_change",(J12-I12)*P12*(1-Q12/100),H12="price_change",(J12-I12)*O12*(1-Q12/100),H12="discount_added",-(O12*P12*(J12-I12)/100),H12="plan_upgrade",O12*(_xlfn.XLOOKUP(J12,$M:$M,$P:$P)-_xlfn.XLOOKUP(I12,$M:$M,$P:$P))*(1-Q12/100),H12="plan_downgrade",O12*(_xlfn.XLOOKUP(J12,$M:$M,$P:$P)-_xlfn.XLOOKUP(I12,$M:$M,$P:$P))*(1-Q12/100)),_xlfn.IFS(H12="created",O12*P12*(1-Q12/100)/12,H12="cancelled",-(O12*P12*(1-Q12/100))/12,H12="seats_change",(J12-I12)*P12*(1-Q12/100)/12,H12="price_change",(J12-I12)*O12*(1-Q12/100)/12,H12="plan_upgrade",(O12*(_xlfn.XLOOKUP(J12,$M:$M,$P:$P)-_xlfn.XLOOKUP(I12,$M:$M,$P:$P))*(1-Q12/100))/12,H12="plan_downgrade",(O12*(_xlfn.XLOOKUP(J12,$M:$M,$P:$P)-_xlfn.XLOOKUP(I12,$M:$M,$P:$P))*(1-Q12/100))/12,H12="discount_added",-(O12*P12*(J12-I12)/100)/12))} -> 5400 | T12: =IF(H12<>"created",0,IF(COUNTIFS($C$1:C11,$C12,$H$1:H11,"created")=0,1,0)) -> 1 | U12: =IF(H12<>"cancelled",0,IF(COUNTIFS($C$2:$C$1002,$C12,$H$2:$H$1002,"created",$F$2:$F$1002,"<="&F12)-COUNTIFS($C$2:$C$1002,$C12,$H$2:$H$1002,"cancelled",$F$2:$F$1002,"<="&F12)=0,1,0)) -> 0 | V12: =IF(AND(H12="created",T12=0,COUNTIFS($C$2:$C$1002,$C12,$H$2:$H$1002,"cancelled",$F$2:$F$1002,"<"&F12)>0,COUNTIFS($C$2:$C$1002,$C12,$H$2:$H$1002,"created",$F$2:$F$1002,"<"&F12)-COUNTIFS($C$2:$C$1002,$C12,$H$2:$H$1002,"cancelled",$F$2:$F$1002,"<"&F12)=0),1,0) -> 0
A13: EVT012 | B13: SUB010 | C13: CUST010 | D13: Montreal Finance Hub | E13: Eastern Canada | F13: 45413 | G13: 45425 | H13: created | M13: Analytics Starter | N13: Monthly | O13: 13 | P13: 45 | Q13: 0 | R13: {=_xlfn.IFS(H13="created", "New", H13="cancelled", "Churned", AND(H13="seats_change", J13 > I13), "Expansion", AND(H13="seats_change", J13 < I13), "Contraction", AND(H13="price_change", J13 > I13), "Expansion", AND(H13="price_change", J13 < I13), "Contraction", H13="plan_upgrade", "Expansion", H13="plan_downgrade", "Contraction", H13="discount_added", "Contraction")} -> New | S13: {=IF(N13="Monthly",_xlfn.IFS(H13="created",O13*P13*(1-Q13/100),H13="cancelled",-(O13*P13*(1-Q13/100)),H13="seats_change",(J13-I13)*P13*(1-Q13/100),H13="price_change",(J13-I13)*O13*(1-Q13/100),H13="discount_added",-(O13*P13*(J13-I13)/100),H13="plan_upgrade",O13*(_xlfn.XLOOKUP(J13,$M:$M,$P:$P)-_xlfn.XLOOKUP(I13,$M:$M,$P:$P))*(1-Q13/100),H13="plan_downgrade",O13*(_xlfn.XLOOKUP(J13,$M:$M,$P:$P)-_xlfn.XLOOKUP(I13,$M:$M,$P:$P))*(1-Q13/100)),_xlfn.IFS(H13="created",O13*P13*(1-Q13/100)/12,H13="cancelled",-(O13*P13*(1-Q13/100))/12,H13="seats_change",(J13-I13)*P13*(1-Q13/100)/12,H13="price_change",(J13-I13)*O13*(1-Q13/100)/12,H13="plan_upgrade",(O13*(_xlfn.XLOOKUP(J13,$M:$M,$P:$P)-_xlfn.XLOOKUP(I13,$M:$M,$P:$P))*(1-Q13/100))/12,H13="plan_downgrade",(O13*(_xlfn.XLOOKUP(J13,$M:$M,$P:$P)-_xlfn.XLOOKUP(I13,$M:$M,$P:$P))*(1-Q13/100))/12,H13="discount_added",-(O13*P13*(J13-I13)/100)/12))} -> 585 | T13: =IF(H13<>"created",0,IF(COUNTIFS($C$1:C12,$C13,$H$1:H12,"created")=0,1,0)) -> 1 | U13: =IF(H13<>"cancelled",0,IF(COUNTIFS($C$2:$C$1002,$C13,$H$2:$H$1002,"created",$F$2:$F$1002,"<="&F13)-COUNTIFS($C$2:$C$1002,$C13,$H$2:$H$1002,"cancelled",$F$2:$F$1002,"<="&F13)=0,1,0)) -> 0 | V13: =IF(AND(H13="created",T13=0,COUNTIFS($C$2:$C$1002,$C13,$H$2:$H$1002,"cancelled",$F$2:$F$1002,"<"&F13)>0,COUNTIFS($C$2:$C$1002,$C13,$H$2:$H$1002,"created",$F$2:$F$1002,"<"&F13)-COUNTIFS($C$2:$C$1002,$C13,$H$2:$H$1002,"cancelled",$F$2:$F$1002,"<"&F13)=0),1,0) -> 0
... A23: EVT022 | B23: SUB017 | C23: CUST017 | D23: Capital Education Tech | E23: Eastern Canada | F23: 45505 | G23: 45523 | H23: created | M23: Analytics Starter | N23: Monthly | O23: 12 | P23: 45 | Q23: 0 | R23: {=_xlfn.IFS(H23="created", "New", H23="cancelled", "Churned", AND(H23="seats_change", J23 > I23), "Expansion", AND(H23="seats_change", J23 < I23), "Contraction", AND(H23="price_change", J23 > I23), "Expansion", AND(H23="price_change", J23 < I23), "Contraction", H23="plan_upgrade", "Expansion", H23="plan_downgrade", "Contraction", H23="discount_added", "Contraction")} -> New | S23: {=IF(N23="Monthly",_xlfn.IFS(H23="created",O23*P23*(1-Q23/100),H23="cancelled",-(O23*P23*(1-Q23/100)),H23="seats_change",(J23-I23)*P23*(1-Q23/100),H23="price_change",(J23-I23)*O23*(1-Q23/100),H23="discount_added",-(O23*P23*(J23-I23)/100),H23="plan_upgrade",O23*(_xlfn.XLOOKUP(J23,$M:$M,$P:$P)-_xlfn.XLOOKUP(I23,$M:$M,$P:$P))*(1-Q23/100),H23="plan_downgrade",O23*(_xlfn.XLOOKUP(J23,$M:$M,$P:$P)-_xlfn.XLOOKUP(I23,$M:$M,$P:$P))*(1-Q23/100)),_xlfn.IFS(H23="created",O23*P23*(1-Q23/100)/12,H23="cancelled",-(O23*P23*(1-Q23/100))/12,H23="seats_change",(J23-I23)*P23*(1-Q23/100)/12,H23="price_change",(J23-I23)*O23*(1-Q23/100)/12,H23="plan_upgrade",(O23*(_xlfn.XLOOKUP(J23,$M:$M,$P:$P)-_xlfn.XLOOKUP(I23,$M:$M,$P:$P))*(1-Q23/100))/12,H23="plan_downgrade",(O23*(_xlfn.XLOOKUP(J23,$M:$M,$P:$P)-_xlfn.XLOOKUP(I23,$M:$M,$P:$P))*(1-Q23/100))/12,H23="discount_added",-(O23*P23*(J23-I23)/100)/12))} -> 540 | T23: =IF(H23<>"created",0,IF(COUNTIFS($C$1:C22,$C23,$H$1:H22,"created")=0,1,0)) -> 1 | U23: =IF(H23<>"cancelled",0,IF(COUNTIFS($C$2:$C$1002,$C23,$H$2:$H$1002,"created",$F$2:$F$1002,"<="&F23)-COUNTIFS($C$2:$C$1002,$C23,$H$2:$H$1002,"cancelled",$F$2:$F$1002,"<="&F23)=0,1,0)) -> 0 | V23: =IF(AND(H23="created",T23=0,COUNTIFS($C$2:$C$1002,$C23,$H$2:$H$1002,"cancelled",$F$2:$F$1002,"<"&F23)>0,COUNTIFS($C$2:$C$1002,$C23,$H$2:$H$1002,"created",$F$2:$F$1002,"<"&F23)-COUNTIFS($C$2:$C$1002,$C23,$H$2:$H$1002,"cancelled",$F$2:$F$1002,"<"&F23)=0),1,0) -> 0
A24: EVT023 | B24: SUB001 | C24: CUST001 | D24: TechVision Solutions | E24: Eastern Canada | F24: 45505 | G24: 45531 | H24: cancelled | I24: active | J24: churned | K24: status | L24: Missing features | M24: Analytics Growth | N24: Monthly | O24: 20 | P24: 95 | Q24: 0 | R24: {=_xlfn.IFS(H24="created", "New", H24="cancelled", "Churned", AND(H24="seats_change", J24 > I24), "Expansion", AND(H24="seats_change", J24 < I24), "Contraction", AND(H24="price_change", J24 > I24), "Expansion", AND(H24="price_change", J24 < I24), "Contraction", H24="plan_upgrade", "Expansion", H24="plan_downgrade", "Contraction", H24="discount_added", "Contraction")} -> Churned | S24: {=IF(N24="Monthly",_xlfn.IFS(H24="created",O24*P24*(1-Q24/100),H24="cancelled",-(O24*P24*(1-Q24/100)),H24="seats_change",(J24-I24)*P24*(1-Q24/100),H24="price_change",(J24-I24)*O24*(1-Q24/100),H24="discount_added",-(O24*P24*(J24-I24)/100),H24="plan_upgrade",O24*(_xlfn.XLOOKUP(J24,$M:$M,$P:$P)-_xlfn.XLOOKUP(I24,$M:$M,$P:$P))*(1-Q24/100),H24="plan_downgrade",O24*(_xlfn.XLOOKUP(J24,$M:$M,$P:$P)-_xlfn.XLOOKUP(I24,$M:$M,$P:$P))*(1-Q24/100)),_xlfn.IFS(H24="created",O24*P24*(1-Q24/100)/12,H24="cancelled",-(O24*P24*(1-Q24/100))/12,H24="seats_change",(J24-I24)*P24*(1-Q24/100)/12,H24="price_change",(J24-I24)*O24*(1-Q24/100)/12,H24="plan_upgrade",(O24*(_xlfn.XLOOKUP(J24,$M:$M,$P:$P)-_xlfn.XLOOKUP(I24,$M:$M,$P:$P))*(1-Q24/100))/12,H24="plan_downgrade",(O24*(_xlfn.XLOOKUP(J24,$M:$M,$P:$P)-_xlfn.XLOOKUP(I24,$M:$M,$P:$P))*(1-Q24/100))/12,H24="discount_added",-(O24*P24*(J24-I24)/100)/12))} -> -1900 | T24: =IF(H24<>"created",0,IF(COUNTIFS($C$1:C23,$C24,$H$1:H23,"created")=0,1,0)) -> 0 | U24: =IF(H24<>"cancelled",0,IF(COUNTIFS($C$2:$C$1002,$C24,$H$2:$H$1002,"created",$F$2:$F$1002,"<="&F24)-COUNTIFS($C$2:$C$1002,$C24,$H$2:$H$1002,"cancelled",$F$2:$F$1002,"<="&F24)=0,1,0)) -> 0 | V24: =IF(AND(H24="created",T24=0,COUNTIFS($C$2:$C$1002,$C24,$H$2:$H$1002,"cancelled",$F$2:$F$1002,"<"&F24)>0,COUNTIFS($C$2:$C$1002,$C24,$H$2:$H$1002,"created",$F$2:$F$1002,"<"&F24)-COUNTIFS($C$2:$C$1002,$C24,$H$2:$H$1002,"cancelled",$F$2:$F$1002,"<"&F24)=0),1,0) -> 0
A25: EVT024 | B25: SUB018 | C25: CUST018 | D25: Vancouver FinTech Labs | E25: Western Canada | F25: 45536 | G25: 45537 | H25: created | M25: Analytics Enterprise | N25: Monthly | O25: 35 | P25: 180 | Q25: 0 | R25: {=_xlfn.IFS(H25="created", "New", H25="cancelled", "Churned", AND(H25="seats_change", J25 > I25), "Expansion", AND(H25="seats_change", J25 < I25), "Contraction", AND(H25="price_change", J25 > I25), "Expansion", AND(H25="price_change", J25 < I25), "Contraction", H25="plan_upgrade", "Expansion", H25="plan_downgrade", "Contraction", H25="discount_added", "Contraction")} -> New | S25: {=IF(N25="Monthly",_xlfn.IFS(H25="created",O25*P25*(1-Q25/100),H25="cancelled",-(O25*P25*(1-Q25/100)),H25="seats_change",(J25-I25)*P25*(1-Q25/100),H25="price_change",(J25-I25)*O25*(1-Q25/100),H25="discount_added",-(O25*P25*(J25-I25)/100),H25="plan_upgrade",O25*(_xlfn.XLOOKUP(J25,$M:$M,$P:$P)-_xlfn.XLOOKUP(I25,$M:$M,$P:$P))*(1-Q25/100),H25="plan_downgrade",O25*(_xlfn.XLOOKUP(J25,$M:$M,$P:$P)-_xlfn.XLOOKUP(I25,$M:$M,$P:$P))*(1-Q25/100)),_xlfn.IFS(H25="created",O25*P25*(1-Q25/100)/12,H25="cancelled",-(O25*P25*(1-Q25/100))/12,H25="seats_change",(J25-I25)*P25*(1-Q25/100)/12,H25="price_change",(J25-I25)*O25*(1-Q25/100)/12,H25="plan_upgrade",(O25*(_xlfn.XLOOKUP(J25,$M:$M,$P:$P)-_xlfn.XLOOKUP(I25,$M:$M,$P:$P))*(1-Q25/100))/12,H25="plan_downgrade",(O25*(_xlfn.XLOOKUP(J25,$M:$M,$P:$P)-_xlfn.XLOOKUP(I25,$M:$M,$P:$P))*(1-Q25/100))/12,H25="discount_added",-(O25*P25*(J25-I25)/100)/12))} -> 6300 | T25: =IF(H25<>"created",0,IF(COUNTIFS($C$1:C24,$C25,$H$1:H24,"created")=0,1,0)) -> 1 | U25: =IF(H25<>"cancelled",0,IF(COUNTIFS($C$2:$C$1002,$C25,$H$2:$H$1002,"created",$F$2:$F$1002,"<="&F25)-COUNTIFS($C$2:$C$1002,$C25,$H$2:$H$1002,"cancelled",$F$2:$F$1002,"<="&F25)=0,1,0)) -> 0 | V25: =IF(AND(H25="created",T25=0,COUNTIFS($C$2:$C$1002,$C25,$H$2:$H$1002,"cancelled",$F$2:$F$1002,"<"&F25)>0,COUNTIFS($C$2:$C$1002,$C25,$H$2:$H$1002,"created",$F$2:$F$1002,"<"&F25)-COUNTIFS($C$2:$C$1002,$C25,$H$2:$H$1002,"cancelled",$F$2:$F$1002,"<"&F25)=0),1,0) -> 0
A26: EVT025 | B26: SUB042 | C26: CUST003 | D26: Maple Healthcare Systems | E26: Eastern Canada | F26: 45536 | G26: 45545 | H26: created | M26: Sales Hub | N26: Monthly | O26: 19 | P26: 110 | Q26: 0 | R26: {=_xlfn.IFS(H26="created", "New", H26="cancelled", "Churned", AND(H26="seats_change", J26 > I26), "Expansion", AND(H26="seats_change", J26 < I26), "Contraction", AND(H26="price_change", J26 > I26), "Expansion", AND(H26="price_change", J26 < I26), "Contraction", H26="plan_upgrade", "Expansion", H26="plan_downgrade", "Contraction", H26="discount_added", "Contraction")} -> New | S26: {=IF(N26="Monthly",_xlfn.IFS(H26="created",O26*P26*(1-Q26/100),H26="cancelled",-(O26*P26*(1-Q26/100)),H26="seats_change",(J26-I26)*P26*(1-Q26/100),H26="price_change",(J26-I26)*O26*(1-Q26/100),H26="discount_added",-(O26*P26*(J26-I26)/100),H26="plan_upgrade",O26*(_xlfn.XLOOKUP(J26,$M:$M,$P:$P)-_xlfn.XLOOKUP(I26,$M:$M,$P:$P))*(1-Q26/100),H26="plan_downgrade",O26*(_xlfn.XLOOKUP(J26,$M:$M,$P:$P)-_xlfn.XLOOKUP(I26,$M:$M,$P:$P))*(1-Q26/100)),_xlfn.IFS(H26="created",O26*P26*(1-Q26/100)/12,H26="cancelled",-(O26*P26*(1-Q26/100))/12,H26="seats_change",(J26-I26)*P26*(1-Q26/100)/12,H26="price_change",(J26-I26)*O26*(1-Q26/100)/12,H26="plan_upgrade",(O26*(_xlfn.XLOOKUP(J26,$M:$M,$P:$P)-_xlfn.XLOOKUP(I26,$M:$M,$P:$P))*(1-Q26/100))/12,H26="plan_downgrade",(O26*(_xlfn.XLOOKUP(J26,$M:$M,$P:$P)-_xlfn.XLOOKUP(I26,$M:$M,$P:$P))*(1-Q26/100))/12,H26="discount_added",-(O26*P26*(J26-I26)/100)/12))} -> 2090 | T26: =IF(H26<>"created",0,IF(COUNTIFS($C$1:C25,$C26,$H$1:H25,"created")=0,1,0)) -> 0 | U26: =IF(H26<>"cancelled",0,IF(COUNTIFS($C$2:$C$1002,$C26,$H$2:$H$1002,"created",$F$2:$F$1002,"<="&F26)-COUNTIFS($C$2:$C$1002,$C26,$H$2:$H$1002,"cancelled",$F$2:$F$1002,"<="&F26)=0,1,0)) -> 0 | V26: =IF(AND(H26="created",T26=0,COUNTIFS($C$2:$C$1002,$C26,$H$2:$H$1002,"cancelled",$F$2:$F$1002,"<"&F26)>0,COUNTIFS($C$2:$C$1002,$C26,$H$2:$H$1002,"created",$F$2:$F$1002,"<"&F26)-COUNTIFS($C$2:$C$1002,$C26,$H$2:$H$1002,"cancelled",$F$2:$F$1002,"<"&F26)=0),1,0) -> 0
A27: EVT026 | B27: SUB019 | C27: CUST019 | D27: Central Healthcare Partners | E27: Central Canada | F27: 45536 | G27: 45551 | H27: created | M27: Marketing Pro | N27: Monthly | O27: 19 | P27: 85 | Q27: 0 | R27: {=_xlfn.IFS(H27="created", "New", H27="cancelled", "Churned", AND(H27="seats_change", J27 > I27), "Expansion", AND(H27="seats_change", J27 < I27), "Contraction", AND(H27="price_change", J27 > I27), "Expansion", AND(H27="price_change", J27 < I27), "Contraction", H27="plan_upgrade", "Expansion", H27="plan_downgrade", "Contraction", H27="discount_added", "Contraction")} -> New | S27: {=IF(N27="Monthly",_xlfn.IFS(H27="created",O27*P27*(1-Q27/100),H27="cancelled",-(O27*P27*(1-Q27/100)),H27="seats_change",(J27-I27)*P27*(1-Q27/100),H27="price_change",(J27-I27)*O27*(1-Q27/100),H27="discount_added",-(O27*P27*(J27-I27)/100),H27="plan_upgrade",O27*(_xlfn.XLOOKUP(J27,$M:$M,$P:$P)-_xlfn.XLOOKUP(I27,$M:$M,$P:$P))*(1-Q27/100),H27="plan_downgrade",O27*(_xlfn.XLOOKUP(J27,$M:$M,$P:$P)-_xlfn.XLOOKUP(I27,$M:$M,$P:$P))*(1-Q27/100)),_xlfn.IFS(H27="created",O27*P27*(1-Q27/100)/12,H27="cancelled",-(O27*P27*(1-Q27/100))/12,H27="seats_change",(J27-I27)*P27*(1-Q27/100)/12,H27="price_change",(J27-I27)*O27*(1-Q27/100)/12,H27="plan_upgrade",(O27*(_xlfn.XLOOKUP(J27,$M:$M,$P:$P)-_xlfn.XLOOKUP(I27,$M:$M,$P:$P))*(1-Q27/100))/12,H27="plan_downgrade",(O27*(_xlfn.XLOOKUP(J27,$M:$M,$P:$P)-_xlfn.XLOOKUP(I27,$M:$M,$P:$P))*(1-Q27/100))/12,H27="discount_added",-(O27*P27*(J27-I27)/100)/12))} -> 1615 | T27: =IF(H27<>"created",0,IF(COUNTIFS($C$1:C26,$C27,$H$1:H26,"created")=0,1,0)) -> 1 | U27: =IF(H27<>"cancelled",0,IF(COUNTIFS($C$2:$C$1002,$C27,$H$2:$H$1002,"created",$F$2:$F$1002,"<="&F27)-COUNTIFS($C$2:$C$1002,$C27,$H$2:$H$1002,"cancelled",$F$2:$F$1002,"<="&F27)=0,1,0)) -> 0 | V27: =IF(AND(H27="created",T27=0,COUNTIFS($C$2:$C$1002,$C27,$H$2:$H$1002,"cancelled",$F$2:$F$1002,"<"&F27)>0,COUNTIFS($C$2:$C$1002,$C27,$H$2:$H$1002,"created",$F$2:$F$1002,"<"&F27)-COUNTIFS($C$2:$C$1002,$C27,$H$2:$H$1002,"cancelled",$F$2:$F$1002,"<"&F27)=0),1,0) -> 0
A28: EVT027 | B28: SUB060 | C28: CUST019 | D28: Central Healthcare Partners | E28: Central Canada | F28: 45536 | G28: 45551 | H28: created | M28: Sales Hub | N28: Monthly | O28: 16 | P28: 110 | Q28: 0 | R28: {=_xlfn.IFS(H28="created", "New", H28="cancelled", "Churned", AND(H28="seats_change", J28 > I28), "Expansion", AND(H28="seats_change", J28 < I28), "Contraction", AND(H28="price_change", J28 > I28), "Expansion", AND(H28="price_change", J28 < I28), "Contraction", H28="plan_upgrade", "Expansion", H28="plan_downgrade", "Contraction", H28="discount_added", "Contraction")} -> New | S28: {=IF(N28="Monthly",_xlfn.IFS(H28="created",O28*P28*(1-Q28/100),H28="cancelled",-(O28*P28*(1-Q28/100)),H28="seats_change",(J28-I28)*P28*(1-Q28/100),H28="price_change",(J28-I28)*O28*(1-Q28/100),H28="discount_added",-(O28*P28*(J28-I28)/100),H28="plan_upgrade",O28*(_xlfn.XLOOKUP(J28,$M:$M,$P:$P)-_xlfn.XLOOKUP(I28,$M:$M,$P:$P))*(1-Q28/100),H28="plan_downgrade",O28*(_xlfn.XLOOKUP(J28,$M:$M,$P:$P)-_xlfn.XLOOKUP(I28,$M:$M,$P:$P))*(1-Q28/100)),_xlfn.IFS(H28="created",O28*P28*(1-Q28/100)/12,H28="cancelled",-(O28*P28*(1-Q28/100))/12,H28="seats_change",(J28-I28)*P28*(1-Q28/100)/12,H28="price_change",(J28-I28)*O28*(1-Q28/100)/12,H28="plan_upgrade",(O28*(_xlfn.XLOOKUP(J28,$M:$M,$P:$P)-_xlfn.XLOOKUP(I28,$M:$M,$P:$P))*(1-Q28/100))/12,H28="plan_downgrade",(O28*(_xlfn.XLOOKUP(J28,$M:$M,$P:$P)-_xlfn.XLOOKUP(I28,$M:$M,$P:$P))*(1-Q28/100))/12,H28="discount_added",-(O28*P28*(J28-I28)/100)/12))} -> 1760 | T28: =IF(H28<>"created",0,IF(COUNTIFS($C$1:C27,$C28,$H$1:H27,"created")=0,1,0)) -> 0 | U28: =IF(H28<>"cancelled",0,IF(COUNTIFS($C$2:$C$1002,$C28,$H$2:$H$1002,"created",$F$2:$F$1002,"<="&F28)-COUNTIFS($C$2:$C$1002,$C28,$H$2:$H$1002,"cancelled",$F$2:$F$1002,"<="&F28)=0,1,0)) -> 0 | V28: =IF(AND(H28="created",T28=0,COUNTIFS($C$2:$C$1002,$C28,$H$2:$H$1002,"cancelled",$F$2:$F$1002,"<"&F28)>0,COUNTIFS($C$2:$C$1002,$C28,$H$2:$H$1002,"created",$F$2:$F$1002,"<"&F28)-COUNTIFS($C$2:$C$1002,$C28,$H$2:$H$1002,"cancelled",$F$2:$F$1002,"<"&F28)=0),1,0) -> 0
A29: EVT028 | B29: SUB020 | C29: CUST020 | D29: Atlantic SaaS Systems | E29: Eastern Canada | F29: 45536 | G29: 45565 | H29: created | M29: Sales Hub | N29: Monthly | O29: 15 | P29: 110 | Q29: 0 | R29: {=_xlfn.IFS(H29="created", "New", H29="cancelled", "Churned", AND(H29="seats_change", J29 > I29), "Expansion", AND(H29="seats_change", J29 < I29), "Contraction", AND(H29="price_change", J29 > I29), "Expansion", AND(H29="price_change", J29 < I29), "Contraction", H29="plan_upgrade", "Expansion", H29="plan_downgrade", "Contraction", H29="discount_added", "Contraction")} -> New | S29: {=IF(N29="Monthly",_xlfn.IFS(H29="created",O29*P29*(1-Q29/100),H29="cancelled",-(O29*P29*(1-Q29/100)),H29="seats_change",(J29-I29)*P29*(1-Q29/100),H29="price_change",(J29-I29)*O29*(1-Q29/100),H29="discount_added",-(O29*P29*(J29-I29)/100),H29="plan_upgrade",O29*(_xlfn.XLOOKUP(J29,$M:$M,$P:$P)-_xlfn.XLOOKUP(I29,$M:$M,$P:$P))*(1-Q29/100),H29="plan_downgrade",O29*(_xlfn.XLOOKUP(J29,$M:$M,$P:$P)-_xlfn.XLOOKUP(I29,$M:$M,$P:$P))*(1-Q29/100)),_xlfn.IFS(H29="created",O29*P29*(1-Q29/100)/12,H29="cancelled",-(O29*P29*(1-Q29/100))/12,H29="seats_change",(J29-I29)*P29*(1-Q29/100)/12,H29="price_change",(J29-I29)*O29*(1-Q29/100)/12,H29="plan_upgrade",(O29*(_xlfn.XLOOKUP(J29,$M:$M,$P:$P)-_xlfn.XLOOKUP(I29,$M:$M,$P:$P))*(1-Q29/100))/12,H29="plan_downgrade",(O29*(_xlfn.XLOOKUP(J29,$M:$M,$P:$P)-_xlfn.XLOOKUP(I29,$M:$M,$P:$P))*(1-Q29/100))/12,H29="discount_added",-(O29*P29*(J29-I29)/100)/12))} -> 1650 | T29: =IF(H29<>"created",0,IF(COUNTIFS($C$1:C28,$C29,$H$1:H28,"created")=0,1,0)) -> 1 | U29: =IF(H29<>"cancelled",0,IF(COUNTIFS($C$2:$C$1002,$C29,$H$2:$H$1002,"created",$F$2:$F$1002,"<="&F29)-COUNTIFS($C$2:$C$1002,$C29,$H$2:$H$1002,"cancelled",$F$2:$F$1002,"<="&F29)=0,1,0)) -> 0 | V29: =IF(AND(H29="created",T29=0,COUNTIFS($C$2:$C$1002,$C29,$H$2:$H$1002,"cancelled",$F$2:$F$1002,"<"&F29)>0,COUNTIFS($C$2:$C$1002,$C29,$H$2:$H$1002,"created",$F$2:$F$1002,"<"&F29)-COUNTIFS($C$2:$C$1002,$C29,$H$2:$H$1002,"cancelled",$F$2:$F$1002,"<"&F29)=0),1,0) -> 0
A30: EVT029 | B30: SUB043 | C30: CUST006 | D30: Northern Retail Solutions | E30: Western Canada | F30: 45566 | G30: 45570 | H30: created | M30: Marketing Pro | N30: Monthly | O30: 33 | P30: 85 | Q30: 0 | R30: {=_xlfn.IFS(H30="created", "New", H30="cancelled", "Churned", AND(H30="seats_change", J30 > I30), "Expansion", AND(H30="seats_change", J30 < I30), "Contraction", AND(H30="price_change", J30 > I30), "Expansion", AND(H30="price_change", J30 < I30), "Contraction", H30="plan_upgrade", "Expansion", H30="plan_downgrade", "Contraction", H30="discount_added", "Contraction")} -> New | S30: {=IF(N30="Monthly",_xlfn.IFS(H30="created",O30*P30*(1-Q30/100),H30="cancelled",-(O30*P30*(1-Q30/100)),H30="seats_change",(J30-I30)*P30*(1-Q30/100),H30="price_change",(J30-I30)*O30*(1-Q30/100),H30="discount_added",-(O30*P30*(J30-I30)/100),H30="plan_upgrade",O30*(_xlfn.XLOOKUP(J30,$M:$M,$P:$P)-_xlfn.XLOOKUP(I30,$M:$M,$P:$P))*(1-Q30/100),H30="plan_downgrade",O30*(_xlfn.XLOOKUP(J30,$M:$M,$P:$P)-_xlfn.XLOOKUP(I30,$M:$M,$P:$P))*(1-Q30/100)),_xlfn.IFS(H30="created",O30*P30*(1-Q30/100)/12,H30="cancelled",-(O30*P30*(1-Q30/100))/12,H30="seats_change",(J30-I30)*P30*(1-Q30/100)/12,H30="price_change",(J30-I30)*O30*(1-Q30/100)/12,H30="plan_upgrade",(O30*(_xlfn.XLOOKUP(J30,$M:$M,$P:$P)-_xlfn.XLOOKUP(I30,$M:$M,$P:$P))*(1-Q30/100))/12,H30="plan_downgrade",(O30*(_xlfn.XLOOKUP(J30,$M:$M,$P:$P)-_xlfn.XLOOKUP(I30,$M:$M,$P:$P))*(1-Q30/100))/12,H30="discount_added",-(O30*P30*(J30-I30)/100)/12))} -> 2805 | T30: =IF(H30<>"created",0,IF(COUNTIFS($C$1:C29,$C30,$H$1:H29,"created")=0,1,0)) -> 0 | U30: =IF(H30<>"cancelled",0,IF(COUNTIFS($C$2:$C$1002,$C30,$H$2:$H$1002,"created",$F$2:$F$1002,"<="&F30)-COUNTIFS($C$2:$C$1002,$C30,$H$2:$H$1002,"cancelled",$F$2:$F$1002,"<="&F30)=0,1,0)) -> 0 | V30: =IF(AND(H30="created",T30=0,COUNTIFS($C$2:$C$1002,$C30,$H$2:$H$1002,"cancelled",$F$2:$F$1002,"<"&F30)>0,COUNTIFS($C$2:$C$1002,$C30,$H$2:$H$1002,"created",$F$2:$F$1002,"<"&F30)-COUNTIFS($C$2:$C$1002,$C30,$H$2:$H$1002,"cancelled",$F$2:$F$1002,"<"&F30)=0),1,0) -> 0
A31: EVT030 | B31: SUB021 | C31: CUST021 | D31: Calgary Commerce Solutions | E31: Western Canada | F31: 45566 | G31: 45579 | H31: created | M31: Analytics Growth | N31: Monthly | O31: 25 | P31: 95 | Q31: 0 | R31: {=_xlfn.IFS(H31="created", "New", H31="cancelled", "Churned", AND(H31="seats_change", J31 > I31), "Expansion", AND(H31="seats_change", J31 < I31), "Contraction", AND(H31="price_change", J31 > I31), "Expansion", AND(H31="price_change", J31 < I31), "Contraction", H31="plan_upgrade", "Expansion", H31="plan_downgrade", "Contraction", H31="discount_added", "Contraction")} -> New | S31: {=IF(N31="Monthly",_xlfn.IFS(H31="created",O31*P31*(1-Q31/100),H31="cancelled",-(O31*P31*(1-Q31/100)),H31="seats_change",(J31-I31)*P31*(1-Q31/100),H31="price_change",(J31-I31)*O31*(1-Q31/100),H31="discount_added",-(O31*P31*(J31-I31)/100),H31="plan_upgrade",O31*(_xlfn.XLOOKUP(J31,$M:$M,$P:$P)-_xlfn.XLOOKUP(I31,$M:$M,$P:$P))*(1-Q31/100),H31="plan_downgrade",O31*(_xlfn.XLOOKUP(J31,$M:$M,$P:$P)-_xlfn.XLOOKUP(I31,$M:$M,$P:$P))*(1-Q31/100)),_xlfn.IFS(H31="created",O31*P31*(1-Q31/100)/12,H31="cancelled",-(O31*P31*(1-Q31/100))/12,H31="seats_change",(J31-I31)*P31*(1-Q31/100)/12,H31="price_change",(J31-I31)*O31*(1-Q31/100)/12,H31="plan_upgrade",(O31*(_xlfn.XLOOKUP(J31,$M:$M,$P:$P)-_xlfn.XLOOKUP(I31,$M:$M,$P:$P))*(1-Q31/100))/12,H31="plan_downgrade",(O31*(_xlfn.XLOOKUP(J31,$M:$M,$P:$P)-_xlfn.XLOOKUP(I31,$M:$M,$P:$P))*(1-Q31/100))/12,H31="discount_added",-(O31*P31*(J31-I31)/100)/12))} -> 2375 | T31: =IF(H31<>"created",0,IF(COUNTIFS($C$1:C30,$C31,$H$1:H30,"created")=0,1,0)) -> 1 | U31: =IF(H31<>"cancelled",0,IF(COUNTIFS($C$2:$C$1002,$C31,$H$2:$H$1002,"created",$F$2:$F$1002,"<="&F31)-COUNTIFS($C$2:$C$1002,$C31,$H$2:$H$1002,"cancelled",$F$2:$F$1002,"<="&F31)=0,1,0)) -> 0 | V31: =IF(AND(H31="created",T31=0,COUNTIFS($C$2:$C$1002,$C31,$H$2:$H$1002,"cancelled",$F$2:$F$1002,"<"&F31)>0,COUNTIFS($C$2:$C$1002,$C31,$H$2:$H$1002,"created",$F$2:$F$1002,"<"&F31)-COUNTIFS($C$2:$C$1002,$C31,$H$2:$H$1002,"cancelled",$F$2:$F$1002,"<"&F31)=0),1,0) -> 0
A32: EVT031 | B32: SUB022 | C32: CUST022 | D32: Toronto Tech Ventures | E32: Eastern Canada | F32: 45566 | G32: 45593 | H32: created | M32: Platform Suite | N32: Monthly | O32: 33 | P32: 150 | Q32: 0 | R32: {=_xlfn.IFS(H32="created", "New", H32="cancelled", "Churned", AND(H32="seats_change", J32 > I32), "Expansion", AND(H32="seats_change", J32 < I32), "Contraction", AND(H32="price_change", J32 > I32), "Expansion", AND(H32="price_change", J32 < I32), "Contraction", H32="plan_upgrade", "Expansion", H32="plan_downgrade", "Contraction", H32="discount_added", "Contraction")} -> New | S32: {=IF(N32="Monthly",_xlfn.IFS(H32="created",O32*P32*(1-Q32/100),H32="cancelled",-(O32*P32*(1-Q32/100)),H32="seats_change",(J32-I32)*P32*(1-Q32/100),H32="price_change",(J32-I32)*O32*(1-Q32/100),H32="discount_added",-(O32*P32*(J32-I32)/100),H32="plan_upgrade",O32*(_xlfn.XLOOKUP(J32,$M:$M,$P:$P)-_xlfn.XLOOKUP(I32,$M:$M,$P:$P))*(1-Q32/100),H32="plan_downgrade",O32*(_xlfn.XLOOKUP(J32,$M:$M,$P:$P)-_xlfn.XLOOKUP(I32,$M:$M,$P:$P))*(1-Q32/100)),_xlfn.IFS(H32="created",O32*P32*(1-Q32/100)/12,H32="cancelled",-(O32*P32*(1-Q32/100))/12,H32="seats_change",(J32-I32)*P32*(1-Q32/100)/12,H32="price_change",(J32-I32)*O32*(1-Q32/100)/12,H32="plan_upgrade",(O32*(_xlfn.XLOOKUP(J32,$M:$M,$P:$P)-_xlfn.XLOOKUP(I32,$M:$M,$P:$P))*(1-Q32/100))/12,H32="plan_downgrade",(O32*(_xlfn.XLOOKUP(J32,$M:$M,$P:$P)-_xlfn.XLOOKUP(I32,$M:$M,$P:$P))*(1-Q32/100))/12,H32="discount_added",-(O32*P32*(J32-I32)/100)/12))} -> 4950 | T32: =IF(H32<>"created",0,IF(COUNTIFS($C$1:C31,$C32,$H$1:H31,"created")=0,1,0)) -> 1 | U32: =IF(H32<>"cancelled",0,IF(COUNTIFS($C$2:$C$1002,$C32,$H$2:$H$1002,"created",$F$2:$F$1002,"<="&F32)-COUNTIFS($C$2:$C$1002,$C32,$H$2:$H$1002,"cancelled",$F$2:$F$1002,"<="&F32)=0,1,0)) -> 0 | V32: =IF(AND(H32="created",T32=0,COUNTIFS($C$2:$C$1002,$C32,$H$2:$H$1002,"cancelled",$F$2:$F$1002,"<"&F32)>0,COUNTIFS($C$2:$C$1002,$C32,$H$2:$H$1002,"created",$F$2:$F$1002,"<"&F32)-COUNTIFS($C$2:$C$1002,$C32,$H$2:$H$1002,"cancelled",$F$2:$F$1002,"<"&F32)=0),1,0) -> 0
A33: EVT032 | B33: SUB059 | C33: CUST008 | D33: Quantum Education Platform | E33: Eastern Canada | F33: 45597 | G33: 45601 | H33: created | M33: Marketing Pro | N33: Monthly | O33: 22 | P33: 85 | Q33: 0 | R33: {=_xlfn.IFS(H33="created", "New", H33="cancelled", "Churned", AND(H33="seats_change", J33 > I33), "Expansion", AND(H33="seats_change", J33 < I33), "Contraction", AND(H33="price_change", J33 > I33), "Expansion", AND(H33="price_change", J33 < I33), "Contraction", H33="plan_upgrade", "Expansion", H33="plan_downgrade", "Contraction", H33="discount_added", "Contraction")} -> New | S33: {=IF(N33="Monthly",_xlfn.IFS(H33="created",O33*P33*(1-Q33/100),H33="cancelled",-(O33*P33*(1-Q33/100)),H33="seats_change",(J33-I33)*P33*(1-Q33/100),H33="price_change",(J33-I33)*O33*(1-Q33/100),H33="discount_added",-(O33*P33*(J33-I33)/100),H33="plan_upgrade",O33*(_xlfn.XLOOKUP(J33,$M:$M,$P:$P)-_xlfn.XLOOKUP(I33,$M:$M,$P:$P))*(1-Q33/100),H33="plan_downgrade",O33*(_xlfn.XLOOKUP(J33,$M:$M,$P:$P)-_xlfn.XLOOKUP(I33,$M:$M,$P:$P))*(1-Q33/100)),_xlfn.IFS(H33="created",O33*P33*(1-Q33/100)/12,H33="cancelled",-(O33*P33*(1-Q33/100))/12,H33="seats_change",(J33-I33)*P33*(1-Q33/100)/12,H33="price_change",(J33-I33)*O33*(1-Q33/100)/12,H33="plan_upgrade",(O33*(_xlfn.XLOOKUP(J33,$M:$M,$P:$P)-_xlfn.XLOOKUP(I33,$M:$M,$P:$P))*(1-Q33/100))/12,H33="plan_downgrade",(O33*(_xlfn.XLOOKUP(J33,$M:$M,$P:$P)-_xlfn.XLOOKUP(I33,$M:$M,$P:$P))*(1-Q33/100))/12,H33="discount_added",-(O33*P33*(J33-I33)/100)/12))} -> 1870 | T33: =IF(H33<>"created",0,IF(COUNTIFS($C$1:C32,$C33,$H$1:H32,"created")=0,1,0)) -> 0 | U33: =IF(H33<>"cancelled",0,IF(COUNTIFS($C$2:$C$1002,$C33,$H$2:$H$1002,"created",$F$2:$F$1002,"<="&F33)-COUNTIFS($C$2:$C$1002,$C33,$H$2:$H$1002,"cancelled",$F$2:$F$1002,"<="&F33)=0,1,0)) -> 0 | V33: =IF(AND(H33="created",T33=0,COUNTIFS($C$2:$C$1002,$C33,$H$2:$H$1002,"cancelled",$F$2:$F$1002,"<"&F33)>0,COUNTIFS($C$2:$C$1002,$C33,$H$2:$H$1002,"created",$F$2:$F$1002,"<"&F33)-COUNTIFS($C$2:$C$1002,$C33,$H$2:$H$1002,"cancelled",$F$2:$F$1002,"<"&F33)=0),1,0) -> 0
A34: EVT033 | B34: SUB023 | C34: CUST023 | D34: Island Media Productions | E34: Eastern Canada | F34: 45597 | G34: 45607 | H34: created | M34: Analytics Starter | N34: Monthly | O34: 10 | P34: 45 | Q34: 0 | R34: {=_xlfn.IFS(H34="created", "New", H34="cancelled", "Churned", AND(H34="seats_change", J34 > I34), "Expansion", AND(H34="seats_change", J34 < I34), "Contraction", AND(H34="price_change", J34 > I34), "Expansion", AND(H34="price_change", J34 < I34), "Contraction", H34="plan_upgrade", "Expansion", H34="plan_downgrade", "Contraction", H34="discount_added", "Contraction")} -> New | S34: {=IF(N34="Monthly",_xlfn.IFS(H34="created",O34*P34*(1-Q34/100),H34="cancelled",-(O34*P34*(1-Q34/100)),H34="seats_change",(J34-I34)*P34*(1-Q34/100),H34="price_change",(J34-I34)*O34*(1-Q34/100),H34="discount_added",-(O34*P34*(J34-I34)/100),H34="plan_upgrade",O34*(_xlfn.XLOOKUP(J34,$M:$M,$P:$P)-_xlfn.XLOOKUP(I34,$M:$M,$P:$P))*(1-Q34/100),H34="plan_downgrade",O34*(_xlfn.XLOOKUP(J34,$M:$M,$P:$P)-_xlfn.XLOOKUP(I34,$M:$M,$P:$P))*(1-Q34/100)),_xlfn.IFS(H34="created",O34*P34*(1-Q34/100)/12,H34="cancelled",-(O34*P34*(1-Q34/100))/12,H34="seats_change",(J34-I34)*P34*(1-Q34/100)/12,H34="price_change",(J34-I34)*O34*(1-Q34/100)/12,H34="plan_upgrade",(O34*(_xlfn.XLOOKUP(J34,$M:$M,$P:$P)-_xlfn.XLOOKUP(I34,$M:$M,$P:$P))*(1-Q34/100))/12,H34="plan_downgrade",(O34*(_xlfn.XLOOKUP(J34,$M:$M,$P:$P)-_xlfn.XLOOKUP(I34,$M:$M,$P:$P))*(1-Q34/100))/12,H34="discount_added",-(O34*P34*(J34-I34)/100)/12))} -> 450 | T34: =IF(H34<>"created",0,IF(COUNTIFS($C$1:C33,$C34,$H$1:H33,"created")=0,1,0)) -> 1 | U34: =IF(H34<>"cancelled",0,IF(COUNTIFS($C$2:$C$1002,$C34,$H$2:$H$1002,"created",$F$2:$F$1002,"<="&F34)-COUNTIFS($C$2:$C$1002,$C34,$H$2:$H$1002,"cancelled",$F$2:$F$1002,"<="&F34)=0,1,0)) -> 0 | V34: =IF(AND(H34="created",T34=0,COUNTIFS($C$2:$C$1002,$C34,$H$2:$H$1002,"cancelled",$F$2:$F$1002,"<"&F34)>0,COUNTIFS($C$2:$C$1002,$C34,$H$2:$H$1002,"created",$F$2:$F$1002,"<"&F34)-COUNTIFS($C$2:$C$1002,$C34,$H$2:$H$1002,"cancelled",$F$2:$F$1002,"<"&F34)=0),1,0) -> 0
A35: EVT034 | B35: SUB005 | C35: CUST005 | D35: Atlantic Media Corp | E35: Eastern Canada | F35: 45597 | G35: 45616 | H35: cancelled | I35: active | J35: churned | K35: status | L35: Price too high | M35: Analytics Starter | N35: Monthly | O35: 11 | P35: 45 | Q35: 0 | R35: {=_xlfn.IFS(H35="created", "New", H35="cancelled", "Churned", AND(H35="seats_change", J35 > I35), "Expansion", AND(H35="seats_change", J35 < I35), "Contraction", AND(H35="price_change", J35 > I35), "Expansion", AND(H35="price_change", J35 < I35), "Contraction", H35="plan_upgrade", "Expansion", H35="plan_downgrade", "Contraction", H35="discount_added", "Contraction")} -> Churned | S35: {=IF(N35="Monthly",_xlfn.IFS(H35="created",O35*P35*(1-Q35/100),H35="cancelled",-(O35*P35*(1-Q35/100)),H35="seats_change",(J35-I35)*P35*(1-Q35/100),H35="price_change",(J35-I35)*O35*(1-Q35/100),H35="discount_added",-(O35*P35*(J35-I35)/100),H35="plan_upgrade",O35*(_xlfn.XLOOKUP(J35,$M:$M,$P:$P)-_xlfn.XLOOKUP(I35,$M:$M,$P:$P))*(1-Q35/100),H35="plan_downgrade",O35*(_xlfn.XLOOKUP(J35,$M:$M,$P:$P)-_xlfn.XLOOKUP(I35,$M:$M,$P:$P))*(1-Q35/100)),_xlfn.IFS(H35="created",O35*P35*(1-Q35/100)/12,H35="cancelled",-(O35*P35*(1-Q35/100))/12,H35="seats_change",(J35-I35)*P35*(1-Q35/100)/12,H35="price_change",(J35-I35)*O35*(1-Q35/100)/12,H35="plan_upgrade",(O35*(_xlfn.XLOOKUP(J35,$M:$M,$P:$P)-_xlfn.XLOOKUP(I35,$M:$M,$P:$P))*(1-Q35/100))/12,H35="plan_downgrade",(O35*(_xlfn.XLOOKUP(J35,$M:$M,$P:$P)-_xlfn.XLOOKUP(I35,$M:$M,$P:$P))*(1-Q35/100))/12,H35="discount_added",-(O35*P35*(J35-I35)/100)/12))} -> -495 | T35: =IF(H35<>"created",0,IF(COUNTIFS($C$1:C34,$C35,$H$1:H34,"created")=0,1,0)) -> 0 | U35: =IF(H35<>"cancelled",0,IF(COUNTIFS($C$2:$C$1002,$C35,$H$2:$H$1002,"created",$F$2:$F$1002,"<="&F35)-COUNTIFS($C$2:$C$1002,$C35,$H$2:$H$1002,"cancelled",$F$2:$F$1002,"<="&F35)=0,1,0)) -> 1 | V35: =IF(AND(H35="created",T35=0,COUNTIFS($C$2:$C$1002,$C35,$H$2:$H$1002,"cancelled",$F$2:$F$1002,"<"&F35)>0,COUNTIFS($C$2:$C$1002,$C35,$H$2:$H$1002,"created",$F$2:$F$1002,"<"&F35)-COUNTIFS($C$2:$C$1002,$C35,$H$2:$H$1002,"cancelled",$F$2:$F$1002,"<"&F35)=0),1,0) -> 0
A36: EVT035 | B36: SUB024 | C36: CUST024 | D36: Western Retail Group | E36: Western Canada | F36: 45597 | G36: 45621 | H36: created | M36: Marketing Pro | N36: Monthly | O36: 31 | P36: 85 | Q36: 0 | R36: {=_xlfn.IFS(H36="created", "New", H36="cancelled", "Churned", AND(H36="seats_change", J36 > I36), "Expansion", AND(H36="seats_change", J36 < I36), "Contraction", AND(H36="price_change", J36 > I36), "Expansion", AND(H36="price_change", J36 < I36), "Contraction", H36="plan_upgrade", "Expansion", H36="plan_downgrade", "Contraction", H36="discount_added", "Contraction")} -> New | S36: {=IF(N36="Monthly",_xlfn.IFS(H36="created",O36*P36*(1-Q36/100),H36="cancelled",-(O36*P36*(1-Q36/100)),H36="seats_change",(J36-I36)*P36*(1-Q36/100),H36="price_change",(J36-I36)*O36*(1-Q36/100),H36="discount_added",-(O36*P36*(J36-I36)/100),H36="plan_upgrade",O36*(_xlfn.XLOOKUP(J36,$M:$M,$P:$P)-_xlfn.XLOOKUP(I36,$M:$M,$P:$P))*(1-Q36/100),H36="plan_downgrade",O36*(_xlfn.XLOOKUP(J36,$M:$M,$P:$P)-_xlfn.XLOOKUP(I36,$M:$M,$P:$P))*(1-Q36/100)),_xlfn.IFS(H36="created",O36*P36*(1-Q36/100)/12,H36="cancelled",-(O36*P36*(1-Q36/100))/12,H36="seats_change",(J36-I36)*P36*(1-Q36/100)/12,H36="price_change",(J36-I36)*O36*(1-Q36/100)/12,H36="plan_upgrade",(O36*(_xlfn.XLOOKUP(J36,$M:$M,$P:$P)-_xlfn.XLOOKUP(I36,$M:$M,$P:$P))*(1-Q36/100))/12,H36="plan_downgrade",(O36*(_xlfn.XLOOKUP(J36,$M:$M,$P:$P)-_xlfn.XLOOKUP(I36,$M:$M,$P:$P))*(1-Q36/100))/12,H36="discount_added",-(O36*P36*(J36-I36)/100)/12))} -> 2635 | T36: =IF(H36<>"created",0,IF(COUNTIFS($C$1:C35,$C36,$H$1:H35,"created")=0,1,0)) -> 1 | U36: =IF(H36<>"cancelled",0,IF(COUNTIFS($C$2:$C$1002,$C36,$H$2:$H$1002,"created",$F$2:$F$1002,"<="&F36)-COUNTIFS($C$2:$C$1002,$C36,$H$2:$H$1002,"cancelled",$F$2:$F$1002,"<="&F36)=0,1,0)) -> 0 | V36: =IF(AND(H36="created",T36=0,COUNTIFS($C$2:$C$1002,$C36,$H$2:$H$1002,"cancelled",$F$2:$F$1002,"<"&F36)>0,COUNTIFS($C$2:$C$1002,$C36,$H$2:$H$1002,"created",$F$2:$F$1002,"<"&F36)-COUNTIFS($C$2:$C$1002,$C36,$H$2:$H$1002,"cancelled",$F$2:$F$1002,"<"&F36)=0),1,0) -> 0
A37: EVT036 | B37: SUB025 | C37: CUST025 | D37: Montreal Manufacturing Pro | E37: Eastern Canada | F37: 45627 | G37: 45635 | H37: created | M37: Analytics Enterprise | N37: Annual | O37: 38 | P37: 2160 | Q37: 0 | R37: {=_xlfn.IFS(H37="created", "New", H37="cancelled", "Churned", AND(H37="seats_change", J37 > I37), "Expansion", AND(H37="seats_change", J37 < I37), "Contraction", AND(H37="price_change", J37 > I37), "Expansion", AND(H37="price_change", J37 < I37), "Contraction", H37="plan_upgrade", "Expansion", H37="plan_downgrade", "Contraction", H37="discount_added", "Contraction")} -> New | S37: {=IF(N37="Monthly",_xlfn.IFS(H37="created",O37*P37*(1-Q37/100),H37="cancelled",-(O37*P37*(1-Q37/100)),H37="seats_change",(J37-I37)*P37*(1-Q37/100),H37="price_change",(J37-I37)*O37*(1-Q37/100),H37="discount_added",-(O37*P37*(J37-I37)/100),H37="plan_upgrade",O37*(_xlfn.XLOOKUP(J37,$M:$M,$P:$P)-_xlfn.XLOOKUP(I37,$M:$M,$P:$P))*(1-Q37/100),H37="plan_downgrade",O37*(_xlfn.XLOOKUP(J37,$M:$M,$P:$P)-_xlfn.XLOOKUP(I37,$M:$M,$P:$P))*(1-Q37/100)),_xlfn.IFS(H37="created",O37*P37*(1-Q37/100)/12,H37="cancelled",-(O37*P37*(1-Q37/100))/12,H37="seats_change",(J37-I37)*P37*(1-Q37/100)/12,H37="price_change",(J37-I37)*O37*(1-Q37/100)/12,H37="plan_upgrade",(O37*(_xlfn.XLOOKUP(J37,$M:$M,$P:$P)-_xlfn.XLOOKUP(I37,$M:$M,$P:$P))*(1-Q37/100))/12,H37="plan_downgrade",(O37*(_xlfn.XLOOKUP(J37,$M:$M,$P:$P)-_xlfn.XLOOKUP(I37,$M:$M,$P:$P))*(1-Q37/100))/12,H37="discount_added",-(O37*P37*(J37-I37)/100)/12))} -> 6840 | T37: =IF(H37<>"created",0,IF(COUNTIFS($C$1:C36,$C37,$H$1:H36,"created")=0,1,0)) -> 1 | U37: =IF(H37<>"cancelled",0,IF(COUNTIFS($C$2:$C$1002,$C37,$H$2:$H$1002,"created",$F$2:$F$1002,"<="&F37)-COUNTIFS($C$2:$C$1002,$C37,$H$2:$H$1002,"cancelled",$F$2:$F$1002,"<="&F37)=0,1,0)) -> 0 | V37: =IF(AND(H37="created",T37=0,COUNTIFS($C$2:$C$1002,$C37,$H$2:$H$1002,"cancelled",$F$2:$F$1002,"<"&F37)>0,COUNTIFS($C$2:$C$1002,$C37,$H$2:$H$1002,"created",$F$2:$F$1002,"<"&F37)-COUNTIFS($C$2:$C$1002,$C37,$H$2:$H$1002,"cancelled",$F$2:$F$1002,"<"&F37)=0),1,0) -> 0
A38: EVT037 | B38: SUB056 | C38: CUST016 | D38: Quebec Manufacturing | E38: Eastern Canada | F38: 45627 | G38: 45638 | H38: created | M38: Marketing Pro | N38: Monthly | O38: 38 | P38: 85 | Q38: 0 | R38: {=_xlfn.IFS(H38="created", "New", H38="cancelled", "Churned", AND(H38="seats_change", J38 > I38), "Expansion", AND(H38="seats_change", J38 < I38), "Contraction", AND(H38="price_change", J38 > I38), "Expansion", AND(H38="price_change", J38 < I38), "Contraction", H38="plan_upgrade", "Expansion", H38="plan_downgrade", "Contraction", H38="discount_added", "Contraction")} -> New | S38: {=IF(N38="Monthly",_xlfn.IFS(H38="created",O38*P38*(1-Q38/100),H38="cancelled",-(O38*P38*(1-Q38/100)),H38="seats_change",(J38-I38)*P38*(1-Q38/100),H38="price_change",(J38-I38)*O38*(1-Q38/100),H38="discount_added",-(O38*P38*(J38-I38)/100),H38="plan_upgrade",O38*(_xlfn.XLOOKUP(J38,$M:$M,$P:$P)-_xlfn.XLOOKUP(I38,$M:$M,$P:$P))*(1-Q38/100),H38="plan_downgrade",O38*(_xlfn.XLOOKUP(J38,$M:$M,$P:$P)-_xlfn.XLOOKUP(I38,$M:$M,$P:$P))*(1-Q38/100)),_xlfn.IFS(H38="created",O38*P38*(1-Q38/100)/12,H38="cancelled",-(O38*P38*(1-Q38/100))/12,H38="seats_change",(J38-I38)*P38*(1-Q38/100)/12,H38="price_change",(J38-I38)*O38*(1-Q38/100)/12,H38="plan_upgrade",(O38*(_xlfn.XLOOKUP(J38,$M:$M,$P:$P)-_xlfn.XLOOKUP(I38,$M:$M,$P:$P))*(1-Q38/100))/12,H38="plan_downgrade",(O38*(_xlfn.XLOOKUP(J38,$M:$M,$P:$P)-_xlfn.XLOOKUP(I38,$M:$M,$P:$P))*(1-Q38/100))/12,H38="discount_added",-(O38*P38*(J38-I38)/100)/12))} -> 3230 | T38: =IF(H38<>"created",0,IF(COUNTIFS($C$1:C37,$C38,$H$1:H37,"created")=0,1,0)) -> 0 | U38: =IF(H38<>"cancelled",0,IF(COUNTIFS($C$2:$C$1002,$C38,$H$2:$H$1002,"created",$F$2:$F$1002,"<="&F38)-COUNTIFS($C$2:$C$1002,$C38,$H$2:$H$1002,"cancelled",$F$2:$F$1002,"<="&F38)=0,1,0)) -> 0 | V38: =IF(AND(H38="created",T38=0,COUNTIFS($C$2:$C$1002,$C38,$H$2:$H$1002,"cancelled",$F$2:$F$1002,"<"&F38)>0,COUNTIFS($C$2:$C$1002,$C38,$H$2:$H$1002,"created",$F$2:$F$1002,"<"&F38)-COUNTIFS($C$2:$C$1002,$C38,$H$2:$H$1002,"cancelled",$F$2:$F$1002,"<"&F38)=0),1,0) -> 0
A39: EVT038 | B39: SUB044 | C39: CUST009 | D39: West Coast Logistics | E39: Western Canada | F39: 45627 | G39: 45646 | H39: created | M39: Analytics Growth | N39: Monthly | O39: 35 | P39: 95 | Q39: 0 | R39: {=_xlfn.IFS(H39="created", "New", H39="cancelled", "Churned", AND(H39="seats_change", J39 > I39), "Expansion", AND(H39="seats_change", J39 < I39), "Contraction", AND(H39="price_change", J39 > I39), "Expansion", AND(H39="price_change", J39 < I39), "Contraction", H39="plan_upgrade", "Expansion", H39="plan_downgrade", "Contraction", H39="discount_added", "Contraction")} -> New | S39: {=IF(N39="Monthly",_xlfn.IFS(H39="created",O39*P39*(1-Q39/100),H39="cancelled",-(O39*P39*(1-Q39/100)),H39="seats_change",(J39-I39)*P39*(1-Q39/100),H39="price_change",(J39-I39)*O39*(1-Q39/100),H39="discount_added",-(O39*P39*(J39-I39)/100),H39="plan_upgrade",O39*(_xlfn.XLOOKUP(J39,$M:$M,$P:$P)-_xlfn.XLOOKUP(I39,$M:$M,$P:$P))*(1-Q39/100),H39="plan_downgrade",O39*(_xlfn.XLOOKUP(J39,$M:$M,$P:$P)-_xlfn.XLOOKUP(I39,$M:$M,$P:$P))*(1-Q39/100)),_xlfn.IFS(H39="created",O39*P39*(1-Q39/100)/12,H39="cancelled",-(O39*P39*(1-Q39/100))/12,H39="seats_change",(J39-I39)*P39*(1-Q39/100)/12,H39="price_change",(J39-I39)*O39*(1-Q39/100)/12,H39="plan_upgrade",(O39*(_xlfn.XLOOKUP(J39,$M:$M,$P:$P)-_xlfn.XLOOKUP(I39,$M:$M,$P:$P))*(1-Q39/100))/12,H39="plan_downgrade",(O39*(_xlfn.XLOOKUP(J39,$M:$M,$P:$P)-_xlfn.XLOOKUP(I39,$M:$M,$P:$P))*(1-Q39/100))/12,H39="discount_added",-(O39*P39*(J39-I39)/100)/12))} -> 3325 | T39: =IF(H39<>"created",0,IF(COUNTIFS($C$1:C38,$C39,$H$1:H38,"created")=0,1,0)) -> 0 | U39: =IF(H39<>"cancelled",0,IF(COUNTIFS($C$2:$C$1002,$C39,$H$2:$H$1002,"created",$F$2:$F$1002,"<="&F39)-COUNTIFS($C$2:$C$1002,$C39,$H$2:$H$1002,"cancelled",$F$2:$F$1002,"<="&F39)=0,1,0)) -> 0 | V39: =IF(AND(H39="created",T39=0,COUNTIFS($C$2:$C$1002,$C39,$H$2:$H$1002,"cancelled",$F$2:$F$1002,"<"&F39)>0,COUNTIFS($C$2:$C$1002,$C39,$H$2:$H$1002,"created",$F$2:$F$1002,"<"&F39)-COUNTIFS($C$2:$C$1002,$C39,$H$2:$H$1002,"cancelled",$F$2:$F$1002,"<"&F39)=0),1,0) -> 0
A40: EVT039 | B40: SUB008 | C40: CUST008 | D40: Quantum Education Platform | E40: Eastern Canada | F40: 45627 | G40: 45648 | H40: cancelled | I40: active | J40: churned | K40: status | L40: Price too high | M40: Analytics Growth | N40: Monthly | O40: 22 | P40: 95 | Q40: 0 | R40: {=_xlfn.IFS(H40="created", "New", H40="cancelled", "Churned", AND(H40="seats_change", J40 > I40), "Expansion", AND(H40="seats_change", J40 < I40), "Contraction", AND(H40="price_change", J40 > I40), "Expansion", AND(H40="price_change", J40 < I40), "Contraction", H40="plan_upgrade", "Expansion", H40="plan_downgrade", "Contraction", H40="discount_added", "Contraction")} -> Churned | S40: {=IF(N40="Monthly",_xlfn.IFS(H40="created",O40*P40*(1-Q40/100),H40="cancelled",-(O40*P40*(1-Q40/100)),H40="seats_change",(J40-I40)*P40*(1-Q40/100),H40="price_change",(J40-I40)*O40*(1-Q40/100),H40="discount_added",-(O40*P40*(J40-I40)/100),H40="plan_upgrade",O40*(_xlfn.XLOOKUP(J40,$M:$M,$P:$P)-_xlfn.XLOOKUP(I40,$M:$M,$P:$P))*(1-Q40/100),H40="plan_downgrade",O40*(_xlfn.XLOOKUP(J40,$M:$M,$P:$P)-_xlfn.XLOOKUP(I40,$M:$M,$P:$P))*(1-Q40/100)),_xlfn.IFS(H40="created",O40*P40*(1-Q40/100)/12,H40="cancelled",-(O40*P40*(1-Q40/100))/12,H40="seats_change",(J40-I40)*P40*(1-Q40/100)/12,H40="price_change",(J40-I40)*O40*(1-Q40/100)/12,H40="plan_upgrade",(O40*(_xlfn.XLOOKUP(J40,$M:$M,$P:$P)-_xlfn.XLOOKUP(I40,$M:$M,$P:$P))*(1-Q40/100))/12,H40="plan_downgrade",(O40*(_xlfn.XLOOKUP(J40,$M:$M,$P:$P)-_xlfn.XLOOKUP(I40,$M:$M,$P:$P))*(1-Q40/100))/12,H40="discount_added",-(O40*P40*(J40-I40)/100)/12))} -> -2090 | T40: =IF(H40<>"created",0,IF(COUNTIFS($C$1:C39,$C40,$H$1:H39,"created")=0,1,0)) -> 0 | U40: =IF(H40<>"cancelled",0,IF(COUNTIFS($C$2:$C$1002,$C40,$H$2:$H$1002,"created",$F$2:$F$1002,"<="&F40)-COUNTIFS($C$2:$C$1002,$C40,$H$2:$H$1002,"cancelled",$F$2:$F$1002,"<="&F40)=0,1,0)) -> 0 | V40: =IF(AND(H40="created",T40=0,COUNTIFS($C$2:$C$1002,$C40,$H$2:$H$1002,"cancelled",$F$2:$F$1002,"<"&F40)>0,COUNTIFS($C$2:$C$1002,$C40,$H$2:$H$1002,"created",$F$2:$F$1002,"<"&F40)-COUNTIFS($C$2:$C$1002,$C40,$H$2:$H$1002,"cancelled",$F$2:$F$1002,"<"&F40)=0),1,0) -> 0
A41: EVT040 | B41: SUB026 | C41: CUST026 | D41: Ontario Education Connect | E41: Eastern Canada | F41: 45627 | G41: 45649 | H41: created | M41: Analytics Growth | N41: Monthly | O41: 16 | P41: 95 | Q41: 0 | R41: {=_xlfn.IFS(H41="created", "New", H41="cancelled", "Churned", AND(H41="seats_change", J41 > I41), "Expansion", AND(H41="seats_change", J41 < I41), "Contraction", AND(H41="price_change", J41 > I41), "Expansion", AND(H41="price_change", J41 < I41), "Contraction", H41="plan_upgrade", "Expansion", H41="plan_downgrade", "Contraction", H41="discount_added", "Contraction")} -> New | S41: {=IF(N41="Monthly",_xlfn.IFS(H41="created",O41*P41*(1-Q41/100),H41="cancelled",-(O41*P41*(1-Q41/100)),H41="seats_change",(J41-I41)*P41*(1-Q41/100),H41="price_change",(J41-I41)*O41*(1-Q41/100),H41="discount_added",-(O41*P41*(J41-I41)/100),H41="plan_upgrade",O41*(_xlfn.XLOOKUP(J41,$M:$M,$P:$P)-_xlfn.XLOOKUP(I41,$M:$M,$P:$P))*(1-Q41/100),H41="plan_downgrade",O41*(_xlfn.XLOOKUP(J41,$M:$M,$P:$P)-_xlfn.XLOOKUP(I41,$M:$M,$P:$P))*(1-Q41/100)),_xlfn.IFS(H41="created",O41*P41*(1-Q41/100)/12,H41="cancelled",-(O41*P41*(1-Q41/100))/12,H41="seats_change",(J41-I41)*P41*(1-Q41/100)/12,H41="price_change",(J41-I41)*O41*(1-Q41/100)/12,H41="plan_upgrade",(O41*(_xlfn.XLOOKUP(J41,$M:$M,$P:$P)-_xlfn.XLOOKUP(I41,$M:$M,$P:$P))*(1-Q41/100))/12,H41="plan_downgrade",(O41*(_xlfn.XLOOKUP(J41,$M:$M,$P:$P)-_xlfn.XLOOKUP(I41,$M:$M,$P:$P))*(1-Q41/100))/12,H41="discount_added",-(O41*P41*(J41-I41)/100)/12))} -> 1520 | T41: =IF(H41<>"created",0,IF(COUNTIFS($C$1:C40,$C41,$H$1:H40,"created")=0,1,0)) -> 1 | U41: =IF(H41<>"cancelled",0,IF(COUNTIFS($C$2:$C$1002,$C41,$H$2:$H$1002,"created",$F$2:$F$1002,"<="&F41)-COUNTIFS($C$2:$C$1002,$C41,$H$2:$H$1002,"cancelled",$F$2:$F$1002,"<="&F41)=0,1,0)) -> 0 | V41: =IF(AND(H41="created",T41=0,COUNTIFS($C$2:$C$1002,$C41,$H$2:$H$1002,"cancelled",$F$2:$F$1002,"<"&F41)>0,COUNTIFS($C$2:$C$1002,$C41,$H$2:$H$1002,"created",$F$2:$F$1002,"<"&F41)-COUNTIFS($C$2:$C$1002,$C41,$H$2:$H$1002,"cancelled",$F$2:$F$1002,"<"&F41)=0),1,0) -> 0
A42: EVT041 | B42: SUB027 | C42: CUST027 | D42: Pacific Finance Corp | E42: Western Canada | F42: 45658 | G42: 45663 | H42: created | M42: Sales Hub | N42: Monthly | O42: 28 | P42: 110 | Q42: 0 | R42: {=_xlfn.IFS(H42="created", "New", H42="cancelled", "Churned", AND(H42="seats_change", J42 > I42), "Expansion", AND(H42="seats_change", J42 < I42), "Contraction", AND(H42="price_change", J42 > I42), "Expansion", AND(H42="price_change", J42 < I42), "Contraction", H42="plan_upgrade", "Expansion", H42="plan_downgrade", "Contraction", H42="discount_added", "Contraction")} -> New | S42: {=IF(N42="Monthly",_xlfn.IFS(H42="created",O42*P42*(1-Q42/100),H42="cancelled",-(O42*P42*(1-Q42/100)),H42="seats_change",(J42-I42)*P42*(1-Q42/100),H42="price_change",(J42-I42)*O42*(1-Q42/100),H42="discount_added",-(O42*P42*(J42-I42)/100),H42="plan_upgrade",O42*(_xlfn.XLOOKUP(J42,$M:$M,$P:$P)-_xlfn.XLOOKUP(I42,$M:$M,$P:$P))*(1-Q42/100),H42="plan_downgrade",O42*(_xlfn.XLOOKUP(J42,$M:$M,$P:$P)-_xlfn.XLOOKUP(I42,$M:$M,$P:$P))*(1-Q42/100)),_xlfn.IFS(H42="created",O42*P42*(1-Q42/100)/12,H42="cancelled",-(O42*P42*(1-Q42/100))/12,H42="seats_change",(J42-I42)*P42*(1-Q42/100)/12,H42="price_change",(J42-I42)*O42*(1-Q42/100)/12,H42="plan_upgrade",(O42*(_xlfn.XLOOKUP(J42,$M:$M,$P:$P)-_xlfn.XLOOKUP(I42,$M:$M,$P:$P))*(1-Q42/100))/12,H42="plan_downgrade",(O42*(_xlfn.XLOOKUP(J42,$M:$M,$P:$P)-_xlfn.XLOOKUP(I42,$M:$M,$P:$P))*(1-Q42/100))/12,H42="discount_added",-(O42*P42*(J42-I42)/100)/12))} -> 3080 | T42: =IF(H42<>"created",0,IF(COUNTIFS($C$1:C41,$C42,$H$1:H41,"created")=0,1,0)) -> 1 | U42: =IF(H42<>"cancelled",0,IF(COUNTIFS($C$2:$C$1002,$C42,$H$2:$H$1002,"created",$F$2:$F$1002,"<="&F42)-COUNTIFS($C$2:$C$1002,$C42,$H$2:$H$1002,"cancelled",$F$2:$F$1002,"<="&F42)=0,1,0)) -> 0 | V42: =IF(AND(H42="created",T42=0,COUNTIFS($C$2:$C$1002,$C42,$H$2:$H$1002,"cancelled",$F$2:$F$1002,"<"&F42)>0,COUNTIFS($C$2:$C$1002,$C42,$H$2:$H$1002,"created",$F$2:$F$1002,"<"&F42)-COUNTIFS($C$2:$C$1002,$C42,$H$2:$H$1002,"cancelled",$F$2:$F$1002,"<"&F42)=0),1,0) -> 0
A43: EVT042 | B43: SUB014 | C43: CUST014 | D43: Toronto Media Group | E43: Eastern Canada | F43: 45658 | G43: 45665 | H43: price_change | I43: 80 | J43: 85 | K43: price_per_seat | L43: Annual price increase applied at renewal | M43: Marketing Pro | N43: Monthly | O43: 28 | P43: 85 | Q43: 0 | R43: {=_xlfn.IFS(H43="created", "New", H43="cancelled", "Churned", AND(H43="seats_change", J43 > I43), "Expansion", AND(H43="seats_change", J43 < I43), "Contraction", AND(H43="price_change", J43 > I43), "Expansion", AND(H43="price_change", J43 < I43), "Contraction", H43="plan_upgrade", "Expansion", H43="plan_downgrade", "Contraction", H43="discount_added", "Contraction")} -> Expansion | S43: {=IF(N43="Monthly",_xlfn.IFS(H43="created",O43*P43*(1-Q43/100),H43="cancelled",-(O43*P43*(1-Q43/100)),H43="seats_change",(J43-I43)*P43*(1-Q43/100),H43="price_change",(J43-I43)*O43*(1-Q43/100),H43="discount_added",-(O43*P43*(J43-I43)/100),H43="plan_upgrade",O43*(_xlfn.XLOOKUP(J43,$M:$M,$P:$P)-_xlfn.XLOOKUP(I43,$M:$M,$P:$P))*(1-Q43/100),H43="plan_downgrade",O43*(_xlfn.XLOOKUP(J43,$M:$M,$P:$P)-_xlfn.XLOOKUP(I43,$M:$M,$P:$P))*(1-Q43/100)),_xlfn.IFS(H43="created",O43*P43*(1-Q43/100)/12,H43="cancelled",-(O43*P43*(1-Q43/100))/12,H43="seats_change",(J43-I43)*P43*(1-Q43/100)/12,H43="price_change",(J43-I43)*O43*(1-Q43/100)/12,H43="plan_upgrade",(O43*(_xlfn.XLOOKUP(J43,$M:$M,$P:$P)-_xlfn.XLOOKUP(I43,$M:$M,$P:$P))*(1-Q43/100))/12,H43="plan_downgrade",(O43*(_xlfn.XLOOKUP(J43,$M:$M,$P:$P)-_xlfn.XLOOKUP(I43,$M:$M,$P:$P))*(1-Q43/100))/12,H43="discount_added",-(O43*P43*(J43-I43)/100)/12))} -> 140 | T43: =IF(H43<>"created",0,IF(COUNTIFS($C$1:C42,$C43,$H$1:H42,"created")=0,1,0)) -> 0 | U43: =IF(H43<>"cancelled",0,IF(COUNTIFS($C$2:$C$1002,$C43,$H$2:$H$1002,"created",$F$2:$F$1002,"<="&F43)-COUNTIFS($C$2:$C$1002,$C43,$H$2:$H$1002,"cancelled",$F$2:$F$1002,"<="&F43)=0,1,0)) -> 0 | V43: =IF(AND(H43="created",T43=0,COUNTIFS($C$2:$C$1002,$C43,$H$2:$H$1002,"cancelled",$F$2:$F$1002,"<"&F43)>0,COUNTIFS($C$2:$C$1002,$C43,$H$2:$H$1002,"created",$F$2:$F$1002,"<"&F43)-COUNTIFS($C$2:$C$1002,$C43,$H$2:$H$1002,"cancelled",$F$2:$F$1002,"<"&F43)=0),1,0) -> 0
A44: EVT043 | B44: SUB013 | C44: CUST013 | D44: Alberta Tech Innovators | E44: Western Canada | F44: 45658 | G44: 45672 | H44: cancelled | I44: active | J44: churned | K44: status | L44: Switched to competitor | M44: Analytics Starter | N44: Monthly | O44: 10 | P44: 45 | Q44: 0 | R44: {=_xlfn.IFS(H44="created", "New", H44="cancelled", "Churned", AND(H44="seats_change", J44 > I44), "Expansion", AND(H44="seats_change", J44 < I44), "Contraction", AND(H44="price_change", J44 > I44), "Expansion", AND(H44="price_change", J44 < I44), "Contraction", H44="plan_upgrade", "Expansion", H44="plan_downgrade", "Contraction", H44="discount_added", "Contraction")} -> Churned | S44: {=IF(N44="Monthly",_xlfn.IFS(H44="created",O44*P44*(1-Q44/100),H44="cancelled",-(O44*P44*(1-Q44/100)),H44="seats_change",(J44-I44)*P44*(1-Q44/100),H44="price_change",(J44-I44)*O44*(1-Q44/100),H44="discount_added",-(O44*P44*(J44-I44)/100),H44="plan_upgrade",O44*(_xlfn.XLOOKUP(J44,$M:$M,$P:$P)-_xlfn.XLOOKUP(I44,$M:$M,$P:$P))*(1-Q44/100),H44="plan_downgrade",O44*(_xlfn.XLOOKUP(J44,$M:$M,$P:$P)-_xlfn.XLOOKUP(I44,$M:$M,$P:$P))*(1-Q44/100)),_xlfn.IFS(H44="created",O44*P44*(1-Q44/100)/12,H44="cancelled",-(O44*P44*(1-Q44/100))/12,H44="seats_change",(J44-I44)*P44*(1-Q44/100)/12,H44="price_change",(J44-I44)*O44*(1-Q44/100)/12,H44="plan_upgrade",(O44*(_xlfn.XLOOKUP(J44,$M:$M,$P:$P)-_xlfn.XLOOKUP(I44,$M:$M,$P:$P))*(1-Q44/100))/12,H44="plan_downgrade",(O44*(_xlfn.XLOOKUP(J44,$M:$M,$P:$P)-_xlfn.XLOOKUP(I44,$M:$M,$P:$P))*(1-Q44/100))/12,H44="discount_added",-(O44*P44*(J44-I44)/100)/12))} -> -450 | T44: =IF(H44<>"created",0,IF(COUNTIFS($C$1:C43,$C44,$H$1:H43,"created")=0,1,0)) -> 0 | U44: =IF(H44<>"cancelled",0,IF(COUNTIFS($C$2:$C$1002,$C44,$H$2:$H$1002,"created",$F$2:$F$1002,"<="&F44)-COUNTIFS($C$2:$C$1002,$C44,$H$2:$H$1002,"cancelled",$F$2:$F$1002,"<="&F44)=0,1,0)) -> 1 | V44: =IF(AND(H44="created",T44=0,COUNTIFS($C$2:$C$1002,$C44,$H$2:$H$1002,"cancelled",$F$2:$F$1002,"<"&F44)>0,COUNTIFS($C$2:$C$1002,$C44,$H$2:$H$1002,"created",$F$2:$F$1002,"<"&F44)-COUNTIFS($C$2:$C$1002,$C44,$H$2:$H$1002,"cancelled",$F$2:$F$1002,"<"&F44)=0),1,0) -> 0
A45: EVT044 | B45: SUB028 | C45: CUST028 | D45: Prairie SaaS Innovations | E45: Central Canada | F45: 45658 | G45: 45677 | H45: created | M45: Analytics Starter | N45: Monthly | O45: 15 | P45: 45 | Q45: 0 | R45: {=_xlfn.IFS(H45="created", "New", H45="cancelled", "Churned", AND(H45="seats_change", J45 > I45), "Expansion", AND(H45="seats_change", J45 < I45), "Contraction", AND(H45="price_change", J45 > I45), "Expansion", AND(H45="price_change", J45 < I45), "Contraction", H45="plan_upgrade", "Expansion", H45="plan_downgrade", "Contraction", H45="discount_added", "Contraction")} -> New | S45: {=IF(N45="Monthly",_xlfn.IFS(H45="created",O45*P45*(1-Q45/100),H45="cancelled",-(O45*P45*(1-Q45/100)),H45="seats_change",(J45-I45)*P45*(1-Q45/100),H45="price_change",(J45-I45)*O45*(1-Q45/100),H45="discount_added",-(O45*P45*(J45-I45)/100),H45="plan_upgrade",O45*(_xlfn.XLOOKUP(J45,$M:$M,$P:$P)-_xlfn.XLOOKUP(I45,$M:$M,$P:$P))*(1-Q45/100),H45="plan_downgrade",O45*(_xlfn.XLOOKUP(J45,$M:$M,$P:$P)-_xlfn.XLOOKUP(I45,$M:$M,$P:$P))*(1-Q45/100)),_xlfn.IFS(H45="created",O45*P45*(1-Q45/100)/12,H45="cancelled",-(O45*P45*(1-Q45/100))/12,H45="seats_change",(J45-I45)*P45*(1-Q45/100)/12,H45="price_change",(J45-I45)*O45*(1-Q45/100)/12,H45="plan_upgrade",(O45*(_xlfn.XLOOKUP(J45,$M:$M,$P:$P)-_xlfn.XLOOKUP(I45,$M:$M,$P:$P))*(1-Q45/100))/12,H45="plan_downgrade",(O45*(_xlfn.XLOOKUP(J45,$M:$M,$P:$P)-_xlfn.XLOOKUP(I45,$M:$M,$P:$P))*(1-Q45/100))/12,H45="discount_added",-(O45*P45*(J45-I45)/100)/12))} -> 675 | T45: =IF(H45<>"created",0,IF(COUNTIFS($C$1:C44,$C45,$H$1:H44,"created")=0,1,0)) -> 1 | U45: =IF(H45<>"cancelled",0,IF(COUNTIFS($C$2:$C$1002,$C45,$H$2:$H$1002,"created",$F$2:$F$1002,"<="&F45)-COUNTIFS($C$2:$C$1002,$C45,$H$2:$H$1002,"cancelled",$F$2:$F$1002,"<="&F45)=0,1,0)) -> 0 | V45: =IF(AND(H45="created",T45=0,COUNTIFS($C$2:$C$1002,$C45,$H$2:$H$1002,"cancelled",$F$2:$F$1002,"<"&F45)>0,COUNTIFS($C$2:$C$1002,$C45,$H$2:$H$1002,"created",$F$2:$F$1002,"<"&F45)-COUNTIFS($C$2:$C$1002,$C45,$H$2:$H$1002,"cancelled",$F$2:$F$1002,"<"&F45)=0),1,0) -> 0
A46: EVT045 | B46: SUB054 | C46: CUST002 | D46: Pacific Analytics Inc | E46: Western Canada | F46: 45658 | G46: 45679 | H46: created | M46: Analytics Growth | N46: Annual | O46: 22 | P46: 1140 | Q46: 5 | R46: {=_xlfn.IFS(H46="created", "New", H46="cancelled", "Churned", AND(H46="seats_change", J46 > I46), "Expansion", AND(H46="seats_change", J46 < I46), "Contraction", AND(H46="price_change", J46 > I46), "Expansion", AND(H46="price_change", J46 < I46), "Contraction", H46="plan_upgrade", "Expansion", H46="plan_downgrade", "Contraction", H46="discount_added", "Contraction")} -> New | S46: {=IF(N46="Monthly",_xlfn.IFS(H46="created",O46*P46*(1-Q46/100),H46="cancelled",-(O46*P46*(1-Q46/100)),H46="seats_change",(J46-I46)*P46*(1-Q46/100),H46="price_change",(J46-I46)*O46*(1-Q46/100),H46="discount_added",-(O46*P46*(J46-I46)/100),H46="plan_upgrade",O46*(_xlfn.XLOOKUP(J46,$M:$M,$P:$P)-_xlfn.XLOOKUP(I46,$M:$M,$P:$P))*(1-Q46/100),H46="plan_downgrade",O46*(_xlfn.XLOOKUP(J46,$M:$M,$P:$P)-_xlfn.XLOOKUP(I46,$M:$M,$P:$P))*(1-Q46/100)),_xlfn.IFS(H46="created",O46*P46*(1-Q46/100)/12,H46="cancelled",-(O46*P46*(1-Q46/100))/12,H46="seats_change",(J46-I46)*P46*(1-Q46/100)/12,H46="price_change",(J46-I46)*O46*(1-Q46/100)/12,H46="plan_upgrade",(O46*(_xlfn.XLOOKUP(J46,$M:$M,$P:$P)-_xlfn.XLOOKUP(I46,$M:$M,$P:$P))*(1-Q46/100))/12,H46="plan_downgrade",(O46*(_xlfn.XLOOKUP(J46,$M:$M,$P:$P)-_xlfn.XLOOKUP(I46,$M:$M,$P:$P))*(1-Q46/100))/12,H46="discount_added",-(O46*P46*(J46-I46)/100)/12))} -> 1985.5 | T46: =IF(H46<>"created",0,IF(COUNTIFS($C$1:C45,$C46,$H$1:H45,"created")=0,1,0)) -> 0 | U46: =IF(H46<>"cancelled",0,IF(COUNTIFS($C$2:$C$1002,$C46,$H$2:$H$1002,"created",$F$2:$F$1002,"<="&F46)-COUNTIFS($C$2:$C$1002,$C46,$H$2:$H$1002,"cancelled",$F$2:$F$1002,"<="&F46)=0,1,0)) -> 0 | V46: =IF(AND(H46="created",T46=0,COUNTIFS($C$2:$C$1002,$C46,$H$2:$H$1002,"cancelled",$F$2:$F$1002,"<"&F46)>0,COUNTIFS($C$2:$C$1002,$C46,$H$2:$H$1002,"created",$F$2:$F$1002,"<"&F46)-COUNTIFS($C$2:$C$1002,$C46,$H$2:$H$1002,"cancelled",$F$2:$F$1002,"<"&F46)=0),1,0) -> 0
A47: EVT046 | B47: SUB057 | C47: CUST021 | D47: Calgary Commerce Solutions | E47: Western Canada | F47: 45658 | G47: 45685 | H47: created | M47: Platform Suite | N47: Monthly | O47: 28 | P47: 150 | Q47: 0 | R47: {=_xlfn.IFS(H47="created", "New", H47="cancelled", "Churned", AND(H47="seats_change", J47 > I47), "Expansion", AND(H47="seats_change", J47 < I47), "Contraction", AND(H47="price_change", J47 > I47), "Expansion", AND(H47="price_change", J47 < I47), "Contraction", H47="plan_upgrade", "Expansion", H47="plan_downgrade", "Contraction", H47="discount_added", "Contraction")} -> New | S47: {=IF(N47="Monthly",_xlfn.IFS(H47="created",O47*P47*(1-Q47/100),H47="cancelled",-(O47*P47*(1-Q47/100)),H47="seats_change",(J47-I47)*P47*(1-Q47/100),H47="price_change",(J47-I47)*O47*(1-Q47/100),H47="discount_added",-(O47*P47*(J47-I47)/100),H47="plan_upgrade",O47*(_xlfn.XLOOKUP(J47,$M:$M,$P:$P)-_xlfn.XLOOKUP(I47,$M:$M,$P:$P))*(1-Q47/100),H47="plan_downgrade",O47*(_xlfn.XLOOKUP(J47,$M:$M,$P:$P)-_xlfn.XLOOKUP(I47,$M:$M,$P:$P))*(1-Q47/100)),_xlfn.IFS(H47="created",O47*P47*(1-Q47/100)/12,H47="cancelled",-(O47*P47*(1-Q47/100))/12,H47="seats_change",(J47-I47)*P47*(1-Q47/100)/12,H47="price_change",(J47-I47)*O47*(1-Q47/100)/12,H47="plan_upgrade",(O47*(_xlfn.XLOOKUP(J47,$M:$M,$P:$P)-_xlfn.XLOOKUP(I47,$M:$M,$P:$P))*(1-Q47/100))/12,H47="plan_downgrade",(O47*(_xlfn.XLOOKUP(J47,$M:$M,$P:$P)-_xlfn.XLOOKUP(I47,$M:$M,$P:$P))*(1-Q47/100))/12,H47="discount_added",-(O47*P47*(J47-I47)/100)/12))} -> 4200 | T47: =IF(H47<>"created",0,IF(COUNTIFS($C$1:C46,$C47,$H$1:H46,"created")=0,1,0)) -> 0 | U47: =IF(H47<>"cancelled",0,IF(COUNTIFS($C$2:$C$1002,$C47,$H$2:$H$1002,"created",$F$2:$F$1002,"<="&F47)-COUNTIFS($C$2:$C$1002,$C47,$H$2:$H$1002,"cancelled",$F$2:$F$1002,"<="&F47)=0,1,0)) -> 0 | V47: =IF(AND(H47="created",T47=0,COUNTIFS($C$2:$C$1002,$C47,$H$2:$H$1002,"cancelled",$F$2:$F$1002,"<"&F47)>0,COUNTIFS($C$2:$C$1002,$C47,$H$2:$H$1002,"created",$F$2:$F$1002,"<"&F47)-COUNTIFS($C$2:$C$1002,$C47,$H$2:$H$1002,"cancelled",$F$2:$F$1002,"<"&F47)=0),1,0) -> 0
A48: EVT047 | B48: SUB029 | C48: CUST029 | D48: Halifax Healthcare Tech | E48: Eastern Canada | F48: 45689 | G48: 45691 | H48: created | M48: Marketing Pro | N48: Monthly | O48: 22 | P48: 85 | Q48: 0 | R48: {=_xlfn.IFS(H48="created", "New", H48="cancelled", "Churned", AND(H48="seats_change", J48 > I48), "Expansion", AND(H48="seats_change", J48 < I48), "Contraction", AND(H48="price_change", J48 > I48), "Expansion", AND(H48="price_change", J48 < I48), "Contraction", H48="plan_upgrade", "Expansion", H48="plan_downgrade", "Contraction", H48="discount_added", "Contraction")} -> New | S48: {=IF(N48="Monthly",_xlfn.IFS(H48="created",O48*P48*(1-Q48/100),H48="cancelled",-(O48*P48*(1-Q48/100)),H48="seats_change",(J48-I48)*P48*(1-Q48/100),H48="price_change",(J48-I48)*O48*(1-Q48/100),H48="discount_added",-(O48*P48*(J48-I48)/100),H48="plan_upgrade",O48*(_xlfn.XLOOKUP(J48,$M:$M,$P:$P)-_xlfn.XLOOKUP(I48,$M:$M,$P:$P))*(1-Q48/100),H48="plan_downgrade",O48*(_xlfn.XLOOKUP(J48,$M:$M,$P:$P)-_xlfn.XLOOKUP(I48,$M:$M,$P:$P))*(1-Q48/100)),_xlfn.IFS(H48="created",O48*P48*(1-Q48/100)/12,H48="cancelled",-(O48*P48*(1-Q48/100))/12,H48="seats_change",(J48-I48)*P48*(1-Q48/100)/12,H48="price_change",(J48-I48)*O48*(1-Q48/100)/12,H48="plan_upgrade",(O48*(_xlfn.XLOOKUP(J48,$M:$M,$P:$P)-_xlfn.XLOOKUP(I48,$M:$M,$P:$P))*(1-Q48/100))/12,H48="plan_downgrade",(O48*(_xlfn.XLOOKUP(J48,$M:$M,$P:$P)-_xlfn.XLOOKUP(I48,$M:$M,$P:$P))*(1-Q48/100))/12,H48="discount_added",-(O48*P48*(J48-I48)/100)/12))} -> 1870 | T48: =IF(H48<>"created",0,IF(COUNTIFS($C$1:C47,$C48,$H$1:H47,"created")=0,1,0)) -> 1 | U48: =IF(H48<>"cancelled",0,IF(COUNTIFS($C$2:$C$1002,$C48,$H$2:$H$1002,"created",$F$2:$F$1002,"<="&F48)-COUNTIFS($C$2:$C$1002,$C48,$H$2:$H$1002,"cancelled",$F$2:$F$1002,"<="&F48)=0,1,0)) -> 0 | V48: =IF(AND(H48="created",T48=0,COUNTIFS($C$2:$C$1002,$C48,$H$2:$H$1002,"cancelled",$F$2:$F$1002,"<"&F48)>0,COUNTIFS($C$2:$C$1002,$C48,$H$2:$H$1002,"created",$F$2:$F$1002,"<"&F48)-COUNTIFS($C$2:$C$1002,$C48,$H$2:$H$1002,"cancelled",$F$2:$F$1002,"<"&F48)=0),1,0) -> 0
A49: EVT048 | B49: SUB045 | C49: CUST010 | D49: Montreal Finance Hub | E49: Eastern Canada | F49: 45689 | G49: 45696 | H49: created | M49: Marketing Pro | N49: Monthly | O49: 13 | P49: 85 | Q49: 0 | R49: {=_xlfn.IFS(H49="created", "New", H49="cancelled", "Churned", AND(H49="seats_change", J49 > I49), "Expansion", AND(H49="seats_change", J49 < I49), "Contraction", AND(H49="price_change", J49 > I49), "Expansion", AND(H49="price_change", J49 < I49), "Contraction", H49="plan_upgrade", "Expansion", H49="plan_downgrade", "Contraction", H49="discount_added", "Contraction")} -> New | S49: {=IF(N49="Monthly",_xlfn.IFS(H49="created",O49*P49*(1-Q49/100),H49="cancelled",-(O49*P49*(1-Q49/100)),H49="seats_change",(J49-I49)*P49*(1-Q49/100),H49="price_change",(J49-I49)*O49*(1-Q49/100),H49="discount_added",-(O49*P49*(J49-I49)/100),H49="plan_upgrade",O49*(_xlfn.XLOOKUP(J49,$M:$M,$P:$P)-_xlfn.XLOOKUP(I49,$M:$M,$P:$P))*(1-Q49/100),H49="plan_downgrade",O49*(_xlfn.XLOOKUP(J49,$M:$M,$P:$P)-_xlfn.XLOOKUP(I49,$M:$M,$P:$P))*(1-Q49/100)),_xlfn.IFS(H49="created",O49*P49*(1-Q49/100)/12,H49="cancelled",-(O49*P49*(1-Q49/100))/12,H49="seats_change",(J49-I49)*P49*(1-Q49/100)/12,H49="price_change",(J49-I49)*O49*(1-Q49/100)/12,H49="plan_upgrade",(O49*(_xlfn.XLOOKUP(J49,$M:$M,$P:$P)-_xlfn.XLOOKUP(I49,$M:$M,$P:$P))*(1-Q49/100))/12,H49="plan_downgrade",(O49*(_xlfn.XLOOKUP(J49,$M:$M,$P:$P)-_xlfn.XLOOKUP(I49,$M:$M,$P:$P))*(1-Q49/100))/12,H49="discount_added",-(O49*P49*(J49-I49)/100)/12))} -> 1105 | T49: =IF(H49<>"created",0,IF(COUNTIFS($C$1:C48,$C49,$H$1:H48,"created")=0,1,0)) -> 0 | U49: =IF(H49<>"cancelled",0,IF(COUNTIFS($C$2:$C$1002,$C49,$H$2:$H$1002,"created",$F$2:$F$1002,"<="&F49)-COUNTIFS($C$2:$C$1002,$C49,$H$2:$H$1002,"cancelled",$F$2:$F$1002,"<="&F49)=0,1,0)) -> 0 | V49: =IF(AND(H49="created",T49=0,COUNTIFS($C$2:$C$1002,$C49,$H$2:$H$1002,"cancelled",$F$2:$F$1002,"<"&F49)>0,COUNTIFS($C$2:$C$1002,$C49,$H$2:$H$1002,"created",$F$2:$F$1002,"<"&F49)-COUNTIFS($C$2:$C$1002,$C49,$H$2:$H$1002,"cancelled",$F$2:$F$1002,"<"&F49)=0),1,0) -> 0
A50: EVT049 | B50: SUB051 | C50: CUST014 | D50: Toronto Media Group | E50: Eastern Canada | F50: 45689 | G50: 45698 | H50: created | M50: Sales Hub | N50: Monthly | O50: 23 | P50: 110 | Q50: 0 | R50: {=_xlfn.IFS(H50="created", "New", H50="cancelled", "Churned", AND(H50="seats_change", J50 > I50), "Expansion", AND(H50="seats_change", J50 < I50), "Contraction", AND(H50="price_change", J50 > I50), "Expansion", AND(H50="price_change", J50 < I50), "Contraction", H50="plan_upgrade", "Expansion", H50="plan_downgrade", "Contraction", H50="discount_added", "Contraction")} -> New | S50: {=IF(N50="Monthly",_xlfn.IFS(H50="created",O50*P50*(1-Q50/100),H50="cancelled",-(O50*P50*(1-Q50/100)),H50="seats_change",(J50-I50)*P50*(1-Q50/100),H50="price_change",(J50-I50)*O50*(1-Q50/100),H50="discount_added",-(O50*P50*(J50-I50)/100),H50="plan_upgrade",O50*(_xlfn.XLOOKUP(J50,$M:$M,$P:$P)-_xlfn.XLOOKUP(I50,$M:$M,$P:$P))*(1-Q50/100),H50="plan_downgrade",O50*(_xlfn.XLOOKUP(J50,$M:$M,$P:$P)-_xlfn.XLOOKUP(I50,$M:$M,$P:$P))*(1-Q50/100)),_xlfn.IFS(H50="created",O50*P50*(1-Q50/100)/12,H50="cancelled",-(O50*P50*(1-Q50/100))/12,H50="seats_change",(J50-I50)*P50*(1-Q50/100)/12,H50="price_change",(J50-I50)*O50*(1-Q50/100)/12,H50="plan_upgrade",(O50*(_xlfn.XLOOKUP(J50,$M:$M,$P:$P)-_xlfn.XLOOKUP(I50,$M:$M,$P:$P))*(1-Q50/100))/12,H50="plan_downgrade",(O50*(_xlfn.XLOOKUP(J50,$M:$M,$P:$P)-_xlfn.XLOOKUP(I50,$M:$M,$P:$P))*(1-Q50/100))/12,H50="discount_added",-(O50*P50*(J50-I50)/100)/12))} -> 2530 | T50: =IF(H50<>"created",0,IF(COUNTIFS($C$1:C49,$C50,$H$1:H49,"created")=0,1,0)) -> 0 | U50: =IF(H50<>"cancelled",0,IF(COUNTIFS($C$2:$C$1002,$C50,$H$2:$H$1002,"created",$F$2:$F$1002,"<="&F50)-COUNTIFS($C$2:$C$1002,$C50,$H$2:$H$1002,"cancelled",$F$2:$F$1002,"<="&F50)=0,1,0)) -> 0 | V50: =IF(AND(H50="created",T50=0,COUNTIFS($C$2:$C$1002,$C50,$H$2:$H$1002,"cancelled",$F$2:$F$1002,"<"&F50)>0,COUNTIFS($C$2:$C$1002,$C50,$H$2:$H$1002,"created",$F$2:$F$1002,"<"&F50)-COUNTIFS($C$2:$C$1002,$C50,$H$2:$H$1002,"cancelled",$F$2:$F$1002,"<"&F50)=0),1,0) -> 0
A51: EVT050 | B51: SUB030 | C51: CUST030 | D51: Alberta E-commerce Hub | E51: Western Canada | F51: 45689 | G51: 45705 | H51: created | M51: Analytics Growth | N51: Monthly | O51: 20 | P51: 95 | Q51: 0 | R51: {=_xlfn.IFS(H51="created", "New", H51="cancelled", "Churned", AND(H51="seats_change", J51 > I51), "Expansion", AND(H51="seats_change", J51 < I51), "Contraction", AND(H51="price_change", J51 > I51), "Expansion", AND(H51="price_change", J51 < I51), "Contraction", H51="plan_upgrade", "Expansion", H51="plan_downgrade", "Contraction", H51="discount_added", "Contraction")} -> New | S51: {=IF(N51="Monthly",_xlfn.IFS(H51="created",O51*P51*(1-Q51/100),H51="cancelled",-(O51*P51*(1-Q51/100)),H51="seats_change",(J51-I51)*P51*(1-Q51/100),H51="price_change",(J51-I51)*O51*(1-Q51/100),H51="discount_added",-(O51*P51*(J51-I51)/100),H51="plan_upgrade",O51*(_xlfn.XLOOKUP(J51,$M:$M,$P:$P)-_xlfn.XLOOKUP(I51,$M:$M,$P:$P))*(1-Q51/100),H51="plan_downgrade",O51*(_xlfn.XLOOKUP(J51,$M:$M,$P:$P)-_xlfn.XLOOKUP(I51,$M:$M,$P:$P))*(1-Q51/100)),_xlfn.IFS(H51="created",O51*P51*(1-Q51/100)/12,H51="cancelled",-(O51*P51*(1-Q51/100))/12,H51="seats_change",(J51-I51)*P51*(1-Q51/100)/12,H51="price_change",(J51-I51)*O51*(1-Q51/100)/12,H51="plan_upgrade",(O51*(_xlfn.XLOOKUP(J51,$M:$M,$P:$P)-_xlfn.XLOOKUP(I51,$M:$M,$P:$P))*(1-Q51/100))/12,H51="plan_downgrade",(O51*(_xlfn.XLOOKUP(J51,$M:$M,$P:$P)-_xlfn.XLOOKUP(I51,$M:$M,$P:$P))*(1-Q51/100))/12,H51="discount_added",-(O51*P51*(J51-I51)/100)/12))} -> 1900 | T51: =IF(H51<>"created",0,IF(COUNTIFS($C$1:C50,$C51,$H$1:H50,"created")=0,1,0)) -> 1 | U51: =IF(H51<>"cancelled",0,IF(COUNTIFS($C$2:$C$1002,$C51,$H$2:$H$1002,"created",$F$2:$F$1002,"<="&F51)-COUNTIFS($C$2:$C$1002,$C51,$H$2:$H$1002,"cancelled",$F$2:$F$1002,"<="&F51)=0,1,0)) -> 0 | V51: =IF(AND(H51="created",T51=0,COUNTIFS($C$2:$C$1002,$C51,$H$2:$H$1002,"cancelled",$F$2:$F$1002,"<"&F51)>0,COUNTIFS($C$2:$C$1002,$C51,$H$2:$H$1002,"created",$F$2:$F$1002,"<"&F51)-COUNTIFS($C$2:$C$1002,$C51,$H$2:$H$1002,"cancelled",$F$2:$F$1002,"<"&F51)=0),1,0) -> 0
A52: EVT051 | B52: SUB031 | C52: CUST031 | D52: Toronto Digital Media | E52: Eastern Canada | F52: 45717 | G52: 45719 | H52: created | M52: Platform Suite | N52: Annual | O52: 45 | P52: 1800 | Q52: 0 | R52: {=_xlfn.IFS(H52="created", "New", H52="cancelled", "Churned", AND(H52="seats_change", J52 > I52), "Expansion", AND(H52="seats_change", J52 < I52), "Contraction", AND(H52="price_change", J52 > I52), "Expansion", AND(H52="price_change", J52 < I52), "Contraction", H52="plan_upgrade", "Expansion", H52="plan_downgrade", "Contraction", H52="discount_added", "Contraction")} -> New | S52: {=IF(N52="Monthly",_xlfn.IFS(H52="created",O52*P52*(1-Q52/100),H52="cancelled",-(O52*P52*(1-Q52/100)),H52="seats_change",(J52-I52)*P52*(1-Q52/100),H52="price_change",(J52-I52)*O52*(1-Q52/100),H52="discount_added",-(O52*P52*(J52-I52)/100),H52="plan_upgrade",O52*(_xlfn.XLOOKUP(J52,$M:$M,$P:$P)-_xlfn.XLOOKUP(I52,$M:$M,$P:$P))*(1-Q52/100),H52="plan_downgrade",O52*(_xlfn.XLOOKUP(J52,$M:$M,$P:$P)-_xlfn.XLOOKUP(I52,$M:$M,$P:$P))*(1-Q52/100)),_xlfn.IFS(H52="created",O52*P52*(1-Q52/100)/12,H52="cancelled",-(O52*P52*(1-Q52/100))/12,H52="seats_change",(J52-I52)*P52*(1-Q52/100)/12,H52="price_change",(J52-I52)*O52*(1-Q52/100)/12,H52="plan_upgrade",(O52*(_xlfn.XLOOKUP(J52,$M:$M,$P:$P)-_xlfn.XLOOKUP(I52,$M:$M,$P:$P))*(1-Q52/100))/12,H52="plan_downgrade",(O52*(_xlfn.XLOOKUP(J52,$M:$M,$P:$P)-_xlfn.XLOOKUP(I52,$M:$M,$P:$P))*(1-Q52/100))/12,H52="discount_added",-(O52*P52*(J52-I52)/100)/12))} -> 6750 | T52: =IF(H52<>"created",0,IF(COUNTIFS($C$1:C51,$C52,$H$1:H51,"created")=0,1,0)) -> 1 | U52: =IF(H52<>"cancelled",0,IF(COUNTIFS($C$2:$C$1002,$C52,$H$2:$H$1002,"created",$F$2:$F$1002,"<="&F52)-COUNTIFS($C$2:$C$1002,$C52,$H$2:$H$1002,"cancelled",$F$2:$F$1002,"<="&F52)=0,1,0)) -> 0 | V52: =IF(AND(H52="created",T52=0,COUNTIFS($C$2:$C$1002,$C52,$H$2:$H$1002,"cancelled",$F$2:$F$1002,"<"&F52)>0,COUNTIFS($C$2:$C$1002,$C52,$H$2:$H$1002,"created",$F$2:$F$1002,"<"&F52)-COUNTIFS($C$2:$C$1002,$C52,$H$2:$H$1002,"cancelled",$F$2:$F$1002,"<"&F52)=0),1,0) -> 0
A53: EVT052 | B53: SUB058 | C53: CUST024 | D53: Western Retail Group | E53: Western Canada | F53: 45717 | G53: 45724 | H53: created | M53: Sales Hub | N53: Monthly | O53: 26 | P53: 110 | Q53: 0 | R53: {=_xlfn.IFS(H53="created", "New", H53="cancelled", "Churned", AND(H53="seats_change", J53 > I53), "Expansion", AND(H53="seats_change", J53 < I53), "Contraction", AND(H53="price_change", J53 > I53), "Expansion", AND(H53="price_change", J53 < I53), "Contraction", H53="plan_upgrade", "Expansion", H53="plan_downgrade", "Contraction", H53="discount_added", "Contraction")} -> New | S53: {=IF(N53="Monthly",_xlfn.IFS(H53="created",O53*P53*(1-Q53/100),H53="cancelled",-(O53*P53*(1-Q53/100)),H53="seats_change",(J53-I53)*P53*(1-Q53/100),H53="price_change",(J53-I53)*O53*(1-Q53/100),H53="discount_added",-(O53*P53*(J53-I53)/100),H53="plan_upgrade",O53*(_xlfn.XLOOKUP(J53,$M:$M,$P:$P)-_xlfn.XLOOKUP(I53,$M:$M,$P:$P))*(1-Q53/100),H53="plan_downgrade",O53*(_xlfn.XLOOKUP(J53,$M:$M,$P:$P)-_xlfn.XLOOKUP(I53,$M:$M,$P:$P))*(1-Q53/100)),_xlfn.IFS(H53="created",O53*P53*(1-Q53/100)/12,H53="cancelled",-(O53*P53*(1-Q53/100))/12,H53="seats_change",(J53-I53)*P53*(1-Q53/100)/12,H53="price_change",(J53-I53)*O53*(1-Q53/100)/12,H53="plan_upgrade",(O53*(_xlfn.XLOOKUP(J53,$M:$M,$P:$P)-_xlfn.XLOOKUP(I53,$M:$M,$P:$P))*(1-Q53/100))/12,H53="plan_downgrade",(O53*(_xlfn.XLOOKUP(J53,$M:$M,$P:$P)-_xlfn.XLOOKUP(I53,$M:$M,$P:$P))*(1-Q53/100))/12,H53="discount_added",-(O53*P53*(J53-I53)/100)/12))} -> 2860 | T53: =IF(H53<>"created",0,IF(COUNTIFS($C$1:C52,$C53,$H$1:H52,"created")=0,1,0)) -> 0 | U53: =IF(H53<>"cancelled",0,IF(COUNTIFS($C$2:$C$1002,$C53,$H$2:$H$1002,"created",$F$2:$F$1002,"<="&F53)-COUNTIFS($C$2:$C$1002,$C53,$H$2:$H$1002,"cancelled",$F$2:$F$1002,"<="&F53)=0,1,0)) -> 0 | V53: =IF(AND(H53="created",T53=0,COUNTIFS($C$2:$C$1002,$C53,$H$2:$H$1002,"cancelled",$F$2:$F$1002,"<"&F53)>0,COUNTIFS($C$2:$C$1002,$C53,$H$2:$H$1002,"created",$F$2:$F$1002,"<"&F53)-COUNTIFS($C$2:$C$1002,$C53,$H$2:$H$1002,"cancelled",$F$2:$F$1002,"<"&F53)=0),1,0) -> 0
A54: EVT053 | B54: SUB010 | C54: CUST010 | D54: Montreal Finance Hub | E54: Eastern Canada | F54: 45717 | G54: 45729 | H54: plan_downgrade | I54: Analytics Growth | J54: Analytics Starter | K54: plan_name | L54: Cost reduction initiative - downgraded to starter tier | M54: Analytics Starter | N54: Monthly | O54: 13 | P54: 45 | Q54: 0 | R54: {=_xlfn.IFS(H54="created", "New", H54="cancelled", "Churned", AND(H54="seats_change", J54 > I54), "Expansion", AND(H54="seats_change", J54 < I54), "Contraction", AND(H54="price_change", J54 > I54), "Expansion", AND(H54="price_change", J54 < I54), "Contraction", H54="plan_upgrade", "Expansion", H54="plan_downgrade", "Contraction", H54="discount_added", "Contraction")} -> Contraction | S54: {=IF(N54="Monthly",_xlfn.IFS(H54="created",O54*P54*(1-Q54/100),H54="cancelled",-(O54*P54*(1-Q54/100)),H54="seats_change",(J54-I54)*P54*(1-Q54/100),H54="price_change",(J54-I54)*O54*(1-Q54/100),H54="discount_added",-(O54*P54*(J54-I54)/100),H54="plan_upgrade",O54*(_xlfn.XLOOKUP(J54,$M:$M,$P:$P)-_xlfn.XLOOKUP(I54,$M:$M,$P:$P))*(1-Q54/100),H54="plan_downgrade",O54*(_xlfn.XLOOKUP(J54,$M:$M,$P:$P)-_xlfn.XLOOKUP(I54,$M:$M,$P:$P))*(1-Q54/100)),_xlfn.IFS(H54="created",O54*P54*(1-Q54/100)/12,H54="cancelled",-(O54*P54*(1-Q54/100))/12,H54="seats_change",(J54-I54)*P54*(1-Q54/100)/12,H54="price_change",(J54-I54)*O54*(1-Q54/100)/12,H54="plan_upgrade",(O54*(_xlfn.XLOOKUP(J54,$M:$M,$P:$P)-_xlfn.XLOOKUP(I54,$M:$M,$P:$P))*(1-Q54/100))/12,H54="plan_downgrade",(O54*(_xlfn.XLOOKUP(J54,$M:$M,$P:$P)-_xlfn.XLOOKUP(I54,$M:$M,$P:$P))*(1-Q54/100))/12,H54="discount_added",-(O54*P54*(J54-I54)/100)/12))} -> -650 | T54: =IF(H54<>"created",0,IF(COUNTIFS($C$1:C53,$C54,$H$1:H53,"created")=0,1,0)) -> 0 | U54: =IF(H54<>"cancelled",0,IF(COUNTIFS($C$2:$C$1002,$C54,$H$2:$H$1002,"created",$F$2:$F$1002,"<="&F54)-COUNTIFS($C$2:$C$1002,$C54,$H$2:$H$1002,"cancelled",$F$2:$F$1002,"<="&F54)=0,1,0)) -> 0 | V54: =IF(AND(H54="created",T54=0,COUNTIFS($C$2:$C$1002,$C54,$H$2:$H$1002,"cancelled",$F$2:$F$1002,"<"&F54)>0,COUNTIFS($C$2:$C$1002,$C54,$H$2:$H$1002,"created",$F$2:$F$1002,"<"&F54)-COUNTIFS($C$2:$C$1002,$C54,$H$2:$H$1002,"cancelled",$F$2:$F$1002,"<"&F54)=0),1,0) -> 0
A55: EVT054 | B55: SUB052 | C55: CUST018 | D55: Vancouver FinTech Labs | E55: Western Canada | F55: 45717 | G55: 45731 | H55: created | M55: Marketing Pro | N55: Monthly | O55: 35 | P55: 85 | Q55: 0 | R55: {=_xlfn.IFS(H55="created", "New", H55="cancelled", "Churned", AND(H55="seats_change", J55 > I55), "Expansion", AND(H55="seats_change", J55 < I55), "Contraction", AND(H55="price_change", J55 > I55), "Expansion", AND(H55="price_change", J55 < I55), "Contraction", H55="plan_upgrade", "Expansion", H55="plan_downgrade", "Contraction", H55="discount_added", "Contraction")} -> New | S55: {=IF(N55="Monthly",_xlfn.IFS(H55="created",O55*P55*(1-Q55/100),H55="cancelled",-(O55*P55*(1-Q55/100)),H55="seats_change",(J55-I55)*P55*(1-Q55/100),H55="price_change",(J55-I55)*O55*(1-Q55/100),H55="discount_added",-(O55*P55*(J55-I55)/100),H55="plan_upgrade",O55*(_xlfn.XLOOKUP(J55,$M:$M,$P:$P)-_xlfn.XLOOKUP(I55,$M:$M,$P:$P))*(1-Q55/100),H55="plan_downgrade",O55*(_xlfn.XLOOKUP(J55,$M:$M,$P:$P)-_xlfn.XLOOKUP(I55,$M:$M,$P:$P))*(1-Q55/100)),_xlfn.IFS(H55="created",O55*P55*(1-Q55/100)/12,H55="cancelled",-(O55*P55*(1-Q55/100))/12,H55="seats_change",(J55-I55)*P55*(1-Q55/100)/12,H55="price_change",(J55-I55)*O55*(1-Q55/100)/12,H55="plan_upgrade",(O55*(_xlfn.XLOOKUP(J55,$M:$M,$P:$P)-_xlfn.XLOOKUP(I55,$M:$M,$P:$P))*(1-Q55/100))/12,H55="plan_downgrade",(O55*(_xlfn.XLOOKUP(J55,$M:$M,$P:$P)-_xlfn.XLOOKUP(I55,$M:$M,$P:$P))*(1-Q55/100))/12,H55="discount_added",-(O55*P55*(J55-I55)/100)/12))} -> 2975 | T55: =IF(H55<>"created",0,IF(COUNTIFS($C$1:C54,$C55,$H$1:H54,"created")=0,1,0)) -> 0 | U55: =IF(H55<>"cancelled",0,IF(COUNTIFS($C$2:$C$1002,$C55,$H$2:$H$1002,"created",$F$2:$F$1002,"<="&F55)-COUNTIFS($C$2:$C$1002,$C55,$H$2:$H$1002,"cancelled",$F$2:$F$1002,"<="&F55)=0,1,0)) -> 0 | V55: =IF(AND(H55="created",T55=0,COUNTIFS($C$2:$C$1002,$C55,$H$2:$H$1002,"cancelled",$F$2:$F$1002,"<"&F55)>0,COUNTIFS($C$2:$C$1002,$C55,$H$2:$H$1002,"created",$F$2:$F$1002,"<"&F55)-COUNTIFS($C$2:$C$1002,$C55,$H$2:$H$1002,"cancelled",$F$2:$F$1002,"<"&F55)=0),1,0) -> 0
A56: EVT055 | B56: SUB054 | C56: CUST002 | D56: Pacific Analytics Inc | E56: Western Canada | F56: 45717 | G56: 45731 | H56: discount_added | I56: 0 | J56: 5 | K56: discount_percent | L56: Annual contract loyalty discount applied | M56: Analytics Growth | N56: Annual | O56: 22 | P56: 1140 | Q56: 5 | R56: {=_xlfn.IFS(H56="created", "New", H56="cancelled", "Churned", AND(H56="seats_change", J56 > I56), "Expansion", AND(H56="seats_change", J56 < I56), "Contraction", AND(H56="price_change", J56 > I56), "Expansion", AND(H56="price_change", J56 < I56), "Contraction", H56="plan_upgrade", "Expansion", H56="plan_downgrade", "Contraction", H56="discount_added", "Contraction")} -> Contraction | S56: {=IF(N56="Monthly",_xlfn.IFS(H56="created",O56*P56*(1-Q56/100),H56="cancelled",-(O56*P56*(1-Q56/100)),H56="seats_change",(J56-I56)*P56*(1-Q56/100),H56="price_change",(J56-I56)*O56*(1-Q56/100),H56="discount_added",-(O56*P56*(J56-I56)/100),H56="plan_upgrade",O56*(_xlfn.XLOOKUP(J56,$M:$M,$P:$P)-_xlfn.XLOOKUP(I56,$M:$M,$P:$P))*(1-Q56/100),H56="plan_downgrade",O56*(_xlfn.XLOOKUP(J56,$M:$M,$P:$P)-_xlfn.XLOOKUP(I56,$M:$M,$P:$P))*(1-Q56/100)),_xlfn.IFS(H56="created",O56*P56*(1-Q56/100)/12,H56="cancelled",-(O56*P56*(1-Q56/100))/12,H56="seats_change",(J56-I56)*P56*(1-Q56/100)/12,H56="price_change",(J56-I56)*O56*(1-Q56/100)/12,H56="plan_upgrade",(O56*(_xlfn.XLOOKUP(J56,$M:$M,$P:$P)-_xlfn.XLOOKUP(I56,$M:$M,$P:$P))*(1-Q56/100))/12,H56="plan_downgrade",(O56*(_xlfn.XLOOKUP(J56,$M:$M,$P:$P)-_xlfn.XLOOKUP(I56,$M:$M,$P:$P))*(1-Q56/100))/12,H56="discount_added",-(O56*P56*(J56-I56)/100)/12))} -> -104.5 | T56: =IF(H56<>"created",0,IF(COUNTIFS($C$1:C55,$C56,$H$1:H55,"created")=0,1,0)) -> 0 | U56: =IF(H56<>"cancelled",0,IF(COUNTIFS($C$2:$C$1002,$C56,$H$2:$H$1002,"created",$F$2:$F$1002,"<="&F56)-COUNTIFS($C$2:$C$1002,$C56,$H$2:$H$1002,"cancelled",$F$2:$F$1002,"<="&F56)=0,1,0)) -> 0 | V56: =IF(AND(H56="created",T56=0,COUNTIFS($C$2:$C$1002,$C56,$H$2:$H$1002,"cancelled",$F$2:$F$1002,"<"&F56)>0,COUNTIFS($C$2:$C$1002,$C56,$H$2:$H$1002,"created",$F$2:$F$1002,"<"&F56)-COUNTIFS($C$2:$C$1002,$C56,$H$2:$H$1002,"cancelled",$F$2:$F$1002,"<"&F56)=0),1,0) -> 0
A57: EVT056 | B57: SUB032 | C57: CUST032 | D57: BC Manufacturing Systems | E57: Western Canada | F57: 45717 | G57: 45733 | H57: created | M57: Analytics Enterprise | N57: Monthly | O57: 26 | P57: 180 | Q57: 0 | R57: {=_xlfn.IFS(H57="created", "New", H57="cancelled", "Churned", AND(H57="seats_change", J57 > I57), "Expansion", AND(H57="seats_change", J57 < I57), "Contraction", AND(H57="price_change", J57 > I57), "Expansion", AND(H57="price_change", J57 < I57), "Contraction", H57="plan_upgrade", "Expansion", H57="plan_downgrade", "Contraction", H57="discount_added", "Contraction")} -> New | S57: {=IF(N57="Monthly",_xlfn.IFS(H57="created",O57*P57*(1-Q57/100),H57="cancelled",-(O57*P57*(1-Q57/100)),H57="seats_change",(J57-I57)*P57*(1-Q57/100),H57="price_change",(J57-I57)*O57*(1-Q57/100),H57="discount_added",-(O57*P57*(J57-I57)/100),H57="plan_upgrade",O57*(_xlfn.XLOOKUP(J57,$M:$M,$P:$P)-_xlfn.XLOOKUP(I57,$M:$M,$P:$P))*(1-Q57/100),H57="plan_downgrade",O57*(_xlfn.XLOOKUP(J57,$M:$M,$P:$P)-_xlfn.XLOOKUP(I57,$M:$M,$P:$P))*(1-Q57/100)),_xlfn.IFS(H57="created",O57*P57*(1-Q57/100)/12,H57="cancelled",-(O57*P57*(1-Q57/100))/12,H57="seats_change",(J57-I57)*P57*(1-Q57/100)/12,H57="price_change",(J57-I57)*O57*(1-Q57/100)/12,H57="plan_upgrade",(O57*(_xlfn.XLOOKUP(J57,$M:$M,$P:$P)-_xlfn.XLOOKUP(I57,$M:$M,$P:$P))*(1-Q57/100))/12,H57="plan_downgrade",(O57*(_xlfn.XLOOKUP(J57,$M:$M,$P:$P)-_xlfn.XLOOKUP(I57,$M:$M,$P:$P))*(1-Q57/100))/12,H57="discount_added",-(O57*P57*(J57-I57)/100)/12))} -> 4680 | T57: =IF(H57<>"created",0,IF(COUNTIFS($C$1:C56,$C57,$H$1:H56,"created")=0,1,0)) -> 1 | U57: =IF(H57<>"cancelled",0,IF(COUNTIFS($C$2:$C$1002,$C57,$H$2:$H$1002,"created",$F$2:$F$1002,"<="&F57)-COUNTIFS($C$2:$C$1002,$C57,$H$2:$H$1002,"cancelled",$F$2:$F$1002,"<="&F57)=0,1,0)) -> 0 | V57: =IF(AND(H57="created",T57=0,COUNTIFS($C$2:$C$1002,$C57,$H$2:$H$1002,"cancelled",$F$2:$F$1002,"<"&F57)>0,COUNTIFS($C$2:$C$1002,$C57,$H$2:$H$1002,"created",$F$2:$F$1002,"<"&F57)-COUNTIFS($C$2:$C$1002,$C57,$H$2:$H$1002,"cancelled",$F$2:$F$1002,"<"&F57)=0),1,0) -> 0
A58: EVT057 | B58: SUB019 | C58: CUST019 | D58: Central Healthcare Partners | E58: Central Canada | F58: 45717 | G58: 45736 | H58: seats_change | I58: 22 | J58: 19 | K58: seats | L58: Headcount reduction - Q1 restructuring | M58: Marketing Pro | N58: Monthly | O58: 19 | P58: 85 | Q58: 0 | R58: {=_xlfn.IFS(H58="created", "New", H58="cancelled", "Churned", AND(H58="seats_change", J58 > I58), "Expansion", AND(H58="seats_change", J58 < I58), "Contraction", AND(H58="price_change", J58 > I58), "Expansion", AND(H58="price_change", J58 < I58), "Contraction", H58="plan_upgrade", "Expansion", H58="plan_downgrade", "Contraction", H58="discount_added", "Contraction")} -> Contraction | S58: {=IF(N58="Monthly",_xlfn.IFS(H58="created",O58*P58*(1-Q58/100),H58="cancelled",-(O58*P58*(1-Q58/100)),H58="seats_change",(J58-I58)*P58*(1-Q58/100),H58="price_change",(J58-I58)*O58*(1-Q58/100),H58="discount_added",-(O58*P58*(J58-I58)/100),H58="plan_upgrade",O58*(_xlfn.XLOOKUP(J58,$M:$M,$P:$P)-_xlfn.XLOOKUP(I58,$M:$M,$P:$P))*(1-Q58/100),H58="plan_downgrade",O58*(_xlfn.XLOOKUP(J58,$M:$M,$P:$P)-_xlfn.XLOOKUP(I58,$M:$M,$P:$P))*(1-Q58/100)),_xlfn.IFS(H58="created",O58*P58*(1-Q58/100)/12,H58="cancelled",-(O58*P58*(1-Q58/100))/12,H58="seats_change",(J58-I58)*P58*(1-Q58/100)/12,H58="price_change",(J58-I58)*O58*(1-Q58/100)/12,H58="plan_upgrade",(O58*(_xlfn.XLOOKUP(J58,$M:$M,$P:$P)-_xlfn.XLOOKUP(I58,$M:$M,$P:$P))*(1-Q58/100))/12,H58="plan_downgrade",(O58*(_xlfn.XLOOKUP(J58,$M:$M,$P:$P)-_xlfn.XLOOKUP(I58,$M:$M,$P:$P))*(1-Q58/100))/12,H58="discount_added",-(O58*P58*(J58-I58)/100)/12))} -> -255 | T58: =IF(H58<>"created",0,IF(COUNTIFS($C$1:C57,$C58,$H$1:H57,"created")=0,1,0)) -> 0 | U58: =IF(H58<>"cancelled",0,IF(COUNTIFS($C$2:$C$1002,$C58,$H$2:$H$1002,"created",$F$2:$F$1002,"<="&F58)-COUNTIFS($C$2:$C$1002,$C58,$H$2:$H$1002,"cancelled",$F$2:$F$1002,"<="&F58)=0,1,0)) -> 0 | V58: =IF(AND(H58="created",T58=0,COUNTIFS($C$2:$C$1002,$C58,$H$2:$H$1002,"cancelled",$F$2:$F$1002,"<"&F58)>0,COUNTIFS($C$2:$C$1002,$C58,$H$2:$H$1002,"created",$F$2:$F$1002,"<"&F58)-COUNTIFS($C$2:$C$1002,$C58,$H$2:$H$1002,"cancelled",$F$2:$F$1002,"<"&F58)=0),1,0) -> 0
