Workbook

Sheet Raw Snapshot
A1: subscription_id | B1: customer_id | C1: company_name | D1: account_owner | E1: region | F1: plan_name | G1: billing_cycle | H1: mrr
A2: SUB025 | B2: CUST025 | C2: Montreal Manufacturing Pro | D2: Sarah Chen | E2: Eastern Canada | F2: Analytics Enterprise | G2: Annual | H2: 6840
A3: SUB031 | B3: CUST031 | C3: Toronto Digital Media | D3: James Wilson | E3: Eastern Canada | F3: Platform Suite | G3: Annual | H3: 6750
A4: SUB018 | B4: CUST018 | C4: Vancouver FinTech Labs | D4: Michael Rodriguez | E4: Western Canada | F4: Analytics Enterprise | G4: Monthly | H4: 6300
A5: SUB016 | B5: CUST016 | C5: Quebec Manufacturing | D5: Sarah Chen | E5: Eastern Canada | F5: Platform Suite | G5: Annual | H5: 6300
A6: SUB053 | B6: CUST027 | C6: Pacific Finance Corp | D6: Michael Rodriguez | E6: Western Canada | F6: Analytics Enterprise | G6: Monthly | H6: 5580
A7: SUB006 | B7: CUST006 | C7: Northern Retail Solutions | D7: Michael Rodriguez | E7: Western Canada | F7: Analytics Enterprise | G7: Annual | H7: 5580
A8: SUB009 | B8: CUST009 | C8: West Coast Logistics | D8: Michael Rodriguez | E8: Western Canada | F8: Platform Suite | G8: Annual | H8: 5400
A9: SUB037 | B9: CUST037 | C9: Maritime SaaS Ventures | D9: Sarah Chen | E9: Eastern Canada | F9: Platform Suite | G9: Monthly | H9: 5250
A10: SUB022 | B10: CUST022 | C10: Toronto Tech Ventures | D10: James Wilson | E10: Eastern Canada | F10: Platform Suite | G10: Monthly | H10: 4950
A11: SUB032 | B11: CUST032 | C11: BC Manufacturing Systems | D11: Michael Rodriguez | E11: Western Canada | F11: Analytics Enterprise | G11: Monthly | H11: 4680
A12: SUB057 | B12: CUST021 | C12: Calgary Commerce Solutions | D12: Michael Rodriguez | E12: Western Canada | F12: Platform Suite | G12: Monthly | H12: 4200
A13: SUB048 | B13: CUST025 | C13: Montreal Manufacturing Pro | D13: Sarah Chen | E13: Eastern Canada | F13: Sales Hub | G13: Monthly | H13: 3960
... A52: SUB017 | B52: CUST017 | C52: Capital Education Tech | D52: James Wilson | E52: Eastern Canada | F52: Analytics Starter | G52: Monthly | H52: 540

Sheet Raw Events
A1: event_id | B1: subscription_id | C1: customer_id | D1: company_name | E1: region | F1: month | G1: event_date | H1: event_date | I1: event_type | J1: old_value | K1: new_value | L1: field_changed | M1: reason | N1: plan_name | O1: billing_cycle | P1: price_per_seat | Q1: discount_percent
A2: EVT001 | B2: SUB001 | C2: CUST001 | D2: TechVision Solutions | E2: Eastern Canada | F2: 45292 | G2: 45299 | H2: 45299 | I2: created | N2: Analytics Growth | O2: Monthly | P2: 95 | Q2: 0
A3: EVT002 | B3: SUB002 | C3: CUST002 | D3: Pacific Analytics Inc | E3: Western Canada | F3: 45292 | G3: 45313 | H3: 45313 | I3: created | N3: Platform Suite | O3: Annual | P3: 1800 | Q3: 0
A4: EVT003 | B4: SUB003 | C4: CUST003 | D4: Maple Healthcare Systems | E4: Eastern Canada | F4: 45323 | G4: 45327 | H4: 45327 | I4: created | N4: Marketing Pro | O4: Monthly | P4: 85 | Q4: 0
A5: EVT004 | B5: SUB004 | C5: CUST004 | D5: Prairie Commerce Group | E5: Western Canada | F5: 45323 | G5: 45341 | H5: 45341 | I5: created | N5: Sales Hub | O5: Monthly | P5: 110 | Q5: 0
A6: EVT005 | B6: SUB055 | C6: CUST004 | D6: Prairie Commerce Group | E6: Western Canada | F6: 45323 | G6: 45341 | H6: 45341 | I6: created | N6: Analytics Enterprise | O6: Monthly | P6: 180 | Q6: 0
A7: EVT006 | B7: SUB005 | C7: CUST005 | D7: Atlantic Media Corp | E7: Eastern Canada | F7: 45352 | G7: 45355 | H7: 45355 | I7: created | N7: Analytics Starter | O7: Monthly | P7: 45 | Q7: 0
A8: EVT007 | B8: SUB006 | C8: CUST006 | D8: Northern Retail Solutions | E8: Western Canada | F8: 45352 | G8: 45369 | H8: 45369 | I8: created | N8: Analytics Enterprise | O8: Annual | P8: 2160 | Q8: 0
A9: EVT008 | B9: SUB007 | C9: CUST007 | D9: Ontario Manufacturing Tech | E9: Eastern Canada | F9: 45383 | G9: 45383 | H9: 45383 | I9: created | N9: Marketing Pro | O9: Monthly | P9: 85 | Q9: 0
A10: EVT009 | B10: SUB050 | C10: CUST007 | D10: Ontario Manufacturing Tech | E10: Eastern Canada | F10: 45383 | G10: 45383 | H10: 45383 | I10: created | N10: Analytics Starter | O10: Monthly | P10: 45 | Q10: 12
A11: EVT010 | B11: SUB008 | C11: CUST008 | D11: Quantum Education Platform | E11: Eastern Canada | F11: 45383 | G11: 45397 | H11: 45397 | I11: created | N11: Analytics Growth | O11: Monthly | P11: 95 | Q11: 0
A12: EVT011 | B12: SUB009 | C12: CUST009 | D12: West Coast Logistics | E12: Western Canada | F12: 45383 | G12: 45411 | H12: 45411 | I12: created | N12: Platform Suite | O12: Annual | P12: 1800 | Q12: 0
A13: EVT012 | B13: SUB010 | C13: CUST010 | D13: Montreal Finance Hub | E13: Eastern Canada | F13: 45413 | G13: 45425 | H13: 45425 | I13: created | N13: Analytics Starter | O13: Monthly | P13: 45 | Q13: 0
... A23: EVT022 | B23: SUB017 | C23: CUST017 | D23: Capital Education Tech | E23: Eastern Canada | F23: 45505 | G23: 45523 | H23: 45523 | I23: created | N23: Analytics Starter | O23: Monthly | P23: 45 | Q23: 0
A24: EVT023 | B24: SUB001 | C24: CUST001 | D24: TechVision Solutions | E24: Eastern Canada | F24: 45505 | G24: 45531 | H24: 45531 | I24: cancelled | J24: active | K24: churned | L24: status | M24: Missing features | N24: Analytics Growth | O24: Monthly | P24: 95 | Q24: 0
A25: EVT024 | B25: SUB018 | C25: CUST018 | D25: Vancouver FinTech Labs | E25: Western Canada | F25: 45536 | G25: 45537 | H25: 45537 | I25: created | N25: Analytics Enterprise | O25: Monthly | P25: 180 | Q25: 0
A26: EVT025 | B26: SUB042 | C26: CUST003 | D26: Maple Healthcare Systems | E26: Eastern Canada | F26: 45536 | G26: 45545 | H26: 45545 | I26: created | N26: Sales Hub | O26: Monthly | P26: 110 | Q26: 0
A27: EVT026 | B27: SUB019 | C27: CUST019 | D27: Central Healthcare Partners | E27: Central Canada | F27: 45536 | G27: 45551 | H27: 45551 | I27: created | N27: Marketing Pro | O27: Monthly | P27: 85 | Q27: 0
A28: EVT027 | B28: SUB060 | C28: CUST019 | D28: Central Healthcare Partners | E28: Central Canada | F28: 45536 | G28: 45551 | H28: 45551 | I28: created | N28: Sales Hub | O28: Monthly | P28: 110 | Q28: 0
A29: EVT028 | B29: SUB020 | C29: CUST020 | D29: Atlantic SaaS Systems | E29: Eastern Canada | F29: 45536 | G29: 45565 | H29: 45565 | I29: created | N29: Sales Hub | O29: Monthly | P29: 110 | Q29: 0
A30: EVT029 | B30: SUB043 | C30: CUST006 | D30: Northern Retail Solutions | E30: Western Canada | F30: 45566 | G30: 45570 | H30: 45570 | I30: created | N30: Marketing Pro | O30: Monthly | P30: 85 | Q30: 0
A31: EVT030 | B31: SUB021 | C31: CUST021 | D31: Calgary Commerce Solutions | E31: Western Canada | F31: 45566 | G31: 45579 | H31: 45579 | I31: created | N31: Analytics Growth | O31: Monthly | P31: 95 | Q31: 0
A32: EVT031 | B32: SUB022 | C32: CUST022 | D32: Toronto Tech Ventures | E32: Eastern Canada | F32: 45566 | G32: 45593 | H32: 45593 | I32: created | N32: Platform Suite | O32: Monthly | P32: 150 | Q32: 0
A33: EVT032 | B33: SUB059 | C33: CUST008 | D33: Quantum Education Platform | E33: Eastern Canada | F33: 45597 | G33: 45601 | H33: 45601 | I33: created | N33: Marketing Pro | O33: Monthly | P33: 85 | Q33: 0
A34: EVT033 | B34: SUB023 | C34: CUST023 | D34: Island Media Productions | E34: Eastern Canada | F34: 45597 | G34: 45607 | H34: 45607 | I34: created | N34: Analytics Starter | O34: Monthly | P34: 45 | Q34: 0
A35: EVT034 | B35: SUB005 | C35: CUST005 | D35: Atlantic Media Corp | E35: Eastern Canada | F35: 45597 | G35: 45616 | H35: 45616 | I35: cancelled | J35: active | K35: churned | L35: status | M35: Price too high | N35: Analytics Starter | O35: Monthly | P35: 45 | Q35: 0
A36: EVT035 | B36: SUB024 | C36: CUST024 | D36: Western Retail Group | E36: Western Canada | F36: 45597 | G36: 45621 | H36: 45621 | I36: created | N36: Marketing Pro | O36: Monthly | P36: 85 | Q36: 0
A37: EVT036 | B37: SUB025 | C37: CUST025 | D37: Montreal Manufacturing Pro | E37: Eastern Canada | F37: 45627 | G37: 45635 | H37: 45635 | I37: created | N37: Analytics Enterprise | O37: Annual | P37: 2160 | Q37: 0
A38: EVT037 | B38: SUB056 | C38: CUST016 | D38: Quebec Manufacturing | E38: Eastern Canada | F38: 45627 | G38: 45638 | H38: 45638 | I38: created | N38: Marketing Pro | O38: Monthly | P38: 85 | Q38: 0
A39: EVT038 | B39: SUB044 | C39: CUST009 | D39: West Coast Logistics | E39: Western Canada | F39: 45627 | G39: 45646 | H39: 45646 | I39: created | N39: Analytics Growth | O39: Monthly | P39: 95 | Q39: 0
A40: EVT039 | B40: SUB008 | C40: CUST008 | D40: Quantum Education Platform | E40: Eastern Canada | F40: 45627 | G40: 45648 | H40: 45648 | I40: cancelled | J40: active | K40: churned | L40: status | M40: Price too high | N40: Analytics Growth | O40: Monthly | P40: 95 | Q40: 0
A41: EVT040 | B41: SUB026 | C41: CUST026 | D41: Ontario Education Connect | E41: Eastern Canada | F41: 45627 | G41: 45649 | H41: 45649 | I41: created | N41: Analytics Growth | O41: Monthly | P41: 95 | Q41: 0
A42: EVT041 | B42: SUB027 | C42: CUST027 | D42: Pacific Finance Corp | E42: Western Canada | F42: 45658 | G42: 45663 | H42: 45663 | I42: created | N42: Sales Hub | O42: Monthly | P42: 110 | Q42: 0
A43: EVT042 | B43: SUB014 | C43: CUST014 | D43: Toronto Media Group | E43: Eastern Canada | F43: 45658 | G43: 45665 | H43: 45665 | I43: price_change | J43: 80 | K43: 85 | L43: price_per_seat | M43: Annual price increase applied at renewal | N43: Marketing Pro | O43: Monthly | P43: 85 | Q43: 0
A44: EVT043 | B44: SUB013 | C44: CUST013 | D44: Alberta Tech Innovators | E44: Western Canada | F44: 45658 | G44: 45672 | H44: 45672 | I44: cancelled | J44: active | K44: churned | L44: status | M44: Switched to competitor | N44: Analytics Starter | O44: Monthly | P44: 45 | Q44: 0
A45: EVT044 | B45: SUB028 | C45: CUST028 | D45: Prairie SaaS Innovations | E45: Central Canada | F45: 45658 | G45: 45677 | H45: 45677 | I45: created | N45: Analytics Starter | O45: Monthly | P45: 45 | Q45: 0
A46: EVT045 | B46: SUB054 | C46: CUST002 | D46: Pacific Analytics Inc | E46: Western Canada | F46: 45658 | G46: 45679 | H46: 45679 | I46: created | N46: Analytics Growth | O46: Annual | P46: 1140 | Q46: 5
A47: EVT046 | B47: SUB057 | C47: CUST021 | D47: Calgary Commerce Solutions | E47: Western Canada | F47: 45658 | G47: 45685 | H47: 45685 | I47: created | N47: Platform Suite | O47: Monthly | P47: 150 | Q47: 0
A48: EVT047 | B48: SUB029 | C48: CUST029 | D48: Halifax Healthcare Tech | E48: Eastern Canada | F48: 45689 | G48: 45691 | H48: 45691 | I48: created | N48: Marketing Pro | O48: Monthly | P48: 85 | Q48: 0
A49: EVT048 | B49: SUB045 | C49: CUST010 | D49: Montreal Finance Hub | E49: Eastern Canada | F49: 45689 | G49: 45696 | H49: 45696 | I49: created | N49: Marketing Pro | O49: Monthly | P49: 85 | Q49: 0
A50: EVT049 | B50: SUB051 | C50: CUST014 | D50: Toronto Media Group | E50: Eastern Canada | F50: 45689 | G50: 45698 | H50: 45698 | I50: created | N50: Sales Hub | O50: Monthly | P50: 110 | Q50: 0
A51: EVT050 | B51: SUB030 | C51: CUST030 | D51: Alberta E-commerce Hub | E51: Western Canada | F51: 45689 | G51: 45705 | H51: 45705 | I51: created | N51: Analytics Growth | O51: Monthly | P51: 95 | Q51: 0
A52: EVT051 | B52: SUB031 | C52: CUST031 | D52: Toronto Digital Media | E52: Eastern Canada | F52: 45717 | G52: 45719 | H52: 45719 | I52: created | N52: Platform Suite | O52: Annual | P52: 1800 | Q52: 0
A53: EVT052 | B53: SUB058 | C53: CUST024 | D53: Western Retail Group | E53: Western Canada | F53: 45717 | G53: 45724 | H53: 45724 | I53: created | N53: Sales Hub | O53: Monthly | P53: 110 | Q53: 0
A54: EVT053 | B54: SUB010 | C54: CUST010 | D54: Montreal Finance Hub | E54: Eastern Canada | F54: 45717 | G54: 45729 | H54: 45729 | I54: plan_downgrade | J54: Analytics Growth | K54: Analytics Starter | L54: plan_name | M54: Cost reduction initiative - downgraded to starter tier | N54: Analytics Starter | O54: Monthly | P54: 45 | Q54: 0
A55: EVT054 | B55: SUB052 | C55: CUST018 | D55: Vancouver FinTech Labs | E55: Western Canada | F55: 45717 | G55: 45731 | H55: 45731 | I55: created | N55: Marketing Pro | O55: Monthly | P55: 85 | Q55: 0
A56: EVT055 | B56: SUB054 | C56: CUST002 | D56: Pacific Analytics Inc | E56: Western Canada | F56: 45717 | G56: 45731 | H56: 45731 | I56: discount_added | J56: 0 | K56: 5 | L56: discount_percent | M56: Annual contract loyalty discount applied | N56: Analytics Growth | O56: Annual | P56: 1140 | Q56: 5
A57: EVT056 | B57: SUB032 | C57: CUST032 | D57: BC Manufacturing Systems | E57: Western Canada | F57: 45717 | G57: 45733 | H57: 45733 | I57: created | N57: Analytics Enterprise | O57: Monthly | P57: 180 | Q57: 0
A58: EVT057 | B58: SUB019 | C58: CUST019 | D58: Central Healthcare Partners | E58: Central Canada | F58: 45717 | G58: 45736 | H58: 45736 | I58: seats_change | J58: 22 | K58: 19 | L58: seats | M58: Headcount reduction - Q1 restructuring | N58: Marketing Pro | O58: Monthly | P58: 85 | Q58: 0
A59: EVT058 | B59: SUB033 | C59: CUST033 | D59: Ottawa Retail Solutions | E59: Eastern Canada | F59: 45717 | G59: 45747 | H59: 45747 | I59: created | N59: Marketing Pro | O59: Monthly | P59: 85 | Q59: 0
A60: EVT059 | B60: SUB027 | C60: CUST027 | D60: Pacific Finance Corp | E60: Western Canada | F60: 45748 | G60: 45753 | H60: 45753 | I60: price_change | J60: 100 | K60: 110 | L60: price_per_seat | M60: Annual price increase applied at renewal | N60: Sales Hub | O60: Monthly | P60: 110 | Q60: 0
A61: EVT060 | B61: SUB034 | C61: CUST034 | D61: Quebec Education Platform | E61: Eastern Canada | F61: 45748 | G61: 45761 | H61: 45761 | I61: created | N61: Analytics Starter | O61: Monthly | P61: 45 | Q61: 0
A62: EVT061 | B62: SUB012 | C62: CUST012 | D62: Maritime E-commerce | E62: Eastern Canada | F62: 45748 | G62: 45762 | H62: 45762 | I62: seats_change | J62: 18 | K62: 23 | L62: seats | M62: New hires onboarded - sales team expansion | N62: Analytics Growth | O62: Monthly | P62: 95 | Q62: 0
A63: EVT062 | B63: SUB047 | C63: CUST022 | D63: Toronto Tech Ventures | E63: Eastern Canada | F63: 45748 | G63: 45765 | H63: 45765 | I63: created | N63: Sales Hub | O63: Monthly | P63: 110 | Q63: 0
A64: EVT063 | B64: SUB035 | C64: CUST035 | D64: Vancouver Health Systems | E64: Western Canada | F64: 45748 | G64: 45775 | H64: 45775 | I64: created | N64: Sales Hub | O64: Monthly | P64: 110 | Q64: 0
A65: EVT064 | B65: SUB004 | C65: CUST004 | D65: Prairie Commerce Group | E65: Western Canada | F65: 45778 | G65: 45787 | H65: 45787 | I65: seats_change | J65: 15 | K65: 18 | L65: seats | M65: Team expansion - 3 new account managers onboarded | N65: Sales Hub | O65: Monthly | P65: 110 | Q65: 0
A66: EVT065 | B66: SUB036 | C66: CUST036 | D66: Manitoba Finance Group | E66: Central Canada | F66: 45778 | G66: 45789 | H66: 45789 | I66: created | N66: Analytics Growth | O66: Monthly | P66: 95 | Q66: 0
A67: EVT066 | B67: SUB061 | C67: CUST013 | D67: Alberta Tech Innovators | E67: Western Canada | F67: 45778 | G67: 45797 | H67: 45797 | I67: created | M67: Returning customer â€” reactivation | N67: Analytics Growth | O67: Monthly | P67: 95 | Q67: 0
A68: EVT067 | B68: SUB048 | C68: CUST025 | D68: Montreal Manufacturing Pro | E68: Eastern Canada | F68: 45778 | G68: 45799 | H68: 45799 | I68: created | N68: Sales Hub | O68: Monthly | P68: 110 | Q68: 0
A69: EVT068 | B69: SUB021 | C69: CUST021 | D69: Calgary Commerce Solutions | E69: Western Canada | F69: 45778 | G69: 45803 | H69: 45803 | I69: cancelled | J69: active | K69: churned | L69: status | M69: Company downsizing | N69: Analytics Growth | O69: Monthly | P69: 95 | Q69: 0
A70: EVT069 | B70: SUB037 | C70: CUST037 | D70: Maritime SaaS Ventures | E70: Eastern Canada | F70: 45778 | G70: 45803 | H70: 45803 | I70: created | N70: Platform Suite | O70: Monthly | P70: 150 | Q70: 0
A71: EVT070 | B71: SUB018 | C71: CUST018 | D71: Vancouver FinTech Labs | E71: Western Canada | F71: 45809 | G71: 45809 | H71: 45809 | I71: seats_change | J71: 30 | K71: 35 | L71: seats | M71: Department growth - added analytics sub-team | N71: Analytics Enterprise | O71: Monthly | P71: 180 | Q71: 0
A72: EVT071 | B72: SUB053 | C72: CUST027 | D72: Pacific Finance Corp | E72: Western Canada | F72: 45809 | G72: 45813 | H72: 45813 | I72: created | N72: Analytics Enterprise | O72: Monthly | P72: 180 | Q72: 0
A73: EVT072 | B73: SUB038 | C73: CUST038 | D73: Calgary Tech Partners | E73: Western Canada | F73: 45809 | G73: 45817 | H73: 45817 | I73: created | N73: Analytics Starter | O73: Monthly | P73: 45 | Q73: 0
A74: EVT073 | B74: SUB049 | C74: CUST012 | D74: Maritime E-commerce | E74: Eastern Canada | F74: 45809 | G74: 45818 | H74: 45818 | I74: cancelled | J74: active | K74: cancelled | L74: status | M74: No longer needed | N74: Analytics Starter | O74: Monthly | P74: 45 | Q74: 0
A75: EVT074 | B75: SUB026 | C75: CUST026 | D75: Ontario Education Connect | E75: Eastern Canada | F75: 45809 | G75: 45823 | H75: 45823 | I75: plan_upgrade | J75: Analytics Starter | K75: Analytics Growth | L75: plan_name | M75: Growing usage - upgraded for advanced features and higher limits | N75: Analytics Growth | O75: Monthly | P75: 95 | Q75: 0
A76: EVT075 | B76: SUB039 | C76: CUST039 | D76: Toronto Commerce Cloud | E76: Eastern Canada | F76: 45809 | G76: 45831 | H76: 45831 | I76: created | N76: Marketing Pro | O76: Monthly | P76: 85 | Q76: 0
A77: EVT076 | B77: SUB023 | C77: CUST023 | D77: Island Media Productions | E77: Eastern Canada | F77: 45809 | G77: 45833 | H77: 45833 | I77: cancelled | J77: active | K77: churned | L77: status | M77: Missing features | N77: Analytics Starter | O77: Monthly | P77: 45 | Q77: 0
A78: EVT077 | B78: SUB059 | C78: CUST008 | D78: Quantum Education Platform | E78: Eastern Canada | F78: 45839 | G78: 45843 | H78: 45843 | I78: price_change | J78: 75 | K78: 85 | L78: price_per_seat | M78: Annual price increase applied at renewal | N78: Marketing Pro | O78: Monthly | P78: 85 | Q78: 0
A79: EVT078 | B79: SUB060 | C79: CUST019 | D79: Central Healthcare Partners | E79: Central Canada | F79: 45839 | G79: 45858 | H79: 45858 | I79: cancelled | J79: active | K79: cancelled | L79: status | M79: Budget cuts | N79: Sales Hub | O79: Monthly | P79: 110 | Q79: 0
A80: EVT079 | B80: SUB011 | C80: CUST011 | D80: Prairie Health Connect | E80: Central Canada | F80: 45839 | G80: 45860 | H80: 45860 | I80: seats_change | J80: 14 | K80: 18 | L80: seats | M80: Team expansion - mid-year headcount increase | N80: Sales Hub | O80: Monthly | P80: 110 | Q80: 0
A81: EVT080 | B81: SUB029 | C81: CUST029 | D81: Halifax Healthcare Tech | E81: Eastern Canada | F81: 45870 | G81: 45872 | H81: 45872 | I81: price_change | J81: 90 | K81: 85 | L81: price_per_seat | M81: Renewal negotiation - competitive pricing match | N81: Marketing Pro | O81: Monthly | P81: 85 | Q81: 0
A82: EVT081 | B82: SUB032 | C82: CUST032 | D82: BC Manufacturing Systems | E82: Western Canada | F82: 45870 | G82: 45881 | H82: 45881 | I82: plan_upgrade | J82: Analytics Growth | K82: Analytics Enterprise | L82: plan_name | M82: Enterprise SSO and audit logs required | N82: Analytics Enterprise | O82: Monthly | P82: 180 | Q82: 0
A83: EVT082 | B83: SUB017 | C83: CUST017 | D83: Capital Education Tech | E83: Eastern Canada | F83: 45870 | G83: 45888 | H83: 45888 | I83: plan_downgrade | J83: Analytics Growth | K83: Analytics Starter | L83: plan_name | M83: Reduced usage - advanced features no longer needed | N83: Analytics Starter | O83: Monthly | P83: 45 | Q83: 0
A84: EVT083 | B84: SUB022 | C84: CUST022 | D84: Toronto Tech Ventures | E84: Eastern Canada | F84: 45870 | G84: 45889 | H84: 45889 | I84: seats_change | J84: 28 | K84: 33 | L84: seats | M84: Team expansion - ops team grew | N84: Platform Suite | O84: Monthly | P84: 150 | Q84: 0
A85: EVT084 | B85: SUB055 | C85: CUST004 | D85: Prairie Commerce Group | E85: Western Canada | F85: 45870 | G85: 45899 | H85: 45899 | I85: cancelled | J85: active | K85: churned | L85: status | M85: Switched to competitor | N85: Analytics Enterprise | O85: Monthly | P85: 180 | Q85: 0
A86: EVT085 | B86: SUB030 | C86: CUST030 | D86: Alberta E-commerce Hub | E86: Western Canada | F86: 45901 | G86: 45905 | H86: 45905 | I86: plan_upgrade | J86: Analytics Starter | K86: Analytics Growth | L86: plan_name | M86: Upgraded for advanced analytics and API access | N86: Analytics Growth | O86: Monthly | P86: 95 | Q86: 0
A87: EVT086 | B87: SUB053 | C87: CUST027 | D87: Pacific Finance Corp | E87: Western Canada | F87: 45901 | G87: 45910 | H87: 45910 | I87: seats_change | J87: 26 | K87: 31 | L87: seats | M87: Department expansion - data team scaling | N87: Analytics Enterprise | O87: Monthly | P87: 180 | Q87: 0
A88: EVT087 | B88: SUB033 | C88: CUST033 | D88: Ottawa Retail Solutions | E88: Eastern Canada | F88: 45901 | G88: 45930 | H88: 45930 | I88: price_change | J88: 90 | K88: 85 | L88: price_per_seat | M88: Renewal negotiation - loyalty discount applied | N88: Marketing Pro | O88: Monthly | P88: 85 | Q88: 0
A89: EVT088 | B89: SUB024 | C89: CUST024 | D89: Western Retail Group | E89: Western Canada | F89: 45931 | G89: 45935 | H89: 45935 | I89: seats_change | J89: 26 | K89: 31 | L89: seats | M89: New department added - customer success team | N89: Marketing Pro | O89: Monthly | P89: 85 | Q89: 0
A90: EVT089 | B90: SUB062 | C90: CUST023 | D90: Island Media Productions | E90: Eastern Canada | F90: 45931 | G90: 45945 | H90: 45945 | I90: created | M90: Returning customer â€” reactivation | N90: Marketing Pro | O90: Monthly | P90: 85 | Q90: 0
A91: EVT090 | B91: SUB036 | C91: CUST036 | D91: Manitoba Finance Group | E91: Central Canada | F91: 45931 | G91: 45950 | H91: 45950 | I91: plan_upgrade | J91: Analytics Starter | K91: Analytics Growth | L91: plan_name | M91: Reached Starter usage limits - upgraded | N91: Analytics Growth | O91: Monthly | P91: 95 | Q91: 0
A92: EVT091 | B92: SUB015 | C92: CUST015 | D92: BC Retail Networks | E92: Western Canada | F92: 45962 | G92: 45962 | H92: 45962 | I92: discount_added | J92: 0 | K92: 10 | L92: discount_percent | M92: Retention discount - customer at-risk of churning | N92: Analytics Growth | O92: Monthly | P92: 95 | Q92: 10
A93: EVT092 | B93: SUB039 | C93: CUST039 | D93: Toronto Commerce Cloud | E93: Eastern Canada | F93: 45962 | G93: 45976 | H93: 45976 | I93: seats_change | J93: 32 | K93: 29 | L93: seats | M93: Restructuring - reduced team size | N93: Marketing Pro | O93: Monthly | P93: 85 | Q93: 0
A94: EVT093 | B94: SUB047 | C94: CUST022 | D94: Toronto Tech Ventures | E94: Eastern Canada | F94: 45992 | G94: 45999 | H94: 45999 | I94: seats_change | J94: 22 | K94: 26 | L94: seats | M94: Year-end headcount increase | N94: Sales Hub | O94: Monthly | P94: 110 | Q94: 0
A95: EVT094 | B95: SUB050 | C95: CUST007 | D95: Ontario Manufacturing Tech | E95: Eastern Canada | F95: 45992 | G95: 46006 | H95: 46006 | I95: discount_added | J95: 0 | K95: 12 | L95: discount_percent | M95: Retention discount - at-risk account escalated | N95: Analytics Starter | O95: Monthly | P95: 45 | Q95: 12
A96: EVT095 | B96: SUB015 | C96: CUST015 | D96: BC Retail Networks | E96: Western Canada | F96: 45992 | G96: 46021 | H96: 46021 | I96: cancelled | J96: active | K96: churned | L96: status | M96: Switched to competitor | N96: Analytics Growth | O96: Monthly | P96: 95 | Q96: 10
A97: EVT096 | B97: SUB040 | C97: CUST040 | D97: BC Education Innovations | E97: Western Canada | F97: 46023 | G97: 46048 | H97: 46048 | I97: created | N97: Analytics Growth | O97: Monthly | P97: 95 | Q97: 0
A98: EVT097 | B98: SUB050 | C98: CUST007 | D98: Ontario Manufacturing Tech | E98: Eastern Canada | F98: 46054 | G98: 46073 | H98: 46073 | I98: cancelled | J98: active | K98: churned | L98: status | M98: Poor support | N98: Analytics Starter | O98: Monthly | P98: 45 | Q98: 12

Sheet Raw Cash
A1: month | B1: invoice_count | C1: revenue | D1: running_total | E1: prior_month_revenue | F1: pct_change
A2: 45292 | B2: 2 | C2: 48700 | D2: 48700
A3: 45323 | B3: 4 | C3: 10185 | D3: 58885 | E3: 48700 | F3: -79.1
A4: 45352 | B4: 6 | C4: 77640 | D4: 136525 | E4: 10185 | F4: 662.3
A5: 45383 | B5: 8 | C5: 78930 | D5: 215455 | E5: 77640 | F5: 1.7
A6: 45413 | B6: 10 | C6: 17580 | D6: 233035 | E6: 78930 | F6: -77.7
A7: 45444 | B7: 13 | C7: 20595 | D7: 253630 | E7: 17580 | F7: 17.2
A8: 45474 | B8: 16 | C8: 26400 | D8: 280030 | E8: 20595 | F8: 28.2
A9: 45505 | B9: 19 | C9: 106740 | D9: 386770 | E9: 26400 | F9: 304.3
A10: 45536 | B10: 22 | C10: 42010 | D10: 428780 | E10: 106740 | F10: -60.6
A11: 45566 | B11: 25 | C11: 51390 | D11: 480170 | E11: 42010 | F11: 22.3
A12: 45597 | B12: 28 | C12: 55700 | D12: 535870 | E12: 51390 | F12: 8.4
A13: 45627 | B13: 31 | C13: 144560 | D13: 680430 | E13: 55700 | F13: 159.5
A14: 45658 | B14: 33 | C14: 139635 | D14: 820065 | E14: 144560 | F14: -3.4
... A27: 46054 | B27: 2 | C27: 2075 | D27: 2475630 | E27: 179985 | F27: -98.8

Sheet Ref
A1: plan_name | B1: monthly_price
A2: Analytics Starter | B2: 45
A3: Analytics Growth | B3: 95
A4: Analytics Enterprise | B4: 180
A5: Marketing Pro | B5: 85
A6: Sales Hub | B6: 110
A7: Platform Suite | B7: 150
A9: SaaS Growth Benchmarks
A10: Metric | B10: Threshold | C10: Label
A11: MoM Growth | B11: > 10% | C11: Exceptional (early stage)
A12: MoM Growth | B12: 5 – 10% | C12: Strong
A13: MoM Growth | B13: 2 – 5% | C13: Good (post-PMF)
A14: MoM Growth | B14: 0 – 2% | C14: Stalling
A15: MoM Growth | B15: < 0% | C15: Declining
A16: CMGR 6-month | B16: > 15% | C16: Exceptional
A17: CMGR 6-month | B17: 10 – 15% | C17: Strong
A18: CMGR 6-month | B18: 5 – 10% | C18: Good
A19: CMGR 6-month | B19: 2 – 5% | C19: Moderate
A20: CMGR 6-month | B20: < 2% | C20: Stalling
A21: Quick Ratio | B21: > 4.0 | C21: Excellent
... A24: Quick Ratio | B24: < 1.0 | C24: Shrinking

Sheet Engine
A1: event_id | B1: subscription_id | C1: customer_id | D1: company_name | E1: region | F1: month | G1: event_date | H1: event_type | I1: old_value | J1: new_value | K1: field_changed | L1: reason | M1: plan_name | N1: billing_cycle | O1: seats | P1: price_per_seat | Q1: discount_percent | R1: movement | S1: mrr_delta
A2: EVT001 | B2: SUB001 | C2: CUST001 | D2: TechVision Solutions | E2: Eastern Canada | F2: 45292 | G2: 45299 | H2: created | M2: Analytics Growth | N2: Monthly | O2: 20 | P2: 95 | Q2: 0 | R2: {=_xlfn.IFS(H2="created", "New", H2="cancelled", "Churned", AND(H2="seats_change", J2 > I2), "Expansion", AND(H2="seats_change", J2 < I2), "Contraction", AND(H2="price_change", J2 > I2), "Expansion", AND(H2="price_change", J2 < I2), "Contraction", H2="plan_upgrade", "Expansion", H2="plan_downgrade", "Contraction", H2="discount_added", "Contraction")} -> New | S2: {=_xlfn.IFS(H2="created",O2*P2*(1-Q2/100),H2="cancelled",-(O2*P2*(1-Q2/100)),H2="seats_change",(J2-I2)*P2*(1-Q2/100),H2="price_change",(J2-I2)*O2*(1-Q2/100),H2="discount_added",-(O2*P2*(J2-I2)/100),H2="plan_upgrade",O2*(_xlfn.XLOOKUP(J2,tbl_Plans[plan_name],tbl_Plans[monthly_price])-_xlfn.XLOOKUP(I2,tbl_Plans[plan_name],tbl_Plans[monthly_price]))*(1-Q2/100),H2="plan_downgrade",O2*(_xlfn.XLOOKUP(J2,tbl_Plans[plan_name],tbl_Plans[monthly_price])-_xlfn.XLOOKUP(I2,tbl_Plans[plan_name],tbl_Plans[monthly_price]))*(1-Q2/100))*IF(N2="Annual",1/12,1)} -> 1900
A3: EVT002 | B3: SUB002 | C3: CUST002 | D3: Pacific Analytics Inc | E3: Western Canada | F3: 45292 | G3: 45313 | H3: created | M3: Platform Suite | N3: Annual | O3: 26 | P3: 1800 | Q3: 0 | R3: {=_xlfn.IFS(H3="created", "New", H3="cancelled", "Churned", AND(H3="seats_change", J3 > I3), "Expansion", AND(H3="seats_change", J3 < I3), "Contraction", AND(H3="price_change", J3 > I3), "Expansion", AND(H3="price_change", J3 < I3), "Contraction", H3="plan_upgrade", "Expansion", H3="plan_downgrade", "Contraction", H3="discount_added", "Contraction")} -> New | S3: {=_xlfn.IFS(H3="created",O3*P3*(1-Q3/100),H3="cancelled",-(O3*P3*(1-Q3/100)),H3="seats_change",(J3-I3)*P3*(1-Q3/100),H3="price_change",(J3-I3)*O3*(1-Q3/100),H3="discount_added",-(O3*P3*(J3-I3)/100),H3="plan_upgrade",O3*(_xlfn.XLOOKUP(J3,tbl_Plans[plan_name],tbl_Plans[monthly_price])-_xlfn.XLOOKUP(I3,tbl_Plans[plan_name],tbl_Plans[monthly_price]))*(1-Q3/100),H3="plan_downgrade",O3*(_xlfn.XLOOKUP(J3,tbl_Plans[plan_name],tbl_Plans[monthly_price])-_xlfn.XLOOKUP(I3,tbl_Plans[plan_name],tbl_Plans[monthly_price]))*(1-Q3/100))*IF(N3="Annual",1/12,1)} -> 3900
A4: EVT003 | B4: SUB003 | C4: CUST003 | D4: Maple Healthcare Systems | E4: Eastern Canada | F4: 45323 | G4: 45327 | H4: created | M4: Marketing Pro | N4: Monthly | O4: 23 | P4: 85 | Q4: 0 | R4: {=_xlfn.IFS(H4="created", "New", H4="cancelled", "Churned", AND(H4="seats_change", J4 > I4), "Expansion", AND(H4="seats_change", J4 < I4), "Contraction", AND(H4="price_change", J4 > I4), "Expansion", AND(H4="price_change", J4 < I4), "Contraction", H4="plan_upgrade", "Expansion", H4="plan_downgrade", "Contraction", H4="discount_added", "Contraction")} -> New | S4: {=_xlfn.IFS(H4="created",O4*P4*(1-Q4/100),H4="cancelled",-(O4*P4*(1-Q4/100)),H4="seats_change",(J4-I4)*P4*(1-Q4/100),H4="price_change",(J4-I4)*O4*(1-Q4/100),H4="discount_added",-(O4*P4*(J4-I4)/100),H4="plan_upgrade",O4*(_xlfn.XLOOKUP(J4,tbl_Plans[plan_name],tbl_Plans[monthly_price])-_xlfn.XLOOKUP(I4,tbl_Plans[plan_name],tbl_Plans[monthly_price]))*(1-Q4/100),H4="plan_downgrade",O4*(_xlfn.XLOOKUP(J4,tbl_Plans[plan_name],tbl_Plans[monthly_price])-_xlfn.XLOOKUP(I4,tbl_Plans[plan_name],tbl_Plans[monthly_price]))*(1-Q4/100))*IF(N4="Annual",1/12,1)} -> 1955
A5: EVT004 | B5: SUB004 | C5: CUST004 | D5: Prairie Commerce Group | E5: Western Canada | F5: 45323 | G5: 45341 | H5: created | M5: Sales Hub | N5: Monthly | O5: 18 | P5: 110 | Q5: 0 | R5: {=_xlfn.IFS(H5="created", "New", H5="cancelled", "Churned", AND(H5="seats_change", J5 > I5), "Expansion", AND(H5="seats_change", J5 < I5), "Contraction", AND(H5="price_change", J5 > I5), "Expansion", AND(H5="price_change", J5 < I5), "Contraction", H5="plan_upgrade", "Expansion", H5="plan_downgrade", "Contraction", H5="discount_added", "Contraction")} -> New | S5: {=_xlfn.IFS(H5="created",O5*P5*(1-Q5/100),H5="cancelled",-(O5*P5*(1-Q5/100)),H5="seats_change",(J5-I5)*P5*(1-Q5/100),H5="price_change",(J5-I5)*O5*(1-Q5/100),H5="discount_added",-(O5*P5*(J5-I5)/100),H5="plan_upgrade",O5*(_xlfn.XLOOKUP(J5,tbl_Plans[plan_name],tbl_Plans[monthly_price])-_xlfn.XLOOKUP(I5,tbl_Plans[plan_name],tbl_Plans[monthly_price]))*(1-Q5/100),H5="plan_downgrade",O5*(_xlfn.XLOOKUP(J5,tbl_Plans[plan_name],tbl_Plans[monthly_price])-_xlfn.XLOOKUP(I5,tbl_Plans[plan_name],tbl_Plans[monthly_price]))*(1-Q5/100))*IF(N5="Annual",1/12,1)} -> 1980
A6: EVT005 | B6: SUB055 | C6: CUST004 | D6: Prairie Commerce Group | E6: Western Canada | F6: 45323 | G6: 45341 | H6: created | M6: Analytics Enterprise | N6: Monthly | O6: 26 | P6: 180 | Q6: 0 | R6: {=_xlfn.IFS(H6="created", "New", H6="cancelled", "Churned", AND(H6="seats_change", J6 > I6), "Expansion", AND(H6="seats_change", J6 < I6), "Contraction", AND(H6="price_change", J6 > I6), "Expansion", AND(H6="price_change", J6 < I6), "Contraction", H6="plan_upgrade", "Expansion", H6="plan_downgrade", "Contraction", H6="discount_added", "Contraction")} -> New | S6: {=_xlfn.IFS(H6="created",O6*P6*(1-Q6/100),H6="cancelled",-(O6*P6*(1-Q6/100)),H6="seats_change",(J6-I6)*P6*(1-Q6/100),H6="price_change",(J6-I6)*O6*(1-Q6/100),H6="discount_added",-(O6*P6*(J6-I6)/100),H6="plan_upgrade",O6*(_xlfn.XLOOKUP(J6,tbl_Plans[plan_name],tbl_Plans[monthly_price])-_xlfn.XLOOKUP(I6,tbl_Plans[plan_name],tbl_Plans[monthly_price]))*(1-Q6/100),H6="plan_downgrade",O6*(_xlfn.XLOOKUP(J6,tbl_Plans[plan_name],tbl_Plans[monthly_price])-_xlfn.XLOOKUP(I6,tbl_Plans[plan_name],tbl_Plans[monthly_price]))*(1-Q6/100))*IF(N6="Annual",1/12,1)} -> 4680
A7: EVT006 | B7: SUB005 | C7: CUST005 | D7: Atlantic Media Corp | E7: Eastern Canada | F7: 45352 | G7: 45355 | H7: created | M7: Analytics Starter | N7: Monthly | O7: 11 | P7: 45 | Q7: 0 | R7: {=_xlfn.IFS(H7="created", "New", H7="cancelled", "Churned", AND(H7="seats_change", J7 > I7), "Expansion", AND(H7="seats_change", J7 < I7), "Contraction", AND(H7="price_change", J7 > I7), "Expansion", AND(H7="price_change", J7 < I7), "Contraction", H7="plan_upgrade", "Expansion", H7="plan_downgrade", "Contraction", H7="discount_added", "Contraction")} -> New | S7: {=_xlfn.IFS(H7="created",O7*P7*(1-Q7/100),H7="cancelled",-(O7*P7*(1-Q7/100)),H7="seats_change",(J7-I7)*P7*(1-Q7/100),H7="price_change",(J7-I7)*O7*(1-Q7/100),H7="discount_added",-(O7*P7*(J7-I7)/100),H7="plan_upgrade",O7*(_xlfn.XLOOKUP(J7,tbl_Plans[plan_name],tbl_Plans[monthly_price])-_xlfn.XLOOKUP(I7,tbl_Plans[plan_name],tbl_Plans[monthly_price]))*(1-Q7/100),H7="plan_downgrade",O7*(_xlfn.XLOOKUP(J7,tbl_Plans[plan_name],tbl_Plans[monthly_price])-_xlfn.XLOOKUP(I7,tbl_Plans[plan_name],tbl_Plans[monthly_price]))*(1-Q7/100))*IF(N7="Annual",1/12,1)} -> 495
A8: EVT007 | B8: SUB006 | C8: CUST006 | D8: Northern Retail Solutions | E8: Western Canada | F8: 45352 | G8: 45369 | H8: created | M8: Analytics Enterprise | N8: Annual | O8: 31 | P8: 2160 | Q8: 0 | R8: {=_xlfn.IFS(H8="created", "New", H8="cancelled", "Churned", AND(H8="seats_change", J8 > I8), "Expansion", AND(H8="seats_change", J8 < I8), "Contraction", AND(H8="price_change", J8 > I8), "Expansion", AND(H8="price_change", J8 < I8), "Contraction", H8="plan_upgrade", "Expansion", H8="plan_downgrade", "Contraction", H8="discount_added", "Contraction")} -> New | S8: {=_xlfn.IFS(H8="created",O8*P8*(1-Q8/100),H8="cancelled",-(O8*P8*(1-Q8/100)),H8="seats_change",(J8-I8)*P8*(1-Q8/100),H8="price_change",(J8-I8)*O8*(1-Q8/100),H8="discount_added",-(O8*P8*(J8-I8)/100),H8="plan_upgrade",O8*(_xlfn.XLOOKUP(J8,tbl_Plans[plan_name],tbl_Plans[monthly_price])-_xlfn.XLOOKUP(I8,tbl_Plans[plan_name],tbl_Plans[monthly_price]))*(1-Q8/100),H8="plan_downgrade",O8*(_xlfn.XLOOKUP(J8,tbl_Plans[plan_name],tbl_Plans[monthly_price])-_xlfn.XLOOKUP(I8,tbl_Plans[plan_name],tbl_Plans[monthly_price]))*(1-Q8/100))*IF(N8="Annual",1/12,1)} -> 5580
A9: EVT008 | B9: SUB007 | C9: CUST007 | D9: Ontario Manufacturing Tech | E9: Eastern Canada | F9: 45383 | G9: 45383 | H9: created | M9: Marketing Pro | N9: Monthly | O9: 16 | P9: 85 | Q9: 0 | R9: {=_xlfn.IFS(H9="created", "New", H9="cancelled", "Churned", AND(H9="seats_change", J9 > I9), "Expansion", AND(H9="seats_change", J9 < I9), "Contraction", AND(H9="price_change", J9 > I9), "Expansion", AND(H9="price_change", J9 < I9), "Contraction", H9="plan_upgrade", "Expansion", H9="plan_downgrade", "Contraction", H9="discount_added", "Contraction")} -> New | S9: {=_xlfn.IFS(H9="created",O9*P9*(1-Q9/100),H9="cancelled",-(O9*P9*(1-Q9/100)),H9="seats_change",(J9-I9)*P9*(1-Q9/100),H9="price_change",(J9-I9)*O9*(1-Q9/100),H9="discount_added",-(O9*P9*(J9-I9)/100),H9="plan_upgrade",O9*(_xlfn.XLOOKUP(J9,tbl_Plans[plan_name],tbl_Plans[monthly_price])-_xlfn.XLOOKUP(I9,tbl_Plans[plan_name],tbl_Plans[monthly_price]))*(1-Q9/100),H9="plan_downgrade",O9*(_xlfn.XLOOKUP(J9,tbl_Plans[plan_name],tbl_Plans[monthly_price])-_xlfn.XLOOKUP(I9,tbl_Plans[plan_name],tbl_Plans[monthly_price]))*(1-Q9/100))*IF(N9="Annual",1/12,1)} -> 1360
A10: EVT009 | B10: SUB050 | C10: CUST007 | D10: Ontario Manufacturing Tech | E10: Eastern Canada | F10: 45383 | G10: 45383 | H10: created | M10: Analytics Starter | N10: Monthly | O10: 15 | P10: 45 | Q10: 12 | R10: {=_xlfn.IFS(H10="created", "New", H10="cancelled", "Churned", AND(H10="seats_change", J10 > I10), "Expansion", AND(H10="seats_change", J10 < I10), "Contraction", AND(H10="price_change", J10 > I10), "Expansion", AND(H10="price_change", J10 < I10), "Contraction", H10="plan_upgrade", "Expansion", H10="plan_downgrade", "Contraction", H10="discount_added", "Contraction")} -> New | S10: {=_xlfn.IFS(H10="created",O10*P10*(1-Q10/100),H10="cancelled",-(O10*P10*(1-Q10/100)),H10="seats_change",(J10-I10)*P10*(1-Q10/100),H10="price_change",(J10-I10)*O10*(1-Q10/100),H10="discount_added",-(O10*P10*(J10-I10)/100),H10="plan_upgrade",O10*(_xlfn.XLOOKUP(J10,tbl_Plans[plan_name],tbl_Plans[monthly_price])-_xlfn.XLOOKUP(I10,tbl_Plans[plan_name],tbl_Plans[monthly_price]))*(1-Q10/100),H10="plan_downgrade",O10*(_xlfn.XLOOKUP(J10,tbl_Plans[plan_name],tbl_Plans[monthly_price])-_xlfn.XLOOKUP(I10,tbl_Plans[plan_name],tbl_Plans[monthly_price]))*(1-Q10/100))*IF(N10="Annual",1/12,1)} -> 594
A11: EVT010 | B11: SUB008 | C11: CUST008 | D11: Quantum Education Platform | E11: Eastern Canada | F11: 45383 | G11: 45397 | H11: created | M11: Analytics Growth | N11: Monthly | O11: 22 | P11: 95 | Q11: 0 | R11: {=_xlfn.IFS(H11="created", "New", H11="cancelled", "Churned", AND(H11="seats_change", J11 > I11), "Expansion", AND(H11="seats_change", J11 < I11), "Contraction", AND(H11="price_change", J11 > I11), "Expansion", AND(H11="price_change", J11 < I11), "Contraction", H11="plan_upgrade", "Expansion", H11="plan_downgrade", "Contraction", H11="discount_added", "Contraction")} -> New | S11: {=_xlfn.IFS(H11="created",O11*P11*(1-Q11/100),H11="cancelled",-(O11*P11*(1-Q11/100)),H11="seats_change",(J11-I11)*P11*(1-Q11/100),H11="price_change",(J11-I11)*O11*(1-Q11/100),H11="discount_added",-(O11*P11*(J11-I11)/100),H11="plan_upgrade",O11*(_xlfn.XLOOKUP(J11,tbl_Plans[plan_name],tbl_Plans[monthly_price])-_xlfn.XLOOKUP(I11,tbl_Plans[plan_name],tbl_Plans[monthly_price]))*(1-Q11/100),H11="plan_downgrade",O11*(_xlfn.XLOOKUP(J11,tbl_Plans[plan_name],tbl_Plans[monthly_price])-_xlfn.XLOOKUP(I11,tbl_Plans[plan_name],tbl_Plans[monthly_price]))*(1-Q11/100))*IF(N11="Annual",1/12,1)} -> 2090
A12: EVT011 | B12: SUB009 | C12: CUST009 | D12: West Coast Logistics | E12: Western Canada | F12: 45383 | G12: 45411 | H12: created | M12: Platform Suite | N12: Annual | O12: 36 | P12: 1800 | Q12: 0 | R12: {=_xlfn.IFS(H12="created", "New", H12="cancelled", "Churned", AND(H12="seats_change", J12 > I12), "Expansion", AND(H12="seats_change", J12 < I12), "Contraction", AND(H12="price_change", J12 > I12), "Expansion", AND(H12="price_change", J12 < I12), "Contraction", H12="plan_upgrade", "Expansion", H12="plan_downgrade", "Contraction", H12="discount_added", "Contraction")} -> New | S12: {=_xlfn.IFS(H12="created",O12*P12*(1-Q12/100),H12="cancelled",-(O12*P12*(1-Q12/100)),H12="seats_change",(J12-I12)*P12*(1-Q12/100),H12="price_change",(J12-I12)*O12*(1-Q12/100),H12="discount_added",-(O12*P12*(J12-I12)/100),H12="plan_upgrade",O12*(_xlfn.XLOOKUP(J12,tbl_Plans[plan_name],tbl_Plans[monthly_price])-_xlfn.XLOOKUP(I12,tbl_Plans[plan_name],tbl_Plans[monthly_price]))*(1-Q12/100),H12="plan_downgrade",O12*(_xlfn.XLOOKUP(J12,tbl_Plans[plan_name],tbl_Plans[monthly_price])-_xlfn.XLOOKUP(I12,tbl_Plans[plan_name],tbl_Plans[monthly_price]))*(1-Q12/100))*IF(N12="Annual",1/12,1)} -> 5400
A13: EVT012 | B13: SUB010 | C13: CUST010 | D13: Montreal Finance Hub | E13: Eastern Canada | F13: 45413 | G13: 45425 | H13: created | M13: Analytics Starter | N13: Monthly | O13: 13 | P13: 45 | Q13: 0 | R13: {=_xlfn.IFS(H13="created", "New", H13="cancelled", "Churned", AND(H13="seats_change", J13 > I13), "Expansion", AND(H13="seats_change", J13 < I13), "Contraction", AND(H13="price_change", J13 > I13), "Expansion", AND(H13="price_change", J13 < I13), "Contraction", H13="plan_upgrade", "Expansion", H13="plan_downgrade", "Contraction", H13="discount_added", "Contraction")} -> New | S13: {=_xlfn.IFS(H13="created",O13*P13*(1-Q13/100),H13="cancelled",-(O13*P13*(1-Q13/100)),H13="seats_change",(J13-I13)*P13*(1-Q13/100),H13="price_change",(J13-I13)*O13*(1-Q13/100),H13="discount_added",-(O13*P13*(J13-I13)/100),H13="plan_upgrade",O13*(_xlfn.XLOOKUP(J13,tbl_Plans[plan_name],tbl_Plans[monthly_price])-_xlfn.XLOOKUP(I13,tbl_Plans[plan_name],tbl_Plans[monthly_price]))*(1-Q13/100),H13="plan_downgrade",O13*(_xlfn.XLOOKUP(J13,tbl_Plans[plan_name],tbl_Plans[monthly_price])-_xlfn.XLOOKUP(I13,tbl_Plans[plan_name],tbl_Plans[monthly_price]))*(1-Q13/100))*IF(N13="Annual",1/12,1)} -> 585
... A23: EVT022 | B23: SUB017 | C23: CUST017 | D23: Capital Education Tech | E23: Eastern Canada | F23: 45505 | G23: 45523 | H23: created | M23: Analytics Starter | N23: Monthly | O23: 12 | P23: 45 | Q23: 0 | R23: {=_xlfn.IFS(H23="created", "New", H23="cancelled", "Churned", AND(H23="seats_change", J23 > I23), "Expansion", AND(H23="seats_change", J23 < I23), "Contraction", AND(H23="price_change", J23 > I23), "Expansion", AND(H23="price_change", J23 < I23), "Contraction", H23="plan_upgrade", "Expansion", H23="plan_downgrade", "Contraction", H23="discount_added", "Contraction")} -> New | S23: {=_xlfn.IFS(H23="created",O23*P23*(1-Q23/100),H23="cancelled",-(O23*P23*(1-Q23/100)),H23="seats_change",(J23-I23)*P23*(1-Q23/100),H23="price_change",(J23-I23)*O23*(1-Q23/100),H23="discount_added",-(O23*P23*(J23-I23)/100),H23="plan_upgrade",O23*(_xlfn.XLOOKUP(J23,tbl_Plans[plan_name],tbl_Plans[monthly_price])-_xlfn.XLOOKUP(I23,tbl_Plans[plan_name],tbl_Plans[monthly_price]))*(1-Q23/100),H23="plan_downgrade",O23*(_xlfn.XLOOKUP(J23,tbl_Plans[plan_name],tbl_Plans[monthly_price])-_xlfn.XLOOKUP(I23,tbl_Plans[plan_name],tbl_Plans[monthly_price]))*(1-Q23/100))*IF(N23="Annual",1/12,1)} -> 540
A24: EVT023 | B24: SUB001 | C24: CUST001 | D24: TechVision Solutions | E24: Eastern Canada | F24: 45505 | G24: 45531 | H24: cancelled | I24: active | J24: churned | K24: status | L24: Missing features | M24: Analytics Growth | N24: Monthly | O24: 20 | P24: 95 | Q24: 0 | R24: {=_xlfn.IFS(H24="created", "New", H24="cancelled", "Churned", AND(H24="seats_change", J24 > I24), "Expansion", AND(H24="seats_change", J24 < I24), "Contraction", AND(H24="price_change", J24 > I24), "Expansion", AND(H24="price_change", J24 < I24), "Contraction", H24="plan_upgrade", "Expansion", H24="plan_downgrade", "Contraction", H24="discount_added", "Contraction")} -> Churned | S24: {=_xlfn.IFS(H24="created",O24*P24*(1-Q24/100),H24="cancelled",-(O24*P24*(1-Q24/100)),H24="seats_change",(J24-I24)*P24*(1-Q24/100),H24="price_change",(J24-I24)*O24*(1-Q24/100),H24="discount_added",-(O24*P24*(J24-I24)/100),H24="plan_upgrade",O24*(_xlfn.XLOOKUP(J24,tbl_Plans[plan_name],tbl_Plans[monthly_price])-_xlfn.XLOOKUP(I24,tbl_Plans[plan_name],tbl_Plans[monthly_price]))*(1-Q24/100),H24="plan_downgrade",O24*(_xlfn.XLOOKUP(J24,tbl_Plans[plan_name],tbl_Plans[monthly_price])-_xlfn.XLOOKUP(I24,tbl_Plans[plan_name],tbl_Plans[monthly_price]))*(1-Q24/100))*IF(N24="Annual",1/12,1)} -> -1900
A25: EVT024 | B25: SUB018 | C25: CUST018 | D25: Vancouver FinTech Labs | E25: Western Canada | F25: 45536 | G25: 45537 | H25: created | M25: Analytics Enterprise | N25: Monthly | O25: 35 | P25: 180 | Q25: 0 | R25: {=_xlfn.IFS(H25="created", "New", H25="cancelled", "Churned", AND(H25="seats_change", J25 > I25), "Expansion", AND(H25="seats_change", J25 < I25), "Contraction", AND(H25="price_change", J25 > I25), "Expansion", AND(H25="price_change", J25 < I25), "Contraction", H25="plan_upgrade", "Expansion", H25="plan_downgrade", "Contraction", H25="discount_added", "Contraction")} -> New | S25: {=_xlfn.IFS(H25="created",O25*P25*(1-Q25/100),H25="cancelled",-(O25*P25*(1-Q25/100)),H25="seats_change",(J25-I25)*P25*(1-Q25/100),H25="price_change",(J25-I25)*O25*(1-Q25/100),H25="discount_added",-(O25*P25*(J25-I25)/100),H25="plan_upgrade",O25*(_xlfn.XLOOKUP(J25,tbl_Plans[plan_name],tbl_Plans[monthly_price])-_xlfn.XLOOKUP(I25,tbl_Plans[plan_name],tbl_Plans[monthly_price]))*(1-Q25/100),H25="plan_downgrade",O25*(_xlfn.XLOOKUP(J25,tbl_Plans[plan_name],tbl_Plans[monthly_price])-_xlfn.XLOOKUP(I25,tbl_Plans[plan_name],tbl_Plans[monthly_price]))*(1-Q25/100))*IF(N25="Annual",1/12,1)} -> 6300
A26: EVT025 | B26: SUB042 | C26: CUST003 | D26: Maple Healthcare Systems | E26: Eastern Canada | F26: 45536 | G26: 45545 | H26: created | M26: Sales Hub | N26: Monthly | O26: 19 | P26: 110 | Q26: 0 | R26: {=_xlfn.IFS(H26="created", "New", H26="cancelled", "Churned", AND(H26="seats_change", J26 > I26), "Expansion", AND(H26="seats_change", J26 < I26), "Contraction", AND(H26="price_change", J26 > I26), "Expansion", AND(H26="price_change", J26 < I26), "Contraction", H26="plan_upgrade", "Expansion", H26="plan_downgrade", "Contraction", H26="discount_added", "Contraction")} -> New | S26: {=_xlfn.IFS(H26="created",O26*P26*(1-Q26/100),H26="cancelled",-(O26*P26*(1-Q26/100)),H26="seats_change",(J26-I26)*P26*(1-Q26/100),H26="price_change",(J26-I26)*O26*(1-Q26/100),H26="discount_added",-(O26*P26*(J26-I26)/100),H26="plan_upgrade",O26*(_xlfn.XLOOKUP(J26,tbl_Plans[plan_name],tbl_Plans[monthly_price])-_xlfn.XLOOKUP(I26,tbl_Plans[plan_name],tbl_Plans[monthly_price]))*(1-Q26/100),H26="plan_downgrade",O26*(_xlfn.XLOOKUP(J26,tbl_Plans[plan_name],tbl_Plans[monthly_price])-_xlfn.XLOOKUP(I26,tbl_Plans[plan_name],tbl_Plans[monthly_price]))*(1-Q26/100))*IF(N26="Annual",1/12,1)} -> 2090
A27: EVT026 | B27: SUB019 | C27: CUST019 | D27: Central Healthcare Partners | E27: Central Canada | F27: 45536 | G27: 45551 | H27: created | M27: Marketing Pro | N27: Monthly | O27: 19 | P27: 85 | Q27: 0 | R27: {=_xlfn.IFS(H27="created", "New", H27="cancelled", "Churned", AND(H27="seats_change", J27 > I27), "Expansion", AND(H27="seats_change", J27 < I27), "Contraction", AND(H27="price_change", J27 > I27), "Expansion", AND(H27="price_change", J27 < I27), "Contraction", H27="plan_upgrade", "Expansion", H27="plan_downgrade", "Contraction", H27="discount_added", "Contraction")} -> New | S27: {=_xlfn.IFS(H27="created",O27*P27*(1-Q27/100),H27="cancelled",-(O27*P27*(1-Q27/100)),H27="seats_change",(J27-I27)*P27*(1-Q27/100),H27="price_change",(J27-I27)*O27*(1-Q27/100),H27="discount_added",-(O27*P27*(J27-I27)/100),H27="plan_upgrade",O27*(_xlfn.XLOOKUP(J27,tbl_Plans[plan_name],tbl_Plans[monthly_price])-_xlfn.XLOOKUP(I27,tbl_Plans[plan_name],tbl_Plans[monthly_price]))*(1-Q27/100),H27="plan_downgrade",O27*(_xlfn.XLOOKUP(J27,tbl_Plans[plan_name],tbl_Plans[monthly_price])-_xlfn.XLOOKUP(I27,tbl_Plans[plan_name],tbl_Plans[monthly_price]))*(1-Q27/100))*IF(N27="Annual",1/12,1)} -> 1615
A28: EVT027 | B28: SUB060 | C28: CUST019 | D28: Central Healthcare Partners | E28: Central Canada | F28: 45536 | G28: 45551 | H28: created | M28: Sales Hub | N28: Monthly | O28: 16 | P28: 110 | Q28: 0 | R28: {=_xlfn.IFS(H28="created", "New", H28="cancelled", "Churned", AND(H28="seats_change", J28 > I28), "Expansion", AND(H28="seats_change", J28 < I28), "Contraction", AND(H28="price_change", J28 > I28), "Expansion", AND(H28="price_change", J28 < I28), "Contraction", H28="plan_upgrade", "Expansion", H28="plan_downgrade", "Contraction", H28="discount_added", "Contraction")} -> New | S28: {=_xlfn.IFS(H28="created",O28*P28*(1-Q28/100),H28="cancelled",-(O28*P28*(1-Q28/100)),H28="seats_change",(J28-I28)*P28*(1-Q28/100),H28="price_change",(J28-I28)*O28*(1-Q28/100),H28="discount_added",-(O28*P28*(J28-I28)/100),H28="plan_upgrade",O28*(_xlfn.XLOOKUP(J28,tbl_Plans[plan_name],tbl_Plans[monthly_price])-_xlfn.XLOOKUP(I28,tbl_Plans[plan_name],tbl_Plans[monthly_price]))*(1-Q28/100),H28="plan_downgrade",O28*(_xlfn.XLOOKUP(J28,tbl_Plans[plan_name],tbl_Plans[monthly_price])-_xlfn.XLOOKUP(I28,tbl_Plans[plan_name],tbl_Plans[monthly_price]))*(1-Q28/100))*IF(N28="Annual",1/12,1)} -> 1760
A29: EVT028 | B29: SUB020 | C29: CUST020 | D29: Atlantic SaaS Systems | E29: Eastern Canada | F29: 45536 | G29: 45565 | H29: created | M29: Sales Hub | N29: Monthly | O29: 15 | P29: 110 | Q29: 0 | R29: {=_xlfn.IFS(H29="created", "New", H29="cancelled", "Churned", AND(H29="seats_change", J29 > I29), "Expansion", AND(H29="seats_change", J29 < I29), "Contraction", AND(H29="price_change", J29 > I29), "Expansion", AND(H29="price_change", J29 < I29), "Contraction", H29="plan_upgrade", "Expansion", H29="plan_downgrade", "Contraction", H29="discount_added", "Contraction")} -> New | S29: {=_xlfn.IFS(H29="created",O29*P29*(1-Q29/100),H29="cancelled",-(O29*P29*(1-Q29/100)),H29="seats_change",(J29-I29)*P29*(1-Q29/100),H29="price_change",(J29-I29)*O29*(1-Q29/100),H29="discount_added",-(O29*P29*(J29-I29)/100),H29="plan_upgrade",O29*(_xlfn.XLOOKUP(J29,tbl_Plans[plan_name],tbl_Plans[monthly_price])-_xlfn.XLOOKUP(I29,tbl_Plans[plan_name],tbl_Plans[monthly_price]))*(1-Q29/100),H29="plan_downgrade",O29*(_xlfn.XLOOKUP(J29,tbl_Plans[plan_name],tbl_Plans[monthly_price])-_xlfn.XLOOKUP(I29,tbl_Plans[plan_name],tbl_Plans[monthly_price]))*(1-Q29/100))*IF(N29="Annual",1/12,1)} -> 1650
A30: EVT029 | B30: SUB043 | C30: CUST006 | D30: Northern Retail Solutions | E30: Western Canada | F30: 45566 | G30: 45570 | H30: created | M30: Marketing Pro | N30: Monthly | O30: 33 | P30: 85 | Q30: 0 | R30: {=_xlfn.IFS(H30="created", "New", H30="cancelled", "Churned", AND(H30="seats_change", J30 > I30), "Expansion", AND(H30="seats_change", J30 < I30), "Contraction", AND(H30="price_change", J30 > I30), "Expansion", AND(H30="price_change", J30 < I30), "Contraction", H30="plan_upgrade", "Expansion", H30="plan_downgrade", "Contraction", H30="discount_added", "Contraction")} -> New | S30: {=_xlfn.IFS(H30="created",O30*P30*(1-Q30/100),H30="cancelled",-(O30*P30*(1-Q30/100)),H30="seats_change",(J30-I30)*P30*(1-Q30/100),H30="price_change",(J30-I30)*O30*(1-Q30/100),H30="discount_added",-(O30*P30*(J30-I30)/100),H30="plan_upgrade",O30*(_xlfn.XLOOKUP(J30,tbl_Plans[plan_name],tbl_Plans[monthly_price])-_xlfn.XLOOKUP(I30,tbl_Plans[plan_name],tbl_Plans[monthly_price]))*(1-Q30/100),H30="plan_downgrade",O30*(_xlfn.XLOOKUP(J30,tbl_Plans[plan_name],tbl_Plans[monthly_price])-_xlfn.XLOOKUP(I30,tbl_Plans[plan_name],tbl_Plans[monthly_price]))*(1-Q30/100))*IF(N30="Annual",1/12,1)} -> 2805
A31: EVT030 | B31: SUB021 | C31: CUST021 | D31: Calgary Commerce Solutions | E31: Western Canada | F31: 45566 | G31: 45579 | H31: created | M31: Analytics Growth | N31: Monthly | O31: 25 | P31: 95 | Q31: 0 | R31: {=_xlfn.IFS(H31="created", "New", H31="cancelled", "Churned", AND(H31="seats_change", J31 > I31), "Expansion", AND(H31="seats_change", J31 < I31), "Contraction", AND(H31="price_change", J31 > I31), "Expansion", AND(H31="price_change", J31 < I31), "Contraction", H31="plan_upgrade", "Expansion", H31="plan_downgrade", "Contraction", H31="discount_added", "Contraction")} -> New | S31: {=_xlfn.IFS(H31="created",O31*P31*(1-Q31/100),H31="cancelled",-(O31*P31*(1-Q31/100)),H31="seats_change",(J31-I31)*P31*(1-Q31/100),H31="price_change",(J31-I31)*O31*(1-Q31/100),H31="discount_added",-(O31*P31*(J31-I31)/100),H31="plan_upgrade",O31*(_xlfn.XLOOKUP(J31,tbl_Plans[plan_name],tbl_Plans[monthly_price])-_xlfn.XLOOKUP(I31,tbl_Plans[plan_name],tbl_Plans[monthly_price]))*(1-Q31/100),H31="plan_downgrade",O31*(_xlfn.XLOOKUP(J31,tbl_Plans[plan_name],tbl_Plans[monthly_price])-_xlfn.XLOOKUP(I31,tbl_Plans[plan_name],tbl_Plans[monthly_price]))*(1-Q31/100))*IF(N31="Annual",1/12,1)} -> 2375
A32: EVT031 | B32: SUB022 | C32: CUST022 | D32: Toronto Tech Ventures | E32: Eastern Canada | F32: 45566 | G32: 45593 | H32: created | M32: Platform Suite | N32: Monthly | O32: 33 | P32: 150 | Q32: 0 | R32: {=_xlfn.IFS(H32="created", "New", H32="cancelled", "Churned", AND(H32="seats_change", J32 > I32), "Expansion", AND(H32="seats_change", J32 < I32), "Contraction", AND(H32="price_change", J32 > I32), "Expansion", AND(H32="price_change", J32 < I32), "Contraction", H32="plan_upgrade", "Expansion", H32="plan_downgrade", "Contraction", H32="discount_added", "Contraction")} -> New | S32: {=_xlfn.IFS(H32="created",O32*P32*(1-Q32/100),H32="cancelled",-(O32*P32*(1-Q32/100)),H32="seats_change",(J32-I32)*P32*(1-Q32/100),H32="price_change",(J32-I32)*O32*(1-Q32/100),H32="discount_added",-(O32*P32*(J32-I32)/100),H32="plan_upgrade",O32*(_xlfn.XLOOKUP(J32,tbl_Plans[plan_name],tbl_Plans[monthly_price])-_xlfn.XLOOKUP(I32,tbl_Plans[plan_name],tbl_Plans[monthly_price]))*(1-Q32/100),H32="plan_downgrade",O32*(_xlfn.XLOOKUP(J32,tbl_Plans[plan_name],tbl_Plans[monthly_price])-_xlfn.XLOOKUP(I32,tbl_Plans[plan_name],tbl_Plans[monthly_price]))*(1-Q32/100))*IF(N32="Annual",1/12,1)} -> 4950
A33: EVT032 | B33: SUB059 | C33: CUST008 | D33: Quantum Education Platform | E33: Eastern Canada | F33: 45597 | G33: 45601 | H33: created | M33: Marketing Pro | N33: Monthly | O33: 22 | P33: 85 | Q33: 0 | R33: {=_xlfn.IFS(H33="created", "New", H33="cancelled", "Churned", AND(H33="seats_change", J33 > I33), "Expansion", AND(H33="seats_change", J33 < I33), "Contraction", AND(H33="price_change", J33 > I33), "Expansion", AND(H33="price_change", J33 < I33), "Contraction", H33="plan_upgrade", "Expansion", H33="plan_downgrade", "Contraction", H33="discount_added", "Contraction")} -> New | S33: {=_xlfn.IFS(H33="created",O33*P33*(1-Q33/100),H33="cancelled",-(O33*P33*(1-Q33/100)),H33="seats_change",(J33-I33)*P33*(1-Q33/100),H33="price_change",(J33-I33)*O33*(1-Q33/100),H33="discount_added",-(O33*P33*(J33-I33)/100),H33="plan_upgrade",O33*(_xlfn.XLOOKUP(J33,tbl_Plans[plan_name],tbl_Plans[monthly_price])-_xlfn.XLOOKUP(I33,tbl_Plans[plan_name],tbl_Plans[monthly_price]))*(1-Q33/100),H33="plan_downgrade",O33*(_xlfn.XLOOKUP(J33,tbl_Plans[plan_name],tbl_Plans[monthly_price])-_xlfn.XLOOKUP(I33,tbl_Plans[plan_name],tbl_Plans[monthly_price]))*(1-Q33/100))*IF(N33="Annual",1/12,1)} -> 1870
A34: EVT033 | B34: SUB023 | C34: CUST023 | D34: Island Media Productions | E34: Eastern Canada | F34: 45597 | G34: 45607 | H34: created | M34: Analytics Starter | N34: Monthly | O34: 10 | P34: 45 | Q34: 0 | R34: {=_xlfn.IFS(H34="created", "New", H34="cancelled", "Churned", AND(H34="seats_change", J34 > I34), "Expansion", AND(H34="seats_change", J34 < I34), "Contraction", AND(H34="price_change", J34 > I34), "Expansion", AND(H34="price_change", J34 < I34), "Contraction", H34="plan_upgrade", "Expansion", H34="plan_downgrade", "Contraction", H34="discount_added", "Contraction")} -> New | S34: {=_xlfn.IFS(H34="created",O34*P34*(1-Q34/100),H34="cancelled",-(O34*P34*(1-Q34/100)),H34="seats_change",(J34-I34)*P34*(1-Q34/100),H34="price_change",(J34-I34)*O34*(1-Q34/100),H34="discount_added",-(O34*P34*(J34-I34)/100),H34="plan_upgrade",O34*(_xlfn.XLOOKUP(J34,tbl_Plans[plan_name],tbl_Plans[monthly_price])-_xlfn.XLOOKUP(I34,tbl_Plans[plan_name],tbl_Plans[monthly_price]))*(1-Q34/100),H34="plan_downgrade",O34*(_xlfn.XLOOKUP(J34,tbl_Plans[plan_name],tbl_Plans[monthly_price])-_xlfn.XLOOKUP(I34,tbl_Plans[plan_name],tbl_Plans[monthly_price]))*(1-Q34/100))*IF(N34="Annual",1/12,1)} -> 450
A35: EVT034 | B35: SUB005 | C35: CUST005 | D35: Atlantic Media Corp | E35: Eastern Canada | F35: 45597 | G35: 45616 | H35: cancelled | I35: active | J35: churned | K35: status | L35: Price too high | M35: Analytics Starter | N35: Monthly | O35: 11 | P35: 45 | Q35: 0 | R35: {=_xlfn.IFS(H35="created", "New", H35="cancelled", "Churned", AND(H35="seats_change", J35 > I35), "Expansion", AND(H35="seats_change", J35 < I35), "Contraction", AND(H35="price_change", J35 > I35), "Expansion", AND(H35="price_change", J35 < I35), "Contraction", H35="plan_upgrade", "Expansion", H35="plan_downgrade", "Contraction", H35="discount_added", "Contraction")} -> Churned | S35: {=_xlfn.IFS(H35="created",O35*P35*(1-Q35/100),H35="cancelled",-(O35*P35*(1-Q35/100)),H35="seats_change",(J35-I35)*P35*(1-Q35/100),H35="price_change",(J35-I35)*O35*(1-Q35/100),H35="discount_added",-(O35*P35*(J35-I35)/100),H35="plan_upgrade",O35*(_xlfn.XLOOKUP(J35,tbl_Plans[plan_name],tbl_Plans[monthly_price])-_xlfn.XLOOKUP(I35,tbl_Plans[plan_name],tbl_Plans[monthly_price]))*(1-Q35/100),H35="plan_downgrade",O35*(_xlfn.XLOOKUP(J35,tbl_Plans[plan_name],tbl_Plans[monthly_price])-_xlfn.XLOOKUP(I35,tbl_Plans[plan_name],tbl_Plans[monthly_price]))*(1-Q35/100))*IF(N35="Annual",1/12,1)} -> -495
A36: EVT035 | B36: SUB024 | C36: CUST024 | D36: Western Retail Group | E36: Western Canada | F36: 45597 | G36: 45621 | H36: created | M36: Marketing Pro | N36: Monthly | O36: 31 | P36: 85 | Q36: 0 | R36: {=_xlfn.IFS(H36="created", "New", H36="cancelled", "Churned", AND(H36="seats_change", J36 > I36), "Expansion", AND(H36="seats_change", J36 < I36), "Contraction", AND(H36="price_change", J36 > I36), "Expansion", AND(H36="price_change", J36 < I36), "Contraction", H36="plan_upgrade", "Expansion", H36="plan_downgrade", "Contraction", H36="discount_added", "Contraction")} -> New | S36: {=_xlfn.IFS(H36="created",O36*P36*(1-Q36/100),H36="cancelled",-(O36*P36*(1-Q36/100)),H36="seats_change",(J36-I36)*P36*(1-Q36/100),H36="price_change",(J36-I36)*O36*(1-Q36/100),H36="discount_added",-(O36*P36*(J36-I36)/100),H36="plan_upgrade",O36*(_xlfn.XLOOKUP(J36,tbl_Plans[plan_name],tbl_Plans[monthly_price])-_xlfn.XLOOKUP(I36,tbl_Plans[plan_name],tbl_Plans[monthly_price]))*(1-Q36/100),H36="plan_downgrade",O36*(_xlfn.XLOOKUP(J36,tbl_Plans[plan_name],tbl_Plans[monthly_price])-_xlfn.XLOOKUP(I36,tbl_Plans[plan_name],tbl_Plans[monthly_price]))*(1-Q36/100))*IF(N36="Annual",1/12,1)} -> 2635
A37: EVT036 | B37: SUB025 | C37: CUST025 | D37: Montreal Manufacturing Pro | E37: Eastern Canada | F37: 45627 | G37: 45635 | H37: created | M37: Analytics Enterprise | N37: Annual | O37: 38 | P37: 2160 | Q37: 0 | R37: {=_xlfn.IFS(H37="created", "New", H37="cancelled", "Churned", AND(H37="seats_change", J37 > I37), "Expansion", AND(H37="seats_change", J37 < I37), "Contraction", AND(H37="price_change", J37 > I37), "Expansion", AND(H37="price_change", J37 < I37), "Contraction", H37="plan_upgrade", "Expansion", H37="plan_downgrade", "Contraction", H37="discount_added", "Contraction")} -> New | S37: {=_xlfn.IFS(H37="created",O37*P37*(1-Q37/100),H37="cancelled",-(O37*P37*(1-Q37/100)),H37="seats_change",(J37-I37)*P37*(1-Q37/100),H37="price_change",(J37-I37)*O37*(1-Q37/100),H37="discount_added",-(O37*P37*(J37-I37)/100),H37="plan_upgrade",O37*(_xlfn.XLOOKUP(J37,tbl_Plans[plan_name],tbl_Plans[monthly_price])-_xlfn.XLOOKUP(I37,tbl_Plans[plan_name],tbl_Plans[monthly_price]))*(1-Q37/100),H37="plan_downgrade",O37*(_xlfn.XLOOKUP(J37,tbl_Plans[plan_name],tbl_Plans[monthly_price])-_xlfn.XLOOKUP(I37,tbl_Plans[plan_name],tbl_Plans[monthly_price]))*(1-Q37/100))*IF(N37="Annual",1/12,1)} -> 6840
A38: EVT037 | B38: SUB056 | C38: CUST016 | D38: Quebec Manufacturing | E38: Eastern Canada | F38: 45627 | G38: 45638 | H38: created | M38: Marketing Pro | N38: Monthly | O38: 38 | P38: 85 | Q38: 0 | R38: {=_xlfn.IFS(H38="created", "New", H38="cancelled", "Churned", AND(H38="seats_change", J38 > I38), "Expansion", AND(H38="seats_change", J38 < I38), "Contraction", AND(H38="price_change", J38 > I38), "Expansion", AND(H38="price_change", J38 < I38), "Contraction", H38="plan_upgrade", "Expansion", H38="plan_downgrade", "Contraction", H38="discount_added", "Contraction")} -> New | S38: {=_xlfn.IFS(H38="created",O38*P38*(1-Q38/100),H38="cancelled",-(O38*P38*(1-Q38/100)),H38="seats_change",(J38-I38)*P38*(1-Q38/100),H38="price_change",(J38-I38)*O38*(1-Q38/100),H38="discount_added",-(O38*P38*(J38-I38)/100),H38="plan_upgrade",O38*(_xlfn.XLOOKUP(J38,tbl_Plans[plan_name],tbl_Plans[monthly_price])-_xlfn.XLOOKUP(I38,tbl_Plans[plan_name],tbl_Plans[monthly_price]))*(1-Q38/100),H38="plan_downgrade",O38*(_xlfn.XLOOKUP(J38,tbl_Plans[plan_name],tbl_Plans[monthly_price])-_xlfn.XLOOKUP(I38,tbl_Plans[plan_name],tbl_Plans[monthly_price]))*(1-Q38/100))*IF(N38="Annual",1/12,1)} -> 3230
A39: EVT038 | B39: SUB044 | C39: CUST009 | D39: West Coast Logistics | E39: Western Canada | F39: 45627 | G39: 45646 | H39: created | M39: Analytics Growth | N39: Monthly | O39: 35 | P39: 95 | Q39: 0 | R39: {=_xlfn.IFS(H39="created", "New", H39="cancelled", "Churned", AND(H39="seats_change", J39 > I39), "Expansion", AND(H39="seats_change", J39 < I39), "Contraction", AND(H39="price_change", J39 > I39), "Expansion", AND(H39="price_change", J39 < I39), "Contraction", H39="plan_upgrade", "Expansion", H39="plan_downgrade", "Contraction", H39="discount_added", "Contraction")} -> New | S39: {=_xlfn.IFS(H39="created",O39*P39*(1-Q39/100),H39="cancelled",-(O39*P39*(1-Q39/100)),H39="seats_change",(J39-I39)*P39*(1-Q39/100),H39="price_change",(J39-I39)*O39*(1-Q39/100),H39="discount_added",-(O39*P39*(J39-I39)/100),H39="plan_upgrade",O39*(_xlfn.XLOOKUP(J39,tbl_Plans[plan_name],tbl_Plans[monthly_price])-_xlfn.XLOOKUP(I39,tbl_Plans[plan_name],tbl_Plans[monthly_price]))*(1-Q39/100),H39="plan_downgrade",O39*(_xlfn.XLOOKUP(J39,tbl_Plans[plan_name],tbl_Plans[monthly_price])-_xlfn.XLOOKUP(I39,tbl_Plans[plan_name],tbl_Plans[monthly_price]))*(1-Q39/100))*IF(N39="Annual",1/12,1)} -> 3325
A40: EVT039 | B40: SUB008 | C40: CUST008 | D40: Quantum Education Platform | E40: Eastern Canada | F40: 45627 | G40: 45648 | H40: cancelled | I40: active | J40: churned | K40: status | L40: Price too high | M40: Analytics Growth | N40: Monthly | O40: 22 | P40: 95 | Q40: 0 | R40: {=_xlfn.IFS(H40="created", "New", H40="cancelled", "Churned", AND(H40="seats_change", J40 > I40), "Expansion", AND(H40="seats_change", J40 < I40), "Contraction", AND(H40="price_change", J40 > I40), "Expansion", AND(H40="price_change", J40 < I40), "Contraction", H40="plan_upgrade", "Expansion", H40="plan_downgrade", "Contraction", H40="discount_added", "Contraction")} -> Churned | S40: {=_xlfn.IFS(H40="created",O40*P40*(1-Q40/100),H40="cancelled",-(O40*P40*(1-Q40/100)),H40="seats_change",(J40-I40)*P40*(1-Q40/100),H40="price_change",(J40-I40)*O40*(1-Q40/100),H40="discount_added",-(O40*P40*(J40-I40)/100),H40="plan_upgrade",O40*(_xlfn.XLOOKUP(J40,tbl_Plans[plan_name],tbl_Plans[monthly_price])-_xlfn.XLOOKUP(I40,tbl_Plans[plan_name],tbl_Plans[monthly_price]))*(1-Q40/100),H40="plan_downgrade",O40*(_xlfn.XLOOKUP(J40,tbl_Plans[plan_name],tbl_Plans[monthly_price])-_xlfn.XLOOKUP(I40,tbl_Plans[plan_name],tbl_Plans[monthly_price]))*(1-Q40/100))*IF(N40="Annual",1/12,1)} -> -2090
A41: EVT040 | B41: SUB026 | C41: CUST026 | D41: Ontario Education Connect | E41: Eastern Canada | F41: 45627 | G41: 45649 | H41: created | M41: Analytics Growth | N41: Monthly | O41: 16 | P41: 95 | Q41: 0 | R41: {=_xlfn.IFS(H41="created", "New", H41="cancelled", "Churned", AND(H41="seats_change", J41 > I41), "Expansion", AND(H41="seats_change", J41 < I41), "Contraction", AND(H41="price_change", J41 > I41), "Expansion", AND(H41="price_change", J41 < I41), "Contraction", H41="plan_upgrade", "Expansion", H41="plan_downgrade", "Contraction", H41="discount_added", "Contraction")} -> New | S41: {=_xlfn.IFS(H41="created",O41*P41*(1-Q41/100),H41="cancelled",-(O41*P41*(1-Q41/100)),H41="seats_change",(J41-I41)*P41*(1-Q41/100),H41="price_change",(J41-I41)*O41*(1-Q41/100),H41="discount_added",-(O41*P41*(J41-I41)/100),H41="plan_upgrade",O41*(_xlfn.XLOOKUP(J41,tbl_Plans[plan_name],tbl_Plans[monthly_price])-_xlfn.XLOOKUP(I41,tbl_Plans[plan_name],tbl_Plans[monthly_price]))*(1-Q41/100),H41="plan_downgrade",O41*(_xlfn.XLOOKUP(J41,tbl_Plans[plan_name],tbl_Plans[monthly_price])-_xlfn.XLOOKUP(I41,tbl_Plans[plan_name],tbl_Plans[monthly_price]))*(1-Q41/100))*IF(N41="Annual",1/12,1)} -> 1520
A42: EVT041 | B42: SUB027 | C42: CUST027 | D42: Pacific Finance Corp | E42: Western Canada | F42: 45658 | G42: 45663 | H42: created | M42: Sales Hub | N42: Monthly | O42: 28 | P42: 110 | Q42: 0 | R42: {=_xlfn.IFS(H42="created", "New", H42="cancelled", "Churned", AND(H42="seats_change", J42 > I42), "Expansion", AND(H42="seats_change", J42 < I42), "Contraction", AND(H42="price_change", J42 > I42), "Expansion", AND(H42="price_change", J42 < I42), "Contraction", H42="plan_upgrade", "Expansion", H42="plan_downgrade", "Contraction", H42="discount_added", "Contraction")} -> New | S42: {=_xlfn.IFS(H42="created",O42*P42*(1-Q42/100),H42="cancelled",-(O42*P42*(1-Q42/100)),H42="seats_change",(J42-I42)*P42*(1-Q42/100),H42="price_change",(J42-I42)*O42*(1-Q42/100),H42="discount_added",-(O42*P42*(J42-I42)/100),H42="plan_upgrade",O42*(_xlfn.XLOOKUP(J42,tbl_Plans[plan_name],tbl_Plans[monthly_price])-_xlfn.XLOOKUP(I42,tbl_Plans[plan_name],tbl_Plans[monthly_price]))*(1-Q42/100),H42="plan_downgrade",O42*(_xlfn.XLOOKUP(J42,tbl_Plans[plan_name],tbl_Plans[monthly_price])-_xlfn.XLOOKUP(I42,tbl_Plans[plan_name],tbl_Plans[monthly_price]))*(1-Q42/100))*IF(N42="Annual",1/12,1)} -> 3080
A43: EVT042 | B43: SUB014 | C43: CUST014 | D43: Toronto Media Group | E43: Eastern Canada | F43: 45658 | G43: 45665 | H43: price_change | I43: 80 | J43: 85 | K43: price_per_seat | L43: Annual price increase applied at renewal | M43: Marketing Pro | N43: Monthly | O43: 28 | P43: 85 | Q43: 0 | R43: {=_xlfn.IFS(H43="created", "New", H43="cancelled", "Churned", AND(H43="seats_change", J43 > I43), "Expansion", AND(H43="seats_change", J43 < I43), "Contraction", AND(H43="price_change", J43 > I43), "Expansion", AND(H43="price_change", J43 < I43), "Contraction", H43="plan_upgrade", "Expansion", H43="plan_downgrade", "Contraction", H43="discount_added", "Contraction")} -> Expansion | S43: {=_xlfn.IFS(H43="created",O43*P43*(1-Q43/100),H43="cancelled",-(O43*P43*(1-Q43/100)),H43="seats_change",(J43-I43)*P43*(1-Q43/100),H43="price_change",(J43-I43)*O43*(1-Q43/100),H43="discount_added",-(O43*P43*(J43-I43)/100),H43="plan_upgrade",O43*(_xlfn.XLOOKUP(J43,tbl_Plans[plan_name],tbl_Plans[monthly_price])-_xlfn.XLOOKUP(I43,tbl_Plans[plan_name],tbl_Plans[monthly_price]))*(1-Q43/100),H43="plan_downgrade",O43*(_xlfn.XLOOKUP(J43,tbl_Plans[plan_name],tbl_Plans[monthly_price])-_xlfn.XLOOKUP(I43,tbl_Plans[plan_name],tbl_Plans[monthly_price]))*(1-Q43/100))*IF(N43="Annual",1/12,1)} -> 140
A44: EVT043 | B44: SUB013 | C44: CUST013 | D44: Alberta Tech Innovators | E44: Western Canada | F44: 45658 | G44: 45672 | H44: cancelled | I44: active | J44: churned | K44: status | L44: Switched to competitor | M44: Analytics Starter | N44: Monthly | O44: 10 | P44: 45 | Q44: 0 | R44: {=_xlfn.IFS(H44="created", "New", H44="cancelled", "Churned", AND(H44="seats_change", J44 > I44), "Expansion", AND(H44="seats_change", J44 < I44), "Contraction", AND(H44="price_change", J44 > I44), "Expansion", AND(H44="price_change", J44 < I44), "Contraction", H44="plan_upgrade", "Expansion", H44="plan_downgrade", "Contraction", H44="discount_added", "Contraction")} -> Churned | S44: {=_xlfn.IFS(H44="created",O44*P44*(1-Q44/100),H44="cancelled",-(O44*P44*(1-Q44/100)),H44="seats_change",(J44-I44)*P44*(1-Q44/100),H44="price_change",(J44-I44)*O44*(1-Q44/100),H44="discount_added",-(O44*P44*(J44-I44)/100),H44="plan_upgrade",O44*(_xlfn.XLOOKUP(J44,tbl_Plans[plan_name],tbl_Plans[monthly_price])-_xlfn.XLOOKUP(I44,tbl_Plans[plan_name],tbl_Plans[monthly_price]))*(1-Q44/100),H44="plan_downgrade",O44*(_xlfn.XLOOKUP(J44,tbl_Plans[plan_name],tbl_Plans[monthly_price])-_xlfn.XLOOKUP(I44,tbl_Plans[plan_name],tbl_Plans[monthly_price]))*(1-Q44/100))*IF(N44="Annual",1/12,1)} -> -450
A45: EVT044 | B45: SUB028 | C45: CUST028 | D45: Prairie SaaS Innovations | E45: Central Canada | F45: 45658 | G45: 45677 | H45: created | M45: Analytics Starter | N45: Monthly | O45: 15 | P45: 45 | Q45: 0 | R45: {=_xlfn.IFS(H45="created", "New", H45="cancelled", "Churned", AND(H45="seats_change", J45 > I45), "Expansion", AND(H45="seats_change", J45 < I45), "Contraction", AND(H45="price_change", J45 > I45), "Expansion", AND(H45="price_change", J45 < I45), "Contraction", H45="plan_upgrade", "Expansion", H45="plan_downgrade", "Contraction", H45="discount_added", "Contraction")} -> New | S45: {=_xlfn.IFS(H45="created",O45*P45*(1-Q45/100),H45="cancelled",-(O45*P45*(1-Q45/100)),H45="seats_change",(J45-I45)*P45*(1-Q45/100),H45="price_change",(J45-I45)*O45*(1-Q45/100),H45="discount_added",-(O45*P45*(J45-I45)/100),H45="plan_upgrade",O45*(_xlfn.XLOOKUP(J45,tbl_Plans[plan_name],tbl_Plans[monthly_price])-_xlfn.XLOOKUP(I45,tbl_Plans[plan_name],tbl_Plans[monthly_price]))*(1-Q45/100),H45="plan_downgrade",O45*(_xlfn.XLOOKUP(J45,tbl_Plans[plan_name],tbl_Plans[monthly_price])-_xlfn.XLOOKUP(I45,tbl_Plans[plan_name],tbl_Plans[monthly_price]))*(1-Q45/100))*IF(N45="Annual",1/12,1)} -> 675
A46: EVT045 | B46: SUB054 | C46: CUST002 | D46: Pacific Analytics Inc | E46: Western Canada | F46: 45658 | G46: 45679 | H46: created | M46: Analytics Growth | N46: Annual | O46: 22 | P46: 1140 | Q46: 5 | R46: {=_xlfn.IFS(H46="created", "New", H46="cancelled", "Churned", AND(H46="seats_change", J46 > I46), "Expansion", AND(H46="seats_change", J46 < I46), "Contraction", AND(H46="price_change", J46 > I46), "Expansion", AND(H46="price_change", J46 < I46), "Contraction", H46="plan_upgrade", "Expansion", H46="plan_downgrade", "Contraction", H46="discount_added", "Contraction")} -> New | S46: {=_xlfn.IFS(H46="created",O46*P46*(1-Q46/100),H46="cancelled",-(O46*P46*(1-Q46/100)),H46="seats_change",(J46-I46)*P46*(1-Q46/100),H46="price_change",(J46-I46)*O46*(1-Q46/100),H46="discount_added",-(O46*P46*(J46-I46)/100),H46="plan_upgrade",O46*(_xlfn.XLOOKUP(J46,tbl_Plans[plan_name],tbl_Plans[monthly_price])-_xlfn.XLOOKUP(I46,tbl_Plans[plan_name],tbl_Plans[monthly_price]))*(1-Q46/100),H46="plan_downgrade",O46*(_xlfn.XLOOKUP(J46,tbl_Plans[plan_name],tbl_Plans[monthly_price])-_xlfn.XLOOKUP(I46,tbl_Plans[plan_name],tbl_Plans[monthly_price]))*(1-Q46/100))*IF(N46="Annual",1/12,1)} -> 1985.5
A47: EVT046 | B47: SUB057 | C47: CUST021 | D47: Calgary Commerce Solutions | E47: Western Canada | F47: 45658 | G47: 45685 | H47: created | M47: Platform Suite | N47: Monthly | O47: 28 | P47: 150 | Q47: 0 | R47: {=_xlfn.IFS(H47="created", "New", H47="cancelled", "Churned", AND(H47="seats_change", J47 > I47), "Expansion", AND(H47="seats_change", J47 < I47), "Contraction", AND(H47="price_change", J47 > I47), "Expansion", AND(H47="price_change", J47 < I47), "Contraction", H47="plan_upgrade", "Expansion", H47="plan_downgrade", "Contraction", H47="discount_added", "Contraction")} -> New | S47: {=_xlfn.IFS(H47="created",O47*P47*(1-Q47/100),H47="cancelled",-(O47*P47*(1-Q47/100)),H47="seats_change",(J47-I47)*P47*(1-Q47/100),H47="price_change",(J47-I47)*O47*(1-Q47/100),H47="discount_added",-(O47*P47*(J47-I47)/100),H47="plan_upgrade",O47*(_xlfn.XLOOKUP(J47,tbl_Plans[plan_name],tbl_Plans[monthly_price])-_xlfn.XLOOKUP(I47,tbl_Plans[plan_name],tbl_Plans[monthly_price]))*(1-Q47/100),H47="plan_downgrade",O47*(_xlfn.XLOOKUP(J47,tbl_Plans[plan_name],tbl_Plans[monthly_price])-_xlfn.XLOOKUP(I47,tbl_Plans[plan_name],tbl_Plans[monthly_price]))*(1-Q47/100))*IF(N47="Annual",1/12,1)} -> 4200
A48: EVT047 | B48: SUB029 | C48: CUST029 | D48: Halifax Healthcare Tech | E48: Eastern Canada | F48: 45689 | G48: 45691 | H48: created | M48: Marketing Pro | N48: Monthly | O48: 22 | P48: 85 | Q48: 0 | R48: {=_xlfn.IFS(H48="created", "New", H48="cancelled", "Churned", AND(H48="seats_change", J48 > I48), "Expansion", AND(H48="seats_change", J48 < I48), "Contraction", AND(H48="price_change", J48 > I48), "Expansion", AND(H48="price_change", J48 < I48), "Contraction", H48="plan_upgrade", "Expansion", H48="plan_downgrade", "Contraction", H48="discount_added", "Contraction")} -> New | S48: {=_xlfn.IFS(H48="created",O48*P48*(1-Q48/100),H48="cancelled",-(O48*P48*(1-Q48/100)),H48="seats_change",(J48-I48)*P48*(1-Q48/100),H48="price_change",(J48-I48)*O48*(1-Q48/100),H48="discount_added",-(O48*P48*(J48-I48)/100),H48="plan_upgrade",O48*(_xlfn.XLOOKUP(J48,tbl_Plans[plan_name],tbl_Plans[monthly_price])-_xlfn.XLOOKUP(I48,tbl_Plans[plan_name],tbl_Plans[monthly_price]))*(1-Q48/100),H48="plan_downgrade",O48*(_xlfn.XLOOKUP(J48,tbl_Plans[plan_name],tbl_Plans[monthly_price])-_xlfn.XLOOKUP(I48,tbl_Plans[plan_name],tbl_Plans[monthly_price]))*(1-Q48/100))*IF(N48="Annual",1/12,1)} -> 1870
A49: EVT048 | B49: SUB045 | C49: CUST010 | D49: Montreal Finance Hub | E49: Eastern Canada | F49: 45689 | G49: 45696 | H49: created | M49: Marketing Pro | N49: Monthly | O49: 13 | P49: 85 | Q49: 0 | R49: {=_xlfn.IFS(H49="created", "New", H49="cancelled", "Churned", AND(H49="seats_change", J49 > I49), "Expansion", AND(H49="seats_change", J49 < I49), "Contraction", AND(H49="price_change", J49 > I49), "Expansion", AND(H49="price_change", J49 < I49), "Contraction", H49="plan_upgrade", "Expansion", H49="plan_downgrade", "Contraction", H49="discount_added", "Contraction")} -> New | S49: {=_xlfn.IFS(H49="created",O49*P49*(1-Q49/100),H49="cancelled",-(O49*P49*(1-Q49/100)),H49="seats_change",(J49-I49)*P49*(1-Q49/100),H49="price_change",(J49-I49)*O49*(1-Q49/100),H49="discount_added",-(O49*P49*(J49-I49)/100),H49="plan_upgrade",O49*(_xlfn.XLOOKUP(J49,tbl_Plans[plan_name],tbl_Plans[monthly_price])-_xlfn.XLOOKUP(I49,tbl_Plans[plan_name],tbl_Plans[monthly_price]))*(1-Q49/100),H49="plan_downgrade",O49*(_xlfn.XLOOKUP(J49,tbl_Plans[plan_name],tbl_Plans[monthly_price])-_xlfn.XLOOKUP(I49,tbl_Plans[plan_name],tbl_Plans[monthly_price]))*(1-Q49/100))*IF(N49="Annual",1/12,1)} -> 1105
A50: EVT049 | B50: SUB051 | C50: CUST014 | D50: Toronto Media Group | E50: Eastern Canada | F50: 45689 | G50: 45698 | H50: created | M50: Sales Hub | N50: Monthly | O50: 23 | P50: 110 | Q50: 0 | R50: {=_xlfn.IFS(H50="created", "New", H50="cancelled", "Churned", AND(H50="seats_change", J50 > I50), "Expansion", AND(H50="seats_change", J50 < I50), "Contraction", AND(H50="price_change", J50 > I50), "Expansion", AND(H50="price_change", J50 < I50), "Contraction", H50="plan_upgrade", "Expansion", H50="plan_downgrade", "Contraction", H50="discount_added", "Contraction")} -> New | S50: {=_xlfn.IFS(H50="created",O50*P50*(1-Q50/100),H50="cancelled",-(O50*P50*(1-Q50/100)),H50="seats_change",(J50-I50)*P50*(1-Q50/100),H50="price_change",(J50-I50)*O50*(1-Q50/100),H50="discount_added",-(O50*P50*(J50-I50)/100),H50="plan_upgrade",O50*(_xlfn.XLOOKUP(J50,tbl_Plans[plan_name],tbl_Plans[monthly_price])-_xlfn.XLOOKUP(I50,tbl_Plans[plan_name],tbl_Plans[monthly_price]))*(1-Q50/100),H50="plan_downgrade",O50*(_xlfn.XLOOKUP(J50,tbl_Plans[plan_name],tbl_Plans[monthly_price])-_xlfn.XLOOKUP(I50,tbl_Plans[plan_name],tbl_Plans[monthly_price]))*(1-Q50/100))*IF(N50="Annual",1/12,1)} -> 2530
A51: EVT050 | B51: SUB030 | C51: CUST030 | D51: Alberta E-commerce Hub | E51: Western Canada | F51: 45689 | G51: 45705 | H51: created | M51: Analytics Growth | N51: Monthly | O51: 20 | P51: 95 | Q51: 0 | R51: {=_xlfn.IFS(H51="created", "New", H51="cancelled", "Churned", AND(H51="seats_change", J51 > I51), "Expansion", AND(H51="seats_change", J51 < I51), "Contraction", AND(H51="price_change", J51 > I51), "Expansion", AND(H51="price_change", J51 < I51), "Contraction", H51="plan_upgrade", "Expansion", H51="plan_downgrade", "Contraction", H51="discount_added", "Contraction")} -> New | S51: {=_xlfn.IFS(H51="created",O51*P51*(1-Q51/100),H51="cancelled",-(O51*P51*(1-Q51/100)),H51="seats_change",(J51-I51)*P51*(1-Q51/100),H51="price_change",(J51-I51)*O51*(1-Q51/100),H51="discount_added",-(O51*P51*(J51-I51)/100),H51="plan_upgrade",O51*(_xlfn.XLOOKUP(J51,tbl_Plans[plan_name],tbl_Plans[monthly_price])-_xlfn.XLOOKUP(I51,tbl_Plans[plan_name],tbl_Plans[monthly_price]))*(1-Q51/100),H51="plan_downgrade",O51*(_xlfn.XLOOKUP(J51,tbl_Plans[plan_name],tbl_Plans[monthly_price])-_xlfn.XLOOKUP(I51,tbl_Plans[plan_name],tbl_Plans[monthly_price]))*(1-Q51/100))*IF(N51="Annual",1/12,1)} -> 1900
A52: EVT051 | B52: SUB031 | C52: CUST031 | D52: Toronto Digital Media | E52: Eastern Canada | F52: 45717 | G52: 45719 | H52: created | M52: Platform Suite | N52: Annual | O52: 45 | P52: 1800 | Q52: 0 | R52: {=_xlfn.IFS(H52="created", "New", H52="cancelled", "Churned", AND(H52="seats_change", J52 > I52), "Expansion", AND(H52="seats_change", J52 < I52), "Contraction", AND(H52="price_change", J52 > I52), "Expansion", AND(H52="price_change", J52 < I52), "Contraction", H52="plan_upgrade", "Expansion", H52="plan_downgrade", "Contraction", H52="discount_added", "Contraction")} -> New | S52: {=_xlfn.IFS(H52="created",O52*P52*(1-Q52/100),H52="cancelled",-(O52*P52*(1-Q52/100)),H52="seats_change",(J52-I52)*P52*(1-Q52/100),H52="price_change",(J52-I52)*O52*(1-Q52/100),H52="discount_added",-(O52*P52*(J52-I52)/100),H52="plan_upgrade",O52*(_xlfn.XLOOKUP(J52,tbl_Plans[plan_name],tbl_Plans[monthly_price])-_xlfn.XLOOKUP(I52,tbl_Plans[plan_name],tbl_Plans[monthly_price]))*(1-Q52/100),H52="plan_downgrade",O52*(_xlfn.XLOOKUP(J52,tbl_Plans[plan_name],tbl_Plans[monthly_price])-_xlfn.XLOOKUP(I52,tbl_Plans[plan_name],tbl_Plans[monthly_price]))*(1-Q52/100))*IF(N52="Annual",1/12,1)} -> 6750
A53: EVT052 | B53: SUB058 | C53: CUST024 | D53: Western Retail Group | E53: Western Canada | F53: 45717 | G53: 45724 | H53: created | M53: Sales Hub | N53: Monthly | O53: 26 | P53: 110 | Q53: 0 | R53: {=_xlfn.IFS(H53="created", "New", H53="cancelled", "Churned", AND(H53="seats_change", J53 > I53), "Expansion", AND(H53="seats_change", J53 < I53), "Contraction", AND(H53="price_change", J53 > I53), "Expansion", AND(H53="price_change", J53 < I53), "Contraction", H53="plan_upgrade", "Expansion", H53="plan_downgrade", "Contraction", H53="discount_added", "Contraction")} -> New | S53: {=_xlfn.IFS(H53="created",O53*P53*(1-Q53/100),H53="cancelled",-(O53*P53*(1-Q53/100)),H53="seats_change",(J53-I53)*P53*(1-Q53/100),H53="price_change",(J53-I53)*O53*(1-Q53/100),H53="discount_added",-(O53*P53*(J53-I53)/100),H53="plan_upgrade",O53*(_xlfn.XLOOKUP(J53,tbl_Plans[plan_name],tbl_Plans[monthly_price])-_xlfn.XLOOKUP(I53,tbl_Plans[plan_name],tbl_Plans[monthly_price]))*(1-Q53/100),H53="plan_downgrade",O53*(_xlfn.XLOOKUP(J53,tbl_Plans[plan_name],tbl_Plans[monthly_price])-_xlfn.XLOOKUP(I53,tbl_Plans[plan_name],tbl_Plans[monthly_price]))*(1-Q53/100))*IF(N53="Annual",1/12,1)} -> 2860
A54: EVT053 | B54: SUB010 | C54: CUST010 | D54: Montreal Finance Hub | E54: Eastern Canada | F54: 45717 | G54: 45729 | H54: plan_downgrade | I54: Analytics Growth | J54: Analytics Starter | K54: plan_name | L54: Cost reduction initiative - downgraded to starter tier | M54: Analytics Starter | N54: Monthly | O54: 13 | P54: 45 | Q54: 0 | R54: {=_xlfn.IFS(H54="created", "New", H54="cancelled", "Churned", AND(H54="seats_change", J54 > I54), "Expansion", AND(H54="seats_change", J54 < I54), "Contraction", AND(H54="price_change", J54 > I54), "Expansion", AND(H54="price_change", J54 < I54), "Contraction", H54="plan_upgrade", "Expansion", H54="plan_downgrade", "Contraction", H54="discount_added", "Contraction")} -> Contraction | S54: {=_xlfn.IFS(H54="created",O54*P54*(1-Q54/100),H54="cancelled",-(O54*P54*(1-Q54/100)),H54="seats_change",(J54-I54)*P54*(1-Q54/100),H54="price_change",(J54-I54)*O54*(1-Q54/100),H54="discount_added",-(O54*P54*(J54-I54)/100),H54="plan_upgrade",O54*(_xlfn.XLOOKUP(J54,tbl_Plans[plan_name],tbl_Plans[monthly_price])-_xlfn.XLOOKUP(I54,tbl_Plans[plan_name],tbl_Plans[monthly_price]))*(1-Q54/100),H54="plan_downgrade",O54*(_xlfn.XLOOKUP(J54,tbl_Plans[plan_name],tbl_Plans[monthly_price])-_xlfn.XLOOKUP(I54,tbl_Plans[plan_name],tbl_Plans[monthly_price]))*(1-Q54/100))*IF(N54="Annual",1/12,1)} -> -650
A55: EVT054 | B55: SUB052 | C55: CUST018 | D55: Vancouver FinTech Labs | E55: Western Canada | F55: 45717 | G55: 45731 | H55: created | M55: Marketing Pro | N55: Monthly | O55: 35 | P55: 85 | Q55: 0 | R55: {=_xlfn.IFS(H55="created", "New", H55="cancelled", "Churned", AND(H55="seats_change", J55 > I55), "Expansion", AND(H55="seats_change", J55 < I55), "Contraction", AND(H55="price_change", J55 > I55), "Expansion", AND(H55="price_change", J55 < I55), "Contraction", H55="plan_upgrade", "Expansion", H55="plan_downgrade", "Contraction", H55="discount_added", "Contraction")} -> New | S55: {=_xlfn.IFS(H55="created",O55*P55*(1-Q55/100),H55="cancelled",-(O55*P55*(1-Q55/100)),H55="seats_change",(J55-I55)*P55*(1-Q55/100),H55="price_change",(J55-I55)*O55*(1-Q55/100),H55="discount_added",-(O55*P55*(J55-I55)/100),H55="plan_upgrade",O55*(_xlfn.XLOOKUP(J55,tbl_Plans[plan_name],tbl_Plans[monthly_price])-_xlfn.XLOOKUP(I55,tbl_Plans[plan_name],tbl_Plans[monthly_price]))*(1-Q55/100),H55="plan_downgrade",O55*(_xlfn.XLOOKUP(J55,tbl_Plans[plan_name],tbl_Plans[monthly_price])-_xlfn.XLOOKUP(I55,tbl_Plans[plan_name],tbl_Plans[monthly_price]))*(1-Q55/100))*IF(N55="Annual",1/12,1)} -> 2975
A56: EVT055 | B56: SUB054 | C56: CUST002 | D56: Pacific Analytics Inc | E56: Western Canada | F56: 45717 | G56: 45731 | H56: discount_added | I56: 0 | J56: 5 | K56: discount_percent | L56: Annual contract loyalty discount applied | M56: Analytics Growth | N56: Annual | O56: 22 | P56: 1140 | Q56: 5 | R56: {=_xlfn.IFS(H56="created", "New", H56="cancelled", "Churned", AND(H56="seats_change", J56 > I56), "Expansion", AND(H56="seats_change", J56 < I56), "Contraction", AND(H56="price_change", J56 > I56), "Expansion", AND(H56="price_change", J56 < I56), "Contraction", H56="plan_upgrade", "Expansion", H56="plan_downgrade", "Contraction", H56="discount_added", "Contraction")} -> Contraction | S56: {=_xlfn.IFS(H56="created",O56*P56*(1-Q56/100),H56="cancelled",-(O56*P56*(1-Q56/100)),H56="seats_change",(J56-I56)*P56*(1-Q56/100),H56="price_change",(J56-I56)*O56*(1-Q56/100),H56="discount_added",-(O56*P56*(J56-I56)/100),H56="plan_upgrade",O56*(_xlfn.XLOOKUP(J56,tbl_Plans[plan_name],tbl_Plans[monthly_price])-_xlfn.XLOOKUP(I56,tbl_Plans[plan_name],tbl_Plans[monthly_price]))*(1-Q56/100),H56="plan_downgrade",O56*(_xlfn.XLOOKUP(J56,tbl_Plans[plan_name],tbl_Plans[monthly_price])-_xlfn.XLOOKUP(I56,tbl_Plans[plan_name],tbl_Plans[monthly_price]))*(1-Q56/100))*IF(N56="Annual",1/12,1)} -> -104.5
A57: EVT056 | B57: SUB032 | C57: CUST032 | D57: BC Manufacturing Systems | E57: Western Canada | F57: 45717 | G57: 45733 | H57: created | M57: Analytics Enterprise | N57: Monthly | O57: 26 | P57: 180 | Q57: 0 | R57: {=_xlfn.IFS(H57="created", "New", H57="cancelled", "Churned", AND(H57="seats_change", J57 > I57), "Expansion", AND(H57="seats_change", J57 < I57), "Contraction", AND(H57="price_change", J57 > I57), "Expansion", AND(H57="price_change", J57 < I57), "Contraction", H57="plan_upgrade", "Expansion", H57="plan_downgrade", "Contraction", H57="discount_added", "Contraction")} -> New | S57: {=_xlfn.IFS(H57="created",O57*P57*(1-Q57/100),H57="cancelled",-(O57*P57*(1-Q57/100)),H57="seats_change",(J57-I57)*P57*(1-Q57/100),H57="price_change",(J57-I57)*O57*(1-Q57/100),H57="discount_added",-(O57*P57*(J57-I57)/100),H57="plan_upgrade",O57*(_xlfn.XLOOKUP(J57,tbl_Plans[plan_name],tbl_Plans[monthly_price])-_xlfn.XLOOKUP(I57,tbl_Plans[plan_name],tbl_Plans[monthly_price]))*(1-Q57/100),H57="plan_downgrade",O57*(_xlfn.XLOOKUP(J57,tbl_Plans[plan_name],tbl_Plans[monthly_price])-_xlfn.XLOOKUP(I57,tbl_Plans[plan_name],tbl_Plans[monthly_price]))*(1-Q57/100))*IF(N57="Annual",1/12,1)} -> 4680
A58: EVT057 | B58: SUB019 | C58: CUST019 | D58: Central Healthcare Partners | E58: Central Canada | F58: 45717 | G58: 45736 | H58: seats_change | I58: 22 | J58: 19 | K58: seats | L58: Headcount reduction - Q1 restructuring | M58: Marketing Pro | N58: Monthly | O58: 19 | P58: 85 | Q58: 0 | R58: {=_xlfn.IFS(H58="created", "New", H58="cancelled", "Churned", AND(H58="seats_change", J58 > I58), "Expansion", AND(H58="seats_change", J58 < I58), "Contraction", AND(H58="price_change", J58 > I58), "Expansion", AND(H58="price_change", J58 < I58), "Contraction", H58="plan_upgrade", "Expansion", H58="plan_downgrade", "Contraction", H58="discount_added", "Contraction")} -> Contraction | S58: {=_xlfn.IFS(H58="created",O58*P58*(1-Q58/100),H58="cancelled",-(O58*P58*(1-Q58/100)),H58="seats_change",(J58-I58)*P58*(1-Q58/100),H58="price_change",(J58-I58)*O58*(1-Q58/100),H58="discount_added",-(O58*P58*(J58-I58)/100),H58="plan_upgrade",O58*(_xlfn.XLOOKUP(J58,tbl_Plans[plan_name],tbl_Plans[monthly_price])-_xlfn.XLOOKUP(I58,tbl_Plans[plan_name],tbl_Plans[monthly_price]))*(1-Q58/100),H58="plan_downgrade",O58*(_xlfn.XLOOKUP(J58,tbl_Plans[plan_name],tbl_Plans[monthly_price])-_xlfn.XLOOKUP(I58,tbl_Plans[plan_name],tbl_Plans[monthly_price]))*(1-Q58/100))*IF(N58="Annual",1/12,1)} -> -255
A59: EVT058 | B59: SUB033 | C59: CUST033 | D59: Ottawa Retail Solutions | E59: Eastern Canada | F59: 45717 | G59: 45747 | H59: created | M59: Marketing Pro | N59: Monthly | O59: 25 | P59: 85 | Q59: 0 | R59: {=_xlfn.IFS(H59="created", "New", H59="cancelled", "Churned", AND(H59="seats_change", J59 > I59), "Expansion", AND(H59="seats_change", J59 < I59), "Contraction", AND(H59="price_change", J59 > I59), "Expansion", AND(H59="price_change", J59 < I59), "Contraction", H59="plan_upgrade", "Expansion", H59="plan_downgrade", "Contraction", H59="discount_added", "Contraction")} -> New | S59: {=_xlfn.IFS(H59="created",O59*P59*(1-Q59/100),H59="cancelled",-(O59*P59*(1-Q59/100)),H59="seats_change",(J59-I59)*P59*(1-Q59/100),H59="price_change",(J59-I59)*O59*(1-Q59/100),H59="discount_added",-(O59*P59*(J59-I59)/100),H59="plan_upgrade",O59*(_xlfn.XLOOKUP(J59,tbl_Plans[plan_name],tbl_Plans[monthly_price])-_xlfn.XLOOKUP(I59,tbl_Plans[plan_name],tbl_Plans[monthly_price]))*(1-Q59/100),H59="plan_downgrade",O59*(_xlfn.XLOOKUP(J59,tbl_Plans[plan_name],tbl_Plans[monthly_price])-_xlfn.XLOOKUP(I59,tbl_Plans[plan_name],tbl_Plans[monthly_price]))*(1-Q59/100))*IF(N59="Annual",1/12,1)} -> 2125
A60: EVT059 | B60: SUB027 | C60: CUST027 | D60: Pacific Finance Corp | E60: Western Canada | F60: 45748 | G60: 45753 | H60: price_change | I60: 100 | J60: 110 | K60: price_per_seat | L60: Annual price increase applied at renewal | M60: Sales Hub | N60: Monthly | O60: 28 | P60: 110 | Q60: 0 | R60: {=_xlfn.IFS(H60="created", "New", H60="cancelled", "Churned", AND(H60="seats_change", J60 > I60), "Expansion", AND(H60="seats_change", J60 < I60), "Contraction", AND(H60="price_change", J60 > I60), "Expansion", AND(H60="price_change", J60 < I60), "Contraction", H60="plan_upgrade", "Expansion", H60="plan_downgrade", "Contraction", H60="discount_added", "Contraction")} -> Expansion | S60: {=_xlfn.IFS(H60="created",O60*P60*(1-Q60/100),H60="cancelled",-(O60*P60*(1-Q60/100)),H60="seats_change",(J60-I60)*P60*(1-Q60/100),H60="price_change",(J60-I60)*O60*(1-Q60/100),H60="discount_added",-(O60*P60*(J60-I60)/100),H60="plan_upgrade",O60*(_xlfn.XLOOKUP(J60,tbl_Plans[plan_name],tbl_Plans[monthly_price])-_xlfn.XLOOKUP(I60,tbl_Plans[plan_name],tbl_Plans[monthly_price]))*(1-Q60/100),H60="plan_downgrade",O60*(_xlfn.XLOOKUP(J60,tbl_Plans[plan_name],tbl_Plans[monthly_price])-_xlfn.XLOOKUP(I60,tbl_Plans[plan_name],tbl_Plans[monthly_price]))*(1-Q60/100))*IF(N60="Annual",1/12,1)} -> 280
A61: EVT060 | B61: SUB034 | C61: CUST034 | D61: Quebec Education Platform | E61: Eastern Canada | F61: 45748 | G61: 45761 | H61: created | M61: Analytics Starter | N61: Monthly | O61: 16 | P61: 45 | Q61: 0 | R61: {=_xlfn.IFS(H61="created", "New", H61="cancelled", "Churned", AND(H61="seats_change", J61 > I61), "Expansion", AND(H61="seats_change", J61 < I61), "Contraction", AND(H61="price_change", J61 > I61), "Expansion", AND(H61="price_change", J61 < I61), "Contraction", H61="plan_upgrade", "Expansion", H61="plan_downgrade", "Contraction", H61="discount_added", "Contraction")} -> New | S61: {=_xlfn.IFS(H61="created",O61*P61*(1-Q61/100),H61="cancelled",-(O61*P61*(1-Q61/100)),H61="seats_change",(J61-I61)*P61*(1-Q61/100),H61="price_change",(J61-I61)*O61*(1-Q61/100),H61="discount_added",-(O61*P61*(J61-I61)/100),H61="plan_upgrade",O61*(_xlfn.XLOOKUP(J61,tbl_Plans[plan_name],tbl_Plans[monthly_price])-_xlfn.XLOOKUP(I61,tbl_Plans[plan_name],tbl_Plans[monthly_price]))*(1-Q61/100),H61="plan_downgrade",O61*(_xlfn.XLOOKUP(J61,tbl_Plans[plan_name],tbl_Plans[monthly_price])-_xlfn.XLOOKUP(I61,tbl_Plans[plan_name],tbl_Plans[monthly_price]))*(1-Q61/100))*IF(N61="Annual",1/12,1)} -> 720
A62: EVT061 | B62: SUB012 | C62: CUST012 | D62: Maritime E-commerce | E62: Eastern Canada | F62: 45748 | G62: 45762 | H62: seats_change | I62: 18 | J62: 23 | K62: seats | L62: New hires onboarded - sales team expansion | M62: Analytics Growth | N62: Monthly | O62: 23 | P62: 95 | Q62: 0 | R62: {=_xlfn.IFS(H62="created", "New", H62="cancelled", "Churned", AND(H62="seats_change", J62 > I62), "Expansion", AND(H62="seats_change", J62 < I62), "Contraction", AND(H62="price_change", J62 > I62), "Expansion", AND(H62="price_change", J62 < I62), "Contraction", H62="plan_upgrade", "Expansion", H62="plan_downgrade", "Contraction", H62="discount_added", "Contraction")} -> Expansion | S62: {=_xlfn.IFS(H62="created",O62*P62*(1-Q62/100),H62="cancelled",-(O62*P62*(1-Q62/100)),H62="seats_change",(J62-I62)*P62*(1-Q62/100),H62="price_change",(J62-I62)*O62*(1-Q62/100),H62="discount_added",-(O62*P62*(J62-I62)/100),H62="plan_upgrade",O62*(_xlfn.XLOOKUP(J62,tbl_Plans[plan_name],tbl_Plans[monthly_price])-_xlfn.XLOOKUP(I62,tbl_Plans[plan_name],tbl_Plans[monthly_price]))*(1-Q62/100),H62="plan_downgrade",O62*(_xlfn.XLOOKUP(J62,tbl_Plans[plan_name],tbl_Plans[monthly_price])-_xlfn.XLOOKUP(I62,tbl_Plans[plan_name],tbl_Plans[monthly_price]))*(1-Q62/100))*IF(N62="Annual",1/12,1)} -> 475
A63: EVT062 | B63: SUB047 | C63: CUST022 | D63: Toronto Tech Ventures | E63: Eastern Canada | F63: 45748 | G63: 45765 | H63: created | M63: Sales Hub | N63: Monthly | O63: 26 | P63: 110 | Q63: 0 | R63: {=_xlfn.IFS(H63="created", "New", H63="cancelled", "Churned", AND(H63="seats_change", J63 > I63), "Expansion", AND(H63="seats_change", J63 < I63), "Contraction", AND(H63="price_change", J63 > I63), "Expansion", AND(H63="price_change", J63 < I63), "Contraction", H63="plan_upgrade", "Expansion", H63="plan_downgrade", "Contraction", H63="discount_added", "Contraction")} -> New | S63: {=_xlfn.IFS(H63="created",O63*P63*(1-Q63/100),H63="cancelled",-(O63*P63*(1-Q63/100)),H63="seats_change",(J63-I63)*P63*(1-Q63/100),H63="price_change",(J63-I63)*O63*(1-Q63/100),H63="discount_added",-(O63*P63*(J63-I63)/100),H63="plan_upgrade",O63*(_xlfn.XLOOKUP(J63,tbl_Plans[plan_name],tbl_Plans[monthly_price])-_xlfn.XLOOKUP(I63,tbl_Plans[plan_name],tbl_Plans[monthly_price]))*(1-Q63/100),H63="plan_downgrade",O63*(_xlfn.XLOOKUP(J63,tbl_Plans[plan_name],tbl_Plans[monthly_price])-_xlfn.XLOOKUP(I63,tbl_Plans[plan_name],tbl_Plans[monthly_price]))*(1-Q63/100))*IF(N63="Annual",1/12,1)} -> 2860
A64: EVT063 | B64: SUB035 | C64: CUST035 | D64: Vancouver Health Systems | E64: Western Canada | F64: 45748 | G64: 45775 | H64: created | M64: Sales Hub | N64: Monthly | O64: 20 | P64: 110 | Q64: 0 | R64: {=_xlfn.IFS(H64="created", "New", H64="cancelled", "Churned", AND(H64="seats_change", J64 > I64), "Expansion", AND(H64="seats_change", J64 < I64), "Contraction", AND(H64="price_change", J64 > I64), "Expansion", AND(H64="price_change", J64 < I64), "Contraction", H64="plan_upgrade", "Expansion", H64="plan_downgrade", "Contraction", H64="discount_added", "Contraction")} -> New | S64: {=_xlfn.IFS(H64="created",O64*P64*(1-Q64/100),H64="cancelled",-(O64*P64*(1-Q64/100)),H64="seats_change",(J64-I64)*P64*(1-Q64/100),H64="price_change",(J64-I64)*O64*(1-Q64/100),H64="discount_added",-(O64*P64*(J64-I64)/100),H64="plan_upgrade",O64*(_xlfn.XLOOKUP(J64,tbl_Plans[plan_name],tbl_Plans[monthly_price])-_xlfn.XLOOKUP(I64,tbl_Plans[plan_name],tbl_Plans[monthly_price]))*(1-Q64/100),H64="plan_downgrade",O64*(_xlfn.XLOOKUP(J64,tbl_Plans[plan_name],tbl_Plans[monthly_price])-_xlfn.XLOOKUP(I64,tbl_Plans[plan_name],tbl_Plans[monthly_price]))*(1-Q64/100))*IF(N64="Annual",1/12,1)} -> 2200
A65: EVT064 | B65: SUB004 | C65: CUST004 | D65: Prairie Commerce Group | E65: Western Canada | F65: 45778 | G65: 45787 | H65: seats_change | I65: 15 | J65: 18 | K65: seats | L65: Team expansion - 3 new account managers onboarded | M65: Sales Hub | N65: Monthly | O65: 18 | P65: 110 | Q65: 0 | R65: {=_xlfn.IFS(H65="created", "New", H65="cancelled", "Churned", AND(H65="seats_change", J65 > I65), "Expansion", AND(H65="seats_change", J65 < I65), "Contraction", AND(H65="price_change", J65 > I65), "Expansion", AND(H65="price_change", J65 < I65), "Contraction", H65="plan_upgrade", "Expansion", H65="plan_downgrade", "Contraction", H65="discount_added", "Contraction")} -> Expansion | S65: {=_xlfn.IFS(H65="created",O65*P65*(1-Q65/100),H65="cancelled",-(O65*P65*(1-Q65/100)),H65="seats_change",(J65-I65)*P65*(1-Q65/100),H65="price_change",(J65-I65)*O65*(1-Q65/100),H65="discount_added",-(O65*P65*(J65-I65)/100),H65="plan_upgrade",O65*(_xlfn.XLOOKUP(J65,tbl_Plans[plan_name],tbl_Plans[monthly_price])-_xlfn.XLOOKUP(I65,tbl_Plans[plan_name],tbl_Plans[monthly_price]))*(1-Q65/100),H65="plan_downgrade",O65*(_xlfn.XLOOKUP(J65,tbl_Plans[plan_name],tbl_Plans[monthly_price])-_xlfn.XLOOKUP(I65,tbl_Plans[plan_name],tbl_Plans[monthly_price]))*(1-Q65/100))*IF(N65="Annual",1/12,1)} -> 330
A66: EVT065 | B66: SUB036 | C66: CUST036 | D66: Manitoba Finance Group | E66: Central Canada | F66: 45778 | G66: 45789 | H66: created | M66: Analytics Growth | N66: Monthly | O66: 18 | P66: 95 | Q66: 0 | R66: {=_xlfn.IFS(H66="created", "New", H66="cancelled", "Churned", AND(H66="seats_change", J66 > I66), "Expansion", AND(H66="seats_change", J66 < I66), "Contraction", AND(H66="price_change", J66 > I66), "Expansion", AND(H66="price_change", J66 < I66), "Contraction", H66="plan_upgrade", "Expansion", H66="plan_downgrade", "Contraction", H66="discount_added", "Contraction")} -> New | S66: {=_xlfn.IFS(H66="created",O66*P66*(1-Q66/100),H66="cancelled",-(O66*P66*(1-Q66/100)),H66="seats_change",(J66-I66)*P66*(1-Q66/100),H66="price_change",(J66-I66)*O66*(1-Q66/100),H66="discount_added",-(O66*P66*(J66-I66)/100),H66="plan_upgrade",O66*(_xlfn.XLOOKUP(J66,tbl_Plans[plan_name],tbl_Plans[monthly_price])-_xlfn.XLOOKUP(I66,tbl_Plans[plan_name],tbl_Plans[monthly_price]))*(1-Q66/100),H66="plan_downgrade",O66*(_xlfn.XLOOKUP(J66,tbl_Plans[plan_name],tbl_Plans[monthly_price])-_xlfn.XLOOKUP(I66,tbl_Plans[plan_name],tbl_Plans[monthly_price]))*(1-Q66/100))*IF(N66="Annual",1/12,1)} -> 1710
A67: EVT066 | B67: SUB061 | C67: CUST013 | D67: Alberta Tech Innovators | E67: Western Canada | F67: 45778 | G67: 45797 | H67: created | L67: Returning customer â€” reactivation | M67: Analytics Growth | N67: Monthly | O67: 12 | P67: 95 | Q67: 0 | R67: {=_xlfn.IFS(H67="created", "New", H67="cancelled", "Churned", AND(H67="seats_change", J67 > I67), "Expansion", AND(H67="seats_change", J67 < I67), "Contraction", AND(H67="price_change", J67 > I67), "Expansion", AND(H67="price_change", J67 < I67), "Contraction", H67="plan_upgrade", "Expansion", H67="plan_downgrade", "Contraction", H67="discount_added", "Contraction")} -> New | S67: {=_xlfn.IFS(H67="created",O67*P67*(1-Q67/100),H67="cancelled",-(O67*P67*(1-Q67/100)),H67="seats_change",(J67-I67)*P67*(1-Q67/100),H67="price_change",(J67-I67)*O67*(1-Q67/100),H67="discount_added",-(O67*P67*(J67-I67)/100),H67="plan_upgrade",O67*(_xlfn.XLOOKUP(J67,tbl_Plans[plan_name],tbl_Plans[monthly_price])-_xlfn.XLOOKUP(I67,tbl_Plans[plan_name],tbl_Plans[monthly_price]))*(1-Q67/100),H67="plan_downgrade",O67*(_xlfn.XLOOKUP(J67,tbl_Plans[plan_name],tbl_Plans[monthly_price])-_xlfn.XLOOKUP(I67,tbl_Plans[plan_name],tbl_Plans[monthly_price]))*(1-Q67/100))*IF(N67="Annual",1/12,1)} -> 1140
A68: EVT067 | B68: SUB048 | C68: CUST025 | D68: Montreal Manufacturing Pro | E68: Eastern Canada | F68: 45778 | G68: 45799 | H68: created | M68: Sales Hub | N68: Monthly | O68: 36 | P68: 110 | Q68: 0 | R68: {=_xlfn.IFS(H68="created", "New", H68="cancelled", "Churned", AND(H68="seats_change", J68 > I68), "Expansion", AND(H68="seats_change", J68 < I68), "Contraction", AND(H68="price_change", J68 > I68), "Expansion", AND(H68="price_change", J68 < I68), "Contraction", H68="plan_upgrade", "Expansion", H68="plan_downgrade", "Contraction", H68="discount_added", "Contraction")} -> New | S68: {=_xlfn.IFS(H68="created",O68*P68*(1-Q68/100),H68="cancelled",-(O68*P68*(1-Q68/100)),H68="seats_change",(J68-I68)*P68*(1-Q68/100),H68="price_change",(J68-I68)*O68*(1-Q68/100),H68="discount_added",-(O68*P68*(J68-I68)/100),H68="plan_upgrade",O68*(_xlfn.XLOOKUP(J68,tbl_Plans[plan_name],tbl_Plans[monthly_price])-_xlfn.XLOOKUP(I68,tbl_Plans[plan_name],tbl_Plans[monthly_price]))*(1-Q68/100),H68="plan_downgrade",O68*(_xlfn.XLOOKUP(J68,tbl_Plans[plan_name],tbl_Plans[monthly_price])-_xlfn.XLOOKUP(I68,tbl_Plans[plan_name],tbl_Plans[monthly_price]))*(1-Q68/100))*IF(N68="Annual",1/12,1)} -> 3960
A69: EVT068 | B69: SUB021 | C69: CUST021 | D69: Calgary Commerce Solutions | E69: Western Canada | F69: 45778 | G69: 45803 | H69: cancelled | I69: active | J69: churned | K69: status | L69: Company downsizing | M69: Analytics Growth | N69: Monthly | O69: 25 | P69: 95 | Q69: 0 | R69: {=_xlfn.IFS(H69="created", "New", H69="cancelled", "Churned", AND(H69="seats_change", J69 > I69), "Expansion", AND(H69="seats_change", J69 < I69), "Contraction", AND(H69="price_change", J69 > I69), "Expansion", AND(H69="price_change", J69 < I69), "Contraction", H69="plan_upgrade", "Expansion", H69="plan_downgrade", "Contraction", H69="discount_added", "Contraction")} -> Churned | S69: {=_xlfn.IFS(H69="created",O69*P69*(1-Q69/100),H69="cancelled",-(O69*P69*(1-Q69/100)),H69="seats_change",(J69-I69)*P69*(1-Q69/100),H69="price_change",(J69-I69)*O69*(1-Q69/100),H69="discount_added",-(O69*P69*(J69-I69)/100),H69="plan_upgrade",O69*(_xlfn.XLOOKUP(J69,tbl_Plans[plan_name],tbl_Plans[monthly_price])-_xlfn.XLOOKUP(I69,tbl_Plans[plan_name],tbl_Plans[monthly_price]))*(1-Q69/100),H69="plan_downgrade",O69*(_xlfn.XLOOKUP(J69,tbl_Plans[plan_name],tbl_Plans[monthly_price])-_xlfn.XLOOKUP(I69,tbl_Plans[plan_name],tbl_Plans[monthly_price]))*(1-Q69/100))*IF(N69="Annual",1/12,1)} -> -2375
A70: EVT069 | B70: SUB037 | C70: CUST037 | D70: Maritime SaaS Ventures | E70: Eastern Canada | F70: 45778 | G70: 45803 | H70: created | M70: Platform Suite | N70: Monthly | O70: 35 | P70: 150 | Q70: 0 | R70: {=_xlfn.IFS(H70="created", "New", H70="cancelled", "Churned", AND(H70="seats_change", J70 > I70), "Expansion", AND(H70="seats_change", J70 < I70), "Contraction", AND(H70="price_change", J70 > I70), "Expansion", AND(H70="price_change", J70 < I70), "Contraction", H70="plan_upgrade", "Expansion", H70="plan_downgrade", "Contraction", H70="discount_added", "Contraction")} -> New | S70: {=_xlfn.IFS(H70="created",O70*P70*(1-Q70/100),H70="cancelled",-(O70*P70*(1-Q70/100)),H70="seats_change",(J70-I70)*P70*(1-Q70/100),H70="price_change",(J70-I70)*O70*(1-Q70/100),H70="discount_added",-(O70*P70*(J70-I70)/100),H70="plan_upgrade",O70*(_xlfn.XLOOKUP(J70,tbl_Plans[plan_name],tbl_Plans[monthly_price])-_xlfn.XLOOKUP(I70,tbl_Plans[plan_name],tbl_Plans[monthly_price]))*(1-Q70/100),H70="plan_downgrade",O70*(_xlfn.XLOOKUP(J70,tbl_Plans[plan_name],tbl_Plans[monthly_price])-_xlfn.XLOOKUP(I70,tbl_Plans[plan_name],tbl_Plans[monthly_price]))*(1-Q70/100))*IF(N70="Annual",1/12,1)} -> 5250
A71: EVT070 | B71: SUB018 | C71: CUST018 | D71: Vancouver FinTech Labs | E71: Western Canada | F71: 45809 | G71: 45809 | H71: seats_change | I71: 30 | J71: 35 | K71: seats | L71: Department growth - added analytics sub-team | M71: Analytics Enterprise | N71: Monthly | O71: 35 | P71: 180 | Q71: 0 | R71: {=_xlfn.IFS(H71="created", "New", H71="cancelled", "Churned", AND(H71="seats_change", J71 > I71), "Expansion", AND(H71="seats_change", J71 < I71), "Contraction", AND(H71="price_change", J71 > I71), "Expansion", AND(H71="price_change", J71 < I71), "Contraction", H71="plan_upgrade", "Expansion", H71="plan_downgrade", "Contraction", H71="discount_added", "Contraction")} -> Expansion | S71: {=_xlfn.IFS(H71="created",O71*P71*(1-Q71/100),H71="cancelled",-(O71*P71*(1-Q71/100)),H71="seats_change",(J71-I71)*P71*(1-Q71/100),H71="price_change",(J71-I71)*O71*(1-Q71/100),H71="discount_added",-(O71*P71*(J71-I71)/100),H71="plan_upgrade",O71*(_xlfn.XLOOKUP(J71,tbl_Plans[plan_name],tbl_Plans[monthly_price])-_xlfn.XLOOKUP(I71,tbl_Plans[plan_name],tbl_Plans[monthly_price]))*(1-Q71/100),H71="plan_downgrade",O71*(_xlfn.XLOOKUP(J71,tbl_Plans[plan_name],tbl_Plans[monthly_price])-_xlfn.XLOOKUP(I71,tbl_Plans[plan_name],tbl_Plans[monthly_price]))*(1-Q71/100))*IF(N71="Annual",1/12,1)} -> 900
A72: EVT071 | B72: SUB053 | C72: CUST027 | D72: Pacific Finance Corp | E72: Western Canada | F72: 45809 | G72: 45813 | H72: created | M72: Analytics Enterprise | N72: Monthly | O72: 31 | P72: 180 | Q72: 0 | R72: {=_xlfn.IFS(H72="created", "New", H72="cancelled", "Churned", AND(H72="seats_change", J72 > I72), "Expansion", AND(H72="seats_change", J72 < I72), "Contraction", AND(H72="price_change", J72 > I72), "Expansion", AND(H72="price_change", J72 < I72), "Contraction", H72="plan_upgrade", "Expansion", H72="plan_downgrade", "Contraction", H72="discount_added", "Contraction")} -> New | S72: {=_xlfn.IFS(H72="created",O72*P72*(1-Q72/100),H72="cancelled",-(O72*P72*(1-Q72/100)),H72="seats_change",(J72-I72)*P72*(1-Q72/100),H72="price_change",(J72-I72)*O72*(1-Q72/100),H72="discount_added",-(O72*P72*(J72-I72)/100),H72="plan_upgrade",O72*(_xlfn.XLOOKUP(J72,tbl_Plans[plan_name],tbl_Plans[monthly_price])-_xlfn.XLOOKUP(I72,tbl_Plans[plan_name],tbl_Plans[monthly_price]))*(1-Q72/100),H72="plan_downgrade",O72*(_xlfn.XLOOKUP(J72,tbl_Plans[plan_name],tbl_Plans[monthly_price])-_xlfn.XLOOKUP(I72,tbl_Plans[plan_name],tbl_Plans[monthly_price]))*(1-Q72/100))*IF(N72="Annual",1/12,1)} -> 5580
A73: EVT072 | B73: SUB038 | C73: CUST038 | D73: Calgary Tech Partners | E73: Western Canada | F73: 45809 | G73: 45817 | H73: created | M73: Analytics Starter | N73: Monthly | O73: 13 | P73: 45 | Q73: 0 | R73: {=_xlfn.IFS(H73="created", "New", H73="cancelled", "Churned", AND(H73="seats_change", J73 > I73), "Expansion", AND(H73="seats_change", J73 < I73), "Contraction", AND(H73="price_change", J73 > I73), "Expansion", AND(H73="price_change", J73 < I73), "Contraction", H73="plan_upgrade", "Expansion", H73="plan_downgrade", "Contraction", H73="discount_added", "Contraction")} -> New | S73: {=_xlfn.IFS(H73="created",O73*P73*(1-Q73/100),H73="cancelled",-(O73*P73*(1-Q73/100)),H73="seats_change",(J73-I73)*P73*(1-Q73/100),H73="price_change",(J73-I73)*O73*(1-Q73/100),H73="discount_added",-(O73*P73*(J73-I73)/100),H73="plan_upgrade",O73*(_xlfn.XLOOKUP(J73,tbl_Plans[plan_name],tbl_Plans[monthly_price])-_xlfn.XLOOKUP(I73,tbl_Plans[plan_name],tbl_Plans[monthly_price]))*(1-Q73/100),H73="plan_downgrade",O73*(_xlfn.XLOOKUP(J73,tbl_Plans[plan_name],tbl_Plans[monthly_price])-_xlfn.XLOOKUP(I73,tbl_Plans[plan_name],tbl_Plans[monthly_price]))*(1-Q73/100))*IF(N73="Annual",1/12,1)} -> 585
A74: EVT073 | B74: SUB049 | C74: CUST012 | D74: Maritime E-commerce | E74: Eastern Canada | F74: 45809 | G74: 45818 | H74: cancelled | I74: active | J74: cancelled | K74: status | L74: No longer needed | M74: Analytics Starter | N74: Monthly | O74: 19 | P74: 45 | Q74: 0 | R74: {=_xlfn.IFS(H74="created", "New", H74="cancelled", "Churned", AND(H74="seats_change", J74 > I74), "Expansion", AND(H74="seats_change", J74 < I74), "Contraction", AND(H74="price_change", J74 > I74), "Expansion", AND(H74="price_change", J74 < I74), "Contraction", H74="plan_upgrade", "Expansion", H74="plan_downgrade", "Contraction", H74="discount_added", "Contraction")} -> Churned | S74: {=_xlfn.IFS(H74="created",O74*P74*(1-Q74/100),H74="cancelled",-(O74*P74*(1-Q74/100)),H74="seats_change",(J74-I74)*P74*(1-Q74/100),H74="price_change",(J74-I74)*O74*(1-Q74/100),H74="discount_added",-(O74*P74*(J74-I74)/100),H74="plan_upgrade",O74*(_xlfn.XLOOKUP(J74,tbl_Plans[plan_name],tbl_Plans[monthly_price])-_xlfn.XLOOKUP(I74,tbl_Plans[plan_name],tbl_Plans[monthly_price]))*(1-Q74/100),H74="plan_downgrade",O74*(_xlfn.XLOOKUP(J74,tbl_Plans[plan_name],tbl_Plans[monthly_price])-_xlfn.XLOOKUP(I74,tbl_Plans[plan_name],tbl_Plans[monthly_price]))*(1-Q74/100))*IF(N74="Annual",1/12,1)} -> -855
A75: EVT074 | B75: SUB026 | C75: CUST026 | D75: Ontario Education Connect | E75: Eastern Canada | F75: 45809 | G75: 45823 | H75: plan_upgrade | I75: Analytics Starter | J75: Analytics Growth | K75: plan_name | L75: Growing usage - upgraded for advanced features and higher limits | M75: Analytics Growth | N75: Monthly | O75: 16 | P75: 95 | Q75: 0 | R75: {=_xlfn.IFS(H75="created", "New", H75="cancelled", "Churned", AND(H75="seats_change", J75 > I75), "Expansion", AND(H75="seats_change", J75 < I75), "Contraction", AND(H75="price_change", J75 > I75), "Expansion", AND(H75="price_change", J75 < I75), "Contraction", H75="plan_upgrade", "Expansion", H75="plan_downgrade", "Contraction", H75="discount_added", "Contraction")} -> Expansion | S75: {=_xlfn.IFS(H75="created",O75*P75*(1-Q75/100),H75="cancelled",-(O75*P75*(1-Q75/100)),H75="seats_change",(J75-I75)*P75*(1-Q75/100),H75="price_change",(J75-I75)*O75*(1-Q75/100),H75="discount_added",-(O75*P75*(J75-I75)/100),H75="plan_upgrade",O75*(_xlfn.XLOOKUP(J75,tbl_Plans[plan_name],tbl_Plans[monthly_price])-_xlfn.XLOOKUP(I75,tbl_Plans[plan_name],tbl_Plans[monthly_price]))*(1-Q75/100),H75="plan_downgrade",O75*(_xlfn.XLOOKUP(J75,tbl_Plans[plan_name],tbl_Plans[monthly_price])-_xlfn.XLOOKUP(I75,tbl_Plans[plan_name],tbl_Plans[monthly_price]))*(1-Q75/100))*IF(N75="Annual",1/12,1)} -> 800
A76: EVT075 | B76: SUB039 | C76: CUST039 | D76: Toronto Commerce Cloud | E76: Eastern Canada | F76: 45809 | G76: 45831 | H76: created | M76: Marketing Pro | N76: Monthly | O76: 29 | P76: 85 | Q76: 0 | R76: {=_xlfn.IFS(H76="created", "New", H76="cancelled", "Churned", AND(H76="seats_change", J76 > I76), "Expansion", AND(H76="seats_change", J76 < I76), "Contraction", AND(H76="price_change", J76 > I76), "Expansion", AND(H76="price_change", J76 < I76), "Contraction", H76="plan_upgrade", "Expansion", H76="plan_downgrade", "Contraction", H76="discount_added", "Contraction")} -> New | S76: {=_xlfn.IFS(H76="created",O76*P76*(1-Q76/100),H76="cancelled",-(O76*P76*(1-Q76/100)),H76="seats_change",(J76-I76)*P76*(1-Q76/100),H76="price_change",(J76-I76)*O76*(1-Q76/100),H76="discount_added",-(O76*P76*(J76-I76)/100),H76="plan_upgrade",O76*(_xlfn.XLOOKUP(J76,tbl_Plans[plan_name],tbl_Plans[monthly_price])-_xlfn.XLOOKUP(I76,tbl_Plans[plan_name],tbl_Plans[monthly_price]))*(1-Q76/100),H76="plan_downgrade",O76*(_xlfn.XLOOKUP(J76,tbl_Plans[plan_name],tbl_Plans[monthly_price])-_xlfn.XLOOKUP(I76,tbl_Plans[plan_name],tbl_Plans[monthly_price]))*(1-Q76/100))*IF(N76="Annual",1/12,1)} -> 2465
A77: EVT076 | B77: SUB023 | C77: CUST023 | D77: Island Media Productions | E77: Eastern Canada | F77: 45809 | G77: 45833 | H77: cancelled | I77: active | J77: churned | K77: status | L77: Missing features | M77: Analytics Starter | N77: Monthly | O77: 10 | P77: 45 | Q77: 0 | R77: {=_xlfn.IFS(H77="created", "New", H77="cancelled", "Churned", AND(H77="seats_change", J77 > I77), "Expansion", AND(H77="seats_change", J77 < I77), "Contraction", AND(H77="price_change", J77 > I77), "Expansion", AND(H77="price_change", J77 < I77), "Contraction", H77="plan_upgrade", "Expansion", H77="plan_downgrade", "Contraction", H77="discount_added", "Contraction")} -> Churned | S77: {=_xlfn.IFS(H77="created",O77*P77*(1-Q77/100),H77="cancelled",-(O77*P77*(1-Q77/100)),H77="seats_change",(J77-I77)*P77*(1-Q77/100),H77="price_change",(J77-I77)*O77*(1-Q77/100),H77="discount_added",-(O77*P77*(J77-I77)/100),H77="plan_upgrade",O77*(_xlfn.XLOOKUP(J77,tbl_Plans[plan_name],tbl_Plans[monthly_price])-_xlfn.XLOOKUP(I77,tbl_Plans[plan_name],tbl_Plans[monthly_price]))*(1-Q77/100),H77="plan_downgrade",O77*(_xlfn.XLOOKUP(J77,tbl_Plans[plan_name],tbl_Plans[monthly_price])-_xlfn.XLOOKUP(I77,tbl_Plans[plan_name],tbl_Plans[monthly_price]))*(1-Q77/100))*IF(N77="Annual",1/12,1)} -> -450
A78: EVT077 | B78: SUB059 | C78: CUST008 | D78: Quantum Education Platform | E78: Eastern Canada | F78: 45839 | G78: 45843 | H78: price_change | I78: 75 | J78: 85 | K78: price_per_seat | L78: Annual price increase applied at renewal | M78: Marketing Pro | N78: Monthly | O78: 22 | P78: 85 | Q78: 0 | R78: {=_xlfn.IFS(H78="created", "New", H78="cancelled", "Churned", AND(H78="seats_change", J78 > I78), "Expansion", AND(H78="seats_change", J78 < I78), "Contraction", AND(H78="price_change", J78 > I78), "Expansion", AND(H78="price_change", J78 < I78), "Contraction", H78="plan_upgrade", "Expansion", H78="plan_downgrade", "Contraction", H78="discount_added", "Contraction")} -> Expansion | S78: {=_xlfn.IFS(H78="created",O78*P78*(1-Q78/100),H78="cancelled",-(O78*P78*(1-Q78/100)),H78="seats_change",(J78-I78)*P78*(1-Q78/100),H78="price_change",(J78-I78)*O78*(1-Q78/100),H78="discount_added",-(O78*P78*(J78-I78)/100),H78="plan_upgrade",O78*(_xlfn.XLOOKUP(J78,tbl_Plans[plan_name],tbl_Plans[monthly_price])-_xlfn.XLOOKUP(I78,tbl_Plans[plan_name],tbl_Plans[monthly_price]))*(1-Q78/100),H78="plan_downgrade",O78*(_xlfn.XLOOKUP(J78,tbl_Plans[plan_name],tbl_Plans[monthly_price])-_xlfn.XLOOKUP(I78,tbl_Plans[plan_name],tbl_Plans[monthly_price]))*(1-Q78/100))*IF(N78="Annual",1/12,1)} -> 220
A79: EVT078 | B79: SUB060 | C79: CUST019 | D79: Central Healthcare Partners | E79: Central Canada | F79: 45839 | G79: 45858 | H79: cancelled | I79: active | J79: cancelled | K79: status | L79: Budget cuts | M79: Sales Hub | N79: Monthly | O79: 16 | P79: 110 | Q79: 0 | R79: {=_xlfn.IFS(H79="created", "New", H79="cancelled", "Churned", AND(H79="seats_change", J79 > I79), "Expansion", AND(H79="seats_change", J79 < I79), "Contraction", AND(H79="price_change", J79 > I79), "Expansion", AND(H79="price_change", J79 < I79), "Contraction", H79="plan_upgrade", "Expansion", H79="plan_downgrade", "Contraction", H79="discount_added", "Contraction")} -> Churned | S79: {=_xlfn.IFS(H79="created",O79*P79*(1-Q79/100),H79="cancelled",-(O79*P79*(1-Q79/100)),H79="seats_change",(J79-I79)*P79*(1-Q79/100),H79="price_change",(J79-I79)*O79*(1-Q79/100),H79="discount_added",-(O79*P79*(J79-I79)/100),H79="plan_upgrade",O79*(_xlfn.XLOOKUP(J79,tbl_Plans[plan_name],tbl_Plans[monthly_price])-_xlfn.XLOOKUP(I79,tbl_Plans[plan_name],tbl_Plans[monthly_price]))*(1-Q79/100),H79="plan_downgrade",O79*(_xlfn.XLOOKUP(J79,tbl_Plans[plan_name],tbl_Plans[monthly_price])-_xlfn.XLOOKUP(I79,tbl_Plans[plan_name],tbl_Plans[monthly_price]))*(1-Q79/100))*IF(N79="Annual",1/12,1)} -> -1760
A80: EVT079 | B80: SUB011 | C80: CUST011 | D80: Prairie Health Connect | E80: Central Canada | F80: 45839 | G80: 45860 | H80: seats_change | I80: 14 | J80: 18 | K80: seats | L80: Team expansion - mid-year headcount increase | M80: Sales Hub | N80: Monthly | O80: 18 | P80: 110 | Q80: 0 | R80: {=_xlfn.IFS(H80="created", "New", H80="cancelled", "Churned", AND(H80="seats_change", J80 > I80), "Expansion", AND(H80="seats_change", J80 < I80), "Contraction", AND(H80="price_change", J80 > I80), "Expansion", AND(H80="price_change", J80 < I80), "Contraction", H80="plan_upgrade", "Expansion", H80="plan_downgrade", "Contraction", H80="discount_added", "Contraction")} -> Expansion | S80: {=_xlfn.IFS(H80="created",O80*P80*(1-Q80/100),H80="cancelled",-(O80*P80*(1-Q80/100)),H80="seats_change",(J80-I80)*P80*(1-Q80/100),H80="price_change",(J80-I80)*O80*(1-Q80/100),H80="discount_added",-(O80*P80*(J80-I80)/100),H80="plan_upgrade",O80*(_xlfn.XLOOKUP(J80,tbl_Plans[plan_name],tbl_Plans[monthly_price])-_xlfn.XLOOKUP(I80,tbl_Plans[plan_name],tbl_Plans[monthly_price]))*(1-Q80/100),H80="plan_downgrade",O80*(_xlfn.XLOOKUP(J80,tbl_Plans[plan_name],tbl_Plans[monthly_price])-_xlfn.XLOOKUP(I80,tbl_Plans[plan_name],tbl_Plans[monthly_price]))*(1-Q80/100))*IF(N80="Annual",1/12,1)} -> 440
A81: EVT080 | B81: SUB029 | C81: CUST029 | D81: Halifax Healthcare Tech | E81: Eastern Canada | F81: 45870 | G81: 45872 | H81: price_change | I81: 90 | J81: 85 | K81: price_per_seat | L81: Renewal negotiation - competitive pricing match | M81: Marketing Pro | N81: Monthly | O81: 22 | P81: 85 | Q81: 0 | R81: {=_xlfn.IFS(H81="created", "New", H81="cancelled", "Churned", AND(H81="seats_change", J81 > I81), "Expansion", AND(H81="seats_change", J81 < I81), "Contraction", AND(H81="price_change", J81 > I81), "Expansion", AND(H81="price_change", J81 < I81), "Contraction", H81="plan_upgrade", "Expansion", H81="plan_downgrade", "Contraction", H81="discount_added", "Contraction")} -> Contraction | S81: {=_xlfn.IFS(H81="created",O81*P81*(1-Q81/100),H81="cancelled",-(O81*P81*(1-Q81/100)),H81="seats_change",(J81-I81)*P81*(1-Q81/100),H81="price_change",(J81-I81)*O81*(1-Q81/100),H81="discount_added",-(O81*P81*(J81-I81)/100),H81="plan_upgrade",O81*(_xlfn.XLOOKUP(J81,tbl_Plans[plan_name],tbl_Plans[monthly_price])-_xlfn.XLOOKUP(I81,tbl_Plans[plan_name],tbl_Plans[monthly_price]))*(1-Q81/100),H81="plan_downgrade",O81*(_xlfn.XLOOKUP(J81,tbl_Plans[plan_name],tbl_Plans[monthly_price])-_xlfn.XLOOKUP(I81,tbl_Plans[plan_name],tbl_Plans[monthly_price]))*(1-Q81/100))*IF(N81="Annual",1/12,1)} -> -110
A82: EVT081 | B82: SUB032 | C82: CUST032 | D82: BC Manufacturing Systems | E82: Western Canada | F82: 45870 | G82: 45881 | H82: plan_upgrade | I82: Analytics Growth | J82: Analytics Enterprise | K82: plan_name | L82: Enterprise SSO and audit logs required | M82: Analytics Enterprise | N82: Monthly | O82: 26 | P82: 180 | Q82: 0 | R82: {=_xlfn.IFS(H82="created", "New", H82="cancelled", "Churned", AND(H82="seats_change", J82 > I82), "Expansion", AND(H82="seats_change", J82 < I82), "Contraction", AND(H82="price_change", J82 > I82), "Expansion", AND(H82="price_change", J82 < I82), "Contraction", H82="plan_upgrade", "Expansion", H82="plan_downgrade", "Contraction", H82="discount_added", "Contraction")} -> Expansion | S82: {=_xlfn.IFS(H82="created",O82*P82*(1-Q82/100),H82="cancelled",-(O82*P82*(1-Q82/100)),H82="seats_change",(J82-I82)*P82*(1-Q82/100),H82="price_change",(J82-I82)*O82*(1-Q82/100),H82="discount_added",-(O82*P82*(J82-I82)/100),H82="plan_upgrade",O82*(_xlfn.XLOOKUP(J82,tbl_Plans[plan_name],tbl_Plans[monthly_price])-_xlfn.XLOOKUP(I82,tbl_Plans[plan_name],tbl_Plans[monthly_price]))*(1-Q82/100),H82="plan_downgrade",O82*(_xlfn.XLOOKUP(J82,tbl_Plans[plan_name],tbl_Plans[monthly_price])-_xlfn.XLOOKUP(I82,tbl_Plans[plan_name],tbl_Plans[monthly_price]))*(1-Q82/100))*IF(N82="Annual",1/12,1)} -> 2210
A83: EVT082 | B83: SUB017 | C83: CUST017 | D83: Capital Education Tech | E83: Eastern Canada | F83: 45870 | G83: 45888 | H83: plan_downgrade | I83: Analytics Growth | J83: Analytics Starter | K83: plan_name | L83: Reduced usage - advanced features no longer needed | M83: Analytics Starter | N83: Monthly | O83: 12 | P83: 45 | Q83: 0 | R83: {=_xlfn.IFS(H83="created", "New", H83="cancelled", "Churned", AND(H83="seats_change", J83 > I83), "Expansion", AND(H83="seats_change", J83 < I83), "Contraction", AND(H83="price_change", J83 > I83), "Expansion", AND(H83="price_change", J83 < I83), "Contraction", H83="plan_upgrade", "Expansion", H83="plan_downgrade", "Contraction", H83="discount_added", "Contraction")} -> Contraction | S83: {=_xlfn.IFS(H83="created",O83*P83*(1-Q83/100),H83="cancelled",-(O83*P83*(1-Q83/100)),H83="seats_change",(J83-I83)*P83*(1-Q83/100),H83="price_change",(J83-I83)*O83*(1-Q83/100),H83="discount_added",-(O83*P83*(J83-I83)/100),H83="plan_upgrade",O83*(_xlfn.XLOOKUP(J83,tbl_Plans[plan_name],tbl_Plans[monthly_price])-_xlfn.XLOOKUP(I83,tbl_Plans[plan_name],tbl_Plans[monthly_price]))*(1-Q83/100),H83="plan_downgrade",O83*(_xlfn.XLOOKUP(J83,tbl_Plans[plan_name],tbl_Plans[monthly_price])-_xlfn.XLOOKUP(I83,tbl_Plans[plan_name],tbl_Plans[monthly_price]))*(1-Q83/100))*IF(N83="Annual",1/12,1)} -> -600
A84: EVT083 | B84: SUB022 | C84: CUST022 | D84: Toronto Tech Ventures | E84: Eastern Canada | F84: 45870 | G84: 45889 | H84: seats_change | I84: 28 | J84: 33 | K84: seats | L84: Team expansion - ops team grew | M84: Platform Suite | N84: Monthly | O84: 33 | P84: 150 | Q84: 0 | R84: {=_xlfn.IFS(H84="created", "New", H84="cancelled", "Churned", AND(H84="seats_change", J84 > I84), "Expansion", AND(H84="seats_change", J84 < I84), "Contraction", AND(H84="price_change", J84 > I84), "Expansion", AND(H84="price_change", J84 < I84), "Contraction", H84="plan_upgrade", "Expansion", H84="plan_downgrade", "Contraction", H84="discount_added", "Contraction")} -> Expansion | S84: {=_xlfn.IFS(H84="created",O84*P84*(1-Q84/100),H84="cancelled",-(O84*P84*(1-Q84/100)),H84="seats_change",(J84-I84)*P84*(1-Q84/100),H84="price_change",(J84-I84)*O84*(1-Q84/100),H84="discount_added",-(O84*P84*(J84-I84)/100),H84="plan_upgrade",O84*(_xlfn.XLOOKUP(J84,tbl_Plans[plan_name],tbl_Plans[monthly_price])-_xlfn.XLOOKUP(I84,tbl_Plans[plan_name],tbl_Plans[monthly_price]))*(1-Q84/100),H84="plan_downgrade",O84*(_xlfn.XLOOKUP(J84,tbl_Plans[plan_name],tbl_Plans[monthly_price])-_xlfn.XLOOKUP(I84,tbl_Plans[plan_name],tbl_Plans[monthly_price]))*(1-Q84/100))*IF(N84="Annual",1/12,1)} -> 750
A85: EVT084 | B85: SUB055 | C85: CUST004 | D85: Prairie Commerce Group | E85: Western Canada | F85: 45870 | G85: 45899 | H85: cancelled | I85: active | J85: churned | K85: status | L85: Switched to competitor | M85: Analytics Enterprise | N85: Monthly | O85: 26 | P85: 180 | Q85: 0 | R85: {=_xlfn.IFS(H85="created", "New", H85="cancelled", "Churned", AND(H85="seats_change", J85 > I85), "Expansion", AND(H85="seats_change", J85 < I85), "Contraction", AND(H85="price_change", J85 > I85), "Expansion", AND(H85="price_change", J85 < I85), "Contraction", H85="plan_upgrade", "Expansion", H85="plan_downgrade", "Contraction", H85="discount_added", "Contraction")} -> Churned | S85: {=_xlfn.IFS(H85="created",O85*P85*(1-Q85/100),H85="cancelled",-(O85*P85*(1-Q85/100)),H85="seats_change",(J85-I85)*P85*(1-Q85/100),H85="price_change",(J85-I85)*O85*(1-Q85/100),H85="discount_added",-(O85*P85*(J85-I85)/100),H85="plan_upgrade",O85*(_xlfn.XLOOKUP(J85,tbl_Plans[plan_name],tbl_Plans[monthly_price])-_xlfn.XLOOKUP(I85,tbl_Plans[plan_name],tbl_Plans[monthly_price]))*(1-Q85/100),H85="plan_downgrade",O85*(_xlfn.XLOOKUP(J85,tbl_Plans[plan_name],tbl_Plans[monthly_price])-_xlfn.XLOOKUP(I85,tbl_Plans[plan_name],tbl_Plans[monthly_price]))*(1-Q85/100))*IF(N85="Annual",1/12,1)} -> -4680
A86: EVT085 | B86: SUB030 | C86: CUST030 | D86: Alberta E-commerce Hub | E86: Western Canada | F86: 45901 | G86: 45905 | H86: plan_upgrade | I86: Analytics Starter | J86: Analytics Growth | K86: plan_name | L86: Upgraded for advanced analytics and API access | M86: Analytics Growth | N86: Monthly | O86: 20 | P86: 95 | Q86: 0 | R86: {=_xlfn.IFS(H86="created", "New", H86="cancelled", "Churned", AND(H86="seats_change", J86 > I86), "Expansion", AND(H86="seats_change", J86 < I86), "Contraction", AND(H86="price_change", J86 > I86), "Expansion", AND(H86="price_change", J86 < I86), "Contraction", H86="plan_upgrade", "Expansion", H86="plan_downgrade", "Contraction", H86="discount_added", "Contraction")} -> Expansion | S86: {=_xlfn.IFS(H86="created",O86*P86*(1-Q86/100),H86="cancelled",-(O86*P86*(1-Q86/100)),H86="seats_change",(J86-I86)*P86*(1-Q86/100),H86="price_change",(J86-I86)*O86*(1-Q86/100),H86="discount_added",-(O86*P86*(J86-I86)/100),H86="plan_upgrade",O86*(_xlfn.XLOOKUP(J86,tbl_Plans[plan_name],tbl_Plans[monthly_price])-_xlfn.XLOOKUP(I86,tbl_Plans[plan_name],tbl_Plans[monthly_price]))*(1-Q86/100),H86="plan_downgrade",O86*(_xlfn.XLOOKUP(J86,tbl_Plans[plan_name],tbl_Plans[monthly_price])-_xlfn.XLOOKUP(I86,tbl_Plans[plan_name],tbl_Plans[monthly_price]))*(1-Q86/100))*IF(N86="Annual",1/12,1)} -> 1000
A87: EVT086 | B87: SUB053 | C87: CUST027 | D87: Pacific Finance Corp | E87: Western Canada | F87: 45901 | G87: 45910 | H87: seats_change | I87: 26 | J87: 31 | K87: seats | L87: Department expansion - data team scaling | M87: Analytics Enterprise | N87: Monthly | O87: 31 | P87: 180 | Q87: 0 | R87: {=_xlfn.IFS(H87="created", "New", H87="cancelled", "Churned", AND(H87="seats_change", J87 > I87), "Expansion", AND(H87="seats_change", J87 < I87), "Contraction", AND(H87="price_change", J87 > I87), "Expansion", AND(H87="price_change", J87 < I87), "Contraction", H87="plan_upgrade", "Expansion", H87="plan_downgrade", "Contraction", H87="discount_added", "Contraction")} -> Expansion | S87: {=_xlfn.IFS(H87="created",O87*P87*(1-Q87/100),H87="cancelled",-(O87*P87*(1-Q87/100)),H87="seats_change",(J87-I87)*P87*(1-Q87/100),H87="price_change",(J87-I87)*O87*(1-Q87/100),H87="discount_added",-(O87*P87*(J87-I87)/100),H87="plan_upgrade",O87*(_xlfn.XLOOKUP(J87,tbl_Plans[plan_name],tbl_Plans[monthly_price])-_xlfn.XLOOKUP(I87,tbl_Plans[plan_name],tbl_Plans[monthly_price]))*(1-Q87/100),H87="plan_downgrade",O87*(_xlfn.XLOOKUP(J87,tbl_Plans[plan_name],tbl_Plans[monthly_price])-_xlfn.XLOOKUP(I87,tbl_Plans[plan_name],tbl_Plans[monthly_price]))*(1-Q87/100))*IF(N87="Annual",1/12,1)} -> 900
A88: EVT087 | B88: SUB033 | C88: CUST033 | D88: Ottawa Retail Solutions | E88: Eastern Canada | F88: 45901 | G88: 45930 | H88: price_change | I88: 90 | J88: 85 | K88: price_per_seat | L88: Renewal negotiation - loyalty discount applied | M88: Marketing Pro | N88: Monthly | O88: 25 | P88: 85 | Q88: 0 | R88: {=_xlfn.IFS(H88="created", "New", H88="cancelled", "Churned", AND(H88="seats_change", J88 > I88), "Expansion", AND(H88="seats_change", J88 < I88), "Contraction", AND(H88="price_change", J88 > I88), "Expansion", AND(H88="price_change", J88 < I88), "Contraction", H88="plan_upgrade", "Expansion", H88="plan_downgrade", "Contraction", H88="discount_added", "Contraction")} -> Contraction | S88: {=_xlfn.IFS(H88="created",O88*P88*(1-Q88/100),H88="cancelled",-(O88*P88*(1-Q88/100)),H88="seats_change",(J88-I88)*P88*(1-Q88/100),H88="price_change",(J88-I88)*O88*(1-Q88/100),H88="discount_added",-(O88*P88*(J88-I88)/100),H88="plan_upgrade",O88*(_xlfn.XLOOKUP(J88,tbl_Plans[plan_name],tbl_Plans[monthly_price])-_xlfn.XLOOKUP(I88,tbl_Plans[plan_name],tbl_Plans[monthly_price]))*(1-Q88/100),H88="plan_downgrade",O88*(_xlfn.XLOOKUP(J88,tbl_Plans[plan_name],tbl_Plans[monthly_price])-_xlfn.XLOOKUP(I88,tbl_Plans[plan_name],tbl_Plans[monthly_price]))*(1-Q88/100))*IF(N88="Annual",1/12,1)} -> -125
A89: EVT088 | B89: SUB024 | C89: CUST024 | D89: Western Retail Group | E89: Western Canada | F89: 45931 | G89: 45935 | H89: seats_change | I89: 26 | J89: 31 | K89: seats | L89: New department added - customer success team | M89: Marketing Pro | N89: Monthly | O89: 31 | P89: 85 | Q89: 0 | R89: {=_xlfn.IFS(H89="created", "New", H89="cancelled", "Churned", AND(H89="seats_change", J89 > I89), "Expansion", AND(H89="seats_change", J89 < I89), "Contraction", AND(H89="price_change", J89 > I89), "Expansion", AND(H89="price_change", J89 < I89), "Contraction", H89="plan_upgrade", "Expansion", H89="plan_downgrade", "Contraction", H89="discount_added", "Contraction")} -> Expansion | S89: {=_xlfn.IFS(H89="created",O89*P89*(1-Q89/100),H89="cancelled",-(O89*P89*(1-Q89/100)),H89="seats_change",(J89-I89)*P89*(1-Q89/100),H89="price_change",(J89-I89)*O89*(1-Q89/100),H89="discount_added",-(O89*P89*(J89-I89)/100),H89="plan_upgrade",O89*(_xlfn.XLOOKUP(J89,tbl_Plans[plan_name],tbl_Plans[monthly_price])-_xlfn.XLOOKUP(I89,tbl_Plans[plan_name],tbl_Plans[monthly_price]))*(1-Q89/100),H89="plan_downgrade",O89*(_xlfn.XLOOKUP(J89,tbl_Plans[plan_name],tbl_Plans[monthly_price])-_xlfn.XLOOKUP(I89,tbl_Plans[plan_name],tbl_Plans[monthly_price]))*(1-Q89/100))*IF(N89="Annual",1/12,1)} -> 425
A90: EVT089 | B90: SUB062 | C90: CUST023 | D90: Island Media Productions | E90: Eastern Canada | F90: 45931 | G90: 45945 | H90: created | L90: Returning customer â€” reactivation | M90: Marketing Pro | N90: Monthly | O90: 11 | P90: 85 | Q90: 0 | R90: {=_xlfn.IFS(H90="created", "New", H90="cancelled", "Churned", AND(H90="seats_change", J90 > I90), "Expansion", AND(H90="seats_change", J90 < I90), "Contraction", AND(H90="price_change", J90 > I90), "Expansion", AND(H90="price_change", J90 < I90), "Contraction", H90="plan_upgrade", "Expansion", H90="plan_downgrade", "Contraction", H90="discount_added", "Contraction")} -> New | S90: {=_xlfn.IFS(H90="created",O90*P90*(1-Q90/100),H90="cancelled",-(O90*P90*(1-Q90/100)),H90="seats_change",(J90-I90)*P90*(1-Q90/100),H90="price_change",(J90-I90)*O90*(1-Q90/100),H90="discount_added",-(O90*P90*(J90-I90)/100),H90="plan_upgrade",O90*(_xlfn.XLOOKUP(J90,tbl_Plans[plan_name],tbl_Plans[monthly_price])-_xlfn.XLOOKUP(I90,tbl_Plans[plan_name],tbl_Plans[monthly_price]))*(1-Q90/100),H90="plan_downgrade",O90*(_xlfn.XLOOKUP(J90,tbl_Plans[plan_name],tbl_Plans[monthly_price])-_xlfn.XLOOKUP(I90,tbl_Plans[plan_name],tbl_Plans[monthly_price]))*(1-Q90/100))*IF(N90="Annual",1/12,1)} -> 935
A91: EVT090 | B91: SUB036 | C91: CUST036 | D91: Manitoba Finance Group | E91: Central Canada | F91: 45931 | G91: 45950 | H91: plan_upgrade | I91: Analytics Starter | J91: Analytics Growth | K91: plan_name | L91: Reached Starter usage limits - upgraded | M91: Analytics Growth | N91: Monthly | O91: 18 | P91: 95 | Q91: 0 | R91: {=_xlfn.IFS(H91="created", "New", H91="cancelled", "Churned", AND(H91="seats_change", J91 > I91), "Expansion", AND(H91="seats_change", J91 < I91), "Contraction", AND(H91="price_change", J91 > I91), "Expansion", AND(H91="price_change", J91 < I91), "Contraction", H91="plan_upgrade", "Expansion", H91="plan_downgrade", "Contraction", H91="discount_added", "Contraction")} -> Expansion | S91: {=_xlfn.IFS(H91="created",O91*P91*(1-Q91/100),H91="cancelled",-(O91*P91*(1-Q91/100)),H91="seats_change",(J91-I91)*P91*(1-Q91/100),H91="price_change",(J91-I91)*O91*(1-Q91/100),H91="discount_added",-(O91*P91*(J91-I91)/100),H91="plan_upgrade",O91*(_xlfn.XLOOKUP(J91,tbl_Plans[plan_name],tbl_Plans[monthly_price])-_xlfn.XLOOKUP(I91,tbl_Plans[plan_name],tbl_Plans[monthly_price]))*(1-Q91/100),H91="plan_downgrade",O91*(_xlfn.XLOOKUP(J91,tbl_Plans[plan_name],tbl_Plans[monthly_price])-_xlfn.XLOOKUP(I91,tbl_Plans[plan_name],tbl_Plans[monthly_price]))*(1-Q91/100))*IF(N91="Annual",1/12,1)} -> 900
A92: EVT091 | B92: SUB015 | C92: CUST015 | D92: BC Retail Networks | E92: Western Canada | F92: 45962 | G92: 45962 | H92: discount_added | I92: 0 | J92: 10 | K92: discount_percent | L92: Retention discount - customer at-risk of churning | M92: Analytics Growth | N92: Monthly | O92: 19 | P92: 95 | Q92: 10 | R92: {=_xlfn.IFS(H92="created", "New", H92="cancelled", "Churned", AND(H92="seats_change", J92 > I92), "Expansion", AND(H92="seats_change", J92 < I92), "Contraction", AND(H92="price_change", J92 > I92), "Expansion", AND(H92="price_change", J92 < I92), "Contraction", H92="plan_upgrade", "Expansion", H92="plan_downgrade", "Contraction", H92="discount_added", "Contraction")} -> Contraction | S92: {=_xlfn.IFS(H92="created",O92*P92*(1-Q92/100),H92="cancelled",-(O92*P92*(1-Q92/100)),H92="seats_change",(J92-I92)*P92*(1-Q92/100),H92="price_change",(J92-I92)*O92*(1-Q92/100),H92="discount_added",-(O92*P92*(J92-I92)/100),H92="plan_upgrade",O92*(_xlfn.XLOOKUP(J92,tbl_Plans[plan_name],tbl_Plans[monthly_price])-_xlfn.XLOOKUP(I92,tbl_Plans[plan_name],tbl_Plans[monthly_price]))*(1-Q92/100),H92="plan_downgrade",O92*(_xlfn.XLOOKUP(J92,tbl_Plans[plan_name],tbl_Plans[monthly_price])-_xlfn.XLOOKUP(I92,tbl_Plans[plan_name],tbl_Plans[monthly_price]))*(1-Q92/100))*IF(N92="Annual",1/12,1)} -> -180.5
A93: EVT092 | B93: SUB039 | C93: CUST039 | D93: Toronto Commerce Cloud | E93: Eastern Canada | F93: 45962 | G93: 45976 | H93: seats_change | I93: 32 | J93: 29 | K93: seats | L93: Restructuring - reduced team size | M93: Marketing Pro | N93: Monthly | O93: 29 | P93: 85 | Q93: 0 | R93: {=_xlfn.IFS(H93="created", "New", H93="cancelled", "Churned", AND(H93="seats_change", J93 > I93), "Expansion", AND(H93="seats_change", J93 < I93), "Contraction", AND(H93="price_change", J93 > I93), "Expansion", AND(H93="price_change", J93 < I93), "Contraction", H93="plan_upgrade", "Expansion", H93="plan_downgrade", "Contraction", H93="discount_added", "Contraction")} -> Contraction | S93: {=_xlfn.IFS(H93="created",O93*P93*(1-Q93/100),H93="cancelled",-(O93*P93*(1-Q93/100)),H93="seats_change",(J93-I93)*P93*(1-Q93/100),H93="price_change",(J93-I93)*O93*(1-Q93/100),H93="discount_added",-(O93*P93*(J93-I93)/100),H93="plan_upgrade",O93*(_xlfn.XLOOKUP(J93,tbl_Plans[plan_name],tbl_Plans[monthly_price])-_xlfn.XLOOKUP(I93,tbl_Plans[plan_name],tbl_Plans[monthly_price]))*(1-Q93/100),H93="plan_downgrade",O93*(_xlfn.XLOOKUP(J93,tbl_Plans[plan_name],tbl_Plans[monthly_price])-_xlfn.XLOOKUP(I93,tbl_Plans[plan_name],tbl_Plans[monthly_price]))*(1-Q93/100))*IF(N93="Annual",1/12,1)} -> -255
A94: EVT093 | B94: SUB047 | C94: CUST022 | D94: Toronto Tech Ventures | E94: Eastern Canada | F94: 45992 | G94: 45999 | H94: seats_change | I94: 22 | J94: 26 | K94: seats | L94: Year-end headcount increase | M94: Sales Hub | N94: Monthly | O94: 26 | P94: 110 | Q94: 0 | R94: {=_xlfn.IFS(H94="created", "New", H94="cancelled", "Churned", AND(H94="seats_change", J94 > I94), "Expansion", AND(H94="seats_change", J94 < I94), "Contraction", AND(H94="price_change", J94 > I94), "Expansion", AND(H94="price_change", J94 < I94), "Contraction", H94="plan_upgrade", "Expansion", H94="plan_downgrade", "Contraction", H94="discount_added", "Contraction")} -> Expansion | S94: {=_xlfn.IFS(H94="created",O94*P94*(1-Q94/100),H94="cancelled",-(O94*P94*(1-Q94/100)),H94="seats_change",(J94-I94)*P94*(1-Q94/100),H94="price_change",(J94-I94)*O94*(1-Q94/100),H94="discount_added",-(O94*P94*(J94-I94)/100),H94="plan_upgrade",O94*(_xlfn.XLOOKUP(J94,tbl_Plans[plan_name],tbl_Plans[monthly_price])-_xlfn.XLOOKUP(I94,tbl_Plans[plan_name],tbl_Plans[monthly_price]))*(1-Q94/100),H94="plan_downgrade",O94*(_xlfn.XLOOKUP(J94,tbl_Plans[plan_name],tbl_Plans[monthly_price])-_xlfn.XLOOKUP(I94,tbl_Plans[plan_name],tbl_Plans[monthly_price]))*(1-Q94/100))*IF(N94="Annual",1/12,1)} -> 440
A95: EVT094 | B95: SUB050 | C95: CUST007 | D95: Ontario Manufacturing Tech | E95: Eastern Canada | F95: 45992 | G95: 46006 | H95: discount_added | I95: 0 | J95: 12 | K95: discount_percent | L95: Retention discount - at-risk account escalated | M95: Analytics Starter | N95: Monthly | O95: 15 | P95: 45 | Q95: 12 | R95: {=_xlfn.IFS(H95="created", "New", H95="cancelled", "Churned", AND(H95="seats_change", J95 > I95), "Expansion", AND(H95="seats_change", J95 < I95), "Contraction", AND(H95="price_change", J95 > I95), "Expansion", AND(H95="price_change", J95 < I95), "Contraction", H95="plan_upgrade", "Expansion", H95="plan_downgrade", "Contraction", H95="discount_added", "Contraction")} -> Contraction | S95: {=_xlfn.IFS(H95="created",O95*P95*(1-Q95/100),H95="cancelled",-(O95*P95*(1-Q95/100)),H95="seats_change",(J95-I95)*P95*(1-Q95/100),H95="price_change",(J95-I95)*O95*(1-Q95/100),H95="discount_added",-(O95*P95*(J95-I95)/100),H95="plan_upgrade",O95*(_xlfn.XLOOKUP(J95,tbl_Plans[plan_name],tbl_Plans[monthly_price])-_xlfn.XLOOKUP(I95,tbl_Plans[plan_name],tbl_Plans[monthly_price]))*(1-Q95/100),H95="plan_downgrade",O95*(_xlfn.XLOOKUP(J95,tbl_Plans[plan_name],tbl_Plans[monthly_price])-_xlfn.XLOOKUP(I95,tbl_Plans[plan_name],tbl_Plans[monthly_price]))*(1-Q95/100))*IF(N95="Annual",1/12,1)} -> -81
A96: EVT095 | B96: SUB015 | C96: CUST015 | D96: BC Retail Networks | E96: Western Canada | F96: 45992 | G96: 46021 | H96: cancelled | I96: active | J96: churned | K96: status | L96: Switched to competitor | M96: Analytics Growth | N96: Monthly | O96: 19 | P96: 95 | Q96: 10 | R96: {=_xlfn.IFS(H96="created", "New", H96="cancelled", "Churned", AND(H96="seats_change", J96 > I96), "Expansion", AND(H96="seats_change", J96 < I96), "Contraction", AND(H96="price_change", J96 > I96), "Expansion", AND(H96="price_change", J96 < I96), "Contraction", H96="plan_upgrade", "Expansion", H96="plan_downgrade", "Contraction", H96="discount_added", "Contraction")} -> Churned | S96: {=_xlfn.IFS(H96="created",O96*P96*(1-Q96/100),H96="cancelled",-(O96*P96*(1-Q96/100)),H96="seats_change",(J96-I96)*P96*(1-Q96/100),H96="price_change",(J96-I96)*O96*(1-Q96/100),H96="discount_added",-(O96*P96*(J96-I96)/100),H96="plan_upgrade",O96*(_xlfn.XLOOKUP(J96,tbl_Plans[plan_name],tbl_Plans[monthly_price])-_xlfn.XLOOKUP(I96,tbl_Plans[plan_name],tbl_Plans[monthly_price]))*(1-Q96/100),H96="plan_downgrade",O96*(_xlfn.XLOOKUP(J96,tbl_Plans[plan_name],tbl_Plans[monthly_price])-_xlfn.XLOOKUP(I96,tbl_Plans[plan_name],tbl_Plans[monthly_price]))*(1-Q96/100))*IF(N96="Annual",1/12,1)} -> -1624.5
A97: EVT096 | B97: SUB040 | C97: CUST040 | D97: BC Education Innovations | E97: Western Canada | F97: 46023 | G97: 46048 | H97: created | M97: Analytics Growth | N97: Monthly | O97: 18 | P97: 95 | Q97: 0 | R97: {=_xlfn.IFS(H97="created", "New", H97="cancelled", "Churned", AND(H97="seats_change", J97 > I97), "Expansion", AND(H97="seats_change", J97 < I97), "Contraction", AND(H97="price_change", J97 > I97), "Expansion", AND(H97="price_change", J97 < I97), "Contraction", H97="plan_upgrade", "Expansion", H97="plan_downgrade", "Contraction", H97="discount_added", "Contraction")} -> New | S97: {=_xlfn.IFS(H97="created",O97*P97*(1-Q97/100),H97="cancelled",-(O97*P97*(1-Q97/100)),H97="seats_change",(J97-I97)*P97*(1-Q97/100),H97="price_change",(J97-I97)*O97*(1-Q97/100),H97="discount_added",-(O97*P97*(J97-I97)/100),H97="plan_upgrade",O97*(_xlfn.XLOOKUP(J97,tbl_Plans[plan_name],tbl_Plans[monthly_price])-_xlfn.XLOOKUP(I97,tbl_Plans[plan_name],tbl_Plans[monthly_price]))*(1-Q97/100),H97="plan_downgrade",O97*(_xlfn.XLOOKUP(J97,tbl_Plans[plan_name],tbl_Plans[monthly_price])-_xlfn.XLOOKUP(I97,tbl_Plans[plan_name],tbl_Plans[monthly_price]))*(1-Q97/100))*IF(N97="Annual",1/12,1)} -> 1710
A98: EVT097 | B98: SUB050 | C98: CUST007 | D98: Ontario Manufacturing Tech | E98: Eastern Canada | F98: 46054 | G98: 46073 | H98: cancelled | I98: active | J98: churned | K98: status | L98: Poor support | M98: Analytics Starter | N98: Monthly | O98: 15 | P98: 45 | Q98: 12 | R98: {=_xlfn.IFS(H98="created", "New", H98="cancelled", "Churned", AND(H98="seats_change", J98 > I98), "Expansion", AND(H98="seats_change", J98 < I98), "Contraction", AND(H98="price_change", J98 > I98), "Expansion", AND(H98="price_change", J98 < I98), "Contraction", H98="plan_upgrade", "Expansion", H98="plan_downgrade", "Contraction", H98="discount_added", "Contraction")} -> Churned | S98: {=_xlfn.IFS(H98="created",O98*P98*(1-Q98/100),H98="cancelled",-(O98*P98*(1-Q98/100)),H98="seats_change",(J98-I98)*P98*(1-Q98/100),H98="price_change",(J98-I98)*O98*(1-Q98/100),H98="discount_added",-(O98*P98*(J98-I98)/100),H98="plan_upgrade",O98*(_xlfn.XLOOKUP(J98,tbl_Plans[plan_name],tbl_Plans[monthly_price])-_xlfn.XLOOKUP(I98,tbl_Plans[plan_name],tbl_Plans[monthly_price]))*(1-Q98/100),H98="plan_downgrade",O98*(_xlfn.XLOOKUP(J98,tbl_Plans[plan_name],tbl_Plans[monthly_price])-_xlfn.XLOOKUP(I98,tbl_Plans[plan_name],tbl_Plans[monthly_price]))*(1-Q98/100))*IF(N98="Annual",1/12,1)} -> -594

Sheet Waterfall
A1: MRR Waterfall - January 2024 to February 2026
A2: Month | B2: Opening | C2: New | D2: Expansion | E2: Contraction | F2: Churned | G2: Net | H2: Closing
A3: 45292 | B3: =0 -> 0 | C3: =SUMIFS(Engine!$S$2:$S$98, Engine!$R$2:$R$98, "New", Engine!$F$2:$F$98, Waterfall!A3) -> 5800 | D3: =SUMIFS(Engine!$S$2:$S$98, Engine!$R$2:$R$98, "Expansion", Engine!$F$2:$F$98, Waterfall!A3) -> 0 | E3: =SUMIFS(Engine!$S$2:$S$98, Engine!$R$2:$R$98, "Contraction", Engine!$F$2:$F$98, Waterfall!A3) -> 0 | F3: =SUMIFS(Engine!$S$2:$S$98, Engine!$R$2:$R$98, "Churned", Engine!$F$2:$F$98, Waterfall!A3) -> 0 | G3: =C3+D3+E3+F3 -> 5800 | H3: =B3+G3 -> 5800
A4: 45323 | B4: =H3 -> 5800 | C4: =SUMIFS(Engine!$S$2:$S$98, Engine!$R$2:$R$98, "New", Engine!$F$2:$F$98, Waterfall!A4) -> 8615 | D4: =SUMIFS(Engine!$S$2:$S$98, Engine!$R$2:$R$98, "Expansion", Engine!$F$2:$F$98, Waterfall!A4) -> 0 | E4: =SUMIFS(Engine!$S$2:$S$98, Engine!$R$2:$R$98, "Contraction", Engine!$F$2:$F$98, Waterfall!A4) -> 0 | F4: =SUMIFS(Engine!$S$2:$S$98, Engine!$R$2:$R$98, "Churned", Engine!$F$2:$F$98, Waterfall!A4) -> 0 | G4: =C4+D4+E4+F4 -> 8615 | H4: =B4+G4 -> 14415
A5: 45352 | B5: =H4 -> 14415 | C5: =SUMIFS(Engine!$S$2:$S$98, Engine!$R$2:$R$98, "New", Engine!$F$2:$F$98, Waterfall!A5) -> 6075 | D5: =SUMIFS(Engine!$S$2:$S$98, Engine!$R$2:$R$98, "Expansion", Engine!$F$2:$F$98, Waterfall!A5) -> 0 | E5: =SUMIFS(Engine!$S$2:$S$98, Engine!$R$2:$R$98, "Contraction", Engine!$F$2:$F$98, Waterfall!A5) -> 0 | F5: =SUMIFS(Engine!$S$2:$S$98, Engine!$R$2:$R$98, "Churned", Engine!$F$2:$F$98, Waterfall!A5) -> 0 | G5: =C5+D5+E5+F5 -> 6075 | H5: =B5+G5 -> 20490
A6: 45383 | B6: =H5 -> 20490 | C6: =SUMIFS(Engine!$S$2:$S$98, Engine!$R$2:$R$98, "New", Engine!$F$2:$F$98, Waterfall!A6) -> 9444 | D6: =SUMIFS(Engine!$S$2:$S$98, Engine!$R$2:$R$98, "Expansion", Engine!$F$2:$F$98, Waterfall!A6) -> 0 | E6: =SUMIFS(Engine!$S$2:$S$98, Engine!$R$2:$R$98, "Contraction", Engine!$F$2:$F$98, Waterfall!A6) -> 0 | F6: =SUMIFS(Engine!$S$2:$S$98, Engine!$R$2:$R$98, "Churned", Engine!$F$2:$F$98, Waterfall!A6) -> 0 | G6: =C6+D6+E6+F6 -> 9444 | H6: =B6+G6 -> 29934
A7: 45413 | B7: =H6 -> 29934 | C7: =SUMIFS(Engine!$S$2:$S$98, Engine!$R$2:$R$98, "New", Engine!$F$2:$F$98, Waterfall!A7) -> 2565 | D7: =SUMIFS(Engine!$S$2:$S$98, Engine!$R$2:$R$98, "Expansion", Engine!$F$2:$F$98, Waterfall!A7) -> 0 | E7: =SUMIFS(Engine!$S$2:$S$98, Engine!$R$2:$R$98, "Contraction", Engine!$F$2:$F$98, Waterfall!A7) -> 0 | F7: =SUMIFS(Engine!$S$2:$S$98, Engine!$R$2:$R$98, "Churned", Engine!$F$2:$F$98, Waterfall!A7) -> 0 | G7: =C7+D7+E7+F7 -> 2565 | H7: =B7+G7 -> 32499
A8: 45444 | B8: =H7 -> 32499 | C8: =SUMIFS(Engine!$S$2:$S$98, Engine!$R$2:$R$98, "New", Engine!$F$2:$F$98, Waterfall!A8) -> 3490 | D8: =SUMIFS(Engine!$S$2:$S$98, Engine!$R$2:$R$98, "Expansion", Engine!$F$2:$F$98, Waterfall!A8) -> 0 | E8: =SUMIFS(Engine!$S$2:$S$98, Engine!$R$2:$R$98, "Contraction", Engine!$F$2:$F$98, Waterfall!A8) -> 0 | F8: =SUMIFS(Engine!$S$2:$S$98, Engine!$R$2:$R$98, "Churned", Engine!$F$2:$F$98, Waterfall!A8) -> 0 | G8: =C8+D8+E8+F8 -> 3490 | H8: =B8+G8 -> 35989
A9: 45474 | B9: =H8 -> 35989 | C9: =SUMIFS(Engine!$S$2:$S$98, Engine!$R$2:$R$98, "New", Engine!$F$2:$F$98, Waterfall!A9) -> 9364.5 | D9: =SUMIFS(Engine!$S$2:$S$98, Engine!$R$2:$R$98, "Expansion", Engine!$F$2:$F$98, Waterfall!A9) -> 0 | E9: =SUMIFS(Engine!$S$2:$S$98, Engine!$R$2:$R$98, "Contraction", Engine!$F$2:$F$98, Waterfall!A9) -> 0 | F9: =SUMIFS(Engine!$S$2:$S$98, Engine!$R$2:$R$98, "Churned", Engine!$F$2:$F$98, Waterfall!A9) -> 0 | G9: =C9+D9+E9+F9 -> 9364.5 | H9: =B9+G9 -> 45353.5
A10: 45505 | B10: =H9 -> 45353.5 | C10: =SUMIFS(Engine!$S$2:$S$98, Engine!$R$2:$R$98, "New", Engine!$F$2:$F$98, Waterfall!A10) -> 6840 | D10: =SUMIFS(Engine!$S$2:$S$98, Engine!$R$2:$R$98, "Expansion", Engine!$F$2:$F$98, Waterfall!A10) -> 0 | E10: =SUMIFS(Engine!$S$2:$S$98, Engine!$R$2:$R$98, "Contraction", Engine!$F$2:$F$98, Waterfall!A10) -> 0 | F10: =SUMIFS(Engine!$S$2:$S$98, Engine!$R$2:$R$98, "Churned", Engine!$F$2:$F$98, Waterfall!A10) -> -1900 | G10: =C10+D10+E10+F10 -> 4940 | H10: =B10+G10 -> 50293.5
A11: 45536 | B11: =H10 -> 50293.5 | C11: =SUMIFS(Engine!$S$2:$S$98, Engine!$R$2:$R$98, "New", Engine!$F$2:$F$98, Waterfall!A11) -> 13415 | D11: =SUMIFS(Engine!$S$2:$S$98, Engine!$R$2:$R$98, "Expansion", Engine!$F$2:$F$98, Waterfall!A11) -> 0 | E11: =SUMIFS(Engine!$S$2:$S$98, Engine!$R$2:$R$98, "Contraction", Engine!$F$2:$F$98, Waterfall!A11) -> 0 | F11: =SUMIFS(Engine!$S$2:$S$98, Engine!$R$2:$R$98, "Churned", Engine!$F$2:$F$98, Waterfall!A11) -> 0 | G11: =C11+D11+E11+F11 -> 13415 | H11: =B11+G11 -> 63708.5
A12: 45566 | B12: =H11 -> 63708.5 | C12: =SUMIFS(Engine!$S$2:$S$98, Engine!$R$2:$R$98, "New", Engine!$F$2:$F$98, Waterfall!A12) -> 10130 | D12: =SUMIFS(Engine!$S$2:$S$98, Engine!$R$2:$R$98, "Expansion", Engine!$F$2:$F$98, Waterfall!A12) -> 0 | E12: =SUMIFS(Engine!$S$2:$S$98, Engine!$R$2:$R$98, "Contraction", Engine!$F$2:$F$98, Waterfall!A12) -> 0 | F12: =SUMIFS(Engine!$S$2:$S$98, Engine!$R$2:$R$98, "Churned", Engine!$F$2:$F$98, Waterfall!A12) -> 0 | G12: =C12+D12+E12+F12 -> 10130 | H12: =B12+G12 -> 73838.5
A13: 45597 | B13: =H12 -> 73838.5 | C13: =SUMIFS(Engine!$S$2:$S$98, Engine!$R$2:$R$98, "New", Engine!$F$2:$F$98, Waterfall!A13) -> 4955 | D13: =SUMIFS(Engine!$S$2:$S$98, Engine!$R$2:$R$98, "Expansion", Engine!$F$2:$F$98, Waterfall!A13) -> 0 | E13: =SUMIFS(Engine!$S$2:$S$98, Engine!$R$2:$R$98, "Contraction", Engine!$F$2:$F$98, Waterfall!A13) -> 0 | F13: =SUMIFS(Engine!$S$2:$S$98, Engine!$R$2:$R$98, "Churned", Engine!$F$2:$F$98, Waterfall!A13) -> -495 | G13: =C13+D13+E13+F13 -> 4460 | H13: =B13+G13 -> 78298.5
A14: 45627 | B14: =H13 -> 78298.5 | C14: =SUMIFS(Engine!$S$2:$S$98, Engine!$R$2:$R$98, "New", Engine!$F$2:$F$98, Waterfall!A14) -> 14915 | D14: =SUMIFS(Engine!$S$2:$S$98, Engine!$R$2:$R$98, "Expansion", Engine!$F$2:$F$98, Waterfall!A14) -> 0 | E14: =SUMIFS(Engine!$S$2:$S$98, Engine!$R$2:$R$98, "Contraction", Engine!$F$2:$F$98, Waterfall!A14) -> 0 | F14: =SUMIFS(Engine!$S$2:$S$98, Engine!$R$2:$R$98, "Churned", Engine!$F$2:$F$98, Waterfall!A14) -> -2090 | G14: =C14+D14+E14+F14 -> 12825 | H14: =B14+G14 -> 91123.5
A15: 45658 | B15: =H14 -> 91123.5 | C15: =SUMIFS(Engine!$S$2:$S$98, Engine!$R$2:$R$98, "New", Engine!$F$2:$F$98, Waterfall!A15) -> 9940.5 | D15: =SUMIFS(Engine!$S$2:$S$98, Engine!$R$2:$R$98, "Expansion", Engine!$F$2:$F$98, Waterfall!A15) -> 140 | E15: =SUMIFS(Engine!$S$2:$S$98, Engine!$R$2:$R$98, "Contraction", Engine!$F$2:$F$98, Waterfall!A15) -> 0 | F15: =SUMIFS(Engine!$S$2:$S$98, Engine!$R$2:$R$98, "Churned", Engine!$F$2:$F$98, Waterfall!A15) -> -450 | G15: =C15+D15+E15+F15 -> 9630.5 | H15: =B15+G15 -> 100754
... A28: 46054 | B28: =H27 -> 152628.5 | C28: =SUMIFS(Engine!$S$2:$S$98, Engine!$R$2:$R$98, "New", Engine!$F$2:$F$98, Waterfall!A28) -> 0 | D28: =SUMIFS(Engine!$S$2:$S$98, Engine!$R$2:$R$98, "Expansion", Engine!$F$2:$F$98, Waterfall!A28) -> 0 | E28: =SUMIFS(Engine!$S$2:$S$98, Engine!$R$2:$R$98, "Contraction", Engine!$F$2:$F$98, Waterfall!A28) -> 0 | F28: =SUMIFS(Engine!$S$2:$S$98, Engine!$R$2:$R$98, "Churned", Engine!$F$2:$F$98, Waterfall!A28) -> -594 | G28: =C28+D28+E28+F28 -> -594 | H28: =B28+G28 -> 152034.5
A30: Waterfall Closing MRR: | B30: =H28 -> 152034.5
A31: Snapshot MRR: | B31: =SUM('Raw Snapshot'!H2:H52) -> 144185.5
A32: Reconciliation Gap: | B32: =B30-B31 -> 7849

Sheet Growth
A1: Growth Analysis — January 2024 to February 2026
A3: 1. MRR & ARR
A4: Month | B4: =Waterfall!A3 -> 45292 | C4: =Waterfall!A4 -> 45323 | D4: =Waterfall!A5 -> 45352 | E4: =Waterfall!A6 -> 45383 | F4: =Waterfall!A7 -> 45413 | G4: =Waterfall!A8 -> 45444 | H4: =Waterfall!A9 -> 45474 | I4: =Waterfall!A10 -> 45505 | J4: =Waterfall!A11 -> 45536 | K4: =Waterfall!A12 -> 45566 | L4: =Waterfall!A13 -> 45597 | M4: =Waterfall!A14 -> 45627 | N4: =Waterfall!A15 -> 45658 | O4: =Waterfall!A16 -> 45689 | P4: =Waterfall!A17 -> 45717 | Q4: =Waterfall!A18 -> 45748 | R4: =Waterfall!A19 -> 45778 | S4: =Waterfall!A20 -> 45809 | T4: =Waterfall!A21 -> 45839 | U4: =Waterfall!A22 -> 45870 | V4: =Waterfall!A23 -> 45901 | W4: =Waterfall!A24 -> 45931 | X4: =Waterfall!A25 -> 45962 | Y4: =Waterfall!A26 -> 45992 | Z4: =Waterfall!A27 -> 46023 | AA4: =Waterfall!A28 -> 46054
A5: Closing MRR | B5: =Waterfall!H3 -> 5800 | C5: =Waterfall!H4 -> 14415 | D5: =Waterfall!H5 -> 20490 | E5: =Waterfall!H6 -> 29934 | F5: =Waterfall!H7 -> 32499 | G5: =Waterfall!H8 -> 35989 | H5: =Waterfall!H9 -> 45353.5 | I5: =Waterfall!H10 -> 50293.5 | J5: =Waterfall!H11 -> 63708.5 | K5: =Waterfall!H12 -> 73838.5 | L5: =Waterfall!H13 -> 78298.5 | M5: =Waterfall!H14 -> 91123.5 | N5: =Waterfall!H15 -> 100754 | O5: =Waterfall!H16 -> 108159 | P5: =Waterfall!H17 -> 126539.5 | Q5: =Waterfall!H18 -> 133074.5 | R5: =Waterfall!H19 -> 143089.5 | S5: =Waterfall!H20 -> 152114.5 | T5: =Waterfall!H21 -> 151014.5 | U5: =Waterfall!H22 -> 148584.5 | V5: =Waterfall!H23 -> 150359.5 | W5: =Waterfall!H24 -> 152619.5 | X5: =Waterfall!H25 -> 152184 | Y5: =Waterfall!H26 -> 150918.5 | Z5: =Waterfall!H27 -> 152628.5 | AA5: =Waterfall!H28 -> 152034.5
A6: ARR | B6: =B5*12 -> 69600 | C6: =C5*12 -> 172980 | D6: =D5*12 -> 245880 | E6: =E5*12 -> 359208 | F6: =F5*12 -> 389988 | G6: =G5*12 -> 431868 | H6: =H5*12 -> 544242 | I6: =I5*12 -> 603522 | ... AA6: =AA5*12 -> 1824414
A7: Net New MRR | B7: =Waterfall!G3 -> 5800 | C7: =Waterfall!G4 -> 8615 | D7: =Waterfall!G5 -> 6075 | E7: =Waterfall!G6 -> 9444 | F7: =Waterfall!G7 -> 2565 | G7: =Waterfall!G8 -> 3490 | H7: =Waterfall!G9 -> 9364.5 | I7: =Waterfall!G10 -> 4940 | J7: =Waterfall!G11 -> 13415 | K7: =Waterfall!G12 -> 10130 | L7: =Waterfall!G13 -> 4460 | M7: =Waterfall!G14 -> 12825 | N7: =Waterfall!G15 -> 9630.5 | O7: =Waterfall!G16 -> 7405 | P7: =Waterfall!G17 -> 18380.5 | Q7: =Waterfall!G18 -> 6535 | R7: =Waterfall!G19 -> 10015 | S7: =Waterfall!G20 -> 9025 | T7: =Waterfall!G21 -> -1100 | U7: =Waterfall!G22 -> -2430 | V7: =Waterfall!G23 -> 1775 | W7: =Waterfall!G24 -> 2260 | X7: =Waterfall!G25 -> -435.5 | Y7: =Waterfall!G26 -> -1265.5 | Z7: =Waterfall!G27 -> 1710 | AA7: =Waterfall!G28 -> -594
A8: Cumulative Net New MRR | B8: =B7 -> 5800 | C8: =B8+C7 -> 14415 | D8: =C8+D7 -> 20490 | E8: =D8+E7 -> 29934 | F8: =E8+F7 -> 32499 | G8: =F8+G7 -> 35989 | H8: =G8+H7 -> 45353.5 | I8: =H8+I7 -> 50293.5 | J8: =I8+J7 -> 63708.5 | ... AA8: =Z8+AA7 -> 152034.5
A10: 2. Growth Rates
A11: MoM Growth % | C11: =IFERROR(C7/B5,"") -> 1.4853448 | D11: =IFERROR(D7/C5,"") -> 0.421436 | E11: =IFERROR(E7/D5,"") -> 0.46090776 | F11: =IFERROR(F7/E5,"") -> 0.085688515 | G11: =IFERROR(G7/F5,"") -> 0.10738792 | H11: =IFERROR(H7/G5,"") -> 0.26020451 | I11: =IFERROR(I7/H5,"") -> 0.10892213 | J11: =IFERROR(J7/I5,"") -> 0.26673427 | ... AA11: =IFERROR(AA7/Z5,"") -> -0.0038918026
A12: YoY Growth % | N12: =IFERROR((N5-B5)/B5,"") -> 16.371379 | O12: =IFERROR((O5-C5)/C5,"") -> 6.5032258 | P12: =IFERROR((P5-D5)/D5,"") -> 5.1756711 | Q12: =IFERROR((Q5-E5)/E5,"") -> 3.445597 | R12: =IFERROR((R5-F5)/F5,"") -> 3.4028893 | S12: =IFERROR((S5-G5)/G5,"") -> 3.2266943 | T12: =IFERROR((T5-H5)/H5,"") -> 2.329721 | U12: =IFERROR((U5-I5)/I5,"") -> 1.954348 | ... AA12: =IFERROR((AA5-O5)/O5,"") -> 0.40565741
A14: CMGR (6-month) | H14: =IFERROR((H5/B5)^(1/6)-1,"") -> 0.40884691 | I14: =IFERROR((I5/C5)^(1/6)-1,"") -> 0.23154287 | J14: =IFERROR((J5/D5)^(1/6)-1,"") -> 0.20811767 | K14: =IFERROR((K5/E5)^(1/6)-1,"") -> 0.16239309 | L14: =IFERROR((L5/F5)^(1/6)-1,"") -> 0.15783651 | M14: =IFERROR((M5/G5)^(1/6)-1,"") -> 0.16746383 | N14: =IFERROR((N5/H5)^(1/6)-1,"") -> 0.14228704 | O14: =IFERROR((O5/I5)^(1/6)-1,"") -> 0.13612243 | ... AA14: =IFERROR((AA5/U5)^(1/6)-1,"") -> 0.0038329351
A15: CMGR (12-month) | N15: =IFERROR((N5/B5)^(1/12)-1,"") -> 0.26858486 | O15: =IFERROR((O5/C5)^(1/12)-1,"") -> 0.18287086 | P15: =IFERROR((P5/D5)^(1/12)-1,"") -> 0.16383214 | Q15: =IFERROR((Q5/E5)^(1/12)-1,"") -> 0.13238517 | R15: =IFERROR((R5/F5)^(1/12)-1,"") -> 0.13147461 | S15: =IFERROR((S5/G5)^(1/12)-1,"") -> 0.1276303 | T15: =IFERROR((T5/H5)^(1/12)-1,"") -> 0.10543697 | U15: =IFERROR((U5/I5)^(1/12)-1,"") -> 0.094473214 | ... AA15: =IFERROR((AA5/O5)^(1/12)-1,"") -> 0.028781843
A16: Trailing 3-month avg MoM | E16: =IFERROR(AVERAGE(C11:E11),"") -> 0.78922953 | F16: =IFERROR(AVERAGE(D11:F11),"") -> 0.32267743 | G16: =IFERROR(AVERAGE(E11:G11),"") -> 0.21799473 | H16: =IFERROR(AVERAGE(F11:H11),"") -> 0.15109365 | I16: =IFERROR(AVERAGE(G11:I11),"") -> 0.15883819 | J16: =IFERROR(AVERAGE(H11:J11),"") -> 0.21195364 | K16: =IFERROR(AVERAGE(I11:K11),"") -> 0.17822062 | L16: =IFERROR(AVERAGE(J11:L11),"") -> 0.16204728 | ... AA16: =IFERROR(AVERAGE(Y11:AA11),"") -> -0.00029225848
A18: 3. Growth Quality
A19: Gains (New + Expansion) | B19: =Waterfall!C3+Waterfall!D3 -> 5800 | C19: =Waterfall!C4+Waterfall!D4 -> 8615 | D19: =Waterfall!C5+Waterfall!D5 -> 6075 | E19: =Waterfall!C6+Waterfall!D6 -> 9444 | F19: =Waterfall!C7+Waterfall!D7 -> 2565 | G19: =Waterfall!C8+Waterfall!D8 -> 3490 | H19: =Waterfall!C9+Waterfall!D9 -> 9364.5 | I19: =Waterfall!C10+Waterfall!D10 -> 6840 | J19: =Waterfall!C11+Waterfall!D11 -> 13415 | K19: =Waterfall!C12+Waterfall!D12 -> 10130 | L19: =Waterfall!C13+Waterfall!D13 -> 4955 | M19: =Waterfall!C14+Waterfall!D14 -> 14915 | N19: =Waterfall!C15+Waterfall!D15 -> 10080.5 | O19: =Waterfall!C16+Waterfall!D16 -> 7405 | P19: =Waterfall!C17+Waterfall!D17 -> 19390 | Q19: =Waterfall!C18+Waterfall!D18 -> 6535 | R19: =Waterfall!C19+Waterfall!D19 -> 12390 | S19: =Waterfall!C20+Waterfall!D20 -> 10330 | T19: =Waterfall!C21+Waterfall!D21 -> 660 | U19: =Waterfall!C22+Waterfall!D22 -> 2960 | V19: =Waterfall!C23+Waterfall!D23 -> 1900 | W19: =Waterfall!C24+Waterfall!D24 -> 2260 | X19: =Waterfall!C25+Waterfall!D25 -> 0 | Y19: =Waterfall!C26+Waterfall!D26 -> 440 | Z19: =Waterfall!C27+Waterfall!D27 -> 1710 | AA19: =Waterfall!C28+Waterfall!D28 -> 0
A20: Losses (Contraction + Churned) | B20: =ABS(Waterfall!E3)+ABS(Waterfall!F3) -> 0 | C20: =ABS(Waterfall!E4)+ABS(Waterfall!F4) -> 0 | D20: =ABS(Waterfall!E5)+ABS(Waterfall!F5) -> 0 | E20: =ABS(Waterfall!E6)+ABS(Waterfall!F6) -> 0 | F20: =ABS(Waterfall!E7)+ABS(Waterfall!F7) -> 0 | G20: =ABS(Waterfall!E8)+ABS(Waterfall!F8) -> 0 | H20: =ABS(Waterfall!E9)+ABS(Waterfall!F9) -> 0 | I20: =ABS(Waterfall!E10)+ABS(Waterfall!F10) -> 1900 | J20: =ABS(Waterfall!E11)+ABS(Waterfall!F11) -> 0 | K20: =ABS(Waterfall!E12)+ABS(Waterfall!F12) -> 0 | L20: =ABS(Waterfall!E13)+ABS(Waterfall!F13) -> 495 | M20: =ABS(Waterfall!E14)+ABS(Waterfall!F14) -> 2090 | N20: =ABS(Waterfall!E15)+ABS(Waterfall!F15) -> 450 | O20: =ABS(Waterfall!E16)+ABS(Waterfall!F16) -> 0 | P20: =ABS(Waterfall!E17)+ABS(Waterfall!F17) -> 1009.5 | Q20: =ABS(Waterfall!E18)+ABS(Waterfall!F18) -> 0 | R20: =ABS(Waterfall!E19)+ABS(Waterfall!F19) -> 2375 | S20: =ABS(Waterfall!E20)+ABS(Waterfall!F20) -> 1305 | T20: =ABS(Waterfall!E21)+ABS(Waterfall!F21) -> 1760 | U20: =ABS(Waterfall!E22)+ABS(Waterfall!F22) -> 5390 | V20: =ABS(Waterfall!E23)+ABS(Waterfall!F23) -> 125 | W20: =ABS(Waterfall!E24)+ABS(Waterfall!F24) -> 0 | X20: =ABS(Waterfall!E25)+ABS(Waterfall!F25) -> 435.5 | Y20: =ABS(Waterfall!E26)+ABS(Waterfall!F26) -> 1705.5 | Z20: =ABS(Waterfall!E27)+ABS(Waterfall!F27) -> 0 | AA20: =ABS(Waterfall!E28)+ABS(Waterfall!F28) -> 594
A21: Quick Ratio | B21: =IFERROR(B19/B20,"∞") -> ∞ | C21: =IFERROR(C19/C20,"∞") -> ∞ | D21: =IFERROR(D19/D20,"∞") -> ∞ | E21: =IFERROR(E19/E20,"∞") -> ∞ | F21: =IFERROR(F19/F20,"∞") -> ∞ | G21: =IFERROR(G19/G20,"∞") -> ∞ | H21: =IFERROR(H19/H20,"∞") -> ∞ | I21: =IFERROR(I19/I20,"∞") -> 3.6 | ... AA21: =IFERROR(AA19/AA20,"∞") -> 0
A23: New as % of gains | B23: =IFERROR(Waterfall!C3/B19,"") -> 1 | C23: =IFERROR(Waterfall!C4/C19,"") -> 1 | D23: =IFERROR(Waterfall!C5/D19,"") -> 1 | E23: =IFERROR(Waterfall!C6/E19,"") -> 1 | F23: =IFERROR(Waterfall!C7/F19,"") -> 1 | G23: =IFERROR(Waterfall!C8/G19,"") -> 1 | H23: =IFERROR(Waterfall!C9/H19,"") -> 1 | I23: =IFERROR(Waterfall!C10/I19,"") -> 1 | J23: =IFERROR(Waterfall!C11/J19,"") -> 1 | K23: =IFERROR(Waterfall!C12/K19,"") -> 1 | L23: =IFERROR(Waterfall!C13/L19,"") -> 1 | M23: =IFERROR(Waterfall!C14/M19,"") -> 1 | N23: =IFERROR(Waterfall!C15/N19,"") -> 0.9861118 | O23: =IFERROR(Waterfall!C16/O19,"") -> 1 | P23: =IFERROR(Waterfall!C17/P19,"") -> 1 | Q23: =IFERROR(Waterfall!C18/Q19,"") -> 0.88446825 | R23: =IFERROR(Waterfall!C19/R19,"") -> 0.97336562 | S23: =IFERROR(Waterfall!C20/S19,"") -> 0.83543078 | T23: =IFERROR(Waterfall!C21/T19,"") -> 0 | U23: =IFERROR(Waterfall!C22/U19,"") -> 0 | V23: =IFERROR(Waterfall!C23/V19,"") -> 0 | W23: =IFERROR(Waterfall!C24/W19,"") -> 0.41371681 | X23: =IFERROR(Waterfall!C25/X19,"") | Y23: =IFERROR(Waterfall!C26/Y19,"") -> 0 | Z23: =IFERROR(Waterfall!C27/Z19,"") -> 1 | AA23: =IFERROR(Waterfall!C28/AA19,"")
A24: Expansion as % of gains | B24: =IFERROR(Waterfall!D3/B19,"") -> 0 | C24: =IFERROR(Waterfall!D4/C19,"") -> 0 | D24: =IFERROR(Waterfall!D5/D19,"") -> 0 | E24: =IFERROR(Waterfall!D6/E19,"") -> 0 | F24: =IFERROR(Waterfall!D7/F19,"") -> 0 | G24: =IFERROR(Waterfall!D8/G19,"") -> 0 | H24: =IFERROR(Waterfall!D9/H19,"") -> 0 | I24: =IFERROR(Waterfall!D10/I19,"") -> 0 | J24: =IFERROR(Waterfall!D11/J19,"") -> 0 | K24: =IFERROR(Waterfall!D12/K19,"") -> 0 | L24: =IFERROR(Waterfall!D13/L19,"") -> 0 | M24: =IFERROR(Waterfall!D14/M19,"") -> 0 | N24: =IFERROR(Waterfall!D15/N19,"") -> 0.0138882 | O24: =IFERROR(Waterfall!D16/O19,"") -> 0 | P24: =IFERROR(Waterfall!D17/P19,"") -> 0 | Q24: =IFERROR(Waterfall!D18/Q19,"") -> 0.11553175 | R24: =IFERROR(Waterfall!D19/R19,"") -> 0.026634383 | S24: =IFERROR(Waterfall!D20/S19,"") -> 0.16456922 | T24: =IFERROR(Waterfall!D21/T19,"") -> 1 | U24: =IFERROR(Waterfall!D22/U19,"") -> 1 | V24: =IFERROR(Waterfall!D23/V19,"") -> 1 | W24: =IFERROR(Waterfall!D24/W19,"") -> 0.58628319 | X24: =IFERROR(Waterfall!D25/X19,"") | Y24: =IFERROR(Waterfall!D26/Y19,"") -> 1 | Z24: =IFERROR(Waterfall!D27/Z19,"") -> 0 | AA24: =IFERROR(Waterfall!D28/AA19,"")
A27: 4. What the Numbers Say
A28: The Growth Story
A29: iDynamics grew from $0 to $152K MRR in 26 months, but the trajectory breaks into two distinct chapters. The first 12 months were explosive: the 6-month CMGR hit 40.9% in Jul 2024, and the 12-month CMGR stood at 26.9% by Jan 2025, reflecting a business that more than doubled every quarter in its early life. Growth was lumpy rather than steady — the best single months were Sep 2024 ($13.4K net new) and Mar 2025 ($18.4K net new), while May 2024 contributed just $2.6K. From mid-2025 onward, the compounding engine stalled: the 6-month CMGR collapsed from 8.9% in Jun 2025 to 0.4% by Feb 2026, and the 12-month CMGR fell from 26.9% to 2.9% over the same window. The business didn't crash — it plateaued, hovering between $148K and $153K for the final eight months.
A33: The H2 2025 Problem
A34: Something broke in Jul 2025. Net new MRR turned negative for the first time at –$1,100, then worsened to –$2,430 in Aug 2025. The Quick Ratio tells the story: it plunged to 0.4x in Jul and 0.5x in Aug, meaning the business lost more than twice what it gained. New customer acquisition fell to zero in both months — gains came entirely from expansion ($660 and $2,960 respectively), which couldn't offset churn of $1,760 and combined losses of $5,390 in Aug. The Sep–Dec 2025 period partially recovered, but erratically: Quick Ratio swung from 15.2x (Sep) to 0.0x (Nov, where gains were literally zero — no new customers and no expansion), back to ∞ in Jan 2026 (gains of $1,710 against zero losses). The core issue is clear: new logo acquisition, which drove 100% of gains for the first 14 months, has essentially stopped.
A38: Where the Business Is Headed
A39: The business is flat, not growing. The trailing 6-month CMGR as of Feb 2026 is 0.4% — essentially zero. The 12-month CMGR has fallen to 2.9%, meaning even the longer-term trend has lost almost all momentum. The Feb 2026 Quick Ratio is 0.0x (losses of $594 against zero gains), confirming that the most recent month added nothing. For the board, the headline is: ARR has stalled at ~$1.82M and the growth engine that built it has gone quiet. The one metric to watch is Gains — specifically, whether new customer acquisition restarts. Expansion alone cannot sustain or grow the base; it appeared in only 9 of 26 months and never exceeded $3K. Until new logo MRR returns to the $5K–$10K/month range that characterized 2024, the business is coasting on its installed base and vulnerable to any churn spike.
