Workbook

Sheet Instructions
A1: iDynamics Software Inc.
A2: Instructions
A4: Instructions:
A5: Today is April 7, 2025. You are a Junior Finance Analyst at iDynamics Software Inc., a B2B SaaS company. The company has just closed Q1 2025 (January–March), and David Chen, VP of Finance, would like to review how the business performed. David has sent you an email — please reference the "Email" tab.
A7: Objective:
A8: 1) Review David's email, and in the Commentary section of the Email tab, provide the necessary details.
A10: Details:
A11: 1) The Q1 subscription data is provided in the "Subscriptions" tab.
A12: a) Review the data and address the email.
A13: 2) You may use the "Analysis" tab to conduct your analysis.
A14: a) Add additional columns, rows, or tabs as needed.
A15: b) Any additional analysis you deem relevant is welcome.
A17: This file is the property of iDynamics Software Inc. — For training purposes only.

Sheet Subscriptions
A1: Month | B1: Subscription ID | C1: Customer ID | D1: Company Name | E1: Plan Name | F1: Billing Cycle | G1: Seats | H1: List Price / Seat | I1: Discount % | J1: Cost / Seat | K1: Plan Category | L1: Total COGS | M1: Total Net Revenue | N1: Total Gross Revenue | O1: Total Net Margin | P1: Total Gross Margin ($) | Q1: Total Gross Margin (%)
A2: 2025-01 | B2: SUB002 | C2: CUST002 | D2: Pacific Analytics Inc | E2: Platform Suite | F2: Annual | G2: 26 | H2: 1800 | I2: 0 | J2: 720 | K2: =_xlfn.XLOOKUP(E2, 'Plan Category Mapping'!$B$3:$B$8, 'Plan Category Mapping'!$C$3:$C$8, "N/A") -> Suite | L2: =IF(F2="Annual", J2/12, J2)*G2*(1-I2) -> 1560 | M2: =IF(F2="Annual", H2/12, H2)*G2*(1-I2) -> 3900 | N2: =IF(F2="Annual", H2/12, H2)*G2 -> 3900 | O2: =M2-L2 -> 2340 | P2: =Table1[[#This Row],[Total Gross Revenue]]-Table1[[#This Row],[Total COGS]] -> 2340 | Q2: =O2/M2 -> 0.6
A3: 2025-01 | B3: SUB003 | C3: CUST003 | D3: Maple Healthcare Systems | E3: Marketing Pro | F3: Monthly | G3: 23 | H3: 85 | I3: 0 | J3: 31.5 | K3: =_xlfn.XLOOKUP(E3, 'Plan Category Mapping'!$B$3:$B$8, 'Plan Category Mapping'!$C$3:$C$8, "N/A") -> Marketing | L3: =IF(F3="Annual", J3/12, J3)*G3*(1-I3) -> 724.5 | M3: =IF(F3="Annual", H3/12, H3)*G3*(1-I3) -> 1955 | N3: =IF(F3="Annual", H3/12, H3)*G3 -> 1955 | O3: =M3-L3 -> 1230.5 | P3: =Table1[[#This Row],[Total Gross Revenue]]-Table1[[#This Row],[Total COGS]] -> 1230.5 | Q3: =O3/M3 -> 0.62941176
A4: 2025-01 | B4: SUB004 | C4: CUST004 | D4: Prairie Commerce Group | E4: Sales Hub | F4: Monthly | G4: 18 | H4: 110 | I4: 0 | J4: 31 | K4: =_xlfn.XLOOKUP(E4, 'Plan Category Mapping'!$B$3:$B$8, 'Plan Category Mapping'!$C$3:$C$8, "N/A") -> Sales | L4: =IF(F4="Annual", J4/12, J4)*G4*(1-I4) -> 558 | M4: =IF(F4="Annual", H4/12, H4)*G4*(1-I4) -> 1980 | N4: =IF(F4="Annual", H4/12, H4)*G4 -> 1980 | O4: =M4-L4 -> 1422 | P4: =Table1[[#This Row],[Total Gross Revenue]]-Table1[[#This Row],[Total COGS]] -> 1422 | Q4: =O4/M4 -> 0.71818182
A5: 2025-01 | B5: SUB006 | C5: CUST006 | D5: Northern Retail Solutions | E5: Analytics Enterprise | F5: Annual | G5: 31 | H5: 2160 | I5: 0 | J5: 756 | K5: =_xlfn.XLOOKUP(E5, 'Plan Category Mapping'!$B$3:$B$8, 'Plan Category Mapping'!$C$3:$C$8, "N/A") -> Analytics | L5: =IF(F5="Annual", J5/12, J5)*G5*(1-I5) -> 1953 | M5: =IF(F5="Annual", H5/12, H5)*G5*(1-I5) -> 5580 | N5: =IF(F5="Annual", H5/12, H5)*G5 -> 5580 | O5: =M5-L5 -> 3627 | P5: =Table1[[#This Row],[Total Gross Revenue]]-Table1[[#This Row],[Total COGS]] -> 3627 | Q5: =O5/M5 -> 0.65
A6: 2025-01 | B6: SUB007 | C6: CUST007 | D6: Ontario Manufacturing Tech | E6: Marketing Pro | F6: Monthly | G6: 16 | H6: 85 | I6: 0 | J6: 31.5 | K6: =_xlfn.XLOOKUP(E6, 'Plan Category Mapping'!$B$3:$B$8, 'Plan Category Mapping'!$C$3:$C$8, "N/A") -> Marketing | L6: =IF(F6="Annual", J6/12, J6)*G6*(1-I6) -> 504 | M6: =IF(F6="Annual", H6/12, H6)*G6*(1-I6) -> 1360 | N6: =IF(F6="Annual", H6/12, H6)*G6 -> 1360 | O6: =M6-L6 -> 856 | P6: =Table1[[#This Row],[Total Gross Revenue]]-Table1[[#This Row],[Total COGS]] -> 856 | Q6: =O6/M6 -> 0.62941176
A7: 2025-01 | B7: SUB009 | C7: CUST009 | D7: West Coast Logistics | E7: Platform Suite | F7: Annual | G7: 36 | H7: 1800 | I7: 0 | J7: 720 | K7: =_xlfn.XLOOKUP(E7, 'Plan Category Mapping'!$B$3:$B$8, 'Plan Category Mapping'!$C$3:$C$8, "N/A") -> Suite | L7: =IF(F7="Annual", J7/12, J7)*G7*(1-I7) -> 2160 | M7: =IF(F7="Annual", H7/12, H7)*G7*(1-I7) -> 5400 | N7: =IF(F7="Annual", H7/12, H7)*G7 -> 5400 | O7: =M7-L7 -> 3240 | P7: =Table1[[#This Row],[Total Gross Revenue]]-Table1[[#This Row],[Total COGS]] -> 3240 | Q7: =O7/M7 -> 0.6
A8: 2025-01 | B8: SUB010 | C8: CUST010 | D8: Montreal Finance Hub | E8: Analytics Starter | F8: Monthly | G8: 13 | H8: 45 | I8: 0 | J8: 9 | K8: =_xlfn.XLOOKUP(E8, 'Plan Category Mapping'!$B$3:$B$8, 'Plan Category Mapping'!$C$3:$C$8, "N/A") -> Analytics | L8: =IF(F8="Annual", J8/12, J8)*G8*(1-I8) -> 117 | M8: =IF(F8="Annual", H8/12, H8)*G8*(1-I8) -> 585 | N8: =IF(F8="Annual", H8/12, H8)*G8 -> 585 | O8: =M8-L8 -> 468 | P8: =Table1[[#This Row],[Total Gross Revenue]]-Table1[[#This Row],[Total COGS]] -> 468 | Q8: =O8/M8 -> 0.8
A9: 2025-01 | B9: SUB011 | C9: CUST011 | D9: Prairie Health Connect | E9: Sales Hub | F9: Monthly | G9: 18 | H9: 110 | I9: 0 | J9: 31 | K9: =_xlfn.XLOOKUP(E9, 'Plan Category Mapping'!$B$3:$B$8, 'Plan Category Mapping'!$C$3:$C$8, "N/A") -> Sales | L9: =IF(F9="Annual", J9/12, J9)*G9*(1-I9) -> 558 | M9: =IF(F9="Annual", H9/12, H9)*G9*(1-I9) -> 1980 | N9: =IF(F9="Annual", H9/12, H9)*G9 -> 1980 | O9: =M9-L9 -> 1422 | P9: =Table1[[#This Row],[Total Gross Revenue]]-Table1[[#This Row],[Total COGS]] -> 1422 | Q9: =O9/M9 -> 0.71818182
A10: 2025-01 | B10: SUB012 | C10: CUST012 | D10: Maritime E-commerce | E10: Analytics Growth | F10: Monthly | G10: 23 | H10: 95 | I10: 0 | J10: 24 | K10: =_xlfn.XLOOKUP(E10, 'Plan Category Mapping'!$B$3:$B$8, 'Plan Category Mapping'!$C$3:$C$8, "N/A") -> Analytics | L10: =IF(F10="Annual", J10/12, J10)*G10*(1-I10) -> 552 | M10: =IF(F10="Annual", H10/12, H10)*G10*(1-I10) -> 2185 | N10: =IF(F10="Annual", H10/12, H10)*G10 -> 2185 | O10: =M10-L10 -> 1633 | P10: =Table1[[#This Row],[Total Gross Revenue]]-Table1[[#This Row],[Total COGS]] -> 1633 | Q10: =O10/M10 -> 0.74736842
A11: 2025-01 | B11: SUB013 | C11: CUST013 | D11: Alberta Tech Innovators | E11: Analytics Starter | F11: Monthly | G11: 10 | H11: 45 | I11: 0 | J11: 9 | K11: =_xlfn.XLOOKUP(E11, 'Plan Category Mapping'!$B$3:$B$8, 'Plan Category Mapping'!$C$3:$C$8, "N/A") -> Analytics | L11: =IF(F11="Annual", J11/12, J11)*G11*(1-I11) -> 90 | M11: =IF(F11="Annual", H11/12, H11)*G11*(1-I11) -> 450 | N11: =IF(F11="Annual", H11/12, H11)*G11 -> 450 | O11: =M11-L11 -> 360 | P11: =Table1[[#This Row],[Total Gross Revenue]]-Table1[[#This Row],[Total COGS]] -> 360 | Q11: =O11/M11 -> 0.8
A12: 2025-01 | B12: SUB014 | C12: CUST014 | D12: Toronto Media Group | E12: Marketing Pro | F12: Monthly | G12: 28 | H12: 85 | I12: 0 | J12: 31.5 | K12: =_xlfn.XLOOKUP(E12, 'Plan Category Mapping'!$B$3:$B$8, 'Plan Category Mapping'!$C$3:$C$8, "N/A") -> Marketing | L12: =IF(F12="Annual", J12/12, J12)*G12*(1-I12) -> 882 | M12: =IF(F12="Annual", H12/12, H12)*G12*(1-I12) -> 2380 | N12: =IF(F12="Annual", H12/12, H12)*G12 -> 2380 | O12: =M12-L12 -> 1498 | P12: =Table1[[#This Row],[Total Gross Revenue]]-Table1[[#This Row],[Total COGS]] -> 1498 | Q12: =O12/M12 -> 0.62941176
A13: 2025-01 | B13: SUB015 | C13: CUST015 | D13: BC Retail Networks | E13: Analytics Growth | F13: Monthly | G13: 19 | H13: 95 | I13: 0.1 | J13: 24 | K13: =_xlfn.XLOOKUP(E13, 'Plan Category Mapping'!$B$3:$B$8, 'Plan Category Mapping'!$C$3:$C$8, "N/A") -> Analytics | L13: =IF(F13="Annual", J13/12, J13)*G13*(1-I13) -> 410.4 | M13: =IF(F13="Annual", H13/12, H13)*G13*(1-I13) -> 1624.5 | N13: =IF(F13="Annual", H13/12, H13)*G13 -> 1805 | O13: =M13-L13 -> 1214.1 | P13: =Table1[[#This Row],[Total Gross Revenue]]-Table1[[#This Row],[Total COGS]] -> 1394.6 | Q13: =O13/M13 -> 0.74736842
... A126: 2025-03 | B126: SUB060 | C126: CUST019 | D126: Central Healthcare Partners | E126: Sales Hub | F126: Monthly | G126: 16 | H126: 110 | I126: 0 | J126: 31 | K126: =_xlfn.XLOOKUP(E126, 'Plan Category Mapping'!$B$3:$B$8, 'Plan Category Mapping'!$C$3:$C$8, "N/A") -> Sales | L126: =IF(F126="Annual", J126/12, J126)*G126*(1-I126) -> 496 | M126: =IF(F126="Annual", H126/12, H126)*G126*(1-I126) -> 1760 | N126: =IF(F126="Annual", H126/12, H126)*G126 -> 1760 | O126: =M126-L126 -> 1264 | P126: =Table1[[#This Row],[Total Gross Revenue]]-Table1[[#This Row],[Total COGS]] -> 1264 | Q126: =O126/M126 -> 0.71818182

Sheet Plan Category Mapping
B1: Plan Category Mapping
B2: Plan Name | C2: Plan Category
B3: Analytics Starter | C3: Analytics
B4: Analytics Growth | C4: Analytics
B5: Analytics Enterprise | C5: Analytics
B6: Sales Hub | C6: Sales
B7: Marketing Pro | C7: Marketing
B8: Platform Suite | C8: Suite

Sheet Email
A1: iDynamics Software Inc.
B3: To: FP&A Team Inbox
B4: From: David Chen (VP Finance)
B5: Re: Q1 2025 Performance Review
B6: Sent: April 7, 2025 | 9:45 AM
B8: Hello FP&A Team,
B9: Q1 is closed. Before I present to Daniel next week I want a quick read on how we performed. Can you pull together the following?
B10: 1. What is our total revenue, gross margin, and gross margin % for Q1? Can you also break this down by month? I want to see if there were any swings across January, February, and March.
B12: 2. For all of Q1, give me a breakdown of gross margin $ by plan category. Which categories performed the strongest and weakest?
B14: 3. For the plan category with the weakest gross margin $, identify which customer has the lowest gross margin contribution and explain why their contribution is low. (Set aside any impact from discounts — focus on the underlying subscription.)
B16: 4. I'm curious what our margins would have looked like had we not offered any discounts. Can you assess what our gross margin would have been without discounts, and share any relevant observations?
B18: Please have this ready before EOD. Thanks, David
A21: iDynamics Software Inc.
B23: To: David Chen (VP Finance)
B24: From: Michael (FP&A)
B25: Re: Q1 2025 Performance Review
B26: Sent: April 7, 2025 | [Time]
B28: Hi David,
B29: Please find the requested details below:
B31: 1. What is our total revenue, gross margin, and gross margin % for Q1? Breakdown by month?
B32: Commentary:
B37: 2. Gross margin $ breakdown by plan category:
B38: Commentary:
B43: 3. Weakest plan category — lowest GM$ customer and reason:
B44: Commentary:
... B50: Commentary:

Sheet Analysis
A1: Analysis — Use this tab freely. Add rows, columns, or additional tabs as needed.
A3: 1. What is our total revenue, gross margin, and gross margin % for Q1? Can you also break this down by month? I want to see if there were any swings across January, February, and March.
A5: Month | B5: Total Revenue | C5: Total Gross Margin ($) | D5: Total Gross Margin (%)
A6: 45658 | B6: =SUMIFS(Subscriptions!$M$2:$M$126, Subscriptions!$A$2:$A$126, Analysis!A6) -> 100602 | C6: =SUMIFS(Subscriptions!$O$2:$O$126, Subscriptions!$A$2:$A$126, Analysis!A6) -> 66619.4 | D6: =C6/B6 -> 0.66220751
A7: 45689 | B7: =SUMIFS(Subscriptions!$M$2:$M$126, Subscriptions!$A$2:$A$126, Analysis!A7) -> 107557 | C7: =SUMIFS(Subscriptions!$O$2:$O$126, Subscriptions!$A$2:$A$126, Analysis!A7) -> 71368.9 | D7: =C7/B7 -> 0.66354491
A8: 45717 | B8: =SUMIFS(Subscriptions!$M$2:$M$126, Subscriptions!$A$2:$A$126, Analysis!A8) -> 126947 | C8: =SUMIFS(Subscriptions!$O$2:$O$126, Subscriptions!$A$2:$A$126, Analysis!A8) -> 83724.9 | D8: =C8/B8 -> 0.65952642
A10: 2. For all of Q1, give me a breakdown of gross margin $ by plan category. Which categories performed the strongest and weakest?
B11: Plan Category | C11: (All)
B13: Row Labels | C13: Sum of Total Gross Margin ($)
B14: Analytics Enterprise | C14: 55692
B15: Analytics Growth | C15: 32876
B16: Analytics Starter | C16: 9480.6
B17: Marketing Pro | C17: 40660
B18: Platform Suite | C18: 48600
B19: Sales Hub | C19: 36888.6
B20: Grand Total | C20: 224197.2
A22: 3. For the plan category with the weakest gross margin $, identify which customer has the lowest gross margin contribution and explain why their contribution is low. (Set aside any impact from discounts — focus on the underlying subscription.)
B23: Plan Category | C23: Sales
B25: Row Labels | C25: Sum of Total Gross Margin ($) | D25: Sum of Seats
B26: Sales Hub | C26: 36888.6 | D26: 462
B27: Grand Total | C27: 36888.6 | D27: 462
B29: Row Labels | C29: Sum of Total Gross Margin ($) | D29: Sum of Seats
B30: Analytics | C30: 98048.6 | D30: 1198
B31: Marketing | C31: 40660 | D31: 760
B32: Sales | C32: 36888.6 | D32: 462
B33: Suite | C33: 48600 | D33: 540
B34: Grand Total | C34: 224197.2 | D34: 2960
A36: 4. I'm curious what our margins would have looked like had we not offered any discounts. Can you assess what our gross margin would have been without discounts, and share any relevant observations?
B38: Row Labels | C38: Sum of Total Net Margin | D38: Sum of Seats
B39: Analytics | C39: 96950.6 | D39: 1198
B40: Marketing | C40: 40660 | D40: 760
B41: Sales | C41: 35502.6 | D41: 462
B42: Suite | C42: 48600 | D42: 540
B43: Grand Total | C43: 221713.2 | D43: 2960
B45: Analytics | C45: =SUMIFS($C$30:$C$33,$B$30:$B$33,B45) - SUMIFS($C$39:$C$42,$B$39:$B$42,B45) -> 1098
B46: Marketing | C46: =SUMIFS($C$30:$C$33,$B$30:$B$33,B46) - SUMIFS($C$39:$C$42,$B$39:$B$42,B46) -> 0
B47: Sales | C47: =SUMIFS($C$30:$C$33,$B$30:$B$33,B47) - SUMIFS($C$39:$C$42,$B$39:$B$42,B47) -> 1386
B48: Suite | C48: =SUMIFS($C$30:$C$33,$B$30:$B$33,B48) - SUMIFS($C$39:$C$42,$B$39:$B$42,B48) -> 0
B49: Grand Total | C49: =SUM(C45:C48) -> 2484
